Workbook

Sheet 기업리스트
B2: 실적 기업 정보
B3: Ticker | C3: Company | D3: Date | E3: Time | F3: Quarter Ending | G3: Market Cap (mil$)
B4: AMZN | C4: Amazon.com, Inc. | D4: 05-Feb-26 | E4: After Hours | F4: Dec-25 | G4: 2558170
B5: SHEL | C5: Shell plc | D5: 05-Feb-26 | F5: Dec-25 | G5: 218501
B6: LIN | C6: Linde plc | D6: 05-Feb-26 | E6: Pre Market | F6: Dec-25 | G6: 213382
B7: BBVA | C7: Banco Bilbao Vizcaya Argentaria, S.A. | D7: 05-Feb-26 | F7: Dec-25 | G7: 145037
B8: 6758 | C8: Sony Group Corporation | D8: 05-Feb-26 | E8: Pre Market | F8: Dec-25 | G8: 133941
B9: COP | C9: ConocoPhillips | D9: 05-Feb-26 | E9: Pre Market | F9: Dec-25 | G9: 128799
B10: BNP | C10: BNP Paribas SA | D10: 05-Feb-26 | F10: Dec-25 | G10: 119716
B11: BMY | C11: Bristol-Myers Squibb Company | D11: 05-Feb-26 | E11: Pre Market | F11: Dec-25 | G11: 112068
B12: KKR | C12: KKR & Co. Inc. | D12: 05-Feb-26 | E12: Pre Market | F12: Dec-25 | G12: 101846
B13: ICE | C13: Intercontinental Exchange, Inc. | D13: 05-Feb-26 | F13: Dec-25 | G13: 99085.63
B14: 8058 | C14: Mitsubishi Corporation | D14: 05-Feb-26 | F14: Dec-25 | G14: 98651.89
B15: 8001 | C15: ITOCHU Corporation | D15: 05-Feb-26 | F15: Dec-25 | G15: 89964.99
B16: DG | C16: Vinci SA | D16: 05-Feb-26 | F16: Dec-25 | G16: 80084.42
B17: CMI | C17: Cummins Inc. | D17: 05-Feb-26 | E17: Pre Market | F17: Dec-25 | G17: 79898.14
B18: ABX | C18: Barrick Mining Corporation | D18: 05-Feb-26 | E18: Pre Market | F18: Dec-25 | G18: 77132.47
B19: CI | C19: The Cigna Group | D19: 05-Feb-26 | E19: Pre Market | F19: Dec-25 | G19: 73221.86
B20: FTNT | C20: Fortinet, Inc. | D20: 05-Feb-26 | E20: After Hours | F20: Dec-25 | G20: 60428.84
B21: DLR | C21: Digital Realty Trust, Inc. | D21: 05-Feb-26 | E21: After Hours | F21: Dec-25 | G21: 57004.08
B22: LICI | C22: Life Insurance Corporation of India | D22: 05-Feb-26 | F22: Dec-25 | G22: 56784.9
B23: SHL | C23: Siemens Healthineers AG | D23: 05-Feb-26 | F23: Dec-25 | G23: 56067.39
B24: MPWR | C24: Monolithic Power Systems, Inc. | D24: 05-Feb-26 | E24: After Hours | F24: Dec-25 | G24: 53854.65
B25: CAH | C25: Cardinal Health, Inc. | D25: 05-Feb-26 | E25: Pre Market | F25: Dec-25 | G25: 51054.42
B26: CARR | C26: Carrier Global Corporation | D26: 05-Feb-26 | E26: Pre Market | F26: Dec-25 | G26: 50178.86
B27: TRI | C27: Thomson Reuters Corporation | D27: 05-Feb-26 | F27: Dec-25 | G27: 49352.43
B28: MSTR | C28: Strategy Inc | D28: 05-Feb-26 | E28: After Hours | F28: Dec-25 | G28: 48394.89
B29: ROK | C29: Rockwell Automation, Inc. | D29: 05-Feb-26 | E29: Pre Market | F29: Dec-25 | G29: 47407.45
B30: RBLX | C30: Roblox Corporation | D30: 05-Feb-26 | E30: After Hours | F30: Dec-25 | G30: 46158.62
B31: ASSA B | C31: ASSA ABLOY AB (publ) | D31: 05-Feb-26 | F31: Dec-25 | G31: 45396.5
B32: XEL | C32: Xcel Energy Inc. | D32: 05-Feb-26 | E32: Pre Market | F32: Dec-25 | G32: 44992.52
B33: RDDT | C33: Reddit, Inc. | D33: 05-Feb-26 | E33: After Hours | F33: Dec-25 | G33: 43775.42
B34: 3711 | C34: ASE Technology Holding Co., Ltd. | D34: 05-Feb-26 | E34: Pre Market | F34: Dec-25 | G34: 41944.43
B35: EL | C35: The Estée Lauder Companies Inc. | D35: 05-Feb-26 | F35: Dec-25 | G35: 41459.45
B36: SAAB B | C36: Saab AB (publ) | D36: 05-Feb-26 | F36: Dec-25 | G36: 41191.6
B37: DANSKE | C37: Danske Bank A/S | D37: 05-Feb-26 | F37: Dec-25 | G37: 41185.25
B38: IQV | C38: IQVIA Holdings Inc. | D38: 05-Feb-26 | F38: Dec-25 | G38: 40476.9
B39: MCHP | C39: Microchip Technology Incorporated | D39: 05-Feb-26 | E39: After Hours | F39: Dec-25 | G39: 40371.38
B40: HSY | C40: The Hershey Company | D40: 05-Feb-26 | F40: Dec-25 | G40: 40102.79
B41: ARES | C41: Ares Management Corporation | D41: 05-Feb-26 | E41: Pre Market | F41: Dec-25 | G41: 37389.88
B42: MT | C42: ArcelorMittal S.A. | D42: 05-Feb-26 | F42: Dec-25 | G42: 37137.72
B43: VTR | C43: Ventas, Inc. | D43: 05-Feb-26 | E43: After Hours | F43: Dec-25 | G43: 36850.54
B44: BE | C44: Bloom Energy Corporation | D44: 05-Feb-26 | E44: After Hours | F44: Dec-25 | G44: 35358.36
B45: WEC | C45: WEC Energy Group, Inc. | D45: 05-Feb-26 | E45: Pre Market | F45: Dec-25 | G45: 35323.7
B46: BBDC4 | C46: Banco Bradesco S.A. | D46: 05-Feb-26 | F46: Dec-25 | G46: 34533.34
B47: MAERSK B | C47: A.P. Møller - Mærsk A/S | D47: 05-Feb-26 | F47: Dec-25 | G47: 33851.66
B48: TEAM | C48: Atlassian Corporation | D48: 05-Feb-26 | F48: Dec-25 | G48: 31191.82
B49: SAMPO | C49: Sampo Oyj | D49: 05-Feb-26 | F49: Dec-25 | G49: 30855.68
B50: MTD | C50: Mettler-Toledo International Inc. | D50: 05-Feb-26 | F50: Dec-25 | G50: 29838.4
B51: 7269 | C51: Suzuki Motor Corporation | D51: 05-Feb-26 | F51: Dec-25 | G51: 28802.43
B52: BMRI | C52: PT Bank Mandiri (Persero) Tbk | D52: 05-Feb-26 | F52: Dec-25 | G52: 27574.5
B53: TPR | C53: Tapestry, Inc. | D53: 05-Feb-26 | E53: Pre Market | F53: Dec-25 | G53: 26745.68
B54: 6723 | C54: Renesas Electronics Corporation | D54: 05-Feb-26 | F54: Dec-25 | G54: 26688.6
B55: 4901 | C55: FUJIFILM Holdings Corporation | D55: 05-Feb-26 | F55: Dec-25 | G55: 26235.85
B56: A055550 | C56: Shinhan Financial Group Co., Ltd. | D56: 05-Feb-26 | F56: Dec-25 | G56: 25905.92
B57: AFRM | C57: Affirm Holdings, Inc. | D57: 05-Feb-26 | E57: After Hours | F57: Dec-25 | G57: 24676.31
B58: IOC | C58: Indian Oil Corporation Limited | D58: 05-Feb-26 | F58: Dec-25 | G58: 24484.04
B59: EQR | C59: Equity Residential | D59: 05-Feb-26 | E59: After Hours | F59: Dec-25 | G59: 23604.65
B60: VRSN | C60: VeriSign, Inc. | D60: 05-Feb-26 | E60: After Hours | F60: Dec-25 | G60: 23125.87
B61: TW | C61: Tradeweb Markets Inc. | D61: 05-Feb-26 | E61: Pre Market | F61: Dec-25 | G61: 22678.13
B62: BCE | C62: BCE Inc. | D62: 05-Feb-26 | F62: Dec-25 | G62: 22549.04
B63: BAMI | C63: Banco BPM S.p.A. | D63: 05-Feb-26 | F63: Dec-25 | G63: 22230.52
B64: 5401 | C64: Nippon Steel Corporation | D64: 05-Feb-26 | F64: Dec-25 | G64: 22022.21
B65: CMS | C65: CMS Energy Corporation | D65: 05-Feb-26 | E65: Pre Market | F65: Dec-25 | G65: 21813.64
B66: 2802 | C66: Ajinomoto Co., Inc. | D66: 05-Feb-26 | F66: Dec-25 | G66: 21002.87
B67: SSNC | C67: SS&C Technologies Holdings, Inc. | D67: 05-Feb-26 | E67: After Hours | F67: Dec-25 | G67: 20932.59
B68: VWS | C68: Vestas Wind Systems A/S | D68: 05-Feb-26 | F68: Dec-25 | G68: 20069.94
B69: RL | C69: Ralph Lauren Corporation | D69: 05-Feb-26 | E69: Pre Market | F69: Dec-25 | G69: 18735.02
B70: SNA | C70: Snap-on Incorporated | D70: 05-Feb-26 | F70: Dec-25 | G70: 18122.6
B71: 4452 | C71: Kao Corporation | D71: 05-Feb-26 | F71: Dec-25 | G71: 17760.21
B72: WMG | C72: Warner Music Group Corp. | D72: 05-Feb-26 | E72: After Hours | F72: Dec-25 | G72: 17647.49
B73: GEN | C73: Gen Digital Inc. | D73: 05-Feb-26 | E73: After Hours | F73: Dec-25 | G73: 17133.48
B74: 500570 | C74: Tata Motors Passenger Vehicles Limited | D74: 05-Feb-26 | F74: Dec-25 | G74: 16870.72
B75: EVO | C75: Evolution AB (publ) | D75: 05-Feb-26 | F75: Dec-25 | G75: 16204.39
B76: ILMN | C76: Illumina, Inc. | D76: 05-Feb-26 | E76: After Hours | F76: Dec-25 | G76: 15702.96
B77: NWSA | C77: News Corporation | D77: 05-Feb-26 | E77: After Hours | F77: Dec-25 | G77: 15696.54
B78: PFC | C78: Power Finance Corporation Limited | D78: 05-Feb-26 | F78: Dec-25 | G78: 15322.29
B79: XPO | C79: XPO, Inc. | D79: 05-Feb-26 | E79: Pre Market | F79: Dec-25 | G79: 15132.43
B80: NESTE | C80: Neste Oyj | D80: 05-Feb-26 | F80: Dec-25 | G80: 14575.43
B81: ITT | C81: ITT Inc. | D81: 05-Feb-26 | E81: Pre Market | F81: Dec-25 | G81: 14130.48
B82: RBC | C82: RBC Bearings Incorporated | D82: 05-Feb-26 | E82: Pre Market | F82: Dec-25 | G82: 14018.69
B83: IREN | C83: IREN Limited | D83: 05-Feb-26 | E83: After Hours | F83: Dec-25 | G83: 13724.14
B84: DOCS | C84: Doximity, Inc. | D84: 05-Feb-26 | E84: After Hours | F84: Dec-25 | G84: 13721.56
B85: UNM | C85: Unum Group | D85: 05-Feb-26 | E85: After Hours | F85: Dec-25 | G85: 13526.28
B86: CEMEX CPO | C86: CEMEX, S.A.B. de C.V. | D86: 05-Feb-26 | F86: Dec-25 | G86: 13140.7
B87: MAZDOCK | C87: Mazagon Dock Shipbuilders Limited | D87: 05-Feb-26 | F87: Dec-25 | G87: 13091.55
B88: RGA | C88: Reinsurance Group of America, Incorporated | D88: 05-Feb-26 | E88: After Hours | F88: Dec-25 | G88: 13050.87
B89: REG | C89: Regency Centers Corporation | D89: 05-Feb-26 | E89: After Hours | F89: Dec-25 | G89: 12978.56
B90: EHC | C90: Encompass Health Corporation | D90: 05-Feb-26 | E90: After Hours | F90: Dec-25 | G90: 12412.2
B91: 543220 | C91: Max Healthcare Institute Limited | D91: 05-Feb-26 | F91: Dec-25 | G91: 11707.34
B92: SOBI | C92: Swedish Orphan Biovitrum AB (publ) | D92: 05-Feb-26 | F92: Dec-25 | G92: 11644.75
B93: HII | C93: Huntington Ingalls Industries, Inc. | D93: 05-Feb-26 | E93: Pre Market | F93: Dec-25 | G93: 11153.76
B94: CPT | C94: Camden Property Trust | D94: 05-Feb-26 | E94: After Hours | F94: Dec-25 | G94: 11134.05
B95: SPSN | C95: Swiss Prime Site AG | D95: 05-Feb-26 | F95: Dec-25 | G95: 11120.19
B96: WMS | C96: Advanced Drainage Systems, Inc. | D96: 05-Feb-26 | E96: Pre Market | F96: Dec-25 | G96: 11036.98
B97: ARX | C97: ARC Resources Ltd. | D97: 05-Feb-26 | F97: Dec-25 | G97: 11016.36
B98: VOLCAR B | C98: Volvo Car AB (publ.) | D98: 05-Feb-26 | F98: Dec-25 | G98: 11007.05
B99: MOH | C99: Molina Healthcare, Inc. | D99: 05-Feb-26 | F99: Dec-25 | G99: 10946.77
B100: SAP | C100: Saputo Inc. | D100: 05-Feb-26 | F100: Dec-25 | G100: 10938.66
B101: OWL | C101: Blue Owl Capital Inc. | D101: 05-Feb-26 | F101: Dec-25 | G101: 10593.27
...

Sheet Revenue
B2: Ticker | C2: Country | D2: Industry | E2: Latest_Date | F2: Growth_Rate | G2: 4Q21 | H2: 1Q22 | I2: 2Q22 | J2: 3Q22 | K2: 4Q22 | L2: 1Q23 | M2: 2Q23 | N2: 3Q23 | O2: 4Q23 | P2: 1Q24 | Q2: 2Q24 | R2: 3Q24 | S2: 4Q24 | T2: 1Q25 | U2: 2Q25 | V2: 3Q25 | W2: 4Q25 | X2: 1Q25 | Y2: 2Q25 | Z2: 3Q25 | AA2: 4Q25
B3: MOFG | C3: United States | D3: Banks - Regional | E3: Sep'25 | F3: 224.8 | G3: 50.6 | H3: 49.43 | I3: 48.98 | J3: 50.05 | K3: 57.68 | L3: 52.68 | M3: 35.1 | N3: 44.11 | O3: 42.89 | P3: 34.65 | Q3: 39.79 | R3: 56.63 | S3: -94.4 | T3: 58.48 | U3: 55.89 | V3: 48.34 | W3: 59.13 | X3: 0.64985001 | Y3: 0.2661157 | Z3: -0.10822454 | AA3: 2.2475479
B4: ARWR | C4: United States | D4: Biotechnology | E4: Mar'26 | F4: 31.5 | G4: 27.44 | H4: 151.81 | I4: 32.41 | J4: 31.58 | K4: 62.55 | L4: 146.27 | M4: 15.83 | N4: 16.1 | O4: 3.55 | P4: 0 | Q4: 0 | R4: 0 | S4: 2.5 | T4: 542.71 | U4: 27.77 | V4: 256.47 | W4: 264.03 | X4: 217.084 | Y4: 0.050934502 | Z4: 0.44760725 | AA4: 0.31530532
B5: GOLD | C5: United States | D5: Capital Markets | E5: Jun'26 | F5: 31.3 | G5: 1946 | H5: 2109 | I5: 2090 | J5: 1900 | K5: 1950 | L5: 2317 | M5: 3119 | N5: 2485 | O5: 2079 | P5: 2611 | Q5: 2525 | R5: 2715 | S5: 2742 | T5: 3009 | U5: 2512 | V5: 3681 | W5: 6477 | X5: 0.037571981 | Y5: -0.0011827859 | Z5: 0.08799417 | AA5: 0.31270931
B6: ABX | C6: United States | D6: Insurance - Life | E6: Sep'25 | F6: 21.5 | G6: 0.32 | H6: 0.2 | I6: 9.88 | J6: 8.4 | K6: 11.51 | L6: 14.93 | M6: 10.27 | N6: 11.38 | O6: 21.12 | P6: 23.7 | Q6: 21.49 | R6: 29.08 | S6: 28.15 | T6: 33.21 | U6: 44.14 | V6: 56.22 | W6: 62.98 | X6: 0.092852958 | Y6: 0.20235862 | Z6: 0.20166444 | AA6: 0.21537225
B7: BLSH | C7: United States | D7: Software - Infrastructure | E7: Dec'25 | F7: 19.3 | L7: 0.26 | M7: 0.26 | N7: -0.11 | O7: -0.11 | P7: 38.37 | Q7: 47.99 | R7: 32.86 | S7: 39.27 | T7: 46.82 | U7: 47.66 | V7: 65.05 | W7: 77.71 | X7: 0.053315667 | Y7: -0.0019767581 | Z7: 0.19320569 | AA7: 0.19336016
B8: STEP | C8: United States | D8: Asset Management | E8: Sep'26 | F8: 16.1 | G8: 410.47 | H8: 364.69 | I8: -77.22 | J8: -158.5 | K8: -4.24 | L8: 172.37 | M8: 178.01 | N8: 191.42 | O8: -14.61 | P8: 356.81 | Q8: 186.4 | R8: 271.68 | S8: 339.02 | T8: 377.73 | U8: 364.29 | V8: 454.23 | W8: 586.51 | X8: 0.018129663 | Y8: 0.15141765 | Z8: 0.13495032 | AA8: 0.16120292
B9: RDDT | C9: United States | D9: Internet Content & Information | E9: Dec'25 | F9: 15.6 | G9: 176.67 | H9: 146.18 | I9: 148.56 | J9: 171.54 | K9: 200.43 | L9: 163.74 | M9: 183.03 | N9: 207.51 | O9: 249.75 | P9: 242.96 | Q9: 281.18 | R9: 348.35 | S9: 427.71 | T9: 392.36 | U9: 499.63 | V9: 584.91 | W9: 725.61 | X9: 0.1149054 | Y9: 0.15069674 | Z9: 0.14181829 | AA9: 0.15640997
B10: KKR | C10: United States | D10: Asset Management | E10: Dec'25 | F10: 15.6 | G10: 4103 | H10: 2592 | I10: -1396 | J10: 1844 | K10: 2476 | L10: 3213 | M10: 4517 | N10: 5074 | O10: 5860 | P10: 10613 | Q10: 5064 | R10: 6279 | S10: 4466 | T10: 4500 | U10: 6175 | V10: 7105 | W10: 7928 | X10: -0.23136023 | Y10: 0.054704811 | Z10: 0.038562092 | AA10: 0.15562348
B11: ARX | C11: United States | D11: Insurance Brokers | E11: Sep'25 | F11: 11.5 | O11: 68.6 | P11: 111 | Q11: 119.8 | R11: 121.4 | S11: 138.6 | T11: 181.2 | U11: 163.5 | V11: 204.7 | W11: 217.8 | X11: 0.14303178 | Y11: 0.077896613 | Z11: 0.13775426 | AA11: 0.11511628
B12: BE | C12: United States | D12: Electrical Equipment & Parts | E12: Dec'25 | F12: 11.3 | G12: 342.47 | H12: 201.04 | I12: 243.24 | J12: 292.27 | K12: 462.58 | L12: 275.19 | M12: 301.1 | N12: 400.27 | O12: 356.92 | P12: 235.3 | Q12: 335.77 | R12: 330.4 | S12: 572.39 | T12: 326.02 | U12: 401.24 | V12: 519.05 | W12: 777.68 | X12: 0.061552658 | Y12: 0.041845096 | Z12: 0.11573265 | AA12: 0.11287733
B13: TPG | C13: United States | D13: Asset Management | E13: Dec'25 | F13: 9.8 | G13: 1079 | H13: 1111 | I13: -108.28 | J13: 561.12 | K13: 439.34 | L13: 643.15 | M13: 603.27 | N13: 160.36 | O13: 983.14 | P13: 824.07 | Q13: 744.19 | R13: 855.4 | S13: 1076 | T13: 1035 | U13: 920.54 | V13: 1224 | W13: 1491 | X13: 0.060271569 | Y13: 0.047526135 | Z13: 0.094830381 | AA13: 0.097519939
B14: IREN | C14: United States | D14: Capital Markets | E14: Jun'26 | F14: 9.7 | G14: 20.15 | H14: 15.18 | I14: 16.21 | J14: 14.98 | K14: 13.76 | L14: 11.33 | M14: 34.22 | N14: 34.4 | O14: 42.57 | P14: 54.35 | Q14: 55.87 | R14: 52.76 | S14: 117.9 | T14: 148.1 | U14: 180.64 | V14: 240.3 | W14: 184.69 | X14: 0.33377243 | Y14: 0.33304861 | Z14: 0.37553064 | AA14: 0.097228288
B15: ADPT | C15: United States | D15: Biotechnology | E15: Dec'25 | F15: 9.6 | G15: 37.93 | H15: 38.62 | I15: 43.66 | J15: 47.83 | K15: 55.2 | L15: 37.65 | M15: 48.93 | N15: 37.92 | O15: 45.78 | P15: 41.87 | Q15: 43.19 | R15: 46.44 | S15: 47.46 | T15: 52.44 | U15: 58.88 | V15: 93.97 | W15: 71.68 | X15: 0.059063478 | Y15: 0.082783728 | Z15: 0.23160511 | AA15: 0.095825915
B16: RBLX | C16: United States | D16: Electronic Gaming & Multimedia | E16: Dec'25 | F16: 9.6 | G16: 568.77 | H16: 537.13 | I16: 591.21 | J16: 517.71 | K16: 579 | L16: 655.34 | M16: 680.77 | N16: 713.23 | O16: 749.94 | P16: 801.3 | Q16: 893.54 | R16: 918.95 | S16: 988.18 | T16: 1035 | U16: 1081 | V16: 1360 | W16: 1415 | X16: 0.064881162 | Y16: 0.048872818 | Z16: 0.10962857 | AA16: 0.095609944
B17: ROAD | C17: United States | D17: Engineering & Construction | E17: Mar'26 | F17: 8.8 | G17: 284.96 | H17: 243.39 | I17: 380.27 | J17: 393.05 | K17: 341.78 | L17: 324.85 | M17: 421.89 | N17: 475.03 | O17: 396.51 | P17: 371.43 | Q17: 517.79 | R17: 538.16 | S17: 561.58 | T17: 571.65 | U17: 779.28 | V17: 899.85 | W17: 809.47 | X17: 0.10066567 | Y17: 0.11944655 | Z17: 0.14758821 | AA17: 0.088143054
B18: AFRM | C18: United States | D18: Credit Services | E18: Jun'26 | F18: 7.4 | G18: 361.01 | H18: 354.76 | I18: 364.13 | J18: 361.62 | K18: 399.56 | L18: 380.98 | M18: 445.83 | N18: 496.55 | O18: 591.11 | P18: 576.16 | Q18: 659.19 | R18: 698.48 | S18: 866.38 | T18: 783.14 | U18: 876.42 | V18: 933.34 | W18: 1123 | X18: 0.073915885 | Y18: 0.072236872 | Z18: 0.072837906 | AA18: 0.074183067
B19: GOOS | C19: United States | D19: Apparel Manufacturing | E19: Sep'26 | F19: 6.3 | G19: 586.1 | H19: 223.1 | I19: 69.9 | J19: 277.2 | K19: 576.7 | L19: 293.2 | M19: 84.8 | N19: 281.1 | O19: 609.9 | P19: 358 | Q19: 88.1 | R19: 267.8 | S19: 607.9 | T19: 384.6 | U19: 107.8 | V19: 272.6 | W19: 694.5 | X19: 0.020124073 | Y19: 0.014609908 | Z19: 0.0035085155 | AA19: 0.063078156
B20: RGA | C20: United States | D20: Insurance - Reinsurance | E20: Dec'25 | F20: 6.2 | G20: 4359 | H20: 3917 | I20: 3903 | J20: 4050 | K20: 4357 | L20: 4251 | M20: 4156 | N20: 5153 | O20: 5007 | P20: 6337 | Q20: 4878 | R20: 5651 | S20: 5241 | T20: 5260 | U20: 5599 | V20: 6204 | W20: 6635 | X20: -0.048717601 | Y20: 0.034284356 | Z20: 0.025424118 | AA20: 0.0625
B21: GEN | C21: United States | D21: Software - Infrastructure | E21: Sep'26 | F21: 5.7 | G21: 702 | H21: 716 | I21: 707 | J21: 748 | K21: 936 | L21: 947 | M21: 943 | N21: 945 | O21: 948 | P21: 964 | Q21: 965 | R21: 974 | S21: 986 | T21: 1010 | U21: 1257 | V21: 1220 | W21: 1240 | X21: 0.011828233 | Y21: 0.074205845 | Z21: 0.058197303 | AA21: 0.056785155
B22: MTSI | C22: United States | D22: Semiconductors | E22: Mar'26 | F22: 5.5 | G22: 159.62 | H22: 165.15 | I22: 172.26 | J22: 178.14 | K22: 180.1 | L22: 169.41 | M22: 148.52 | N22: 150.38 | O22: 157.15 | P22: 181.23 | Q22: 190.49 | R22: 200.71 | S22: 218.12 | T22: 235.89 | U22: 252.08 | V22: 261.17 | W22: 271.61 | X22: 0.069141737 | Y22: 0.072869464 | Z22: 0.066674019 | AA22: 0.05530054
B23: TEAM | C23: United States | D23: Software - Application | E23: Jun'26 | F23: 5.5 | G23: 688.53 | H23: 740.49 | I23: 759.84 | J23: 807.39 | K23: 872.7 | L23: 915.45 | M23: 939.1 | N23: 977.78 | O23: 1060 | P23: 1189 | Q23: 1132 | R23: 1188 | S23: 1286 | T23: 1357 | U23: 1384 | V23: 1433 | W23: 1586 | X23: 0.035036496 | Y23: 0.05077574 | Z23: 0.046979866 | AA23: 0.054945055
... B53: TW | C53: United States | D53: Capital Markets | E53: Dec'25 | F53: 2.9 | G53: 276.47 | H53: 311.04 | I53: 297.14 | J53: 287.12 | K53: 293.04 | L53: 328.8 | M53: 310.15 | N53: 327.89 | O53: 369.33 | P53: 407.02 | Q53: 404.41 | R53: 447.47 | S53: 462.77 | T53: 509.09 | U53: 512.54 | V53: 508.08 | W53: 520.78 | X53: 0.059285461 | Y53: 0.05929025 | Z53: 0.031373747 | AA53: 0.02911447
B54: MAGN | C54: United States | D54: Household & Personal Products | E54: Mar'26 | F54: 2.8 | N54: 542 | O54: 519 | P54: 558 | Q54: 556 | R54: 554 | S54: 702 | T54: 824 | U54: 839 | V54: 839 | W54: 792 | X54: 0.11223629 | Y54: 0.10735964 | Z54: 0.097636177 | AA54: 0.028089888
B55: LSPD | C55: United States | D55: Software - Application | E55: Sep'26 | F55: 2.8 | G55: 152.68 | H55: 146.56 | I55: 173.88 | J55: 183.7 | K55: 188.7 | L55: 184.23 | M55: 209.09 | N55: 230.27 | O55: 239.7 | P55: 230.22 | Q55: 266.09 | R55: 277.18 | S55: 280.13 | T55: 253.42 | U55: 304.94 | V55: 318.96 | W55: 312.35 | X55: 0.022019324 | Y55: 0.036078453 | Z55: 0.037448349 | AA55: 0.027837056
B56: OMF | C56: United States | D56: Credit Services | E56: Dec'25 | F56: 2.8 | G56: 813 | H56: 794 | I56: 704 | J56: 642 | K56: 657 | L56: 647 | M56: 579 | N56: 675 | O56: 659 | P56: 647 | Q56: 533 | R56: 652 | S56: 665 | T56: 733 | U56: 708 | V56: 786 | W56: 745 | X56: 0.03444133 | Y56: 0.067750678 | Z56: 0.048585932 | AA56: 0.027662517
B57: ROK | C57: United States | D57: Specialty Industrial Machinery | E57: Mar'26 | F57: 2.7 | G57: 1857 | H57: 1808 | I57: 1969 | J57: 2126 | K57: 1981 | L57: 2275 | M57: 2239 | N57: 2563 | O57: 2052 | P57: 2126 | Q57: 2051 | R57: 2035 | S57: 1881 | T57: 2001 | U57: 2144 | V57: 2316 | W57: 2105 | X57: -0.015445447 | Y57: 0.011671687 | Z57: 0.034859199 | AA57: 0.026852074
B58: WEC | C58: United States | D58: Utilities - Regulated Electric | E58: Dec'25 | F58: 2.6 | G58: 2202 | H58: 2908 | I58: 2128 | J58: 2003 | K58: 2558 | L58: 2888 | M58: 1830 | N58: 1957 | O58: 2218 | P58: 2680 | Q58: 1772 | R58: 1864 | S58: 2284 | T58: 3150 | U58: 2010 | V58: 2104 | W58: 2537 | X58: 0.054651163 | Y58: 0.026240353 | Z58: 0.025784272 | AA58: 0.026497696
B59: DOCS | C59: United States | D59: Health Information Services | E59: Sep'26 | F59: 2.6 | G59: 97.88 | H59: 93.65 | I59: 90.64 | J59: 102.19 | K59: 115.26 | L59: 110.97 | M59: 108.47 | N59: 113.61 | O59: 135.28 | P59: 118.06 | Q59: 126.68 | R59: 136.83 | S59: 168.6 | T59: 138.29 | U59: 145.91 | V59: 168.53 | W59: 185.05 | X59: 0.036770453 | Y59: 0.033713184 | Z59: 0.053762529 | AA59: 0.026475464
B60: WMG | C60: United States | D60: Entertainment | E60: Mar'26 | F60: 2.6 | G60: 1614 | H60: 1376 | I60: 1432 | J60: 1497 | K60: 1488 | L60: 1399 | M60: 1564 | N60: 1586 | O60: 1748 | P60: 1494 | Q60: 1554 | R60: 1630 | S60: 1666 | T60: 1484 | U60: 1689 | V60: 1868 | W60: 1840 | X60: -0.0015762926 | Y60: 0.021313546 | Z60: 0.036790849 | AA60: 0.025943045
B61: IQV | C61: United States | D61: Diagnostics & Research | E61: Dec'25 | F61: 2.6 | G61: 3636 | H61: 3568 | I61: 3541 | J61: 3562 | K61: 3739 | L61: 3652 | M61: 3728 | N61: 3736 | O61: 3868 | P61: 3737 | Q61: 3814 | R61: 3896 | S61: 3958 | T61: 3829 | U61: 4017 | V61: 4100 | W61: 4364 | X61: 0.005972087 | Y61: 0.01309931 | Z61: 0.012993631 | AA61: 0.025528169
B62: CLSK | C62: United States | D62: Capital Markets | E62: Mar'26 | F62: 2.5 | G62: 37.13 | H62: 37.2 | I62: 31.03 | J62: 26.17 | K62: 27.82 | L62: 42.55 | M62: 45.52 | N62: 52.52 | O62: 73.79 | P62: 111.8 | Q62: 104.11 | R62: 89.28 | S62: 162.31 | T62: 181.71 | U62: 198.64 | V62: 223.65 | W62: 181.18 | X62: 0.14954011 | Y62: 0.17589922 | Z62: 0.21263095 | AA62: 0.024624499
B63: THR | C63: United States | D63: Specialty Industrial Machinery | E63: Sep'26 | F63: 2.5 | G63: 100.61 | H63: 102.58 | I63: 95.44 | J63: 100.56 | K63: 122.11 | L63: 122.48 | M63: 106.89 | N63: 123.66 | O63: 136.43 | P63: 127.65 | Q63: 115.13 | R63: 114.65 | S63: 134.35 | T63: 134.08 | U63: 108.9 | V63: 131.72 | W63: 147.31 | X63: 0.013074952 | Y63: -0.012504767 | Z63: 0.034696532 | AA63: 0.025459189
B64: CI | C64: United States | D64: Healthcare Plans | E64: Dec'25 | F64: 2.5 | G64: 45688 | H64: 44006 | I64: 45478 | J64: 45281 | K64: 45753 | L64: 46517 | M64: 48586 | N64: 49048 | O64: 51114 | P64: 57255 | Q64: 60523 | R64: 63694 | S64: 65649 | T64: 65502 | U64: 67178 | V64: 69748 | W64: 72472 | X64: 0.033372316 | Y64: 0.02606043 | Z64: 0.023104842 | AA64: 0.025451643
B65: QLYS | C65: United States | D65: Software - Infrastructure | E65: Dec'25 | F65: 2.5 | G65: 109.78 | H65: 113.42 | I65: 119.89 | J65: 125.56 | K65: 130.85 | L65: 130.68 | M65: 137.21 | N65: 142 | O65: 144.57 | P65: 145.81 | Q65: 148.71 | R65: 153.87 | S65: 159.19 | T65: 159.9 | U65: 164.06 | V65: 169.88 | W65: 175.28 | X65: 0.023190362 | Y65: 0.024691557 | Z65: 0.025132649 | AA65: 0.024638991
B66: POST | C66: United States | D66: Packaged Foods | E66: Mar'26 | F66: 2.5 | G66: 1338 | H66: 1410 | I66: 1525 | J66: 1579 | K66: 1566 | L66: 1620 | M66: 1859 | N66: 1945 | O66: 1966 | P66: 1999 | Q66: 1948 | R66: 2010 | S66: 1975 | T66: 1952 | U66: 1984 | V66: 2247 | W66: 2175 | X66: -0.0059253656 | Y66: 0.0045656309 | Z66: 0.029920465 | AA66: 0.024515813
... B152: AB | C152: United States | D152: Asset Management | E152: Dec'25 | F152: -164.8 | G152: 0 | H152: 0 | I152: 0 | J152: 0 | K152: 0 | L152: 0 | M152: 0 | N152: 65.76 | O152: -211.26 | P152: 0 | Q152: 0 | R152: 136.37 | S152: -345.36 | T152: 0 | U152: 0 | V152: 81.41 | W152: 89.76 | X152: 0 | Y152: 0 | Z152: 0.26297909 | AA152: -1.648494
B153: FABG | C153: Sweden | D153: =VLOOKUP(B153,기업리스트!$B:$G,2,FALSE) -> Fabege AB (publ) | E153: Dec'25 | F153: 6.3 | G153: 830 | H153: 766 | I153: 724 | J153: 884 | K153: 920 | L153: 1006 | M153: 960 | N153: 1101 | O153: 897 | P153: 997 | Q153: 837 | R153: 916 | S153: 830 | T153: 841 | U153: 966 | V153: 852 | W153: 1051 | X153: -0.043575419 | Y153: 0.037675234 | Z153: -0.018012947 | AA153: 0.063341932
B154: EAST | C154: Sweden | D154: =VLOOKUP(B154,기업리스트!$B:$G,2,FALSE) -> Eastnine AB (publ) | E154: Dec'25 | F154: 5.1 | G154: 5.45 | H154: 6.23 | I154: 7.35 | J154: 8.23 | K154: 8.5 | L154: 9.05 | M154: 9.09 | N154: 9.06 | O154: 8.97 | P154: 9.06 | Q154: 9.35 | R154: 10.7 | S154: 12.41 | T154: 15.61 | U154: 15.16 | V154: 15.53 | W154: 15.43 | X154: 0.1577553 | Y154: 0.1208654 | Z154: 0.089643653 | AA154: 0.051439278
B155: HTRO | C155: Sweden | D155: =VLOOKUP(B155,기업리스트!$B:$G,2,FALSE) -> Hexatronic Group AB (publ) | E155: Dec'25 | F155: 0.3 | G155: 1170 | H155: 1388 | I155: 1662 | J155: 1729 | K155: 1795 | L155: 2115 | M155: 2258 | N155: 1916 | O155: 1860 | P155: 1781 | Q155: 2024 | R155: 1951 | S155: 1824 | T155: 1881 | U155: 1906 | V155: 1883 | W155: 1848 | X155: 0.013192612 | Y155: -0.015364583 | Z155: -0.0089923301 | AA155: 0.003202562
B156: MYCR | C156: Sweden | D156: =VLOOKUP(B156,기업리스트!$B:$G,2,FALSE) -> Mycronic AB (publ) | E156: Dec'25 | F156: -0.5 | G156: 1294 | H156: 1135 | I156: 1273 | J156: 1214 | K156: 1497 | L156: 1219 | M156: 1245 | N156: 1274 | O156: 1968 | P156: 1692 | Q156: 1527 | R156: 1780 | S156: 2058 | T156: 2142 | U156: 2066 | V156: 1709 | W156: 2021 | X156: 0.063766473 | Y156: 0.071799654 | Z156: -0.0088242605 | AA156: -0.0046394984
B157: AFRY | C157: Sweden | D157: =VLOOKUP(B157,기업리스트!$B:$G,2,FALSE) -> Afry AB | E157: Dec'25 | F157: -1.7 | G157: 5508 | H157: 5670 | I157: 5975 | J157: 5298 | K157: 6609 | L157: 6916 | M157: 6869 | N157: 6059 | O157: 7135 | P157: 6891 | Q157: 7191 | R157: 5993 | S157: 7084 | T157: 6749 | U157: 6674 | V157: 5687 | W157: 6647 | X157: -0.0052284694 | Y157: -0.019136099 | Z157: -0.01154717 | AA157: -0.01668321
B158: 8020 | C158: Japan | D158: =VLOOKUP(B158,기업리스트!$B:$G,2,FALSE) -> Kanematsu Corporation | E158: Jun'26 | F158: 96.4 | G158: 188571 | H158: 196802 | I158: 767963 | J158: 0 | K158: 234993 | L158: 228264 | M158: 911408 | N158: 0 | O158: 249636 | P158: 251915 | Q158: 985993 | R158: 251011 | S158: -251011 | T158: 263171 | U158: 269192 | V158: 251116 | W158: 262379 | X158: 0.0090927597 | Y158: -0.57382457 | Z158: 0.00019723384 | AA158: 0.96417062
B159: 8934 | C159: Japan | D159: =VLOOKUP(B159,기업리스트!$B:$G,2,FALSE) -> Sun Frontier Fudousan Co., Ltd. | E159: Jun'26 | F159: 8.5 | G159: 14113 | H159: 16292 | I159: 9633 | J159: 22903 | K159: 12430 | L159: 39995 | M159: 7449 | N159: 18452 | O159: 30546 | P159: 13260 | Q159: 17610 | R159: 15685 | S159: 21101 | T159: 23715 | U159: 42673 | V159: 27319 | W159: 30913 | X159: 0.15453175 | Y159: 0.3208639 | Z159: 0.11276097 | AA159: 0.085464428
B160: 5351 | C160: Japan | D160: =VLOOKUP(B160,기업리스트!$B:$G,2,FALSE) -> Shinagawa Refra Co., Ltd. | E160: Jun'26 | F160: 6.2 | G160: 26611 | H160: 30191 | I160: 28140 | J160: 29661 | K160: 31403 | L160: 33285 | M160: 30614 | N160: 36670 | O160: 36034 | P160: 36426 | Q160: 35045 | R160: 33867 | S160: 34363 | T160: 36864 | U160: 38978 | V160: 38266 | W160: 43577 | X160: 0.0031352675 | Y160: 0.028064993 | Z160: 0.030533344 | AA160: 0.062059257
B161: 6479 | C161: Japan | D161: =VLOOKUP(B161,기업리스트!$B:$G,2,FALSE) -> MINEBEA MITSUMI Inc. | E161: Sep'26 | F161: 5.5 | G161: 304348 | H161: 289532 | I161: 251040 | J161: 330021 | K161: 371424 | L161: 339718 | M161: 292370 | N161: 379747 | O161: 381207 | P161: 348803 | Q161: 355454 | R161: 422783 | S161: 369643 | T161: 374823 | U161: 366925 | V161: 411389 | W161: 453921 | X161: 0.017385111 | Y161: 0.0075333141 | Z161: -0.0074267977 | AA161: 0.05534483
B162: 8425 | C162: Japan | D162: =VLOOKUP(B162,기업리스트!$B:$G,2,FALSE) -> Mizuho Leasing Company, Limited | E162: Jun'26 | F162: 5.2 | G162: 141699 | H162: 129577 | I162: 165269 | J162: 114038 | K162: 114791 | L162: 110987 | M162: 189884 | N162: 123854 | O162: 147944 | P162: 230946 | Q162: 153383 | R162: 128217 | S162: 170200 | T162: 162497 | U162: 234509 | V162: 219516 | W162: 211089 | X162: -0.10025544 | Y162: 0.13206316 | Z162: 0.13128556 | AA162: 0.051973887
B163: 5401 | C163: Japan | D163: =VLOOKUP(B163,기업리스트!$B:$G,2,FALSE) -> Nippon Steel Corporation | E163: Sep'26 | F163: 5 | G163: 1778537 | H163: 1866409 | I163: 1919181 | J163: 1955225 | K163: 2087275 | L163: 2013904 | M163: 2199786 | N163: 2212635 | O163: 2229394 | P163: 2226281 | Q163: 2191509 | R163: 2188226 | S163: 2172763 | T163: 2143028 | U163: 2008749 | V163: 2626898 | W163: 2620676 | X163: -0.0094834373 | Y163: -0.021017705 | Z163: 0.051531077 | AA163: 0.050038106
B164: 4483 | C164: Japan | D164: =VLOOKUP(B164,기업리스트!$B:$G,2,FALSE) -> JMDC Inc. | E164: Jun'26 | F164: 4.8 | G164: 5020 | H164: 6128 | I164: 6135 | J164: 5776 | K164: 6283 | L164: 7482 | M164: 8267 | N164: 6698 | O164: 7048 | P164: 8534 | Q164: 10100 | R164: 8422 | S164: 10775 | T164: 11408 | U164: 0 | V164: 10725 | W164: 12355 | X164: 0.075969443 | Y164: -0.24812677 | Z164: 0.075249142 | AA164: 0.048012641
B165: 2317 | C165: Japan | D165: =VLOOKUP(B165,기업리스트!$B:$G,2,FALSE) -> Systena Corporation | E165: Jun'26 | F165: 4.7 | G165: 15545 | H165: 16163 | I165: 18233 | J165: 17627 | K165: 18178 | L165: 18529 | M165: 20192 | N165: 18734 | O165: 18787 | P165: 19619 | Q165: 19800 | R165: 19746 | S165: 20346 | T165: 20472 | U165: 23057 | V165: 22553 | W165: 24414 | X165: 0.010728075 | Y165: 0.040528097 | Z165: 0.033568123 | AA165: 0.04706808
B166: 6723 | C166: Japan | D166: =VLOOKUP(B166,기업리스트!$B:$G,2,FALSE) -> Renesas Electronics Corporation | E166: Dec'25 | F166: 4.7 | G166: 313922 | H166: 346288 | I166: 376620 | J166: 387132 | K166: 390813 | L166: 359374 | M166: 368717 | N166: 379391 | O166: 361933 | P166: 351790 | Q166: 358807 | R166: 345282 | S166: 292600 | T166: 308777 | U166: 325534 | V166: 335364 | W166: 351537 | X166: -0.031897419 | Y166: -0.02548745 | Z166: -0.0077959869 | AA166: 0.046691093
B167: 3636 | C167: Japan | D167: =VLOOKUP(B167,기업리스트!$B:$G,2,FALSE) -> Mitsubishi Research Institute, Inc. | E167: Dec'25 | F167: 4 | G167: 22628 | H167: 25358 | I167: 42907 | J167: 23408 | K167: 24947 | L167: 27459 | M167: 45866 | N167: 23553 | O167: 25248 | P167: 27668 | Q167: 38866 | R167: 23720 | S167: 25108 | T167: 27706 | U167: 37731 | V167: 26186 | W167: 29835 | X167: 0.0003293979 | Y167: -0.0098353553 | Z167: 0.021581412 | AA167: 0.040494813
B168: 7186 | C168: Japan | D168: =VLOOKUP(B168,기업리스트!$B:$G,2,FALSE) -> Yokohama Financial Group, Inc. | E168: Sep'26 | F168: 4 | G168: 65768 | H168: 63065 | I168: 68632 | J168: 64772 | K168: 68179 | L168: 65403 | M168: 70191 | N168: 75226 | O168: 68627 | P168: 77436 | Q168: 76731 | R168: 77813 | S168: 80513 | T168: 81314 | U168: 90820 | V168: 99424 | W168: 94590 | X168: 0.012409878 | Y168: 0.044533159 | Z168: 0.06539672 | AA168: 0.039983412
B169: 1926 | C169: Japan | D169: =VLOOKUP(B169,기업리스트!$B:$G,2,FALSE) -> Raito Kogyo Co., Ltd. | E169: Jun'26 | F169: 3.9 | G169: 26314 | H169: 29154 | I169: 30824 | J169: 23865 | K169: 27934 | L169: 31190 | M169: 31985 | N169: 25771 | O169: 29304 | P169: 30164 | Q169: 32085 | R169: 25421 | S169: 29546 | T169: 34119 | U169: 32371 | V169: 30520 | W169: 34543 | X169: 0.033741127 | Y169: 0.0023603007 | Z169: 0.041981936 | AA169: 0.039484497
... B174: 3034 | C174: Japan | D174: =VLOOKUP(B174,기업리스트!$B:$G,2,FALSE) -> Qol Holdings Co., Ltd. | E174: Jun'26 | F174: 2.5 | G174: 41464 | H174: 42731 | I174: 41654 | J174: 40550 | K174: 41909 | L174: 43642 | M174: 43935 | N174: 43403 | O174: 45137 | P174: 45988 | Q174: 45524 | R174: 61036 | S174: 63735 | T174: 73436 | U174: 65765 | V174: 71730 | W174: 70500 | X174: 0.1269078 | Y174: 0.083046473 | Z174: 0.040511872 | AA174: 0.024629914
B175: 7088 | C175: Japan | D175: =VLOOKUP(B175,기업리스트!$B:$G,2,FALSE) -> Forum Engineering Inc. | E175: Jun'26 | F175: 2.3 | N175: 7720 | O175: 7584 | P175: 8188 | Q175: 7787 | R175: 8528 | S175: 8427 | T175: 9097 | U175: 8636 | V175: 9228 | W175: 9252 | X175: 0.027604009 | Y175: 0.025089394 | Z175: 0.020179889 | AA175: 0.023312987
B176: 8111 | C176: Japan | D176: =VLOOKUP(B176,기업리스트!$B:$G,2,FALSE) -> Goldwin Inc. | E176: Jun'26 | F176: 2.2 | G176: 21130 | H176: 35574 | I176: 24453 | J176: 21099 | K176: 24210 | L176: 41437 | M176: 28306 | N176: 23150 | O176: 27946 | P176: 43736 | Q176: 32075 | R176: 24601 | S176: 28766 | T176: 43466 | U176: 35472 | V176: 23878 | W176: 31711 | X176: -0.0020901392 | Y176: 0.026352127 | Z176: -0.0054646461 | AA176: 0.022381481
B177: 7250 | C177: Japan | D177: =VLOOKUP(B177,기업리스트!$B:$G,2,FALSE) -> Pacific Industrial Co., Ltd. | E177: Jun'26 | F177: 2.2 | G177: 36892 | H177: 41626 | I177: 44424 | J177: 44468 | K177: 46443 | L177: 52512 | M177: 47831 | N177: 49301 | O177: 53354 | P177: 53328 | Q177: 51365 | R177: 49789 | S177: 47857 | T177: 51731 | U177: 54820 | V177: 52561 | W177: 52475 | X177: -0.0078926949 | Y177: 0.017211147 | Z177: 0.013575126 | AA177: 0.02231252
B178: 3110 | C178: Japan | D178: =VLOOKUP(B178,기업리스트!$B:$G,2,FALSE) -> Nitto Boseki Co., Ltd. | E178: Jun'26 | F178: 2 | G178: 20568 | H178: 21034 | I178: 21931 | J178: 23827 | K178: 23210 | L178: 21725 | M178: 18767 | N178: 20297 | O178: 22437 | P178: 25307 | Q178: 25212 | R178: 26115 | S178: 26936 | T178: 28469 | U178: 27515 | V178: 28231 | W178: 29181 | X178: 0.030530076 | Y178: 0.021577409 | Z178: 0.019406613 | AA178: 0.020197749
B179: 6645 | C179: Japan | D179: =VLOOKUP(B179,기업리스트!$B:$G,2,FALSE) -> OMRON Corporation | E179: Sep'26 | F179: 1.9 | G179: 189258 | H179: 204318 | I179: 184386 | J179: 220032 | K179: 233559 | L179: 238105 | M179: 203351 | N179: 197323 | O179: 207311 | P179: 210776 | Q179: 183713 | R179: 190925 | S179: 205060 | T179: 222055 | U179: 189477 | V179: 203971 | W179: 220840 | X179: 0.014268654 | Y179: 0.0071892466 | Z179: 0.016155697 | AA179: 0.019230699
B180: 9404 | C180: Japan | D180: =VLOOKUP(B180,기업리스트!$B:$G,2,FALSE) -> Nippon Television Holdings, Inc. | E180: Jun'26 | F180: 1.9 | G180: 97121 | H180: 106247 | I180: 105198 | J180: 100453 | K180: 98988 | L180: 106192 | M180: 108346 | N180: 98010 | O180: 97990 | P180: 110219 | Q180: 117304 | R180: 106087 | S180: 110786 | T180: 116740 | U180: 128302 | V180: 114649 | W180: 119832 | X180: 0.014673849 | Y180: 0.024390298 | Z180: 0.018535878 | AA180: 0.019227295
B181: 4901 | C181: Japan | D181: =VLOOKUP(B181,기업리스트!$B:$G,2,FALSE) -> FUJIFILM Holdings Corporation | E181: Jun'26 | F181: 1.8 | G181: 622481 | H181: 655768 | I181: 664871 | J181: 625860 | K181: 724071 | L181: 744329 | M181: 764781 | N181: 660759 | O181: 727711 | P181: 766941 | Q181: 805505 | R181: 749015 | S181: 765734 | T181: 812770 | U181: 868309 | V181: 749482 | W181: 822881 | X181: 0.014844867 | Y181: 0.020045809 | Z181: 0.00014612801 | AA181: 0.017879138
B182: 6590 | C182: Japan | D182: =VLOOKUP(B182,기업리스트!$B:$G,2,FALSE) -> Shibaura Mechatronics Corporation | E182: Jun'26 | F182: 1.8 | G182: 11816 | H182: 11753 | I182: 15603 | J182: 13821 | K182: 15435 | L182: 16201 | M182: 15544 | N182: 14254 | O182: 16257 | P182: 17388 | Q182: 19657 | R182: 17129 | S182: 19262 | T182: 20163 | U182: 24361 | V182: 21512 | W182: 20765 | X182: 0.037788006 | Y182: 0.061723373 | Z182: 0.054167954 | AA182: 0.017620577
B183: 7701 | C183: Japan | D183: =VLOOKUP(B183,기업리스트!$B:$G,2,FALSE) -> Shimadzu Corporation | E183: Sep'26 | F183: 1.7 | G183: 103791 | H183: 122317 | I183: 98639 | J183: 123254 | K183: 117579 | L183: 142768 | M183: 109200 | N183: 130314 | O183: 126109 | P183: 146272 | Q183: 116938 | R183: 134309 | S183: 133049 | T183: 154751 | U183: 118370 | V183: 137972 | W183: 142380 | X183: 0.015980986 | Y183: 0.0026565402 | Z183: 0.0067773216 | AA183: 0.017148097
B184: 6965 | C184: Japan | D184: =VLOOKUP(B184,기업리스트!$B:$G,2,FALSE) -> Hamamatsu Photonics K.K. | E184: Dec'25 | F184: 1.5 | G184: 47160 | H184: 47028 | I184: 53488 | J184: 51247 | K184: 57040 | L184: 55163 | M184: 56455 | N184: 52870 | O184: 56957 | P184: 53512 | Q184: 50474 | R184: 46562 | S184: 53413 | T184: 50587 | U184: 56158 | V184: 48722 | W184: 56584 | X184: -0.014340977 | Y184: 0.028273543 | Z184: 0.010448916 | AA184: 0.015180965
B185: 7917 | C185: Japan | D185: =VLOOKUP(B185,기업리스트!$B:$G,2,FALSE) -> ZACROS Corporation | E185: Jun'26 | F185: 1.3 | G185: 30608 | H185: 33063 | I185: 32928 | J185: 33348 | K185: 32910 | L185: 32891 | M185: 30215 | N185: 31893 | O185: 34024 | P185: 35846 | Q185: 34392 | R185: 38469 | S185: 36980 | T185: 37643 | U185: 37348 | V185: 39307 | W185: 39022 | X185: 0.012334663 | Y185: 0.020042852 | Z185: 0.005570327 | AA185: 0.013498328
B186: 4975 | C186: Japan | D186: =VLOOKUP(B186,기업리스트!$B:$G,2,FALSE) -> JCU Corporation | E186: Jun'26 | F186: 1.3 | G186: 6137 | H186: 6187 | I186: 6415 | J186: 6160 | K186: 6957 | L186: 7585 | M186: 6435 | N186: 5225 | O186: 5639 | P186: 6348 | Q186: 7647 | R186: 5912 | S186: 6824 | T186: 7996 | U186: 7624 | V186: 7037 | W186: 7221 | X186: 0.061651266 | Y186: -0.00081045844 | Z186: 0.039674143 | AA186: 0.0134663
B187: 7287 | C187: Japan | D187: =VLOOKUP(B187,기업리스트!$B:$G,2,FALSE) -> Nippon Seiki Co., Ltd. | E187: Jun'26 | F187: 1.3 | G187: 49810 | H187: 55708 | I187: 62912 | J187: 56212 | K187: 71742 | L187: 71570 | M187: 76251 | N187: 74397 | O187: 75794 | P187: 79454 | Q187: 82709 | R187: 76383 | S187: 76064 | T187: 75353 | U187: 88597 | V187: 76224 | W187: 80018 | X187: -0.013035186 | Y187: 0.018962413 | Z187: -0.00050253321 | AA187: 0.012503241
... B201: 7752 | C201: Japan | D201: =VLOOKUP(B201,기업리스트!$B:$G,2,FALSE) -> Ricoh Company, Ltd. | E201: Jun'26 | F201: 0.5 | G201: 418659 | H201: 432732 | I201: 482392 | J201: 459341 | K201: 514195 | L201: 555072 | M201: 605572 | N201: 534601 | O201: 577989 | P201: 585098 | Q201: 651299 | R201: 574379 | S201: 628209 | T201: 632816 | U201: 692472 | V201: 580798 | W201: 641653 | X201: 0.019564696 | Y201: 0.016557265 | Z201: 0.0025392859 | AA201: 0.0053048284
B202: 7164 | C202: Japan | D202: =VLOOKUP(B202,기업리스트!$B:$G,2,FALSE) -> ZENKOKU HOSHO Co.,Ltd. | E202: Jun'26 | F202: 0.5 | J202: 10276 | K202: 10374 | L202: 10410 | M202: 19212 | N202: 10536 | O202: 10643 | P202: 10725 | Q202: 19734 | R202: 10761 | S202: 11301 | T202: 11384 | U202: 23526 | V202: 11481 | W202: 11586 | X202: 0.012547362 | Y202: 0.071305002 | Z202: 0.012637787 | AA202: 0.0049400263
B203: 9831 | C203: Japan | D203: =VLOOKUP(B203,기업리스트!$B:$G,2,FALSE) -> Yamada Holdings Co., Ltd. | E203: Jun'26 | F203: 0.3 | G203: 417412 | H203: 392398 | I203: 426582 | J203: 375859 | K203: 398775 | L203: 402710 | M203: 423242 | N203: 363709 | O203: 411494 | P203: 395858 | Q203: 420948 | R203: 379103 | S203: 416898 | T203: 397653 | U203: 435415 | V203: 377663 | W203: 422436 | X203: 0.0011129664 | Y203: 0.0089601029 | Z203: -0.00088394046 | AA203: 0.0034024953
B204: 2001 | C204: Japan | D204: =VLOOKUP(B204,기업리스트!$B:$G,2,FALSE) -> Nippn Corporation | E204: Jun'26 | F204: 0.2 | G204: 79577 | H204: 84244 | I204: 79538 | J204: 86205 | K204: 90283 | L204: 98193 | M204: 90844 | N204: 98631 | O204: 100342 | P204: 106001 | Q204: 95540 | R204: 101969 | S204: 102940 | T204: 107604 | U204: 98365 | V204: 104219 | W204: 103684 | X204: 0.0039439045 | Y204: 0.0069231203 | Z204: 0.0054760781 | AA204: 0.0018008946
B205: 8001 | C205: Japan | D205: =VLOOKUP(B205,기업리스트!$B:$G,2,FALSE) -> ITOCHU Corporation | E205: Sep'26 | F205: -0.1 | G205: 3218884 | H205: 3199694 | I205: 3378021 | J205: 3614143 | K205: 3552055 | L205: 3401414 | M205: 3348491 | N205: 3425607 | O205: 3676963 | P205: 3578849 | Q205: 3598918 | R205: 3692389 | S205: 3748140 | T205: 3684787 | U205: 3558933 | V205: 3690226 | W205: 3737092 | X205: 0.0072469459 | Y205: -0.0027155912 | Z205: -0.00014730069 | AA205: -0.00075248163
B206: 4536 | C206: Japan | D206: =VLOOKUP(B206,기업리스트!$B:$G,2,FALSE) -> Santen Pharmaceutical Co., Ltd. | E206: Jun'26 | F206: -0.8 | G206: 63773 | H206: 67042 | I206: 70456 | J206: 65533 | K206: 63382 | L206: 70871 | M206: 79251 | N206: 72389 | O206: 73417 | P206: 77027 | Q206: 79132 | R206: 74771 | S206: 71633 | T206: 76369 | U206: 77231 | V206: 68737 | W206: 69142 | X206: -0.0021747537 | Y206: -0.0062966827 | Z206: -0.020113065 | AA206: -0.0084736538
B207: 7004 | C207: Japan | D207: =VLOOKUP(B207,기업리스트!$B:$G,2,FALSE) -> Kanadevia Corporation | E207: Jun'26 | F207: -1 | G207: 100000 | H207: 107596 | I207: 153767 | J207: 96350 | K207: 110884 | L207: 124169 | M207: 161289 | N207: 102475 | O207: 129717 | P207: 140125 | Q207: 183527 | R207: 121563 | S207: 148397 | T207: 143472 | U207: 197091 | V207: 125441 | W207: 142273 | X207: 0.0056383631 | Y207: 0.022721828 | Z207: 0.006351931 | AA207: -0.0099674317
B208: 7731 | C208: Japan | D208: =VLOOKUP(B208,기업리스트!$B:$G,2,FALSE) -> Nikon Corporation | E208: Sep'26 | F208: -1.3 | G208: 133297 | H208: 133267 | I208: 145648 | J208: 142682 | K208: 167767 | L208: 172008 | M208: 158146 | N208: 173150 | O208: 197616 | P208: 188333 | Q208: 163896 | R208: 168883 | S208: 179892 | T208: 202614 | U208: 158121 | V208: 154794 | W208: 170993 | X208: 0.020372209 | Y208: -0.0080737049 | Z208: -0.019857366 | AA208: -0.012796565
B209: 8058 | C209: Japan | D209: =VLOOKUP(B209,기업리스트!$B:$G,2,FALSE) -> Mitsubishi Corporation | E209: Jun'26 | F209: -1.4 | G209: 3933005 | H209: 4644403 | I209: 4893690 | J209: 5443439 | K209: 5278439 | L209: 5562666 | M209: 5287429 | N209: 4735665 | O209: 4825346 | P209: 5144571 | Q209: 4862019 | R209: 4685953 | S209: 4668798 | T209: 4588524 | U209: 4674326 | V209: 4218706 | W209: 4419137 | X209: -0.028719447 | Y209: -0.0099808596 | Z209: -0.025097057 | AA209: -0.013755159
B210: 7240 | C210: Japan | D210: =VLOOKUP(B210,기업리스트!$B:$G,2,FALSE) -> NOK Corporation | E210: Jun'26 | F210: -2.4 | G210: 167633 | H210: 181884 | I210: 176255 | J210: 161031 | K210: 191738 | L210: 187446 | M210: 169741 | N210: 163957 | O210: 190282 | P210: 213308 | Q210: 182955 | R210: 188170 | S210: 205496 | T210: 195440 | U210: 177753 | V210: 171866 | W210: 187531 | X210: -0.022619754 | Y210: -0.0067378096 | Z210: -0.021260753 | AA210: -0.023935621
B211: 5411 | C211: Japan | D211: =VLOOKUP(B211,기업리스트!$B:$G,2,FALSE) -> JFE Holdings, Inc. | E211: Jun'26 | F211: -2.6 | G211: 1054036 | H211: 1154416 | I211: 1267751 | J211: 1253600 | K211: 1310735 | L211: 1344252 | M211: 1360206 | N211: 1262086 | O211: 1314501 | P211: 1289159 | Q211: 1308885 | R211: 1211141 | S211: 1239640 | T211: 1224689 | U211: 1184177 | V211: 1115313 | W211: 1117336 | X211: -0.012769308 | Y211: -0.025019887 | Z211: -0.019719128 | AA211: -0.02567352
B212: 5449 | C212: Japan | D212: =VLOOKUP(B212,기업리스트!$B:$G,2,FALSE) -> Osaka Steel Co., Ltd. | E212: Jun'26 | F212: -4.9 | G212: 24897 | H212: 27975 | I212: 29259 | J212: 28018 | K212: 27174 | L212: 30603 | M212: 31346 | N212: 30887 | O212: 26670 | P212: 29087 | Q212: 30483 | R212: 31626 | S212: 28323 | T212: 28194 | U212: 28281 | V212: 25771 | W212: 22870 | X212: -0.0074716154 | Y212: -0.018562541 | Z212: -0.050290318 | AA212: -0.049317621
B213: 6758 | C213: Japan | D213: =VLOOKUP(B213,기업리스트!$B:$G,2,FALSE) -> Sony Group Corporation | E213: Sep'26 | F213: -5.4 | G213: 3031319 | H213: 2263986 | I213: 2229760 | J213: 2625464 | K213: 3078304 | L213: 3040845 | M213: 2963652 | N213: 2828623 | O213: 3747527 | P213: 3480966 | Q213: 2565361 | R213: 2971224 | S213: 4409574 | T213: 2630244 | U213: 2621615 | V213: 3107907 | W213: 3713681 | X213: -0.063358463 | Y213: 0.0044729801 | Z213: 0.010819814 | AA213: -0.054497178
B214: 2432 | C214: Japan | D214: =VLOOKUP(B214,기업리스트!$B:$G,2,FALSE) -> DeNA Co., Ltd. | E214: Sep'26 | F214: -8.6 | G214: 31045 | H214: 31738 | I214: 34773 | J214: 36449 | K214: 30172 | L214: 33519 | M214: 36150 | N214: 38997 | O214: 29002 | P214: 32584 | Q214: 33982 | R214: 36280 | S214: 46465 | T214: 47270 | U214: 41727 | V214: 41424 | W214: 31301 | X214: 0.09835846 | Y214: 0.047226474 | Z214: 0.029951905 | AA214: -0.085727531
B215: SUZLON | C215: India | D215: =VLOOKUP(B215,기업리스트!$B:$G,2,FALSE) -> Suzlon Energy Limited | E215: Jun'26 | F215: 14.8 | G215: 13465 | H215: 15969 | I215: 24416 | J215: 13776 | K215: 14304 | L215: 14490 | M215: 16899 | N215: 13475 | O215: 14172 | P215: 15529 | Q215: 21792 | R215: 20160 | S215: 20930 | T215: 29688 | U215: 37735 | V215: 31173 | W215: 38655 | X215: 0.18057415 | Y215: 0.17222642 | Z215: 0.10149014 | AA215: 0.1482941
B216: NYKAA | C216: India | D216: =VLOOKUP(B216,기업리스트!$B:$G,2,FALSE) -> FSN E-Commerce Ventures Limited | E216: Sep'26 | F216: 6.9 | G216: 10984 | H216: 9733 | I216: 11484 | J216: 12308 | K216: 14628 | L216: 13017 | M216: 14218 | N216: 15070 | O216: 17888 | P216: 16680 | Q216: 17461 | R216: 18747 | S216: 22672 | T216: 20618 | U216: 21549 | V216: 23460 | W216: 28733 | X216: 0.052117522 | Y216: 0.051422677 | Z216: 0.056385041 | AA216: 0.068641774
B217: BALRAMCHIN | C217: India | D217: =VLOOKUP(B217,기업리스트!$B:$G,2,FALSE) -> Balrampur Chini Mills Limited | E217: Jun'26 | F217: 6.7 | G217: 12138 | H217: 12122 | I217: 12796 | J217: 10801 | K217: 11131 | L217: 9812 | M217: 14915 | N217: 13896 | O217: 15395 | P217: 12304 | Q217: 14343 | R217: 14216 | S217: 12979 | T217: 11921 | U217: 15037 | V217: 15423 | W217: 16708 | X217: -0.0071134059 | Y217: 0.012981911 | Z217: 0.022288701 | AA217: 0.067359104
B218: DATAPATTNS | C218: India | D218: =VLOOKUP(B218,기업리스트!$B:$G,2,FALSE) -> Data Patterns (India) Limited | E218: Sep'26 | F218: 6.7 | G218: 438.4 | H218: 1705 | I218: 683.8 | J218: 881.6 | K218: 1118 | L218: 1851 | M218: 896.9 | N218: 1083 | O218: 1395 | P218: 1823 | Q218: 1041 | R218: 910.2 | S218: 1170 | T218: 3962 | U218: 993.3 | V218: 3075 | W218: 1789 | X218: 0.43262813 | Y218: -0.0067342444 | Z218: 0.30769668 | AA218: 0.067280415
B219: MINDACORP | C219: India | D219: =VLOOKUP(B219,기업리스트!$B:$G,2,FALSE) -> Minda Corporation Limited | E219: Sep'26 | F219: 5.7 | G219: 7383 | H219: 9477 | I219: 10102 | J219: 11471 | K219: 10683 | L219: 10745 | M219: 10745 | N219: 11958 | O219: 11658 | P219: 12149 | Q219: 11924 | R219: 12900 | S219: 12526 | T219: 13212 | U219: 13859 | V219: 15354 | W219: 15637 | X219: 0.021475181 | Y219: 0.038269847 | Z219: 0.046745528 | AA219: 0.056614074
B220: AAVAS | C220: India | D220: =VLOOKUP(B220,기업리스트!$B:$G,2,FALSE) -> Aavas Financiers Limited | E220: Sep'26 | F220: 4.1 | G220: 2065 | H220: 2521 | I220: 2174 | J220: 2526 | K220: 2582 | L220: 2787 | M220: 2747 | N220: 2885 | O220: 2847 | P220: 3192 | Q220: 2988 | R220: 3268 | S220: 3331 | T220: 3646 | U220: 3453 | V220: 3839 | W220: 3923 | X220: 0.035527037 | Y220: 0.035139424 | Z220: 0.041684918 | AA220: 0.041488542
B221: PVRINOX | C221: India | D221: =VLOOKUP(B221,기업리스트!$B:$G,2,FALSE) -> PVR INOX Limited | E221: Sep'26 | F221: 2.6 | G221: 6142 | H221: 5355 | I221: 9814 | J221: 6867 | K221: 9407 | L221: 11418 | M221: 13049 | N221: 19999 | O221: 15459 | P221: 12564 | Q221: 11907 | R221: 16221 | S221: 17173 | T221: 12498 | U221: 14691 | V221: 18230 | W221: 18798 | X221: -0.0011405858 | Y221: 0.048166923 | Z221: 0.033161118 | AA221: 0.025961784
B222: ASTRAL | C222: India | D222: =VLOOKUP(B222,기업리스트!$B:$G,2,FALSE) -> Astral Limited | E222: Sep'26 | F222: 2.6 | G222: 10989 | H222: 14409 | I222: 12129 | J222: 11716 | K222: 12678 | L222: 0 | M222: 12831 | N222: 13630 | O222: 13702 | P222: 16251 | Q222: 13836 | R222: 13704 | S222: 13970 | T222: 16814 | U222: 13612 | V222: 15774 | W222: 15510 | X222: 0.0097470612 | Y222: -0.0038406145 | Z222: 0.035628227 | AA222: 0.02559415
B223: MAZDOCK | C223: India | D223: =VLOOKUP(B223,기업리스트!$B:$G,2,FALSE) -> Mazagon Dock Shipbuilders Limited | E223: Jun'26 | F223: 1.5 | G223: 15701 | H223: 15525 | I223: 13964 | J223: 22303 | K223: 17024 | L223: 18159 | M223: 20786 | N223: 21728 | O223: 18277 | P223: 23625 | Q223: 31037 | R223: 23570 | S223: 27568 | T223: 31436 | U223: 31744 | V223: 26256 | W223: 29292 | X223: 0.073827977 | Y223: 0.006222989 | Z223: 0.023495862 | AA223: 0.014734539
B224: PAGEIND | C224: India | D224: =VLOOKUP(B224,기업리스트!$B:$G,2,FALSE) -> Page Industries Limited | E224: Sep'26 | F224: 1.5 | G224: 11898 | H224: 11111 | I224: 13413 | J224: 12550 | K224: 12233 | L224: 8946 | M224: 12400 | N224: 11251 | O224: 12288 | P224: 9829 | Q224: 12775 | R224: 12463 | S224: 13131 | T224: 10981 | U224: 13166 | V224: 12909 | W224: 13868 | X224: 0.023901407 | Y224: 0.007922999 | Z224: 0.0089664462 | AA224: 0.014685078
B225: WOCKPHARMA | C225: India | D225: =VLOOKUP(B225,기업리스트!$B:$G,2,FALSE) -> Wockhardt Limited | E225: Jun'26 | F225: -0.9 | G225: 8620 | H225: 8539 | I225: 6546 | J225: 5950 | K225: 6790 | L225: 6990 | M225: 6840 | N225: 6440 | O225: 7530 | P225: 7010 | Q225: 7320 | R225: 7390 | S225: 8090 | T225: 7210 | U225: 7660 | V225: 7380 | W225: 7820 | X225: 0.006709158 | Y225: 0.011329557 | Z225: -0.00032948929 | AA225: -0.008899143
B226: ANTHEM | C226: India | D226: =VLOOKUP(B226,기업리스트!$B:$G,2,FALSE) -> Anthem Biosciences Limited | E226: Sep'26 | F226: -3.6 | M226: 2944 | N226: 2944 | O226: 4157 | P226: 4157 | Q226: 3386 | R226: 5250 | S226: 4978 | T226: 4921 | U226: 5402 | V226: 5500 | W226: 4232 | X226: 0.04299139 | Y226: 0.1087672 | Z226: 0.012164858 | AA226: -0.03586366
B227: GODREJPROP | C227: India | D227: =VLOOKUP(B227,기업리스트!$B:$G,2,FALSE) -> Godrej Properties Limited | E227: Sep'26 | F227: -11 | G227: 2788 | H227: 13306 | I227: 2447 | J227: 1651 | K227: 1962 | L227: 16463 | M227: 9361 | N227: 3430 | O227: 3304 | P227: 14261 | Q227: 7390 | R227: 10932 | S227: 9689 | T227: 21217 | U227: 4346 | V227: 7404 | W227: 4984 | X227: 0.16455337 | Y227: -0.061834728 | Z227: -0.076390092 | AA227: -0.11030101
B228: ABFRL | C228: India | D228: =VLOOKUP(B228,기업리스트!$B:$G,2,FALSE) -> Aditya Birla Fashion and Retail Limited | E228: Sep'26 | F228: -19.9 | G228: 29871 | H228: 22828 | I228: 28748 | J228: 30746 | K228: 35888 | L228: 28797 | M228: 31961 | N228: 32264 | O228: 41667 | P228: 0 | Q228: 34278 | R228: 36439 | S228: 43047 | T228: 17195 | U228: 18315 | V228: 19817 | W228: 23432 | X228: 0.15114623 | Y228: -0.12189311 | Z228: -0.14454416 | AA228: -0.19939212
B229: XFAB | C229: France | D229: =VLOOKUP(B229,기업리스트!$B:$G,2,FALSE) -> X-FAB Silicon Foundries SE | E229: Dec'25 | F229: 4 | G229: 172.28 | H229: 178.66 | I229: 188.83 | J229: 188.34 | K229: 183.64 | L229: 208.11 | M229: 227.13 | N229: 233.81 | O229: 237.73 | P229: 216.15 | Q229: 205.1 | R229: 206.37 | S229: 188.76 | T229: 204.11 | U229: 215.28 | V229: 228.57 | W229: 222.29 | X229: -0.014748034 | Y229: 0.012656339 | Z229: 0.027255316 | AA229: 0.040073143

Sheet Operating Income
B2: Ticker | C2: Country | D2: Industry | E2: Latest_Date | F2: Growth_Rate | G2: 4Q21 | H2: 1Q22 | I2: 2Q22 | J2: 3Q22 | K2: 4Q22 | L2: 1Q23 | M2: 2Q23 | N2: 3Q23 | O2: 4Q23 | P2: 1Q24 | Q2: 2Q24 | R2: 3Q24 | S2: 4Q24 | T2: 1Q25 | U2: 2Q25 | V2: 3Q25 | W2: 4Q25 | X2: 1Q25 | Y2: 2Q25 | Z2: 3Q25 | AA2: 4Q25
B3: IREN | C3: United States | D3: Capital Markets | E3: Jun'26 | F3: 22815.6 | G3: 5.56 | H3: 1.18 | I3: -8.63 | J3: -14.34 | K3: -17.74 | L3: -10.12 | M3: -9.65 | N3: -10.45 | O3: -2.44 | P3: 7.02 | Q3: -13.6 | R3: -39.28 | S3: 18.01 | T3: 27.9 | U3: 13.78 | V3: -60.14 | W3: -84.66 | X3: -0.7497307 | Y3: -3.928264 | Z3: -1.022048 | AA3: 228.15556
B4: CLSK | C4: United States | D4: Capital Markets | E4: Mar'26 | F4: 543.5 | G4: 15.59 | H4: 1.88 | I4: -15.32 | J4: -28.36 | K4: -28.88 | L4: -14.78 | M4: -15.59 | N4: -67.16 | O4: 29.19 | P4: 139.17 | Q4: -59.89 | R4: -167.71 | S4: 209.58 | T4: -140.25 | U4: 246.32 | V4: -411.66 | W4: -312.22 | X4: -2.306397 | Y4: -1.9347318 | Z4: -1.6489793 | AA4: 5.4348505
B5: IIIV | C5: United States | D5: Software - Infrastructure | E5: Mar'26 | F5: 430.3 | G5: 4.17 | H5: 5.33 | I5: 5.52 | J5: 7.03 | K5: 7.28 | L5: 0 | M5: 1.61 | N5: 4.11 | O5: 1.25 | P5: 0 | Q5: -1.31 | R5: 3.56 | S5: 4.08 | T5: 0 | U5: -4.77 | V5: 0.03 | W5: 1.24 | X5: 0 | Y5: -0.54660348 | Z5: -1.2299652 | AA5: 4.3030303
B6: ARWR | C6: United States | D6: Biotechnology | E6: Mar'26 | F6: 205.6 | G6: -63.32 | H6: 41.55 | I6: -72.91 | J6: -83.83 | K6: -42.13 | L6: 48.17 | M6: -102.7 | N6: -108.33 | O6: -136.55 | P6: -126.19 | Q6: -176.14 | R6: -162.2 | S6: -161.41 | T6: 381.2 | U6: -165.55 | V6: 44.11 | W6: 40.81 | X6: -0.81060485 | Y6: -0.089329397 | Z6: -1.9109856 | AA6: 2.0561261
B7: AFRM | C7: United States | D7: Credit Services | E7: Jun'26 | F7: 112.6 | G7: -196.1 | H7: -226.55 | I7: -276.83 | J7: -287.47 | K7: -359.53 | L7: -275.1 | M7: -241.55 | N7: -207.03 | O7: -171.1 | P7: -155.59 | Q7: -71.86 | R7: -132.88 | S7: -4.26 | T7: -8.38 | U7: 57.26 | V7: 63.66 | W7: 117.63 | X7: -0.40376862 | Y7: -0.59398289 | Z7: -2.2268298 | AA7: 1.1256926
B8: POWI | C8: United States | D8: Semiconductors | E8: Dec'25 | F8: 90.8 | G8: 44.3 | H8: 51.05 | I8: 61.3 | J8: 48.37 | K8: 20.89 | L8: 5.76 | M8: 12.64 | N8: 17.71 | O8: -1.05 | P8: 0.47 | Q8: 1.96 | R8: 11.58 | S8: 3.92 | T8: 6.72 | U8: -1.35 | V8: -3.95 | W8: 8.77 | X8: 0.3485778 | Y8: -0.13688999 | Z8: -0.74413033 | AA8: 0.9082397
B9: MCHP | C9: United States | D9: Semiconductors | E9: Sep'26 | F9: 78.7 | G9: 514.1 | H9: 560.4 | I9: 684.4 | J9: 759.4 | K9: 818.1 | L9: 850.1 | M9: 904.8 | N9: 886.8 | O9: 530.5 | P9: 236.6 | Q9: 221.7 | R9: 148.1 | S9: 34.4 | T9: -28.7 | U9: 54.3 | V9: 95.2 | W9: 156.5 | X9: -0.41401373 | Y9: -0.44580559 | Z9: -0.25420471 | AA9: 0.7867268
B10: TPG | C10: United States | D10: Asset Management | E10: Dec'25 | F10: 71.5 | G10: 780.55 | H10: 174.34 | I10: -157.26 | J10: 48.82 | K10: 17.12 | L10: 30.97 | M10: 47.52 | N10: -87.98 | O10: 75.19 | P10: 8.8 | Q10: -10.85 | R10: 10.06 | S10: 1.27 | T10: 111.08 | U10: 76.11 | V10: 224.52 | W10: 296.61 | X10: 11.021552 | Y10: 0.77949086 | Z10: 1.0802942 | AA10: 0.71514359
B11: RDDT | C11: United States | D11: Internet Content & Information | E11: Dec'25 | F11: 68 | G11: 7.19 | H11: -35.2 | I11: -53.07 | J11: -50.95 | K11: -29.68 | L11: -70.6 | M11: -52.99 | N11: -19.59 | O11: 3.02 | P11: -589.26 | Q11: -31.04 | R11: 6.85 | S11: 52.87 | T11: 3.9 | U11: 67.71 | V11: 138.54 | W11: 231.83 | X11: -1.0581184 | Y11: 3.0310006 | Z11: 1.0027412 | AA11: 0.68040453
B12: RAMP | C12: United States | D12: Software - Infrastructure | E12: Sep'26 | F12: 62.3 | G12: -13.79 | H12: -27.99 | I12: -24.86 | J12: -14.69 | K12: -12.21 | L12: -28.43 | M12: 2.39 | N12: 14.78 | O12: 17.7 | P12: -9.87 | Q12: -5.04 | R12: 7.88 | S12: 14.82 | T12: -4.27 | U12: 7.64 | V12: 21.43 | W12: 39.52 | X12: 0.71887035 | Y12: 0.94697535 | Z12: 0.51975451 | AA12: 0.62342251
B13: USAR | C13: United States | D13: Other Industrial Metals & Mining | E13: Sep'25 | F13: 54.7 | M13: -7.01 | N13: -7.01 | O13: -4.83 | P13: -5.95 | Q13: -4.7 | R13: -3.01 | S13: -1.96 | T13: -5.92 | U13: -8.72 | V13: -8.8 | W13: -15.86 | X13: -0.0019206146 | Y13: 0.2578576 | Z13: 0.29525752 | AA13: 0.54724409
B14: ILMN | C14: United States | D14: Diagnostics & Research | E14: Dec'25 | F14: 44.8 | G14: -37 | H14: 135 | I14: 30 | J14: 27 | K14: -81 | L14: -65 | M14: -26 | N14: 124 | O14: -98 | P14: -59 | Q14: -18 | R14: 210 | S14: -53 | T14: 184 | U14: 224 | V14: 232 | W14: 210 | X14: 3.0375 | Y14: 0.74922601 | Z14: 0.038938053 | AA14: 0.44804089
B15: ABX | C15: United States | D15: Insurance - Life | E15: Sep'25 | F15: 40.5 | G15: 0.1 | H15: -0.04 | I15: 7.19 | J15: 6.71 | K15: 9.68 | L15: 11.23 | M15: 8.36 | N15: 9.14 | O15: 4.52 | P15: 3.16 | Q15: 3.8 | R15: 7.48 | S15: 6.56 | T15: -7.59 | U15: 17.39 | V15: 22.79 | W15: 22.41 | X15: -0.51190476 | Y15: 1.3258537 | Z15: 0.64219799 | AA15: 0.40485313
B16: PTON | C16: United States | D16: Leisure | E16: Jun'26 | F16: 39 | G16: -390.9 | H16: -326.7 | I16: -474.3 | J16: -197.4 | K16: -231.6 | L16: -129.9 | M16: -175.8 | N16: -87 | O16: -167 | P16: -87.4 | Q16: -55 | R16: 43.9 | S16: -25.9 | T16: 0.5 | U16: 66.7 | V16: 54 | W16: 11.3 | X16: -0.70659164 | Y16: -3.3342466 | Z16: 0.1185446 | AA16: 0.39034627
B17: GOLD | C17: United States | D17: Capital Markets | E17: Jun'26 | F17: 24.4 | G17: 38.96 | H17: 44.88 | I17: 44.19 | J17: 55.71 | K17: 39.96 | L17: 48.36 | M17: 53.13 | N17: 24.82 | O17: 21.32 | P17: 11.26 | Q17: 17.78 | R17: 12.02 | S17: 15.06 | T17: 7.27 | U17: 19.17 | V17: 3.09 | W17: 25.95 | X17: -0.071097648 | Y17: 0.026664109 | Z17: -0.16685351 | AA17: 0.24422516
B18: AOSL | C18: United States | D18: Semiconductors | E18: Jun'26 | F18: 23.4 | G18: 27.72 | H18: 31.23 | I18: 18.14 | J18: 25.53 | K18: 8.79 | L18: -14.4 | M18: 2.61 | N18: 9.38 | O18: -1.13 | P18: -10.5 | Q18: -1.5 | R18: -0.25 | S18: -5.91 | T18: -10.66 | U18: -11.62 | V18: -4.58 | W18: -13.57 | X18: 0.0088105727 | Y18: 0.55240175 | Z18: 0.15225035 | AA18: 0.23375038
B19: MTSI | C19: United States | D19: Semiconductors | E19: Mar'26 | F19: 20.1 | G19: 27.07 | H19: 32.57 | I19: 36 | J19: 37.53 | K19: 39.38 | L19: 38.7 | M19: 19.51 | N19: 20.61 | O19: 18.11 | P19: 15.71 | Q19: 19.72 | R19: 27.83 | S19: 17.53 | T19: 34.87 | U19: 37.66 | V19: 39.7 | W19: 43.58 | X19: 0.23715806 | Y19: 0.17948974 | Z19: 0.10068708 | AA19: 0.20075524
B20: CTLP | C20: United States | D20: Software - Infrastructure | E20: Mar'26 | F20: 19.4 | G20: -1.14 | H20: -0.32 | I20: 0.88 | J20: -2.08 | K20: -8.22 | L20: 1.87 | M20: 6.74 | N20: 3.81 | O20: 2.83 | P20: 3.68 | Q20: 5.2 | R20: 2.16 | S20: 4.3 | T20: 6.21 | U20: 6.37 | V20: 6.47 | W20: 8.83 | X20: 0.16492829 | Y20: 0.06547286 | Z20: 0.22636555 | AA20: 0.19400428
B21: MAGN | C21: United States | D21: Household & Personal Products | E21: Mar'26 | F21: 19.3 | N21: 17 | O21: -2 | P21: 25 | Q21: 17 | R21: 35 | S21: 10 | T21: 27 | U21: 13 | V21: 85 | W21: 36 | X21: 0.022988506 | Y21: -0.04494382 | Z21: 0.58823529 | AA21: 0.19259259
B22: RGA | C22: United States | D22: Insurance - Reinsurance | E22: Dec'25 | F22: 18.5 | G22: 59 | H22: 310 | I22: 191 | J22: -28 | K22: 436 | L22: 404 | M22: 328 | N22: 452 | O22: 233 | P22: 340 | Q22: 341 | R22: 292 | S22: 311 | T22: 449 | U22: 431 | V22: 418 | W22: 608 | X22: 0.084890966 | Y22: 0.064608758 | Z22: 0.084962913 | AA22: 0.1845867
B23: COUR | C23: United States | D23: Education & Training Services | E23: Dec'25 | F23: 16 | G23: -47.49 | H23: -35.28 | I23: -42.14 | J23: -33.65 | K23: -45.88 | L23: -44.74 | M23: -38.52 | N23: -39.58 | O23: -25.5 | P23: -27.7 | Q23: -31.2 | R23: -21.7 | S23: -21.48 | T23: -15.3 | U23: -15.1 | V23: -15.6 | W23: -32.3 | X23: -0.12147335 | Y23: -0.17952721 | Z23: -0.082902963 | AA23: 0.16034381
B24: KKR | C24: United States | D24: Asset Management | E24: Dec'25 | F24: 15.6 | G24: 1027 | H24: 1289 | I24: -1917 | J24: 206.19 | K24: 129.15 | L24: 408.44 | M24: 1451 | N24: 2819 | O24: 1876 | P24: 1363 | Q24: 1210 | R24: 1645 | S24: 1643 | T24: 771.07 | U24: 1529 | V24: 2200 | W24: 2600 | X24: -0.10099471 | Y24: 0.060541993 | Z24: 0.099318727 | AA24: 0.1557853
B25: PI | C25: United States | D25: Semiconductors | E25: Dec'25 | F25: 13.8 | G25: -7.23 | H25: -9.32 | I25: -8.48 | J25: -1.74 | K25: -0.05 | L25: -4.44 | M25: -8.37 | N25: -15.83 | O25: -11.57 | P25: -9.01 | Q25: 9.05 | R25: -0.77 | S25: -2.61 | T25: -9.57 | U25: 10.87 | V25: 0.66 | W25: -2.7 | X25: 0.16766467 | Y25: -0.46666667 | Z25: -0.6875 | AA25: 0.13846154
B26: EVO | C26: United States | D26: Drug Manufacturers - Specialty & Generic | E26: Sep'25 | F26: 13.6 | G26: 17.74 | H26: 12.49 | I26: 0.46 | J26: -3.77 | K26: -13.53 | L26: 37.69 | M26: 12.52 | N26: -31.17 | O26: -12.18 | P26: 19.94 | Q26: -18.21 | R26: -36.15 | S26: -32.69 | T26: 1.17 | U26: -19.82 | V26: -28.6 | W26: -43.59 | X26: 0.27969006 | Y26: 0.018747089 | Z26: -0.086295577 | AA26: 0.13635226
B27: MMS | C27: United States | D27: Specialty Business Services | E27: Mar'26 | F27: 12.2 | G27: 81.53 | H27: 75.29 | I27: 54.56 | J27: 103.81 | K27: 74.78 | L27: 62.51 | M27: 58.39 | N27: 128.42 | O27: 107.51 | P27: 127.49 | Q27: 141.74 | R27: 110.74 | S27: 86.79 | T27: 152.97 | U27: 165.67 | V27: 83.52 | W27: 146.21 | X27: 0.054589082 | Y27: 0.048614497 | Z27: -0.052734564 | AA27: 0.12152572
B28: RBLX | C28: United States | D28: Electronic Gaming & Multimedia | E28: Dec'25 | F28: 12 | G28: -139.65 | H28: -151.61 | I28: -170.27 | J28: -300.01 | K28: -301.9 | L28: -289.84 | M28: -313.99 | N28: -300.04 | O28: -355.18 | P28: -302.33 | Q28: -237.95 | R28: -261.03 | S28: -226.21 | T28: -254.71 | U28: -322.46 | V28: -296.54 | W28: -358.64 | X28: -0.046344597 | Y28: 0.086243494 | Z28: 0.033361205 | AA28: 0.12039967
B29: EL | C29: United States | D29: Household & Personal Products | E29: Jun'26 | F29: 11.7 | G29: 1434 | H29: 978 | I29: 117 | J29: 661 | K29: 773 | L29: 316 | M29: 31 | N29: 101 | O29: 584 | P29: 553 | Q29: 340 | R29: 133 | S29: 461 | T29: 399 | U29: 109 | V29: 253 | W29: 604 | X29: -0.10356422 | Y29: -0.17329332 | Z29: 0.10889292 | AA29: 0.11702128
B30: TPR | C30: United States | D30: Luxury Goods | E30: Jun'26 | F30: 11.6 | G30: 476.1 | H30: 175.8 | I30: 259.6 | J30: 254.3 | K30: 418.2 | L30: 226.3 | M30: 280.8 | N30: 272.8 | O30: 475.9 | P30: 239.3 | Q30: 268.3 | R30: 285.4 | S30: 548.2 | T30: 272.3 | U30: 302.4 | V30: 361.6 | W30: 719.8 | X30: 0.024604831 | Y30: 0.024814437 | Z30: 0.05410779 | AA30: 0.11559448
B31: ARX | C31: United States | D31: Insurance Brokers | E31: Sep'25 | F31: 10.9 | O31: 2.1 | P31: 7.2 | Q31: 5.7 | R31: -10.8 | S31: -5.3 | T31: 18.3 | U31: 8.3 | V31: 29 | W31: 0.2 | X31: -3.46875 | Y31: 0.32911392 | Z31: 3.7904762 | AA31: 0.10934394
B32: LSPD | C32: United States | D32: Software - Application | E32: Sep'26 | F32: 10.5 | G32: -58.32 | H32: -91.39 | I32: -83.05 | J32: -72.39 | K32: -68.68 | L32: -48.73 | M32: -53.94 | N32: -50.19 | O32: -47.21 | P32: -30.81 | Q32: -27.71 | R32: -31.41 | S32: -22.2 | T32: -22.56 | U32: -35.6 | V32: -33.76 | W32: -34.2 | X32: -0.073575314 | Y32: 0.075953023 | Z32: 0.02102532 | AA32: 0.10515247
B33: AGCO | C33: United States | D33: Farm & Heavy Construction Machinery | E33: Dec'25 | F33: 10.3 | G33: 270.3 | H33: 241 | I33: 262 | J33: 331.4 | K33: 465.8 | L33: 386 | M33: 499.7 | N33: 421.5 | O33: 413.5 | P33: 272.3 | Q33: 286 | R33: 126.3 | S33: 212.5 | T33: 60.2 | U33: 195.5 | V33: 156.2 | W33: 276.8 | X33: -0.23642849 | Y33: -0.13211679 | Z33: 0.050294365 | AA33: 0.10297886
B34: ROAD | C34: United States | D34: Engineering & Construction | E34: Mar'26 | F34: 10.2 | G34: 8.02 | H34: -11.53 | I34: 18.12 | J34: 18.85 | K34: 0.77 | L34: -3.26 | M34: 32.3 | N34: 49.78 | O34: 16.43 | P34: 5.47 | Q34: 45.51 | R34: 58.03 | S34: 32.31 | T34: 26.55 | U34: 80.78 | V34: 132.35 | W34: 60 | X34: 0.14916502 | Y34: 0.2171798 | Z34: 0.37598017 | AA34: 0.10180521
B35: KN | C35: United States | D35: Electronic Components | E35: Sep'25 | F35: 9.5 | G35: 38.4 | H35: 42.5 | I35: 27.7 | J35: 25.6 | K35: 16 | L35: 30.1 | M35: -0.1 | N35: 0 | O35: 13 | P35: 0 | Q35: 10.7 | R35: 14 | S35: 20.2 | T35: 18.4 | U35: 7.7 | V35: 18 | W35: 26.3 | X35: 0.40979955 | Y35: -0.047393365 | Z35: 0.066334992 | AA35: 0.094867807
B36: FLS | C36: United States | D36: Specialty Industrial Machinery | E36: Dec'25 | F36: 9.2 | G36: 79.53 | H36: 5.81 | I36: 58.45 | J36: 28.94 | K36: 129.02 | L36: 76.44 | M36: 111.83 | N36: 102.02 | O36: 110.85 | P36: 116.12 | Q36: 138.42 | R36: 123.3 | S36: 125.95 | T36: 134.77 | U36: 137.29 | V36: 159.69 | W36: 177.37 | X36: 0.037019393 | Y36: -0.0021629278 | Z36: 0.069804915 | AA36: 0.092200108
B37: CAH | C37: United States | D37: Medical Distribution | E37: Jun'26 | F37: 9 | G37: 386 | H37: 466 | I37: 363 | J37: 346 | K37: 401 | L37: 532 | M37: 510 | N37: 493 | O37: 523 | P37: 586 | Q37: 548 | R37: 551 | S37: 566 | T37: 731 | U37: 629 | V37: 771 | W37: 809 | X37: 0.064415815 | Y37: 0.033806344 | Z37: 0.088817117 | AA37: 0.090100111
B38: XEL | C38: United States | D38: Utilities - Regulated Electric | E38: Dec'25 | F38: 9 | G38: 434 | H38: 518 | I38: 478 | J38: 931 | K38: 533 | L38: 578 | M38: 423 | N38: 954 | O38: 655 | P38: 684 | Q38: 455 | R38: 917 | S38: 351 | T38: 681 | U38: 581 | V38: 1042 | W38: 589 | X38: -0.0012463648 | Y38: 0.052412646 | Z38: 0.049407115 | AA38: 0.089642185
B39: HII | C39: United States | D39: Aerospace & Defense | E39: Dec'25 | F39: 8.8 | G39: 155 | H39: 202 | I39: 231 | J39: 189 | K39: 171 | L39: 166 | M39: 189 | N39: 200 | O39: 217 | P39: 186 | Q39: 224 | R39: 114 | S39: 141 | T39: 196 | U39: 202 | V39: 197 | W39: 206 | X39: 0.015037594 | Y39: -0.032592593 | Z39: 0.12710567 | AA39: 0.088315217
B40: WMG | C40: United States | D40: Entertainment | E40: Mar'26 | F40: 8.7 | G40: 239 | H40: 169 | I40: 146 | J40: 166 | K40: 224 | L40: 179 | M40: 203 | N40: 254 | O40: 337 | P40: 219 | Q40: 225 | R40: 244 | S40: 241 | T40: 199 | U40: 261 | V40: 288 | W40: 327 | X40: -0.021528525 | Y40: 0.03960396 | Z40: 0.046560847 | AA40: 0.086956522
B41: ROK | C41: United States | D41: Specialty Industrial Machinery | E41: Mar'26 | F41: 8.4 | G41: 306.1 | H41: 214.3 | I41: 372.6 | J41: 438.5 | K41: 356.8 | L41: 325.5 | M41: 419.5 | N41: 508.8 | O41: 286 | P41: 337 | Q41: 368 | R41: 318 | S41: 246 | T41: 341 | U41: 378 | V41: 457 | W41: 366 | X41: 0.0031520883 | Y41: 0.0078554595 | Z41: 0.10833983 | AA41: 0.084388186
B42: OWL | C42: United States | D42: Asset Management | E42: Dec'25 | F42: 8.3 | G42: 106.31 | H42: 74.85 | I42: 91.09 | J42: 100.62 | K42: 127.47 | L42: 110.2 | M42: 90.08 | N42: 146.82 | O42: 163.74 | P42: 183.39 | Q42: 203.98 | R42: 201.66 | S42: 189.35 | T42: 196.96 | U42: 203.49 | V42: 145.6 | W42: 250.55 | X42: 0.017433644 | Y42: -0.00061872593 | Z42: -0.070831122 | AA42: 0.083220016
B43: RL | C43: United States | D43: Apparel Manufacturing | E43: Sep'26 | F43: 7.6 | G43: 287.8 | H43: 37.6 | I43: 189.9 | J43: 211.4 | K43: 286.9 | L43: 57.6 | M43: 195 | N43: 171.7 | O43: 312.8 | P43: 120.9 | Q43: 210.8 | R43: 197.3 | S43: 387.2 | T43: 150.2 | U43: 279.4 | V43: 283 | W43: 471.3 | X43: 0.031979917 | Y43: 0.072554204 | Z43: 0.084508431 | AA43: 0.076468449
... B141: MBUU | C141: United States | D141: Recreational Vehicles | E141: Jun'26 | F141: -30.8 | G141: 41.86 | H141: 73.18 | I141: 63.06 | J141: 48.48 | K141: 48.68 | L141: 71.9 | M141: 77.14 | N141: 29.48 | O141: 15 | P141: 15.99 | Q141: -19.55 | R141: -1.11 | S141: 5.21 | T141: 19.82 | U141: 2.95 | V141: 0.34 | W141: -3.5 | X141: 7.0925926 | Y141: 5.1487414 | Z141: 0.053963528 | AA141: -0.3075565
B142: LBRX | C142: United States | D142: Biotechnology | E142: Sep'25 | F142: -40.1 | Q142: -0.98 | R142: -16.63 | S142: -26.58 | T142: -16.08 | U142: -5.29 | V142: -5.29 | W142: -5.25 | Y142: 0.071511531 | Z142: -0.17559616 | AA142: -0.40063862
B143: MOH | C143: United States | D143: Healthcare Plans | E143: Dec'25 | F143: -40.8 | G143: 212 | H143: 372 | I143: 361 | J143: 335 | K143: 317 | L143: 455 | M143: 443 | N143: 359 | O143: 357 | P143: 426 | Q143: 434 | R143: 467 | S143: 378 | T143: 435 | U143: 373 | V143: 137 | W143: -162 | X143: 0.0052785924 | Y143: -0.035589265 | Z143: -0.19963702 | AA143: -0.40816327
B144: SYNA | C144: United States | D144: Semiconductors | E144: Jun'26 | F144: -42.3 | G144: 82.7 | H144: 99.4 | I144: 124.6 | J144: 112 | K144: 46.1 | L144: 34.2 | M144: -38 | N144: -27.2 | O144: -16.6 | P144: -17.6 | Q144: -13.7 | R144: -14.2 | S144: -14.4 | T144: -12 | U144: -22.8 | V144: -20.7 | W144: 15.2 | X144: -0.093489149 | Y144: 0.16758748 | Z144: 0.10252366 | AA144: -0.42346209
B145: RBBN | C145: United States | D145: Software - Application | E145: Dec'25 | F145: -43.4 | G145: 0.4 | H145: -32.39 | I145: -2.81 | J145: -1.04 | K145: 5.04 | L145: -26.61 | M145: -1.82 | N145: 4.38 | O145: 20.45 | P145: -10.42 | Q145: -0.02 | R145: 2.87 | S145: 34.6 | T145: -14.27 | U145: 9.47 | V145: 6.71 | W145: 18.76 | X145: -0.14243433 | Y145: 0.40940466 | Z145: 0.11753903 | AA145: -0.43385374
B146: BTU | C146: United States | D146: Thermal Coal | E146: Dec'25 | F146: -48.4 | G146: 461.7 | H146: -106.4 | I146: 400.3 | J146: 402.9 | K146: 587.5 | L146: 412.6 | M146: 265 | N146: 162.7 | O146: 259.4 | P146: 63 | Q146: 128.5 | R146: 134.1 | S146: 44.2 | T146: 44.9 | U146: -22.6 | V146: -18.6 | W146: 21 | X146: -0.048945376 | Y146: -0.42962752 | Z146: -0.76121635 | AA146: -0.48434238
B147: UDMY | C147: United States | D147: Education & Training Services | E147: Dec'25 | F147: -51.7 | G147: -40.95 | H147: -25.32 | I147: -28.53 | J147: -43.25 | K147: -54.1 | L147: -37.15 | M147: -27.33 | N147: -21.5 | O147: -25.66 | P147: -22.73 | Q147: -25.55 | R147: -18.18 | S147: -6.18 | T147: -3.02 | U147: 4.04 | V147: -0.16 | W147: -3.43 | X147: -0.27133811 | Y147: -0.55904024 | Z147: -0.77206512 | AA147: -0.51691729
B148: OMCL | C148: United States | D148: Health Information Services | E148: Dec'25 | F148: -72.1 | G148: 18.59 | H148: 10.36 | I148: 17.19 | J148: 21.56 | K148: -32.88 | L148: -9.83 | M148: 8.47 | N148: 4.43 | O148: -11.1 | P148: -18.68 | Q148: 3.22 | R148: 7.18 | S148: 13.77 | T148: -11.62 | U148: 8.12 | V148: 8.24 | W148: 0.42 | X148: 1.2859745 | Y148: 0.39043825 | Z148: 0.060744986 | AA148: -0.72123177
B149: AB | C149: United States | D149: Asset Management | E149: Dec'25 | F149: -164.8 | G149: 0 | H149: 0 | I149: 0 | J149: 0 | K149: 0 | L149: 0 | M149: 0 | N149: 65.76 | O149: -211.26 | P149: 0 | Q149: 0 | R149: 136.37 | S149: -345.36 | T149: 0 | U149: 0 | V149: 81.41 | W149: 89.76 | X149: 0 | Y149: 0 | Z149: 0.26297909 | AA149: -1.648494
B150: MSGS | C150: United States | D150: Entertainment | E150: Jun'26 | F150: -194.6 | G150: 35.86 | H150: 61.33 | I150: 23.64 | J150: -35.96 | K150: 51.45 | L150: 81.69 | M150: -12.29 | N150: -14.9 | O150: 28.74 | P150: 79.66 | Q150: 52.23 | R150: -8.27 | S150: 13.23 | T150: 32.26 | U150: -22.66 | V150: -27.43 | W150: 22.18 | X150: -0.34636463 | Y150: -0.8372275 | Z150: -1.3159341 | AA150: -1.9456522
B151: MOFG | C151: United States | D151: Banks - Regional | E151: Sep'25 | F151: -197.2 | G151: 20.82 | H151: 18.98 | I151: 17.34 | J151: 16.71 | K151: 23.06 | L151: 19.49 | M151: 1.78 | N151: 9.19 | O151: 11.34 | P151: 2.52 | Q151: 4.23 | R151: 20.87 | S151: -130.2 | T151: 21.11 | U151: 19.6 | V151: 12.58 | W151: 21.49 | X151: -0.18122441 | Y151: -0.18299798 | Z151: 0.12081026 | AA151: -1.9723053
B152: X | C152: United States | D152: N/A | E152: Mar'25 | F152: -207 | G152: 300 | H152: 999 | I152: 2285 | J152: 1081 | K152: 1082 | L152: 1159 | M152: 543 | N152: 127 | O152: 202 | P152: 526 | Q152: 226 | R152: -270 | S152: 140 | T152: 136 | U152: 31 | V152: -179 | W152: -125 | X152: -0.62700965 | Y152: -0.84051724 | Z152: 2.4594595 | AA152: -2.0703125
B153: MSTR | C153: United States | D153: Software - Application | E153: Dec'25 | F153: -231.6 | G153: -137.47 | H153: -169.96 | I153: -918.12 | J153: 6.06 | K153: -193.72 | L153: -20.31 | M153: -25.51 | N153: -25.25 | O153: -42.79 | P153: -203.7 | Q153: -200.27 | R153: -432.58 | S153: -1018 | T153: -5921 | U153: 14032 | V153: -0.01 | W153: -17446 | X153: 3.0828503 | Y153: -1.8796292 | Z153: 0.064946355 | AA153: -2.3160895
B154: BLSH | C154: United States | D154: Software - Infrastructure | E154: Dec'25 | F154: -10675.3 | L154: -50.26 | M154: -50.26 | N154: -587.54 | O154: -587.54 | P154: 153.87 | Q154: -106.81 | R154: -25.8 | S154: 175.58 | T154: -262.19 | U154: 55.69 | V154: 36.95 | W154: -468.14 | X154: -2.1136964 | Y154: -0.74126448 | Z154: -1.1063117 | AA154: -106.7529
B155: EAST | C155: Sweden | D155: =VLOOKUP(B155,기업리스트!$B:$G,2,FALSE) -> Eastnine AB (publ) | E155: Dec'25 | F155: 5.1 | G155: 3.61 | H155: 4.48 | I155: 5.48 | J155: 6.64 | K155: 6.66 | L155: 7.47 | M155: 7.54 | N155: 7.63 | O155: 7.31 | P155: 7.16 | Q155: 7.7 | R155: 8.87 | S155: 10.49 | T155: 13.45 | U155: 13.01 | V155: 13.44 | W155: 13.05 | X155: 0.18381064 | Y155: 0.13107875 | Z155: 0.099738106 | AA155: 0.050803731
B156: FABG | C156: Sweden | D156: =VLOOKUP(B156,기업리스트!$B:$G,2,FALSE) -> Fabege AB (publ) | E156: Dec'25 | F156: 1.4 | G156: 548 | H156: 508 | I156: 484 | J156: 567 | K156: 505 | L156: 572 | M156: 590 | N156: 675 | O156: 588 | P156: 569 | Q156: 576 | R156: 595 | S156: 641 | T156: 527 | U156: 612 | V156: 629 | W156: 674 | X156: -0.017639647 | Y156: 0.015391193 | Z156: 0.014315789 | AA156: 0.01369863
B157: MYCR | C157: Sweden | D157: =VLOOKUP(B157,기업리스트!$B:$G,2,FALSE) -> Mycronic AB (publ) | E157: Dec'25 | F157: -6.6 | G157: 181 | H157: 206 | I157: 223 | J157: 203 | K157: 227 | L157: 181 | M157: 171 | N157: 263 | O157: 635 | P157: 599 | Q157: 349 | R157: 547 | S157: 522 | T157: 776 | U157: 569 | V157: 255 | W157: 382 | X157: 0.08775409 | Y157: 0.10027347 | Z157: -0.12096106 | AA157: -0.065975495
B158: AFRY | C158: Sweden | D158: =VLOOKUP(B158,기업리스트!$B:$G,2,FALSE) -> Afry AB | E158: Dec'25 | F158: -9 | G158: 462 | H158: 357 | I158: 430 | J158: 373 | K158: 522 | L158: 690 | M158: 398 | N158: 310 | O158: 548 | P158: 582 | Q158: 573 | R158: 364 | S158: 573 | T158: 459 | U158: 346 | V158: 331 | W158: 419 | X158: -0.058795411 | Y158: -0.11528695 | Z158: -0.018943743 | AA158: -0.090111176
B159: HTRO | C159: Sweden | D159: =VLOOKUP(B159,기업리스트!$B:$G,2,FALSE) -> Hexatronic Group AB (publ) | E159: Dec'25 | F159: -34.3 | G159: 107.8 | H159: 172 | I159: 265 | J159: 302 | K159: 283 | L159: 340 | M159: 377 | N159: 266 | O159: 132 | P159: 139 | Q159: 191 | R159: 199 | S159: 130 | T159: 154 | U159: 142 | V159: -82 | W159: 12 | X159: 0.02276176 | Y159: -0.072700297 | Z159: -0.4496 | AA159: -0.34302326
B160: 6723 | C160: Japan | D160: =VLOOKUP(B160,기업리스트!$B:$G,2,FALSE) -> Renesas Electronics Corporation | E160: Dec'25 | F160: 30.4 | G160: 110207 | H160: 99823 | I160: 110182 | J160: 117937 | K160: 99250 | L160: 123265 | M160: 97257 | N160: 98006 | O160: 52775 | P160: 77836 | Q160: 69729 | R160: 58118 | S160: 29431 | T160: 35258 | U160: 26043 | V160: 68905 | W160: 78028 | X160: -0.18109513 | Y160: -0.22689783 | Z160: 0.072468928 | AA160: 0.30442191
B161: 7287 | C161: Japan | D161: =VLOOKUP(B161,기업리스트!$B:$G,2,FALSE) -> Nippon Seiki Co., Ltd. | E161: Jun'26 | F161: 28.3 | G161: -2014 | H161: -1954 | I161: 2675 | J161: -3297 | K161: 3047 | L161: 1804 | M161: 1254 | N161: 2307 | O161: 2486 | P161: 1849 | Q161: 3598 | R161: 2182 | S161: 1265 | T161: 2179 | U161: 3725 | V161: 1522 | W161: 3727 | X161: 0.037103665 | Y161: 0.01376843 | Z161: -0.070580687 | AA161: 0.28328156
B162: 7752 | C162: Japan | D162: =VLOOKUP(B162,기업리스트!$B:$G,2,FALSE) -> Ricoh Company, Ltd. | E162: Jun'26 | F162: 23.5 | G162: 7434 | H162: 12609 | I162: -497 | J162: 9814 | K162: 13822 | L162: 16160 | M162: 25519 | N162: 10171 | O162: 9390 | P162: 17597 | Q162: 24473 | R162: 6332 | S162: 477 | T162: 27747 | U162: 53955 | V162: 12642 | W162: 22806 | X162: 0.20765564 | Y162: 0.49944942 | Z162: 0.071290574 | AA162: 0.23548581
B163: 3636 | C163: Japan | D163: =VLOOKUP(B163,기업리스트!$B:$G,2,FALSE) -> Mitsubishi Research Institute, Inc. | E163: Dec'25 | F163: 20.7 | G163: 213 | H163: 1836 | I163: 7479 | J163: 22 | K163: -171 | L163: 2359 | M163: 6934 | N163: -906 | O163: 302 | P163: 2037 | Q163: 6565 | R163: -1542 | S163: 2 | T163: 1480 | U163: 5340 | V163: -186 | W163: 1378 | X163: -0.078872841 | Y163: -0.18831668 | Z163: 0.25681818 | AA163: 0.20735383
B164: 8934 | C164: Japan | D164: =VLOOKUP(B164,기업리스트!$B:$G,2,FALSE) -> Sun Frontier Fudousan Co., Ltd. | E164: Jun'26 | F164: 17.3 | G164: 2060 | H164: 2750 | I164: -24 | J164: 6669 | K164: 1377 | L164: 6651 | M164: 209 | N164: 4207 | O164: 7816 | P164: 2140 | Q164: 3439 | R164: 2835 | S164: 3869 | T164: 5267 | U164: 9309 | V164: 6022 | W164: 8109 | X164: 0.2545795 | Y164: 0.38092148 | Z164: 0.14976504 | AA164: 0.17329464
B165: 7250 | C165: Japan | D165: =VLOOKUP(B165,기업리스트!$B:$G,2,FALSE) -> Pacific Industrial Co., Ltd. | E165: Jun'26 | F165: 13.9 | G165: 1664 | H165: 2759 | I165: 2973 | J165: 1663 | K165: 939 | L165: 3089 | M165: 3608 | N165: 3149 | O165: 4346 | P165: 3746 | Q165: 3215 | R165: 2452 | S165: 2123 | T165: 4174 | U165: 4600 | V165: 4366 | W165: 4248 | X165: 0.037101248 | Y165: 0.11576396 | Z165: 0.14338153 | AA165: 0.13922558
B166: 7186 | C166: Japan | D166: =VLOOKUP(B166,기업리스트!$B:$G,2,FALSE) -> Yokohama Financial Group, Inc. | E166: Sep'26 | F166: 12.6 | G166: 21370 | H166: 6214 | I166: 24781 | J166: 17421 | K166: 23594 | L166: 14735 | M166: 22099 | N166: 25439 | O166: 23373 | P166: 20479 | Q166: 32351 | R166: 31283 | S166: 26514 | T166: 28768 | U166: 38108 | V166: 41091 | W166: 43457 | X166: 0.074927459 | Y166: 0.048412325 | Z166: 0.0786698 | AA166: 0.12598806
B167: 6486 | C167: Japan | D167: =VLOOKUP(B167,기업리스트!$B:$G,2,FALSE) -> Eagle Industry Co.,Ltd. | E167: Jun'26 | F167: 10.3 | G167: 1411 | H167: 1319 | I167: 2320 | J167: 1946 | K167: 1817 | L167: 3750 | M167: 1752 | N167: 1497 | O167: 1588 | P167: 2867 | Q167: 2156 | R167: 2625 | S167: 1640 | T167: 2065 | U167: 2164 | V167: 2999 | W167: 2549 | X167: -0.086347976 | Y167: 0.0009427292 | Z167: 0.044031081 | AA167: 0.10250338
B168: 3110 | C168: Japan | D168: =VLOOKUP(B168,기업리스트!$B:$G,2,FALSE) -> Nitto Boseki Co., Ltd. | E168: Jun'26 | F168: 10.2 | G168: 2238 | H168: 1724 | I168: 1612 | J168: 2614 | K168: 1983 | L168: 1250 | M168: -967 | N168: 886 | O168: 2234 | P168: 2585 | Q168: 2684 | R168: 3908 | S168: 3438 | T168: 4466 | U168: 4633 | V168: 4299 | W168: 5157 | X168: 0.1491082 | Y168: 0.13445088 | Z168: 0.023776224 | AA168: 0.10210264
B169: 9404 | C169: Japan | D169: =VLOOKUP(B169,기업리스트!$B:$G,2,FALSE) -> Nippon Television Holdings, Inc. | E169: Jun'26 | F169: 9.9 | G169: 10933 | H169: 20494 | I169: 13846 | J169: 11729 | K169: 7646 | L169: 16116 | M169: 11103 | N169: 10344 | O169: 6453 | P169: 14266 | Q169: 10815 | R169: 11439 | S169: 9703 | T169: 16284 | U169: 17491 | V169: 17476 | W169: 15735 | X169: 0.043657919 | Y169: 0.13838851 | Z169: 0.10992953 | AA169: 0.098959871
B170: 4534 | C170: Japan | D170: =VLOOKUP(B170,기업리스트!$B:$G,2,FALSE) -> Mochida Pharmaceutical Co., Ltd. | E170: Jun'26 | F170: 9.3 | G170: 2949 | H170: 6913 | I170: 1346 | J170: 4266 | K170: 1014 | L170: 5077 | M170: -1849 | N170: 2516 | O170: 1436 | P170: 1840 | Q170: 11 | R170: 2190 | S170: 1603 | T170: 3451 | U170: 883 | V170: 2573 | W170: 2395 | X170: 0.28543586 | Y170: 0.12019297 | Z170: 0.047126861 | AA170: 0.09306698
B171: 2317 | C171: Japan | D171: =VLOOKUP(B171,기업리스트!$B:$G,2,FALSE) -> Systena Corporation | E171: Jun'26 | F171: 8.9 | G171: 2064 | H171: 2473 | I171: 2400 | J171: 1822 | K171: 2613 | L171: 2579 | M171: 2831 | N171: 1910 | O171: 2458 | P171: 2658 | Q171: 2688 | R171: 2644 | S171: 2930 | T171: 3141 | U171: 3354 | V171: 3516 | W171: 4078 | X171: 0.044230769 | Y171: 0.058405683 | Z171: 0.072251222 | AA171: 0.088710301
B172: 7088 | C172: Japan | D172: =VLOOKUP(B172,기업리스트!$B:$G,2,FALSE) -> Forum Engineering Inc. | E172: Jun'26 | F172: 8.3 | N172: 659 | O172: 619 | P172: 1145 | Q172: 607 | R172: 1142 | S172: 887 | T172: 1389 | U172: 784 | V172: 1186 | W172: 1241 | X172: 0.064533192 | Y172: 0.043975155 | Z172: 0.010471204 | AA172: 0.083372586
B173: 8111 | C173: Japan | D173: =VLOOKUP(B173,기업리스트!$B:$G,2,FALSE) -> Goldwin Inc. | E173: Jun'26 | F173: 6.8 | G173: 2164 | H173: 10858 | I173: 2345 | J173: 2268 | K173: 3010 | L173: 13004 | M173: 3624 | N173: 2264 | O173: 3807 | P173: 13118 | Q173: 4658 | R173: 1839 | S173: 3375 | T173: 11726 | U173: 4966 | V173: 2080 | W173: 4880 | X173: -0.060548064 | Y173: 0.01426058 | Z173: 0.011001552 | AA173: 0.067955028
B174: 4928 | C174: Japan | D174: =VLOOKUP(B174,기업리스트!$B:$G,2,FALSE) -> Noevir Holdings Co., Ltd. | E174: Dec'25 | F174: 6.5 | G174: 1597 | H174: 2773 | I174: 2456 | J174: 2731 | K174: 2156 | L174: 3330 | M174: 2420 | N174: 3032 | O174: 2242 | P174: 3535 | Q174: 2631 | R174: 2850 | S174: 2408 | T174: 2857 | U174: 2539 | V174: 2297 | W174: 3066 | X174: -0.059348739 | Y174: -0.0085613251 | Z174: -0.051905388 | AA174: 0.065142065
B175: 6370 | C175: Japan | D175: =VLOOKUP(B175,기업리스트!$B:$G,2,FALSE) -> Kurita Water Industries Ltd. | E175: Jun'26 | F175: 6.4 | G175: 8934 | H175: 10790 | I175: 7237 | J175: 6380 | K175: 9969 | L175: 11323 | M175: 9397 | N175: 8132 | O175: 10155 | P175: 12231 | Q175: 10829 | R175: 8639 | S175: 12853 | T175: 13217 | U175: 16113 | V175: 8804 | W175: 16098 | X175: 0.022131442 | Y175: 0.11603496 | Z175: 0.0032466255 | AA175: 0.063643674
B176: 1926 | C176: Japan | D176: =VLOOKUP(B176,기업리스트!$B:$G,2,FALSE) -> Raito Kogyo Co., Ltd. | E176: Jun'26 | F176: 6.3 | G176: 3341 | H176: 3819 | I176: 4058 | J176: 1640 | K176: 3355 | L176: 4311 | M176: 3480 | N176: 1731 | O176: 3532 | P176: 3210 | Q176: 2773 | R176: 2099 | S176: 3404 | T176: 3920 | U176: 3389 | V176: 2666 | W176: 4243 | X176: 0.061814383 | Y176: 0.050508363 | Z176: 0.044255386 | AA176: 0.062710218
B177: 3167 | C177: Japan | D177: =VLOOKUP(B177,기업리스트!$B:$G,2,FALSE) -> TOKAI Holdings Corporation | E177: Jun'26 | F177: 5.5 | G177: 1995 | H177: 4026 | I177: 6545 | J177: 3355 | K177: 899 | L177: 4212 | M177: 6454 | N177: 2485 | O177: 1771 | P177: 4542 | Q177: 6714 | R177: 3320 | S177: 1341 | T177: 5051 | U177: 7130 | V177: 3942 | W177: 2308 | X177: 0.031978388 | Y177: 0.025325703 | Z177: 0.036931481 | AA177: 0.055371049
B178: 6590 | C178: Japan | D178: =VLOOKUP(B178,기업리스트!$B:$G,2,FALSE) -> Shibaura Mechatronics Corporation | E178: Jun'26 | F178: 5.5 | G178: 1189 | H178: 1128 | I178: 2077 | J178: 2122 | K178: 2478 | L178: 3717 | M178: 2590 | N178: 2129 | O178: 2888 | P178: 3088 | Q178: 3583 | R178: 3070 | S178: 2678 | T178: 3550 | U178: 4839 | V178: 4065 | W178: 3508 | X178: 0.037201063 | Y178: 0.097507957 | Z178: 0.070382684 | AA178: 0.054850648
B179: 4483 | C179: Japan | D179: =VLOOKUP(B179,기업리스트!$B:$G,2,FALSE) -> JMDC Inc. | E179: Jun'26 | F179: 5 | G179: 916 | H179: 1677 | I179: 1450 | J179: 1082 | K179: 1126 | L179: 1822 | M179: 1839 | N179: 2547 | O179: 1056 | P179: 2066 | Q179: 855 | R179: 1091 | S179: 2159 | T179: 2564 | U179: 0 | V179: 1553 | W179: 2473 | X179: 0.080700049 | Y179: -0.12820513 | Z179: 0.079463364 | AA179: 0.050031867
B180: 6479 | C180: Japan | D180: =VLOOKUP(B180,기업리스트!$B:$G,2,FALSE) -> MINEBEA MITSUMI Inc. | E180: Sep'26 | F180: 4.9 | G180: 25832 | H180: 21181 | I180: 14255 | J180: 26394 | K180: 26432 | L180: 5420 | M180: 6052 | N180: 21174 | O180: 24027 | P180: 18873 | Q180: 20025 | R180: 28146 | S180: 26423 | T180: 19142 | U180: 17432 | V180: 26955 | W180: 30821 | X180: 0.0028780211 | Y180: -0.027662798 | Z180: -0.013067378 | AA180: 0.048892743
B181: 5411 | C181: Japan | D181: =VLOOKUP(B181,기업리스트!$B:$G,2,FALSE) -> JFE Holdings, Inc. | E181: Jun'26 | F181: 4.3 | G181: 84574 | H181: 94068 | I181: 75240 | J181: 95190 | K181: 68775 | L181: 44351 | M181: 14324 | N181: 67122 | O181: 70607 | P181: 62756 | Q181: 50770 | R181: 41897 | S181: 16550 | T181: 33436 | U181: 18779 | V181: 3266 | W181: 19680 | X181: -0.17049188 | Y181: -0.22425746 | Z181: -0.34909002 | AA181: 0.043453513
B182: 9090 | C182: Japan | D182: =VLOOKUP(B182,기업리스트!$B:$G,2,FALSE) -> AZ-COM MARUWA Holdings Inc. | E182: Jun'26 | F182: 4.3 | G182: 2045 | H182: 2445 | I182: 1870 | J182: 2372 | K182: 2658 | L182: 3535 | M182: 2798 | N182: 3747 | O182: 3571 | P182: 4256 | Q182: 2272 | R182: 1857 | S182: 2471 | T182: 4617 | U182: 2025 | V182: 3078 | W182: 2990 | X182: 0.0332535 | Y182: -0.022020148 | Z182: 0.11130356 | AA182: 0.042572389
B183: 4452 | C183: Japan | D183: =VLOOKUP(B183,기업리스트!$B:$G,2,FALSE) -> Kao Corporation | E183: Dec'25 | F183: 3.3 | G183: 43749 | H183: 22952 | I183: 30709 | J183: 23256 | K183: 36812 | L183: 7287 | M183: 18613 | N183: 24805 | O183: 49505 | P183: 21984 | Q183: 35955 | R183: 43116 | S183: 43959 | T183: 31184 | U183: 38285 | V183: 45398 | W183: 49202 | X183: 0.06344215 | Y183: 0.015108875 | Z183: 0.014577371 | AA183: 0.033010968
B184: 2802 | C184: Japan | D184: =VLOOKUP(B184,기업리스트!$B:$G,2,FALSE) -> Ajinomoto Co., Inc. | E184: Sep'26 | F184: 3.3 | G184: 40469 | H184: 2237 | I184: 39442 | J184: 31381 | K184: 42918 | L184: 16863 | M184: 39847 | N184: 31526 | O184: 43296 | P184: 26444 | Q184: 38489 | R184: 38375 | S184: 50030 | T184: 19977 | U184: 46254 | V184: 31084 | W184: 54857 | X184: -0.042174803 | Y184: 0.052869525 | Z184: -0.047149435 | AA184: 0.032759849
... B199: 4722 | C199: Japan | D199: =VLOOKUP(B199,기업리스트!$B:$G,2,FALSE) -> Future Corporation | E199: Sep'25 | F199: -0.6 | G199: 2798 | H199: 2456 | I199: 3341 | J199: 2875 | K199: 3145 | L199: 2868 | M199: 3173 | N199: 3152 | O199: 4059 | P199: 3317 | Q199: 3418 | R199: 3485 | S199: 4697 | T199: 3068 | U199: 3340 | V199: 3770 | W199: 4604 | X199: -0.016692364 | Y199: -0.0053176984 | Z199: 0.019533927 | AA199: -0.0062521008
B200: 7164 | C200: Japan | D200: =VLOOKUP(B200,기업리스트!$B:$G,2,FALSE) -> ZENKOKU HOSHO Co.,Ltd. | E200: Jun'26 | F200: -0.8 | J200: 7605 | K200: 8262 | L200: 8036 | M200: 18843 | N200: 7813 | O200: 7628 | P200: 7783 | Q200: 15878 | R200: 8421 | S200: 6472 | T200: 8838 | U200: 15964 | V200: 8770 | W200: 6156 | X200: 0.027364216 | Y200: 0.0021712237 | Z200: 0.0087920393 | AA200: -0.0078913195
B201: 4536 | C201: Japan | D201: =VLOOKUP(B201,기업리스트!$B:$G,2,FALSE) -> Santen Pharmaceutical Co., Ltd. | E201: Jun'26 | F201: -0.9 | G201: 9650 | H201: 7575 | I201: 9496 | J201: 8334 | K201: -27354 | L201: 8873 | M201: 45447 | N201: 12750 | O201: 12349 | P201: 11059 | Q201: 16027 | R201: 13156 | S201: 10717 | T201: 11323 | U201: 13099 | V201: 7573 | W201: 10342 | X201: 0.0051806354 | Y201: -0.057161822 | Z201: -0.11560203 | AA201: -0.008779734
B202: 6645 | C202: Japan | D202: =VLOOKUP(B202,기업리스트!$B:$G,2,FALSE) -> OMRON Corporation | E202: Sep'26 | F202: -1 | G202: 21131 | H202: 22458 | I202: 11935 | J202: 29678 | K202: 31241 | L202: 27832 | M202: 14304 | N202: 6347 | O202: 5921 | P202: 7770 | Q202: 6267 | R202: 12959 | S202: 16678 | T202: 18134 | U202: 6376 | V202: 11343 | W202: 16136 | X202: 0.23730366 | Y202: 0.0020170991 | Z202: -0.029844682 | AA202: -0.010317717
B203: 9831 | C203: Japan | D203: =VLOOKUP(B203,기업리스트!$B:$G,2,FALSE) -> Yamada Holdings Co., Ltd. | E203: Jun'26 | F203: -1.4 | G203: 13659 | H203: 22915 | I203: 7703 | J203: 12264 | K203: 7513 | L203: 19552 | M203: 4737 | N203: 11073 | O203: 9294 | P203: 18385 | Q203: 2739 | R203: 14347 | S203: 8881 | T203: 16104 | U203: 3489 | V203: 13393 | W203: 8278 | X203: -0.051429473 | Y203: 0.017827007 | Z203: -0.022278788 | AA203: -0.014402752
B204: 6849 | C204: Japan | D204: =VLOOKUP(B204,기업리스트!$B:$G,2,FALSE) -> Nihon Kohden Corporation | E204: Jun'26 | F204: -4.4 | G204: 10990 | H204: 5902 | I204: 7676 | J204: 1818 | K204: 5400 | L204: 4160 | M204: 9743 | N204: 2206 | O204: 5285 | P204: 3025 | Q204: 9076 | R204: -1248 | S204: 6364 | T204: 5820 | U204: 9778 | V204: 1423 | W204: 5340 | X204: 0.16233955 | Y204: 0.035078953 | Z204: 0.12894661 | AA204: -0.043788753
B205: 8425 | C205: Japan | D205: =VLOOKUP(B205,기업리스트!$B:$G,2,FALSE) -> Mizuho Leasing Company, Limited | E205: Jun'26 | F205: -4.7 | G205: 6894 | H205: 4467 | I205: 148 | J205: 8573 | K205: 8801 | L205: 9344 | M205: 5039 | N205: 7200 | O205: 11663 | P205: 11199 | Q205: 9450 | R205: 9971 | S205: 14206 | T205: 11451 | U205: 13338 | V205: 11641 | W205: 11817 | X205: 0.0056217374 | Y205: 0.086250499 | Z205: 0.034105298 | AA205: -0.047179872
B206: 7269 | C206: Japan | D206: =VLOOKUP(B206,기업리스트!$B:$G,2,FALSE) -> Suzuki Motor Corporation | E206: Jun'26 | F206: -6.9 | G206: 44644 | H206: 47547 | I206: 44801 | J206: 74513 | K206: 89830 | L206: 102636 | M206: 83573 | N206: 99804 | O206: 129658 | P206: 117188 | Q206: 118913 | R206: 157557 | S206: 177393 | T206: 144771 | U206: 159735 | V206: 142136 | W206: 134344 | X206: 0.048302166 | Y206: 0.068191917 | Z206: -0.024115811 | AA206: -0.068984913
B207: 5192 | C207: Japan | D207: =VLOOKUP(B207,기업리스트!$B:$G,2,FALSE) -> Mitsuboshi Belting Ltd. | E207: Jun'26 | F207: -7.7 | G207: 1682 | H207: 2002 | I207: 1640 | J207: 2146 | K207: 2453 | L207: 2682 | M207: 1750 | N207: 2028 | O207: 2110 | P207: 2087 | Q207: 1535 | R207: 1592 | S207: 2957 | T207: 1975 | U207: 2405 | V207: 2395 | W207: 2204 | X207: -0.013707013 | Y207: 0.10795384 | Z207: 0.089931683 | AA207: -0.077373613
B208: 8058 | C208: Japan | D208: =VLOOKUP(B208,기업리스트!$B:$G,2,FALSE) -> Mitsubishi Corporation | E208: Jun'26 | F208: -8.9 | G208: 116388 | H208: 240204 | I208: 288669 | J208: 407653 | K208: 133056 | L208: 205282 | M208: 195363 | N208: 222997 | O208: 117201 | P208: 231096 | Q208: 68651 | R208: 108930 | S208: 58262 | T208: 112339 | U208: -724 | V208: 77980 | W208: 36299 | X208: -0.25433087 | Y208: -0.19924924 | Z208: -0.11100869 | AA208: -0.088611578
B209: 5401 | C209: Japan | D209: =VLOOKUP(B209,기업리스트!$B:$G,2,FALSE) -> Nippon Steel Corporation | E209: Sep'26 | F209: -10.4 | G209: 232986 | H209: 143289 | I209: 293662 | J209: 166696 | K209: 212355 | L209: 87819 | M209: 221450 | N209: 194884 | O209: 170211 | P209: 74632 | Q209: 184871 | R209: 106900 | S209: 161473 | T209: 117904 | U209: 64604 | V209: 137411 | W209: 111608 | X209: 0.081973797 | Y209: -0.21057064 | Z209: 0.06766974 | AA209: -0.10358502
B210: 7240 | C210: Japan | D210: =VLOOKUP(B210,기업리스트!$B:$G,2,FALSE) -> NOK Corporation | E210: Jun'26 | F210: -12.2 | G210: 7986 | H210: 8371 | I210: 8097 | J210: -1395 | K210: 7513 | L210: 8961 | M210: 301 | N210: -1226 | O210: 6089 | P210: 12730 | Q210: 5320 | R210: 5653 | S210: 13432 | T210: 12089 | U210: 6091 | V210: 7003 | W210: 8712 | X210: -0.017261344 | Y210: 0.021126761 | Z210: 0.036227023 | AA210: -0.12223229
B211: 6965 | C211: Japan | D211: =VLOOKUP(B211,기업리스트!$B:$G,2,FALSE) -> Hamamatsu Photonics K.K. | E211: Dec'25 | F211: -15.4 | G211: 10829 | H211: 11186 | I211: 16912 | J211: 13297 | K211: 15589 | L211: 15507 | M211: 16013 | N211: 11437 | O211: 13719 | P211: 11481 | Q211: 8584 | R211: 5238 | S211: 6815 | T211: 4282 | U211: 6497 | V211: 1508 | W211: 3877 | X211: -0.22414223 | Y211: -0.083751354 | Z211: -0.1633672 | AA211: -0.15380588
B212: 8584 | C212: Japan | D212: =VLOOKUP(B212,기업리스트!$B:$G,2,FALSE) -> JACCS Co., Ltd. | E212: Jun'26 | F212: -25.2 | G212: 6594 | H212: 8162 | I212: 4644 | J212: 8942 | K212: 7444 | L212: 9827 | M212: 5466 | N212: 11154 | O212: 7266 | P212: 8718 | Q212: 5989 | R212: 8803 | S212: 7282 | T212: 25137 | U212: -15490 | V212: 13710 | W212: -428 | X212: 0.53322292 | Y212: -0.45495753 | Z212: 0.19069641 | AA212: -0.25164007
...

Sheet 빨간줄
B2: (단위: mil $)
Y3: IIIV | Z3: 6723 | AA3: Renesas Electronics Corporation
B4: 3110 | C4: 6 | D4: 7 | E4: 8 | F4: 9 | G4: 10 | H4: 11 | I4: 12 | J4: 13 | K4: 14 | L4: 15 | M4: 16 | N4: 17 | O4: 18 | P4: 19 | Q4: 20 | R4: 21 | S4: 22 | Y4: ARWR | Z4: 7287 | AA4: Nippon Seiki Co., Ltd.
Y5: AFRM | Z5: 7752 | AA5: Ricoh Company, Ltd.
C6: 4Q21 | D6: 1Q22 | E6: 2Q22 | F6: 3Q22 | G6: 4Q22 | H6: 1Q23 | I6: 2Q23 | J6: 3Q23 | K6: 4Q23 | L6: 1Q24 | M6: 2Q24 | N6: 3Q24 | O6: 4Q24 | P6: 1Q25 | Q6: 2Q25 | R6: 3Q25 | S6: 4Q25 | T6: 1Q26 | U6: 2Q26 | V6: 3Q26 | W6: 4Q26 | Y6: POWI | Z6: 3636 | AA6: Mitsubishi Research Institute, Inc.
B7: Revenue | C7: =VLOOKUP($B$4,Revenue!$B:$W,C4,FALSE) -> 20568 | D7: =VLOOKUP($B$4,Revenue!$B:$W,D4,FALSE) -> 21034 | E7: =VLOOKUP($B$4,Revenue!$B:$W,E4,FALSE) -> 21931 | F7: =VLOOKUP($B$4,Revenue!$B:$W,F4,FALSE) -> 23827 | G7: =VLOOKUP($B$4,Revenue!$B:$W,G4,FALSE) -> 23210 | H7: =VLOOKUP($B$4,Revenue!$B:$W,H4,FALSE) -> 21725 | I7: =VLOOKUP($B$4,Revenue!$B:$W,I4,FALSE) -> 18767 | J7: =VLOOKUP($B$4,Revenue!$B:$W,J4,FALSE) -> 20297 | ... S7: =VLOOKUP($B$4,Revenue!$B:$W,S4,FALSE) -> 29181 | Y7: MCHP | Z7: 8934 | AA7: Sun Frontier Fudousan Co., Ltd.
B8: OP | C8: =VLOOKUP($B$4,'Operating Income'!$B:$W,C4,FALSE) -> 2238 | D8: =VLOOKUP($B$4,'Operating Income'!$B:$W,D4,FALSE) -> 1724 | E8: =VLOOKUP($B$4,'Operating Income'!$B:$W,E4,FALSE) -> 1612 | F8: =VLOOKUP($B$4,'Operating Income'!$B:$W,F4,FALSE) -> 2614 | G8: =VLOOKUP($B$4,'Operating Income'!$B:$W,G4,FALSE) -> 1983 | H8: =VLOOKUP($B$4,'Operating Income'!$B:$W,H4,FALSE) -> 1250 | I8: =VLOOKUP($B$4,'Operating Income'!$B:$W,I4,FALSE) -> -967 | J8: =VLOOKUP($B$4,'Operating Income'!$B:$W,J4,FALSE) -> 886 | ... S8: =VLOOKUP($B$4,'Operating Income'!$B:$W,S4,FALSE) -> 5157 | Y8: TPG | Z8: 7250 | AA8: Pacific Industrial Co., Ltd.
B9: Trailing 4Q OP avg. | C9: =AVERAGE(C8:C8) -> 2238 | D9: =AVERAGE(C8:D8) -> 1981 | E9: =AVERAGE(C8:E8) -> 1858 | F9: =AVERAGE(C8:F8) -> 2047 | G9: =AVERAGE(D8:G8) -> 1983.25 | H9: =AVERAGE(E8:H8) -> 1864.75 | I9: =AVERAGE(F8:I8) -> 1220 | J9: =AVERAGE(G8:J8) -> 788 | K9: =AVERAGE(H8:K8) -> 850.75 | L9: =AVERAGE(I8:L8) -> 1184.5 | M9: =AVERAGE(J8:M8) -> 2097.25 | ... S9: =AVERAGE(P8:S8) -> 4638.75 | Y9: RDDT | Z9: 7186 | AA9: Yokohama Financial Group, Inc.
B10: Trailing 4Q OP sum. | C10: =SUM(C8:C8) -> 2238 | D10: =SUM(C8:D8) -> 3962 | E10: =SUM(C8:E8) -> 5574 | F10: =SUM(C8:F8) -> 8188 | G10: =SUM(D8:G8) -> 7933 | H10: =SUM(E8:H8) -> 7459 | I10: =SUM(F8:I8) -> 4880 | J10: =SUM(G8:J8) -> 3152 | K10: =SUM(H8:K8) -> 3403 | L10: =SUM(I8:L8) -> 4738 | M10: =SUM(J8:M8) -> 8389 | ... S10: =SUM(P8:S8) -> 18555 | Y10: RAMP | Z10: 6486 | AA10: Eagle Industry Co.,Ltd.
B11: Trailing OP Delta | D11: =D9/C9-1 -> -0.11483467 | E11: =E9/D9-1 -> -0.062089854 | F11: =F9/E9-1 -> 0.10172228 | G11: =G9/F9-1 -> -0.031143136 | H11: =H9/G9-1 -> -0.05975041 | I11: =I9/H9-1 -> -0.3457568 | J11: =J9/I9-1 -> -0.35409836 | K11: =K9/J9-1 -> 0.07963198 | ... S11: =S9/R9-1 -> 0.10210264 | Z11: 3110 | AA11: Nitto Boseki Co., Ltd.
B12: opm | C12: =IFERROR(C8/C7,"-") -> 0.1088098 | D12: =IFERROR(D8/D7,"-") -> 0.081962537 | E12: =IFERROR(E8/E7,"-") -> 0.07350326 | F12: =IFERROR(F8/F7,"-") -> 0.10970747 | G12: =IFERROR(G8/G7,"-") -> 0.085437312 | H12: =IFERROR(H8/H7,"-") -> 0.057537399 | I12: =IFERROR(I8/I7,"-") -> -0.051526616 | J12: =IFERROR(J8/J7,"-") -> 0.043651771 | ... S12: =IFERROR(S8/S7,"-") -> 0.17672458 | Y12: ILMN
B13: op yoy | G13: =G8/C8-1 -> -0.11394102 | H13: =H8/D8-1 -> -0.274942 | I13: =I8/E8-1 -> -1.5998759 | J13: =J8/F8-1 -> -0.66105585 | K13: =K8/G8-1 -> 0.1265759 | L13: =L8/H8-1 -> 1.068 | M13: =M8/I8-1 -> -3.7755946 | N13: =N8/J8-1 -> 3.4108352 | ... S13: =S8/O8-1 -> 0.5 | Y13: ABX
B14: rv yoy | G14: =G7/C7-1 -> 0.12845196 | H14: =H7/D7-1 -> 0.032851574 | I14: =I7/E7-1 -> -0.14427067 | J14: =J7/F7-1 -> -0.14815126 | K14: =K7/G7-1 -> -0.03330461 | L14: =L7/H7-1 -> 0.16487917 | M14: =M7/I7-1 -> 0.34342196 | N14: =N7/J7-1 -> 0.28664335 | ... S14: =S7/O7-1 -> 0.083345708 | Y14: PTON
Y15: GOLD
Y17: MTSI
Y18: CTLP
Y19: MAGN
Y20: RGA
Y22: KKR
Y23: MMS
Y25: EL
Y26: TPR
Y27: ARX
Y29: AGCO
Y30: ROAD
