Workbook

Sheet 기업리스트
B2: 실적 기업 정보
B3: Ticker | C3: Company | D3: Date | E3: Time | F3: Quarter Ending | G3: Market Cap (mil$)
B4: AMAT | C4: Applied Materials, Inc. | D4: 12-Feb-26 | E4: After Hours | F4: Jan-26 | G4: 255983
B5: RMS | C5: Hermès International Société en commandite par actions | D5: 12-Feb-26 | F5: Dec-25 | G5: 254688
B6: OR | C6: L'Oréal S.A. | D6: 12-Feb-26 | F6: Dec-25 | G6: 248655
B7: SIE | C7: Siemens Aktiengesellschaft | D7: 12-Feb-26 | F7: Dec-25 | G7: 229885
B8: ANET | C8: Arista Networks, Inc. | D8: 12-Feb-26 | E8: After Hours | F8: Dec-25 | G8: 173139
B9: ULVR | C9: Unilever PLC | D9: 12-Feb-26 | F9: Dec-25 | G9: 158619
B10: ABI | C10: Anheuser-Busch InBev SA/NV | D10: 12-Feb-26 | F10: Dec-25 | G10: 148335
B11: 9984 | C11: SoftBank Group Corp. | D11: 12-Feb-26 | F11: Dec-25 | G11: 145052
B12: BATS | C12: British American Tobacco p.l.c. | D12: 12-Feb-26 | F12: Dec-25 | G12: 136225
B13: VRTX | C13: Vertex Pharmaceuticals Incorporated | D13: 12-Feb-26 | E13: After Hours | F13: Dec-25 | G13: 121257
B14: BN | C14: Brookfield Corporation | D14: 12-Feb-26 | E14: Pre Market | F14: Dec-25 | G14: 101439
B15: AEM | C15: Agnico Eagle Mines Limited | D15: 12-Feb-26 | E15: After Hours | F15: Dec-25 | G15: 98702.35
B16: HWM | C16: Howmet Aerospace Inc. | D16: 12-Feb-26 | E16: Pre Market | F16: Dec-25 | G16: 89724.21
B17: ABNB | C17: Airbnb, Inc. | D17: 12-Feb-26 | E17: After Hours | F17: Dec-25 | G17: 74083.81
B18: VALE3 | C18: Vale S.A. | D18: 12-Feb-26 | F18: Dec-25 | G18: 70068.94
B19: MBG | C19: Mercedes-Benz Group AG | D19: 12-Feb-26 | F19: Dec-25 | G19: 66248.67
B20: 285A | C20: Kioxia Holdings Corporation | D20: 12-Feb-26 | F20: Dec-25 | G20: 66176.67
B21: AEP | C21: American Electric Power Company, Inc. | D21: 12-Feb-26 | E21: Pre Market | F21: Dec-25 | G21: 64518.62
B22: KBC | C22: KBC Group NV | D22: 12-Feb-26 | F22: Dec-25 | G22: 56390.83
B23: ZTS | C23: Zoetis Inc. | D23: 12-Feb-26 | E23: Pre Market | F23: Dec-25 | G23: 56153.13
B24: REL | C24: RELX PLC | D24: 12-Feb-26 | E24: Pre Market | F24: Dec-25 | G24: 52874.83
B25: PSA | C25: Public Storage | D25: 12-Feb-26 | E25: After Hours | F25: Dec-25 | G25: 50357.89
B26: CBRE | C26: CBRE Group, Inc. | D26: 12-Feb-26 | E26: Pre Market | F26: Dec-25 | G26: 49736.33
B27: EXC | C27: Exelon Corporation | D27: 12-Feb-26 | E27: Pre Market | F27: Dec-25 | G27: 44786.17
B28: COIN | C28: Coinbase Global, Inc. | D28: 12-Feb-26 | E28: After Hours | F28: Dec-25 | G28: 44525.87
B29: ETR | C29: Entergy Corporation | D29: 12-Feb-26 | E29: Pre Market | F29: Dec-25 | G29: 44306.28
B30: SCMN | C30: Swisscom AG | D30: 12-Feb-26 | F30: Dec-25 | G30: 44228.91
B31: ALNY | C31: Alnylam Pharmaceuticals, Inc. | D31: 12-Feb-26 | E31: Pre Market | F31: Dec-25 | G31: 43354.47
B32: ADYEN | C32: Adyen N.V. | D32: 12-Feb-26 | F32: Dec-25 | G32: 42269.11
B33: IR | C33: Ingersoll Rand Inc. | D33: 12-Feb-26 | E33: After Hours | F33: Dec-25 | G33: 38918.37
B34: EMAAR | C34: Emaar Properties PJSC | D34: 12-Feb-26 | F34: Dec-25 | G34: 38386.62
B35: ONGC | C35: Oil and Natural Gas Corporation Limited | D35: 12-Feb-26 | F35: Dec-25 | G35: 37351.94
B36: PCG | C36: PG&E Corporation | D36: 12-Feb-26 | F36: Dec-25 | G36: 36045.73
B37: COALINDIA | C37: Coal India Limited | D37: 12-Feb-26 | F37: Dec-25 | G37: 31410.13
B38: HAL | C38: Hindustan Aeronautics Limited | D38: 12-Feb-26 | F38: Dec-25 | G38: 30030.25
B39: EXPE | C39: Expedia Group, Inc. | D39: 12-Feb-26 | E39: After Hours | F39: Dec-25 | G39: 29021.83
B40: IRM | C40: Iron Mountain Incorporated | D40: 12-Feb-26 | E40: Pre Market | F40: Dec-25 | G40: 28311.56
B41: NBIS | C41: Nebius Group N.V. | D41: 12-Feb-26 | F41: Dec-25 | G41: 27379
B42: DXCM | C42: DexCom, Inc. | D42: 12-Feb-26 | E42: After Hours | F42: Dec-25 | G42: 27121.73
B43: 1347 | C43: Hua Hong Semiconductor Limited | D43: 12-Feb-26 | F43: Dec-25 | G43: 26409.93
B44: ES | C44: Eversource Energy | D44: 12-Feb-26 | E44: After Hours | F44: Dec-25 | G44: 26304.51
B45: FTS | C45: Fortis Inc. | D45: 12-Feb-26 | E45: Pre Market | F45: Dec-25 | G45: 26099.25
B46: BAP | C46: Credicorp Ltd. | D46: 12-Feb-26 | E46: After Hours | F46: Dec-25 | G46: 25542.55
B47: FMCC | C47: Federal Home Loan Mortgage Corporation | D47: 12-Feb-26 | F47: Dec-25 | G47: 24739.9
B48: 1605 | C48: Inpex Corporation | D48: 12-Feb-26 | F48: Dec-25 | G48: 23554.1
B49: 500440 | C49: Hindalco Industries Limited | D49: 12-Feb-26 | F49: Dec-25 | G49: 22873.03
B50: QSR | C50: Restaurant Brands International Inc. | D50: 12-Feb-26 | E50: Pre Market | F50: Dec-25 | G50: 22399.4
B51: WST | C51: West Pharmaceutical Services, Inc. | D51: 12-Feb-26 | E51: Pre Market | F51: Dec-25 | G51: 20643.44
B52: RIVN | C52: Rivian Automotive, Inc. | D52: 12-Feb-26 | E52: After Hours | F52: Dec-25 | G52: 20435.97
B53: T | C53: TELUS Corporation | D53: 12-Feb-26 | E53: Pre Market | F53: Dec-25 | G53: 20375.63
B54: CHKP | C54: Check Point Software Technologies Ltd. | D54: 12-Feb-26 | E54: Pre Market | F54: Dec-25 | G54: 19918.6
B55: TOST | C55: Toast, Inc. | D55: 12-Feb-26 | E55: After Hours | F55: Dec-25 | G55: 19709.76
B56: DSFIR | C56: DSM-Firmenich AG | D56: 12-Feb-26 | F56: Dec-25 | G56: 19562.72
B57: 7532 | C57: Pan Pacific International Holdings Corporation | D57: 12-Feb-26 | F57: Dec-25 | G57: 18958.89
B58: A035720 | C58: Kakao Corp. | D58: 12-Feb-26 | F58: Dec-25 | G58: 18654.46
B59: NN | C59: NN Group N.V. | D59: 12-Feb-26 | F59: Dec-25 | G59: 18385.82
B60: 3659 | C60: NEXON Co., Ltd. | D60: 12-Feb-26 | F60: Dec-25 | G60: 17896.37
B61: AC * | C61: Arca Continental, S.A.B. de C.V. | D61: 12-Feb-26 | F61: Dec-25 | G61: 17598.57
B62: AOT | C62: Airports of Thailand Public Company Limited | D62: 12-Feb-26 | F62: Dec-25 | G62: 17576.45
B63: DKNG | C63: DraftKings Inc. | D63: 12-Feb-26 | E63: After Hours | F63: Dec-25 | G63: 17560.15
B64: PINS | C64: Pinterest, Inc. | D64: 12-Feb-26 | E64: After Hours | F64: Dec-25 | G64: 17503.7
B65: 2502 | C65: Asahi Group Holdings, Ltd. | D65: 12-Feb-26 | F65: Dec-25 | G65: 17430.95
B66: USFD | C66: US Foods Holding Corp. | D66: 12-Feb-26 | E66: Pre Market | F66: Dec-25 | G66: 17153.57
B67: TWLO | C67: Twilio Inc. | D67: 12-Feb-26 | E67: After Hours | F67: Dec-25 | G67: 15794.46
B68: ZBRA | C68: Zebra Technologies Corporation | D68: 12-Feb-26 | E68: Pre Market | F68: Dec-25 | G68: 15508.28
B69: URW | C69: Unibail-Rodamco-Westfield SE | D69: 12-Feb-26 | F69: Dec-25 | G69: 15356.18
B70: ROKU | C70: Roku, Inc. | D70: 12-Feb-26 | E70: After Hours | F70: Dec-25 | G70: 15300.29
B71: TRU | C71: TransUnion | D71: 12-Feb-26 | E71: Pre Market | F71: Dec-25 | G71: 15065.83
B72: 6326 | C72: Kubota Corporation | D72: 12-Feb-26 | F72: Dec-25 | G72: 14795.03
B73: MAP | C73: Mapfre, S.A. | D73: 12-Feb-26 | F73: Dec-25 | G73: 14594.13
B74: KIM | C74: Kimco Realty Corporation | D74: 12-Feb-26 | E74: Pre Market | F74: Dec-25 | G74: 14539.49
B75: BBD.B | C75: Bombardier Inc. | D75: 12-Feb-26 | F75: Dec-25 | G75: 14321.71
B76: H | C76: Hyatt Hotels Corporation | D76: 12-Feb-26 | E76: Pre Market | F76: Dec-25 | G76: 14035.34
B77: BNT | C77: Brookfield Wealth Solutions Ltd. | D77: 12-Feb-26 | F77: Dec-25 | G77: 13823.06
B78: 4755 | C78: Rakuten Group, Inc. | D78: 12-Feb-26 | F78: Dec-25 | G78: 13729.84
B79: LECO | C79: Lincoln Electric Holdings, Inc. | D79: 12-Feb-26 | E79: Pre Market | F79: Dec-25 | G79: 13045.48
B80: WYNN | C80: Wynn Resorts, Limited | D80: 12-Feb-26 | E80: After Hours | F80: Dec-25 | G80: 12731.73
B81: 9435 | C81: Hikari Tsushin, Inc. | D81: 12-Feb-26 | F81: Dec-25 | G81: 12385.15
B82: 8136 | C82: Sanrio Company, Ltd. | D82: 12-Feb-26 | F82: Dec-25 | G82: 12258.57
B83: BAX | C83: Baxter International Inc. | D83: 12-Feb-26 | E83: Pre Market | F83: Dec-25 | G83: 12255
B84: 8795 | C84: T&D Holdings, Inc. | D84: 12-Feb-26 | F84: Dec-25 | G84: 11636.47
B85: 8113 | C85: Unicharm Corporation | D85: 12-Feb-26 | F85: Dec-25 | G85: 11632.46
B86: 6383 | C86: Daifuku Co., Ltd. | D86: 12-Feb-26 | F86: Dec-25 | G86: 11626.67
B87: 500850 | C87: The Indian Hotels Company Limited | D87: 12-Feb-26 | F87: Dec-25 | G87: 11619.39
B88: METSO | C88: Metso Oyj | D88: 12-Feb-26 | F88: Dec-25 | G88: 11529.35
B89: IPN | C89: Ipsen S.A. | D89: 12-Feb-26 | F89: Dec-25 | G89: 11230.13
B90: PCOR | C90: Procore Technologies, Inc. | D90: 12-Feb-26 | E90: After Hours | F90: Dec-25 | G90: 10917.51
B91: KNSL | C91: Kinsale Capital Group, Inc. | D91: 12-Feb-26 | E91: After Hours | F91: Dec-25 | G91: 10863.86
B92: ORNBV | C92: Orion Oyj | D92: 12-Feb-26 | F92: Dec-25 | G92: 10774.54
B93: 7550 | C93: Zensho Holdings Co., Ltd. | D93: 12-Feb-26 | F93: Dec-25 | G93: 10600.32
B94: 500257 | C94: Lupin Limited | D94: 12-Feb-26 | F94: Dec-25 | G94: 10499.22
B95: CART | C95: Maplebear Inc. | D95: 12-Feb-26 | E95: After Hours | F95: Dec-25 | G95: 10346.42
B96: ORK | C96: Orkla ASA | D96: 12-Feb-26 | F96: Dec-25 | G96: 10327.38
B97: BCVN | C97: Banque Cantonale Vaudoise | D97: 12-Feb-26 | F97: Dec-25 | G97: 10194.42
B98: 9024 | C98: Seibu Holdings Inc. | D98: 12-Feb-26 | F98: Dec-25 | G98: 9571.28
B99: NVMI | C99: Nova Ltd. | D99: 12-Feb-26 | E99: Pre Market | F99: Dec-25 | G99: 9548.98
B100: MORN | C100: Morningstar, Inc. | D100: 12-Feb-26 | E100: After Hours | F100: Dec-25 | G100: 9537.23
B101: 2587 | C101: Suntory Beverage & Food Limited | D101: 12-Feb-26 | F101: Dec-25 | G101: 9523.2
...

Sheet Revenue
B2: Ticker | C2: Country | D2: Industry | E2: Latest_Date | F2: Growth_Rate | G2: 4Q21 | H2: 1Q22 | I2: 2Q22 | J2: 3Q22 | K2: 4Q22 | L2: 1Q23 | M2: 2Q23 | N2: 3Q23 | O2: 4Q23 | P2: 1Q24 | Q2: 2Q24 | R2: 3Q24 | S2: 4Q24 | T2: 1Q25 | U2: 2Q25 | V2: 3Q25 | W2: 4Q25 | X2: 1Q25 | Y2: 2Q25 | Z2: 3Q25 | AA2: 4Q25
B3: 1347 | C3: Hong Kong | D3: N/A | E3: Sep'25 | F3: 5 | G3: 451.48 | H3: 528.32 | I3: 594.65 | J3: 620.82 | K3: 629.91 | L3: 630.11 | M3: 630.84 | N3: 631.38 | O3: 568.53 | P3: 455.36 | Q3: 459.99 | R3: 478.52 | S3: 526.31 | T3: 539.18 | U3: 540.94 | V3: 566.07 | W3: 635.18 | X3: 0.043652158 | Y3: 0.040394212 | Z3: 0.041991415 | AA3: 0.050112773
B4: NBIS | C4: United States | D4: Internet Content & Information | E4: Dec'25 | F4: 55.1 | G4: 1470 | H4: 1288 | I4: 2161 | J4: 2201 | K4: 2261 | L4: 2107 | M4: 2039 | N4: 2095 | O4: 0 | P4: 11.3 | Q4: 12.08 | R4: 32.1 | S4: 37.9 | T4: 55.3 | U4: 105.1 | V4: 146.1 | W4: 227.7 | X4: 0.47119297 | Y4: 0.67710001 | Z4: 0.49479167 | AA4: 0.55110337
B5: BTDR | C5: United States | D5: Software - Application | E5: Dec'25 | F5: 33.6 | G5: 87.49 | H5: 90.44 | I5: 89.18 | J5: 76.58 | K5: 77.14 | L5: 72.59 | M5: 93.82 | N5: 87.3 | O5: 114.85 | P5: 119.51 | Q5: 99.23 | R5: 62.03 | S5: 69.02 | T5: 70.13 | U5: 155.58 | V5: 169.71 | W5: 224.84 | X5: -0.14117042 | Y5: 0.18757698 | Z5: 0.30182756 | AA5: 0.33550082
B6: H | C6: United States | D6: Lodging | E6: Dec'25 | F6: 30.8 | G6: 575 | H6: 739 | I6: 843 | J6: 836 | K6: 853 | L6: 951 | M6: 921 | N6: 868 | O6: 869 | P6: 912 | Q6: 861 | R6: 762 | S6: 761 | T6: 832 | U6: 863 | V6: 883 | W6: 1789 | X6: -0.024271845 | Y6: 0.00062189055 | Z6: 0.037600994 | AA6: 0.30787661
B7: FWDI | C7: United States | D7: Footwear & Accessories | E7: Dec'25 | F7: 21.4 | G7: 10.94 | H7: 11.61 | I7: 10.31 | J7: 10.59 | K7: 0 | L7: 9.75 | M7: 9.74 | N7: 8.71 | O7: 8.49 | P7: 5.14 | Q7: 5.07 | R7: 5.04 | S7: 4.74 | T7: 4.62 | U7: 3.12 | V7: 2.49 | W7: 7.95 | X7: -0.026013007 | Y7: -0.10015408 | Z7: -0.14554795 | AA7: 0.21442886
B8: AGIO | C8: United States | D8: Biotechnology | E8: Dec'25 | F8: 20.6 | G8: 0 | H8: 0.83 | I8: 5.58 | J8: 3.52 | K8: 4.31 | L8: 5.61 | M8: 6.71 | N8: 7.4 | O8: 7.1 | P8: 8.19 | Q8: 8.62 | R8: 8.96 | S8: 10.73 | T8: 8.73 | U8: 12.46 | V8: 12.88 | W8: 19.97 | X8: 0.014794521 | Y8: 0.10367171 | Z8: 0.095890411 | AA8: 0.20625
B9: KEY | C9: United States | D9: Banks - Regional | E9: Dec'25 | F9: 18.1 | G9: 1938 | H9: 1607 | I9: 1740 | J9: 1770 | K9: 1626 | L9: 1568 | M9: 1420 | N9: 1477 | O9: 1429 | P9: 1421 | Q9: 1414 | R9: 588 | S9: 816 | T9: 1646 | U9: 1693 | V9: 1779 | W9: 1889 | X9: 0.053078556 | Y9: 0.0625 | Z9: 0.25110689 | AA9: 0.18082238
B10: ELVA | C10: United States | D10: Electrical Equipment & Parts | E10: Dec'25 | F10: 16.3 | G10: 4.16 | H10: 1.25 | I10: 4.29 | J10: 4.31 | K10: 6.43 | L10: 8.56 | M10: 8.47 | N10: 10.6 | O10: 16.43 | P10: 12.09 | Q10: 10.7 | R10: 10.27 | S10: 11.56 | T10: 11.17 | U10: 15.02 | V10: 17.13 | W10: 20.51 | X10: -0.020618557 | Y10: 0.098855835 | Z10: 0.14285714 | AA10: 0.16308309
B11: ALNY | C11: United States | D11: Biotechnology | E11: Dec'25 | F11: 15.7 | G11: 258.54 | H11: 213.26 | I11: 224.82 | J11: 264.31 | K11: 335.04 | L11: 319.29 | M11: 318.75 | N11: 750.53 | O11: 439.72 | P11: 494.33 | Q11: 659.83 | R11: 500.92 | S11: 593.17 | T11: 594.19 | U11: 773.69 | V11: 1249 | W11: 1097 | X11: 0.044416769 | Y11: 0.048490062 | Z11: 0.30385423 | AA11: 0.15695394
B12: AEM | C12: United States | D12: Gold | E12: Dec'25 | F12: 12.7 | G12: 951.53 | H12: 1326 | I12: 1581 | J12: 1450 | K12: 1385 | L12: 1510 | M12: 1718 | N12: 1642 | O12: 1757 | P12: 1830 | Q12: 2077 | R12: 2156 | S12: 2224 | T12: 2468 | U12: 2816 | V12: 3060 | W12: 3564 | X12: 0.076988054 | Y12: 0.08280112 | Z12: 0.093543046 | AA12: 0.12679788
B13: 2212 | C13: Japan | D13: N/A | E13: Sep'25 | F13: 1.2 | G13: 249845 | H13: 290917 | I13: 259727 | J13: 268525 | K13: 263876 | L13: 284881 | M13: 276839 | N13: 287105 | O13: 282281 | P13: 329337 | Q13: 306658 | R13: 311089 | S13: 301846 | T13: 324895 | U13: 318735 | V13: 331898 | W13: 317467 | X13: -0.0035566445 | Y13: 0.0097043925 | Z13: 0.016560226 | AA13: 0.012228995
B14: CNR | C14: United States | D14: Thermal Coal | E14: Dec'25 | F14: 12.7 | G14: 340.19 | H14: 539.5 | I14: 611.61 | J14: 533.61 | K14: 612.15 | L14: 680.88 | M14: 657.96 | N14: 564.52 | O14: 624.46 | P14: 546.69 | Q14: 490.72 | R14: 553.43 | S14: 573.17 | T14: 1017 | U14: 1102 | V14: 1003 | W14: 1042 | X14: 0.21733264 | Y14: 0.2320447 | Z14: 0.13851676 | AA14: 0.12687644
B15: CTRE | C15: United States | D15: REIT - Healthcare Facilities | E15: Dec'25 | F15: 11.2 | G15: 49.74 | H15: 46.48 | I15: 47.55 | J15: 50.29 | K15: 51.81 | L15: 50.61 | M15: 51.55 | N15: 55.88 | O15: 59.73 | P15: 63.07 | Q15: 68.89 | R15: 77.38 | S15: 86.94 | T15: 96.62 | U15: 112.47 | V15: 132.44 | W15: 134.86 | X15: 0.11323748 | Y15: 0.13212867 | Z15: 0.14745186 | AA15: 0.1118398
B16: DKNG | C16: United States | D16: Gambling | E16: Dec'25 | F16: 10.9 | G16: 473.33 | H16: 417.21 | I16: 466.19 | J16: 501.94 | K16: 855.13 | L16: 769.65 | M16: 874.93 | N16: 789.96 | O16: 1231 | P16: 1175 | Q16: 1104 | R16: 1095 | S16: 1393 | T16: 1409 | U16: 1513 | V16: 1144 | W16: 1989 | X16: 0.049087476 | Y16: 0.081783643 | Z16: 0.0090573013 | AA16: 0.10917751
B17: 2502 | C17: Japan | D17: N/A | E17: Jun'25 | F17: -1.1 | G17: 576926 | H17: 586708 | I17: 615773 | J17: 496863 | K17: 654476 | L17: 698604 | M17: 661164 | N17: 556335 | O17: 696664 | P17: 770004 | Q17: 746087 | R17: 616614 | S17: 762352 | T17: 788986 | U17: 771470 | V17: 679776 | W17: 729128 | X17: 0.006556693 | Y17: 0.0087105904 | Z17: 0.021487898 | AA17: -0.011065136
B18: SPHR | C18: United States | D18: Entertainment | E18: Dec'25 | F18: 7.6 | G18: 0 | H18: 352.53 | I18: -318.39 | J18: 123.13 | K18: 159.54 | L18: 162.06 | M18: 0 | N18: 118.01 | O18: 314.16 | P18: 321.33 | Q18: 273.4 | R18: 227.91 | S18: 308.29 | T18: 280.57 | U18: 282.68 | V18: 262.51 | W18: 394.28 | X18: -0.036041134 | Y18: 0.0085124338 | Z18: 0.031470281 | AA18: 0.075825581
B19: AIP | C19: United States | D19: Semiconductors | E19: Dec'25 | F19: 7.1 | G19: 11.43 | H19: 11.76 | I19: 14.82 | J19: 12.6 | K19: 11.2 | L19: 13.15 | M19: 14.73 | N19: 13.27 | O19: 12.5 | P19: 12.95 | Q19: 14.58 | R19: 14.71 | S19: 15.49 | T19: 16.53 | U19: 16.5 | V19: 17.41 | W19: 20.14 | X19: 0.062012818 | Y19: 0.031316262 | Z19: 0.042701249 | AA19: 0.070529349
B20: HCC | C20: United States | D20: Coking Coal | E20: Dec'25 | F20: 7 | G20: 415.55 | H20: 378.67 | I20: 625.17 | J20: 390.18 | K20: 344.75 | L20: 509.67 | M20: 379.16 | N20: 423.49 | O20: 365 | P20: 503.51 | Q20: 396.52 | R20: 327.72 | S20: 297.47 | T20: 302.64 | U20: 296.12 | V20: 328.09 | W20: 383.19 | X20: -0.13169903 | Y20: -0.075810775 | Z20: 0.00030229993 | AA20: 0.070014375
B21: RARE | C21: United States | D21: Biotechnology | E21: Dec'25 | F21: 6.7 | G21: 83.39 | H21: 79.94 | I21: 89.34 | J21: 90.7 | K21: 103.35 | L21: 100.5 | M21: 108.31 | N21: 98.05 | O21: 127.39 | P21: 108.83 | Q21: 147.03 | R21: 139.49 | S21: 164.88 | T21: 139.29 | U21: 166.5 | V21: 159.93 | W21: 207 | X21: 0.054370526 | Y21: 0.032961452 | Z21: 0.03349941 | AA21: 0.06679353
B22: ANET | C22: United States | D22: Computer Hardware | E22: Dec'25 | F22: 6.6 | G22: 824.46 | H22: 877.07 | I22: 1052 | J22: 1177 | K22: 1276 | L22: 1351 | M22: 1459 | N22: 1509 | O22: 1540 | P22: 1571 | Q22: 1690 | R22: 1811 | S22: 1930 | T22: 2005 | U22: 2205 | V22: 2308 | W22: 2488 | X22: 0.061982291 | Y22: 0.069257665 | Z22: 0.062507861 | AA22: 0.066051136
B23: 3659 | C23: Japan | D23: N/A | E23: Sep'25 | F23: -3.8 | G23: 75890 | H23: 54250 | I23: 87578 | J23: 84122 | K23: 97463 | L23: 81095 | M23: 124087 | N23: 94436 | O23: 120256 | P23: 84577 | Q23: 108418 | R23: 122474 | S23: 135593 | T23: 79726 | U23: 113934 | V23: 118850 | W23: 118719 | X23: -0.010754619 | Y23: 0.012361865 | Z23: -0.0080225446 | AA23: -0.037656521
B24: BGC | C24: United States | D24: Capital Markets | E24: Dec'25 | F24: 6.6 | G24: 445.53 | H24: 492.16 | I24: 421.41 | J24: 402.07 | K24: 421.73 | L24: 517.13 | M24: 473.17 | N24: 461.91 | O24: 495.97 | P24: 558.48 | Q24: 529.21 | R24: 535.99 | S24: 548.07 | T24: 639.59 | U24: 750.2 | V24: 703.03 | W24: 723.33 | X24: 0.037347761 | Y24: 0.098093091 | Z24: 0.067522283 | AA24: 0.066363991
B25: 3964 | C25: Japan | D25: N/A | E25: Sep'25 | F25: 1.7 | G25: 8652 | H25: 9447 | I25: 10501 | J25: 10102 | K25: 9882 | L25: 9970 | M25: 10728 | N25: 11203 | O25: 10311 | P25: 11061 | Q25: 10988 | R25: 15583 | S25: 13872 | T25: 15467 | U25: 15978 | V25: 16554 | W25: 14949 | X25: 0.085546754 | Y25: 0.089250581 | Z25: 0.015944171 | AA25: 0.017407186
B26: BROS | C26: United States | D26: Restaurants | E26: Dec'25 | F26: 6.6 | G26: 140.08 | H26: 152.16 | I26: 186.38 | J26: 198.65 | K26: 201.83 | L26: 197.27 | M26: 249.88 | N26: 264.51 | O26: 254.12 | P26: 275.1 | Q26: 324.92 | R26: 338.21 | S26: 342.79 | T26: 355.15 | U26: 415.81 | V26: 423.58 | W26: 443.61 | X26: 0.062489266 | Y26: 0.066778344 | Z26: 0.058796386 | AA26: 0.065581235
B27: COHU | C27: United States | D27: Semiconductor Equipment & Materials | E27: Dec'25 | F27: 6.6 | G27: 191.86 | H27: 197.76 | I27: 217.23 | J27: 206.69 | K27: 191.11 | L27: 179.37 | M27: 168.92 | N27: 150.8 | O27: 137.23 | P27: 107.61 | Q27: 104.7 | R27: 95.34 | S27: 94.12 | T27: 96.8 | U27: 107.68 | V27: 126.25 | W27: 122.23 | X27: -0.026905941 | Y27: 0.0076222631 | Z27: 0.078463725 | AA27: 0.066164529
B28: 4045 | C28: Japan | D28: N/A | E28: Sep'25 | F28: -1.4 | G28: 39231 | H28: 42918 | I28: 37750 | J28: 40227 | K28: 40740 | L28: 42108 | M28: 38198 | N28: 38749 | O28: 39202 | P28: 43222 | Q28: 39014 | R28: 42557 | S28: 41792 | T28: 44231 | U28: 39822 | V28: 40522 | W28: 39519 | X28: 0.0060569679 | Y28: 0.004821175 | Z28: -0.01208418 | AA28: -0.013662565
B29: 4293 | C29: Japan | D29: N/A | E29: Sep'25 | F29: 0.6 | G29: 5473 | H29: 6572 | I29: 7885 | J29: 7109 | K29: 7252 | L29: 6973 | M29: 7566 | N29: 7097 | O29: 7470 | P29: 0 | Q29: 7291 | R29: 6697 | S29: 6898 | T29: 7397 | U29: 8206 | V29: 7001 | W29: 7081 | X29: 0.35416068 | Y29: 0.032351589 | Z29: 0.010411672 | AA29: 0.0062029693
B30: STNG | C30: United States | D30: Oil & Gas Midstream | E30: Dec'25 | F30: 5.5 | G30: 147.91 | H30: 174.05 | I30: 405.07 | J30: 490 | K30: 493.76 | L30: 384.43 | M30: 329.3 | N30: 291.18 | O30: 336.31 | P30: 391.34 | Q30: 380.66 | R30: 267.99 | S30: 203.97 | T30: 213.98 | U30: 230.23 | V30: 241.36 | W30: 252.65 | X30: -0.14257693 | Y30: -0.14103694 | Z30: -0.029066658 | AA30: 0.054724914
B31: TOST | C31: United States | D31: Software - Infrastructure | E31: Dec'25 | F31: 5 | G31: 512 | H31: 535 | I31: 675 | J31: 752 | K31: 768 | L31: 819 | M31: 978 | N31: 1032 | O31: 1036 | P31: 1075 | Q31: 1242 | R31: 1305 | S31: 1338 | T31: 1337 | U31: 1550 | V31: 1633 | W31: 1633 | X31: 0.052822581 | Y31: 0.058981233 | Z31: 0.059312839 | AA31: 0.050358484
B32: 4755 | C32: Japan | D32: N/A | E32: Sep'25 | F32: 2.6 | G32: 406903 | H32: 481183 | I32: 437127 | J32: 456471 | K32: 471110 | L32: 563170 | M32: 475635 | N32: 497165 | O32: 518439 | P32: 580076 | Q32: 513624 | R32: 537284 | S32: 566713 | T32: 661612 | U32: 562704 | V32: 596369 | W32: 628562 | X32: 0.037100656 | Y32: 0.02153356 | Z32: 0.025376743 | AA32: 0.025906447
B33: 4776 | C33: Japan | D33: N/A | E33: Sep'25 | F33: 6.4 | G33: 4637 | H33: 4879 | I33: 5184 | J33: 5379 | K33: 5630 | L33: 5874 | M33: 6059 | N33: 6229 | O33: 6448 | P33: 6696 | Q33: 6907 | R33: 7180 | S33: 7381 | T33: 8207 | U33: 8759 | V33: 9140 | W33: 9514 | X33: 0.05365005 | Y33: 0.062409436 | Z33: 0.062168935 | AA33: 0.06369636
B34: 4784 | C34: Japan | D34: N/A | E34: Sep'25 | F34: 37.3 | G34: 7747 | H34: 8770 | I34: 3986 | J34: 4400 | K34: 4240 | L34: 4003 | M34: 4269 | N34: 3876 | O34: 3461 | P34: 3297 | Q34: 3454 | R34: 3083 | S34: 3084 | T34: 3376 | U34: 19080 | V34: 19426 | W34: 19839 | X34: 0.0061154978 | Y34: 1.2022774 | Z34: 0.57097439 | AA34: 0.37261486
B35: 4812 | C35: Japan | D35: N/A | E35: Sep'25 | F35: 1.8 | G35: 25591 | H35: 32201 | I35: 29982 | J35: 31476 | K35: 32350 | L35: 35246 | M35: 34779 | N35: 35070 | O35: 35418 | P35: 37341 | Q35: 37099 | R35: 37136 | S35: 37996 | T35: 40411 | U35: 40244 | V35: 39995 | W35: 40912 | X35: 0.020525232 | Y35: 0.020603766 | Z35: 0.018351981 | AA35: 0.018380545
B36: 4912 | C36: Japan | D36: N/A | E36: Sep'25 | F36: 0.7 | G36: 94368 | H36: 98642 | I36: 87030 | J36: 98165 | K36: 100946 | L36: 103728 | M36: 90849 | N36: 102037 | O36: 103210 | P36: 106670 | Q36: 92965 | R36: 105668 | S36: 102525 | T36: 111784 | U36: 94237 | V36: 105222 | W36: 105486 | X36: 0.0125396 | Y36: 0.0030803357 | Z36: -0.0010767381 | AA36: 0.0071561841
B37: 4922 | C37: Japan | D37: N/A | E37: Sep'25 | F37: 0.1 | G37: 64163 | H37: 102050 | I37: 59013 | J37: 71591 | K37: 70283 | L37: 88249 | M37: 68158 | N37: 76137 | O37: 74666 | P37: 81445 | Q37: 77583 | R37: 81550 | S37: 79592 | T37: 84033 | U37: 78998 | V37: 81526 | W37: 79986 | X37: 0.0080832058 | Y37: 0.0043840896 | Z37: -7.4034543e-05 | AA37: 0.0012154904
B38: 4971 | C38: Japan | D38: N/A | E38: Sep'25 | F38: 4.3 | G38: 4133 | H38: 3881 | I38: 3955 | J38: 4172 | K38: 4237 | L38: 3965 | M38: 2765 | N38: 3433 | O38: 3783 | P38: 4039 | Q38: 4354 | R38: 4528 | S38: 4800 | T38: 4552 | U38: 4424 | V38: 4963 | W38: 5601 | X38: 0.028948705 | Y38: 0.0038389821 | Z38: 0.023765297 | AA38: 0.042745077
B39: ECX | C39: United States | D39: Auto Parts | E39: Dec'25 | F39: 4.8 | G39: 133.35 | H39: 103.46 | I39: 98.23 | J39: 101.18 | K39: 221.57 | L39: 111.38 | M39: 133.96 | N39: 149.19 | O39: 264.35 | P39: 129.88 | Q39: 174.45 | R39: 198.2 | S39: 265.88 | T39: 168.46 | U39: 152.66 | V39: 219.9 | W39: 304.7 | X39: 0.050207571 | Y39: -0.027001574 | Z39: 0.027636271 | AA39: 0.048110051
B40: CNCK | C40: United States | D40: Capital Markets | E40: Sep'26 | F40: 4.5 | G40: 335265 | H40: 335265 | I40: 59294 | J40: 59294 | K40: 29169 | L40: 29169 | M40: 26114 | N40: 37419 | O40: 59116 | P40: 101400 | Q40: 75300 | R40: 70348 | S40: 123104 | T40: 114579 | U40: 83989 | V40: 133105 | W40: 143455 | X40: 0.035604292 | Y40: 0.022667094 | Z40: 0.16008622 | AA40: 0.044749405
B41: 5301 | C41: Japan | D41: N/A | E41: Sep'25 | F41: -2.5 | G41: 67715 | H41: 73779 | I41: 69512 | J41: 87558 | K41: 89262 | L41: 94039 | M41: 86530 | N41: 91898 | O41: 89247 | P41: 96271 | Q41: 82161 | R41: 88761 | S41: 87737 | T41: 91455 | U41: 80346 | V41: 77730 | W41: 79260 | X41: -0.013568873 | Y41: -0.0051840258 | Z41: -0.031671064 | AA41: -0.025134315
B42: AORT | C42: United States | D42: Medical Devices | E42: Dec'25 | F42: 4.4 | G42: 79.39 | H42: 77.21 | I42: 80.34 | J42: 76.84 | K42: 79.4 | L42: 83.23 | M42: 89.25 | N42: 87.85 | O42: 93.67 | P42: 97.43 | Q42: 98.02 | R42: 95.78 | S42: 97.31 | T42: 98.98 | U42: 112.97 | V42: 113.39 | W42: 115.99 | X42: 0.0039892933 | Y42: 0.038324489 | Z42: 0.043477187 | AA42: 0.044197326
B43: GVA | C43: United States | D43: Engineering & Construction | E43: Dec'25 | F43: 4.4 | G43: 805.65 | H43: 653.89 | I43: 849.25 | J43: 1009 | K43: 789.21 | L43: 560.07 | M43: 898.55 | N43: 1117 | O43: 933.7 | P43: 672.28 | Q43: 1082 | R43: 1276 | S43: 977.3 | T43: 699.55 | U43: 1126 | V43: 1433 | W43: 1165 | X43: 0.0068046053 | Y43: 0.01090499 | Z43: 0.038491241 | AA43: 0.04431224
B44: ROKU | C44: United States | D44: Entertainment | E44: Dec'25 | F44: 4.3 | G44: 865.33 | H44: 733.7 | I44: 764.41 | J44: 761.37 | K44: 867.06 | L44: 740.99 | M44: 847.19 | N44: 912.02 | O44: 984.43 | P44: 881.47 | Q44: 968.18 | R44: 1062 | S44: 1201 | T44: 1021 | U44: 1111 | V44: 1211 | W44: 1395 | X44: 0.03392703 | Y44: 0.033587477 | Z44: 0.033902162 | AA44: 0.042693662
B45: IPGP | C45: United States | D45: Semiconductor Equipment & Materials | E45: Dec'25 | F45: 4.2 | G45: 364.47 | H45: 369.98 | I45: 377.02 | J45: 349.01 | K45: 333.54 | L45: 347.17 | M45: 339.97 | N45: 301.4 | O45: 298.89 | P45: 252.01 | Q45: 257.65 | R45: 233.14 | S45: 234.34 | T45: 227.79 | U45: 250.72 | V45: 250.79 | W45: 274.47 | X45: -0.024786622 | Y45: -0.0072723838 | Z45: 0.018657703 | AA45: 0.041644182
B46: PINS | C46: United States | D46: Internet Content & Information | E46: Dec'25 | F46: 4.1 | G46: 846.66 | H46: 574.89 | I46: 665.93 | J46: 684.55 | K46: 877.21 | L46: 602.58 | M46: 708.03 | N46: 763.2 | O46: 981.26 | P46: 739.98 | Q46: 853.68 | R46: 898.37 | S46: 1154 | T46: 854.99 | U46: 998.23 | V46: 1049 | W46: 1319 | X46: 0.031543898 | Y46: 0.038433518 | Z46: 0.038567796 | AA46: 0.040678267
B47: GEO | C47: United States | D47: Security & Protection Services | E47: Dec'25 | F47: 4 | G47: 557.54 | H47: 551.19 | I47: 588.18 | J47: 616.68 | K47: 620.68 | L47: 608.21 | M47: 593.89 | N47: 602.79 | O47: 608.28 | P47: 605.67 | Q47: 607.19 | R47: 603.13 | S47: 607.72 | T47: 604.65 | U47: 636.17 | V47: 682.34 | W47: 707.7 | X47: -0.00042084243 | Y47: 0.01196191 | Z47: 0.03230859 | AA47: 0.039504046
B48: IRM | C48: United States | D48: REIT - Specialty | E48: Dec'25 | F48: 3.9 | G48: 1160 | H48: 1248 | I48: 1290 | J48: 1287 | K48: 1279 | L48: 1314 | M48: 1358 | N48: 1388 | O48: 1420 | P48: 1477 | Q48: 1534 | R48: 1557 | S48: 1581 | T48: 1593 | U48: 1712 | V48: 1754 | W48: 1843 | X48: 0.018864856 | Y48: 0.028411812 | Z48: 0.030575819 | AA48: 0.039457831
B49: KNSL | C49: United States | D49: Insurance - Property & Casualty | E49: Dec'25 | F49: 3.9 | G49: 183.6 | H49: 184.66 | I49: 183.88 | J49: 222.06 | K49: 248.21 | L49: 263.15 | M49: 295.77 | N49: 314.37 | O49: 351.17 | P49: 372.79 | Q49: 384.55 | R49: 418.06 | S49: 412.12 | T49: 423.4 | U49: 469.81 | V49: 497.51 | W49: 483.27 | X49: 0.031879913 | Y49: 0.052047151 | Z49: 0.046100999 | AA49: 0.03946551
B50: 6250 | C50: Japan | D50: N/A | E50: Sep'25 | F50: 1.9 | G50: 36037 | H50: 29893 | I50: 35348 | J50: 44292 | K50: 41970 | L50: 34549 | M50: 38861 | N50: 41292 | O50: 37668 | P50: 33579 | Q50: 40805 | R50: 45601 | S50: 40745 | T50: 37687 | U50: 43785 | V50: 47503 | W50: 44029 | X50: 0.02555839 | Y50: 0.018078356 | Z50: 0.011333707 | AA50: 0.019349517
B51: 6268 | C51: Japan | D51: N/A | E51: Sep'25 | F51: -23 | G51: 68408 | H51: 85685 | I51: 70386 | J51: 71809 | K51: 76737 | L51: 89759 | M51: 82193 | N51: 80804 | O51: 80587 | P51: 90047 | Q51: 72181 | R51: 80309 | S51: 77339 | T51: 93554 | U51: 81698 | V51: 83918 | W51: 0 | X51: 0.010963623 | Y51: 0.0294295 | Z51: 0.010841093 | AA51: -0.22982743
B52: 6278 | C52: Japan | D52: N/A | E52: Sep'25 | F52: 7.8 | G52: 7223 | H52: 7670 | I52: 7475 | J52: 7851 | K52: 7774 | L52: 5991 | M52: 5792 | N52: 6526 | O52: 6661 | P52: 6359 | Q52: 7423 | R52: 8371 | S52: 7031 | T52: 9781 | U52: 8802 | V52: 9445 | W52: 9768 | X52: 0.11725603 | Y52: 0.04229283 | Z52: 0.031602177 | AA52: 0.078068399
B53: AL | C53: United States | D53: Rental & Leasing Services | E53: Dec'25 | F53: 3.7 | G53: 597.18 | H53: 596.66 | I53: 557.7 | J53: 561.33 | K53: 601.61 | L53: 636.14 | M53: 672.9 | N53: 659.36 | O53: 716.57 | P53: 663.31 | Q53: 667.29 | R53: 690.16 | S53: 712.9 | T53: 738.28 | U53: 731.7 | V53: 725.39 | W53: 820.38 | X53: 0.027424771 | Y53: 0.022932889 | Z53: 0.012262273 | AA53: 0.036956679
B54: 6326 | C54: Japan | D54: N/A | E54: Sep'25 | F54: 1.8 | G54: 540235 | H54: 555126 | I54: 593223 | J54: 667257 | K54: 693700 | L54: 724592 | M54: 781563 | N54: 738477 | O54: 738191 | P54: 762480 | Q54: 775232 | R54: 804367 | S54: 698326 | T54: 738356 | U54: 712556 | V54: 742377 | W54: 749349 | X54: -0.0079344693 | Y54: -0.020779231 | Z54: -0.020987911 | AA54: 0.017645157
B55: 6383 | C55: Japan | D55: N/A | E55: Sep'25 | F55: 0.3 | G55: 123202 | H55: 126058 | I55: 142788 | J55: 130211 | K55: 147571 | L55: 157907 | M55: 166233 | N55: 134552 | O55: 146715 | P55: 156122 | Q55: 174088 | R55: 145091 | S55: 157530 | T55: 260607 | U55: 160256 | V55: 166233 | W55: 159525 | X55: 0.16510727 | Y55: -0.018759935 | Z55: 0.029222485 | AA55: 0.0026791973
B56: 6481 | C56: Japan | D56: N/A | E56: Sep'25 | F56: 1.9 | G56: 79106 | H56: 88042 | I56: 88097 | J56: 98572 | K56: 100865 | L56: 106151 | M56: 93537 | N56: 92056 | O56: 82526 | P56: 83820 | Q56: 85127 | R56: 94723 | S56: 85279 | T56: 87629 | U56: 84946 | V56: 91300 | W56: 91981 | X56: 0.010915635 | Y56: -0.00051309963 | Z56: -0.0097085176 | AA56: 0.019194968
B57: 6498 | C57: Japan | D57: N/A | E57: Sep'25 | F57: 0.5 | G57: 34730 | H57: 37943 | I57: 36750 | J57: 40182 | K57: 41327 | L57: 41655 | M57: 39241 | N57: 42033 | O57: 42084 | P57: 43583 | Q57: 40211 | R57: 43586 | S57: 43498 | T57: 44747 | U57: 41740 | V57: 44640 | W57: 44436 | X57: 0.0068118775 | Y57: 0.0088873647 | Z57: 0.006072443 | AA57: 0.0053715104
B58: PCOR | C58: United States | D58: Software - Application | E58: Dec'25 | F58: 3.7 | G58: 146.1 | H58: 159.52 | I58: 172.21 | J58: 186.43 | K58: 202.05 | L58: 213.53 | M58: 228.54 | N58: 247.91 | O58: 260.04 | P58: 269.43 | Q58: 284.35 | R58: 295.89 | S58: 302.05 | T58: 310.63 | U58: 323.92 | V58: 338.85 | W58: 349.11 | X58: 0.035772584 | Y58: 0.033170707 | Z58: 0.034856267 | AA58: 0.036896782
B59: 6524 | C59: Japan | D59: N/A | E59: Sep'25 | F59: 1.1 | H59: 3951 | I59: 3954 | J59: 4004 | K59: 3943 | L59: 3772 | M59: 3521 | N59: 3502 | O59: 3332 | P59: 3117 | Q59: 3413 | R59: 4294 | S59: 4430 | T59: 3787 | U59: 3558 | V59: 4317 | W59: 4605 | X59: 0.043922905 | Y59: 0.0091057523 | Z59: 0.0014313274 | AA59: 0.010874969
B60: SBRA | C60: United States | D60: REIT - Healthcare Facilities | E60: Dec'25 | F60: 3.6 | G60: -30.94 | H60: 158 | I60: 153.43 | J60: 136.38 | K60: 84.14 | L60: 160.49 | M60: 160.51 | N60: 160.98 | O60: 162.64 | P60: 166.15 | Q60: 176.22 | R60: 178.22 | S60: 182.65 | T60: 183.76 | U60: 189.98 | V60: 191.26 | W60: 209.63 | X60: 0.025041238 | Y60: 0.019088576 | Z60: 0.017750915 | AA60: 0.036086404
B61: HWM | C61: United States | D61: Aerospace & Defense | E61: Dec'25 | F61: 3.5 | G61: 1285 | H61: 1324 | I61: 1393 | J61: 1433 | K61: 1513 | L61: 1603 | M61: 1648 | N61: 1658 | O61: 1731 | P61: 1824 | Q61: 1880 | R61: 1835 | S61: 1891 | T61: 1942 | U61: 2053 | V61: 2089 | W61: 2168 | X61: 0.015881561 | Y61: 0.022919979 | Z61: 0.032897293 | AA61: 0.034733542
B62: PACB | C62: United States | D62: Medical Devices | E62: Dec'25 | F62: 3.5 | G62: 36.02 | H62: 33.17 | I62: 35.47 | J62: 32.31 | K62: 27.35 | L62: 38.9 | M62: 47.57 | N62: 55.69 | O62: 58.36 | P62: 38.81 | Q62: 36.01 | R62: 39.97 | S62: 39.22 | T62: 37.15 | U62: 39.77 | V62: 38.44 | W62: 44.65 | X62: -0.010778521 | Y62: 0.024680013 | Z62: -0.0098007815 | AA62: 0.035127442
B63: 6856 | C63: Japan | D63: N/A | E63: Sep'25 | F63: 2.5 | G63: 52640 | H63: 70357 | I63: 55510 | J63: 59455 | K63: 70156 | L63: 85012 | M63: 65854 | N63: 65251 | O63: 69574 | P63: 89879 | Q63: 70252 | R63: 72468 | S63: 73159 | T63: 101490 | U63: 71877 | V63: 77066 | W63: 81302 | X63: 0.037974477 | Y63: 0.0051202228 | Z63: 0.014414064 | AA63: 0.025164405
B64: RYAN | C64: United States | D64: Insurance - Specialty | E64: Dec'25 | F64: 3.5 | G64: 378.38 | H64: 386.68 | I64: 490.23 | J64: 407.55 | K64: 427.4 | L64: 447.51 | M64: 573.02 | N64: 487.35 | O64: 518.72 | P64: 537.89 | Q64: 680.25 | R64: 588.13 | S64: 649.41 | T64: 676.13 | U64: 840.86 | V64: 739.55 | W64: 751.21 | X64: 0.05629398 | Y64: 0.061917869 | Z64: 0.054971266 | AA64: 0.035031573
B65: TWLO | C65: United States | D65: Software - Infrastructure | E65: Dec'25 | F65: 3.5 | G65: 842.74 | H65: 875.36 | I65: 943.35 | J65: 983.03 | K65: 1025 | L65: 1007 | M65: 1038 | N65: 1034 | O65: 1076 | P65: 1047 | Q65: 1083 | R65: 1134 | S65: 1195 | T65: 1172 | U65: 1228 | V65: 1300 | W65: 1366 | X65: 0.028033191 | Y65: 0.031631763 | Z65: 0.035102559 | AA65: 0.034933606
B66: NVMI | C66: United States | D66: Semiconductor Equipment & Materials | E66: Dec'25 | F66: 3.3 | G66: 121.52 | H66: 133.96 | I66: 141.63 | J66: 143.91 | K66: 151.24 | L66: 132.19 | M66: 122.7 | N66: 128.81 | O66: 134.22 | P66: 141.8 | Q66: 156.86 | R66: 178.97 | S66: 194.77 | T66: 213.36 | U66: 219.99 | V66: 224.61 | W66: 222.62 | X66: 0.10642475 | Y66: 0.084856713 | Z66: 0.056548836 | AA66: 0.03265981
B67: XP | C67: United States | D67: Capital Markets | E67: Dec'25 | F67: 3.3 | G67: 3202 | H67: 3073 | I67: 3352 | J67: 3493 | K67: 3027 | L67: 2971 | M67: 3396 | N67: 3997 | O67: 3879 | P67: 3872 | Q67: 4016 | R67: 4120 | S67: 4244 | T67: 4167 | U67: 4280 | V67: 4519 | W67: 4808 | X67: 0.018151612 | Y67: 0.015954554 | Z67: 0.02373446 | AA67: 0.032771644
B68: DXCM | C68: United States | D68: Medical Devices | E68: Dec'25 | F68: 3.2 | G68: 698.2 | H68: 628.8 | I68: 696.2 | J68: 769.6 | K68: 815.2 | L68: 741.5 | M68: 871.3 | N68: 975 | O68: 1035 | P68: 921 | Q68: 1004 | R68: 994.2 | S68: 1114 | T68: 1036 | U68: 1157 | V68: 1209 | W68: 1260 | X68: 0.028513339 | Y68: 0.036883468 | Z68: 0.049939552 | AA68: 0.032329495
B69: CBRE | C69: United States | D69: Real Estate Services | E69: Dec'25 | F69: 3.1 | G69: 8550 | H69: 7333 | I69: 7771 | J69: 7530 | K69: 8194 | L69: 7411 | M69: 7720 | N69: 7868 | O69: 8950 | P69: 7935 | Q69: 8391 | R69: 9036 | S69: 10404 | T69: 8910 | U69: 9754 | V69: 10258 | W69: 11629 | X69: 0.027260527 | Y69: 0.03709752 | Z69: 0.032070124 | AA69: 0.031149875
B70: 7718 | C70: Japan | D70: N/A | E70: Sep'25 | F70: 1.4 | G70: 17717 | H70: 18713 | I70: 17539 | J70: 21713 | K70: 22405 | L70: 25711 | M70: 21116 | N70: 21810 | O70: 17842 | P70: 17428 | Q70: 13920 | R70: 17066 | S70: 17062 | T70: 16946 | U70: 15629 | V70: 17972 | W70: 18041 | X70: -0.007361476 | Y70: 0.026294735 | Z70: 0.013582597 | AA70: 0.014480321
B71: DBD | C71: United States | D71: Software - Application | E71: Dec'25 | F71: 3.1 | G71: 1060 | H71: 829.8 | I71: 851.7 | J71: 810.4 | K71: 968.8 | L71: 858.1 | M71: 922.2 | N71: 943.4 | O71: 1037 | P71: 895.4 | Q71: 939.7 | R71: 927.1 | S71: 988.9 | T71: 841.1 | U71: 915.2 | V71: 945.2 | W71: 1104 | X71: -0.014475754 | Y71: -0.0066273534 | Z71: 0.0049287912 | AA71: 0.031189031
B72: 7976 | C72: Japan | D72: N/A | E72: Sep'25 | F72: 0.4 | G72: 13965 | H72: 17310 | I72: 18106 | J72: 15775 | K72: 16242 | L72: 18874 | M72: 18955 | N72: 17285 | O72: 16889 | P72: 21672 | Q72: 20073 | R72: 22361 | S72: 20478 | T72: 25908 | U72: 22588 | V72: 20657 | W72: 20836 | X72: 0.050080393 | Y72: 0.028315695 | Z72: -0.018656594 | AA72: 0.0039941538
B73: MTRN | C73: United States | D73: Other Industrial Metals & Mining | E73: Dec'25 | F73: 3.1 | G73: 397.23 | H73: 449.05 | I73: 445.3 | J73: 428.19 | K73: 434.58 | L73: 442.53 | M73: 398.55 | N73: 403.07 | O73: 421.04 | P73: 385.29 | Q73: 425.87 | R73: 436.72 | S73: 436.87 | T73: 420.33 | U73: 431.66 | V73: 444.81 | W73: 489.75 | X73: 0.020798338 | Y73: 0.0033666901 | Z73: 0.0046882787 | AA73: 0.030501768
B74: ES | C74: United States | D74: Utilities - Regulated Electric | E74: Dec'25 | F74: 3 | G74: 2482 | H74: 3471 | I74: 2573 | J74: 3216 | K74: 3030 | L74: 3796 | M74: 2629 | N74: 2791 | O74: 2694 | P74: 3333 | Q74: 2534 | R74: 3063 | S74: 2971 | T74: 4118 | U74: 2838 | V74: 3221 | W74: 3370 | X74: 0.065960844 | Y74: 0.023963424 | Z74: 0.012163202 | AA74: 0.030346821
B75: SPSC | C75: United States | D75: Software - Application | E75: Dec'25 | F75: 3 | G75: 102.76 | H75: 105.19 | I75: 109.18 | J75: 114.49 | K75: 122.02 | L75: 125.87 | M75: 130.42 | N75: 135.66 | O75: 144.97 | P75: 149.58 | Q75: 153.6 | R75: 163.69 | S75: 170.91 | T75: 181.55 | U75: 187.4 | V75: 189.9 | W75: 192.65 | X75: 0.050127003 | Y75: 0.050466592 | Z75: 0.037253927 | AA75: 0.029790616
B76: 8113 | C76: Japan | D76: N/A | E76: Sep'25 | F76: -0.4 | G76: 194918 | H76: 210845 | I76: 204373 | J76: 217240 | K76: 232935 | L76: 243474 | M76: 220839 | N76: 233099 | O76: 233493 | P76: 254359 | Q76: 236281 | R76: 251448 | S76: 234323 | T76: 266929 | U76: 227520 | V76: 236650 | W76: 230055 | X76: 0.012873677 | Y76: -0.0088586131 | Z76: -0.015096611 | AA76: -0.0044208647
B77: TRU | C77: United States | D77: Financial Data & Stock Exchanges | E77: Dec'25 | F77: 3 | G77: 789.8 | H77: 921.3 | I77: 948.3 | J77: 938.2 | K77: 902.1 | L77: 940.3 | M77: 968 | N77: 968.7 | O77: 954.3 | P77: 1021 | Q77: 1041 | R77: 1085 | S77: 1037 | T77: 1096 | U77: 1140 | V77: 1170 | W77: 1171 | X77: 0.01792543 | Y77: 0.023244893 | Z77: 0.01950436 | AA77: 0.030159802
B78: AEP | C78: United States | D78: Utilities - Regulated Electric | E78: Dec'25 | F78: 2.9 | G78: 4061 | H78: 4593 | I78: 4640 | J78: 5526 | K78: 4881 | L78: 4691 | M78: 4373 | N78: 5342 | O78: 4577 | P78: 5026 | Q78: 4579 | R78: 5420 | S78: 4696 | T78: 5463 | U78: 5087 | V78: 6010 | W78: 5315 | X78: 0.02215912 | Y78: 0.025200913 | Z78: 0.028549308 | AA78: 0.029121189
B79: TRUP | C79: United States | D79: Insurance - Property & Casualty | E79: Dec'25 | F79: 2.8 | G79: 194.38 | H79: 206 | I79: 219.41 | J79: 233.76 | K79: 246.01 | L79: 256.33 | M79: 270.57 | N79: 285.85 | O79: 295.86 | P79: 306.12 | Q79: 314.8 | R79: 327.46 | S79: 337.31 | T79: 341.98 | U79: 353.56 | V79: 366.92 | W79: 376.85 | X79: 0.027891638 | Y79: 0.029329197 | Z79: 0.029008094 | AA79: 0.028247498
B80: ZBRA | C80: United States | D80: Communication Equipment | E80: Dec'25 | F80: 2.7 | G80: 1467 | H80: 1432 | I80: 1468 | J80: 1378 | K80: 1503 | L80: 1405 | M80: 1214 | N80: 956 | O80: 1009 | P80: 1175 | Q80: 1217 | R80: 1255 | S80: 1334 | T80: 1308 | U80: 1293 | V80: 1320 | W80: 1475 | X80: 0.026701466 | Y80: 0.014861165 | Z80: 0.012524085 | AA80: 0.026831589
B81: IR | C81: United States | D81: Specialty Industrial Machinery | E81: Dec'25 | F81: 2.6 | G81: 1419 | H81: 1337 | I81: 1440 | J81: 1516 | K81: 1624 | L81: 1629 | M81: 1687 | N81: 1739 | O81: 1821 | P81: 1670 | Q81: 1805 | R81: 1861 | S81: 1899 | T81: 1717 | U81: 1888 | V81: 1955 | W81: 2091 | X81: 0.006496199 | Y81: 0.011397968 | Z81: 0.012763069 | AA81: 0.025740716
B82: 8804 | C82: Japan | D82: N/A | E82: Sep'25 | F82: 2.1 | G82: 60586 | H82: 117301 | I82: 121684 | J82: 93382 | K82: 53389 | L82: 81485 | M82: 118393 | N82: 61277 | O82: 58529 | P82: 137747 | Q82: 116195 | R82: 161421 | S82: 82280 | T82: 103828 | U82: 104397 | V82: 82128 | W82: 90040 | X82: -0.068159303 | Y82: -0.025441858 | Z82: -0.17545572 | AA82: 0.020824779
B83: ABNB | C83: United States | D83: Travel Services | E83: Dec'25 | F83: 2.5 | G83: 1532 | H83: 1509 | I83: 2104 | J83: 2884 | K83: 1902 | L83: 1818 | M83: 2484 | N83: 3397 | O83: 2218 | P83: 2142 | Q83: 2748 | R83: 3732 | S83: 2480 | T83: 2272 | U83: 3096 | V83: 4095 | W83: 2778 | X83: 0.011709602 | Y83: 0.030982906 | Z83: 0.03134715 | AA83: 0.024951855
B84: EXPE | C84: United States | D84: Travel Services | E84: Dec'25 | F84: 2.5 | G84: 2279 | H84: 2249 | I84: 3181 | J84: 3619 | K84: 2618 | L84: 2665 | M84: 3358 | N84: 3929 | O84: 2887 | P84: 2889 | Q84: 3558 | R84: 4060 | S84: 3184 | T84: 2988 | U84: 3786 | V84: 4412 | W84: 3547 | X84: 0.0072310277 | Y84: 0.01653372 | Z84: 0.025110572 | AA84: 0.02526096
B85: FLO | C85: United States | D85: Packaged Foods | E85: Dec'25 | F85: 2.4 | G85: 983.49 | H85: 1436 | I85: 1129 | J85: 1158 | K85: 1083 | L85: 1534 | M85: 1228 | N85: 1199 | O85: 1129 | P85: 1577 | Q85: 1225 | R85: 1191 | S85: 1111 | T85: 1554 | U85: 1243 | V85: 1227 | W85: 1233 | X85: -0.0045062696 | Y85: 0.0035426097 | Z85: 0.0070602079 | AA85: 0.02375852
B86: VRTX | C86: United States | D86: Biotechnology | E86: Dec'25 | F86: 2.4 | G86: 2073 | H86: 2098 | I86: 2196 | J86: 2334 | K86: 2303 | L86: 2375 | M86: 2493 | N86: 2484 | O86: 2518 | P86: 2691 | Q86: 2646 | R86: 2772 | S86: 2912 | T86: 2770 | U86: 2965 | V86: 3076 | W86: 3190 | X86: 0.0071681336 | Y86: 0.028738739 | Z86: 0.026622296 | AA86: 0.023714066
B87: BFAM | C87: United States | D87: Personal Services | E87: Dec'25 | F87: 2.1 | G87: 462.66 | H87: 460.41 | I87: 490.34 | J87: 540.22 | K87: 529.52 | L87: 553.61 | M87: 603.22 | N87: 645.79 | O87: 615.65 | P87: 622.71 | Q87: 670.06 | R87: 719.1 | S87: 674.15 | T87: 665.53 | U87: 731.57 | V87: 802.81 | W87: 733.7 | X87: 0.015941802 | Y87: 0.022540713 | Z87: 0.029999821 | AA87: 0.020719818
B88: CAE | C88: United States | D88: Aerospace & Defense | E88: Jun'26 | F88: 2.1 | G88: 814.9 | H88: 848.7 | I88: 955 | J88: 933.3 | K88: 0 | L88: 969.9 | M88: 1197 | N88: 1012 | O88: 1050 | P88: 1095 | Q88: 0 | R88: 1073 | S88: 1137 | T88: 1223 | U88: 1275 | V88: 1099 | W88: 1237 | X88: 0.038729198 | Y88: 0.37139528 | Z88: 0.0055225149 | AA88: 0.021123785
B89: MORN | C89: United States | D89: Financial Data & Stock Exchanges | E89: Dec'25 | F89: 2.1 | G89: 462.2 | H89: 457 | I89: 470.4 | J89: 468.2 | K89: 475 | L89: 479.7 | M89: 504.7 | N89: 515.5 | O89: 538.7 | P89: 542.8 | Q89: 571.9 | R89: 569.4 | S89: 591 | T89: 581.9 | U89: 605.1 | V89: 617.4 | W89: 641.1 | X89: 0.017186058 | Y89: 0.01434621 | Z89: 0.020448155 | AA89: 0.020915087
B90: 9449 | C90: Japan | D90: N/A | E90: Sep'25 | F90: 0.6 | G90: 56471 | H90: 64495 | I90: 56065 | J90: 69491 | K90: 57578 | L90: 62562 | M90: 65593 | N90: 64450 | O90: 62502 | P90: 66098 | Q90: 68861 | R90: 67619 | S90: 69624 | T90: 71303 | U90: 71547 | V90: 71004 | W90: 71264 | X90: 0.019121829 | Y90: 0.0096825242 | Z90: 0.012085272 | AA90: 0.0057852814
B91: BAX | C91: United States | D91: Medical Instruments & Supplies | E91: Dec'25 | F91: 2 | G91: 3514 | H91: 3558 | I91: 3594 | J91: 3609 | K91: 3745 | L91: 3513 | M91: 1522 | N91: 2599 | O91: 2726 | P91: 2490 | Q91: 2694 | R91: 2699 | S91: 2753 | T91: 2625 | U91: 2810 | V91: 2835 | W91: 2974 | X91: 0.012692742 | Y91: 0.010769659 | Z91: 0.012491963 | AA91: 0.020048988
B92: 9722 | C92: Japan | D92: N/A | E92: Sep'25 | F92: 0.5 | G92: 7293 | H92: 9212 | I92: 7959 | J92: 10349 | K92: 11029 | L92: 14412 | M92: 13163 | N92: 15999 | O92: 16394 | P92: 18991 | Q92: 16985 | R92: 18897 | S92: 18296 | T92: 22033 | U92: 19978 | V92: 21190 | W92: 18691 | X92: 0.041574984 | Y92: 0.039272546 | Z92: 0.028950558 | AA92: 0.0048468042
B93: BDC | C93: United States | D93: Communication Equipment | E93: Dec'25 | F93: 2 | G93: 611.96 | H93: 610.37 | I93: 666.55 | J93: 670.49 | K93: 659.07 | L93: 641.79 | M93: 692.25 | N93: 626.81 | O93: 551.24 | P93: 535.68 | Q93: 604.34 | R93: 654.93 | S93: 666.04 | T93: 624.86 | U93: 671.99 | V93: 698.22 | W93: 720.12 | X93: 0.036237449 | Y93: 0.026527643 | Z93: 0.01653666 | AA93: 0.020322347
B94: FRT | C94: United States | D94: REIT - Retail | E94: Dec'25 | F94: 2 | G94: 255.49 | H94: 256.97 | I94: 266.91 | J94: 275.32 | K94: 280.35 | L94: 273.58 | M94: 282.34 | N94: 287.92 | O94: 292.19 | P94: 291.36 | Q94: 296.96 | R94: 304.52 | S94: 309.62 | T94: 309.33 | U94: 312.43 | V94: 322.86 | W94: 334.36 | X94: 0.014944364 | Y94: 0.01267586 | Z94: 0.014839388 | AA94: 0.019725092
B95: MLCO | C95: United States | D95: Resorts & Casinos | E95: Dec'25 | F95: 2 | G95: 480.61 | H95: 474.95 | I95: 296.11 | J95: 241.84 | K95: 337.09 | L95: 716.48 | M95: 947.94 | N95: 1017 | O95: 1094 | P95: 1112 | Q95: 1160 | R95: 1175 | S95: 1191 | T95: 1232 | U95: 1328 | V95: 1310 | W95: 1293 | X95: 0.025873221 | Y95: 0.035308953 | Z95: 0.027405603 | AA95: 0.02015412
B96: BIRK | C96: United States | D96: Footwear & Accessories | E96: Mar'26 | F96: 1.9 | G96: 271.28 | H96: 271.28 | I96: 378.67 | J96: 321.61 | K96: 248.49 | L96: 395.68 | M96: 473.2 | N96: 374.54 | O96: 302.92 | P96: 481.24 | Q96: 564.76 | R96: 455.76 | S96: 361.72 | T96: 574.33 | U96: 635.04 | V96: 526.34 | W96: 401.9 | X96: 0.049954923 | Y96: 0.035920003 | Z96: 0.034822508 | AA96: 0.019156778
B97: AC | C97: France | D97: N/A | E97: H1 2025 | F97: 4.3 | N97: 704 | O97: 824 | P97: 1380 | Q97: 1725 | R97: 0 | S97: 2402 | T97: 0 | U97: 2677 | V97: 2929 | W97: 2745 | X97: -0.25059016 | Y97: 0.23067604 | Z97: 0.57668832 | AA97: 0.042832168
B98: QSR | C98: United States | D98: Restaurants | E98: Dec'25 | F98: 1.8 | G98: 1546 | H98: 1451 | I98: 1639 | J98: 1726 | K98: 1689 | L98: 1590 | M98: 1775 | N98: 1837 | O98: 1820 | P98: 1739 | Q98: 2080 | R98: 2291 | S98: 2296 | T98: 2109 | U98: 2410 | V98: 2449 | W98: 2466 | X98: 0.044016179 | Y98: 0.037602552 | Z98: 0.017351197 | AA98: 0.018350604
B99: PHIN | C99: United States | D99: Auto Parts | E99: Dec'25 | F99: 1.6 | H99: 842 | I99: 796 | J99: 859 | K99: 851 | L99: 835 | M99: 887 | N99: 896 | O99: 882 | P99: 863 | Q99: 868 | R99: 839 | S99: 833 | T99: 796 | U99: 890 | V99: 908 | W99: 889 | X99: -0.01968851 | Y99: 0.0065947242 | Z99: 0.020547945 | AA99: 0.016340823
B100: CHKP | C100: United States | D100: Software - Infrastructure | E100: Dec'25 | F100: 1.5 | G100: 599.1 | H100: 542.7 | I100: 571.1 | J100: 577.6 | K100: 638.5 | L100: 566.2 | M100: 588.7 | N100: 596.3 | O100: 663.5 | P100: 598.8 | Q100: 627.4 | R100: 635.1 | S100: 703.7 | T100: 637.8 | U100: 665.2 | V100: 677.5 | W100: 744.9 | X100: 0.015204678 | Y100: 0.014516129 | Z100: 0.016049663 | AA100: 0.01534908
B101: AHL | C101: United States | D101: Insurance - Property & Casualty | E101: Sep'25 | F101: 0.4 | G101: 689.2 | H101: 689.2 | I101: 644.75 | J101: 644.75 | K101: 669.1 | L101: 748.8 | M101: 717.4 | N101: 712.1 | O101: 741.4 | P101: 733.8 | Q101: 741.5 | R101: 761.8 | S101: 784 | T101: 870.8 | U101: 778.3 | V101: 746.1 | W101: 796.4 | X101: 0.045347721 | Y101: 0.011652576 | Z101: -0.0049140818 | AA101: 0.0039003523
...

Sheet Operating Income
B2: Ticker | C2: Country | D2: Industry | E2: Latest_Date | F2: Growth_Rate | G2: 4Q21 | H2: 1Q22 | I2: 2Q22 | J2: 3Q22 | K2: 4Q22 | L2: 1Q23 | M2: 2Q23 | N2: 3Q23 | O2: 4Q23 | P2: 1Q24 | Q2: 2Q24 | R2: 3Q24 | S2: 4Q24 | T2: 1Q25 | U2: 2Q25 | V2: 3Q25 | W2: 4Q25 | X2: 1Q25 | Y2: 2Q25 | Z2: 3Q25 | AA2: 4Q25
B3: WYFI | C3: United States | D3: Software - Application | E3: Sep'25 | F3: 143.4 | Q3: 0.93 | R3: 2.41 | S3: -0.85 | T3: -1.55 | U3: 2.04 | V3: -9.16 | W3: -14.5 | Y3: 1.1808511 | Z3: -5.6439024 | AA3: 1.4338235
B4: HCC | C4: United States | D4: Coking Coal | E4: Dec'25 | F4: 520.5 | G4: 191.74 | H4: 193.54 | I4: 378.82 | J4: 131.54 | K4: 120.98 | L4: 213.88 | M4: 93.98 | N4: 108.1 | O4: 133.75 | P4: 149.08 | Q4: 70.9 | R4: 39.12 | S4: -3.69 | T4: -17.38 | U4: 7.72 | V4: 20.72 | W4: 34.67 | X4: -0.65173642 | Y4: -0.71028668 | Z4: -0.71400854 | AA4: 5.2048847
B5: ALNY | C5: United States | D5: Biotechnology | E5: Dec'25 | F5: 89.5 | G5: -194.56 | H5: -146.73 | I5: -191.69 | J5: -258.04 | K5: -188.61 | L5: -149.81 | M5: -229.83 | N5: 213.87 | O5: -116.4 | P5: -43.44 | Q5: 48.61 | R5: -76.91 | S5: -105.16 | T5: 18.08 | U5: -16.2 | V5: 367.98 | W5: 131.72 | X5: -0.3477671 | Y5: 0.56170914 | Z5: -2.4690049 | AA5: 0.89489989
B6: KEY | C6: United States | D6: Banks - Regional | E6: Dec'25 | F6: 85.4 | G6: 768 | H6: 537 | I6: 662 | J6: 664 | K6: 470 | L6: 392 | M6: 344 | N6: 367 | O6: 57 | P6: 278 | Q6: 335 | R6: -506 | S6: -413 | T6: 515 | U6: 539 | V6: 602 | W6: 648 | X6: -0.7745098 | Y6: -2.9565217 | Z6: 8.2074074 | AA6: 0.85358005
B7: HR | C7: United States | D7: REIT - Healthcare Facilities | E7: Dec'25 | F7: 58.9 | G7: 20.75 | H7: 18.71 | I7: 20.39 | J7: 18.42 | K7: 21.36 | L7: 10.4 | M7: 13.41 | N7: 13.01 | O7: 13.69 | P7: 12 | Q7: 10.55 | R7: 11.33 | S7: -0.54 | T7: 18.51 | U7: 15.91 | V7: 24.86 | W7: 34.08 | X7: 0.19526095 | Y7: 0.13450439 | Z7: 0.29927007 | AA7: 0.58937692
B8: NN | C8: United States | D8: Software - Infrastructure | E8: Sep'25 | F8: 6.1 | G8: -7.03 | H8: -14.16 | I8: -16.05 | J8: -17.02 | K8: -17.94 | L8: -13.64 | M8: -13.95 | N8: -15.03 | O8: -14.62 | P8: -19.93 | Q8: -16.15 | R8: -15.33 | S8: -13.85 | T8: -14.77 | U8: -17 | V8: -17.24 | W8: -17.67 | X8: -0.079068342 | Y8: 0.014143095 | Z8: 0.031337162 | AA8: 0.060769965
B9: ELVA | C9: United States | D9: Electrical Equipment & Parts | E9: Dec'25 | F9: 42.8 | G9: -1.36 | H9: -1.57 | I9: -1.36 | J9: -1.09 | K9: -3.24 | L9: -0.8 | M9: -0.68 | N9: 0.9 | O9: 1.8 | P9: -0.1 | Q9: 0.7 | R9: -0.58 | S9: 0.71 | T9: -0.19 | U9: 1.4 | V9: 1.96 | W9: 2.37 | X9: -0.12328767 | Y9: 1.09375 | Z9: 1.8955224 | AA9: 0.42783505
B10: TWLO | C10: United States | D10: Software - Infrastructure | E10: Dec'25 | F10: 42 | G10: -276.18 | H10: -217.15 | I10: -310.1 | J10: -286.7 | K10: -211.76 | L10: -118.12 | M10: -114.5 | N10: -102.12 | O10: -50.01 | P10: -43.5 | Q10: -19.04 | R10: -4.89 | S10: 13.67 | T10: 23.08 | U10: 36.99 | V10: 40.95 | W10: 61.83 | X10: -1.2384673 | Y10: 4.3705148 | Z10: 0.66579521 | AA10: 0.41991455
B11: DRUG | C11: United States | D11: Biotechnology | E11: Mar'26 | F11: 38 | G11: -4.72 | H11: -4.38 | I11: -2.65 | J11: -2.97 | K11: -2.26 | L11: -1.96 | M11: -1.43 | N11: -1.55 | O11: -1.62 | P11: -0.47 | Q11: 0.25 | R11: -0.77 | S11: -1.58 | T11: -3.24 | U11: -3.03 | V11: -5.76 | W11: -6.75 | X11: 1.077821 | Y11: 0.61423221 | Z11: 0.57888631 | AA11: 0.37986774
B12: PINS | C12: United States | D12: Internet Content & Information | E12: Dec'25 | F12: 30.2 | G12: 179.45 | H12: -3.67 | I12: -34.51 | J12: -69.38 | K12: 15.27 | L12: -243.69 | M12: -73.24 | N12: -5 | O12: 196.25 | P12: -54.42 | Q12: -21.44 | R12: 28.73 | S12: 226.94 | T12: -35.48 | U12: -4.33 | V12: 58.52 | W12: 301.17 | X12: 0.10533341 | Y12: 0.08608805 | Z12: 0.13800612 | AA12: 0.3021779
B13: AEM | C13: United States | D13: Gold | E13: Dec'25 | F13: 24.8 | G13: 263.1 | H13: 406.78 | I13: 523.08 | J13: 225.88 | K13: 472.8 | L13: 445.88 | M13: 526.74 | N13: 315.01 | O13: 164.03 | P13: 532.71 | Q13: 792.35 | R13: 876.22 | S13: 804.98 | T13: 1236 | U13: 1650 | V13: 1625 | W13: 2123 | X13: 0.23394184 | Y13: 0.23120055 | Z13: 0.16394728 | AA13: 0.24793547
B14: TRUP | C14: United States | D14: Insurance - Property & Casualty | E14: Dec'25 | F14: 20.7 | G14: -5.74 | H14: -9.05 | I14: -12.73 | J14: -11.66 | K14: -8.94 | L14: -20.31 | M14: -12.95 | N14: -3.49 | O14: 0.49 | P14: -6.03 | Q14: -5.42 | R14: 1.78 | S14: 5.65 | T14: -1.17 | U14: 2.31 | V14: 5.86 | W14: 8.27 | X14: -1.2089552 | Y14: 9.202381 | Z14: 0.47607935 | AA14: 0.20711462
B15: TOST | C15: United States | D15: Software - Infrastructure | E15: Dec'25 | F15: 20.6 | G15: -111 | H15: -101 | I15: -99 | J15: -85 | K15: -99 | L15: -92 | M15: -80 | N15: -59 | O15: -42 | P15: -15 | Q15: 9 | R15: 34 | S15: 37 | T15: 50 | U15: 81 | V15: 84 | W15: 89 | X15: 1 | Y15: 0.55384615 | Z15: 0.24752475 | AA15: 0.20634921
... B68: BN | C68: United States | D68: Asset Management | E68: Dec'25 | F68: 0.7 | G68: 4020 | H68: 3997 | I68: 3953 | J68: 4553 | K68: 4246 | L68: 3892 | M68: 4140 | N68: 4146 | O68: 4336 | P68: 4530 | Q68: 4704 | R68: 5443 | S68: 6046 | T68: 4995 | U68: 4615 | V68: 4810 | W68: 6186 | X68: 0.022438836 | Y68: -0.0042004908 | Z68: -0.030001422 | AA68: 0.0068406137
B69: PHIN | C69: United States | D69: Auto Parts | E69: Dec'25 | F69: 0.6 | H69: 82 | I69: 77 | J69: 127 | K69: 101 | L69: 80 | M69: 100 | N69: 75 | O69: 79 | P69: 90 | Q69: 76 | R69: 80 | S69: 72 | T69: 79 | U69: 97 | V69: 92 | W69: 74 | X69: -0.034591195 | Y69: 0.068403909 | Z69: 0.036585366 | AA69: 0.0058823529
B70: BLX | C70: United States | D70: Banks - Regional | E70: Sep'25 | F70: 0.9 | G70: 15.73 | H70: 20.07 | I70: 11.12 | J70: 23.02 | K70: 26.87 | L70: 31.03 | M70: 36.95 | N70: 37.07 | O70: 45.75 | P70: 46.39 | Q70: 51.27 | R70: 50.12 | S70: 52.99 | T70: 51.49 | U70: 51.73 | V70: 64.18 | W70: 54.97 | X70: 0.025402202 | Y70: 0.0022344198 | Z70: 0.068143266 | AA70: 0.0089840737
B71: BIO | C71: United States | D71: Medical Devices | E71: Sep'25 | F71: 0.8 | G71: 155.8 | H71: 185.19 | I71: 146.41 | J71: 122.79 | K71: 94.55 | L71: 123.07 | M71: 61.91 | N71: 89.92 | O71: 91.15 | P71: 94.92 | Q71: 51.7 | R71: 100.5 | S71: 66 | T71: 57.93 | U71: 56.9 | V71: 79.6 | W71: 68 | X71: -0.11813362 | Y71: 0.01883171 | Z71: -0.07428998 | AA71: 0.0076796068
B72: IR | C72: United States | D72: Specialty Industrial Machinery | E72: Dec'25 | F72: 0.5 | G72: 159.3 | H72: 175.8 | I72: 211.6 | J72: 203.6 | K72: 288.4 | L72: 263.3 | M72: 293.6 | N72: 331.4 | O72: 361.6 | P72: 317.9 | Q72: 360.8 | R72: 385.2 | S72: 390.8 | T72: 326.2 | U72: 365.3 | V72: 400.3 | W72: 397.8 | X72: 0.0057056438 | Y72: 0.0030758715 | Z72: 0.010289608 | AA72: 0.0047214353
B73: BDC | C73: United States | D73: Communication Equipment | E73: Dec'25 | F73: 0.4 | G73: 85.84 | H73: 77.7 | I73: 84.17 | J73: 96.42 | K73: 81.78 | L73: 86.03 | M73: 93.24 | N73: 83.7 | O73: 63.01 | P73: 53.25 | Q73: 69.14 | R73: 75.64 | S73: 85.04 | T73: 72.19 | U73: 78.87 | V73: 75.89 | W73: 86.35 | X73: 0.066909245 | Y73: 0.032217476 | Z73: 0.00080195034 | AA73: 0.0041988525
B74: PSA | C74: United States | D74: REIT - Industrial | E74: Dec'25 | F74: 0.3 | G74: 481.93 | H74: 487.06 | I74: 552.33 | J74: 569 | K74: 597.18 | L74: 567.85 | M74: 604.41 | N74: 597.56 | O74: 562.39 | P74: 528.57 | Q74: 565.82 | R74: 559.87 | S74: 551.23 | T74: 543.47 | U74: 570.39 | V74: 576.38 | W74: 557.23 | X74: 0.0067558683 | Y74: 0.002058197 | Z74: 0.0074203581 | AA74: 0.0026768148
B75: LECO | C75: United States | D75: Tools & Accessories | E75: Dec'25 | F75: 0.1 | G75: 118.35 | H75: 161.31 | I75: 169.56 | J75: 156.53 | K75: 134.68 | L75: 162.41 | M75: 179.15 | N75: 190.07 | O75: 171.19 | P75: 173.03 | Q75: 182.78 | R75: 166.65 | S75: 189.83 | T75: 161.11 | U75: 181.49 | V75: 184.45 | W75: 190.3 | X75: -0.016734757 | Y75: -0.0018418836 | Z75: 0.025462036 | AA75: 0.00065561879
B76: FTS | C76: United States | D76: Utilities - Regulated Electric | E76: Dec'25 | F76: 0 | G76: 654 | H76: 700 | I76: 639 | J76: 716 | K76: 777 | L76: 846 | M76: 670 | N76: 836 | O76: 794 | P76: 894 | Q76: 756 | R76: 833 | S76: 809 | T76: 972 | U76: 820 | V76: 890 | W76: 810 | X76: 0.023693803 | Y76: 0.018991098 | Z76: 0.016598719 | AA76: 0.00028645087
B77: FLO | C77: United States | D77: Packaged Foods | E77: Dec'25 | F77: -0.1 | G77: 59.53 | H77: 122.27 | I77: 87.25 | J77: 87.69 | K77: 69.73 | L77: 107.49 | M77: 98.19 | N77: 85.27 | O77: 59.35 | P77: 111.33 | Q77: 106.75 | R77: 96.1 | S77: 65.41 | T77: 112.86 | U77: 97.94 | V77: 78.33 | W77: 64.99 | X77: 0.0040306647 | Y77: -0.023116079 | Z77: -0.047729043 | AA77: -0.0011846336
B78: ETR | C78: United States | D78: Utilities - Regulated Electric | E78: Sep'25 | F78: 0.1 | G78: 828.85 | H78: 276.17 | I78: 568.05 | J78: -79.61 | K78: 924 | L78: 503.22 | M78: 469.31 | N78: 763.46 | O78: 1191 | P78: 272.88 | Q78: 386.43 | R78: 635.52 | S78: 1141 | T78: 659.92 | U78: 708.63 | V78: 849.83 | W78: 1146 | X78: 0.1588945 | Y78: 0.11413916 | Z78: 0.068141568 | AA78: 0.0014883699
B79: TOP | C79: United States | D79: Capital Markets | E79: H1 2026 | F79: -0.11490126 | G79: 0.91 | I79: 2.67 | K79: 1.84 | M79: 1.59 | O79: 3.59 | Q79: -2.6 | S79: -0.45 | U79: -5.12 | W79: 0.19 | X79: -0.80888031 | Y79: -4.0808081 | Z79: 0.82622951 | AA79: -0.11490126
B80: GTES | C80: United States | D80: Specialty Industrial Machinery | E80: Dec'25 | F80: -0.5 | G80: 77.4 | H80: 71.6 | I80: 119 | J80: 111.3 | K80: 88 | L80: 105.5 | M80: 133.7 | N80: 130.6 | O80: 122.6 | P80: 119.2 | Q80: 136.7 | R80: 121.3 | S80: 118.3 | T80: 129.6 | U80: 132.8 | V80: 127.8 | W80: 115.8 | X80: 0.0209889 | Y80: -0.0077090334 | Z80: 0.012948207 | AA80: -0.0049164208
B81: AGIO | C81: United States | D81: Biotechnology | E81: Dec'25 | F81: -0.7 | G81: -104.83 | H81: -101.15 | I81: -97.64 | J81: -91.09 | K81: -99.17 | L81: -90.61 | M81: -93.7 | N81: -100.9 | O81: -106.28 | P81: -92.07 | Q81: -105.82 | R81: -102.81 | S81: -125.04 | T81: -106.63 | U81: -127.06 | V81: -116.87 | W81: -121.58 | X81: 0.034199277 | Y81: 0.048239836 | Z81: 0.030463232 | AA81: -0.007275021
B82: ZBRA | C82: United States | D82: Communication Equipment | E82: Dec'25 | F82: -0.7 | G82: 244 | H82: 216 | I82: 243 | J82: 205 | K82: 272 | L82: 235 | M82: 210 | N82: 48 | O82: 92 | P82: 170 | Q82: 171 | R82: 196 | S82: 228 | T82: 198 | U82: 187 | V82: 193 | W82: 222 | X82: 0.036601307 | Y82: 0.020176545 | Z82: -0.0037082818 | AA82: -0.0074441687
B83: AMAT | C83: United States | D83: Semiconductor Equipment & Materials | E83: Mar'26 | F83: -0.9 | G83: 1972 | H83: 1894 | I83: 1924 | J83: 1994 | K83: 1970 | L83: 1911 | M83: 1802 | N83: 1971 | O83: 1967 | P83: 1912 | Q83: 1942 | R83: 2046 | S83: 2175 | T83: 2169 | U83: 2233 | V83: 1934 | W83: 2096 | X83: 0.031826625 | Y83: 0.034925588 | Z83: -0.012988519 | AA83: -0.0092821055
B84: RARE | C84: United States | D84: Biotechnology | E84: Dec'25 | F84: -1.5 | G84: -102.56 | H84: -136.63 | I84: -141.59 | J84: -225.07 | K84: -145.63 | L84: -154.11 | M84: -147.96 | N84: -145.1 | O84: -122.05 | P84: -165.35 | Q84: -116.36 | R84: -131.99 | S84: -122.28 | T84: -142.94 | U84: -107.89 | V84: -170.89 | W84: -114 | X84: -0.041811262 | Y84: -0.016492396 | Z84: 0.077014453 | AA84: -0.015220588
B85: TRN | C85: United States | D85: Railroads | E85: Dec'25 | F85: -1.8 | G85: 53.4 | H85: 29.3 | I85: 46.1 | J85: 53.1 | K85: 53.1 | L85: 53.3 | M85: 66.9 | N85: 92.7 | O85: 111.6 | P85: 112.4 | Q85: 117.7 | R85: 109 | S85: 92.7 | T85: 92.2 | U85: 84 | V85: 96.2 | W85: 86 | X85: -0.046780917 | Y85: -0.081875607 | Z85: -0.033871395 | AA85: -0.018351137
B86: VNT | C86: United States | D86: Scientific & Technical Instruments | E86: Dec'25 | F86: -1.8 | G86: 174 | H86: 134.8 | I86: 136.5 | J86: 150.2 | K86: 167.9 | L86: 133.8 | M86: 120.6 | N86: 142.6 | O86: 171.6 | P86: 146.8 | Q86: 114.1 | R86: 131.5 | S86: 162.8 | T86: 134.4 | U86: 136.4 | V86: 142.4 | W86: 152.7 | X86: -0.022334294 | Y86: 0.041083272 | Z86: 0.019288621 | AA86: -0.017534722
B87: DBD | C87: United States | D87: Software - Application | E87: Dec'25 | F87: -2.3 | G87: 68.2 | H87: -29 | I87: -7.2 | J87: 26.7 | K87: 28.8 | L87: 14.4 | M87: 15.8 | N87: 50 | O87: 69.8 | P87: 60.5 | Q87: 81.3 | R87: 80.3 | S87: 89.1 | T87: 49.6 | U87: 72.5 | V87: 86.4 | W87: 82.4 | X87: -0.035025707 | Y87: -0.029304029 | Z87: 0.020926244 | AA87: -0.022513441
B88: RYAN | C88: United States | D88: Insurance - Specialty | E88: Dec'25 | F88: -2.3 | G88: 68.47 | H88: 53.5 | I88: 115.53 | J88: 65.46 | K88: 74.54 | L88: 68.04 | M88: 135.25 | N88: 81.43 | O88: 97.04 | P88: 103.48 | Q88: 177.45 | R88: 107.49 | S88: 120.19 | T88: 104.27 | U88: 200.48 | V88: 134.54 | W88: 107.52 | X88: 0.001553253 | Y88: 0.045210051 | Z88: 0.050804801 | AA88: -0.022646028
B89: CALY | C89: United States | D89: Leisure | E89: Sep'25 | F89: -1.9 | G89: 76 | H89: -67.1 | I89: 94.3 | J89: 129 | K89: 68.2 | L89: -29.2 | M89: 80.5 | N89: 116 | O89: 73.8 | P89: -18.6 | Q89: 66.9 | R89: 109.3 | S89: 33.7 | T89: -8.4 | U89: 81.2 | V89: 116.4 | W89: 29.5 | X89: 0.053319394 | Y89: 0.070967742 | Z89: 0.032900834 | AA89: -0.01884253
B90: CHKP | C90: United States | D90: Software - Infrastructure | E90: Dec'25 | F90: -2.5 | G90: 245.9 | H90: 200.2 | I90: 208.8 | J90: 221.3 | K90: 254 | L90: 199.8 | M90: 221.4 | N90: 226.1 | O90: 251.8 | P90: 193.9 | Q90: 209.3 | R90: 218.5 | S90: 254.3 | T90: 195.5 | U90: 203.6 | V90: 199.1 | W90: 232.9 | X90: 0.001826484 | Y90: -0.0064949863 | Z90: -0.022250258 | AA90: -0.025102639
B91: BNT | C91: United States | D91: Insurance - Diversified | E91: Dec'25 | F91: -2.9 | G91: -41 | H91: 154 | I91: -15 | J91: 164 | K91: 206 | L91: 31 | M91: 389 | N91: 185 | O91: 251 | P91: 421 | Q91: 348 | R91: 480 | S91: 326 | T91: 265 | U91: 774 | V91: 994 | W91: 257 | X91: -0.099047619 | Y91: 0.30021142 | Z91: 0.27859079 | AA91: -0.029249682
... B93: YELP | C93: United States | D93: Internet Content & Information | E93: Dec'25 | F93: -3 | G93: 19.59 | H93: -4.46 | I93: 16 | J93: 23.89 | K93: 33.38 | L93: -3.03 | M93: 29.74 | N93: 41.87 | O93: 45.02 | P93: 11.22 | Q93: 39.75 | R93: 52.57 | S93: 54.7 | T93: 30 | U93: 53.35 | V93: 52.66 | W93: 48.89 | X93: 0.11868049 | Y93: 0.076827477 | Z93: 0.00047214353 | AA93: -0.030465104
B94: FMCC | C94: United States | D94: Mortgage Finance | E94: FY 2025 | F94: -3.4 | S94: 15199 | T94: 11604 | U94: 13199 | V94: 14778 | W94: 13361 | AA94: -0.033552391
B95: EEFT | C95: United States | D95: Software - Infrastructure | E95: Dec'25 | F95: -3.9 | G95: 67.59 | H95: 36.7 | I95: 101.1 | J95: 168.5 | K95: 79.1 | L95: 45.6 | M95: 122.6 | N95: 167 | O95: 97.4 | P95: 64 | Q95: 134.3 | R95: 182.2 | S95: 122.7 | T95: 79.7 | U95: 163.1 | V95: 195 | W95: 101 | X95: 0.031200318 | Y95: 0.055502024 | Z95: 0.023370458 | AA95: -0.038715433
B96: OGN | C96: United States | D96: Drug Manufacturers - General | E96: Dec'25 | F96: -4.4 | G96: 418 | H96: 539 | I96: 468 | J96: 419 | K96: 290 | L96: 394 | M96: 389 | N96: 232 | O96: 394 | P96: 414 | Q96: 386 | R96: 390 | S96: 294 | T96: 334 | U96: 336 | V96: 370 | W96: 235 | X96: -0.053908356 | Y96: -0.035612536 | Z96: -0.014771049 | AA96: -0.044227886
B97: CROX | C97: United States | D97: Footwear & Accessories | E97: Dec'25 | F97: -5.8 | G97: 160.29 | H97: 167.18 | I97: 282.26 | J97: 264.06 | K97: 172.1 | L97: 234.93 | M97: 318.49 | N97: 273.85 | O97: 219.2 | P97: 250.51 | Q97: 325.74 | R97: 269.83 | S97: 200.92 | T97: 222.97 | U97: 310.6 | V97: 207.66 | W97: 146.4 | X97: -0.026303725 | Y97: -0.014851 | Z97: -0.061902581 | AA97: -0.057867643
B98: ABNB | C98: United States | D98: Travel Services | E98: Dec'25 | F98: -6 | G98: 76.17 | H98: -5 | I98: 458 | J98: 1203 | K98: 237 | L98: -5 | M98: 523 | N98: 1496 | O98: -496 | P98: 101 | Q98: 497 | R98: 1525 | S98: 430 | T98: 38 | U98: 612 | V98: 1625 | W98: 269 | X98: -0.024676851 | Y98: 0.046184739 | Z98: 0.038387716 | AA98: -0.059519409
B99: WYNN | C99: United States | D99: Resorts & Casinos | E99: Dec'25 | F99: -6.2 | G99: -85.72 | H99: -51.87 | I99: -26.63 | J99: -49.99 | K99: -42.68 | L99: 171.72 | M99: 264.54 | N99: 268.09 | O99: 354.23 | P99: 379.44 | Q99: 245.06 | R99: 155.14 | S99: 350.5 | T99: 279.19 | U99: 274.7 | V99: 310.49 | W99: 274.71 | X99: -0.088705824 | Y99: 0.028779773 | Z99: 0.14662162 | AA99: -0.062384762
B100: SBRA | C100: United States | D100: REIT - Healthcare Facilities | E100: Dec'25 | F100: -7.2 | G100: -120.18 | H100: 63.76 | I100: 61 | J100: 37.67 | K100: -20.59 | L100: 49.56 | M100: 57.68 | N100: 57.83 | O100: 53.56 | P100: 57.49 | Q100: 67.11 | R100: 64.64 | S100: 68.16 | T100: 67.78 | U100: 73.01 | V100: 59.41 | W100: 48.83 | X100: 0.03997669 | Y100: 0.02204042 | Z100: -0.019116196 | AA100: -0.072030109
B101: PACB | C101: United States | D101: Medical Devices | E101: Dec'25 | F101: -8 | G101: -63.13 | H101: -78.59 | I101: -73.41 | J101: -70.34 | K101: -78.78 | L101: -79 | M101: -71.2 | N101: -73.78 | O101: -86.39 | P101: -81.43 | Q101: -81.65 | R101: -62.91 | S101: -89.38 | T101: -432.63 | U101: -44.83 | V101: -38.8 | W101: -41.19 | X101: 1.1136126 | Y101: -0.05523801 | Z101: -0.038285034 | AA101: -0.079568721
B102: FROG | C102: United States | D102: Software - Application | E102: Sep'25 | F102: -7.8 | G102: -17.82 | H102: -17.04 | I102: -16.37 | J102: -19.95 | K102: -20.89 | L102: -21.7 | M102: -20.13 | N102: -16.09 | O102: -16.76 | P102: -14.97 | Q102: -16.11 | R102: -17.93 | S102: -27.57 | T102: -23.74 | U102: -21.31 | V102: -24.32 | W102: -20.01 | X102: 0.11452076 | Y102: 0.0609256 | Z102: 0.070568747 | AA102: -0.077986383
B103: FBIN | C103: United States | D103: Building Products & Equipment | E103: Dec'25 | F103: -8.4 | G103: 0 | H103: 180.4 | I103: 220.5 | J103: 213.3 | K103: 0 | L103: 134.9 | M103: 174.8 | N103: 200.5 | O103: 193.4 | P103: 158.2 | Q103: 217.1 | R103: 217.6 | S103: 188 | T103: 121.8 | U103: 198.9 | V103: 205.3 | W103: 128.2 | X103: -0.046612883 | Y103: -0.024445937 | Z103: -0.016935151 | AA103: -0.083753501
B104: QSR | C104: United States | D104: Restaurants | E104: Dec'25 | F104: -8.7 | G104: 491 | H104: 449 | I104: 530 | J104: 555 | K104: 489 | L104: 485 | M104: 559 | N104: 601 | O104: 492 | P104: 526 | Q104: 612 | R104: 628 | S104: 558 | T104: 517 | U104: 645 | V104: 679 | W104: 350 | X104: -0.0038726334 | Y104: 0.01425486 | Z104: 0.021720613 | AA104: -0.086702793
B105: CBRE | C105: United States | D105: Real Estate Services | E105: Dec'25 | F105: -9.2 | G105: 516.51 | H105: 373.83 | I105: 384.57 | J105: 400.14 | K105: 292.28 | L105: 173 | M105: 297 | N105: 273 | O105: 381 | P105: 191 | Q105: 259 | R105: 391 | S105: 364 | T105: 276 | U105: 430 | V105: 505 | W105: 219 | X105: 0.070539419 | Y105: 0.13255814 | Z105: 0.078028747 | AA105: -0.092063492
B106: BFAM | C106: United States | D106: Personal Services | E106: Dec'25 | F106: -9.3 | G106: 34.53 | H106: 5.86 | I106: 26.42 | J106: 23.85 | K106: 36.72 | L106: 9.05 | M106: 32.03 | N106: 53.62 | O106: 65.79 | P106: 42.24 | Q106: 69.06 | R106: 89.4 | S106: 77.89 | T106: 62.27 | U106: 86.05 | V106: 120.85 | W106: 45.5 | X106: 0.071897771 | Y106: 0.056895051 | Z106: 0.0996483 | AA106: -0.093326802
... B131: IDYA | C131: United States | D131: Biotechnology | E131: Sep'25 | F131: -45.6 | G131: -11.71 | H131: -18.37 | I131: -14.22 | J131: -22.5 | K131: 0.66 | L131: -26.44 | M131: -26.28 | N131: -32.71 | O131: -33.53 | P131: -41.92 | Q131: -51.02 | R131: -64.93 | S131: -66.89 | T131: -144.14 | U131: -84.39 | V131: -88.81 | W131: 108.45 | X131: 0.45479623 | Y131: 0.10205517 | Z131: 0.066268905 | AA131: -0.45634125
B132: NIQ | C132: United States | D132: N/A | E132: Sep'25 | F132: -54.5 | R132: -22.5 | S132: 11.8 | T132: -0.7 | U132: 21.9 | V132: 42 | W132: -29.1 | Z132: 6.1428571 | AA132: -0.54533333
B133: DKNG | C133: United States | D133: Gambling | E133: Dec'25 | F133: -95.5 | G133: -343.44 | H133: -515.58 | I133: -298.42 | J133: -437.72 | K133: -246.5 | L133: -387.22 | M133: -64.91 | N133: -282.01 | O133: -52.45 | P133: -124.61 | Q133: -21.99 | R133: -278.15 | S133: -184 | T133: -46.33 | U133: 150.64 | V133: -271.89 | W133: 151.76 | X133: -0.12859138 | Y133: -0.32542839 | Z133: -0.017493852 | AA133: -0.95500313
B134: ROKU | C134: United States | D134: Entertainment | E134: Dec'25 | F134: -102 | G134: 25.26 | H134: -23.49 | I134: -110.51 | J134: -146.99 | K134: -211.76 | L134: -181.19 | M134: -125.91 | N134: -66.74 | O134: -62.44 | P134: -70.24 | Q134: -60.56 | R134: -17.24 | S134: -39.13 | T134: -54.67 | U134: -19.64 | V134: 10.37 | W134: 65.97 | X134: -0.083186408 | Y134: -0.23846154 | Z134: -0.21127946 | AA134: -1.0196954
B135: CNCK | C135: United States | D135: Capital Markets | E135: Sep'26 | F135: -105.5 | G135: -146 | H135: -146 | I135: 75 | J135: 75 | K135: -434.5 | L135: -434.5 | M135: -412 | N135: -85 | O135: 598 | P135: 2405 | Q135: 823 | R135: 24 | S135: -1636 | T135: -11 | U135: -727 | V135: 516 | W135: 324 | X135: -1.4950495 | Y135: 1.9375 | Z135: -0.2093617 | AA135: -1.0548977
B136: BTDR | C136: United States | D136: Software - Application | E136: Dec'25 | F136: -153.6 | G136: -6.87 | H136: -3.29 | I136: -8.66 | J136: -24.67 | K136: -24.06 | L136: -10.21 | M136: -9.76 | N136: -4.48 | O136: 1.32 | P136: 0.5 | Q136: -1.99 | R136: -53.59 | S136: -514.56 | T136: 416.24 | U136: -76.13 | V136: -231.64 | W136: 109.35 | X136: -0.72982937 | Y136: 0.48174139 | Z136: 0.78078407 | AA136: -1.5363836
B137: CNR | C137: United States | D137: Thermal Coal | E137: Dec'25 | F137: -566.9 | G137: 154.64 | H137: 1.32 | I137: 162.84 | J137: 176.08 | K137: 246.61 | L137: 275.9 | M137: 210.13 | N137: 123.72 | O137: 161.25 | P137: 113.56 | Q137: 67.45 | R137: 112.82 | S137: 94.81 | T137: -16.75 | U137: -25.79 | V137: -18.37 | W137: -97.36 | X137: -0.33529745 | Y137: -0.36093369 | Z137: -0.79465746 | AA137: -5.6687316
B138: STUB | C138: United States | D138: Internet Content & Information | E138: Sep'25 | F138: -1203.9 | N138: 35.89 | O138: 61.26 | P138: 81.12 | Q138: 81.12 | R138: 0.12 | S138: 53.94 | T138: 12.15 | U138: 26.96 | V138: 25.06 | W138: -1368 | X138: -0.31886269 | Y138: -0.36761013 | Z138: 0.26768273 | AA138: -12.039116
B139: JOMA | C139: Sweden | D139: N/A | E139: Sep'25 | F139: 1.5 | G139: 59.7 | H139: 62.4 | I139: 77.5 | J139: 93 | K139: 98.1 | L139: 70.2 | M139: 90.5 | N139: 99.1 | O139: 109 | P139: 87.7 | Q139: 89.8 | R139: 109.3 | S139: 112.3 | T139: 97.9 | U139: 97.8 | V139: 116.5 | W139: 118.5 | X139: 0.025557504 | Y139: 0.019545566 | Z139: 0.017253774 | AA139: 0.014605418
B140: VOLO | C140: Sweden | D140: =VLOOKUP(B140,기업리스트!B:G,2,FALSE) -> Volati AB (publ) | E140: Dec'25 | F140: 1.2 | G140: 0 | H140: 85 | I140: 205 | J140: 178 | K140: 158 | L140: 135 | M140: 226 | N140: 168 | O140: 106 | P140: 64 | Q140: 215 | R140: 156 | S140: 101 | T140: 101 | U140: 211 | V140: 171 | W140: 108 | X140: 0.069029851 | Y140: -0.0069808028 | Z140: 0.026362039 | AA140: 0.011986301
B141: AQ | C141: Sweden | D141: =VLOOKUP(B141,기업리스트!B:G,2,FALSE) -> AQ Group AB (publ) | E141: Dec'25 | F141: 0.4 | G141: 80.1 | H141: 112 | I141: 105 | J141: 123 | K141: 146 | L141: 194 | M141: 203 | N141: 200 | O141: 221 | P141: 223 | Q141: 221 | R141: 188 | S141: 208 | T141: 214 | U141: 219 | V141: 191 | W141: 211 | X141: -0.010714286 | Y141: -0.0024067389 | Z141: 0.0036188179 | AA141: 0.0036057692
B142: NMAN | C142: Sweden | D142: =VLOOKUP(B142,기업리스트!B:G,2,FALSE) -> Nederman Holding AB (publ) | E142: Dec'25 | F142: -3.9 | G142: 124.2 | H142: 98.2 | I142: 107.2 | J142: 138 | K142: 117.6 | L142: 147.1 | M142: 168.5 | N142: 148 | O142: 154.2 | P142: 146.6 | Q142: 159.6 | R142: 126.8 | S142: 149 | T142: 109.2 | U142: 127 | V142: 137.9 | W142: 128.6 | X142: -0.064261168 | Y142: -0.059860448 | Z142: 0.021679688 | AA142: -0.038998279
B143: 4755 | C143: Japan | D143: =VLOOKUP(B143,기업리스트!B:G,2,FALSE) -> Rakuten Group, Inc. | E143: Sep'25 | F143: 561.5 | G143: -7473 | H143: -176374 | I143: -112604 | J143: -84471 | K143: -90018 | L143: -49217 | M143: -76194 | N143: -48893 | O143: -54491 | P143: 4431 | Q143: -33272 | R143: -18331 | S143: 537 | T143: 12510 | U143: -10427 | V143: 3817 | W143: 36682 | X143: -0.17323898 | Y143: -0.59251478 | Z143: -1.4097129 | AA143: 5.6151934
B144: 4784 | C144: Japan | D144: =VLOOKUP(B144,기업리스트!B:G,2,FALSE) -> GMO internet, Inc. | E144: Sep'25 | F144: 65 | G144: 6 | H144: 104 | I144: 303 | J144: 219 | K144: 207 | L144: -18 | M144: 107 | N144: -29 | O144: -91 | P144: -13 | Q144: 71 | R144: -192 | S144: 83 | T144: 178 | U144: 1633 | V144: 1628 | W144: 2373 | X144: -3.745098 | Y144: 11.157143 | Z144: 1.0693302 | AA144: 0.65019875
B145: 5711 | C145: Japan | D145: =VLOOKUP(B145,기업리스트!B:G,2,FALSE) -> Mitsubishi Materials Corporation | E145: Sep'26 | F145: 57.2 | G145: 10281 | H145: 13389 | I145: 13925 | J145: 15635 | K145: 8415 | L145: 12101 | M145: 3792 | N145: 8160 | O145: 3459 | P145: 7866 | Q145: 12811 | R145: 14771 | S145: 4715 | T145: 4822 | U145: -2641 | V145: 13591 | W145: 16430 | X145: -0.075791151 | Y145: -0.41628277 | Z145: -0.054460701 | AA145: 0.57182604
B146: 7222 | C146: Japan | D146: =VLOOKUP(B146,기업리스트!B:G,2,FALSE) -> Nissan Shatai Co., Ltd. | E146: Jun'26 | F146: 38.1 | G146: -596 | H146: -4283 | I146: 1283 | J146: -1759 | K146: 719 | L146: 2577 | M146: 2847 | N146: 60 | O146: 430 | P146: 2503 | Q146: -2025 | R146: -2023 | S146: -247 | T146: 4497 | U146: 2877 | V146: 2208 | W146: 3309 | X146: -1.1127232 | Y146: 24.267327 | Z146: 0.82895768 | AA146: 0.38093198
B147: 4912 | C147: Japan | D147: =VLOOKUP(B147,기업리스트!B:G,2,FALSE) -> Lion Corporation | E147: Sep'25 | F147: 37.9 | G147: 11291 | H147: 6332 | I147: 10491 | J147: 3779 | K147: 8130 | L147: 2341 | M147: 2363 | N147: 3884 | O147: 6268 | P147: 9600 | Q147: 4894 | R147: 8465 | S147: 3752 | T147: 11080 | U147: 5636 | V147: 7744 | W147: 14449 | X147: 0.055407884 | Y147: 0.026320457 | Z147: -0.024919642 | AA147: 0.37916489
B148: 1762 | C148: Japan | D148: =VLOOKUP(B148,기업리스트!B:G,2,FALSE) -> Takamatsu Construction Group Co., Ltd. | E148: Jun'26 | F148: 34.3 | G148: 1692 | H148: 3670 | I148: 4426 | J148: 391 | K148: 2440 | L148: 4041 | M148: 5168 | N148: 808 | O148: 2531 | P148: 3257 | Q148: 5056 | R148: 983 | S148: 1606 | T148: 4251 | U148: 4620 | V148: 1998 | W148: 5882 | X148: 0.091175931 | Y148: -0.036650975 | Z148: 0.088568935 | AA148: 0.34276553
B149: 9409 | C149: Japan | D149: =VLOOKUP(B149,기업리스트!B:G,2,FALSE) -> TV Asahi Holdings Corporation | E149: Jun'26 | F149: 26.9 | G149: 1190 | H149: 7950 | I149: 5079 | J149: 5315 | K149: 2026 | L149: 5883 | M149: 1280 | N149: 3708 | O149: 629 | P149: 4914 | Q149: 3087 | R149: 4765 | S149: 1283 | T149: 7071 | U149: 6586 | V149: 7297 | W149: 7273 | X149: 0.15353406 | Y149: 0.21590769 | Z149: 0.12849531 | AA149: 0.26937087
B150: 4776 | C150: Japan | D150: =VLOOKUP(B150,기업리스트!B:G,2,FALSE) -> Cybozu, Inc. | E150: Sep'25 | F150: 20.4 | G150: 438 | H150: -418 | I150: 314 | J150: 9 | K150: 531 | L150: -243 | M150: 1240 | N150: 792 | O150: 1092 | P150: 270 | Q150: 1311 | R150: 937 | S150: 1211 | T150: 1434 | U150: 2615 | V150: 2549 | W150: 2805 | X150: 0.31214803 | Y150: 0.26650317 | Z150: 0.26012587 | AA150: 0.20412345
B151: 6278 | C151: Japan | D151: =VLOOKUP(B151,기업리스트!B:G,2,FALSE) -> Union Tool Co. | E151: Sep'25 | F151: 16.1 | G151: 1602 | H151: 1528 | I151: 1557 | J151: 1943 | K151: 1984 | L151: 663 | M151: 944 | N151: 1084 | O151: 976 | P151: 731 | Q151: 1415 | R151: 1676 | S151: 1142 | T151: 2611 | U151: 2203 | V151: 1968 | W151: 2416 | X151: 0.37872683 | Y151: 0.11513735 | Z151: 0.038259958 | AA151: 0.16077739
B152: 5831 | C152: Japan | D152: =VLOOKUP(B152,기업리스트!B:G,2,FALSE) -> Shizuoka Financial Group,Inc. | E152: Jun'26 | F152: 13 | G152: 19062 | H152: 17203 | I152: 2789 | J152: 19183 | K152: 19709 | L152: 16804 | M152: 17623 | N152: 23268 | O152: 12845 | P152: 19923 | Q152: 23453 | R152: 28994 | S152: 19991 | T152: 24390 | U152: 31255 | V152: 31391 | W152: 33863 | X152: 0.048364569 | Y152: 0.080575866 | Z152: 0.022909299 | AA152: 0.12961215
B153: 3465 | C153: Japan | D153: =VLOOKUP(B153,기업리스트!B:G,2,FALSE) -> Ki-Star Real Estate Co.,Ltd | E153: Jun'26 | F153: 12.5 | G153: 7138 | H153: 5747 | I153: 5500 | J153: 5074 | K153: 5296 | L153: 4313 | M153: 4507 | N153: 2503 | O153: 2139 | P153: 3243 | Q153: 3477 | R153: 2635 | S153: 4357 | T153: 4432 | U153: 5831 | V153: 4508 | W153: 6739 | X153: 0.086712369 | Y153: 0.15797597 | Z153: 0.10854825 | AA153: 0.12452949
B154: 4971 | C154: Japan | D154: =VLOOKUP(B154,기업리스트!B:G,2,FALSE) -> MEC Company Ltd. | E154: Sep'25 | F154: 11.2 | G154: 1204 | H154: 787 | I154: 1052 | J154: 1032 | K154: 1035 | L154: 886 | M154: 169 | N154: 670 | O154: 833 | P154: 821 | Q154: 1053 | R154: 1310 | S154: 1286 | T154: 913.79 | U154: 1094 | V154: 1347 | W154: 1807 | X154: 0.020758389 | Y154: 0.0089857302 | Z154: 0.0080368566 | AA154: 0.11226537
... B164: 2269 | C164: Japan | D164: =VLOOKUP(B164,기업리스트!B:G,2,FALSE) -> Meiji Holdings Co., Ltd. | E164: Sep'26 | F164: 8.7 | G164: 28682 | H164: 13910 | I164: 18044 | J164: 25150 | K164: 21546 | L164: 10695 | M164: 19498 | N164: 24947 | O164: 25268 | P164: 14609 | Q164: 20499 | R164: 23895 | S164: 22062 | T164: 18247 | U164: 17751 | V164: 23192 | W164: 29122 | X164: 0.044877567 | Y164: -0.032442771 | Z164: -0.0085778781 | AA164: 0.086890169
B165: 6525 | C165: Japan | D165: =VLOOKUP(B165,기업리스트!B:G,2,FALSE) -> Kokusai Electric Corporation | E165: Jun'26 | F165: 8 | M165: 11146 | N165: 3990 | O165: 9383 | P165: 10689 | Q165: 6828 | R165: 17878 | S165: 9562 | T165: 12274 | U165: 11515 | V165: 9717 | W165: 12993 | X165: 0.035255911 | Y165: 0.10070474 | Z165: -0.1593043 | AA165: 0.079664716
B166: 3769 | C166: Japan | D166: =VLOOKUP(B166,기업리스트!B:G,2,FALSE) -> GMO Payment Gateway, Inc. | E166: Dec'25 | F166: 7.7 | G166: 3092 | H166: 4116 | I166: 4159 | J166: 4512 | K166: 3508 | L166: 5091 | M166: 5260 | N166: 5672 | O166: 4362 | P166: 5829 | Q166: 6822 | R166: 6866 | S166: 5701 | T166: 7254 | U166: 8060 | V166: 8131 | W166: 7933 | X166: 0.056507257 | Y166: 0.046466239 | Z166: 0.0453714 | AA166: 0.076579977
B167: 8051 | C167: Japan | D167: =VLOOKUP(B167,기업리스트!B:G,2,FALSE) -> Yamazen Corporation | E167: Jun'26 | F167: 7.7 | G167: 4007 | H167: 4810 | I167: 4837 | J167: 3401 | K167: 4748 | L167: 3989 | M167: 4426 | N167: 2453 | O167: 2418 | P167: 2672 | Q167: 2345 | R167: 871 | S167: 2571 | T167: 2609 | U167: 3486 | V167: 1733 | W167: 3376 | X167: -0.0074476889 | Y167: 0.13589805 | Z167: 0.090384817 | AA167: 0.07741129
B168: 285A | C168: Japan | D168: =VLOOKUP(B168,기업리스트!B:G,2,FALSE) -> Kioxia Holdings Corporation | E168: Sep'26 | F168: 7.1 | G168: 72200 | H168: 30928 | I168: 85100 | J168: 53400 | K168: 93300 | L168: -330815 | M168: -130800 | N168: -100800 | O168: -65000 | P168: 43902 | Q168: 99800 | R168: 192091 | S168: 122715 | T168: 30040 | U168: 44899 | V168: 85921 | W168: 142754 | X168: -0.030232842 | Y168: -0.12347126 | Z168: -0.27240888 | AA168: 0.070665609
B169: 4812 | C169: Japan | D169: =VLOOKUP(B169,기업리스트!B:G,2,FALSE) -> Dentsu Soken Inc. | E169: Sep'25 | F169: 7.1 | G169: 2921 | H169: 4198 | I169: 5292 | J169: 4314 | K169: 4552 | L169: 4406 | M169: 5677 | N169: 4976 | O169: 4899 | P169: 5477 | Q169: 5757 | R169: 4604 | S169: 4102 | T169: 6577 | U169: 5779 | V169: 4884 | W169: 5614 | X169: 0.055165496 | Y169: 0.0010456274 | Z169: 0.013294084 | AA169: 0.070846219
B170: 5036 | C170: Japan | D170: =VLOOKUP(B170,기업리스트!B:G,2,FALSE) -> Japan Business Systems, Inc. | E170: Dec'25 | F170: 6.8 | L170: 1148 | M170: 1106 | N170: 468 | O170: 1513 | P170: 1177 | Q170: 1331 | R170: 937 | S170: 1149 | T170: 1903 | U170: 2604 | V170: 1470 | W170: 1635 | X170: 0.15803222 | Y170: 0.23928571 | Z170: 0.080843319 | AA170: 0.068200954
B171: 4478 | C171: Japan | D171: =VLOOKUP(B171,기업리스트!B:G,2,FALSE) -> freee K.K. | E171: Mar'26 | F171: 6.2 | G171: -501 | H171: -703 | I171: -877 | J171: -962 | K171: -1172 | L171: -1451 | M171: -2081 | N171: -3216 | O171: -2074 | P171: -2642 | Q171: -2245 | R171: -1426 | S171: 183.74 | T171: 684.26 | U171: 290.23 | V171: -493.71 | W171: 224.68 | X171: -0.54268541 | Y171: -0.90447021 | Z171: -3.481682 | AA171: 0.061608379
B172: 9449 | C172: Japan | D172: =VLOOKUP(B172,기업리스트!B:G,2,FALSE) -> GMO internet group, Inc. | E172: Sep'25 | F172: 5.6 | G172: 8012 | H172: 10465 | I172: 11129 | J172: 19813 | K172: 7069 | L172: 5737 | M172: 10992 | N172: 9627 | O172: 9467 | P172: 12072 | Q172: 14437 | R172: 9574 | S172: 11814 | T172: 10336 | U172: 14562 | V172: 15207 | W172: 14718 | X172: -0.036244441 | Y172: 0.0027079136 | Z172: 0.12169987 | AA172: 0.055933281
B173: 3964 | C173: Japan | D173: =VLOOKUP(B173,기업리스트!B:G,2,FALSE) -> Aucnet Inc. | E173: Sep'25 | F173: 5 | G173: 1281 | H173: 1050 | I173: 2143 | J173: 1829 | K173: 1349 | L173: 1280 | M173: 2146 | N173: 1860 | O173: 1418 | P173: 1239 | Q173: 2044 | R173: 1812 | S173: 1755 | T173: 1395 | U173: 3084 | V173: 2753 | W173: 2202 | X173: 0.022773723 | Y173: 0.14844419 | Z173: 0.11695252 | AA173: 0.049738511
B174: 2212 | C174: Japan | D174: =VLOOKUP(B174,기업리스트!B:G,2,FALSE) -> Yamazaki Baking Co., Ltd. | E174: Sep'25 | F174: 4.4 | G174: 1472 | H174: 4663 | I174: 6946 | J174: 7436 | K174: 1645 | L174: 6007 | M174: 9337 | N174: 11274 | O174: 7259 | P174: 14092 | Q174: 16513 | R174: 14518 | S174: 7558 | T174: 13285 | U174: 16818 | V174: 17874 | W174: 10027 | X174: -0.015318616 | Y174: 0.0058796314 | Z174: 0.064317062 | AA174: 0.04445845
B175: 4527 | C175: Japan | D175: =VLOOKUP(B175,기업리스트!B:G,2,FALSE) -> Rohto Pharmaceutical Co.,Ltd. | E175: Jun'26 | F175: 4.1 | G175: 7136 | H175: 9678 | I175: 5668 | J175: 8295 | K175: 7767 | L175: 12265 | M175: 5211 | N175: 11539 | O175: 9428 | P175: 14297 | Q175: 4903 | R175: 11626 | S175: 5937 | T175: 14353 | U175: 6549 | V175: 11627 | W175: 7502 | X175: 0.0015232707 | Y175: 0.044705179 | Z175: 2.599766e-05 | AA175: 0.040685281
B176: 5161 | C176: Japan | D176: =VLOOKUP(B176,기업리스트!B:G,2,FALSE) -> Nishikawa Rubber Co., Ltd. | E176: Jun'26 | F176: 3.3 | G176: 144 | H176: -140 | I176: 674 | J176: -702 | K176: -831 | L176: -352 | M176: 1780 | N176: 879 | O176: 521 | P176: 2868 | Q176: 2288 | R176: 2115 | S176: 1988 | T176: 1273 | U176: 1949 | V176: 1759 | W176: 2221 | X176: -0.17226482 | Y176: -0.044232777 | Z176: -0.048600683 | AA176: 0.033433778
B177: 1605 | C177: Japan | D177: =VLOOKUP(B177,기업리스트!B:G,2,FALSE) -> Inpex Corporation | E177: Dec'25 | F177: 3.2 | G177: 188280 | H177: 228317 | I177: 356178 | J177: 331399 | K177: 330516 | L177: 306302 | M177: 264233 | N177: 268837 | O177: 368115 | P177: 329612 | Q177: 292685 | R177: 301352 | S177: 242086 | T177: 288609 | U177: 263175 | V177: 236040 | W177: 275518 | X177: -0.035173517 | Y177: -0.026237361 | Z177: -0.059633572 | AA177: 0.032461089
B178: 7762 | C178: Japan | D178: =VLOOKUP(B178,기업리스트!B:G,2,FALSE) -> Citizen Watch Co., Ltd. | E178: Jun'26 | F178: 3.1 | G178: 6451 | H178: 8952 | I178: 2630 | J178: 5589 | K178: 6766 | L178: 8679 | M178: 2655 | N178: 5538 | O178: 8006 | P178: 9873 | Q178: 1439 | R178: 4685 | S178: 7643 | T178: 6709 | U178: 1519 | V178: 4701 | W178: 8286 | X178: -0.13384095 | Y178: 0.0039070131 | Z178: 0.00077836155 | AA178: 0.031256076
B179: 3076 | C179: Japan | D179: =VLOOKUP(B179,기업리스트!B:G,2,FALSE) -> Ai Holdings Corporation | E179: Mar'26 | F179: 2.9 | G179: 2526 | H179: 2487 | I179: 2516 | J179: 2322 | K179: 2359 | L179: 2671 | M179: 2671 | N179: 1899 | O179: 2354 | P179: 2765 | Q179: 2661 | R179: 2030 | S179: 1779 | T179: 2105 | U179: 3510 | V179: 1496 | W179: 2040 | X179: -0.071467244 | Y179: 0.099008746 | Z179: -0.056663837 | AA179: 0.02935883
B180: 5301 | C180: Japan | D180: =VLOOKUP(B180,기업리스트!B:G,2,FALSE) -> Tokai Carbon Co., Ltd. | E180: Sep'25 | F180: 2.2 | G180: 6724 | H180: 6977 | I180: 7939 | J180: 8779 | K180: 11298 | L180: 12574 | M180: 11494 | N180: 10246 | O180: 8010 | P180: 8980 | Q180: 3490 | R180: 4935 | S180: 6787 | T180: 4176 | U180: 7137 | V180: 6820 | W180: 7344 | X180: -0.19857804 | Y180: 0.18810604 | Z180: 0.081831995 | AA180: 0.022351525
B181: 6383 | C181: Japan | D181: =VLOOKUP(B181,기업리스트!B:G,2,FALSE) -> Daifuku Co., Ltd. | E181: Sep'25 | F181: 2.2 | G181: 9812 | H181: 12665 | I181: 17260 | J181: 10276 | K181: 14190 | L181: 15705 | M181: 18684 | N181: 8219 | O181: 10842 | P181: 18031 | Q181: 24988 | R181: 16405 | S181: 21741 | T181: 33401 | U181: 23228 | V181: 27876 | W181: 24111 | X181: 0.18936734 | Y181: -0.018231729 | Z181: 0.12103403 | AA181: 0.022306722
B182: 7202 | C182: Japan | D182: =VLOOKUP(B182,기업리스트!B:G,2,FALSE) -> Isuzu Motors Limited | E182: Sep'26 | F182: 2.2 | G182: 51323 | H182: 38580 | I182: 54772 | J182: 57423 | K182: 85690 | L182: 55663 | M182: 68607 | N182: 74589 | O182: 110366 | P182: 39524 | Q182: 76913 | R182: 52286 | S182: 63281 | T182: 40802 | U182: 57223 | V182: 47428 | W182: 67807 | X182: 0.0055085257 | Y182: -0.084404283 | Z182: -0.022744298 | AA182: 0.021683099
... B188: 9989 | C188: Japan | D188: =VLOOKUP(B188,기업리스트!B:G,2,FALSE) -> Sundrug Co.,Ltd. | E188: Jun'26 | F188: 1.1 | G188: 8329 | H188: 9513 | I188: 6610 | J188: 9058 | K188: 9454 | L188: 10982 | M188: 7957 | N188: 9901 | O188: 10709 | P188: 12607 | Q188: 7780 | R188: 10921 | S188: 10291 | T188: 13609 | U188: 9676 | V188: 12277 | W188: 10782 | X188: 0.024087117 | Y188: 0.044505998 | Z188: 0.030473965 | AA188: 0.010708133
B189: 141A | C189: Japan | D189: =VLOOKUP(B189,기업리스트!B:G,2,FALSE) -> TRIAL Holdings, Inc. | E189: Mar'26 | F189: 1 | K189: 3633 | L189: 3633 | M189: 3350 | N189: 3350 | O189: 5785 | P189: 5785 | Q189: 3830 | R189: 3762 | S189: 4931 | T189: 4769 | U189: 3764 | V189: 7642 | W189: 5139 | X189: -0.055494866 | Y189: -0.0038167939 | Z189: 0.22524091 | AA189: 0.0098550175
B190: 5741 | C190: Japan | D190: =VLOOKUP(B190,기업리스트!B:G,2,FALSE) -> UACJ Corporation | E190: Jun'26 | F190: 1 | G190: 16655 | H190: 12950 | I190: 16704 | J190: 18343 | K190: 3129 | L190: -6017 | M190: 1752 | N190: 7646 | O190: 4500 | P190: 9011 | Q190: 9745 | R190: 21841 | S190: 13342 | T190: 12985 | U190: 8045 | V190: 8227 | W190: 13749 | X190: 0.073675819 | Y190: -0.029354376 | Z190: -0.24218597 | AA190: 0.0095542149
B191: 8061 | C191: Japan | D191: =VLOOKUP(B191,기업리스트!B:G,2,FALSE) -> Seika Corporation | E191: Jun'26 | F191: 1 | G191: 596 | H191: 1053 | I191: 1467 | J191: 855 | K191: 590 | L191: 1170 | M191: 2022 | N191: 945 | O191: 1107 | P191: 1400 | Q191: 2129 | R191: 1319 | S191: 1603 | T191: 1398 | U191: 2167 | V191: 1594 | W191: 1671 | X191: -0.00031002945 | Y191: 0.0058923864 | Z191: 0.042392477 | AA191: 0.010056196
B192: 6856 | C192: Japan | D192: =VLOOKUP(B192,기업리스트!B:G,2,FALSE) -> HORIBA, Ltd. | E192: Sep'25 | F192: 0.6 | G192: 6790 | H192: 12188 | I192: 8607 | J192: 7654 | K192: 12312 | L192: 17271 | M192: 10452 | N192: 7387 | O192: 10661 | P192: 18798 | Q192: 10011 | R192: 8606 | S192: 11288 | T192: 18436 | U192: 11756 | V192: 10137 | W192: 11623 | X192: -0.007432807 | Y192: 0.036097722 | Z192: 0.030567424 | AA192: 0.0064901098
...

Sheet 빨간줄
B2: (단위: mil $)
Y3: HCC | Z3: 5711 | AA3: Mitsubishi Materials Corporation
B4: 8136 | C4: 6 | D4: 7 | E4: 8 | F4: 9 | G4: 10 | H4: 11 | I4: 12 | J4: 13 | K4: 14 | L4: 15 | M4: 16 | N4: 17 | O4: 18 | P4: 19 | Q4: 20 | R4: 21 | S4: 22 | Y4: ALNY | Z4: 7222 | AA4: Nissan Shatai Co., Ltd.
Y5: KEY | Z5: 1762 | AA5: Takamatsu Construction Group Co., Ltd.
C6: 4Q21 | D6: 1Q22 | E6: 2Q22 | F6: 3Q22 | G6: 4Q22 | H6: 1Q23 | I6: 2Q23 | J6: 3Q23 | K6: 4Q23 | L6: 1Q24 | M6: 2Q24 | N6: 3Q24 | O6: 4Q24 | P6: 1Q25 | Q6: 2Q25 | R6: 3Q25 | S6: 4Q25 | T6: 1Q26 | U6: 2Q26 | V6: 3Q26 | W6: 4Q26 | Y6: HR | Z6: 9409 | AA6: TV Asahi Holdings Corporation
B7: Revenue | C7: =VLOOKUP($B$4,Revenue!$B:$W,C4,FALSE) -> 12991 | D7: =VLOOKUP($B$4,Revenue!$B:$W,D4,FALSE) -> 14769 | E7: =VLOOKUP($B$4,Revenue!$B:$W,E4,FALSE) -> 14201 | F7: =VLOOKUP($B$4,Revenue!$B:$W,F4,FALSE) -> 13829 | G7: =VLOOKUP($B$4,Revenue!$B:$W,G4,FALSE) -> 16801 | H7: =VLOOKUP($B$4,Revenue!$B:$W,H4,FALSE) -> 20995 | I7: =VLOOKUP($B$4,Revenue!$B:$W,I4,FALSE) -> 20999 | J7: =VLOOKUP($B$4,Revenue!$B:$W,J4,FALSE) -> 20315 | ... S7: =VLOOKUP($B$4,Revenue!$B:$W,S4,FALSE) -> 44579 | Y7: ELVA | Z7: 5831 | AA7: Shizuoka Financial Group,Inc.
B8: OP | C8: =VLOOKUP($B$4,'Operating Income'!$B:$W,C4,FALSE) -> 347 | D8: =VLOOKUP($B$4,'Operating Income'!$B:$W,D4,FALSE) -> 1747 | E8: =VLOOKUP($B$4,'Operating Income'!$B:$W,E4,FALSE) -> 502 | F8: =VLOOKUP($B$4,'Operating Income'!$B:$W,F4,FALSE) -> 2384 | G8: =VLOOKUP($B$4,'Operating Income'!$B:$W,G4,FALSE) -> 2963 | H8: =VLOOKUP($B$4,'Operating Income'!$B:$W,H4,FALSE) -> 5256 | I8: =VLOOKUP($B$4,'Operating Income'!$B:$W,I4,FALSE) -> 2645 | J8: =VLOOKUP($B$4,'Operating Income'!$B:$W,J4,FALSE) -> 5965 | ... S8: =VLOOKUP($B$4,'Operating Income'!$B:$W,S4,FALSE) -> 18985 | Y8: TWLO | Z8: 3465 | AA8: Ki-Star Real Estate Co.,Ltd
B9: Trailing 4Q OP avg. | C9: =AVERAGE(C8:C8) -> 347 | D9: =AVERAGE(C8:D8) -> 1047 | E9: =AVERAGE(C8:E8) -> 865.33333 | F9: =AVERAGE(C8:F8) -> 1245 | G9: =AVERAGE(D8:G8) -> 1899 | H9: =AVERAGE(E8:H8) -> 2776.25 | I9: =AVERAGE(F8:I8) -> 3312 | J9: =AVERAGE(G8:J8) -> 4207.25 | K9: =AVERAGE(H8:K8) -> 5302.25 | L9: =AVERAGE(I8:L8) -> 6009 | M9: =AVERAGE(J8:M8) -> 6738.5 | ... S9: =AVERAGE(P8:S8) -> 16849.5 | Y9: DRUG | Z9: 2264 | AA9: Morinaga Milk Industry Co., Ltd.
B10: Trailing 4Q OP sum. | C10: =SUM(C8:C8) -> 347 | D10: =SUM(C8:D8) -> 2094 | E10: =SUM(C8:E8) -> 2596 | F10: =SUM(C8:F8) -> 4980 | G10: =SUM(D8:G8) -> 7596 | H10: =SUM(E8:H8) -> 11105 | I10: =SUM(F8:I8) -> 13248 | J10: =SUM(G8:J8) -> 16829 | K10: =SUM(H8:K8) -> 21209 | L10: =SUM(I8:L8) -> 24036 | M10: =SUM(J8:M8) -> 26954 | ... S10: =SUM(P8:S8) -> 67398 | Y10: PINS | Z10: 8795 | AA10: T&D Holdings, Inc.
B11: Trailing OP Delta | D11: =D9/C9-1 -> 2.0172911 | E11: =E9/D9-1 -> -0.17351162 | F11: =F9/E9-1 -> 0.43875193 | G11: =G9/F9-1 -> 0.5253012 | H11: =H9/G9-1 -> 0.46195366 | I11: =I9/H9-1 -> 0.19297614 | J11: =J9/I9-1 -> 0.27030495 | K11: =K9/J9-1 -> 0.26026502 | ... S11: =S9/R9-1 -> 0.10023181 | Y11: AEM | Z11: 8136 | AA11: Sanrio Company, Ltd.
B12: opm | C12: =IFERROR(C8/C7,"-") -> 0.0267108 | D12: =IFERROR(D8/D7,"-") -> 0.11828831 | E12: =IFERROR(E8/E7,"-") -> 0.035349623 | F12: =IFERROR(F8/F7,"-") -> 0.17239135 | G12: =IFERROR(G8/G7,"-") -> 0.17635855 | H12: =IFERROR(H8/H7,"-") -> 0.25034532 | I12: =IFERROR(I8/I7,"-") -> 0.12595838 | J12: =IFERROR(J8/J7,"-") -> 0.2936254 | ... S12: =IFERROR(S8/S7,"-") -> 0.42587317 | Y12: TRUP
B13: op yoy | C13: =C8/#REF!-1 -> #REF! | D13: =D8/#REF!-1 -> #REF! | E13: =E8/#REF!-1 -> #REF! | F13: =F8/#REF!-1 -> #REF! | G13: =G8/C8-1 -> 7.5389049 | H13: =H8/D8-1 -> 2.0085861 | I13: =I8/E8-1 -> 4.2689243 | J13: =J8/F8-1 -> 1.5020973 | K13: =K8/G8-1 -> 1.4782315 | L13: =L8/H8-1 -> 0.53786149 | M13: =M8/I8-1 -> 1.1032136 | N13: =N8/J8-1 -> 0.80167645 | ... S13: =S8/O8-1 -> 0.47800701 | Y13: TOST
B14: rv yoy | G14: =G7/C7-1 -> 0.29327996 | H14: =H7/D7-1 -> 0.42155867 | I14: =I7/E7-1 -> 0.47869868 | J14: =J7/F7-1 -> 0.46901439 | K14: =K7/G7-1 -> 0.4055711 | L14: =L7/H7-1 -> 0.35722791 | M14: =M7/I7-1 -> 0.31225296 | N14: =N7/J7-1 -> 0.42313561 | ... S14: =S7/O7-1 -> 0.31516993 | Y14: DXCM
Y15: STNG
Y16: NBIS
Y17: FWDI
Y18: AORT
Y19: CTRE
Y20: HASI
