Workbook

Sheet 기업리스트
B2: 실적 기업 정보
B3: Ticker | C3: Company | D3: Date | E3: Time | F3: Quarter Ending | G3: Market Cap (mil$)
B4: PLTR | C4: Palantir Technologies Inc. | D4: Feb 2, 2026 | E4: After Hours | F4: Dec/2025 | G4: 349387.93
B5: DIS | C5: The Walt Disney Company | D5: Feb 2, 2026 | F5: Dec/2025 | G5: 201380.58
B6: ISP | C6: Intesa Sanpaolo S.p.A. | D6: Feb 2, 2026 | F6: Dec/2025 | G6: 123582.78
B7: 8411 | C7: Mizuho Financial Group, Inc. | D7: Feb 2, 2026 | F7: Dec/2025 | G7: 108869.48
B8: ITUB4 | C8: Itaú Unibanco Holding S.A. | D8: Feb 2, 2026 | F8: Dec/2025 | G8: 91584.13
B9: SPG | C9: Simon Property Group, Inc. | D9: Feb 2, 2026 | E9: After Hours | F9: Dec/2025 | G9: 62220.11
B10: NXPI | C10: NXP Semiconductors N.V. | D10: Feb 2, 2026 | E10: After Hours | F10: Dec/2025 | G10: 56913.66
B11: IDXX | C11: IDEXX Laboratories, Inc. | D11: Feb 2, 2026 | E11: Pre Market | F11: Dec/2025 | G11: 53537.12
B12: 6981 | C12: Murata Manufacturing Co., Ltd. | D12: Feb 2, 2026 | F12: Dec/2025 | G12: 39312.39
B13: TER | C13: Teradyne, Inc. | D13: Feb 2, 2026 | E13: After Hours | F13: Dec/2025 | G13: 35729.4
B14: 9020 | C14: East Japan Railway Company | D14: Feb 2, 2026 | F14: Dec/2025 | G14: 28273.48
B15: 9022 | C15: Central Japan Railway Company | D15: Feb 2, 2026 | F15: Dec/2025 | G15: 25620.45
B16: 6762 | C16: TDK Corporation | D16: Feb 2, 2026 | F16: Dec/2025 | G16: 25069.09
B17: 1010 | C17: Riyad Bank | D17: Feb 2, 2026 | F17: Dec/2025 | G17: 21317.66
B18: 6971 | C18: Kyocera Corporation | D18: Feb 2, 2026 | F18: Dec/2025 | G18: 18668.24
B19: TSN | C19: Tyson Foods, Inc. | D19: Feb 2, 2026 | E19: Pre Market | F19: Dec/2025 | G19: 18514.24
B20: 1150 | C20: Alinma Bank | D20: Feb 2, 2026 | F20: Dec/2025 | G20: 17890.95
B21: 1060 | C21: Saudi Awwal Bank | D21: Feb 2, 2026 | F21: Dec/2025 | G21: 17805.85
B22: APTV | C22: Aptiv PLC | D22: Feb 2, 2026 | E22: Pre Market | F22: Dec/2025 | G22: 16986
B23: WWD | C23: Woodward, Inc. | D23: Feb 2, 2026 | E23: After Hours | F23: Dec/2025 | G23: 15454.49
B24: BAER | C24: Julius Bär Gruppe AG | D24: Feb 2, 2026 | F24: Dec/2025 | G24: 14222.32
B25: DOC | C25: Healthpeak Properties, Inc. | D25: Feb 2, 2026 | E25: After Hours | F25: Dec/2025 | G25: 13460.67
B26: A000810 | C26: Samsung Fire & Marine Insurance Co., Ltd. | D26: Feb 2, 2026 | F26: Dec/2025 | G26: 13406.95
B27: FN | C27: Fabrinet | D27: Feb 2, 2026 | E27: After Hours | F27: Dec/2025 | G27: 13077.03
B28: 1140 | C28: Bank Albilad | D28: Feb 2, 2026 | F28: Dec/2025 | G28: 11582.46
B29: 9532 | C29: Osaka Gas Co., Ltd. | D29: Feb 2, 2026 | F29: Dec/2025 | G29: 11248.27
B30: 8601 | C30: Daiwa Securities Group Inc. | D30: Feb 2, 2026 | F30: Dec/2025 | G30: 11033.39
B31: RVTY | C31: Revvity, Inc. | D31: Feb 2, 2026 | E31: Pre Market | F31: Dec/2025 | G31: 10916.63
B32: RMBS | C32: Rambus Inc. | D32: Feb 2, 2026 | F32: Dec/2025 | G32: 10758.31
B33: INDUSTOWER | C33: Indus Towers Limited | D33: Feb 2, 2026 | F33: Dec/2025 | G33: 10489.07
B34: 9502 | C34: Chubu Electric Power Company, Incorporated | D34: Feb 2, 2026 | F34: Dec/2025 | G34: 10469.58
B35: 3008 | C35: LARGAN Precision Co.,Ltd | D35: Feb 2, 2026 | F35: Dec/2025 | G35: 10468.01
B36: DVA | C36: DaVita Inc. | D36: Feb 2, 2026 | E36: After Hours | F36: Dec/2025 | G36: 9377.94
B37: POLICYBZR | C37: PB Fintech Limited | D37: Feb 2, 2026 | F37: Dec/2025 | G37: 8797.68
B38: CHMF | C38: Public Joint Stock Company Severstal | D38: Feb 2, 2026 | F38: Dec/2025 | G38: 8355.87
B39: 4768 | C39: Otsuka Corporation | D39: Feb 2, 2026 | F39: Dec/2025 | G39: 7822.9
B40: GICRE | C40: General Insurance Corporation of India | D40: Feb 2, 2026 | F40: Dec/2025 | G40: 7374.71
B41: AKBNK | C41: Akbank T.A.S. | D41: Feb 2, 2026 | F41: Dec/2025 | G41: 7252.37
B42: 512070 | C42: UPL Limited | D42: Feb 2, 2026 | F42: Dec/2025 | G42: 7248.48
B43: 8331 | C43: The Chiba Bank, Ltd. | D43: Feb 2, 2026 | F43: Dec/2025 | G43: 6921.95
B44: SUNDARMFIN | C44: Sundaram Finance Limited | D44: Feb 2, 2026 | F44: Dec/2025 | G44: 6622.39
B45: MTG | C45: MGIC Investment Corporation | D45: Feb 2, 2026 | E45: After Hours | F45: Dec/2025 | G45: 6613.78
B46: 4030 | C46: The National Shipping Company of Saudi Arabia | D46: Feb 2, 2026 | F46: Dec/2025 | G46: 6555.59
B47: 9064 | C47: Yamato Holdings Co., Ltd. | D47: Feb 2, 2026 | F47: Dec/2025 | G47: 4859.45
B48: NJR | C48: New Jersey Resources Corporation | D48: Feb 2, 2026 | F48: Dec/2025 | G48: 4719.21
B49: ARG | C49: Argo Investments Limited | D49: Feb 2, 2026 | F49: Dec/2025 | G49: 4689.63
B50: HESM | C50: Hess Midstream LP | D50: Feb 2, 2026 | E50: Pre Market | F50: Dec/2025 | G50: 4510.62
B51: 1020 | C51: Bank AlJazira | D51: Feb 2, 2026 | F51: Dec/2025 | G51: 4441.07
B52: 513683 | C52: NLC India Limited | D52: Feb 2, 2026 | F52: Dec/2025 | G52: 4420.93
B53: 2282 | C53: NH Foods Ltd. | D53: Feb 2, 2026 | F53: Dec/2025 | G53: 4140.02
B54: USLM | C54: United States Lime & Minerals, Inc. | D54: Feb 2, 2026 | F54: Dec/2025 | G54: 3627.74
B55: THERMAX | C55: Thermax Limited | D55: Feb 2, 2026 | F55: Dec/2025 | G55: 3475.46
B56: 517174 | C56: Honeywell Automation India Limited | D56: Feb 2, 2026 | F56: Dec/2025 | G56: 3347.41
B57: PCH | C57: PotlatchDeltic Corporation | D57: Feb 2, 2026 | F57: Dec/2025 | G57: 3159.66
B58: ZUGER | C58: Zuger Kantonalbank | D58: Feb 2, 2026 | F58: Dec/2025 | G58: 3121.23
B59: F&N | C59: Fraser & Neave Holdings Bhd | D59: Feb 2, 2026 | F59: Dec/2025 | G59: 3120.35
B60: ARLP | C60: Alliance Resource Partners, L.P. | D60: Feb 2, 2026 | E60: Pre Market | F60: Dec/2025 | G60: 3105.39
B61: VFQS | C61: Vodafone Qatar P.Q.S.C. | D61: Feb 2, 2026 | F61: Dec/2025 | G61: 2877.46
B62: 7337 | C62: Hirogin Holdings, Inc. | D62: Feb 2, 2026 | F62: Dec/2025 | G62: 2819.65
B63: 3132 | C63: Macnica Holdings, Inc. | D63: Feb 2, 2026 | F63: Dec/2025 | G63: 2552.43
B64: KINV B | C64: Kinnevik AB | D64: Feb 2, 2026 | F64: Dec/2025 | G64: 2510.2
B65: ERIS | C65: Eris Lifesciences Limited | D65: Feb 2, 2026 | F65: Dec/2025 | G65: 2422.48
B66: ASH | C66: Ashland Inc. | D66: Feb 2, 2026 | E66: After Hours | F66: Dec/2025 | G66: 2302.82
B67: CUB | C67: City Union Bank Limited | D67: Feb 2, 2026 | F67: Dec/2025 | G67: 2196.26
B68: 500770 | C68: Tata Chemicals Limited | D68: Feb 2, 2026 | F68: Dec/2025 | G68: 2150.57
B69: BASF | C69: BASF India Limited | D69: Feb 2, 2026 | F69: Dec/2025 | G69: 2146.15
B70: 531768 | C70: Poly Medicure Limited | D70: Feb 2, 2026 | F70: Dec/2025 | G70: 2144.59
B71: A204320 | C71: HL Mando Corporation | D71: Feb 2, 2026 | F71: Dec/2025 | G71: 2098.53
B72: APLLTD | C72: Alembic Pharmaceuticals Limited | D72: Feb 2, 2026 | F72: Dec/2025 | G72: 1997.81
B73: C2PU | C73: Parkway Life Real Estate Investment Trust | D73: Feb 2, 2026 | F73: Dec/2025 | G73: 1985.46
B74: 7451 | C74: Mitsubishi Shokuhin Co., Ltd. | D74: Feb 2, 2026 | F74: Dec/2025 | G74: 1828.98
B75: TWST | C75: Twist Bioscience Corporation | D75: Feb 2, 2026 | E75: Pre Market | F75: Dec/2025 | G75: 1814.45
B76: A000240 | C76: Hankook & Company Co., Ltd. | D76: Feb 2, 2026 | F76: Dec/2025 | G76: 1809.47
B77: 4272 | C77: Nippon Kayaku Co., Ltd. | D77: Feb 2, 2026 | F77: Dec/2025 | G77: 1763.1
B78: 2222 | C78: Kotobuki Spirits Co., Ltd. | D78: Feb 2, 2026 | F78: Dec/2025 | G78: 1740.47
B79: RHLD | C79: Resolute Holdings Management, Inc. | D79: Feb 2, 2026 | F79: Dec/2025 | G79: 1627.87
B80: 2811 | C80: Kagome Co., Ltd. | D80: Feb 2, 2026 | F80: Dec/2025 | G80: 1567.71
B81: FINEORG | C81: Fine Organic Industries Limited | D81: Feb 2, 2026 | F81: Dec/2025 | G81: 1464.28
B82: 531335 | C82: Zydus Wellness Limited | D82: Feb 2, 2026 | F82: Dec/2025 | G82: 1453.69
B83: 524208 | C83: Aarti Industries Limited | D83: Feb 2, 2026 | F83: Dec/2025 | G83: 1438.89
B84: A030000 | C84: Cheil Worldwide Inc. | D84: Feb 2, 2026 | F84: Dec/2025 | G84: 1433.27
B85: GCHE | C85: Public Joint Stock Company Cherkizovo Group"" | D85: Feb 2, 2026 | F85: Dec/2025 | G85: 1422.97
B86: 530007 | C86: JK Tyre & Industries Limited | D86: Feb 2, 2026 | F86: Dec/2025 | G86: 1387.79
B87: A004800 | C87: Hyosung Corporation | D87: Feb 2, 2026 | F87: Dec/2025 | G87: 1386.12
... B92: 8370 | C92: The Kiyo Bank, Ltd. | D92: Feb 2, 2026 | F92: Dec/2025 | G92: 1286.06
B93: CSWC | C93: Capital Southwest Corporation | D93: Feb 2, 2026 | E93: After Hours | F93: Dec/2025 | G93: 1279.79
B94: 523025 | C94: Safari Industries (India) Limited | D94: Feb 2, 2026 | F94: Dec/2025 | G94: 1251.09
B95: A098460 | C95: Koh Young Technology Inc. | D95: Feb 2, 2026 | F95: Dec/2025 | G95: 1191.81
B96: 7981 | C96: Takara Standard Co.,Ltd. | D96: Feb 2, 2026 | F96: Dec/2025 | G96: 1145.62
B97: 8386 | C97: The Hyakujushi Bank, Ltd. | D97: Feb 2, 2026 | F97: Dec/2025 | G97: 1134.57
B98: ATX | C98: ATEX Resources Inc. | D98: Feb 2, 2026 | F98: Dec/2025 | G98: 1097.22
B99: HFCL | C99: HFCL Limited | D99: Feb 2, 2026 | F99: Dec/2025 | G99: 1068.13
B100: A089030 | C100: Techwing, Inc. | D100: Feb 2, 2026 | F100: Dec/2025 | G100: 1047.44
B101: ACAD | C101: AcadeMedia AB (publ) | D101: Feb 2, 2026 | F101: Dec/2025 | G101: 1034.78
B102: TWO | C102: Two Harbors Investment Corp. | D102: Feb 2, 2026 | F102: Dec/2025 | G102: 1034.27
B103: 8346 | C103: The Toho Bank, Ltd. | D103: Feb 2, 2026 | F103: Dec/2025 | G103: 975.05
B104: 7224 | C104: ShinMaywa Industries, Ltd. | D104: Feb 2, 2026 | F104: Dec/2025 | G104: 950.01
B105: BESALCO | C105: Besalco S.A. | D105: Feb 2, 2026 | F105: Dec/2025 | G105: 912.98
...

Sheet Revenue
B2: Ticker | C2: Country | D2: Industry | E2: Latest_Date | F2: Growth_Rate | G2: 4Q21 | H2: 1Q22 | I2: 2Q22 | J2: 3Q22 | K2: 4Q22 | L2: 1Q23 | M2: 2Q23 | N2: 3Q23 | O2: 4Q23 | P2: 1Q24 | Q2: 2Q24 | R2: 3Q24 | S2: 4Q24 | T2: 1Q25 | U2: 2Q25 | V2: 3Q25 | W2: 4Q25 | X2: 1Q25 롤링 | Y2: 2Q25 롤링 | Z2: 3Q25 롤링 | AA2: 4Q25 롤링
B3: PLTR | C3: United States | D3: Software - Infrastructure | E3: Dec'25 | F3: 14.9 | G3: 432.87 | H3: 446.36 | I3: 473.01 | J3: 477.88 | K3: 508.62 | L3: 525.19 | M3: 533.32 | N3: 558.16 | O3: 608.35 | P3: 634.34 | Q3: 678.13 | R3: 725.52 | S3: 827.52 | T3: 883.86 | U3: 1004 | V3: 1181 | W3: 1407 | X3: 0.087076995 | Y3: 0.10461215 | Z3: 0.13237234 | AA3: 0.14872266
B4: TER | C4: United States | D4: Semiconductor Equipment & Materials | E4: Dec'25 | F4: 11.5 | G4: 885.05 | H4: 755.37 | I4: 840.77 | J4: 827.07 | K4: 731.84 | L4: 617.53 | M4: 684.44 | N4: 703.73 | O4: 670.6 | P4: 599.82 | Q4: 729.88 | R4: 737.3 | S4: 752.88 | T4: 685.68 | U4: 651.8 | V4: 769.21 | W4: 1083 | X4: 0.030448104 | Y4: -0.026870952 | Z4: 0.011284949 | AA4: 0.11544393
B5: FN | C5: United States | D5: Electronic Components | E5: Jun'26 | F5: 8.3 | G5: 566.63 | H5: 564.4 | I5: 587.87 | J5: 655.43 | K5: 668.66 | L5: 665.28 | M5: 655.87 | N5: 685.48 | O5: 712.69 | P5: 731.54 | Q5: 753.26 | R5: 804.23 | S5: 833.61 | T5: 871.8 | U5: 909.69 | V5: 978.13 | W5: 1133 | X5: 0.044917121 | Y5: 0.047942015 | Z5: 0.050857917 | AA5: 0.083320578
B6: WWD | C6: United States | D6: Aerospace & Defense | E6: Mar'26 | F6: 6.3 | G6: 541.59 | H6: 586.84 | I6: 614.33 | J6: 640.03 | K6: 618.62 | L6: 718.21 | M6: 800.66 | N6: 777.07 | O6: 786.73 | P6: 835.34 | Q6: 847.69 | R6: 854.49 | S6: 772.73 | T6: 883.63 | U6: 915.45 | V6: 995.26 | W6: 996.45 | X6: 0.014588022 | Y6: 0.020175433 | Z6: 0.041085136 | AA6: 0.062718141
B7: CSWC | C7: United States | D7: Asset Management | E7: Sep'26 | F7: 4.4 | G7: 22.31 | H7: 21.03 | I7: 22.54 | J7: 26.8 | K7: 32.77 | L7: 37.19 | M7: 40.36 | N7: 42.78 | O7: 48.57 | P7: 46.43 | Q7: 51.35 | R7: 48.71 | S7: 51.97 | T7: 52.41 | U7: 55.95 | V7: 56.95 | W7: 61.45 | X7: 0.030132017 | Y7: 0.022500489 | Z7: 0.039418293 | AA7: 0.043630339
B8: RMBS | C8: United States | D8: Semiconductors | E8: Dec'25 | F8: 4.3 | G8: 91.78 | H8: 99.05 | I8: 121.13 | J8: 112.24 | K8: 122.37 | L8: 113.76 | M8: 119.83 | N8: 105.3 | O8: 122.23 | P8: 117.87 | Q8: 132.14 | R8: 145.51 | S8: 161.1 | T8: 166.66 | U8: 172.21 | V8: 178.51 | W8: 190.24 | X8: 0.087654055 | Y8: 0.066186551 | Z8: 0.051124744 | AA8: 0.042948945
B9: TWST | C9: United States | D9: Diagnostics & Research | E9: Mar'26 | F9: 4 | G9: 42.02 | H9: 48.13 | I9: 56.11 | J9: 57.31 | K9: 54.24 | L9: 60.18 | M9: 63.74 | N9: 66.95 | O9: 71.5 | P9: 75.3 | Q9: 81.46 | R9: 84.71 | S9: 88.71 | T9: 92.79 | U9: 96.06 | V9: 99.01 | W9: 103.7 | X9: 0.052971107 | Y9: 0.041993845 | Z9: 0.039473321 | AA9: 0.039806676
B10: SPG | C10: United States | D10: REIT - Retail | E10: Dec'25 | F10: 3.4 | G10: 1324 | H10: 1296 | I10: 1280 | J10: 1316 | K10: 1400 | L10: 1351 | M10: 1370 | N10: 1411 | O10: 1527 | P10: 1443 | Q10: 1458 | R10: 1481 | S10: 1582 | T10: 1473 | U10: 1498 | V10: 1602 | W10: 1791 | X10: 0.0050301811 | Y10: 0.00667334 | Z10: 0.020053033 | AA10: 0.033956133
B11: IDXX | C11: United States | D11: Diagnostics & Research | E11: Dec'25 | F11: 3.3 | G11: 801.09 | H11: 836.55 | I11: 860.55 | J11: 841.66 | K11: 828.57 | L11: 900.2 | M11: 943.63 | N11: 915.53 | O11: 901.6 | P11: 964.1 | Q11: 1004 | R11: 975.54 | S11: 954.29 | T11: 998.43 | U11: 1109 | V11: 1105 | W11: 1091 | X11: 0.0088072387 | Y11: 0.026702202 | Z11: 0.032066302 | AA11: 0.03280998
B12: BSRR | C12: United States | D12: Banks - Regional | E12: Dec'25 | F12: 3.2 | G12: 34.87 | H12: 30.31 | I12: 34.61 | J12: 34.26 | K12: 30.54 | L12: 34.45 | M12: 36.4 | N12: 35.88 | O12: 32.39 | P12: 37.18 | Q12: 36.9 | R12: 37.22 | S12: 35.46 | T12: 34.68 | U12: 38.01 | V12: 36.34 | W12: 40.15 | X12: -0.017034614 | Y12: 0.0076944406 | Z12: -0.0060535186 | AA12: 0.032458994
B13: NSSC | C13: United States | D13: Security & Protection Services | E13: Jun'26 | F13: 2.8 | G13: 33.41 | H13: 35.91 | I13: 43.23 | J13: 39.49 | K13: 42.31 | L13: 43.53 | M13: 44.66 | N13: 41.68 | O13: 47.55 | P13: 49.27 | Q13: 50.33 | R13: 44 | S13: 42.93 | T13: 43.96 | U13: 50.72 | V13: 49.17 | W13: 48.17 | X13: -0.028467271 | Y13: 0.0021520803 | Z13: 0.028467595 | AA13: 0.028054396
B14: DVA | C14: United States | D14: Medical Care Facilities | E14: Dec'25 | F14: 2.4 | G14: 2944 | H14: 2818 | I14: 2927 | J14: 2949 | K14: 0 | L14: 2873 | M14: 3000 | N14: 3121 | O14: 3146 | P14: 3071 | Q14: 3187 | R14: 3264 | S14: 3295 | T14: 3224 | U14: 3380 | V14: 3420 | W14: 3620 | X14: 0.011937271 | Y14: 0.014880493 | Z14: 0.011851402 | AA14: 0.024401231
... B29: TWO | C29: United States | D29: REIT - Mortgage | E29: Dec'25 | F29: -39.5 | G29: 166.7 | H29: -33.03 | I29: -88.9 | J29: 346.8 | K29: -146.17 | L29: -100.54 | M29: 239.29 | N29: 349.87 | O29: -233.74 | P29: 259.25 | Q29: 136.57 | R29: -73.11 | S29: 271.04 | T29: 7.89 | U29: 23.61 | V29: 201.36 | W29: 71.94 | X29: -0.42334316 | Y29: -0.32991618 | Z29: 1.1963126 | AA29: -0.39511808
B30: 8331 | C30: Japan | D30: N/A | E30: Sep'26 | F30: 7 | G30: 52659 | H30: 49973 | I30: 61244 | J30: 63020 | K30: 60603 | L30: 55498 | M30: 60170 | N30: 60590 | O30: 61776 | P30: 55515 | Q30: 67905 | R30: 66474 | S30: 64252 | T30: 65179 | U30: 75955 | V30: 81359 | W30: 84291 | X30: 0.038025387 | Y30: 0.030514385 | Z30: 0.054752446 | AA30: 0.069884392
B31: 7337 | C31: Japan | D31: N/A | E31: Sep'26 | F31: 6.9 | G31: 35473 | H31: 31052 | I31: 36024 | J31: 28051 | K31: 34042 | L31: 33564 | M31: 36058 | N31: 36180 | O31: 35605 | P31: 27550 | Q31: 38834 | R31: 38922 | S31: 42895 | T31: 37223 | U31: 42154 | V31: 39847 | W31: 54153 | X31: 0.065269465 | Y31: 0.021029429 | Z31: 0.005738427 | AA31: 0.069442817
B32: 8386 | C32: Japan | D32: N/A | E32: Jun'26 | F32: 6 | G32: 17037 | H32: 18567 | I32: 15023 | J32: 21178 | K32: 20437 | L32: 19040 | M32: 14645 | N32: 16940 | O32: 14494 | P32: 17039 | Q32: 17520 | R32: 17247 | S32: 14292 | T32: 19913 | U32: 18479 | V32: 20602 | W32: 18703 | X32: 0.043480892 | Y32: 0.013904193 | Z32: 0.047975862 | AA32: 0.060188849
B33: 1814 | C33: Japan | D33: N/A | E33: Jun'26 | F33: 4.9 | G33: 16376 | H33: 18292 | I33: 18640 | J33: 18790 | K33: 20028 | L33: 16361 | M33: 16655 | N33: 17353 | O33: 18899 | P33: 20503 | Q33: 21060 | R33: 19901 | S33: 21156 | T33: 23529 | U33: 24442 | V33: 21464 | W33: 25558 | X33: 0.036625514 | Y33: 0.039488126 | Z33: 0.017556274 | AA33: 0.048592023
B34: 6762 | C34: Japan | D34: N/A | E34: Jun'26 | F34: 3.5 | G34: 474127 | H34: 499670 | I34: 508269 | J34: 510504 | K34: 611489 | L34: 586972 | M34: 471852 | N34: 503399 | O34: 556312 | P34: 559250 | Q34: 484915 | R34: 518809 | S34: 570692 | T34: 581043 | U34: 534262 | V34: 535753 | W34: 647610 | X34: 0.010213876 | Y34: 0.022893964 | Z34: 0.0076850299 | AA34: 0.034620457
B35: 8346 | C35: Japan | D35: N/A | E35: Jun'26 | F35: 3.2 | G35: 14750 | H35: 14288 | I35: 14091 | J35: 14536 | K35: 13215 | L35: 13962 | M35: 13006 | N35: 14421 | O35: 13647 | P35: 15023 | Q35: 13888 | R35: 15806 | S35: 15618 | T35: 16217 | U35: 16230 | V35: 18249 | W35: 17757 | X35: 0.019789509 | Y35: 0.038063352 | Z35: 0.038248971 | AA35: 0.032255632
B36: 3132 | C36: Japan | D36: N/A | E36: Jun'26 | F36: 2.9 | G36: 184279 | H36: 194802 | I36: 204678 | J36: 241320 | K36: 251242 | L36: 275442 | M36: 261259 | N36: 278562 | O36: 268399 | P36: 253342 | Q36: 228415 | R36: 256330 | S36: 262630 | T36: 262829 | U36: 252391 | V36: 281613 | W36: 293822 | X36: 0.0094802027 | Y36: 0.02373382 | Z36: 0.024447388 | AA36: 0.02944133
B37: 8841 | C37: Japan | D37: N/A | E37: Jun'26 | F37: 2.8 | G37: 4012 | H37: 4018 | I37: 4257 | J37: 4001 | K37: 4053 | L37: 3956 | M37: 3676 | N37: 3477 | O37: 3347 | P37: 3486 | Q37: 3405 | R37: 2993 | S37: 3282 | T37: 3382 | U37: 3495 | V37: 3465 | W37: 3666 | X37: -0.0078991341 | Y37: 0.0068902159 | Z37: 0.035888078 | AA37: 0.028185555
B38: 8601 | C38: Japan | D38: N/A | E38: Jun'26 | F38: 2.5 | G38: 154678 | H38: 166602 | I38: 148323 | J38: 146604 | K38: 192551 | L38: 233022 | M38: 293864 | N38: 266255 | O38: 303827 | P38: 335377 | Q38: 372008 | R38: 176188 | S38: 159958 | T38: 160018 | U38: 876860 | V38: 160993 | W38: 194358 | X38: -0.16804388 | Y38: 0.5815115 | Z38: -0.011066813 | AA38: 0.02533456
B39: 3467 | C39: Japan | D39: N/A | E39: Jun'26 | F39: 2.5 | Q39: 13370 | R39: 4971 | S39: 8508 | T39: 6124 | U39: 11140 | V39: 6930 | W39: 9318 | Y39: -0.067631092 | Z39: 0.063721823 | AA39: 0.024769127
B40: 4768 | C40: Japan | D40: N/A | E40: Dec'25 | F40: 2.5 | G40: 192635 | H40: 210069 | I40: 235267 | J40: 207843 | K40: 207843 | L40: 242609 | M40: 278447 | N40: 219002 | O40: 237312 | P40: 266664 | Q40: 303058 | R40: 252540 | S40: 285406 | T40: 315541 | U40: 379591 | V40: 310587 | W40: 317072 | X40: 0.044126038 | Y40: 0.066173819 | Z40: 0.047074881 | AA40: 0.024525898
B41: 2222 | C41: Japan | D41: N/A | E41: Sep'26 | F41: 2.4 | G41: 10963 | H41: 9270 | I41: 9515 | J41: 10584 | K41: 15271 | L41: 14785 | M41: 13853 | N41: 15038 | O41: 18145 | P41: 16999 | Q41: 15526 | R41: 17380 | S41: 20901 | T41: 18542 | U41: 16976 | V41: 18811 | W41: 22698 | X41: 0.021791939 | Y41: 0.020041742 | Z41: 0.019390507 | AA41: 0.023886747
B42: 8081 | C42: Japan | D42: N/A | E42: Jun'26 | F42: 2 | G42: 23819 | H42: 23234 | I42: 32599 | J42: 19355 | K42: 26199 | L42: 24763 | M42: 36102 | N42: 24703 | O42: 28944 | P42: 26716 | Q42: 35908 | R42: 22441 | S42: 29371 | T42: 27588 | U42: 46265 | V42: 29609 | W42: 32048 | X42: 0.0076199797 | Y42: 0.089820307 | Z42: 0.057040544 | AA42: 0.020153125
B43: 6908 | C43: Japan | D43: N/A | E43: Jun'26 | F43: 2 | G43: 10792 | H43: 10446 | I43: 11439 | J43: 11929 | K43: 13614 | L43: 13976 | M43: 13384 | N43: 12496 | O43: 15644 | P43: 13000 | Q43: 14131 | R43: 12534 | S43: 14625 | T43: 15009 | U43: 14164 | V43: 15163 | W43: 15811 | X43: 0.037004973 | Y43: 0.00058615606 | Z43: 0.046669744 | AA43: 0.020114991
B44: 9022 | C44: Japan | D44: N/A | E44: Sep'26 | F44: 1.9 | G44: 299440 | H44: 248750 | I44: 309342 | J44: 324797 | K44: 385012 | L44: 381134 | M44: 395091 | N44: 422454 | O44: 455472 | P44: 437390 | Q44: 435290 | R44: 438575 | S44: 494172 | T44: 463810 | U44: 478283 | V44: 503919 | W44: 531950 | X44: 0.014633657 | Y44: 0.023469755 | Z44: 0.034853107 | AA44: 0.019471349
B45: 6971 | C45: Japan | D45: N/A | E45: Sep'26 | F45: 1.9 | G45: 479328 | H45: 483273 | I45: 491954 | J45: 520218 | K45: 514325 | L45: 498835 | M45: 479420 | N45: 505870 | O45: 507382 | P45: 511549 | Q45: 498868 | R45: 499720 | S45: 493467 | T45: 522399 | U45: 478038 | V45: 513347 | W45: 530611 | X45: 0.0054152417 | Y45: -0.010340271 | Z45: 0.0068352909 | AA45: 0.01850491
B46: 2676 | C46: Japan | D46: N/A | E46: Jun'26 | F46: 1.8 | G46: 5181 | H46: 5200 | I46: 6001 | J46: 4974 | K46: 6144 | L46: 5816 | M46: 6426 | N46: 6080 | O46: 6649 | P46: 6231 | Q46: 6264 | R46: 6421 | S46: 6893 | T46: 6334 | U46: 8450 | V46: 6068 | W46: 7404 | X46: 0.0039908559 | Y46: 0.084362458 | Z46: -0.012563172 | AA46: 0.018417733
B47: 2282 | C47: Japan | D47: N/A | E47: Jun'26 | F47: 1.6 | G47: 308418 | H47: 349874 | I47: 0 | J47: 311512 | K47: 322512 | L47: 352079 | M47: 273689 | N47: 322175 | O47: 329947 | P47: 345835 | Q47: 305475 | R47: 338050 | S47: 345814 | T47: 371154 | U47: 315535 | V47: 354141 | W47: 368458 | X47: 0.018963071 | Y47: 0.0073943784 | Z47: 0.011740516 | AA47: 0.016330075
B48: 9020 | C48: Japan | D48: N/A | E48: Sep'26 | F48: 1.6 | G48: 604954 | H48: 496173 | I48: 557618 | J48: 557455 | K48: 612011 | L48: 678454 | M48: 629472 | N48: 670357 | O48: 701193 | P48: 729096 | Q48: 686670 | R48: 708447 | S48: 730953 | T48: 761483 | U48: 715349 | V48: 747747 | W48: 776926 | X48: 0.011343298 | Y48: 0.0099319389 | Z48: 0.013476294 | AA48: 0.015554898
B49: 9064 | C49: Japan | D49: N/A | E49: Sep'26 | F49: 1.5 | G49: 506916 | H49: 421232 | I49: 424159 | J49: 459596 | K49: 512212 | L49: 404701 | M49: 420212 | N49: 446370 | O49: 500245 | P49: 391799 | Q49: 405632 | R49: 434781 | S49: 504118 | T49: 418165 | U49: 437352 | V49: 469422 | W49: 531982 | X49: 0.015184901 | Y49: 0.017995162 | Z49: 0.019304888 | AA49: 0.01523408
B50: 4272 | C50: Japan | D50: N/A | E50: Jun'26 | F50: 1.5 | G50: 42393 | H50: 49255 | I50: 46710 | J50: 48296 | K50: 54432 | L50: 50899 | M50: 44753 | N50: 48584 | O50: 49324 | P50: 51845 | Q50: 52038 | R50: 53645 | S50: 55464 | T50: 58846 | U50: 54629 | V50: 54758 | W50: 58817 | X50: 0.032869779 | Y50: 0.011777647 | Z50: 0.0050003594 | AA50: 0.014989025
B51: 8411 | C51: Japan | D51: N/A | E51: Sep'26 | F51: 1.5 | G51: 681625 | H51: 802755 | I51: 689784 | J51: 451997 | K51: 995900 | L51: 641535 | M51: 771638 | N51: 788870 | O51: 807972 | P51: 753625 | Q51: 950408 | R51: 1071722 | S51: 1058632 | T51: 818078 | U51: 957553 | V51: 1139963 | W51: 1117111 | X51: 0.016809206 | Y51: 0.0018325964 | Z51: 0.017470881 | AA51: 0.014714563
... B65: 7480 | C65: Japan | D65: N/A | E65: Jun'26 | F65: -1.1 | G65: 13633 | H65: 15441 | I65: 17523 | J65: 15847 | K65: 17287 | L65: 17783 | M65: 16522 | N65: 14281 | O65: 13030 | P65: 12619 | Q65: 10999 | R65: 11021 | S65: 11315 | T65: 12378 | U65: 11917 | V65: 10288 | W65: 10812 | X65: -0.0052443748 | Y65: 0.020081815 | Z65: -0.015719157 | AA65: -0.010959083
B66: SOUTHWEST | C66: India | D66: N/A | E66: Jun'26 | F66: 18.4 | G66: 279.55 | H66: 308.89 | I66: 351.02 | J66: 258.34 | K66: 248.47 | L66: 352.8 | M66: 383.03 | N66: 229.85 | O66: 232.72 | P66: 421.54 | Q66: 450.13 | R66: 294.29 | S66: 273.6 | T66: 485.42 | U66: 749.63 | V66: 402.16 | W66: 624.45 | X66: 0.04437467 | Y66: 0.19920981 | Z66: 0.059830055 | AA66: 0.18361323
B67: CLEDUCATE | C67: India | D67: N/A | E67: Jun'26 | F67: 16 | G67: 532.07 | H67: 501.62 | I67: 539.28 | J67: 692.53 | K67: 891.22 | L67: 631.34 | M67: 698.04 | N67: 900.19 | O67: 890.44 | P67: 664.23 | Q67: 669.54 | R67: 939.86 | S67: 986.82 | T67: 705.36 | U67: 948.81 | V67: 1457 | W67: 1643 | X67: 0.012614823 | Y67: 0.084586774 | Z67: 0.14441822 | AA67: 0.1601224
B68: NILASPACES | C68: India | D68: N/A | E68: Sep'26 | F68: 12.3 | G68: 8.81 | H68: 9.98 | I68: 10.11 | J68: 0 | K68: 0 | L68: 0 | M68: 0 | N68: 0 | O68: 584.23 | P68: 322.9 | Q68: 311.06 | R68: 319.07 | S68: 330.25 | T68: 397.61 | U68: 408.33 | V68: 421.84 | W68: 522 | X68: 0.058218004 | Y68: 0.071627921 | Z68: 0.070619683 | AA68: 0.12307208
B69: JYOTISTRUC | C69: India | D69: N/A | E69: Sep'26 | F69: 11.8 | G69: 0 | H69: 21.66 | I69: 156.51 | J69: 138.85 | K69: 438.64 | L69: 1558 | M69: 1852 | N69: 814.64 | O69: 557.99 | P69: 1290 | Q69: 882.93 | R69: 1075 | S69: 1374 | T69: 1647 | U69: 1562 | V69: 1506 | W69: 2090 | X69: 0.07724046 | Y69: 0.13638874 | Z69: 0.076175327 | AA69: 0.1175891
B70: APOLLO | C70: India | D70: N/A | E70: Jun'26 | F70: 10.7 | G70: 458.99 | H70: 645.92 | I70: 1057 | J70: 562.7 | K70: 520.59 | L70: 823.52 | M70: 1068 | N70: 576.91 | O70: 871.63 | P70: 913.43 | Q70: 1354 | R70: 912.02 | S70: 1607 | T70: 1484 | U70: 1618 | V70: 1336 | W70: 2253 | X70: 0.11920526 | Y70: 0.04928113 | Z70: 0.075427591 | AA70: 0.10686518
B71: POLICYBZR | C71: India | D71: N/A | E71: Sep'26 | F71: 9.8 | G71: 3673 | H71: 5403 | I71: 5052 | J71: 5735 | K71: 6101 | L71: 8691 | M71: 6656 | N71: 8116 | O71: 8709 | P71: 10896 | Q71: 10105 | R71: 11672 | S71: 12916 | T71: 15079 | U71: 13480 | V71: 16136 | W71: 18560 | X71: 0.09175459 | Y71: 0.06780921 | Z71: 0.083993452 | AA71: 0.097967402
B72: PCJEWELLER | C72: India | D72: N/A | E72: Sep'26 | F72: 8.2 | G72: 6110 | H72: 1886 | I72: 5474 | J72: 8976 | K72: 8543 | L72: 1734 | M72: 676.8 | N72: 4492 | O72: 400.6 | P72: 484.9 | Q72: 4012 | R72: 5050 | S72: 6395 | T72: 6990 | U72: 7249 | V72: 8253 | W72: 8754 | X72: 0.40805048 | Y72: 0.14420635 | Z72: 0.12470799 | AA72: 0.081663032
B73: SUNDARMFIN | C73: India | D73: N/A | E73: Sep'26 | F73: 7.6 | G73: 6100 | H73: 7580 | I73: 6329 | J73: 7147 | K73: 7265 | L73: 8111 | M73: 7662 | N73: 8342 | O73: 8942 | P73: 11368 | Q73: 9006 | R73: 9449 | S73: 10017 | T73: 11272 | U73: 9992 | V73: 10830 | W73: 13206 | X73: -0.0024096386 | Y73: 0.024808776 | Z73: 0.033906212 | AA73: 0.075728432
B74: SHRIPISTON | C74: India | D74: N/A | E74: Sep'26 | F74: 5.5 | G74: 5106 | H74: 5873 | I74: 6201 | J74: 6522 | K74: 6360 | L74: 7010 | M74: 7164 | N74: 7516 | O74: 7657 | P74: 8556 | Q74: 8371 | R74: 8765 | S74: 8479 | T74: 9884 | U74: 9633 | V74: 10165 | W74: 10563 | X74: 0.038863364 | Y74: 0.035550297 | Z74: 0.038083839 | AA74: 0.054610728
B75: APLLTD | C75: India | D75: N/A | E75: Jun'26 | F75: 3.8 | G75: 12923 | H75: 12717 | I75: 14157 | J75: 12621 | K75: 14750 | L75: 15090 | M75: 14065 | N75: 14862 | O75: 15949 | P75: 16306 | Q75: 15170 | R75: 15617 | S75: 16480 | T75: 16928 | U75: 17696 | V75: 17107 | W75: 19102 | X75: 0.0097840278 | Y75: 0.039348859 | Z75: 0.0223318 | AA75: 0.038439548
B76: SAKSOFT | C76: India | D76: N/A | E76: Sep'26 | F76: 2.8 | G76: 1250 | H76: 1311 | I76: 1512 | J76: 1670 | K76: 1717 | L76: 1821 | M76: 1835 | N76: 1904 | O76: 1928 | P76: 1949 | Q76: 2010 | R76: 2153 | S76: 2268 | T76: 2399 | U76: 2491 | V76: 2585 | W76: 2536 | X76: 0.053699284 | Y76: 0.054473386 | Z76: 0.046396735 | AA76: 0.027506928
B77: INDUSTOWER | C77: India | D77: N/A | E77: Sep'26 | F77: 2.4 | G77: 69274 | H77: 71163 | I77: 68973 | J77: 79666 | K77: 67650 | L77: 67529 | M77: 70759 | N77: 71325 | O77: 71990 | P77: 71932 | Q77: 73830 | R77: 74653 | S77: 75474 | T77: 77271 | U77: 80576 | V77: 81882 | W77: 83001 | X77: 0.018043929 | Y77: 0.022394996 | Z77: 0.023472761 | AA77: 0.023879849
... B97: LFCR | C97: United States | D97: Drug Manufacturers - Specialty & Generic | E97: Sep'25 | F97: 5 | G97: 41.63 | H97: 11.11 | I97: 37.4 | J97: 21.13 | K97: 23.72 | L97: 21.86 | M97: 26.54 | N97: 0 | O97: 24.52 | P97: 30.15 | Q97: 35.7 | R97: 37.89 | S97: 24.71 | T97: 32.56 | U97: 35.15 | V97: 36.44 | W97: 31.11 | X97: 0.018762164 | Y97: -0.004202965 | Z97: -0.011127312 | AA97: 0.049666305
B98: ODD | C98: United States | D98: Household & Personal Products | E98: Sep'25 | F98: 3.8 | I98: 90.41 | J98: 97.66 | K98: 68.95 | L98: 67.5 | M98: 165.65 | N98: 151.31 | O98: 94.47 | P98: 97.25 | Q98: 211.63 | R98: 192.77 | S98: 119 | T98: 123.64 | U98: 268.08 | V98: 241.14 | W98: 147.9 | X98: 0.042519939 | Y98: 0.087243447 | Z98: 0.068757196 | AA98: 0.038438007
B99: RHLD | C99: United States | D99: Specialty Business Services | E99: Sep'25 | F99: 3.2 | O99: 96.89 | P99: 99.9 | Q99: 104.01 | R99: 108.57 | S99: 107.14 | T99: 100.86 | U99: 103.89 | V99: 119.59 | W99: 120.87 | X99: 0.0022877842 | Y99: -0.00028532027 | Z99: 0.02620939 | AA99: 0.03182071
B100: ACAD | C100: United States | D100: Biotechnology | E100: Sep'25 | F100: 2.8 | G100: 131.61 | H100: 130.76 | I100: 115.47 | J100: 134.56 | K100: 130.71 | L100: 136.49 | M100: 118.46 | N100: 165.24 | O100: 211.7 | P100: 231.04 | Q100: 205.83 | R100: 241.96 | S100: 250.4 | T100: 259.6 | U100: 244.32 | V100: 264.57 | W100: 278.63 | X100: 0.030735125 | Y100: 0.040186262 | Z100: 0.022694423 | AA100: 0.027706622
B101: BAER | C101: United States | D101: Security & Protection Services | E101: Sep'25 | F101: 2.7 | G101: 34.97 | H101: 0.67 | I101: 0.07 | J101: 12.75 | K101: 32.45 | L101: 1.11 | M101: 0.37 | N101: 11.62 | O101: 53.62 | P101: 1.11 | Q101: 5.51 | R101: 13.01 | S101: 64.51 | T101: 15.59 | U101: 15.65 | V101: 30.75 | W101: 67.89 | X101: 0.17209413 | Y101: 0.1028189 | Z101: 0.16311144 | AA101: 0.026719368
B102: AME | C102: United States | D102: Specialty Industrial Machinery | E102: Sep'25 | F102: 2.6 | G102: 1441 | H102: 1504 | I102: 1459 | J102: 1515 | K102: 1552 | L102: 1626 | M102: 1597 | N102: 1646 | O102: 1623 | P102: 1731 | Q102: 1736 | R102: 1735 | S102: 1709 | T102: 1762 | U102: 1732 | V102: 1778 | W102: 1893 | X102: 0.0044856027 | Y102: -0.00057620282 | Z102: 0.0061977515 | AA102: 0.026357255
B103: NRC | C103: United States | D103: Health Information Services | E103: Sep'25 | F103: -0.9 | G103: 37.77 | H103: 38.3 | I103: 38.44 | J103: 37.29 | K103: 37.69 | L103: 38.14 | M103: 36.47 | N103: 36.16 | O103: 37.95 | P103: 38 | Q103: 35.31 | R103: 35.02 | S103: 35.82 | T103: 36.91 | U103: 33.55 | V103: 34.04 | W103: 34.61 | X103: -0.0075615678 | Y103: -0.01230253 | Z103: -0.006935598 | AA103: -0.0086231471
B104: LVRO | C104: United States | D104: Agricultural Inputs | E104: Jun'25 | F104: -8.3 | I104: 878.68 | J104: 2007 | K104: 2007 | L104: 2610 | M104: 1122 | N104: 2286 | O104: 3220 | P104: 2526 | Q104: 1315 | R104: 2366 | S104: 3066 | T104: 2546 | U104: 1415 | V104: 2053 | W104: 2316 | X104: 0.0021567993 | Y104: 0.010760788 | Z104: -0.033322687 | AA104: -0.082599119
B105: NJR | C105: United States | D105: Utilities - Regulated Gas | E105: n/a | F105: -24 | G105: 675.84 | H105: 912.32 | I105: 552.34 | J105: 765.49 | K105: 723.57 | L105: 644.03 | M105: 264.08 | N105: 331.33 | O105: 467.21 | P105: 657.91 | Q105: 275.64 | R105: 395.78 | S105: 488.36 | T105: 913.03 | U105: 298.95 | V105: 336.08 | W105: 0 | X105: 0.14035397 | Y105: 0.011245604 | Z105: -0.028481194 | AA105: -0.23981301
B106: 2160 | C106: Japan | D106: N/A | E106: Sep'25 | F106: 6.8 | G106: 3071 | H106: 3154 | I106: 3933 | J106: 4221 | K106: 4606 | L106: 4657 | M106: 4206 | N106: 9890 | O106: 6451 | P106: 5463 | Q106: 5948 | R106: 5785 | S106: 5458 | T106: 6419 | U106: 5321 | V106: 6931 | W106: 7105 | X106: 0.042200053 | Y106: -0.026556544 | Z106: 0.049862942 | AA106: 0.068258113
B107: 7177 | C107: Japan | D107: N/A | E107: Sep'25 | F107: 0.2 | G107: 8742 | H107: 12365 | I107: 11321 | J107: 10836 | K107: 9931 | L107: 8383 | M107: 11377 | N107: 11585 | O107: 11030 | P107: 11014 | Q107: 11990 | R107: 7883 | S107: 11221 | T107: 9223 | U107: 11869 | V107: 13201 | W107: 11321 | X107: -0.042533485 | Y107: -0.0030012154 | Z107: 0.13230172 | AA107: 0.0021971262
B108: 2811 | C108: Japan | D108: N/A | E108: Sep'25 | F108: -0.2 | G108: 49900 | H108: 47825 | I108: 44144 | J108: 51645 | K108: 54817 | L108: 55011 | M108: 48009 | N108: 57313 | O108: 59544 | P108: 59863 | Q108: 67378 | R108: 80863 | S108: 78138 | T108: 80489 | U108: 67167 | V108: 71514 | W108: 77628 | X108: 0.072057909 | Y108: -0.00068759206 | Z108: -0.030486831 | AA108: -0.0017153928
B109: 1060 | C109: Hong Kong | D109: N/A | E109: H1 2026 | F109: 15.4 | N109: 1932 | O109: 1358 | P109: 2294 | Q109: 1829 | R109: 0 | S109: 2616 | T109: 0 | U109: 3051 | V109: 3652 | W109: 4047 | X109: -0.34040659 | Y109: 0.27491564 | Z109: 0.64443268 | AA109: 0.15355725
B110: CRLO | C110: France | D110: N/A | E110: H1 2025 | F110: -0.1 | N110: 192.29 | O110: 206.73 | P110: 188.58 | Q110: 162.52 | R110: 204.68 | S110: 207.5 | T110: 196.82 | U110: 216.99 | V110: 201.09 | W110: 206.99 | X110: 0.010795514 | Y110: 0.070600892 | Z110: -0.0043462996 | AA110: -0.00062013619
B111: 1020 | C111: Hong Kong | D111: N/A | E111: H1 2025 | F111: -2.9 | N111: 0 | O111: 71.89 | P111: 54.49 | Q111: 21.7 | R111: 35.24 | S111: 34.07 | T111: 77.48 | U111: 44.51 | V111: 48.73 | W111: 28.03 | X111: 0.15800687 | Y111: 0.13537895 | Z111: 0.070517512 | AA111: -0.029493628
B112: 1140 | C112: Hong Kong | D112: N/A | E112: H1 2026 | F112: -4.8 | N112: 64.14 | O112: 49.92 | P112: 45.31 | Q112: 85.91 | R112: 106.83 | S112: 147.42 | T112: 160.91 | U112: 131.47 | V112: 144.16 | W112: 119.55 | X112: 0.29989364 | Y112: 0.09092542 | Z112: 0.068291166 | AA112: -0.047725872
B113: 1150 | C113: Hong Kong | D113: N/A | E113: H1 2025 | F113: -17.6 | N113: 93.44 | O113: 112.83 | P113: 132.19 | Q113: 118.36 | R113: 114.92 | S113: 100 | T113: 72.52 | U113: 63.16 | V113: 48.7 | W113: 50.06 | X113: -0.12819301 | Y113: -0.1360276 | Z113: -0.18887621 | AA113: -0.1756101
B114: 1010 | C114: Hong Kong | D114: N/A | E114: H1 2025 | F114: -57 | N114: 57.32 | O114: 54.47 | P114: 51.15 | Q114: 43.6 | R114: 137.48 | S114: 101.69 | T114: 12.28 | U114: 15.96 | V114: 20.08 | W114: 16.12 | X114: -0.11640513 | Y114: -0.093679037 | Z114: -0.43902621 | AA114: -0.57042864

Sheet Operating Income
B2: Ticker | C2: Country | D2: Industry | E2: Latest_Date | F2: Growth_Rate | G2: 4Q21 | H2: 1Q22 | I2: 2Q22 | J2: 3Q22 | K2: 4Q22 | L2: 1Q23 | M2: 2Q23 | N2: 3Q23 | O2: 4Q23 | P2: 1Q24 | Q2: 2Q24 | R2: 3Q24 | S2: 4Q24 | T2: 1Q25 | U2: 2Q25 | V2: 3Q25 | W2: 4Q25 | X2: 1Q25 롤링 | Y2: 2Q25 롤링 | Z2: 3Q25 롤링 | AA2: 4Q25 롤링
B3: PLTR | C3: United States | D3: Software - Infrastructure | E3: Dec'25 | F3: 66.4 | G3: -58.94 | H3: -39.44 | I3: -41.75 | J3: -62.19 | K3: -17.83 | L3: 4.12 | M3: 10.07 | N3: 39.98 | O3: 65.79 | P3: 80.88 | Q3: 105.34 | R3: 113.14 | S3: 11.04 | T3: 176.05 | U3: 269.32 | V3: 393.26 | W3: 575.39 | X3: 0.30660438 | Y3: 0.40431985 | Z3: 0.49182688 | AA3: 0.66419904
B4: TER | C4: United States | D4: Semiconductor Equipment & Materials | E4: Dec'25 | F4: 26.2 | G4: 270.83 | H4: 200.56 | I4: 247.99 | J4: 232.71 | K4: 215.44 | L4: 94.9 | M4: 145.01 | N4: 147.96 | O4: 130.26 | P4: 81.97 | Q4: 154.88 | R4: 154.54 | S4: 154.55 | T4: 135.3 | U4: 93.04 | V4: 145.32 | W4: 293.2 | X4: 0.097684727 | Y4: -0.10319222 | Z4: -0.017155723 | AA4: 0.2624903
B5: ARLP | C5: United States | D5: Thermal Coal | E5: Dec'25 | F5: 16.2 | G5: 59.22 | H5: 88.46 | I5: 176.51 | J5: 180.36 | K5: 212.17 | L5: 205.83 | M5: 182.35 | N5: 163.9 | O5: 114.16 | P5: 158.32 | Q5: 115.4 | R5: 98.95 | S5: 44.36 | T5: 92.78 | U5: 87.2 | V5: 103.46 | W5: 97.34 | X5: -0.15715896 | Y5: -0.080229879 | Z5: 0.013950323 | AA5: 0.16162294
B6: WWD | C6: United States | D6: Aerospace & Defense | E6: Mar'26 | F6: 13.2 | G6: 35.75 | H6: 56.66 | I6: 56.24 | J6: 59.66 | K6: 33.82 | L6: 45.56 | M6: 104.06 | N6: 91.57 | O6: 103.28 | P6: 120.83 | Q6: 117.46 | R6: 99.73 | S6: 93.94 | T6: 123.53 | U6: 120.07 | V6: 158.01 | W6: 159.42 | X6: 0.0062505788 | Y6: 0.0060046933 | Z6: 0.1332815 | AA6: 0.13213601
B7: FN | C7: United States | D7: Electronic Components | E7: Jun'26 | F7: 10 | G7: 51.58 | H7: 53.66 | I7: 56.71 | J7: 62.19 | K7: 66.29 | L7: 67.7 | M7: 62.76 | N7: 63.98 | O7: 68.82 | P7: 71.31 | Q7: 73.7 | R7: 76.89 | S7: 80.09 | T7: 80.12 | U7: 89 | V7: 94.29 | W7: 114.4 | X7: 0.029173151 | Y7: 0.049227799 | Z7: 0.053357866 | AA7: 0.099883552
B8: BSRR | C8: United States | D8: Banks - Regional | E8: Dec'25 | F8: 8.8 | G8: 12.69 | H8: 10.14 | I8: 12.49 | J8: 13.27 | K8: 9.01 | L8: 11.46 | M8: 13.43 | N8: 13.32 | O8: 8.25 | P8: 12.65 | Q8: 14.21 | R8: 14.41 | S8: 12.6 | T8: 12.27 | U8: 14.24 | V8: 12.7 | W8: 17.14 | X8: -0.0070540189 | Y8: 0.0005608525 | Z8: -0.031950673 | AA8: 0.087627871
B9: NSSC | C9: United States | D9: Security & Protection Services | E9: Jun'26 | F9: 7.4 | G9: 1.27 | H9: 4.58 | I9: 9.38 | J9: 3.65 | K9: 4.33 | L9: 10.54 | M9: 11.36 | N9: 11.56 | O9: 13.81 | P9: 14.49 | Q9: 15.66 | R9: 11.86 | S9: 11.17 | T9: 11.15 | U9: 12.73 | V9: 13.64 | W9: 14.75 | X9: -0.062805566 | Y9: -0.058788122 | Z9: 0.037945001 | AA9: 0.073526391
B10: FLXS | C10: United States | D10: Furnishings, Fixtures & Appliances | E10: Jun'26 | F10: 6.8 | G10: -8.01 | H10: 5.76 | I10: 3.58 | J10: 0.43 | K10: 0.97 | L10: 2.12 | M10: 4.24 | N10: 1.92 | O10: 4.58 | P10: 5.61 | Q10: 4.69 | R10: 6.05 | S10: 6.66 | T10: 8.27 | U10: 10.27 | V10: 8.99 | W10: 9 | X10: 0.11560191 | Y10: 0.21737437 | Z10: 0.09408 | AA10: 0.068441065
B11: DVA | C11: United States | D11: Medical Care Facilities | E11: Dec'25 | F11: 6.2 | G11: 386.26 | H11: 331.26 | I11: 423.57 | J11: 303.28 | K11: 0 | L11: 304.83 | M11: 396.84 | N11: 488.71 | O11: 315.33 | P11: 442.02 | Q11: 500.92 | R11: 531.17 | S11: 432.53 | T11: 433.33 | U11: 530.48 | V11: 507.31 | W11: 551.21 | X11: -0.0045577561 | Y11: 0.015574699 | Z11: -0.012378665 | AA11: 0.062343393
B12: RMBS | C12: United States | D12: Semiconductors | E12: Dec'25 | F12: 5.2 | G12: 16.47 | H12: 9.52 | I12: 30.06 | J12: 19.33 | K12: 22.34 | L12: 8.84 | M12: 28.09 | N12: 18.31 | O12: 36.26 | P12: 30.83 | Q12: 40.19 | R12: 50.15 | S12: 57.86 | T12: 63.14 | U12: 62.99 | V12: 63.26 | W12: 70.83 | X12: 0.18047255 | Y12: 0.10788303 | Z12: 0.055992141 | AA12: 0.052457027
B13: IDXX | C13: United States | D13: Diagnostics & Research | E13: Dec'25 | F13: 4.1 | G13: 199.19 | H13: 248.34 | I13: 179.07 | J13: 244.83 | K13: 226.53 | L13: 280.4 | M13: 296.14 | N13: 275.28 | O13: 245.3 | P13: 298.96 | Q13: 325.3 | R13: 303.89 | S13: 261.69 | T13: 316.53 | U13: 373.05 | V13: 354.85 | W13: 315.61 | X13: 0.014766691 | Y13: 0.039547461 | Z13: 0.040600402 | AA13: 0.041282577
B14: CSWC | C14: United States | D14: Asset Management | E14: Sep'26 | F14: 3.9 | G14: 16.49 | H14: 16.9 | I14: 18.11 | J14: 21.61 | K14: 26.62 | L14: 31.58 | M14: 34.68 | N14: 36.89 | O14: 41.24 | P14: 41.22 | Q14: 43.73 | R14: 42.6 | S14: 45.4 | T14: 43.67 | U14: 47.98 | V14: 50.04 | W14: 52.68 | X14: 0.014165944 | Y14: 0.024230331 | Z14: 0.04141386 | AA14: 0.038911754
... B29: TWO | C29: United States | D29: REIT - Mortgage | E29: Dec'25 | F29: -129.4 | G29: 1.48 | H29: 334.76 | I29: -44.08 | J29: 303.66 | K29: -269.09 | L29: -175.3 | M29: 222.16 | N29: 354.05 | O29: -459.45 | P29: 216.76 | Q29: 69.71 | R29: -248.84 | S29: 308.94 | T29: -78.52 | U29: -57.45 | V29: 52.41 | W29: 17.29 | X29: -0.85200681 | Y29: -2.4792357 | Z29: -3.9706076 | AA29: -1.2940367
B30: 6971 | C30: Japan | D30: N/A | E30: Sep'26 | F30: 75.9 | G30: 42779 | H30: 30452 | I30: 41428 | J30: 35060 | K30: 37396 | L30: 14633 | M30: 25677 | N30: 28325 | O30: 25842 | P30: 13079 | Q30: 20956 | R30: 16920 | S30: -25601 | T30: 55172 | U30: 18550 | V30: 23395 | W30: 28676 | X30: 1.6602114 | Y30: -0.035672454 | Z30: 0.09955259 | AA30: 0.75894905
B31: 2282 | C31: Japan | D31: N/A | E31: Jun'26 | F31: 30.5 | G31: 11670 | H31: 20357 | I31: 0 | J31: 13202 | K31: 6423 | L31: 1760 | M31: -10848 | N31: 17632 | O31: 13023 | P31: 12269 | Q31: -11247 | R31: 19099 | S31: 9780 | T31: 14203 | U31: -6510 | V31: 18261 | W31: 20694 | X31: 0.064680111 | Y31: 0.14879849 | Z31: -0.022913704 | AA31: 0.30542341
B32: 1814 | C32: Japan | D32: N/A | E32: Jun'26 | F32: 26.5 | G32: 374 | H32: 840 | I32: 743 | J32: 229 | K32: 704 | L32: 471 | M32: 483 | N32: 275 | O32: -41 | P32: 263 | Q32: 1094 | R32: 520 | S32: 599 | T32: 799 | U32: 1778 | V32: 793 | W32: 1649 | X32: 0.21647819 | Y32: 0.22709163 | Z32: 0.073863636 | AA32: 0.26455026
B33: 8841 | C33: Japan | D33: N/A | E33: Jun'26 | F33: 17 | G33: 1378 | H33: 1328 | I33: 1483 | J33: 1358 | K33: 1277 | L33: 1024 | M33: 609 | N33: 787 | O33: 452 | P33: 677 | Q33: 370 | R33: 313 | S33: 369 | T33: 608 | U33: 129 | V33: 420 | W33: 629 | X33: -0.039907461 | Y33: -0.14518072 | Z33: 0.075405215 | AA33: 0.17038008
B34: 2676 | C34: Japan | D34: N/A | E34: Jun'26 | F34: 16.6 | G34: 365 | H34: 191 | I34: 402 | J34: 207 | K34: 377 | L34: 346 | M34: 446 | N34: 315 | O34: 399 | P34: 266 | Q34: 486 | R34: 464 | S34: 472 | T34: 427 | U34: 717 | V34: 184 | W34: 770 | X34: 0.095379147 | Y34: 0.1249324 | Z34: -0.13461538 | AA34: 0.16555556
B35: 7241 | C35: Japan | D35: N/A | E35: Jun'26 | F35: 16.4 | G35: -1909 | H35: 940 | I35: 3878 | J35: -2008 | K35: 1718 | L35: 2764 | M35: 5208 | N35: 4730 | O35: 4716 | P35: 6565 | Q35: 3202 | R35: 3615 | S35: 1832 | T35: 4466 | U35: 5265 | V35: 4192 | W35: 4417 | X35: -0.13796503 | Y35: 0.1573008 | Z35: 0.038015549 | AA35: 0.1640749
B36: 8386 | C36: Japan | D36: N/A | E36: Jun'26 | F36: 15.4 | G36: 4702 | H36: 4792 | I36: 479 | J36: 5110 | K36: 3616 | L36: 2197 | M36: 2285 | N36: 5688 | O36: 1616 | P36: 3488 | Q36: 3489 | R36: 4955 | S36: 3016 | T36: 5576 | U36: 4050 | V36: 6603 | W36: 5971 | X36: 0.13968424 | Y36: 0.032930265 | Z36: 0.093652327 | AA36: 0.15354638
B37: 7981 | C37: Japan | D37: N/A | E37: Jun'26 | F37: 9.9 | G37: 3990 | H37: 5837 | I37: 877 | J37: 3225 | K37: 2861 | L37: 3886 | M37: 969 | N37: 2684 | O37: 2624 | P37: 5411 | Q37: 1709 | R37: 3098 | S37: 2860 | T37: 6885 | U37: 2793 | V37: 4196 | W37: 4519 | X37: 0.11270837 | Y37: 0.074491479 | Z37: 0.070222563 | AA37: 0.099139477
B38: 9502 | C38: Japan | D38: N/A | E38: Jun'26 | F38: 9.2 | G38: 31762 | H38: -55866 | I38: -52029 | J38: 41486 | K38: 19776 | L38: -12994 | M38: 58821 | N38: 157186 | O38: 88472 | P38: 43953 | Q38: 53729 | R38: 85868 | S38: 56887 | T38: 41365 | U38: 57925 | V38: 67932 | W38: 77613 | X38: -0.010763734 | Y38: 0.017641445 | Z38: -0.074101923 | AA38: 0.092481783
B39: 8331 | C39: Japan | D39: N/A | E39: Sep'26 | F39: 8.9 | G39: 19452 | H39: 13461 | I39: 23942 | J39: 26698 | K39: 19092 | L39: 16937 | M39: 25921 | N39: 24001 | O39: 22592 | P39: 18153 | Q39: 28626 | R39: 25631 | S39: 25108 | T39: 27460 | U39: 30960 | V39: 31799 | W39: 35358 | X39: 0.095438791 | Y39: 0.021848818 | Z39: 0.056504732 | AA39: 0.088877713
B40: 8346 | C40: Japan | D40: N/A | E40: Jun'26 | F40: 8.5 | G40: 2851 | H40: 2876 | I40: 1558 | J40: 2478 | K40: 1533 | L40: 2341 | M40: 711 | N40: 2858 | O40: 2201 | P40: 3211 | Q40: -276 | R40: 3291 | S40: 3211 | T40: 2872 | U40: 1250 | V40: 4545 | W40: 4222 | X40: -0.035922433 | Y40: 0.16772917 | Z40: 0.11803464 | AA40: 0.085115339
B41: 6762 | C41: Japan | D41: N/A | E41: Jun'26 | F41: 8.5 | G41: 48962 | H41: 59492 | I41: 21407 | J41: 44414 | K41: 75390 | L41: 66228 | M41: -28306 | N41: 25342 | O41: 58605 | P41: 69027 | Q41: 17688 | R41: 57872 | S41: 72806 | T41: 75791 | U41: 11743 | V41: 56419 | W41: 91208 | X41: 0.031114157 | Y41: -0.02652159 | Z41: -0.0066586622 | AA41: 0.084896129
... B43: 9064 | C43: Japan | D43: N/A | E43: Sep'26 | F43: 4.3 | G43: 47482 | H43: -1973 | I43: 2418 | J43: 15631 | K43: 48352 | L43: -6315 | M43: 1598 | N43: 10761 | O43: 38004 | P43: -10303 | Q43: -14205 | R43: -797 | S43: 41267 | T43: -12058 | U43: -6494 | V43: 2712 | W43: 42368 | X43: -0.10994863 | Y43: 0.54276061 | Z43: 0.16009672 | AA43: 0.043300429
B44: 3467 | C44: Japan | D44: N/A | E44: Jun'26 | F44: 4.1 | Q44: 1293 | R44: 226 | S44: 855 | T44: 427 | U44: 1041 | V44: 508 | W44: 971 | Y44: -0.089967869 | Z44: 0.11063162 | AA44: 0.040974921
B45: 8411 | C45: Japan | D45: N/A | E45: Sep'26 | F45: 3.7 | G45: 108485 | H45: 48765 | I45: 207355 | J45: 237700 | K45: 244905 | L45: 89003 | M45: 313573 | N45: 282748 | O45: 325130 | P45: 33582 | Q45: 397385 | R45: 393772 | S45: 376077 | T45: 22849 | U45: 378595 | V45: 520119 | W45: 424507 | X45: -0.0089380888 | Y45: -0.015788815 | Z45: 0.10786968 | AA45: 0.037321599
B46: 4272 | C46: Japan | D46: N/A | E46: Jun'26 | F46: 3.4 | G46: 4964 | H46: 6438 | I46: 3711 | J46: 6381 | K46: 7179 | L46: 5503 | M46: 2443 | N46: 2335 | O46: 2433 | P46: -656 | Q46: 3225 | R46: 5570 | S46: 5591 | T46: 6955 | U46: 2286 | V46: 4369 | W46: 6250 | X46: 0.55433358 | Y46: -0.043999813 | Z46: -0.058866778 | AA46: 0.034321129
B47: 9022 | C47: Japan | D47: N/A | E47: Sep'26 | F47: 3 | G47: 71276 | H47: -35464 | I47: 83541 | J47: 88386 | K47: 134444 | L47: 68133 | M47: 146519 | N47: 165573 | O47: 190507 | P47: 104783 | Q47: 184329 | R47: 180881 | S47: 218719 | T47: 118866 | U47: 221226 | V47: 232826 | W47: 242711 | X47: 0.020448315 | Y47: 0.052500374 | Z47: 0.070225175 | AA47: 0.03030682
B48: 2222 | C48: Japan | D48: N/A | E48: Sep'26 | F48: 2.9 | G48: 2279 | H48: 539 | I48: 1151 | J48: 1679 | K48: 4027 | L48: 3093 | M48: 3059 | N48: 3564 | O48: 5112 | P48: 4044 | Q48: 3428 | R48: 4050 | S48: 6068 | T48: 4064 | U48: 3441 | V48: 3999 | W48: 6573 | X48: 0.0011370097 | Y48: 0.00073821692 | Z48: -0.0028939454 | AA48: 0.028738903
B49: 3024 | C49: Japan | D49: N/A | E49: Jun'26 | F49: 1.9 | G49: 13 | H49: 189 | I49: 118 | J49: 107 | K49: 188 | L49: 214 | M49: 171 | N49: -49 | O49: 140 | P49: 334 | Q49: -12 | R49: 75 | S49: 144 | T49: 328 | U49: 222 | V49: 134 | W49: 160 | X49: -0.011090573 | Y49: 0.43738318 | Z49: 0.076723017 | AA49: 0.019323671
B50: 4768 | C50: Japan | D50: N/A | E50: Dec'25 | F50: 1.5 | G50: 11293 | H50: 13787 | I50: 16992 | J50: 11997 | K50: 11997 | L50: 16876 | M50: 19837 | N50: 10678 | O50: 15574 | P50: 17243 | Q50: 21601 | R50: 13326 | S50: 22047 | T50: 21176 | U50: 27998 | V50: 17357 | W50: 23413 | X50: 0.05299325 | Y50: 0.081855406 | Z50: 0.047677623 | AA50: 0.015421436
B51: 8601 | C51: Japan | D51: N/A | E51: Jun'26 | F51: 0.9 | G51: 56158 | H51: 68276 | I51: 53515 | J51: 49366 | K51: 93611 | L51: 133122 | M51: 192039 | N51: 162882 | O51: 197335 | P51: 225544 | Q51: 254516 | R51: 34552 | S51: 41008 | T51: 37040 | U51: 781179 | V51: 35094 | W51: 48910 | X51: -0.33926784 | Y51: 1.4345956 | Z51: 0.00060641389 | AA51: 0.0088357536
B52: 8081 | C52: Japan | D52: N/A | E52: Jun'26 | F52: 0.6 | G52: 732 | H52: 396 | I52: 1614 | J52: 139 | K52: 1186 | L52: 803 | M52: 1840 | N52: 522 | O52: 1324 | P52: 754 | Q52: 1945 | R52: 338 | S52: 1180 | T52: 507 | U52: 2476 | V52: 470 | W52: 1206 | X52: -0.058572445 | Y52: 0.13375315 | Z52: 0.029326816 | AA52: 0.0056119145
B53: 9020 | C53: Japan | D53: N/A | E53: Sep'26 | F53: 0.3 | G53: 73356 | H53: -111402 | I53: 40298 | J53: 26413 | K53: 45297 | L53: 28622 | M53: 80176 | N53: 111622 | O53: 106713 | P53: 46651 | Q53: 120531 | R53: 115075 | S53: 116948 | T53: 24233 | U53: 114787 | V53: 116694 | W53: 118134 | X53: -0.056156611 | Y53: -0.015244687 | Z53: 0.0043633757 | AA53: 0.0031825085
B54: 3433 | C54: Japan | D54: N/A | E54: Jun'26 | F54: -0.1 | G54: 2351 | H54: 2443 | I54: 2702 | J54: 2724 | K54: 2858 | L54: 2642 | M54: 2335 | N54: 2270 | O54: 2027 | P54: 2108 | Q54: 2793 | R54: 2688 | S54: 2696 | T54: 3107 | U54: 3781 | V54: 3838 | W54: 2682 | X54: 0.097131745 | Y54: 0.087557604 | Z54: 0.093709257 | AA54: -0.0010430636
B55: 9532 | C55: Japan | D55: N/A | E55: Sep'26 | F55: -0.2 | G55: 2137 | H55: 52229 | I55: 7367 | J55: -53057 | K55: 30763 | L55: 74929 | M55: 73664 | N55: 23068 | O55: 43961 | P55: 31862 | Q55: 28750 | R55: 26191 | S55: 44567 | T55: 61224 | U55: 47680 | V55: 41990 | W55: 44079 | X55: 0.22350613 | Y55: 0.11777369 | Z55: 0.087937349 | AA55: -0.0024966617
B56: 3132 | C56: Japan | D56: N/A | E56: Jun'26 | F56: -2.8 | G56: 8130 | H56: 9939 | I56: 11435 | J56: 12266 | K56: 14536 | L56: 18493 | M56: 16353 | N56: 20654 | O56: 17346 | P56: 13311 | Q56: 12422 | R56: 12048 | S56: 10329 | T56: 10841 | U56: 6432 | V56: 8198 | W56: 9309 | X56: -0.051340678 | Y56: -0.13124452 | Z56: -0.097099622 | AA56: -0.02849162
... B65: 7883 | C65: Japan | D65: N/A | E65: Sep'26 | F65: -62.3 | G65: 60 | H65: 254 | I65: 41 | J65: -31 | K65: 119 | L65: 112 | M65: 138 | N65: -60 | O65: 65 | P65: 115 | Q65: 190 | R65: -129 | S65: 89 | T65: -15 | U65: 269 | V65: -184 | W65: -10 | X65: -0.49056604 | Y65: 0.58518519 | Z65: -0.25700935 | AA65: -0.62264151
B66: POLICYBZR | C66: India | D66: N/A | E66: Sep'26 | F66: 155.7 | G66: -3280 | H66: -2669 | I66: -2475 | J66: -2416 | K66: -1507 | L66: -854.94 | M66: -966.21 | N66: -1114 | O66: -485.8 | P66: -183.38 | Q66: -642.7 | R66: -371.8 | S66: -58.9 | T66: 795.8 | U66: 9.1 | V66: 639.6 | W66: 2099 | X66: -0.77911806 | Y66: -2.3479827 | Z66: 2.7028327 | AA66: 1.5573759
B67: CLEDUCATE | C67: India | D67: N/A | E67: Jun'26 | F67: 135 | G67: 51.06 | H67: 7.48 | I67: 26.29 | J67: 52.18 | K67: 56.45 | L67: 28.41 | M67: 12.36 | N67: 54.96 | O67: 33.26 | P67: 11.86 | Q67: 31.48 | R67: 52.07 | S67: 57.11 | T67: -54.04 | U67: -30.1 | V67: 87.66 | W67: 138.96 | X67: -0.43207448 | Y67: -0.71092127 | Z67: 1.4213259 | AA67: 1.3499918
B68: SOUTHWEST | C68: India | D68: N/A | E68: Jun'26 | F68: 39.3 | G68: 38.1 | H68: 39.47 | I68: 78.77 | J68: 31.22 | K68: 21.71 | L68: 21.12 | M68: 71.19 | N68: 17.8 | O68: 22.01 | P68: 67.03 | Q68: 64.96 | R68: 22.74 | S68: 10.13 | T68: 62.74 | U68: 157.19 | V68: 36.55 | W68: 114.93 | X68: -0.026022079 | Y68: 0.57439123 | Z68: 0.054628165 | AA68: 0.39308353
B69: NILASPACES | C69: India | D69: N/A | E69: Sep'26 | F69: 24.6 | G69: -6.08 | H69: -10.23 | I69: -2.34 | J69: -10.48 | K69: -25.72 | L69: -44.31 | M69: -10.57 | N69: -11.58 | O69: 72.42 | P69: 48.96 | Q69: 50.16 | R69: 63.69 | S69: 77.78 | T69: 89.24 | U69: 107.72 | V69: 85.16 | W69: 166.18 | X69: 0.16742175 | Y69: 0.20493467 | Z69: 0.063440002 | AA69: 0.24562378
B70: APOLLO | C70: India | D70: N/A | E70: Jun'26 | F70: 19.1 | G70: 78.27 | H70: 95.5 | I70: 140.6 | J70: 73.76 | K70: 94.07 | L70: 169.63 | M70: 202.4 | N70: 101.33 | O70: 156.61 | P70: 211.74 | Q70: 257.74 | R70: 189.18 | S70: 291.47 | T70: 339.68 | U70: 327.72 | V70: 364.42 | W70: 544.42 | X70: 0.13465526 | Y70: 0.064912297 | Z70: 0.15264144 | AA70: 0.19115236
B71: PCJEWELLER | C71: India | D71: N/A | E71: Sep'26 | F71: 16.4 | G71: 294.7 | H71: -1965 | I71: 779.5 | J71: 1405 | K71: 292.9 | L71: -267.7 | M71: -496.4 | N71: -585.2 | O71: -778.6 | P71: -49 | Q71: 478 | R71: 814.8 | S71: 1071 | T71: 1419 | U71: 1223 | V71: 1727 | W71: 1962 | X71: 0.63418006 | Y71: 0.19694406 | Z71: 0.2014665 | AA71: 0.16378676
B72: THERMAX | C72: India | D72: N/A | E72: Sep'26 | F72: 15.6 | G72: 841.3 | H72: 1078 | I72: 674.8 | J72: 1108 | K72: 1320 | L72: 1743 | M72: 1028 | N72: 1717 | O72: 1516 | P72: 2379 | Q72: 1051 | R72: 2359 | S72: 1539 | T72: 2585 | U72: 1762 | V72: 1206 | W72: 2643 | X72: 0.028111354 | Y72: 0.094372179 | Z72: -0.13984233 | AA72: 0.15566836
B73: CINELINE | C73: India | D73: N/A | E73: Sep'26 | F73: 13 | G73: 31.04 | H73: 44.27 | I73: 39.65 | J73: -32.32 | K73: 23.12 | L73: -3.31 | M73: 23.44 | N73: 152.36 | O73: 104.35 | P73: 0 | Q73: -22.23 | R73: 78.72 | S73: 79.67 | T73: 18.76 | U73: -11.58 | V73: 58.74 | W73: 98.61 | X73: 0.13777908 | Y73: 0.068745159 | Z73: -0.12067404 | AA73: 0.13009135
B74: SUNDARMFIN | C74: India | D74: N/A | E74: Sep'26 | F74: 11.4 | G74: 3434 | H74: 4511 | I74: 3460 | J74: 3974 | K74: 4241 | L74: 5073 | M74: 4220 | N74: 4681 | O74: 5134 | P74: 7111 | Q74: 5165 | R74: 5462 | S74: 5837 | T74: 6834 | U74: 5712 | V74: 6351 | W74: 8654 | X74: -0.011749735 | Y74: 0.02347841 | Z74: 0.037282449 | AA74: 0.11389181
B75: SHALBY | C75: India | D75: N/A | E75: Jun'26 | F75: 11 | G75: 179.69 | H75: 169.51 | I75: 145.43 | J75: 284.75 | K75: 251.75 | L75: 221.63 | M75: 168.72 | N75: 311.88 | O75: 404.2 | P75: 299.25 | Q75: 357.61 | R75: 288.37 | S75: 158.06 | T75: 175.91 | U75: 184.01 | V75: 250.15 | W75: 242.45 | X75: -0.11179291 | Y75: -0.1771519 | Z75: -0.047398772 | AA75: 0.10986422
B76: SHRIPISTON | C76: India | D76: N/A | E76: Sep'26 | F76: 10 | G76: 470.3 | H76: 612.35 | I76: 696.4 | J76: 910.5 | K76: 937.8 | L76: 1112 | M76: 1235 | N76: 1351 | O76: 1323 | P76: 1437 | Q76: 1359 | R76: 1469 | S76: 1397 | T76: 1828 | U76: 1636 | V76: 1747 | W76: 2061 | X76: 0.06905687 | Y76: 0.045762432 | Z76: 0.043917852 | AA76: 0.10048426
B77: APLLTD | C77: India | D77: N/A | E77: Jun'26 | F77: 9.2 | G77: 2026 | H77: 1997 | I77: 23.6 | J77: -524.4 | K77: 1651 | L77: 1822 | M77: 1430 | N77: 1325 | O77: 1407 | P77: 1969 | Q77: 1906 | R77: 1678 | S77: 1688 | T77: 1902 | U77: 2031 | V77: 2076 | W77: 2396 | X77: -0.0092528656 | Y77: 0.017424031 | Z77: 0.054528018 | AA77: 0.09198389
... B98: CNL | C98: United States | D98: Gold | E98: Sep'25 | F98: 18.4 | G98: -2.55 | H98: -3.56 | I98: -4.27 | J98: -4.09 | K98: -4.03 | L98: -4.02 | M98: -3.09 | N98: -4.45 | O98: -5.37 | P98: -6.52 | Q98: -5.04 | R98: -6.4 | S98: -5.95 | T98: -6.44 | U98: -6.76 | V98: -9.67 | W98: -11.24 | X98: -0.0033458804 | Y98: 0.072177927 | Z98: 0.12798434 | AA98: 0.18355309
B99: RHLD | C99: United States | D99: Specialty Business Services | E99: Sep'25 | F99: 6.8 | O99: 30.24 | P99: 32.32 | Q99: 32.44 | R99: 33.39 | S99: 32.85 | T99: 28 | U99: 25.62 | V99: 40.63 | W99: 41.46 | X99: -0.032977099 | Y99: -0.053836438 | Z99: 0.060403804 | AA99: 0.067741935
B100: ACAD | C100: United States | D100: Biotechnology | E100: Sep'25 | F100: 4.6 | G100: -15.3 | H100: -44.66 | I100: -113.02 | J100: -33.65 | K100: -30.87 | L100: -46.06 | M100: -53.58 | N100: 3.04 | O100: -57.78 | P100: 34.94 | Q100: 15.21 | R100: 30.44 | S100: 31.64 | T100: 6.99 | U100: 19.29 | V100: 32.37 | W100: 35.76 | X100: -0.24904215 | Y100: 0.048410062 | Z100: 0.021842463 | AA100: 0.045630745
B101: AME | C101: United States | D101: Specialty Industrial Machinery | E101: Sep'25 | F101: 2.7 | G101: 329.76 | H101: 379.22 | I101: 345.64 | J101: 360.83 | K101: 381.07 | L101: 413.16 | M101: 392.13 | N101: 408.94 | O101: 428.88 | P101: 477.51 | Q101: 434.44 | R101: 438.55 | S101: 438.12 | T101: 497.66 | U101: 444.42 | V101: 453.1 | W101: 488.06 | X101: 0.011265669 | Y101: 0.0055175617 | Z101: 0.008 | AA101: 0.027240495
B102: NRC | C102: United States | D102: Health Information Services | E102: Sep'25 | F102: -0.9 | G102: 13.14 | H102: 13 | I102: 11.7 | J102: 11.5 | K102: 11.12 | L102: 12.24 | M102: 9.02 | N102: 9.37 | O102: 9.98 | P102: 11.71 | Q102: 8.76 | R102: 8.87 | S102: 7.98 | T102: 9.61 | U102: 8.6 | V102: 1.59 | W102: 7.74 | X102: -0.056270096 | Y102: -0.0045428734 | Z102: -0.20764404 | AA102: -0.0086393089
B103: ODD | C103: United States | D103: Household & Personal Products | E103: Sep'25 | F103: -1.8 | I103: 3.64 | J103: 20.45 | K103: 3.72 | L103: 19.76 | M103: 32.52 | N103: 36.83 | O103: 6.31 | P103: 23.85 | Q103: 38.98 | R103: 53.04 | S103: 19.53 | T103: 4.04 | U103: 42.67 | V103: 57.09 | W103: 17.36 | X103: -0.14630724 | Y103: 0.031923177 | Z103: 0.033953722 | AA103: -0.01759507
B104: NJR | C104: United States | D104: Utilities - Regulated Gas | E104: n/a | F104: -29.9 | G104: 156.89 | H104: 138.88 | I104: 29.81 | J104: 80.91 | K104: 172.79 | L104: 165.18 | M104: 4.73 | N104: 64.29 | O104: 135.82 | P104: 170.22 | Q104: 5.94 | R104: 146.13 | S104: 134.72 | T104: 279.26 | U104: -1.61 | V104: 38.3 | W104: 0 | X104: 0.23859434 | Y104: -0.013338044 | Z104: -0.19307073 | AA104: -0.2989327
B105: LFCR | C105: United States | D105: Drug Manufacturers - Specialty & Generic | E105: Sep'25 | F105: -59.9 | G105: -0.91 | H105: 2.46 | I105: -3.3 | J105: -0.28 | K105: -4.34 | L105: -4.79 | M105: -3.97 | N105: 0 | O105: -7.41 | P105: -1.33 | Q105: -0.12 | R105: 2.89 | S105: -9.08 | T105: -1.56 | U105: -2.29 | V105: 2.9 | W105: -3.07 | X105: 0.030104712 | Y105: 0.27573062 | Z105: -0.00099601594 | AA105: -0.59920239
B106: LVRO | C106: United States | D106: Agricultural Inputs | E106: Jun'25 | F106: -4725.4 | I106: -68.27 | J106: 133.96 | K106: 133.96 | L106: 192.76 | M106: -121.35 | N106: 172.4 | O106: 366.2 | P106: -262.44 | Q106: -59.89 | R106: -26.6 | S106: 152.02 | T106: -49.35 | U106: -81.6 | V106: 3.5 | W106: -1009 | X106: -1.0821695 | Y106: -1.34178 | Z106: -5.443038 | AA106: -47.253561
B107: 7177 | C107: Japan | D107: N/A | E107: Sep'25 | F107: 1.3 | G107: 2898 | H107: 2950 | I107: 3395 | J107: 2904 | K107: 2080 | L107: 771 | M107: 3777 | N107: 4154 | O107: 3463 | P107: 3058 | Q107: 4354 | R107: 592 | S107: 3734 | T107: 247 | U107: 4223 | V107: 5554 | W107: 3915 | X107: -0.23947862 | Y107: -0.014674583 | Z107: 0.56412005 | AA107: 0.013155982
B108: 2160 | C108: Japan | D108: N/A | E108: Sep'25 | F108: -7.4 | G108: 505 | H108: -932 | I108: 479 | J108: 525 | K108: 490 | L108: -325 | M108: 398 | N108: 5078 | O108: 1327 | P108: -2296 | Q108: 2284 | R108: -522 | S108: 580.68 | T108: -783.82 | U108: -772.31 | V108: -406.69 | W108: 683.54 | X108: 32.394602 | Y108: -1.9606058 | Z108: -0.077004241 | AA108: -0.074420826
B109: 2811 | C109: Japan | D109: N/A | E109: Sep'25 | F109: -9.8 | G109: 4649 | H109: 2180 | I109: 2149 | J109: 3159 | K109: 4253 | L109: 2390 | M109: 3144 | N109: 5039 | O109: 6011 | P109: 3327 | Q109: 15195 | R109: 10110 | S109: 8169 | T109: -6737 | U109: 4791 | V109: 5734 | W109: 6992 | X109: -0.27347083 | Y109: -0.38912369 | Z109: -0.26792384 | AA109: -0.098436063
B110: 1060 | C110: Hong Kong | D110: N/A | E110: H1 2026 | F110: 7.6 | N110: 428.02 | O110: -192.25 | P110: 209.71 | Q110: 4.64 | R110: 0 | S110: 333.66 | T110: 0 | U110: 538.05 | V110: 261.56 | W110: 419.31 | X110: -0.3826755 | Y110: 1.5767366 | Z110: 0.30005392 | AA110: 0.075577753
B111: 1150 | C111: Hong Kong | D111: N/A | E111: H1 2025 | F111: 5.5 | N111: -7.29 | O111: -0.8 | P111: 0.62 | Q111: -9.09 | R111: -22.78 | S111: -6.67 | T111: -19.52 | U111: -23.85 | V111: -18.86 | W111: -10.43 | X111: 0.53111814 | Y111: 0.25421977 | Z111: -0.053831365 | AA111: 0.054571843
B112: 1010 | C112: Hong Kong | D112: N/A | E112: H1 2025 | F112: 4.4 | N112: -11.38 | O112: -10.06 | P112: -21.38 | Q112: -12.26 | R112: 19.57 | S112: 3.23 | T112: -45.99 | U112: -23.96 | V112: -120.04 | W112: -4.97 | X112: 2.2702952 | Y112: 0.33004231 | Z112: 2.9609756 | AA112: 0.043906618
B113: 1140 | C113: Hong Kong | D113: N/A | E113: H1 2026 | F113: -2 | N113: 94.16 | O113: 55.58 | P113: 32.74 | Q113: 50.31 | R113: 78.01 | S113: 114.57 | T113: 129.93 | U113: 111.4 | V113: 123.49 | W113: 105.03 | X113: 0.35261038 | Y113: 0.16385924 | Z113: 0.10481436 | AA113: -0.01990029
B114: 1020 | C114: Hong Kong | D114: N/A | E114: H1 2025 | F114: -4.4 | N114: 0 | O114: -12.96 | P114: -11.82 | Q114: -4.95 | R114: -13.15 | S114: -5.26 | T114: -1 | U114: -5.34 | V114: -6.43 | W114: -4.47 | X114: -0.30756111 | Y114: 0.016009852 | Z114: -0.27151515 | AA114: -0.043815862
B115: CRLO | C115: France | D115: N/A | E115: H1 2025 | F115: -5.2 | N115: 66.54 | O115: 74.46 | P115: 57.76 | Q115: 32.79 | R115: 68.95 | S115: 70.18 | T115: 57.5 | U115: 71.15 | V115: 52.94 | W115: 57.13 | X115: -0.0011320098 | Y115: 0.16720425 | Z115: -0.059787886 | AA115: -0.051833022

Sheet 빨간줄
B2: (단위: mil $)
B4: PLTR | C4: 6 | D4: 7 | E4: 8 | F4: 9 | G4: 10 | H4: 11 | I4: 12 | J4: 13 | K4: 14 | L4: 15 | M4: 16 | N4: 17 | O4: 18 | P4: 19 | Q4: 20 | R4: 21 | S4: 22
C6: 4Q21 | D6: 1Q22 | E6: 2Q22 | F6: 3Q22 | G6: 4Q22 | H6: 1Q23 | I6: 2Q23 | J6: 3Q23 | K6: 4Q23 | L6: 1Q24 | M6: 2Q24 | N6: 3Q24 | O6: 4Q24 | P6: 1Q25 | Q6: 2Q25 | R6: 3Q25 | S6: 4Q25
B7: Revenue | C7: =IFERROR(VLOOKUP($B$4,Revenue!$B$2:$X$500,C$4,FALSE),"-") -> 432.87 | D7: =IFERROR(VLOOKUP($B$4,Revenue!$B$2:$X$500,D$4,FALSE),"-") -> 446.36 | E7: =IFERROR(VLOOKUP($B$4,Revenue!$B$2:$X$500,E$4,FALSE),"-") -> 473.01 | F7: =IFERROR(VLOOKUP($B$4,Revenue!$B$2:$X$500,F$4,FALSE),"-") -> 477.88 | G7: =IFERROR(VLOOKUP($B$4,Revenue!$B$2:$X$500,G$4,FALSE),"-") -> 508.62 | H7: =IFERROR(VLOOKUP($B$4,Revenue!$B$2:$X$500,H$4,FALSE),"-") -> 525.19 | I7: =IFERROR(VLOOKUP($B$4,Revenue!$B$2:$X$500,I$4,FALSE),"-") -> 533.32 | J7: =IFERROR(VLOOKUP($B$4,Revenue!$B$2:$X$500,J$4,FALSE),"-") -> 558.16 | ... S7: =IFERROR(VLOOKUP($B$4,Revenue!$B$2:$X$500,S$4,FALSE),"-") -> 1407
B8: OP | C8: =IFERROR(VLOOKUP($B$4,'Operating Income'!$B$2:$X$500,C$4,FALSE),"-") -> -58.94 | D8: =IFERROR(VLOOKUP($B$4,'Operating Income'!$B$2:$X$500,D$4,FALSE),"-") -> -39.44 | E8: =IFERROR(VLOOKUP($B$4,'Operating Income'!$B$2:$X$500,E$4,FALSE),"-") -> -41.75 | F8: =IFERROR(VLOOKUP($B$4,'Operating Income'!$B$2:$X$500,F$4,FALSE),"-") -> -62.19 | G8: =IFERROR(VLOOKUP($B$4,'Operating Income'!$B$2:$X$500,G$4,FALSE),"-") -> -17.83 | H8: =IFERROR(VLOOKUP($B$4,'Operating Income'!$B$2:$X$500,H$4,FALSE),"-") -> 4.12 | I8: =IFERROR(VLOOKUP($B$4,'Operating Income'!$B$2:$X$500,I$4,FALSE),"-") -> 10.07 | J8: =IFERROR(VLOOKUP($B$4,'Operating Income'!$B$2:$X$500,J$4,FALSE),"-") -> 39.98 | ... S8: =IFERROR(VLOOKUP($B$4,'Operating Income'!$B$2:$X$500,S$4,FALSE),"-") -> 575.39
B9: Trailing 4Q OP avg. | C9: =IFERROR(AVERAGE(C8:C8),"-") -> -58.94 | D9: =IFERROR(AVERAGE(C8:D8),"-") -> -49.19 | E9: =IFERROR(AVERAGE(C8:E8),"-") -> -46.71 | F9: =IFERROR(AVERAGE(C8:F8),"-") -> -50.58 | G9: =IFERROR(AVERAGE(D8:G8),"-") -> -40.3025 | H9: =IFERROR(AVERAGE(E8:H8),"-") -> -29.4125 | I9: =IFERROR(AVERAGE(F8:I8),"-") -> -16.4575 | J9: =IFERROR(AVERAGE(G8:J8),"-") -> 9.085 | K9: =IFERROR(AVERAGE(H8:K8),"-") -> 29.99 | L9: =IFERROR(AVERAGE(I8:L8),"-") -> 49.18 | M9: =IFERROR(AVERAGE(J8:M8),"-") -> 72.9975 | ... S9: =IFERROR(AVERAGE(P8:S8),"-") -> 353.505
B10: Trailing 4Q OP sum. | C10: =IFERROR(SUM(C8:C8),"-") -> -58.94 | D10: =IFERROR(SUM(C8:D8),"-") -> -98.38 | E10: =IFERROR(SUM(C8:E8),"-") -> -140.13 | F10: =IFERROR(SUM(C8:F8),"-") -> -202.32 | G10: =IFERROR(SUM(D8:G8),"-") -> -161.21 | H10: =IFERROR(SUM(E8:H8),"-") -> -117.65 | I10: =IFERROR(SUM(F8:I8),"-") -> -65.83 | J10: =IFERROR(SUM(G8:J8),"-") -> 36.34 | K10: =IFERROR(SUM(H8:K8),"-") -> 119.96 | L10: =IFERROR(SUM(I8:L8),"-") -> 196.72 | M10: =IFERROR(SUM(J8:M8),"-") -> 291.99 | ... S10: =IFERROR(SUM(P8:S8),"-") -> 1414.02
B11: Trailing OP Delta | D11: =IFERROR(D9/C9-1,"-") -> -0.16542246 | E11: =IFERROR(E9/D9-1,"-") -> -0.050416751 | F11: =IFERROR(F9/E9-1,"-") -> 0.082851638 | G11: =IFERROR(G9/F9-1,"-") -> -0.20319296 | H11: =IFERROR(H9/G9-1,"-") -> -0.27020656 | I11: =IFERROR(I9/H9-1,"-") -> -0.44045899 | J11: =IFERROR(J9/I9-1,"-") -> -1.552028 | K11: =IFERROR(K9/J9-1,"-") -> 2.3010457 | ... S11: =IFERROR(S9/R9-1,"-") -> 0.66419904
B12: opm | C12: =IFERROR(C8/C7,"-") -> -0.13616097 | D12: =IFERROR(D8/D7,"-") -> -0.088359172 | E12: =IFERROR(E8/E7,"-") -> -0.088264519 | F12: =IFERROR(F8/F7,"-") -> -0.13013727 | G12: =IFERROR(G8/G7,"-") -> -0.035055641 | H12: =IFERROR(H8/H7,"-") -> 0.00784478 | I12: =IFERROR(I8/I7,"-") -> 0.018881722 | J12: =IFERROR(J8/J7,"-") -> 0.071628207 | ... S12: =IFERROR(S8/S7,"-") -> 0.40894812
B13: op yoy | G13: =IFERROR(G8/C8-1,"-") -> -0.69748897 | H13: =IFERROR(H8/D8-1,"-") -> -1.1044625 | I13: =IFERROR(I8/E8-1,"-") -> -1.2411976 | J13: =IFERROR(J8/F8-1,"-") -> -1.6428686 | K13: =IFERROR(K8/G8-1,"-") -> -4.6898486 | L13: =IFERROR(L8/H8-1,"-") -> 18.631068 | M13: =IFERROR(M8/I8-1,"-") -> 9.4607746 | N13: =IFERROR(N8/J8-1,"-") -> 1.829915 | ... S13: =IFERROR(S8/O8-1,"-") -> 51.118659
B14: rv yoy | G14: =IFERROR(G7/C7-1,"-") -> 0.1749948 | H14: =IFERROR(H7/D7-1,"-") -> 0.17660633 | I14: =IFERROR(I7/E7-1,"-") -> 0.12750259 | J14: =IFERROR(J7/F7-1,"-") -> 0.16799196 | K14: =IFERROR(K7/G7-1,"-") -> 0.19607959 | L14: =IFERROR(L7/H7-1,"-") -> 0.20782955 | M14: =IFERROR(M7/I7-1,"-") -> 0.27152554 | N14: =IFERROR(N7/J7-1,"-") -> 0.29984234 | ... S14: =IFERROR(S7/O7-1,"-") -> 0.70026102
