Workbook

Sheet 기업리스트
B2: 실적 기업 정보
B3: Ticker | C3: Company | D3: Date | E3: Time | F3: Quarter Ending | G3: Market Cap (mil$)
B4: AMD | C4: Advanced Micro Devices, Inc. | D4: 03-Feb-26 | E4: After Hours | F4: Dec-25 | G4: 385406
B5: MRK | C5: Merck & Co., Inc. | D5: 03-Feb-26 | F5: Dec-25 | G5: 273693
B6: PEP | C6: PepsiCo, Inc. | D6: 03-Feb-26 | F6: Dec-25 | G6: 212497
B7: AMGN | C7: Amgen Inc. | D7: 03-Feb-26 | E7: After Hours | F7: Dec-25 | G7: 184096
B8: PFE | C8: Pfizer Inc. | D8: 03-Feb-26 | F8: Dec-25 | G8: 150330
B9: ETN | C9: Eaton Corporation plc | D9: 03-Feb-26 | F9: Dec-25 | G9: 136492
B10: CB | C10: Chubb Limited | D10: 03-Feb-26 | F10: Dec-25 | G10: 121828
B11: EMR | C11: Emerson Electric Co. | D11: 03-Feb-26 | F11: Dec-25 | G11: 82635.92
B12: TDG | C12: TransDigm Group Incorporated | D12: 03-Feb-26 | F12: Dec-25 | G12: 80587.97
B13: 7974 | C13: Nintendo Co., Ltd. | D13: 03-Feb-26 | F13: Dec-25 | G13: 76065.45
B14: ITW | C14: Illinois Tool Works Inc. | D14: 03-Feb-26 | E14: Pre Market | F14: Dec-25 | G14: 75791.53
B15: MDLZ | C15: Mondelez International, Inc. | D15: 03-Feb-26 | E15: After Hours | F15: Dec-25 | G15: 75447.26
B16: EPD | C16: Enterprise Products Partners L.P. | D16: 03-Feb-26 | E16: Pre Market | F16: Dec-25 | G16: 71800.63
B17: 6503 | C17: Mitsubishi Electric Corporation | D17: 03-Feb-26 | F17: Dec-25 | G17: 64221.8
B18: SU | C18: Suncor Energy Inc. | D18: 03-Feb-26 | F18: Dec-25 | G18: 63761.61
B19: BAJFINANCE | C19: Bajaj Finance Limited | D19: 03-Feb-26 | F19: Dec-25 | G19: 62857.21
B20: MPLX | C20: MPLX LP | D20: 03-Feb-26 | E20: Pre Market | F20: Dec-25 | G20: 56853.94
B21: MPC | C21: Marathon Petroleum Corporation | D21: 03-Feb-26 | E21: Pre Market | F21: Dec-25 | G21: 52963.15
B22: AME | C22: AMETEK, Inc. | D22: 03-Feb-26 | F22: Dec-25 | G22: 51561.06
B23: CMG | C23: Chipotle Mexican Grill, Inc. | D23: 03-Feb-26 | E23: After Hours | F23: Dec-25 | G23: 51396.95
B24: GWW | C24: W.W. Grainger, Inc. | D24: 03-Feb-26 | E24: Pre Market | F24: Dec-25 | G24: 51350.43
B25: EA | C25: Electronic Arts Inc. | D25: 03-Feb-26 | E25: After Hours | F25: Dec-25 | G25: 50858.58
B26: PYPL | C26: PayPal Holdings, Inc. | D26: 03-Feb-26 | E26: Pre Market | F26: Dec-25 | G26: 49299.5
B27: CTVA | C27: Corteva, Inc. | D27: 03-Feb-26 | E27: After Hours | F27: Dec-25 | G27: 49193.29
B28: TTWO | C28: Take-Two Interactive Software, Inc. | D28: 03-Feb-26 | E28: After Hours | F28: Dec-25 | G28: 44372.79
B29: 8015 | C29: Toyota Tsusho Corporation | D29: 03-Feb-26 | F29: Dec-25 | G29: 40700.3
B30: PRU | C30: Prudential Financial, Inc. | D30: 03-Feb-26 | E30: After Hours | F30: Dec-25 | G30: 39080.33
B31: ADANIPORTS | C31: Adani Ports and Special Economic Zone Limited | D31: 03-Feb-26 | F31: Dec-25 | G31: 36104.02
B32: 5802 | C32: Sumitomo Electric Industries, Ltd. | D32: 03-Feb-26 | F32: Dec-25 | G32: 33687.35
B33: 2412 | C33: Chunghwa Telecom Co., Ltd. | D33: 03-Feb-26 | E33: Pre Market | F33: Dec-25 | G33: 32675.86
B34: ADVANC | C34: Advanced Info Service Public Company Limited | D34: 03-Feb-26 | F34: Dec-25 | G34: 32414.91
B35: WTW | C35: Willis Towers Watson Public Limited Company | D35: 03-Feb-26 | E35: Pre Market | F35: Dec-25 | G35: 31540.55
B36: ADM | C36: Archer-Daniels-Midland Company | D36: 03-Feb-26 | E36: Pre Market | F36: Dec-25 | G36: 31323.54
B37: 512599 | C37: Adani Enterprises Limited | D37: 03-Feb-26 | F37: Dec-25 | G37: 30725.1
B38: ATO | C38: Atmos Energy Corporation | D38: 03-Feb-26 | E38: After Hours | F38: Dec-25 | G38: 27573.18
B39: HUBB | C39: Hubbell Incorporated | D39: 03-Feb-26 | F39: Dec-25 | G39: 26004.26
B40: BR | C40: Broadridge Financial Solutions, Inc. | D40: 03-Feb-26 | E40: Pre Market | F40: Dec-25 | G40: 25521.31
B41: VLTO | C41: Veralto Corporation | D41: 03-Feb-26 | F41: Jan-26 | G41: 25492.69
B42: PUB | C42: Publicis Groupe S.A. | D42: 03-Feb-26 | F42: Dec-25 | G42: 25108.03
B43: DIM | C43: Sartorius Stedim Biotech S.A. | D43: 03-Feb-26 | F43: Dec-25 | G43: 24079.42
B44: ALFA | C44: Alfa Laval AB (publ) | D44: 03-Feb-26 | F44: Dec-25 | G44: 22721.28
B45: SMCI | C45: Super Micro Computer, Inc. | D45: 03-Feb-26 | E45: After Hours | F45: Dec-25 | G45: 19485.14
B46: AMCR | C46: Amcor plc | D46: 03-Feb-26 | E46: After Hours | F46: Dec-25 | G46: 18878.29
B47: J | C47: Jacobs Solutions Inc. | D47: 03-Feb-26 | E47: After Hours | F47: Dec-25 | G47: 18480.34
B48: PNR | C48: Pentair plc | D48: 03-Feb-26 | F48: Dec-25 | G48: 18398
B49: IT | C49: Gartner, Inc. | D49: 03-Feb-26 | E49: Pre Market | F49: Dec-25 | G49: 17204.9
B50: FORTUM | C50: Fortum Oyj | D50: 03-Feb-26 | F50: Dec-25 | G50: 17191.86
B51: PIDILITIND | C51: Pidilite Industries Limited | D51: 03-Feb-26 | F51: Dec-25 | G51: 17075.9
B52: VBL | C52: Varun Beverages Limited | D52: 03-Feb-26 | F52: Dec-25 | G52: 16892.57
B53: AMUN | C53: Amundi S.A. | D53: 03-Feb-26 | F53: Dec-25 | G53: 15945.22
B54: CHILE | C54: Banco de Chile | D54: 03-Feb-26 | F54: Dec-25 | G54: 15459.66
B55: CLX | C55: The Clorox Company | D55: 03-Feb-26 | F55: Dec-25 | G55: 15067.3
B56: OMC | C56: Omnicom Group Inc. | D56: 03-Feb-26 | F56: Dec-25 | G56: 15034.83
B57: BMED | C57: Banca Mediolanum S.p.A. | D57: 03-Feb-26 | F57: Dec-25 | G57: 14767.96
B58: SOLARINDS | C58: Solar Industries India Limited | D58: 03-Feb-26 | F58: Dec-25 | G58: 14119.94
B59: CSL | C59: Carlisle Companies Incorporated | D59: 03-Feb-26 | E59: After Hours | F59: Dec-25 | G59: 13991.57
B60: BALL | C60: Ball Corporation | D60: 03-Feb-26 | E60: Pre Market | F60: Dec-25 | G60: 13675.48
B61: 1080 | C61: Arab National Bank | D61: 03-Feb-26 | F61: Dec-25 | G61: 13448.87
B62: BOL | C62: Boliden AB (publ) | D62: 03-Feb-26 | F62: Dec-25 | G62: 13141.51
B63: AFG | C63: American Financial Group, Inc. | D63: 03-Feb-26 | E63: After Hours | F63: Dec-25 | G63: 12401.59
B64: RNR | C64: RenaissanceRe Holdings Ltd. | D64: 03-Feb-26 | E64: After Hours | F64: Dec-25 | G64: 12214.15
B65: LITE | C65: Lumentum Holdings Inc. | D65: 03-Feb-26 | E65: After Hours | F65: Dec-25 | G65: 11450.32
B66: SWKS | C66: Skyworks Solutions, Inc. | D66: 03-Feb-26 | E66: After Hours | F66: Dec-25 | G66: 11443.77
B67: ATI | C67: ATI Inc. | D67: 03-Feb-26 | E67: Pre Market | F67: Dec-25 | G67: 11203
B68: MLI | C68: Mueller Industries, Inc. | D68: 03-Feb-26 | F68: Dec-25 | G68: 11125.43
B69: JKHY | C69: Jack Henry & Associates, Inc. | D69: 03-Feb-26 | E69: After Hours | F69: Dec-25 | G69: 10628.01
B70: 9021 | C70: West Japan Railway Company | D70: 03-Feb-26 | F70: Dec-25 | G70: 9813.29
B71: BPSO | C71: Banca Popolare di Sondrio S.p.A | D71: 03-Feb-26 | F71: Dec-25 | G71: 9249.98
B72: BBNI | C72: PT Bank Negara Indonesia (Persero) Tbk | D72: 03-Feb-26 | F72: Dec-25 | G72: 9059.13
B73: DOX | C73: Amdocs Limited | D73: 03-Feb-26 | E73: After Hours | F73: Dec-25 | G73: 9054.54
B74: ABCAPITAL | C74: Aditya Birla Capital Limited | D74: 03-Feb-26 | F74: Dec-25 | G74: 8944.35
B75: 9107 | C75: Kawasaki Kisen Kaisha, Ltd. | D75: 03-Feb-26 | F75: Dec-25 | G75: 8872.05
B76: 4062 | C76: Ibiden Co.,Ltd. | D76: 03-Feb-26 | F76: Dec-25 | G76: 8731.1
B77: MTCH | C77: Match Group, Inc. | D77: 03-Feb-26 | E77: After Hours | F77: Dec-25 | G77: 8258.15
B78: 526371 | C78: NMDC Limited | D78: 03-Feb-26 | F78: Dec-25 | G78: 8195.49
B79: ZWS | C79: Zurn Elkay Water Solutions Corporation | D79: 03-Feb-26 | E79: After Hours | F79: Dec-25 | G79: 7848.16
B80: 6841 | C80: Yokogawa Electric Corporation | D80: 03-Feb-26 | F80: Dec-25 | G80: 7756.23
B81: UNI | C81: Unicaja Banco, S.A. | D81: 03-Feb-26 | F81: Dec-25 | G81: 7620.1
B82: 3064 | C82: MonotaRO Co., Ltd. | D82: 03-Feb-26 | F82: Dec-25 | G82: 7611.26
B83: DEMANT | C83: Demant A/S | D83: 03-Feb-26 | F83: Dec-25 | G83: 7235.32
B84: INGR | C84: Ingredion Incorporated | D84: 03-Feb-26 | E84: Pre Market | F84: Dec-25 | G84: 7014.36
B85: VOYA | C85: Voya Financial, Inc. | D85: 03-Feb-26 | E85: After Hours | F85: Dec-25 | G85: 6902.17
B86: A003230 | C86: Samyang Foods Co., Ltd. | D86: 03-Feb-26 | F86: Dec-25 | G86: 6581.6
B87: HLUN B | C87: H. Lundbeck A/S | D87: 03-Feb-26 | F87: Dec-25 | G87: 6455.71
B88: THG | C88: The Hanover Insurance Group, Inc. | D88: 03-Feb-26 | E88: After Hours | F88: Dec-25 | G88: 6422.19
B89: HLNE | C89: Hamilton Lane Incorporated | D89: 03-Feb-26 | E89: Pre Market | F89: Dec-25 | G89: 6362.07
B90: RITM | C90: Rithm Capital Corp. | D90: 03-Feb-26 | E90: Pre Market | F90: Dec-25 | G90: 6179.29
B91: CRUS | C91: Cirrus Logic, Inc. | D91: 03-Feb-26 | E91: After Hours | F91: Dec-25 | G91: 6038.94
B92: HRB | C92: H&R Block, Inc. | D92: 03-Feb-26 | E92: After Hours | F92: Dec-25 | G92: 5526.05
B93: ACT | C93: Enact Holdings, Inc. | D93: 03-Feb-26 | E93: After Hours | F93: Dec-25 | G93: 5435.06
B94: SKY | C94: Champion Homes, Inc. | D94: 03-Feb-26 | E94: After Hours | F94: Dec-25 | G94: 4890.95
B95: SR | C95: Spire Inc. | D95: 03-Feb-26 | E95: Pre Market | F95: Dec-25 | G95: 4857.17
B96: ENPH | C96: Enphase Energy, Inc. | D96: 03-Feb-26 | E96: After Hours | F96: Dec-25 | G96: 4811.63
B97: WFRD | C97: Weatherford International plc | D97: 03-Feb-26 | E97: After Hours | F97: Dec-25 | G97: 4715.25
B98: MZTI | C98: The Marzetti Company | D98: 03-Feb-26 | E98: Pre Market | F98: Dec-25 | G98: 4639.48
B99: GPK | C99: Graphic Packaging Holding Company | D99: 03-Feb-26 | E99: Pre Market | F99: Dec-25 | G99: 4630.48
B100: MONET | C100: MONETA Money Bank, a.s. | D100: 03-Feb-26 | F100: Dec-25 | G100: 4624.52
B101: A039490 | C101: Kiwoom Securities Co., Ltd. | D101: 03-Feb-26 | F101: Dec-25 | G101: 4621.54
...

Sheet Revenue
B2: Ticker | C2: Country | D2: Industry | E2: Latest_Date | F2: Growth_Rate | G2: 4Q21 | H2: 1Q22 | I2: 2Q22 | J2: 3Q22 | K2: 4Q22 | L2: 1Q23 | M2: 2Q23 | N2: 3Q23 | O2: 4Q23 | P2: 1Q24 | Q2: 2Q24 | R2: 3Q24 | S2: 4Q24 | T2: 1Q25 | U2: 2Q25 | V2: 3Q25 | W2: 4Q25 | X2: 1Q25 | Y2: 2Q25 | Z2: 3Q25 | AA2: 4Q25
B3: SMCI | C3: United States | D3: Computer Hardware | E3: Jun'26 | F3: 33.3 | G3: 1172 | H3: 1355 | I3: 1635 | J3: 1852 | K3: 1803 | L3: 1283 | M3: 2185 | N3: 2120 | O3: 3665 | P3: 3850 | Q3: 5355 | R3: 5937 | S3: 5678 | T3: 4600 | U3: 5757 | V3: 5018 | W3: 12682 | X3: 0.036023055 | Y3: 0.018636996 | Z3: -0.04182596 | AA3: 0.33268418
B4: LITE | C4: United States | D4: Communication Equipment | E4: Jun'26 | F4: 14.3 | G4: 446.7 | H4: 395.4 | I4: 422.1 | J4: 506.8 | K4: 506 | L4: 383.4 | M4: 370.8 | N4: 317.6 | O4: 366.8 | P4: 366.5 | Q4: 308.3 | R4: 336.9 | S4: 402.2 | T4: 425.2 | U4: 480.7 | V4: 533.8 | W4: 665.5 | X4: 0.041516373 | Y4: 0.11707185 | Z4: 0.11969605 | AA4: 0.14295021
B5: AMCR | C5: United States | D5: Packaging & Containers | E5: Jun'26 | F5: 12.7 | G5: 3507 | H5: 3708 | I5: 3909 | J5: 3712 | K5: 3642 | L5: 3667 | M5: 3673 | N5: 3443 | O5: 3251 | P5: 3411 | Q5: 3535 | R5: 3353 | S5: 3241 | T5: 3333 | U5: 5082 | V5: 5745 | W5: 5449 | X5: -0.005760709 | Y5: 0.11491606 | Z5: 0.15937104 | AA5: 0.12688926
B6: BDN | C6: United States | D6: REIT - Office | E6: Dec'25 | F6: 11 | G6: 117.65 | H6: 120.49 | I6: 121.62 | J6: 119.48 | K6: 120.12 | L6: 123.1 | M6: 118.35 | N6: 119.24 | O6: 77.14 | P6: 112.67 | Q6: 111.27 | R6: 6.17 | S6: 77.38 | T6: 111.21 | U6: 105.34 | V6: 103.14 | W6: 120.95 | X6: -0.0047481219 | Y6: -0.019377185 | Z6: 0.32312562 | AA6: 0.10972876
B7: SIMO | C7: United States | D7: Semiconductors | E7: Dec'25 | F7: 10.9 | G7: 264.36 | H7: 241.98 | I7: 252.37 | J7: 250.81 | K7: 200.76 | L7: 124.07 | M7: 140.36 | N7: 172.33 | O7: 202.38 | P7: 189.31 | Q7: 210.67 | R7: 212.41 | S7: 191.16 | T7: 166.49 | U7: 198.68 | V7: 242 | W7: 278.46 | X7: -0.02839898 | Y7: -0.015357422 | Z7: 0.038491558 | AA7: 0.10935327
B8: AMD | C8: United States | D8: Semiconductors | E8: Dec'25 | F8: 8.2 | G8: 4826 | H8: 5887 | I8: 6550 | J8: 5565 | K8: 5599 | L8: 5353 | M8: 5359 | N8: 5800 | O8: 6168 | P8: 5473 | Q8: 5835 | R8: 6819 | S8: 7658 | T8: 7438 | U8: 7685 | V8: 9246 | W8: 10270 | X8: 0.076207097 | Y8: 0.066666667 | Z8: 0.081993243 | AA8: =SUM(T8:W8)/SUM(S8:V8)-1 -> 0.081556187
B9: RES | C9: United States | D9: Oil & Gas Equipment & Services | E9: Dec'25 | F9: 5.9 | G9: 268.25 | H9: 284.62 | I9: 375.51 | J9: 459.6 | K9: 482.03 | L9: 476.67 | M9: 415.86 | N9: 330.42 | O9: 394.53 | P9: 377.83 | Q9: 364.15 | R9: 337.65 | S9: 335.36 | T9: 332.88 | U9: 420.81 | V9: 447.1 | W9: 425.78 | X9: -0.031767009 | Y9: 0.041356457 | Z9: 0.076715497 | AA9: 0.058861439
B10: TRNS | C10: United States | D10: Specialty Business Services | E10: Sep'26 | F10: 5.7 | G10: 50.9 | H10: 55.88 | I10: 54.66 | J10: 56.44 | K10: 57.4 | L10: 62.07 | M10: 60.6 | N10: 62.8 | O10: 65.17 | P10: 70.91 | Q10: 66.71 | R10: 67.83 | S10: 66.75 | T10: 77.13 | U10: 76.42 | V10: 82.27 | W10: 83.86 | X10: 0.022850845 | Y10: 0.034875368 | Z10: 0.050116267 | AA10: 0.056548898
B11: MSGE | C11: United States | D11: Leisure | E11: Jun'26 | F11: 5.5 | G11: -13.35 | H11: 193.99 | I11: 178.34 | J11: 146.45 | K11: 355.88 | L11: 201.23 | M11: 147.94 | N11: 142.21 | O11: 402.67 | P11: 228.31 | Q11: 186.07 | R11: 138.71 | S11: 407.42 | T11: 242.47 | U11: 154.14 | V11: 158.26 | W11: 459.94 | X11: 0.014742168 | Y11: -0.032759806 | Z11: 0.020737425 | AA11: 0.054578142
B12: TTWO | C12: United States | D12: Electronic Gaming & Multimedia | E12: Sep'26 | F12: 5.4 | G12: 903.3 | H12: 930 | I12: 1102 | J12: 1394 | K12: 1408 | L12: 1446 | M12: 1285 | N12: 1299 | O12: 1366 | P12: 1399 | Q12: 1338 | R12: 1353 | S12: 1360 | T12: 1583 | U12: 1504 | V12: 1774 | W12: 1699 | X12: 0.033761468 | Y12: 0.029463969 | Z12: 0.072586207 | AA12: 0.054492847
B13: ATS | C13: United States | D13: Specialty Industrial Machinery | E13: Jun'26 | F13: 4.5 | G13: 522.13 | H13: 546.8 | I13: 603.16 | J13: 610.59 | K13: 588.95 | L13: 647.05 | M13: 730.79 | N13: 753.65 | O13: 735.72 | P13: 752.05 | Q13: 791.47 | R13: 694.27 | S13: 612.78 | T13: 651.99 | U13: 574.24 | V13: 736.72 | W13: 728.46 | X13: -0.035101752 | Y13: -0.07897808 | Z13: 0.016756932 | AA13: 0.04491154
B14: PGC | C14: United States | D14: Banks - Regional | E14: Dec'25 | F14: 4.3 | G14: 52.43 | H14: 51.96 | I14: 59.95 | J14: 61.31 | K14: 62.9 | L14: 60.52 | M14: 55.8 | N14: 50.01 | O14: 49.2 | P14: 52.45 | Q14: 52.69 | R14: 55.4 | S14: 59.86 | T14: 59.89 | U14: 63.16 | V14: 65.9 | W14: 70.53 | X14: 0.033756806 | Y14: 0.045953301 | Z14: 0.044060258 | AA14: 0.042884128
B15: HLNE | C15: United States | D15: Asset Management | E15: Sep'26 | F15: 4.1 | G15: 91.7 | H15: 100.9 | I15: 135.51 | J15: 153.38 | K15: 127.07 | L15: 112.79 | M15: 125.04 | N15: 126.88 | O15: 125.26 | P15: 176.67 | Q15: 196.73 | R15: 150 | S15: 168.26 | T15: 197.97 | U15: 175.96 | V15: 190.88 | W15: 198.59 | X15: 0.030795478 | Y15: -0.029132069 | Z15: 0.059058929 | AA15: 0.041373948
B16: SR | C16: United States | D16: Utilities - Regulated Gas | E16: Mar'26 | F16: 3.8 | G16: 555.4 | H16: 880.9 | I16: 448 | J16: 314.2 | K16: 814 | L16: 1123 | M16: 418.5 | N16: 310.4 | O16: 756.6 | P16: 1129 | Q16: 414.1 | R16: 293.8 | S16: 669.1 | T16: 1051 | U16: 421.9 | V16: 334.1 | W16: 762.2 | X16: -0.031125299 | Y16: 0.0032125206 | Z16: 0.016544872 | AA16: 0.037599451
B17: BALL | C17: United States | D17: Packaging & Containers | E17: Dec'25 | F17: 3.7 | G17: 3674 | H17: 3716 | I17: 4134 | J17: 3951 | K17: 3548 | L17: 2981 | M17: 3067 | N17: 3111 | O17: 2903 | P17: 2874 | Q17: 2959 | R17: 3082 | S17: 2880 | T17: 3097 | U17: 3338 | V17: 3379 | W17: 3347 | X17: 0.018906316 | Y17: 0.031536029 | Z17: 0.023957409 | AA17: 0.036789034
B18: INTA | C18: United States | D18: Software - Application | E18: Jun'26 | F18: 3.6 | G18: 64.7 | H18: 69.66 | I18: 75.52 | J18: 79.54 | K18: 84.69 | L18: 92.02 | M18: 94.62 | N18: 101.58 | O18: 103.93 | P18: 110.64 | Q18: 114.38 | R18: 118.81 | S18: 121.21 | T18: 129.07 | U18: 135.04 | V18: 139.03 | W18: 140.21 | X18: 0.039630999 | Y18: 0.042732745 | Z18: 0.040108702 | AA18: 0.036235339
B19: ATO | C19: United States | D19: Utilities - Regulated Gas | E19: Mar'26 | F19: 3.6 | G19: 1013 | H19: 1650 | I19: 816.43 | J19: 722.63 | K19: 1484 | L19: 1541 | M19: 662.73 | N19: 587.64 | O19: 1158 | P19: 1647 | Q19: 701.55 | R19: 657.94 | S19: 1176 | T19: 1951 | U19: 838.77 | V19: 737.48 | W19: 1343 | X19: 0.072683975 | Y19: 0.030585157 | Z19: 0.017202636 | AA19: 0.035507362
B20: INNV | C20: United States | D20: Medical Care Facilities | E20: Jun'26 | F20: 3.5 | G20: 175.35 | H20: 177.36 | I20: 172.86 | J20: 171.22 | K20: 167.46 | L20: 172.54 | M20: 176.87 | N20: 182.49 | O20: 188.9 | P20: 193.07 | Q20: 199.4 | R20: 205.14 | S20: 209 | T20: 218.14 | U20: 221.42 | V20: 236.11 | W20: 239.71 | X20: 0.031080696 | Y20: 0.026476529 | Z20: 0.036277381 | AA20: 0.034713509
... B23: AME | C23: United States | D23: Specialty Industrial Machinery | E23: Dec'25 | F23: 3.3 | G23: 1504 | H23: 1459 | I23: 1515 | J23: 1552 | K23: 1626 | L23: 1597 | M23: 1646 | N23: 1623 | O23: 1731 | P23: 1736 | Q23: 1735 | R23: 1709 | S23: 1762 | T23: 1732 | U23: 1778 | V23: 1893 | W23: 1998 | X23: -0.00057620282 | Y23: 0.0061977515 | Z23: 0.026357255 | AA23: 0.032937893
B24: APPS | C24: United States | D24: =VLOOKUP(B24,기업리스트!B:G,2,FALSE) -> Digital Turbine, Inc. | E24: Sep'26 | F24: 3.2 | G24: 216.82 | H24: 184.14 | I24: 188.63 | J24: 174.86 | K24: 162.31 | L24: 140.12 | M24: 146.37 | N24: 143.26 | O24: 142.63 | P24: 112.22 | Q24: 117.99 | R24: 118.73 | S24: 134.64 | T24: 119.15 | U24: 130.93 | V24: 140.38 | W24: 151.4 | X24: 0.014330617 | Y24: 0.026380706 | Z24: 0.043003277 | AA24: 0.03191773
B25: TDG | C25: United States | D25: Aerospace & Defense | E25: Mar'26 | F25: 3.2 | G25: 1194 | H25: 1327 | I25: 1398 | J25: 1510 | K25: 1397 | L25: 1592 | M25: 1744 | N25: 1852 | O25: 1789 | P25: 1919 | Q25: 2046 | R25: 2186 | S25: 2006 | T25: 2150 | U25: 2237 | V25: 2437 | W25: 2285 | X25: 0.028319235 | Y25: 0.022770625 | Z25: 0.029257489 | AA25: 0.031596829
B26: MPLX | C26: United States | D26: Oil & Gas Midstream | E26: Dec'25 | F26: 3.1 | G26: 2641 | H26: 2511 | I26: 2829 | J26: 3276 | K26: 2521 | L26: 2579 | M26: 2545 | N26: 2753 | O26: 2804 | P26: 2689 | Q26: 2707 | R26: 2823 | S26: 2892 | T26: 2938 | U26: 2833 | V26: 2949 | W26: 3252 | X26: 0.022410224 | Y26: 0.011091549 | Z26: 0.010969876 | AA26: 0.031002411
B27: ETN | C27: United States | D27: Specialty Industrial Machinery | E27: Dec'25 | F27: 3.1 | G27: 4798 | H27: 4843 | I27: 5212 | J27: 5313 | K27: 5384 | L27: 5483 | M27: 5866 | N27: 5880 | O27: 5967 | P27: 5943 | Q27: 6350 | R27: 6345 | S27: 6240 | T27: 6377 | U27: 7028 | V27: 6988 | W27: 7055 | X27: 0.017445132 | Y27: 0.026785714 | Z27: 0.024740285 | AA27: 0.030601134
B28: J | C28: United States | D28: Engineering & Construction | E28: Mar'26 | F28: 3 | G28: 3381 | H28: 3834 | I28: 3827 | J28: 3881 | K28: 3799 | L28: 4078 | M28: 4187 | N28: -1212 | O28: 2810 | P28: 2847 | Q28: 2883 | R28: 0 | S28: 2933 | T28: 2910 | U28: 3032 | V28: 3155 | W28: 3293 | X28: 0.0072723075 | Y28: 0.017075407 | Z28: 0.35549296 | AA28: 0.029925187
B29: PRU | C29: United States | D29: Insurance - Life | E29: Dec'25 | F29: 3 | G29: 16424 | H29: 11855 | I29: 11392 | J29: 20201 | K29: 11135 | L29: 17045 | M29: 13498 | N29: 8352 | O29: 15084 | P29: 23509 | Q29: 14883 | R29: 19490 | S29: 12523 | T29: 13470 | U29: 13726 | V29: 17879 | W29: 14229 | X29: -0.1425893 | Y29: -0.019166418 | Z29: -0.027208701 | AA29: 0.029619084
B30: HUBB | C30: United States | D30: Electrical Equipment & Parts | E30: Dec'25 | F30: 2.8 | G30: 1100 | H30: 1156 | I30: 1256 | J30: 1316 | K30: 1220 | L30: 1285 | M30: 1366 | N30: 1376 | O30: 1346 | P30: 1399 | Q30: 1453 | R30: 1443 | S30: 1334 | T30: 1365 | U30: 1484 | V30: 1502 | W30: 1493 | X30: -0.0060401492 | Y30: 0.0055406613 | Z30: 0.010487025 | AA30: 0.027968338
B31: VRNS | C31: United States | D31: Software - Infrastructure | E31: Dec'25 | F31: 2.4 | G31: 126.58 | H31: 96.26 | I31: 111.45 | J31: 123.31 | K31: 142.62 | L31: 107.34 | M31: 115.42 | N31: 122.31 | O31: 154.1 | P31: 114.02 | Q31: 130.35 | R31: 148.07 | S31: 158.51 | T31: 136.42 | U31: 152.16 | V31: 161.58 | W31: 173.37 | X31: 0.040657047 | Y31: 0.038039592 | Z31: 0.022699778 | AA31: 0.024413886
B32: BR | C32: United States | D32: Information Technology Services | E32: Mar'26 | F32: 2.4 | G32: 1193 | H32: 1260 | I32: 1534 | J32: 1723 | K32: 1283 | L32: 1293 | M32: 1646 | N32: 1839 | O32: 1431 | P32: 1405 | Q32: 1727 | R32: 1944 | S32: 1423 | T32: 1589 | U32: 1812 | V32: 2065 | W32: 1589 | X32: 0.028312048 | Y32: 0.012718839 | Z32: 0.017878251 | AA32: 0.024096386
B33: MDLZ | C33: United States | D33: Confectioners | E33: Dec'25 | F33: 2.4 | G33: 7658 | H33: 7764 | I33: 7274 | J33: 7763 | K33: 8695 | L33: 9166 | M33: 8507 | N33: 9029 | O33: 9314 | P33: 9290 | Q33: 8343 | R33: 9204 | S33: 9604 | T33: 9313 | U33: 8984 | V33: 9744 | W33: 10496 | X33: 0.00063115721 | Y33: 0.017578982 | Z33: 0.014553295 | AA33: 0.023695046
B34: ZWS | C34: United States | D34: Pollution & Treatment Controls | E34: Dec'25 | F34: 2.2 | G34: 232.3 | H34: 239.6 | I34: 284.2 | J34: 417.7 | K34: 340.3 | L34: 372.1 | M34: 403.2 | N34: 398.4 | O34: 356.8 | P34: 373.8 | Q34: 412 | R34: 410 | S34: 370.7 | T34: 388.8 | U34: 444.5 | V34: 455.4 | W34: 407.2 | X34: 0.0095754868 | Y34: 0.020550111 | Z34: 0.028128872 | AA34: 0.021995902
B35: AMGN | C35: United States | D35: Drug Manufacturers - General | E35: Dec'25 | F35: 2.2 | G35: 6846 | H35: 6238 | I35: 6594 | J35: 6652 | K35: 6839 | L35: 6105 | M35: 6986 | N35: 6903 | O35: 8196 | P35: 7447 | Q35: 8388 | R35: 8503 | S35: 9086 | T35: 8149 | U35: 9179 | V35: 9557 | W35: 9866 | X35: 0.021002872 | Y35: 0.023178808 | Z35: 0.030185869 | AA35: 0.021684134
B36: SWKS | C36: United States | D36: Semiconductors | E36: Dec'25 | F36: 1.9 | G36: 1311 | H36: 1510 | I36: 1336 | J36: 1233 | K36: 1407 | L36: 1329 | M36: 1153 | N36: 1071 | O36: 1219 | P36: 1202 | Q36: 1046 | R36: 905.5 | S36: 1025 | T36: 1069 | U36: 953.2 | V36: 965 | W36: 1100 | X36: -0.031829604 | Y36: -0.022939068 | Z36: 0.015053002 | AA36: 0.018692986
... B54: MLI | C54: United States | D54: Metal Fabrication | E54: Dec'25 | F54: 0.9 | G54: 956.36 | H54: 1010 | I54: 1150 | J54: 944.83 | K54: 877.58 | L54: 971.19 | M54: 896.98 | N54: 819.79 | O54: 732.38 | P54: 849.65 | Q54: 997.75 | R54: 997.83 | S54: 923.54 | T54: 1000 | U54: 1138 | V54: 1078 | W54: 962.39 | X54: 0.039893652 | Y54: 0.035786095 | Z54: 0.01974937 | AA54: 0.0093851008
B55: VLTO | C55: United States | D55: Pollution & Treatment Controls | E55: Dec'25 | F55: 0.9 | H55: 1172 | I55: 1231 | J55: 1219 | K55: 1248 | L55: 1225 | M55: 1253 | N55: 1255 | O55: 1288 | P55: 1246 | Q55: 1288 | R55: 1314 | S55: 1345 | T55: 1332 | U55: 1371 | V55: 1404 | W55: 1396 | X55: 0.016560755 | Y55: 0.015722675 | Z55: 0.016784782 | AA55: 0.0093543654
B56: POWL | C56: United States | D56: Electrical Equipment & Parts | E56: Mar'26 | F56: 0.9 | G56: 106.57 | H56: 127.85 | I56: 135.48 | J56: 162.68 | K56: 126.86 | L56: 171.44 | M56: 192.37 | N56: 208.64 | O56: 194.02 | P56: 255.11 | Q56: 288.17 | R56: 275.06 | S56: 241.43 | T56: 278.63 | U56: 286.27 | V56: 297.98 | W56: 251.18 | X56: 0.022193495 | Y56: -0.0017539163 | Z56: 0.021194944 | AA56: 0.0088290426
B57: CRVL | C57: United States | D57: Insurance Brokers | E57: Sep'26 | F57: 0.8 | G57: 164.51 | H57: 171.36 | I57: 176.31 | J57: 177.43 | K57: 179.39 | L57: 185.44 | M57: 190.25 | N57: 195.52 | O57: 202.3 | P57: 207.23 | Q57: 211.72 | R57: 224.38 | S57: 227.97 | T57: 231.51 | U57: 234.71 | V57: 239.64 | W57: 235.63 | X57: 0.027866407 | Y57: 0.025670515 | Z57: 0.016612779 | AA57: 0.0082027778
B58: FUBO | C58: United States | D58: Broadcasting | E58: Dec'25 | F58: 0.8 | P58: 1051 | Q58: 1076 | R58: 1058 | S58: 1058 | T58: 1116 | U58: 1125 | V58: 1091 | W58: 1091 | X58: 0.01531935 | Y58: 0.011374188 | Z58: 0.0075740188 | AA58: 0.0075170843
B59: IT | C59: United States | D59: Information Technology Services | E59: Dec'25 | F59: 0.6 | G59: 1306 | H59: 1263 | I59: 1377 | J59: 1332 | K59: 1505 | L59: 1409 | M59: 1503 | N59: 1409 | O59: 1586 | P59: 1473 | Q59: 1595 | R59: 1484 | S59: 1715 | T59: 1534 | U59: 1686 | V59: 1524 | W59: 1753 | X59: 0.0097335248 | Y59: 0.014380531 | Z59: 0.0062315002 | AA59: 0.0058832637
B60: BV | C60: United States | D60: Specialty Business Services | E60: Mar'26 | F60: 0.6 | G60: 591.8 | H60: 711.9 | I60: 747.4 | J60: 723.4 | K60: 655.9 | L60: 650.4 | M60: 766 | N60: 743.7 | O60: 626.7 | P60: 672.9 | Q60: 738.8 | R60: 728.7 | S60: 599.2 | T60: 662.5 | U60: 708.3 | V60: 702.8 | W60: 614.7 | X60: -0.0037961746 | Y60: -0.011175436 | Z60: -0.0095972135 | AA60: 0.0057991619
B61: HRB | C61: United States | D61: Personal Services | E61: Jun'26 | F61: 0.5 | G61: 158.82 | H61: 2062 | I61: 1050 | J61: 179.99 | K61: 166.41 | L61: 2094 | M61: 1032 | N61: 183.8 | O61: 179.08 | P61: 2185 | Q61: 1063 | R61: 193.81 | S61: 179.07 | T61: 2277 | U61: 1111 | V61: 203.55 | W61: 198.87 | X61: 0.025408188 | Y61: 0.01292797 | Z61: 0.0025898194 | AA61: 0.0052511258
B62: MTCH | C62: United States | D62: Internet Content & Information | E62: Dec'25 | F62: 0.5 | G62: 806.07 | H62: 798.63 | I62: 794.51 | J62: 809.55 | K62: 0 | L62: 787.12 | M62: 829.55 | N62: 881.6 | O62: 866.23 | P62: 859.65 | Q62: 864.07 | R62: 895.48 | S62: 860.18 | T62: 831.18 | U62: 863.74 | V62: 914.28 | W62: 878.01 | X62: -0.0081824923 | Y62: -9.5626951e-05 | Z62: 0.0054483594 | AA62: 0.0051392468
B63: MZTI | C63: United States | D63: Packaged Foods | E63: Jun'26 | F63: 0.4 | G63: 428.43 | H63: 403.49 | I63: 452.41 | J63: 425.54 | K63: 477.39 | L63: 464.94 | M63: 454.66 | N63: 461.57 | O63: 485.92 | P63: 471.45 | Q63: 452.83 | R63: 466.56 | S63: 509.3 | T63: 457.84 | U63: 475.43 | V63: 493.47 | W63: 517.95 | X63: -0.0071626301 | Y63: 0.011979666 | Z63: 0.014095426 | AA63: 0.0044678829
B64: SKY | C64: United States | D64: Residential Construction | E64: Sep'26 | F64: 0.4 | G64: 534.69 | H64: 638.12 | I64: 725.88 | J64: 806.83 | K64: 582.32 | L64: 491.53 | M64: 464.77 | N64: 464.24 | O64: 559.46 | P64: 536.36 | Q64: 627.78 | R64: 616.88 | S64: 644.93 | T64: 593.87 | U64: 701.32 | V64: 684.43 | W64: 656.61 | X64: 0.023706177 | Y64: 0.029611912 | Z64: 0.026417677 | AA64: 0.0044502867
B65: BRBR | C65: United States | D65: Packaged Foods | E65: Mar'26 | F65: 0.2 | G65: 306.5 | H65: 315.2 | I65: 370.6 | J65: 379.2 | K65: 362.7 | L65: 385.6 | M65: 445.9 | N65: 472.6 | O65: 430.4 | P65: 494.6 | Q65: 515.4 | R65: 555.8 | S65: 532.9 | T65: 588 | U65: 547.5 | V65: 648.2 | W65: 537.3 | X65: 0.04450374 | Y65: 0.014643493 | Z65: 0.041543027 | AA65: 0.0018993352
B66: GPK | C66: United States | D66: Packaging & Containers | E66: Dec'25 | F66: 0.1 | G66: 1988 | H66: 2245 | I66: 2358 | J66: 2451 | K66: 2386 | L66: 2438 | M66: 2392 | N66: 2349 | O66: 2249 | P66: 2259 | Q66: 2237 | R66: 2216 | S66: 2095 | T66: 2120 | U66: 2204 | V66: 2190 | W66: 2103 | X66: -0.0157829 | Y66: -0.0038071066 | Z66: -0.0030110017 | AA66: 0.00092926008
B67: ATI | C67: United States | D67: Metal Fabrication | E67: Dec'25 | F67: 0.1 | G67: 765.4 | H67: 834.1 | I67: 959.5 | J67: 1032 | K67: 1010 | L67: 1038 | M67: 1046 | N67: 1026 | O67: 1064 | P67: 1043 | Q67: 1095 | R67: 1051 | S67: 1173 | T67: 1144 | U67: 1140 | V67: 1126 | W67: 1177 | X67: 0.023154516 | Y67: 0.010082904 | Z67: 0.01663709 | AA67: 0.00087279075
B68: MPC | C68: United States | D68: Oil & Gas Refining & Marketing | E68: Dec'25 | F68: -0.1 | G68: 35438 | H68: 38260 | I68: 54052 | J68: 46006 | K68: 0 | L68: 34941 | M68: 36612 | N68: 41258 | O68: 36537 | P68: 32987 | Q68: 37990 | R68: 35156 | S68: 33203 | T68: 31620 | U68: 33883 | V68: 34875 | W68: 33049 | X68: -0.009810817 | Y68: -0.029767556 | Z68: -0.0020991768 | AA68: -0.0011528586
B69: CLX | C69: United States | D69: Household & Personal Products | E69: Jun'26 | F69: -0.2 | G69: 1691 | H69: 1809 | I69: 1801 | J69: 1740 | K69: 1715 | L69: 1915 | M69: 2019 | N69: 1386 | O69: 1990 | P69: 1814 | Q69: 1903 | R69: 1762 | S69: 1686 | T69: 1668 | U69: 1988 | V69: 1429 | W69: 1673 | X69: -0.020376832 | Y69: 0.012109987 | Z69: -0.046875 | AA69: -0.0019199527
B70: ATKR | C70: United States | D70: Electrical Equipment & Parts | E70: Mar'26 | F70: -0.2 | G70: 840.8 | H70: 982.57 | I70: 1062 | J70: 1029 | K70: 833.82 | L70: 895.93 | M70: 919.12 | N70: 869.89 | O70: 798.48 | P70: 792.91 | Q70: 822.36 | R70: 788.3 | S70: 661.6 | T70: 701.73 | U70: 735.05 | V70: 752.01 | W70: 655.55 | X70: -0.029747127 | Y70: -0.029357866 | Z70: -0.012571535 | AA70: -0.0021225166
... B93: KREF | C93: United States | D93: REIT - Mortgage | E93: Dec'25 | F93: -74.5 | G93: 47.81 | H93: 48.42 | I93: 38.18 | J93: -29.44 | K93: 34.24 | L93: -9.3 | M93: -5.41 | N93: 41.24 | O93: 1.17 | P93: 13.49 | Q93: 43.11 | R93: 8.82 | S93: 35.2 | T93: 10.35 | U93: -13.98 | V93: 30.44 | W93: -10.97 | X93: -0.03120652 | Y93: -0.5856586 | Z93: 0.53528101 | AA93: -0.74455733
B94: 7974 | C94: Japan | D94: =VLOOKUP(B94,기업리스트!B:G,2,FALSE) -> Nintendo Co., Ltd. | E94: Jun'26 | F94: 16.8 | G94: 301625 | H94: 695947 | I94: 375125 | J94: 307460 | K94: 349514 | L94: 638204 | M94: 306499 | N94: 461341 | O94: 334896 | P94: 598559 | Q94: 277069 | R94: 246638 | S94: 276661 | T94: 432919 | U94: 208704 | V94: 572363 | W94: 527202 | X94: -0.11840503 | Y94: -0.055433164 | Z94: 0.279611 | AA94: 0.16807534
B95: 8386 | C95: Japan | D95: =VLOOKUP(B95,기업리스트!B:G,2,FALSE) -> The Hyakujushi Bank, Ltd. | E95: Jun'26 | F95: 6 | G95: 17037 | H95: 18567 | I95: 15023 | J95: 21178 | K95: 20437 | L95: 19040 | M95: 14645 | N95: 16940 | O95: 14494 | P95: 17039 | Q95: 17520 | R95: 17247 | S95: 14292 | T95: 19913 | U95: 18479 | V95: 20602 | W95: 18703 | X95: 0.043480892 | Y95: 0.013904193 | Z95: 0.047975862 | AA95: 0.060188849
B96: 6471 | C96: Japan | D96: =VLOOKUP(B96,기업리스트!B:G,2,FALSE) -> NSK Ltd. | E96: Sep'26 | F96: 5.8 | G96: 215015 | H96: 232386 | I96: 219387 | J96: 244436 | K96: 236356 | L96: 237918 | M96: 188247 | N96: 198443 | O96: 201368 | P96: 200808 | Q96: 200495 | R96: 197148 | S96: 199278 | T96: 199746 | U96: 195760 | V96: 216490 | W96: 246214 | X96: -0.0013312792 | Y96: -0.0059435122 | Z96: 0.024423814 | AA96: 0.057854683
B97: 8368 | C97: Japan | D97: =VLOOKUP(B97,기업리스트!B:G,2,FALSE) -> The Hyakugo Bank, Ltd. | E97: Jun'26 | F97: 5.5 | G97: 20648 | H97: 21899 | I97: 28457 | J97: 22575 | K97: 22660 | L97: 21777 | M97: 24863 | N97: 27538 | O97: 24911 | P97: 24195 | Q97: 26499 | R97: 25578 | S97: 25223 | T97: 27680 | U97: 26419 | V97: 28942 | W97: 31175 | X97: 0.034336667 | Y97: -0.00076204991 | Z97: 0.032068637 | AA97: 0.054976724
B98: 3064 | C98: Japan | D98: =VLOOKUP(B98,기업리스트!B:G,2,FALSE) -> MonotaRO Co., Ltd. | E98: Dec'25 | F98: 5 | G98: 51281 | H98: 54610 | I98: 55253 | J98: 56130 | K98: 59977 | L98: 62014 | M98: 62386 | N98: 62823 | O98: 67063 | P98: 69139 | Q98: 70258 | R98: 72112 | S98: 76610 | T98: 79106 | U98: 81126 | V98: 81168 | W98: 92480 | X98: 0.034593345 | Y98: 0.036459277 | Z98: 0.029311807 | AA98: 0.049904091
B99: 4062 | C99: Japan | D99: =VLOOKUP(B99,기업리스트!B:G,2,FALSE) -> Ibiden Co.,Ltd. | E99: Sep'26 | F99: 3.8 | G99: 103402 | H99: 101904 | I99: 98318 | J99: 115261 | K99: 103102 | L99: 100868 | M99: 94601 | N99: 93039 | O99: 92527 | P99: 90344 | Q99: 88220 | R99: 93365 | S99: 88752 | T99: 99099 | U99: 97464 | V99: 98021 | W99: 103136 | X99: 0.024273527 | Y99: 0.025021925 | Z99: 0.012295342 | AA99: 0.037523217
B100: 8015 | C100: Japan | D100: =VLOOKUP(B100,기업리스트!B:G,2,FALSE) -> Toyota Tsusho Corporation | E100: Jun'26 | F100: 2.9 | G100: 1872539 | H100: 2032046 | I100: 2251287 | J100: 2375630 | K100: 2532117 | L100: 2459654 | M100: 2481158 | N100: 2540752 | O100: 2594483 | P100: 2574946 | Q100: 2478798 | R100: 2541473 | S100: 2524447 | T100: 2581851 | U100: 2661779 | V100: 2593820 | W100: 2820564 | X100: 0.00068233491 | Y100: 0.018069397 | Z100: 0.0050775252 | AA100: 0.028577489
B101: 2331 | C101: Japan | D101: =VLOOKUP(B101,기업리스트!B:G,2,FALSE) -> Alsok Co.,Ltd. | E101: Jun'26 | F101: 2.8 | G101: 128278 | H101: 118493 | I101: 125309 | J101: 114008 | K101: 122045 | L101: 121764 | M101: 134409 | N101: 121593 | O101: 124786 | P101: 132611 | Q101: 142410 | R101: 129011 | S101: 134269 | T101: 137221 | U101: 151380 | V101: 141154 | W101: 150183 | X101: 0.0085639819 | Y101: 0.016522045 | Z101: 0.022002932 | AA101: 0.028215111
B102: 5802 | C102: Japan | D102: =VLOOKUP(B102,기업리스트!B:G,2,FALSE) -> Sumitomo Electric Industries, Ltd. | E102: Sep'26 | F102: 2.5 | G102: 868697 | H102: 928753 | I102: 877121 | J102: 1013955 | K102: 1020897 | L102: 1093588 | M102: 994123 | N102: 1077980 | O102: 1149823 | P102: 1180888 | Q102: 1115547 | R102: 1132231 | S102: 1193461 | T102: 1238550 | U102: 1148436 | V102: 1225025 | W102: 1313436 | X102: 0.012475209 | Y102: 0.007027881 | Z102: 0.019690291 | AA102: 0.02496633
B103: 6806 | C103: Japan | D103: =VLOOKUP(B103,기업리스트!B:G,2,FALSE) -> Hirose Electric Co.,Ltd. | E103: Sep'26 | F103: 2.3 | G103: 42817 | H103: 41667 | I103: 46574 | J103: 48130 | K103: 47461 | L103: 41059 | M103: 40455 | N103: 42455 | O103: 42252 | P103: 40347 | Q103: 44871 | R103: 49648 | S103: 49903 | T103: 44998 | U103: 48972 | V103: 53053 | W103: 54524 | X103: 0.025171971 | Y103: 0.021650301 | Z103: 0.01759499 | AA103: 0.023465667
B104: 6724 | C104: Japan | D104: =VLOOKUP(B104,기업리스트!B:G,2,FALSE) -> Seiko Epson Corporation | E104: Sep'26 | F104: 2 | G104: 296145 | H104: 282171 | I104: 297874 | J104: 335253 | K104: 361276 | L104: 335927 | M104: 314840 | N104: 323693 | O104: 353568 | P104: 321897 | Q104: 336614 | R104: 337584 | S104: 349620 | T104: 339125 | U104: 320879 | V104: 346473 | W104: 376473 | X104: 0.012802116 | Y104: -0.01154487 | Z104: 0.0065980903 | AA104: 0.019801681
B105: 9021 | C105: Japan | D105: =VLOOKUP(B105,기업리스트!B:G,2,FALSE) -> West Japan Railway Company | E105: Sep'26 | F105: 1.9 | G105: 293156 | H105: 301113 | I105: 297144 | J105: 319561 | K105: 358140 | L105: 420686 | M105: 369270 | N105: 400632 | O105: 424420 | P105: 440701 | Q105: 402780 | R105: 408606 | S105: 434291 | T105: 462267 | U105: 427059 | V105: 444770 | W105: 467641 | X105: 0.012788355 | Y105: 0.014215337 | Z105: 0.02087722 | AA105: 0.018858994
... B128: 5857 | C128: Japan | D128: =VLOOKUP(B128,기업리스트!B:G,2,FALSE) -> ARE Holdings, Inc. | E128: Jun'26 | F128: -8.5 | G128: 46436 | H128: 47626 | I128: 47955 | J128: 59749 | K128: 72903 | L128: 73173 | M128: 86622 | N128: 66523 | O128: 85372 | P128: 83236 | Q128: 0 | R128: 92300 | S128: 148057 | T128: 132612 | U128: 133242 | V128: 137120 | W128: 101119 | X128: 0.15258674 | Y128: 0.35724685 | Z128: 0.088540154 | AA128: -0.08518214
B129: NAZARA | C129: India | D129: =VLOOKUP(B129,기업리스트!B:G,2,FALSE) -> Nazara Technologies Limited | E129: Jun'26 | F129: 11.1 | G129: 1296 | H129: 1858 | I129: 1775 | J129: 2231 | K129: 2638 | L129: 3148 | M129: 2894 | N129: 2544 | O129: 2972 | P129: 3204 | Q129: 2662 | R129: 2501 | S129: 3189 | T129: 5347 | U129: 5204 | V129: 4988 | W129: 5265 | X129: 0.18544479 | Y129: 0.18556099 | Z129: 0.15313096 | AA129: 0.11085006
B130: BAJFINANCE | C130: India | D130: =VLOOKUP(B130,기업리스트!B:G,2,FALSE) -> Bajaj Finance Limited | E130: Sep'26 | F130: 10.4 | G130: 49494 | H130: 53691 | I130: 58829 | J130: 62671 | K130: 65934 | L130: 69240 | M130: 74028 | N130: 77699 | O130: 80506 | P130: 84870 | Q130: 87338 | R130: 90370 | S130: 96294 | T130: 96194 | U130: 104899 | V130: 109007 | W130: 138759 | X130: 0.031554426 | Y130: 0.047437033 | Z130: 0.048063607 | AA130: 0.10449219
B131: ABCAPITAL | C131: India | D131: =VLOOKUP(B131,기업리스트!B:G,2,FALSE) -> Aditya Birla Capital Limited | E131: Sep'26 | F131: 6.9 | G131: 48367 | H131: 50157 | I131: 45186 | J131: 55593 | K131: 80767 | L131: 63486 | M131: 50712 | N131: 55548 | O131: 62544 | P131: 83338 | Q131: 60984 | R131: 76361 | S131: 65194 | T131: 92775 | U131: 63665 | V131: 73982 | W131: 85689 | X131: 0.0330107 | Y131: 0.0090784724 | Z131: -0.0079833554 | AA131: 0.069329806
B132: SOLARINDS | C132: India | D132: =VLOOKUP(B132,기업리스트!B:G,2,FALSE) -> Solar Industries India Limited | E132: Sep'26 | F132: 6.9 | G132: 10179 | H132: 13169 | I132: 16156 | J132: 15666 | K132: 18118 | L132: 19285 | M132: 16822 | N132: 13475 | O132: 14291 | P132: 16107 | Q132: 16948 | R132: 17158 | S132: 19731 | T132: 21666 | U132: 21545 | V132: 20822 | W132: 25483 | X132: 0.079477868 | Y132: 0.060884998 | Z132: 0.045742821 | AA132: 0.068669118
B133: ADANIPORTS | C133: India | D133: =VLOOKUP(B133,기업리스트!B:G,2,FALSE) -> Adani Ports and Special Economic Zone Limited | E133: Sep'26 | F133: 5 | G133: 37971 | H133: 50298 | I133: 46380 | J133: 52108 | K133: 47862 | L133: 57969 | M133: 62476 | N133: 66464 | O133: 69201 | P133: 68965 | Q133: 69563 | R133: 70670 | S133: 79636 | T133: 84884 | U133: 91261 | V133: 91675 | W133: 97046 | X133: 0.055114703 | Y133: 0.071198643 | Z133: 0.0643435 | AA133: 0.050107064
B134: BECTORFOOD | C134: India | D134: =VLOOKUP(B134,기업리스트!B:G,2,FALSE) -> Mrs. Bectors Food Specialities Limited | E134: Jun'26 | F134: 2.9 | G134: 2463 | H134: 2632 | I134: 2523 | J134: 3008 | K134: 3474 | L134: 3679 | M134: 3461 | N134: 3742 | O134: 4145 | P134: 4289 | Q134: 4064 | R134: 4394 | S134: 4963 | T134: 4921 | U134: 4461 | V134: 4730 | W134: 5514 | X134: 0.035686053 | Y134: 0.021644314 | Z134: 0.017930519 | AA134: 0.028885976
B135: PILANIINVS | C135: India | D135: =VLOOKUP(B135,기업리스트!B:G,2,FALSE) -> Pilani Investment and Industries Corporation Limited | E135: Jun'26 | F135: 2.4 | G135: 979.7 | H135: 516.31 | I135: 482.56 | J135: 597.49 | K135: 1124 | L135: 524.55 | M135: 527.86 | N135: 542.74 | O135: 1062 | P135: 611.97 | Q135: 646.59 | R135: 612.53 | S135: 1224 | T135: 609.36 | U135: 596.62 | V135: 495.8 | W135: 1295 | X135: -0.00084327112 | Y135: -0.016158552 | Z135: -0.038366349 | AA135: 0.024267033
B136: PIDILITIND | C136: India | D136: =VLOOKUP(B136,기업리스트!B:G,2,FALSE) -> Pidilite Industries Limited | E136: Jun'26 | F136: 2.4 | G136: 26264 | H136: 28507 | I136: 25071 | J136: 31011 | K136: 30112 | L136: 29976 | M136: 26893 | N136: 32751 | O136: 30760 | P136: 31300 | Q136: 29019 | R136: 33954 | S136: 32349 | T136: 33689 | U136: 31411 | V136: 37531 | W136: 35544 | X136: 0.018867179 | Y136: 0.018541055 | Z136: 0.027221601 | AA136: 0.023670173
B137: RPOWER | C137: India | D137: =VLOOKUP(B137,기업리스트!B:G,2,FALSE) -> Reliance Power Limited | E137: Sep'26 | F137: 0.3 | G137: 17959 | H137: 18461 | I137: 20630 | J137: 18638 | K137: 18861 | L137: 17011 | M137: 19218 | N137: 20523 | O137: 19466 | P137: 19719 | Q137: 19922 | R137: 17598 | S137: 18528 | T137: 19780 | U137: 18856 | V137: 19740 | W137: 18728 | X137: 0.00080509985 | Y137: -0.014058132 | Z137: 0.028650919 | AA137: 0.002600645
B138: CMSINFO | C138: India | D138: =VLOOKUP(B138,기업리스트!B:G,2,FALSE) -> CMS Info Systems Limited | E138: Jun'26 | F138: -0.6 | G138: 3721 | H138: 4037 | I138: 4441 | J138: 4533 | K138: 4717 | L138: 4883 | M138: 5014 | N138: 5116 | O138: 5437 | P138: 5823 | Q138: 6271 | R138: 5994 | S138: 6245 | T138: 5815 | U138: 6191 | V138: 6274 | W138: 6086 | X138: -0.00032877163 | Y138: -0.0032887975 | Z138: 0.011548773 | AA138: -0.0064831804
B139: HGINFRA | C139: India | D139: N/A | E139: Jun'26 | F139: -13.1 | G139: 11059 | H139: 7957 | I139: 11850 | J139: 15354 | K139: 13512 | L139: 9545 | M139: 13645 | N139: 0 | O139: 0 | P139: 0 | Q139: 0 | R139: 9024 | S139: 12648 | T139: 0 | U139: 0 | V139: 14822 | W139: 9045 | X139: 0 | Y139: 0 | Z139: 0.26753415 | AA139: -0.13116127
B140: HMN | C140: United States | D140: Insurance - Property & Casualty | E140: Sep'25 | F140: 1.6 | G140: 329.6 | H140: 331.4 | I140: 346.7 | J140: 345.9 | K140: 342.6 | L140: 346.4 | M140: 353.9 | N140: 356.4 | O140: 378.7 | P140: 402.9 | Q140: 386 | R140: 388.1 | S140: 412.1 | T140: 409 | U140: 416.4 | V140: 411.7 | W140: 438.5 | X140: 0.0038386508 | Y140: 0.019057172 | Z140: 0.014517717 | AA140: 0.016007761
B141: PNI | C141: United States | D141: Asset Management | E141: Jun'25 | F141: 1.1 | G141: 2.21 | H141: 2.07 | I141: 2.07 | J141: 1.85 | K141: 1.85 | L141: 1.87 | M141: 1.87 | N141: 1.83 | O141: 1.83 | P141: 1.81 | Q141: 1.81 | R141: 1.76 | S141: 1.76 | T141: 1.79 | U141: 1.79 | V141: 1.84 | W141: 1.84 | X141: -0.0028011204 | Y141: -0.0028089888 | Z141: 0.011267606 | AA141: 0.011142061
B142: OMC | C142: United States | D142: Advertising Agencies | E142: Sep'25 | F142: 1 | G142: 3435 | H142: 3856 | I142: 3410 | J142: 3567 | K142: 3443 | L142: 3868 | M142: 3443 | N142: 3610 | O142: 3578 | P142: 4061 | Q142: 3631 | R142: 3854 | S142: 3883 | T142: 4322 | U142: 3690 | V142: 4016 | W142: 4037 | X142: 0.016916197 | Y142: 0.0037603569 | Z142: 0.010286367 | AA142: 0.0096788385
B143: SNCY | C143: United States | D143: Airlines | E143: Sep'25 | F143: 0.6 | G143: 173.66 | H143: 172.55 | I143: 226.53 | J143: 219.07 | K143: 221.7 | L143: 227.15 | M143: 294.12 | N143: 261.09 | O143: 248.88 | P143: 245.54 | Q143: 311.48 | R143: 254.38 | S143: 249.47 | T143: 260.41 | U143: 326.65 | V143: 263.62 | W143: 255.54 | X143: 0.014016798 | Y143: 0.014101921 | Z143: 0.0084699929 | AA143: 0.0055174294
B144: CSL | C144: United States | D144: Building Products & Equipment | E144: Sep'25 | F144: 0.3 | G144: 1316 | H144: 1376 | I144: 1425 | J144: 0 | K144: 1497 | L144: 1150 | M144: 892.6 | N144: 1307 | O144: 1260 | P144: 1128 | Q144: 1097 | R144: 1451 | S144: 1334 | T144: 1123 | U144: 1096 | V144: 1450 | W144: 1347 | X144: -0.00099800399 | Y144: -0.0001998002 | Z144: -0.00019984013 | AA144: 0.0025984409
B145: ACT | C145: United States | D145: Insurance - Specialty | E145: Sep'25 | F145: 0.2 | G145: 280.31 | H145: 272.84 | I145: 269.59 | J145: 273.54 | K145: 275.08 | L145: 276.84 | M145: 280.94 | N145: 277.52 | O145: 299.04 | P145: 296.19 | Q145: 291.58 | R145: 298.83 | S145: 309.59 | T145: 301.78 | U145: 306.78 | V145: 304.89 | W145: 311.46 | X145: 0.0046731707 | Y145: 0.012647906 | Z145: 0.0049795395 | AA145: 0.001528977
B146: SNT | C146: United States | D146: Security & Protection Services | E146: Sep'25 | F146: -0.5 | G146: 9.26 | H146: 9.01 | I146: 6.79 | J146: 9.12 | K146: 9.74 | L146: 9.91 | M146: 6.45 | N146: 8.44 | O146: 8.97 | P146: 8.94 | Q146: 7.51 | R146: 8.31 | S146: 9.7 | T146: 10.24 | U146: 8.45 | V146: 9.65 | W146: 9.5 | X146: 0.037724898 | Y146: 0.026286353 | Z146: 0.036512262 | AA146: -0.0052576236
B147: SU | C147: United States | D147: Oil & Gas Integrated | E147: Sep'25 | F147: -0.7 | G147: 10145 | H147: 11149 | I147: 13337 | J147: 16135 | K147: 14944 | L147: 13920 | M147: 11914 | N147: 11719 | O147: 12649 | P147: 12810 | Q147: 12381 | R147: 12889 | S147: 12888 | T147: 12531 | U147: 12323 | V147: 11991 | W147: 12552 | X147: -0.0054740229 | Y147: -0.0011442325 | Z147: -0.01773617 | AA147: -0.0067560775
B148: RNR | C148: United States | D148: Insurance - Reinsurance | E148: Sep'25 | F148: -5.9 | G148: 1549 | H148: 1413 | I148: 891.9 | J148: 917.79 | K148: 1288 | L148: 2020 | M148: 2220 | N148: 1867 | O148: 1862 | P148: 3228 | Q148: 2635 | R148: 2837 | S148: 3957 | T148: 2342 | U148: 3478 | V148: 3198 | W148: 3197 | X148: -0.07000079 | Y148: 0.071616685 | Z148: 0.028618995 | AA148: -0.058574181
B149: SSII | C149: Unknown | D149: Medical Devices | E149: Sep'25 | F149: 30.5 | I149: 0 | J149: 0 | K149: 0.53 | L149: 1.46 | M149: 1.51 | N149: 0.75 | O149: 2.19 | P149: 1.43 | Q149: 3.64 | R149: 4.51 | S149: 4.39 | T149: 8.12 | U149: 5.12 | V149: 10 | W149: 12.83 | X149: 0.47888332 | Y149: 0.071636012 | Z149: 0.24796748 | AA149: 0.30546507
B150: 1080 | C150: Hong Kong | D150: N/A | E150: H1 2025 | F150: 4.5 | N150: 627.15 | O150: 502.82 | P150: 1024 | Q150: 443.28 | R150: 603.61 | S150: 322.27 | T150: 269.62 | U150: 333.6 | V150: 236.47 | W150: 374.83 | X150: -0.31522339 | Y150: -0.066927837 | Z150: -0.24010202 | AA150: 0.045233915
B151: PUB | C151: France | D151: N/A | E151: H1 2025 | F151: 4.5 | N151: 5510 | O151: 5493 | P151: 6245 | Q151: 6547 | R151: 7649 | S151: 7105 | T151: 7697 | U151: 7650 | V151: 8380 | W151: 8483 | X151: 0.052711827 | Y151: 0.038037106 | Z151: 0.024284907 | AA151: 0.044693825
B152: CRLA | C152: France | D152: N/A | E152: H1 2025 | F152: 2.4 | N152: 293.42 | O152: 315.5 | P152: 295.49 | Q152: 362.05 | R152: 262.46 | S152: 313.6 | T152: 258.33 | U152: 314.8 | V152: 248.82 | W152: 340.45 | X152: -0.030123217 | Y152: -0.03949216 | Z152: -0.01186923 | AA152: 0.02364493
B153: INWI | C153: Sweden | D153: N/A | E153: Sep'25 | F153: -0.5 | G153: 1897 | H153: 2175 | I153: 2073 | J153: 2475 | K153: 2386 | L153: 2613 | M153: 2095 | N153: 2263 | O153: 2339 | P153: 2273 | Q153: 1811 | R153: 2331 | S153: 2273 | T153: 2423 | U153: 1999 | V153: 2339 | W153: 2224 | X153: 0.017265193 | Y153: 0.021271781 | Z153: 0.00088632838 | AA153: -0.005423954

Sheet Operating Income
B2: Ticker | C2: Country | D2: Industry | E2: Latest_Date | F2: Growth_Rate | G2: 4Q21 | H2: 1Q22 | I2: 2Q22 | J2: 3Q22 | K2: 4Q22 | L2: 1Q23 | M2: 2Q23 | N2: 3Q23 | O2: 4Q23 | P2: 1Q24 | Q2: 2Q24 | R2: 3Q24 | S2: 4Q24 | T2: 1Q25 | U2: 2Q25 | V2: 3Q25 | W2: 4Q25 | X2: 1Q25 | Y2: 2Q25 | Z2: 3Q25 | AA2: 4Q25
B3: KREF | C3: United States | D3: REIT - Mortgage | E3: Dec'25 | F3: 1180.3 | G3: 35.67 | H3: 35.41 | I3: 25 | J3: -42.92 | K3: 18.86 | L3: -25.09 | M3: -19.95 | N3: 27 | O3: -12.91 | P3: -3.39 | Q3: 25.6 | R3: -7.24 | S3: 19.6 | T3: -5.75 | U3: -30.57 | V3: 12.77 | W3: -27.02 | X3: -0.068267284 | Y3: -1.7438684 | Z3: -0.8351419 | AA3: 11.802532
B4: INNV | C4: United States | D4: Medical Care Facilities | E4: Jun'26 | F4: 239.2 | G4: 2.95 | H4: -6.27 | I4: -12.35 | J4: -16.6 | K4: -13.68 | L4: -8.17 | M4: -10.94 | N4: -10.72 | O4: -1.79 | P4: -5.79 | Q4: -4.88 | R4: -4.9 | S4: -4.06 | T4: -10.16 | U4: 13.07 | V4: 8.39 | W4: 13.26 | X4: 0.22261844 | Y4: -0.74791667 | Z4: -2.1966942 | AA4: 2.3922652
B5: IAC | C5: United States | D5: Internet Content & Information | E5: Dec'25 | F5: 63.8 | G5: -4.52 | H5: -117.74 | I5: -106.37 | J5: -97.26 | K5: 0 | L5: -65.5 | M5: -51.8 | N5: -15.39 | O5: -105.06 | P5: -63.37 | Q5: -21.54 | R5: 8.15 | S5: 51.24 | T5: 35.67 | U5: 0.68 | V5: -20.4 | W5: 94.08 | X5: -3.8808777 | Y5: 0.30223069 | Z5: -0.29820347 | AA5: 0.63759488
B6: ATS | C6: United States | D6: Specialty Industrial Machinery | E6: Jun'26 | F6: 60.8 | G6: 43.65 | H6: 53.69 | I6: 66.61 | J6: 67.15 | K6: 58.72 | L6: 67.17 | M6: 69.13 | N6: 79.15 | O6: 84.22 | P6: 96.46 | Q6: 88.05 | R6: 69.89 | S6: 40.94 | T6: 39.54 | U6: -84.45 | V6: 60.58 | W6: 75.34 | X6: -0.19272703 | Y6: -0.72351313 | Z6: -0.1412318 | AA6: 0.60766649
B7: HTLD | C7: United States | D7: Trucking | E7: Dec'25 | F7: 59.2 | G7: 16.41 | H7: 18.14 | I7: 23.34 | J7: 27.91 | K7: 22.07 | L7: 16.1 | M7: 8.21 | N7: -8.51 | O7: -14.51 | P7: -14.29 | Q7: -0.86 | R7: -7.62 | S7: -4.98 | T7: -16.68 | U7: -15.2 | V7: -13.94 | W7: -35.04 | X7: 0.086126126 | Y7: 0.47577969 | Z7: 0.14208633 | AA7: 0.59173228
B8: PRU | C8: United States | D8: Insurance - Life | E8: Dec'25 | F8: 57.7 | G8: 2448 | H8: -657 | I8: -1061 | J8: -126 | K8: -1435 | L8: 1847 | M8: 621 | N8: -1058 | O8: 2069 | P8: 1390 | Q8: 1415 | R8: 553 | S8: -148 | T8: 920 | U8: 740 | V8: 1773 | W8: 1747 | X8: -0.14641745 | Y8: -0.24635036 | Z8: 0.59079903 | AA8: 0.57686454
B9: MPC | C9: United States | D9: Oil & Gas Refining & Marketing | E9: Dec'25 | F9: 28.4 | G9: 1610 | H9: 1613 | I9: 8110 | J9: 5462 | K9: 0 | L9: 3948 | M9: 3118 | N9: 4448 | O9: 2130 | P9: 1571 | Q9: 2161 | R9: 1140 | S9: 886 | T9: 452 | U9: 1973 | V9: 1733 | W9: 2321 | X9: -0.19433831 | Y9: -0.040525975 | Z9: 0.13322849 | AA9: 0.28449643
B10: AMD | C10: United States | D10: Semiconductors | E10: Dec'25 | F10: 22.899506 | G10: 1174 | H10: 951 | I10: 526 | J10: -64 | K10: -149 | L10: -145 | M10: -20 | N10: 224 | O10: 342 | P10: 36 | Q10: 269 | R10: 724 | S10: 1057 | T10: 806 | U10: -98 | V10: 1270 | W10: 1752 | X10: 0.36912752 | Y10: -0.1285014 | Z10: 0.21936521 | AA10: 0.22899506
B11: MSGE | C11: United States | D11: Leisure | E11: Jun'26 | F11: 19.8 | G11: 59.98 | H11: 21.19 | I11: -5.27 | J11: -11.31 | K11: 116.62 | L11: 27.42 | M11: -25.42 | N11: -20.48 | O11: 137.25 | P11: 18.31 | Q11: -6.9 | R11: -19.38 | S11: 138.11 | T11: 36.25 | U11: -23.19 | V11: -15.41 | W11: 164.94 | X11: 0.13785154 | Y11: -0.1100081 | Z11: 0.030123682 | AA11: 0.19762817
B12: SIMO | C12: United States | D12: Semiconductors | E12: Dec'25 | F12: 17.7 | G12: 68.87 | H12: 66.46 | I12: 67.85 | J12: 55.07 | K12: 24.93 | L12: 5.52 | M12: 5.04 | N12: 15.69 | O12: 14.94 | P12: 17.95 | Q12: 32.04 | R12: 24.46 | S12: 17.69 | T12: 9.77 | U12: 22.33 | V12: 29.23 | W12: 31.71 | X12: -0.088777947 | Y12: -0.11565031 | Z12: 0.064242424 | AA12: 0.17742344
B13: CPRI | C13: United States | D13: Luxury Goods | E13: Sep'26 | F13: 17.2 | G13: 343 | H13: 172 | I13: 233 | J13: 263 | K13: 237 | L13: 89 | M13: 78 | N13: 124 | O13: 141 | P13: 41 | Q13: 17 | R13: 25 | S13: 69 | T13: -39 | U13: 17 | V13: 11 | W13: 79 | X13: -0.52631579 | Y13: 0 | Z13: -0.19444444 | AA13: 0.17241379
B14: VRNS | C14: United States | D14: Software - Infrastructure | E14: Dec'25 | F14: 15.3 | G14: -17.83 | H14: -48.09 | I14: -37.57 | J14: -25.58 | K14: -9.99 | L14: -43.12 | M14: -39.72 | N14: -29.15 | O14: -5.24 | P14: -47.63 | Q14: -28.83 | R14: -23.64 | S14: -10.9 | T14: -43.16 | U14: -36.55 | V14: -35.93 | W14: -30.26 | X14: -0.04027027 | Y14: 0.072467849 | Z14: 0.10757112 | AA14: 0.1529951
... B34: RNR | C34: United States | D34: Insurance - Reinsurance | E34: Sep'25 | F34: -7.7 | G34: -645.83 | H34: 337.76 | I34: -406.75 | J34: -234.56 | K34: -1173 | L34: 700.34 | M34: 895.83 | N34: 420.4 | O34: 478.06 | P34: 1507 | Q34: 712.93 | R34: 757.5 | S34: 1742 | T34: -57.4 | U34: -34.97 | V34: 1366 | W34: 1510 | X34: -0.33148071 | Y34: -0.23705004 | Z34: 0.25279067 | AA34: -0.076932515
B35: SSII | C35: United States | D35: Medical Devices | E35: Sep'25 | F35: -12.5 | I35: -0.94 | J35: -0.71 | K35: -0.43 | L35: -4.53 | M35: -0.91 | N35: -5.36 | O35: -1.85 | P35: -12.16 | Q35: -9.83 | R35: -4.1 | S35: -3.2 | T35: -1.84 | U35: -5.92 | V35: 0.1 | W35: -1.84 | X35: -0.35233868 | Y35: -0.20611492 | Z35: -0.27888446 | AA35: -0.1252302
B36: SNT | C36: United States | D36: Security & Protection Services | E36: Sep'25 | F36: -12.6 | G36: 0.78 | H36: -1.24 | I36: -0.67 | J36: 0.11 | K36: 1.13 | L36: 0.92 | M36: -1.73 | N36: 0.08 | O36: 0.12 | P36: 0.26 | Q36: -0.07 | R36: 0.67 | S36: 1.82 | T36: 1.47 | U36: 1.05 | V36: 0.97 | W36: 1.15 | X36: 0.45149254 | Y36: 0.28791774 | Z36: 0.05988024 | AA36: -0.12617702
B37: APAM | C37: United States | D37: Asset Management | E37: Dec'25 | F37: 5.6 | G37: 137.82 | H37: 106.99 | I37: 88.41 | J37: 78.73 | K37: 71.39 | L37: 68.31 | M37: 76.7 | N37: 82.16 | O37: 76.43 | P37: 77.64 | Q37: 86.65 | R37: 93.18 | S37: 110.14 | T37: 86.54 | U37: 79.77 | V37: 101.82 | W37: 131.5 | X37: 0.02421044 | Y37: -0.018273087 | Z37: 0.023374726 | AA37: 0.056467603
B38: BHE | C38: United States | D38: Electronic Components | E38: Dec'25 | F38: 4.9 | G38: 22.73 | H38: 19.7 | I38: 21.32 | J38: 26.62 | K38: 31 | L38: 24.17 | M38: 27.77 | N38: 31.98 | O38: 34.15 | P38: 28.87 | Q38: 28.72 | R38: 28.9 | S38: 29.25 | T38: 23.18 | U38: 23 | V38: 25.22 | W38: 34.2 | X38: -0.049161915 | Y38: -0.051976374 | Z38: -0.035272692 | AA38: 0.049180328
B39: PFE | C39: United States | D39: Drug Manufacturers - General | E39: Dec'25 | F39: 4.9 | G39: 6745 | H39: 10349 | I39: 12286 | J39: 10148 | K39: 6216 | L39: 6865 | M39: 2788 | N39: -2386 | O39: 5234 | P39: 4706 | Q39: 2973 | R39: 5838 | S39: 2825 | T39: 4823 | U39: 4203 | V39: 5875 | W39: 3688 | X39: 0.0071594664 | Y39: 0.07473115 | Z39: 0.0020916954 | AA39: 0.048685547
B40: BR | C40: United States | D40: Information Technology Services | E40: Mar'26 | F40: 4.6 | G40: 103.3 | H40: 68.9 | I40: 246 | J40: 341.7 | K40: 87.6 | L40: 107.9 | M40: 286.8 | N40: 454.2 | O40: 148.5 | P40: 124.4 | Q40: 303 | R40: 441.4 | S40: 134.5 | T40: 210.6 | U40: 344.9 | V40: 498.7 | W40: 188.7 | X40: 0.085916476 | Y40: 0.038458008 | Z40: 0.050645218 | AA40: 0.045596029
B41: HUBB | C41: United States | D41: Electrical Equipment & Parts | E41: Dec'25 | F41: 4.4 | G41: 135.7 | H41: 143.7 | I41: 187.8 | J41: 208.6 | K41: 171.5 | L41: 244.8 | M41: 289.6 | N41: 277.4 | O41: 227.6 | P41: 223 | Q41: 309.3 | R41: 316.9 | S41: 259.9 | T41: 227.5 | U41: 335.2 | V41: 339.4 | W41: 311.3 | X41: 0.0040573438 | Y41: 0.023257902 | Z41: 0.019745502 | AA41: 0.044234079
B42: MTCH | C42: United States | D42: Internet Content & Information | E42: Dec'25 | F42: 4.3 | G42: 231.92 | H42: 207.82 | I42: 207.32 | J42: 210.64 | K42: 0 | L42: 198.29 | M42: 214.8 | N42: 243.56 | O42: 260.25 | P42: 184.74 | Q42: 204.53 | R42: 241.26 | S42: 253.99 | T42: 172.59 | U42: 208.22 | V42: 281.83 | W42: 293.33 | X42: -0.013736264 | Y42: 0.0042298566 | Z42: 0.046309613 | AA42: 0.04291808
B43: SR | C43: United States | D43: Utilities - Regulated Gas | E43: Mar'26 | F43: 3.9 | G43: 98.8 | H43: 248.9 | I43: 41.7 | J43: 33.2 | K43: 152.4 | L43: 262.5 | M43: 14.2 | N43: -2.2 | O43: 141 | P43: 300.5 | Q43: 32.7 | R43: 22.9 | S43: 152.7 | T43: 310.5 | U43: 73.2 | V43: 3.1 | W43: 173.5 | X43: 0.019654088 | Y43: 0.078064765 | Z43: -0.035401395 | AA43: 0.038554217
B44: MRK | C44: United States | D44: Drug Manufacturers - General | E44: Dec'25 | F44: 3.6 | G44: 3600 | H44: 5817 | I44: 5210 | J44: 5134 | K44: 4329 | L44: 5143 | M44: 5882 | N44: 6083 | O44: -654 | P44: 6699 | Q44: 6384 | R44: 4364 | S44: 5341 | T44: 6221 | U44: 5923 | V44: 7049 | W44: 6236 | X44: -0.020975952 | Y44: -0.02066338 | Z44: 0.12288892 | AA44: 0.036479987
B45: POWL | C45: United States | D45: Electrical Equipment & Parts | E45: Mar'26 | F45: 3.3 | G45: -4.29 | H45: 0.3 | I45: 0.85 | J45: 10.36 | K45: 1.09 | L45: 10.07 | M45: 21.55 | N45: 29.8 | O45: 25.88 | P45: 39.49 | Q45: 57.29 | R45: 56.12 | S45: 35.57 | T45: 58.92 | U45: 60.12 | V45: 63.25 | W45: 42.77 | X45: 0.10309333 | Y45: 0.013612314 | Z45: 0.033834765 | AA45: 0.033048747
B46: HLNE | C46: United States | D46: Asset Management | E46: Sep'26 | F46: 3.3 | G46: 41.05 | H46: 46.27 | I46: 62.53 | J46: 69.83 | K46: 58.37 | L46: 49.32 | M46: 54.94 | N46: 55.6 | O46: 51.39 | P46: 83.89 | Q46: 89.61 | R46: 67.19 | S46: 75.72 | T46: 84.03 | U46: 76.98 | V46: 79.72 | W46: 86.01 | X46: 0.00044246389 | Y46: -0.03989891 | Z46: 0.041227955 | AA46: 0.032516985
B47: ETN | C47: United States | D47: Specialty Industrial Machinery | E47: Dec'25 | F47: 3.2 | G47: 685 | H47: 651 | I47: 719 | J47: 792 | K47: 880 | L47: 811 | M47: 955 | N47: 1070 | O47: 1097 | P47: 1016 | Q47: 1201 | R47: 1221 | S47: 1238 | T47: 1207 | U47: 1305 | V47: 1383 | W47: 1402 | X47: 0.040846878 | Y47: 0.021368399 | Z47: 0.032589016 | AA47: 0.031950127
... B66: J | C66: United States | D66: Engineering & Construction | E66: Mar'26 | F66: 0.5 | G66: 256.02 | H66: 266.2 | I66: 245.75 | J66: 252.13 | K66: 264.46 | L66: 299.52 | M66: 299.9 | N66: -184.71 | O66: 182.92 | P66: 149.36 | Q66: 219.4 | R66: 0 | S66: 227.9 | T66: 194.86 | U66: 264.61 | V66: 331.76 | W66: 232.56 | X66: 0.076257835 | Y66: 0.070403015 | Z66: 0.48265126 | AA66: 0.0045725275
B67: VLTO | C67: United States | D67: Pollution & Treatment Controls | E67: Dec'25 | F67: 0.4 | H67: 231 | I67: 311 | J67: 285 | K67: 295 | L67: 292 | M67: 295 | N67: 273 | O67: 299 | P67: 293 | Q67: 299 | R67: 308 | S67: 311 | T67: 322 | U67: 313 | V67: 326 | W67: 316 | X67: 0.023947151 | Y67: 0.011290323 | Z67: 0.014354067 | AA67: 0.0039308176
B68: JJSF | C68: United States | D68: Packaged Foods | E68: Mar'26 | F68: 0.2 | G68: 14.85 | H68: 4.09 | I68: 21.26 | J68: 25.72 | K68: 9.33 | L68: 10.19 | M68: 48.29 | N68: 43.38 | O68: 11.88 | P68: 17.9 | Q68: 50.12 | R68: 44.84 | S68: 5.74 | T68: 5.72 | U68: 51.48 | V68: 33.7 | W68: 5.95 | X68: -0.10269815 | Y68: 0.012779553 | Z68: -0.10335869 | AA68: 0.0021730132
B69: CMG | C69: United States | D69: Restaurants | E69: Dec'25 | F69: 0.1 | G69: 163 | H69: 194.53 | I69: 342.28 | J69: 342.62 | K69: 302.12 | L69: 375.97 | M69: 448.05 | N69: 402.19 | O69: 369.98 | P69: 446.77 | Q69: 591.82 | R69: 488.43 | S69: 426.36 | T69: 497.3 | U69: 564.52 | V69: 484.58 | W69: 428.78 | X69: 0.025867983 | Y69: -0.013623366 | Z69: -0.0019477793 | AA69: 0.0012267078
B70: PNR | C70: United States | D70: Specialty Industrial Machinery | E70: Dec'25 | F70: 0 | G70: 158.6 | H70: 153.2 | I70: 196 | J70: 175.5 | K70: 197.8 | L70: 195.2 | M70: 215.3 | N70: 182.1 | O70: 171.6 | P70: 203.2 | Q70: 265.1 | R70: 229.3 | S70: 204.8 | T70: 227.1 | U70: 286.9 | V70: 245.1 | W70: 205 | X70: 0.026484929 | Y70: 0.023534492 | Z70: 0.016664909 | AA70: 0.0002074904
B71: VOYA | C71: United States | D71: Financial Conglomerates | E71: Dec'25 | F71: -0.1 | G71: 20 | H71: 171 | I71: 198 | J71: 114 | K71: 232 | L71: 191 | M71: 369 | N71: 248 | O71: 252 | P71: 344 | Q71: 374 | R71: 185 | S71: 198 | T71: 240 | U71: 251 | V71: 367 | W71: 197 | X71: -0.094459582 | Y71: -0.12337011 | Z71: 0.20823799 | AA71: -0.0009469697
B72: MZTI | C72: United States | D72: Packaged Foods | E72: Jun'26 | F72: -0.3 | G72: 45.06 | H72: 13.81 | I72: 44.24 | J72: 49.3 | K72: 51.33 | L72: 29.41 | M72: 36.44 | N72: 56.78 | O72: 65.94 | P72: 50.07 | Q72: 43.87 | R72: 55.86 | S72: 77.47 | T72: 51.59 | U72: 44.09 | V72: 60.4 | W72: 76.85 | X72: 0.0066880803 | Y72: 0.00096158049 | Z72: 0.019824462 | AA72: -0.0026546778
B73: WTW | C73: United States | D73: Insurance Brokers | E73: Dec'25 | F73: -0.5 | G73: 0 | H73: 276 | I73: 300 | J73: 277 | K73: 958 | L73: 375 | M73: 270 | N73: 318 | O73: 965 | P73: 445 | Q73: 333 | R73: 380 | S73: 1045 | T73: 357 | U73: 383 | V73: 432 | W73: 1035 | X73: -0.039945529 | Y73: 0.023640662 | Z73: 0.024018476 | AA73: -0.0045105999
B74: HRB | C74: United States | D74: Personal Services | E74: Jun'26 | F74: -0.7 | G74: -277.3 | H74: 885.37 | I74: 311.6 | J74: -209.11 | K74: -283.2 | L74: 864.5 | M74: 376.51 | N74: -206.33 | O74: -267.43 | P74: 928.2 | Q74: 350.83 | R74: -228.33 | S74: -293.29 | T74: 978.31 | U74: 371.28 | V74: -207.03 | W74: -298.88 | X74: 0.066159676 | Y74: 0.02532445 | Z74: 0.02572557 | AA74: -0.0065821235
B75: ATI | C75: United States | D75: Metal Fabrication | E75: Dec'25 | F75: -1 | G75: 58.1 | H75: 88.4 | I75: 96.4 | J75: 104.1 | K75: 266.2 | L75: 110.2 | M75: 121.2 | N75: 122.4 | O75: 62.7 | P75: 114.6 | Q75: 142.1 | R75: 140.8 | S75: 154.6 | T75: 150.9 | U75: 164.3 | V75: 170.1 | W75: 148 | X75: 0.065748959 | Y75: 0.037729436 | Z75: 0.047985588 | AA75: -0.010314112
B76: GWW | C76: United States | D76: Industrial Distribution | E76: Dec'25 | F76: -1.2 | G76: 588 | H76: 534 | I76: 534 | J76: 603 | K76: 546 | L76: 680 | M76: 661 | N76: 667 | O76: 601 | P76: 669 | Q76: 649 | R76: 686 | S76: 668 | T76: 672 | U76: 678 | V76: 707 | W76: 634 | X76: 0.0011227545 | Y76: 0.010841121 | Z76: 0.0077662722 | AA76: -0.012477064
B77: ADM | C77: United States | D77: Farm Products | E77: Dec'25 | F77: -1.4 | G77: 880 | H77: 1074 | I77: 1292 | J77: 1000 | K77: 805 | L77: 1203 | M77: 1047 | N77: 999 | O77: 751 | P77: 708 | Q77: 489 | R77: 460 | S77: 340 | T77: 248 | U77: 459 | V77: 397 | W77: 320 | X77: -0.23034552 | Y77: -0.019518543 | Z77: -0.04180491 | AA77: -0.013850416
B78: FUBO | C78: United States | D78: Broadcasting | E78: Dec'25 | F78: -1.5 | P78: -38.78 | Q78: -43.98 | R78: -40.75 | S78: -40.75 | T78: -39.75 | U78: -40.91 | V78: -38.39 | W78: -38.39 | X78: 0.0059052721 | Y78: -0.018580161 | Z78: -0.014553527 | AA78: -0.014768461
B79: INGR | C79: United States | D79: Packaged Foods | E79: Dec'25 | F79: -1.9 | G79: 113 | H79: 213 | I79: 215 | J79: 186 | K79: 150 | L79: 291 | M79: 249 | N79: 222 | O79: 200 | P79: 216 | Q79: 263 | R79: 277 | S79: 250 | T79: 283 | U79: 274 | V79: 251 | W79: 230 | X79: 0.066600398 | Y79: 0.010251631 | Z79: -0.02398524 | AA79: -0.018903592
B80: SKY | C80: United States | D80: Residential Construction | E80: Sep'26 | F80: -3.8 | G80: 91.41 | H80: 116 | I80: 157.05 | J80: 190.19 | K80: 102.27 | L80: 68.77 | M80: 59.23 | N80: 52.04 | O80: 56.18 | P80: 7.76 | Q80: 63.3 | R80: 66.68 | S80: 72.81 | T80: 42.87 | U80: 81.42 | V80: 74.82 | W80: 62.47 | X80: 0.16675374 | Y80: 0.073760482 | Z80: 0.030859049 | AA80: -0.03802589
B81: BV | C81: United States | D81: Specialty Business Services | E81: Mar'26 | F81: -4 | G81: -3.6 | H81: 17.3 | I81: 48.2 | J81: 46.1 | K81: -1.9 | L81: -2.6 | M81: 51.2 | N81: 78.1 | O81: -6.2 | P81: 18.3 | Q81: 66 | R81: 62.5 | S81: -0.6 | T81: 39.4 | U81: 61.8 | V81: 60.1 | W81: -7.1 | X81: 0.14432285 | Y81: -0.025104603 | Z81: -0.014714899 | AA81: -0.04044804
B82: CBT | C82: United States | D82: Specialty Chemicals | E82: Mar'26 | F82: -4.1 | G82: 119 | H82: 144 | I82: 170 | J82: 125 | K82: 108 | L82: 130 | M82: 151 | N82: 135 | O82: 136 | P82: 157 | Q82: 172 | R82: 163 | S82: 155 | T82: 163 | U82: 167 | V82: 146 | W82: 129 | X82: 0.0092735703 | Y82: -0.0076569678 | Z82: -0.026234568 | AA82: -0.041204437
B83: AAT | C83: United States | D83: REIT - Diversified | E83: Dec'25 | F83: -6.3 | G83: 25.72 | H83: 28.34 | I83: 28.32 | J83: 31 | K83: 27.07 | L83: 29.72 | M83: 31.49 | N83: 31.14 | O83: 29.4 | P83: 30.55 | Q83: 30.79 | R83: 37.81 | S83: 30.05 | T83: 27.5 | U83: 25.98 | V83: 24.77 | W83: 23.22 | X83: -0.023606811 | Y83: -0.038129211 | Z83: -0.10746662 | AA83: -0.063065559
B84: COLM | C84: United States | D84: Apparel Manufacturing | E84: Dec'25 | F84: -8 | G84: 212.57 | H84: 83.67 | I84: 8.77 | J84: 145.26 | K84: 191.8 | L84: 56.43 | M84: 6.23 | N84: 134.55 | O84: 138.07 | P84: 44.68 | Q84: -23.8 | R84: 112.54 | S84: 137.32 | T84: 46.51 | U84: -23.59 | V84: 96.39 | W84: 116.74 | X84: 0.0067592524 | Y84: 0.00077044429 | Z84: -0.05920522 | AA84: -0.080193274
B85: INTA | C85: United States | D85: Software - Application | E85: Jun'26 | F85: -9 | G85: -23.91 | H85: -28.7 | I85: -21.62 | J85: -17.2 | K85: -20.01 | L85: -18.89 | M85: -11.97 | N85: -15.4 | O85: -11.08 | P85: -7.45 | Q85: 0.34 | R85: -8.17 | S85: -10.19 | T85: -5.7 | U85: -3.74 | V85: -13.95 | W85: -7.18 | X85: -0.068708284 | Y85: 0.17200675 | Z85: 0.20791367 | AA85: -0.089636689
B86: RES | C86: United States | D86: Oil & Gas Equipment & Services | E86: Dec'25 | F86: -9.9 | G86: 16.58 | H86: 20.08 | I86: 58.62 | J86: 90.63 | K86: 112.73 | L86: 105.1 | M86: 80.27 | N86: 20.93 | O86: 47.6 | P86: 31.14 | Q86: 32.13 | R86: 17.41 | S86: 8.66 | T86: 10.86 | U86: 19.89 | V86: 23.7 | W86: 2.4 | X86: -0.22699799 | Y86: -0.17723719 | Z86: 0.11070046 | AA86: -0.099191887
B87: BRBR | C87: United States | D87: Packaged Foods | E87: Mar'26 | F87: -10.3 | G87: 52.6 | H87: 43.5 | I87: 68.4 | J87: 62.4 | K87: 75.2 | L87: 58 | M87: 76 | N87: 85.2 | O87: 90.4 | P87: 91 | Q87: 111.6 | R87: 112.1 | S87: 115.3 | T87: 95.1 | U87: 44.8 | V87: 102.2 | W87: 78.5 | X87: 0.0095348837 | Y87: -0.15388159 | Z87: -0.026953444 | AA87: -0.10296586
B88: SWKS | C88: United States | D88: Semiconductors | E88: Dec'25 | F88: -13.4 | G88: 376.6 | H88: 448.3 | I88: 372 | J88: 327.9 | K88: 409.5 | L88: 367.4 | M88: 296.4 | N88: 235.1 | O88: 254.3 | P88: 274.5 | Q88: 188.9 | R88: 132 | S88: 191.9 | T88: 182.7 | U88: 104.4 | V88: 112.1 | W88: 112.6 | X88: -0.11660104 | Y88: -0.12149533 | Z88: -0.032569558 | AA88: -0.13415666
B89: MDLZ | C89: United States | D89: Confectioners | E89: Dec'25 | F89: -14.2 | G89: 1111 | H89: 1344 | I89: 1003 | J89: 1037 | K89: 1219 | L89: 1619 | M89: 1492 | N89: 1521 | O89: 1339 | P89: 2838 | Q89: 930 | R89: 1026 | S89: 1651 | T89: 723 | U89: 1168 | V89: 1056 | W89: 1000 | X89: -0.32816137 | Y89: 0.054965358 | Z89: 0.0065674256 | AA89: -0.1415833
B90: AMGN | C90: United States | D90: Drug Manufacturers - General | E90: Dec'25 | F90: -14.9 | G90: 2355 | H90: 2490 | I90: 2176 | J90: 2654 | K90: 2138 | L90: 2069 | M90: 2661 | N90: 1874 | O90: 3197 | P90: 1752 | Q90: 2707 | R90: 2708 | S90: 4707 | T90: 2341 | U90: 3004 | V90: 3264 | W90: 2720 | X90: 0.049604177 | Y90: 0.023830538 | Z90: 0.043573668 | AA90: -0.14921898
... B95: ATKR | C95: United States | D95: Electrical Equipment & Parts | E95: Mar'26 | F95: -20.1 | G95: 268.88 | H95: 319.25 | I95: 350.2 | J95: 300.71 | K95: 231.38 | L95: 239.69 | M95: 232.5 | N95: 189.35 | O95: 175.18 | P95: 178.54 | Q95: 168.18 | R95: 101.93 | S95: 67.89 | T95: 75.87 | U95: 63.77 | V95: 30.14 | W95: 20.12 | X95: -0.19876486 | Y95: -0.25227729 | Z95: -0.23198475 | AA95: -0.20099297
B96: CRLA | C96: France | D96: N/A | E96: H1 2025 | F96: 4.9 | N96: 136.21 | O96: 145.68 | P96: 136.96 | Q96: 178.95 | R96: 91.59 | S96: 124.91 | T96: 84.68 | U96: 125.4 | V96: 74.17 | W96: 144.82 | X96: -0.098195 | Y96: -0.11153229 | Z96: -0.04083642 | AA96: 0.048660671
B97: PUB | C97: France | D97: N/A | E97: H1 2025 | F97: 4.5 | N97: 848 | O97: 699 | P97: 938 | Q97: 908 | R97: 1153 | S97: 991 | T97: 1215 | U97: 1078 | V97: 1348 | W97: 1199 | X97: 0.069423559 | Y97: 0.039840637 | Z97: 0.043948614 | AA97: 0.044905009
B98: 1080 | C98: Hong Kong | D98: N/A | E98: H1 2025 | F98: -25 | N98: -92.53 | O98: -56.77 | P98: -33 | Q98: -44.04 | R98: -18.33 | S98: -49.03 | T98: -40.76 | U98: -21.5 | V98: -29.36 | W98: -13.92 | X98: 0.053739612 | Y98: -0.14813354 | Z98: 0.085094893 | AA98: -0.24962673
B99: ENPH | C99: United States | D99: Solar | E99: Dec'25 | F99: -20.5 | G99: 62.6 | H99: 61.82 | I99: 94.04 | J99: 136.04 | K99: 161.35 | L99: 168.36 | M99: 170.5 | N99: 117.99 | O99: 4.58 | P99: -27.19 | Q99: 2.97 | R99: 50.47 | S99: 64.2 | T99: 35.08 | U99: 40.33 | V99: 67.45 | W99: 21.8 | X99: 0.68844666 | Y99: 0.2446307 | Z99: 0.089330808 | AA99: -0.20477156
B100: RITM | C100: United States | D100: REIT - Mortgage | E100: Dec'25 | F100: -27.4 | G100: 200.24 | H100: 892.41 | I100: 471.18 | J100: 161.15 | K100: 138.07 | L100: 73.14 | M100: 443.22 | N100: 273.78 | O100: -4.4 | P100: 352.7 | Q100: 290.17 | R100: 45.15 | S100: 511.18 | T100: 56.78 | U100: 306.41 | V100: 236.87 | W100: 206.33 | X100: -0.24676451 | Y100: 0.017978921 | Z100: 0.20850009 | AA100: -0.27433318
B101: TTWO | C101: United States | D101: Electronic Gaming & Multimedia | E101: Sep'26 | F101: -44.5 | G101: 154.7 | H101: 133.8 | I101: -17.5 | J101: -246.1 | K101: -171.2 | L101: -111.9 | M101: -178.9 | N101: -151.7 | O101: -75.4 | P101: -50.6 | Q101: -135.4 | R101: -280.4 | S101: -107.3 | T101: 31.9 | U101: 17.4 | V101: -97.5 | W101: -38.1 | X101: -0.14380338 | Y101: -0.31107492 | Z101: -0.54048463 | AA101: -0.44501608
B102: MATW | C102: United States | D102: Conglomerates | E102: Mar'26 | F102: -58 | G102: 21.53 | H102: 17.61 | I102: 10.72 | J102: 13.96 | K102: 17.97 | L102: 22.97 | M102: 21.44 | N102: 45.9 | O102: 13.22 | P102: 22.15 | Q102: 7.97 | R102: 53.07 | S102: 6.64 | T102: 3.48 | U102: 20.66 | V102: 7.75 | W102: -15.69 | X102: -0.20783703 | Y102: 0.17833052 | Z102: -0.54048897 | AA102: -0.5795484
B103: LITE | C103: United States | D103: Communication Equipment | E103: Jun'26 | F103: -112.8 | G103: 85.4 | H103: 46.7 | I103: 70.1 | J103: 22.8 | K103: 9.4 | L103: -38.3 | M103: -17.6 | N103: -67.4 | O103: -87 | P103: -90.5 | Q103: -96.6 | R103: -72.7 | S103: -50.9 | T103: -65.4 | U103: -0.5 | V103: 15 | W103: 63.9 | X103: -0.080785323 | Y103: -0.33648459 | Z103: -0.46279683 | AA103: -1.1277014
B104: APPS | C104: United States | D104: Software - Application | E104: Sep'26 | F104: -173.6 | G104: 35.27 | H104: 29.92 | I104: 25.68 | J104: 22.37 | K104: 12.15 | L104: -7.22 | M104: -4.23 | N104: -2.02 | O104: -3.55 | P104: -15.77 | Q104: -14.46 | R104: -13.04 | S104: -9.66 | T104: -10.79 | U104: -4.47 | V104: 6.88 | W104: 21.65 | X104: -0.094086529 | Y104: -0.20834202 | Z104: -0.52476291 | AA104: -1.7355876
B105: SONO | C105: United States | D105: Consumer Electronics | E105: Mar'26 | F105: -308.5 | G105: 132.59 | H105: 10.04 | I105: 6.96 | J105: -60.06 | K105: 86.3 | L105: -52.38 | M105: -10.93 | N105: -27.89 | O105: 80.26 | P105: -70.95 | Q105: 13.88 | R105: -59.38 | S105: 48.03 | T105: -37.52 | U105: -0.95 | V105: -26.54 | W105: 100.42 | X105: -0.48859982 | Y105: 0.42383538 | Z105: -0.65917302 | AA105: -3.0853946
B106: BDN | C106: United States | D106: REIT - Office | E106: Dec'25 | F106: -507.7 | G106: 19.16 | H106: 18.79 | I106: 19.68 | J106: 19.29 | K106: 16.95 | L106: 17.19 | M106: 15.9 | N106: 15.81 | O106: -24.56 | P106: 9.11 | Q106: 11.83 | R106: -97.09 | S106: -24.64 | T106: 1.8 | U106: 6.89 | V106: 6.88 | W106: 21.41 | X106: 0.072527036 | Y106: 0.045698427 | Z106: -0.91976292 | AA106: -5.0771775
B107: MRCY | C107: United States | D107: Aerospace & Defense | E107: Jun'26 | F107: -826.5 | G107: 6.08 | H107: 19.03 | I107: 36.54 | J107: -3.19 | K107: -4.54 | L107: 6.34 | M107: -4.87 | N107: -29.69 | O107: -53.7 | P107: -35.61 | Q107: -0.88 | R107: -10.98 | S107: -12.2 | T107: -12.1 | U107: 24.87 | V107: -1.25 | W107: -6.58 | X107: -0.39400034 | Y107: -0.71211283 | Z107: -0.93467819 | AA107: -8.2647059
B108: 4676 | C108: Japan | D108: =VLOOKUP(B108,기업리스트!B:G,2,FALSE) -> Fuji Media Holdings, Inc. | E108: Jun'26 | F108: 725.3 | G108: 6932 | H108: 14758 | I108: 7005 | J108: 7852 | K108: 4306 | L108: 10282 | M108: 8962 | N108: 5600 | O108: 7421 | P108: 10581 | Q108: 9919 | R108: 6555 | S108: 7325 | T108: 13291 | U108: -8877 | V108: -12778 | W108: -211 | X108: 0.078824898 | Y108: -0.50676732 | Z108: -1.0567946 | AA108: 7.253128
B109: 5857 | C109: Japan | D109: =VLOOKUP(B109,기업리스트!B:G,2,FALSE) -> ARE Holdings, Inc. | E109: Jun'26 | F109: 20.6 | G109: 6715 | H109: 5508 | I109: 7706 | J109: 5665 | K109: 6473 | L109: 5987 | M109: 3236 | N109: 3051 | O109: 3931 | P109: 3061 | Q109: 0 | R109: 3146 | S109: 4201 | T109: 5837 | U109: 7279 | V109: 5543 | W109: 8913 | X109: 0.26671791 | Y109: 0.55210862 | Z109: 0.11713825 | AA109: 0.20612423
B110: 6471 | C110: Japan | D110: =VLOOKUP(B110,기업리스트!B:G,2,FALSE) -> NSK Ltd. | E110: Sep'26 | F110: 19.4 | G110: 4784 | H110: 6222 | I110: 3899 | J110: 8194 | K110: 8195 | L110: 12474 | M110: 3410 | N110: 6363 | O110: 7898 | P110: 7002 | Q110: 5642 | R110: 4220 | S110: 3841 | T110: 12789 | U110: 3729 | V110: 11038 | W110: 9945 | X110: 0.27949771 | Y110: -0.072210479 | Z110: 0.27739127 | AA110: 0.19441348
B111: 5482 | C111: Japan | D111: =VLOOKUP(B111,기업리스트!B:G,2,FALSE) -> Aichi Steel Corporation | E111: Jun'26 | F111: 15.5 | G111: 257 | H111: -97 | I111: 629 | J111: -1186 | K111: 1479 | L111: 314 | M111: 3436 | N111: 3068 | O111: 1655 | P111: 4382 | Q111: 3373 | R111: 1487 | S111: 1811 | T111: 4411 | U111: 4999 | V111: 4529 | W111: 4255 | X111: 0.0026237221 | Y111: 0.14672442 | Z111: 0.23937677 | AA111: 0.1551746
B112: 8386 | C112: Japan | D112: =VLOOKUP(B112,기업리스트!B:G,2,FALSE) -> The Hyakujushi Bank, Ltd. | E112: Jun'26 | F112: 15.4 | G112: 4702 | H112: 4792 | I112: 479 | J112: 5110 | K112: 3616 | L112: 2197 | M112: 2285 | N112: 5688 | O112: 1616 | P112: 3488 | Q112: 3489 | R112: 4955 | S112: 3016 | T112: 5576 | U112: 4050 | V112: 6603 | W112: 5971 | X112: 0.13968424 | Y112: 0.032930265 | Z112: 0.093652327 | AA112: 0.15354638
B113: 8368 | C113: Japan | D113: =VLOOKUP(B113,기업리스트!B:G,2,FALSE) -> The Hyakugo Bank, Ltd. | E113: Jun'26 | F113: 14.7 | G113: 5261 | H113: 5427 | I113: 3834 | J113: 5210 | K113: 5240 | L113: 4225 | M113: 5782 | N113: 6980 | O113: 4605 | P113: 4937 | Q113: 3359 | R113: 7262 | S113: 5493 | T113: 7444 | U113: 5244 | V113: 5097 | W113: 8924 | X113: 0.11909173 | Y113: 0.080015281 | Z113: -0.085092167 | AA113: 0.14739239
B114: 8367 | C114: Japan | D114: =VLOOKUP(B114,기업리스트!B:G,2,FALSE) -> The Nanto Bank, Ltd. | E114: Jun'26 | F114: 11.9 | G114: 3887 | H114: 5671 | I114: 3207 | J114: 4012 | K114: 5188 | L114: 3948 | M114: -6833 | N114: 4137 | O114: 4132 | P114: 4163 | Q114: 4192 | R114: 6660 | S114: 3394 | T114: 6461 | U114: 2967 | V114: 5674 | W114: 5591 | X114: 0.12483025 | Y114: -0.059158739 | Z114: -0.05061082 | AA114: 0.11878244
B115: 4062 | C115: Japan | D115: =VLOOKUP(B115,기업리스트!B:G,2,FALSE) -> Ibiden Co.,Ltd. | E115: Sep'26 | F115: 11.1 | G115: 20071 | H115: 16391 | I115: 18090 | J115: 23316 | K115: 19769 | L115: 11189 | M115: 8182 | N115: 15892 | O115: 12874 | P115: 10621 | Q115: 11295 | R115: 17217 | S115: 5656 | T115: 11711 | U115: 16670 | V115: 13968 | W115: 10986 | X115: 0.024336333 | Y115: 0.117156 | Z115: -0.063390174 | AA115: 0.1110301
B116: 6486 | C116: Japan | D116: =VLOOKUP(B116,기업리스트!B:G,2,FALSE) -> Eagle Industry Co.,Ltd. | E116: Jun'26 | F116: 10.3 | G116: 1411 | H116: 1319 | I116: 2320 | J116: 1946 | K116: 1817 | L116: 3750 | M116: 1752 | N116: 1497 | O116: 1588 | P116: 2867 | Q116: 2156 | R116: 2625 | S116: 1640 | T116: 2065 | U116: 2164 | V116: 2999 | W116: 2549 | X116: -0.086347976 | Y116: 0.0009427292 | Z116: 0.044031081 | AA116: 0.10250338
B117: 2331 | C117: Japan | D117: =VLOOKUP(B117,기업리스트!B:G,2,FALSE) -> Alsok Co.,Ltd. | E117: Jun'26 | F117: 9 | G117: 15072 | H117: 9851 | I117: 7131 | J117: 6924 | K117: 7779 | L117: 9213 | M117: 12046 | N117: 8449 | O117: 8875 | P117: 8911 | Q117: 11845 | R117: 7095 | S117: 8163 | T117: 11331 | U117: 13614 | V117: 10438 | W117: 12083 | X117: 0.06719609 | Y117: 0.046026955 | Z117: 0.083152999 | AA117: 0.090019749
B118: 5802 | C118: Japan | D118: =VLOOKUP(B118,기업리스트!B:G,2,FALSE) -> Sumitomo Electric Industries, Ltd. | E118: Sep'26 | F118: 8.6 | G118: 30372 | H118: 45698 | I118: 19001 | J118: 30738 | K118: 45086 | L118: 82618 | M118: 18936 | N118: 48393 | O118: 81003 | P118: 78286 | Q118: 53285 | R118: 66030 | S118: 87524 | T118: 113824 | U118: 60301 | V118: 92720 | W118: 118024 | X118: 0.12464007 | Y118: 0.021879668 | Z118: 0.081451665 | AA118: 0.086068477
B119: 6472 | C119: Japan | D119: =VLOOKUP(B119,기업리스트!B:G,2,FALSE) -> NTN Corporation | E119: Sep'26 | F119: 8.4 | G119: 934 | H119: 4338 | I119: -784 | J119: 4645 | K119: 6031 | L119: 7255 | M119: 1490 | N119: 5275 | O119: 8629 | P119: 12755 | Q119: 4533 | R119: 5417 | S119: 4264 | T119: 8746 | U119: 6978 | V119: 5889 | W119: 6435 | X119: -0.14865216 | Y119: 0.10648955 | Z119: 0.01857902 | AA119: 0.083896897
... B142: 9107 | C142: Japan | D142: =VLOOKUP(B142,기업리스트!B:G,2,FALSE) -> Kawasaki Kisen Kaisha, Ltd. | E142: Jun'26 | F142: -7.9 | G142: 7781 | H142: 13122 | I142: -5640 | J142: 18879 | K142: 34120 | L142: 27595 | M142: -1735 | N142: 19638 | O142: 25019 | P142: 25497 | Q142: 14610 | R142: 30718 | S142: 30423 | T142: 31105 | U142: 10609 | V142: 19843 | W142: 23113 | X142: 0.055388748 | Y142: -0.037442914 | Z142: -0.10573137 | AA142: -0.079473799
B143: NAZARA | C143: India | D143: =VLOOKUP(B143,기업리스트!B:G,2,FALSE) -> Nazara Technologies Limited | E143: Jun'26 | F143: 45.8 | G143: 99 | H143: 168 | I143: 80 | J143: 165 | K143: 110 | L143: 180 | M143: 77.2 | N143: 178.8 | O143: 128 | P143: 225 | Q143: 116.8 | R143: 97.2 | S143: -5.8 | T143: 218.3 | U143: -3.3 | V143: -170.8 | W143: 11.8 | X143: -0.015466297 | Y143: -0.28159437 | Z143: -0.87467363 | AA143: 0.45833333
B144: SOLARINDS | C144: India | D144: =VLOOKUP(B144,기업리스트!B:G,2,FALSE) -> Solar Industries India Limited | E144: Sep'26 | F144: 8.7 | G144: 1508 | H144: 2839 | I144: 2524 | J144: 2686 | K144: 3175 | L144: 4277 | M144: 2890 | N144: 3025 | O144: 3176 | P144: 5135 | Q144: 4094 | R144: 4012 | S144: 4791 | T144: 4720 | U144: 4789 | V144: 4922 | W144: 6454 | X144: -0.023014641 | Y144: 0.039450531 | Z144: 0.04969419 | AA144: 0.086515451
B145: ABCAPITAL | C145: India | D145: =VLOOKUP(B145,기업리스트!B:G,2,FALSE) -> Aditya Birla Capital Limited | E145: Sep'26 | F145: 7.6 | G145: 6591 | H145: 5287 | I145: 5619 | J145: 5933 | K145: 34391 | L145: 7682 | M145: 8479 | N145: 9568 | O145: 9958 | P145: 14470 | Q145: 9635 | R145: 13284 | S145: 9675 | T145: 11665 | U145: 10710 | V145: 11344 | W145: 12994 | X145: -0.059599694 | Y145: 0.024288845 | Z145: -0.042793488 | AA145: 0.076485228
B146: RPOWER | C146: India | D146: =VLOOKUP(B146,기업리스트!B:G,2,FALSE) -> Reliance Power Limited | E146: Sep'26 | F146: 6.2 | G146: 5594 | H146: -550.9 | I146: 5551 | J146: 3126 | K146: 4093 | L146: -4165 | M146: 3594 | N146: 4693 | O146: -6258 | P146: -896.8 | Q146: 4004 | R146: 1324 | S146: 2874 | T146: 6794 | U146: 3584 | V146: 4102 | W146: 3945 | X146: 1.0527843 | Y146: -0.028007469 | Z146: 0.19058727 | AA146: 0.061714878
B147: ADANIPORTS | C147: India | D147: =VLOOKUP(B147,기업리스트!B:G,2,FALSE) -> Adani Ports and Special Economic Zone Limited | E147: Sep'26 | F147: 4.4 | G147: 17375 | H147: 20989 | I147: 22817 | J147: 24060 | K147: 21277 | L147: 24814 | M147: 28041 | N147: 29060 | O147: 32006 | P147: 31175 | Q147: 32326 | R147: 32923 | S147: 36963 | T147: 38227 | U147: 42404 | V147: 42868 | W147: 44017 | X147: 0.05286872 | Y147: 0.071760693 | Z147: 0.066072271 | AA147: 0.043960564
B148: PIDILITIND | C148: India | D148: =VLOOKUP(B148,기업리스트!B:G,2,FALSE) -> Pidilite Industries Limited | E148: Jun'26 | F148: 2.5 | G148: 4893 | H148: 4886 | I148: 3698 | J148: 4682 | K148: 4362 | L148: 4272 | M148: 4190 | N148: 6335 | O148: 6045 | P148: 6630 | Q148: 4974 | R148: 7283 | S148: 6809 | T148: 7089 | U148: 5539 | V148: 8443 | W148: 7508 | X148: 0.017862702 | Y148: 0.021601988 | Z148: 0.043413174 | AA148: 0.025071736
B149: PILANIINVS | C149: India | D149: =VLOOKUP(B149,기업리스트!B:G,2,FALSE) -> Pilani Investment and Industries Corporation Limited | E149: Jun'26 | F149: 0.7 | G149: 968.72 | H149: 506.35 | I149: 493.08 | J149: 580.52 | K149: 1112 | L149: 511 | M149: 522.03 | N149: 527.46 | O149: 1042 | P149: 568.23 | Q149: 621.28 | R149: 599.96 | S149: 1224 | T149: 570.92 | U149: 533.51 | V149: 460.44 | W149: 1243 | X149: 0.00089265863 | Y149: -0.029099915 | Z149: -0.047643927 | AA149: 0.0068127951
B150: BAJFINANCE | C150: India | D150: =VLOOKUP(B150,기업리스트!B:G,2,FALSE) -> Bajaj Finance Limited | E150: Sep'26 | F150: -0.3 | G150: 28680 | H150: 32902 | I150: 35028 | J150: 37523 | K150: 40116 | L150: 42595 | M150: 45484 | N150: 47576 | O150: 48939 | P150: 51146 | Q150: 52628 | R150: 53980 | S150: 57624 | T150: 56481 | U150: 63668 | V150: 66048 | W150: 56941 | X150: 0.024770404 | Y150: 0.050019709 | Z150: 0.052072681 | AA150: -0.0028012353
B151: BECTORFOOD | C151: India | D151: =VLOOKUP(B151,기업리스트!B:G,2,FALSE) -> Mrs. Bectors Food Specialities Limited | E151: Jun'26 | F151: -3.3 | G151: 237.7 | H151: 212.26 | I151: 134.57 | J151: 186.97 | K151: 309.14 | L151: 374.95 | M151: 348.21 | N151: 440.54 | O151: 496.63 | P151: 450.4 | Q151: 421.78 | R151: 466.75 | S151: 511.16 | T151: 420.15 | U151: 357.04 | V151: 369.47 | W151: 455.93 | X151: -0.016350556 | Y151: -0.035574556 | Z151: -0.055427041 | AA151: -0.033314835
B152: CMSINFO | C152: India | D152: =VLOOKUP(B152,기업리스트!B:G,2,FALSE) -> CMS Info Systems Limited | E152: Jun'26 | F152: -5.3 | G152: 716.82 | H152: 826.72 | I152: 885.74 | J152: 942.13 | K152: 1000 | L152: 1031 | M152: 1099 | N152: 1112 | O152: 1093 | P152: 1131 | Q152: 1157 | R152: 1135 | S152: 1140 | T152: 1184 | U152: 1194 | V152: 1134 | W152: 892.3 | X152: 0.011615165 | Y152: 0.0080155979 | Z152: -0.00021491511 | AA152: -0.053245916
B153: HGINFRA | C153: India | D153: =VLOOKUP(B153,기업리스트!B:G,2,FALSE) -> H.G. Infra Engineering Limited | E153: Jun'26 | F153: -9.4 | G153: 1789 | H153: 1370 | I153: 2123 | J153: 2746 | K153: 2497 | L153: 1848 | M153: 1916 | N153: 3000 | O153: 3000 | P153: 2775 | Q153: 2775 | R153: 1836 | S153: 2507 | T153: 2044 | U153: 2044 | V153: 2350 | W153: 1662 | X153: -0.07389063 | Y153: -0.079786073 | Z153: 0.060965485 | AA153: -0.094466182

Sheet 빨간줄
B2: (단위: mil $)
B4: NAZARA | C4: 6 | D4: 7 | E4: 8 | F4: 9 | G4: 10 | H4: 11 | I4: 12 | J4: 13 | K4: 14 | L4: 15 | M4: 16 | N4: 17 | O4: 18 | P4: 19 | Q4: 20 | R4: 21 | S4: 22
C6: 4Q21 | D6: 1Q22 | E6: 2Q22 | F6: 3Q22 | G6: 4Q22 | H6: 1Q23 | I6: 2Q23 | J6: 3Q23 | K6: 4Q23 | L6: 1Q24 | M6: 2Q24 | N6: 3Q24 | O6: 4Q24 | P6: 1Q25 | Q6: 2Q25 | R6: 3Q25 | S6: 4Q25 | T6: 1Q26 | U6: 2Q26 | V6: 3Q26 | W6: 4Q26
B7: Revenue | C7: =IFERROR(VLOOKUP($B$4,Revenue!$B$2:$X$500,C$4,FALSE),"-") -> 1296 | D7: =IFERROR(VLOOKUP($B$4,Revenue!$B$2:$X$500,D$4,FALSE),"-") -> 1858 | E7: =IFERROR(VLOOKUP($B$4,Revenue!$B$2:$X$500,E$4,FALSE),"-") -> 1775 | F7: =IFERROR(VLOOKUP($B$4,Revenue!$B$2:$X$500,F$4,FALSE),"-") -> 2231 | G7: =IFERROR(VLOOKUP($B$4,Revenue!$B$2:$X$500,G$4,FALSE),"-") -> 2638 | H7: =IFERROR(VLOOKUP($B$4,Revenue!$B$2:$X$500,H$4,FALSE),"-") -> 3148 | I7: =IFERROR(VLOOKUP($B$4,Revenue!$B$2:$X$500,I$4,FALSE),"-") -> 2894 | J7: =IFERROR(VLOOKUP($B$4,Revenue!$B$2:$X$500,J$4,FALSE),"-") -> 2544 | ... S7: =IFERROR(VLOOKUP($B$4,Revenue!$B$2:$X$500,S$4,FALSE),"-") -> 5265
B8: OP | C8: =IFERROR(VLOOKUP($B$4,'Operating Income'!$B$2:$X$500,C$4,FALSE),"-") -> 99 | D8: =IFERROR(VLOOKUP($B$4,'Operating Income'!$B$2:$X$500,D$4,FALSE),"-") -> 168 | E8: =IFERROR(VLOOKUP($B$4,'Operating Income'!$B$2:$X$500,E$4,FALSE),"-") -> 80 | F8: =IFERROR(VLOOKUP($B$4,'Operating Income'!$B$2:$X$500,F$4,FALSE),"-") -> 165 | G8: =IFERROR(VLOOKUP($B$4,'Operating Income'!$B$2:$X$500,G$4,FALSE),"-") -> 110 | H8: =IFERROR(VLOOKUP($B$4,'Operating Income'!$B$2:$X$500,H$4,FALSE),"-") -> 180 | I8: =IFERROR(VLOOKUP($B$4,'Operating Income'!$B$2:$X$500,I$4,FALSE),"-") -> 77.2 | J8: =IFERROR(VLOOKUP($B$4,'Operating Income'!$B$2:$X$500,J$4,FALSE),"-") -> 178.8 | ... S8: =IFERROR(VLOOKUP($B$4,'Operating Income'!$B$2:$X$500,S$4,FALSE),"-") -> 11.8
B9: Trailing 4Q OP avg. | C9: =IFERROR(AVERAGE(C8:C8),"-") -> 99 | D9: =IFERROR(AVERAGE(C8:D8),"-") -> 133.5 | E9: =IFERROR(AVERAGE(C8:E8),"-") -> 115.66667 | F9: =IFERROR(AVERAGE(C8:F8),"-") -> 128 | G9: =IFERROR(AVERAGE(D8:G8),"-") -> 130.75 | H9: =IFERROR(AVERAGE(E8:H8),"-") -> 133.75 | I9: =IFERROR(AVERAGE(F8:I8),"-") -> 133.05 | J9: =IFERROR(AVERAGE(G8:J8),"-") -> 136.5 | K9: =IFERROR(AVERAGE(H8:K8),"-") -> 141 | L9: =IFERROR(AVERAGE(I8:L8),"-") -> 152.25 | M9: =IFERROR(AVERAGE(J8:M8),"-") -> 162.15 | ... S9: =IFERROR(AVERAGE(P8:S8),"-") -> 14
B10: Trailing 4Q OP sum. | C10: =IFERROR(SUM(C8:C8),"-") -> 99 | D10: =IFERROR(SUM(C8:D8),"-") -> 267 | E10: =IFERROR(SUM(C8:E8),"-") -> 347 | F10: =IFERROR(SUM(C8:F8),"-") -> 512 | G10: =IFERROR(SUM(D8:G8),"-") -> 523 | H10: =IFERROR(SUM(E8:H8),"-") -> 535 | I10: =IFERROR(SUM(F8:I8),"-") -> 532.2 | J10: =IFERROR(SUM(G8:J8),"-") -> 546 | K10: =IFERROR(SUM(H8:K8),"-") -> 564 | L10: =IFERROR(SUM(I8:L8),"-") -> 609 | M10: =IFERROR(SUM(J8:M8),"-") -> 648.6 | ... S10: =IFERROR(SUM(P8:S8),"-") -> 56
B11: Trailing OP Delta | D11: =IFERROR(D9/C9-1,"-") -> 0.34848485 | E11: =IFERROR(E9/D9-1,"-") -> -0.13358302 | F11: =IFERROR(F9/E9-1,"-") -> 0.10662824 | G11: =IFERROR(G9/F9-1,"-") -> 0.021484375 | H11: =IFERROR(H9/G9-1,"-") -> 0.022944551 | I11: =IFERROR(I9/H9-1,"-") -> -0.0052336449 | J11: =IFERROR(J9/I9-1,"-") -> 0.025930101 | K11: =IFERROR(K9/J9-1,"-") -> 0.032967033 | ... S11: =IFERROR(S9/R9-1,"-") -> 0.45833333
B12: opm | C12: =IFERROR(C8/C7,"-") -> 0.076388889 | D12: =IFERROR(D8/D7,"-") -> 0.090419806 | E12: =IFERROR(E8/E7,"-") -> 0.045070423 | F12: =IFERROR(F8/F7,"-") -> 0.073957866 | G12: =IFERROR(G8/G7,"-") -> 0.041698256 | H12: =IFERROR(H8/H7,"-") -> 0.057179161 | I12: =IFERROR(I8/I7,"-") -> 0.026675881 | J12: =IFERROR(J8/J7,"-") -> 0.070283019 | ... S12: =IFERROR(S8/S7,"-") -> 0.0022412156
B13: op yoy | G13: =IFERROR(G8/C8-1,"-") -> 0.11111111 | H13: =IFERROR(H8/D8-1,"-") -> 0.071428571 | I13: =IFERROR(I8/E8-1,"-") -> -0.035 | J13: =IFERROR(J8/F8-1,"-") -> 0.083636364 | K13: =IFERROR(K8/G8-1,"-") -> 0.16363636 | L13: =IFERROR(L8/H8-1,"-") -> 0.25 | M13: =IFERROR(M8/I8-1,"-") -> 0.51295337 | N13: =IFERROR(N8/J8-1,"-") -> -0.45637584 | ... S13: =IFERROR(S8/O8-1,"-") -> -3.0344828
B14: rv yoy | G14: =IFERROR(G7/C7-1,"-") -> 1.0354938 | H14: =IFERROR(H7/D7-1,"-") -> 0.69429494 | I14: =IFERROR(I7/E7-1,"-") -> 0.63042254 | J14: =IFERROR(J7/F7-1,"-") -> 0.14029583 | K14: =IFERROR(K7/G7-1,"-") -> 0.12661107 | L14: =IFERROR(L7/H7-1,"-") -> 0.017789072 | M14: =IFERROR(M7/I7-1,"-") -> -0.08016586 | N14: =IFERROR(N7/J7-1,"-") -> -0.016902516 | ... S14: =IFERROR(S7/O7-1,"-") -> 0.65098777
