Workbook

Sheet 실적 기업 정보
B2: 실적 기업 정보
B4: Ticker | C4: Company | D4: Date | E4: Time | F4: Quarter Ending | G4: Market Cap (mil$)
B5: MSFT | C5: Microsoft Corporation | D5: 46050 | E5: After Hours | F5: 46381 | G5: 3417853.2
B6: META | C6: Meta Platforms, Inc. | D6: 46050 | E6: After Hours | F6: 46381 | G6: 1563357.2
B7: TSLA | C7: Tesla, Inc. | D7: 46050 | F7: 46381 | G7: 1455045.9
B8: XOM | C8: Exxon Mobil Corporation | D8: 30-Jan-26 | E8: Pre Market | F8: 25-Dec | G8: 590910.6
B9: ASML | C9: ASML Holding N.V. | D9: 46050 | E9: Pre Market | F9: 46381 | G9: 522992.7
B10: AMD | C10: Advanced Micro Devices, Inc. | D10: 03-Feb-26 | E10: After Hours | F10: Dec-25 | G10: 385406
B11: A000660 | C11: SK hynix Inc. | D11: 46050 | F11: 46381 | G11: 354526.93
B12: CVX | C12: Chevron Corporation | D12: 30-Jan-26 | E12: Pre Market | F12: 25-Dec | G12: 350262
B13: PLTR | C13: Palantir Technologies Inc. | D13: 02-Feb-26 | E13: After Hours | F13: Dec-25 | G13: 349387.93
B14: LRCX | C14: Lam Research Corporation | D14: 46050 | E14: After Hours | F14: 46381 | G14: 273739.18
B15: MRK | C15: Merck & Co., Inc. | D15: 03-Feb-26 | F15: Dec-25 | G15: 273693
B16: IBM | C16: International Business Machines Corporation | D16: 46050 | E16: After Hours | F16: 46381 | G16: 273353.96
B17: AXP | C17: American Express Company | D17: 30-Jan-26 | E17: Pre Market | F17: 25-Dec | G17: 241588.62
B18: PEP | C18: PepsiCo, Inc. | D18: 03-Feb-26 | F18: Dec-25 | G18: 212497
B19: DIS | C19: The Walt Disney Company | D19: 02-Feb-26 | F19: Dec-25 | G19: 201380.58
B20: VZ | C20: Verizon Communications Inc. | D20: 30-Jan-26 | E20: Pre Market | F20: 25-Dec | G20: 187740.84
B21: APH | C21: Amphenol Corporation | D21: 46050 | E21: Pre Market | F21: 46381 | G21: 184820.14
B22: AMGN | C22: Amgen Inc. | D22: 03-Feb-26 | E22: After Hours | F22: Dec-25 | G22: 184096
B23: GEV | C23: GE Vernova Inc. | D23: 46050 | E23: Pre Market | F23: 46381 | G23: 178469.17
B24: T | C24: AT&T Inc. | D24: 46050 | E24: Pre Market | F24: 46381 | G24: 167240.11
B25: DHR | C25: Danaher Corporation | D25: 46050 | E25: Pre Market | F25: 46381 | G25: 165999.21
B26: PFE | C26: Pfizer Inc. | D26: 03-Feb-26 | F26: Dec-25 | G26: 150330
B27: NOW | C27: ServiceNow, Inc. | D27: 46050 | E27: After Hours | F27: 46381 | G27: 138089.32
B28: ETN | C28: Eaton Corporation plc | D28: 03-Feb-26 | F28: Dec-25 | G28: 136492
B29: 8316 | C29: Sumitomo Mitsui Financial Group, Inc. | D29: 30-Jan-26 | F29: 25-Dec | G29: 136109.76
B30: ISP | C30: Intesa Sanpaolo S.p.A. | D30: 02-Feb-26 | F30: Dec-25 | G30: 123582.78
B31: CB | C31: Chubb Limited | D31: 03-Feb-26 | F31: Dec-25 | G31: 121828
B32: PGR | C32: The Progressive Corporation | D32: 46050 | F32: 46351 | G32: 120815.42
B33: SBUX | C33: Starbucks Corporation | D33: 46050 | E33: Pre Market | F33: 46381 | G33: 111003.7
B34: 6857 | C34: Advantest Corporation | D34: 46050 | F34: 46381 | G34: 109823.18
B35: 8411 | C35: Mizuho Financial Group, Inc. | D35: 02-Feb-26 | F35: Dec-25 | G35: 108869.48
B36: ADP | C36: Automatic Data Processing, Inc. | D36: 46050 | E36: Pre Market | F36: 46381 | G36: 104295.2
B37: GD | C37: General Dynamics Corporation | D37: 46050 | E37: Pre Market | F37: 46381 | G37: 97979.74
B38: CABK | C38: CaixaBank, S.A. | D38: 30-Jan-26 | F38: 25-Dec | G38: 93154.76
B39: WM | C39: Waste Management, Inc. | D39: 46050 | E39: After Hours | F39: 46381 | G39: 92349.21
B40: ITUB4 | C40: Itaú Unibanco Holding S.A. | D40: 02-Feb-26 | F40: Dec-25 | G40: 91584.13
B41: EMR | C41: Emerson Electric Co. | D41: 03-Feb-26 | F41: Dec-25 | G41: 82635.92
B42: ELV | C42: Elevance Health, Inc. | D42: 46050 | E42: Pre Market | F42: 46381 | G42: 82463.92
B43: TDG | C43: TransDigm Group Incorporated | D43: 03-Feb-26 | F43: Dec-25 | G43: 80587.97
B44: GLW | C44: Corning Incorporated | D44: 46050 | E44: Pre Market | F44: 46381 | G44: 79991.72
B45: REGN | C45: Regeneron Pharmaceuticals, Inc. | D45: 30-Jan-26 | E45: Pre Market | F45: 25-Dec | G45: 76072.37
B46: 7974 | C46: Nintendo Co., Ltd. | D46: 03-Feb-26 | F46: Dec-25 | G46: 76065.45
B47: ITW | C47: Illinois Tool Works Inc. | D47: 03-Feb-26 | E47: Pre Market | F47: Dec-25 | G47: 75791.53
B48: MDLZ | C48: Mondelez International, Inc. | D48: 03-Feb-26 | E48: After Hours | F48: Dec-25 | G48: 75447.26
B49: AON | C49: Aon plc | D49: 30-Jan-26 | E49: Pre Market | F49: 25-Dec | G49: 74997.78
B50: CL | C50: Colgate-Palmolive Company | D50: 30-Jan-26 | E50: Pre Market | F50: 25-Dec | G50: 72779.6
B51: EPD | C51: Enterprise Products Partners L.P. | D51: 03-Feb-26 | E51: Pre Market | F51: Dec-25 | G51: 71800.63
B52: VOLV B | C52: AB Volvo (publ) | D52: 46050 | F52: 46381 | G52: 71617.48
B53: NDA FI | C53: Nordea Bank Abp | D53: 46050 | F53: 46381 | G53: 67136.19
B54: CP | C54: Canadian Pacific Kansas City Limited | D54: 46050 | E54: After Hours | F54: 46381 | G54: 65616.28
B55: 6503 | C55: Mitsubishi Electric Corporation | D55: 03-Feb-26 | F55: Dec-25 | G55: 64221.8
B56: SU | C56: Suncor Energy Inc. | D56: 03-Feb-26 | F56: Dec-25 | G56: 63761.61
B57: BAJFINANCE | C57: Bajaj Finance Limited | D57: 03-Feb-26 | F57: Dec-25 | G57: 62857.21
B58: SPG | C58: Simon Property Group, Inc. | D58: 02-Feb-26 | E58: After Hours | F58: Dec-25 | G58: 62220.11
B59: APD | C59: Air Products and Chemicals, Inc. | D59: 30-Jan-26 | E59: Pre Market | F59: 25-Dec | G59: 60673.76
B60: CNR | C60: Canadian National Railway Company | D60: 30-Jan-26 | E60: Pre Market | F60: 25-Dec | G60: 59000
B61: URI | C61: United Rentals, Inc. | D61: 46050 | E61: After Hours | F61: 46381 | G61: 58478.01
B62: NXPI | C62: NXP Semiconductors N.V. | D62: 02-Feb-26 | E62: After Hours | F62: Dec-25 | G62: 56913.66
B63: MPLX | C63: MPLX LP | D63: 03-Feb-26 | E63: Pre Market | F63: Dec-25 | G63: 56853.94
B64: 500510 | C64: Larsen & Toubro Limited | D64: 46050 | F64: 46381 | G64: 56215.87
B65: IDXX | C65: IDEXX Laboratories, Inc. | D65: 02-Feb-26 | E65: Pre Market | F65: Dec-25 | G65: 53537.12
B66: MARUTI | C66: Maruti Suzuki India Limited | D66: 46050 | F66: 46381 | G66: 53078.97
B67: MPC | C67: Marathon Petroleum Corporation | D67: 03-Feb-26 | E67: Pre Market | F67: Dec-25 | G67: 52963.15
B68: AME | C68: AMETEK, Inc. | D68: 03-Feb-26 | F68: Dec-25 | G68: 51561.06
B69: CMG | C69: Chipotle Mexican Grill, Inc. | D69: 03-Feb-26 | E69: After Hours | F69: Dec-25 | G69: 51396.95
B70: GWW | C70: W.W. Grainger, Inc. | D70: 03-Feb-26 | E70: Pre Market | F70: Dec-25 | G70: 51350.43
B71: EA | C71: Electronic Arts Inc. | D71: 03-Feb-26 | E71: After Hours | F71: Dec-25 | G71: 50858.58
B72: LONN | C72: Lonza Group AG | D72: 46050 | F72: 46381 | G72: 49897.27
B73: PYPL | C73: PayPal Holdings, Inc. | D73: 03-Feb-26 | E73: Pre Market | F73: Dec-25 | G73: 49299.5
B74: CTVA | C74: Corteva, Inc. | D74: 03-Feb-26 | E74: After Hours | F74: Dec-25 | G74: 49193.29
B75: IMO | C75: Imperial Oil Limited | D75: 30-Jan-26 | E75: Pre Market | F75: 25-Dec | G75: 48855.78
B76: TTWO | C76: Take-Two Interactive Software, Inc. | D76: 03-Feb-26 | E76: After Hours | F76: Dec-25 | G76: 44372.79
B77: MSCI | C77: MSCI Inc. | D77: 46050 | E77: Pre Market | F77: 46381 | G77: 44314.29
B78: SUNPHARMA | C78: Sun Pharmaceutical Industries Limited | D78: 31-Jan-26 | F78: 25-Dec | G78: 44129.9
B79: 8015 | C79: Toyota Tsusho Corporation | D79: 03-Feb-26 | F79: Dec-25 | G79: 40700.3
B80: LVS | C80: Las Vegas Sands Corp. | D80: 46050 | E80: After Hours | F80: 46381 | G80: 39856.88
B81: 6981 | C81: Murata Manufacturing Co., Ltd. | D81: 02-Feb-26 | F81: Dec-25 | G81: 39312.39
B82: PRU | C82: Prudential Financial, Inc. | D82: 03-Feb-26 | E82: After Hours | F82: Dec-25 | G82: 39080.33
B83: FICO | C83: Fair Isaac Corporation | D83: 46050 | E83: After Hours | F83: 46381 | G83: 37244.98
B84: NTPC | C84: NTPC Limited | D84: 30-Jan-26 | F84: 25-Dec | G84: 37012.58
B85: TEVA | C85: Teva Pharmaceutical Industries Limited | D85: 46050 | E85: Pre Market | F85: 46381 | G85: 36437.69
B86: CLS | C86: Celestica Inc. | D86: 46050 | F86: 46381 | G86: 36111
B87: ADANIPORTS | C87: Adani Ports and Special Economic Zone Limited | D87: 03-Feb-26 | F87: Dec-25 | G87: 36104.02
B88: TER | C88: Teradyne, Inc. | D88: 02-Feb-26 | E88: After Hours | F88: Dec-25 | G88: 35729.4
B89: OTIS | C89: Otis Worldwide Corporation | D89: 46050 | E89: Pre Market | F89: 46381 | G89: 35136.78
B90: RJF | C90: Raymond James Financial, Inc. | D90: 46050 | E90: After Hours | F90: 46381 | G90: 33876.71
B91: 5802 | C91: Sumitomo Electric Industries, Ltd. | D91: 03-Feb-26 | F91: Dec-25 | G91: 33687.35
B92: 500049 | C92: Bharat Electronics Limited | D92: 46050 | F92: 46381 | G92: 33041.42
B93: SOFI | C93: SoFi Technologies, Inc. | D93: 30-Jan-26 | F93: 25-Dec | G93: 33019.38
B94: 2412 | C94: Chunghwa Telecom Co., Ltd. | D94: 03-Feb-26 | E94: Pre Market | F94: Dec-25 | G94: 32675.86
B95: ADVANC | C95: Advanced Info Service Public Company Limited | D95: 03-Feb-26 | F95: Dec-25 | G95: 32414.91
B96: 6301 | C96: Komatsu Ltd. | D96: 30-Jan-26 | F96: 25-Dec | G96: 32397.54
B97: WTW | C97: Willis Towers Watson Public Limited Company | D97: 03-Feb-26 | E97: Pre Market | F97: Dec-25 | G97: 31540.55
B98: ADM | C98: Archer-Daniels-Midland Company | D98: 03-Feb-26 | E98: Pre Market | F98: Dec-25 | G98: 31323.54
B99: HEXA B | C99: Hexagon AB (publ) | D99: 30-Jan-26 | F99: 25-Dec | G99: 30885.71
B100: 512599 | C100: Adani Enterprises Limited | D100: 03-Feb-26 | F100: Dec-25 | G100: 30725.1
B101: BAJAJ-AUTO | C101: Bajaj Auto Limited | D101: 30-Jan-26 | F101: 25-Dec | G101: 29228.78
B102: 9020 | C102: East Japan Railway Company | D102: 02-Feb-26 | F102: Dec-25 | G102: 28273.48
...

Sheet Revenue
B1: 1 | C1: 2 | D1: 3 | E1: 4 | F1: 5 | G1: 6 | H1: 7 | I1: 8 | J1: 9 | K1: 10 | L1: 11 | M1: 12 | N1: 13 | O1: 14 | P1: 15 | Q1: 16 | R1: 17 | S1: 18 | T1: 19 | U1: 20 | V1: 21 | W1: 22
B2: Ticker | C2: Country | D2: Industry | E2: Latest_Date | F2: Growth_Rate | G2: 4Q21 | H2: 1Q22 | I2: 2Q22 | J2: 3Q22 | K2: 4Q22 | L2: 1Q23 | M2: 2Q23 | N2: 3Q23 | O2: 4Q23 | P2: 1Q24 | Q2: 2Q24 | R2: 3Q24 | S2: 4Q24 | T2: 1Q25 | U2: 2Q25 | V2: 3Q25 | W2: 4Q25 | X2: 1Q25 | Y2: 2Q25 | Z2: 3Q25 | AA2: 4Q25
A3: 260203 | B3: SMCI | C3: United States | D3: Computer Hardware | E3: Jun'26 | F3: 33.3 | G3: 1172 | H3: 1355 | I3: 1635 | J3: 1852 | K3: 1803 | L3: 1283 | M3: 2185 | N3: 2120 | O3: 3665 | P3: 3850 | Q3: 5355 | R3: 5937 | S3: 5678 | T3: 4600 | U3: 5757 | V3: 5018 | W3: 12682 | X3: 0.036023055 | Y3: 0.018636996 | Z3: -0.04182596 | AA3: 0.33268418
A4: 260203 | B4: LITE | C4: United States | D4: Communication Equipment | E4: Jun'26 | F4: 14.3 | G4: 446.7 | H4: 395.4 | I4: 422.1 | J4: 506.8 | K4: 506 | L4: 383.4 | M4: 370.8 | N4: 317.6 | O4: 366.8 | P4: 366.5 | Q4: 308.3 | R4: 336.9 | S4: 402.2 | T4: 425.2 | U4: 480.7 | V4: 533.8 | W4: 665.5 | X4: 0.041516373 | Y4: 0.11707185 | Z4: 0.11969605 | AA4: 0.14295021
A5: 260203 | B5: AMCR | C5: United States | D5: Packaging & Containers | E5: Jun'26 | F5: 12.7 | G5: 3507 | H5: 3708 | I5: 3909 | J5: 3712 | K5: 3642 | L5: 3667 | M5: 3673 | N5: 3443 | O5: 3251 | P5: 3411 | Q5: 3535 | R5: 3353 | S5: 3241 | T5: 3333 | U5: 5082 | V5: 5745 | W5: 5449 | X5: -0.005760709 | Y5: 0.11491606 | Z5: 0.15937104 | AA5: 0.12688926
A6: 260203 | B6: BDN | C6: United States | D6: REIT - Office | E6: Dec'25 | F6: 11 | G6: 117.65 | H6: 120.49 | I6: 121.62 | J6: 119.48 | K6: 120.12 | L6: 123.1 | M6: 118.35 | N6: 119.24 | O6: 77.14 | P6: 112.67 | Q6: 111.27 | R6: 6.17 | S6: 77.38 | T6: 111.21 | U6: 105.34 | V6: 103.14 | W6: 120.95 | X6: -0.0047481219 | Y6: -0.019377185 | Z6: 0.32312562 | AA6: 0.10972876
A7: 260203 | B7: SIMO | C7: United States | D7: Semiconductors | E7: Dec'25 | F7: 10.9 | G7: 264.36 | H7: 241.98 | I7: 252.37 | J7: 250.81 | K7: 200.76 | L7: 124.07 | M7: 140.36 | N7: 172.33 | O7: 202.38 | P7: 189.31 | Q7: 210.67 | R7: 212.41 | S7: 191.16 | T7: 166.49 | U7: 198.68 | V7: 242 | W7: 278.46 | X7: -0.02839898 | Y7: -0.015357422 | Z7: 0.038491558 | AA7: 0.10935327
A8: 260203 | B8: AMD | C8: United States | D8: Semiconductors | E8: Dec'25 | F8: 8.2 | G8: 4826 | H8: 5887 | I8: 6550 | J8: 5565 | K8: 5599 | L8: 5353 | M8: 5359 | N8: 5800 | O8: 6168 | P8: 5473 | Q8: 5835 | R8: 6819 | S8: 7658 | T8: 7438 | U8: 7685 | V8: 9246 | W8: 10270 | X8: 0.076207097 | Y8: 0.066666667 | Z8: 0.081993243 | AA8: =SUM(T8:W8)/SUM(S8:V8)-1 -> 0.081556187
A9: 260203 | B9: RES | C9: United States | D9: Oil & Gas Equipment & Services | E9: Dec'25 | F9: 5.9 | G9: 268.25 | H9: 284.62 | I9: 375.51 | J9: 459.6 | K9: 482.03 | L9: 476.67 | M9: 415.86 | N9: 330.42 | O9: 394.53 | P9: 377.83 | Q9: 364.15 | R9: 337.65 | S9: 335.36 | T9: 332.88 | U9: 420.81 | V9: 447.1 | W9: 425.78 | X9: -0.031767009 | Y9: 0.041356457 | Z9: 0.076715497 | AA9: 0.058861439
A10: 260203 | B10: TRNS | C10: United States | D10: Specialty Business Services | E10: Sep'26 | F10: 5.7 | G10: 50.9 | H10: 55.88 | I10: 54.66 | J10: 56.44 | K10: 57.4 | L10: 62.07 | M10: 60.6 | N10: 62.8 | O10: 65.17 | P10: 70.91 | Q10: 66.71 | R10: 67.83 | S10: 66.75 | T10: 77.13 | U10: 76.42 | V10: 82.27 | W10: 83.86 | X10: 0.022850845 | Y10: 0.034875368 | Z10: 0.050116267 | AA10: 0.056548898
A11: 260203 | B11: MSGE | C11: United States | D11: Leisure | E11: Jun'26 | F11: 5.5 | G11: -13.35 | H11: 193.99 | I11: 178.34 | J11: 146.45 | K11: 355.88 | L11: 201.23 | M11: 147.94 | N11: 142.21 | O11: 402.67 | P11: 228.31 | Q11: 186.07 | R11: 138.71 | S11: 407.42 | T11: 242.47 | U11: 154.14 | V11: 158.26 | W11: 459.94 | X11: 0.014742168 | Y11: -0.032759806 | Z11: 0.020737425 | AA11: 0.054578142
A12: 260203 | B12: TTWO | C12: United States | D12: Electronic Gaming & Multimedia | E12: Sep'26 | F12: 5.4 | G12: 903.3 | H12: 930 | I12: 1102 | J12: 1394 | K12: 1408 | L12: 1446 | M12: 1285 | N12: 1299 | O12: 1366 | P12: 1399 | Q12: 1338 | R12: 1353 | S12: 1360 | T12: 1583 | U12: 1504 | V12: 1774 | W12: 1699 | X12: 0.033761468 | Y12: 0.029463969 | Z12: 0.072586207 | AA12: 0.054492847
A13: 260203 | B13: ATS | C13: United States | D13: Specialty Industrial Machinery | E13: Jun'26 | F13: 4.5 | G13: 522.13 | H13: 546.8 | I13: 603.16 | J13: 610.59 | K13: 588.95 | L13: 647.05 | M13: 730.79 | N13: 753.65 | O13: 735.72 | P13: 752.05 | Q13: 791.47 | R13: 694.27 | S13: 612.78 | T13: 651.99 | U13: 574.24 | V13: 736.72 | W13: 728.46 | X13: -0.035101752 | Y13: -0.07897808 | Z13: 0.016756932 | AA13: 0.04491154
A14: 260203 | B14: PGC | C14: United States | D14: Banks - Regional | E14: Dec'25 | F14: 4.3 | G14: 52.43 | H14: 51.96 | I14: 59.95 | J14: 61.31 | K14: 62.9 | L14: 60.52 | M14: 55.8 | N14: 50.01 | O14: 49.2 | P14: 52.45 | Q14: 52.69 | R14: 55.4 | S14: 59.86 | T14: 59.89 | U14: 63.16 | V14: 65.9 | W14: 70.53 | X14: 0.033756806 | Y14: 0.045953301 | Z14: 0.044060258 | AA14: 0.042884128
A15: 260203 | B15: HLNE | C15: United States | D15: Asset Management | E15: Sep'26 | F15: 4.1 | G15: 91.7 | H15: 100.9 | I15: 135.51 | J15: 153.38 | K15: 127.07 | L15: 112.79 | M15: 125.04 | N15: 126.88 | O15: 125.26 | P15: 176.67 | Q15: 196.73 | R15: 150 | S15: 168.26 | T15: 197.97 | U15: 175.96 | V15: 190.88 | W15: 198.59 | X15: 0.030795478 | Y15: -0.029132069 | Z15: 0.059058929 | AA15: 0.041373948
A16: 260203 | B16: SR | C16: United States | D16: Utilities - Regulated Gas | E16: Mar'26 | F16: 3.8 | G16: 555.4 | H16: 880.9 | I16: 448 | J16: 314.2 | K16: 814 | L16: 1123 | M16: 418.5 | N16: 310.4 | O16: 756.6 | P16: 1129 | Q16: 414.1 | R16: 293.8 | S16: 669.1 | T16: 1051 | U16: 421.9 | V16: 334.1 | W16: 762.2 | X16: -0.031125299 | Y16: 0.0032125206 | Z16: 0.016544872 | AA16: 0.037599451
A17: 260203 | B17: BALL | C17: United States | D17: Packaging & Containers | E17: Dec'25 | F17: 3.7 | G17: 3674 | H17: 3716 | I17: 4134 | J17: 3951 | K17: 3548 | L17: 2981 | M17: 3067 | N17: 3111 | O17: 2903 | P17: 2874 | Q17: 2959 | R17: 3082 | S17: 2880 | T17: 3097 | U17: 3338 | V17: 3379 | W17: 3347 | X17: 0.018906316 | Y17: 0.031536029 | Z17: 0.023957409 | AA17: 0.036789034
A18: 260203 | B18: INTA | C18: United States | D18: Software - Application | E18: Jun'26 | F18: 3.6 | G18: 64.7 | H18: 69.66 | I18: 75.52 | J18: 79.54 | K18: 84.69 | L18: 92.02 | M18: 94.62 | N18: 101.58 | O18: 103.93 | P18: 110.64 | Q18: 114.38 | R18: 118.81 | S18: 121.21 | T18: 129.07 | U18: 135.04 | V18: 139.03 | W18: 140.21 | X18: 0.039630999 | Y18: 0.042732745 | Z18: 0.040108702 | AA18: 0.036235339
A19: 260203 | B19: ATO | C19: United States | D19: Utilities - Regulated Gas | E19: Mar'26 | F19: 3.6 | G19: 1013 | H19: 1650 | I19: 816.43 | J19: 722.63 | K19: 1484 | L19: 1541 | M19: 662.73 | N19: 587.64 | O19: 1158 | P19: 1647 | Q19: 701.55 | R19: 657.94 | S19: 1176 | T19: 1951 | U19: 838.77 | V19: 737.48 | W19: 1343 | X19: 0.072683975 | Y19: 0.030585157 | Z19: 0.017202636 | AA19: 0.035507362
A20: 260203 | B20: INNV | C20: United States | D20: Medical Care Facilities | E20: Jun'26 | F20: 3.5 | G20: 175.35 | H20: 177.36 | I20: 172.86 | J20: 171.22 | K20: 167.46 | L20: 172.54 | M20: 176.87 | N20: 182.49 | O20: 188.9 | P20: 193.07 | Q20: 199.4 | R20: 205.14 | S20: 209 | T20: 218.14 | U20: 221.42 | V20: 236.11 | W20: 239.71 | X20: 0.031080696 | Y20: 0.026476529 | Z20: 0.036277381 | AA20: 0.034713509
... A23: 260203 | B23: AME | C23: United States | D23: Specialty Industrial Machinery | E23: Dec'25 | F23: 3.3 | G23: 1504 | H23: 1459 | I23: 1515 | J23: 1552 | K23: 1626 | L23: 1597 | M23: 1646 | N23: 1623 | O23: 1731 | P23: 1736 | Q23: 1735 | R23: 1709 | S23: 1762 | T23: 1732 | U23: 1778 | V23: 1893 | W23: 1998 | X23: -0.00057620282 | Y23: 0.0061977515 | Z23: 0.026357255 | AA23: 0.032937893
A24: 260203 | B24: APPS | C24: United States | D24: =VLOOKUP(B24,[1]기업리스트!B:G,2,FALSE) -> Digital Turbine, Inc. | E24: Sep'26 | F24: 3.2 | G24: 216.82 | H24: 184.14 | I24: 188.63 | J24: 174.86 | K24: 162.31 | L24: 140.12 | M24: 146.37 | N24: 143.26 | O24: 142.63 | P24: 112.22 | Q24: 117.99 | R24: 118.73 | S24: 134.64 | T24: 119.15 | U24: 130.93 | V24: 140.38 | W24: 151.4 | X24: 0.014330617 | Y24: 0.026380706 | Z24: 0.043003277 | AA24: 0.03191773
A25: 260203 | B25: TDG | C25: United States | D25: Aerospace & Defense | E25: Mar'26 | F25: 3.2 | G25: 1194 | H25: 1327 | I25: 1398 | J25: 1510 | K25: 1397 | L25: 1592 | M25: 1744 | N25: 1852 | O25: 1789 | P25: 1919 | Q25: 2046 | R25: 2186 | S25: 2006 | T25: 2150 | U25: 2237 | V25: 2437 | W25: 2285 | X25: 0.028319235 | Y25: 0.022770625 | Z25: 0.029257489 | AA25: 0.031596829
A26: 260203 | B26: MPLX | C26: United States | D26: Oil & Gas Midstream | E26: Dec'25 | F26: 3.1 | G26: 2641 | H26: 2511 | I26: 2829 | J26: 3276 | K26: 2521 | L26: 2579 | M26: 2545 | N26: 2753 | O26: 2804 | P26: 2689 | Q26: 2707 | R26: 2823 | S26: 2892 | T26: 2938 | U26: 2833 | V26: 2949 | W26: 3252 | X26: 0.022410224 | Y26: 0.011091549 | Z26: 0.010969876 | AA26: 0.031002411
A27: 260203 | B27: ETN | C27: United States | D27: Specialty Industrial Machinery | E27: Dec'25 | F27: 3.1 | G27: 4798 | H27: 4843 | I27: 5212 | J27: 5313 | K27: 5384 | L27: 5483 | M27: 5866 | N27: 5880 | O27: 5967 | P27: 5943 | Q27: 6350 | R27: 6345 | S27: 6240 | T27: 6377 | U27: 7028 | V27: 6988 | W27: 7055 | X27: 0.017445132 | Y27: 0.026785714 | Z27: 0.024740285 | AA27: 0.030601134
A28: 260203 | B28: J | C28: United States | D28: Engineering & Construction | E28: Mar'26 | F28: 3 | G28: 3381 | H28: 3834 | I28: 3827 | J28: 3881 | K28: 3799 | L28: 4078 | M28: 4187 | N28: -1212 | O28: 2810 | P28: 2847 | Q28: 2883 | R28: 0 | S28: 2933 | T28: 2910 | U28: 3032 | V28: 3155 | W28: 3293 | X28: 0.0072723075 | Y28: 0.017075407 | Z28: 0.35549296 | AA28: 0.029925187
A29: 260203 | B29: PRU | C29: United States | D29: Insurance - Life | E29: Dec'25 | F29: 3 | G29: 16424 | H29: 11855 | I29: 11392 | J29: 20201 | K29: 11135 | L29: 17045 | M29: 13498 | N29: 8352 | O29: 15084 | P29: 23509 | Q29: 14883 | R29: 19490 | S29: 12523 | T29: 13470 | U29: 13726 | V29: 17879 | W29: 14229 | X29: -0.1425893 | Y29: -0.019166418 | Z29: -0.027208701 | AA29: 0.029619084
A30: 260203 | B30: HUBB | C30: United States | D30: Electrical Equipment & Parts | E30: Dec'25 | F30: 2.8 | G30: 1100 | H30: 1156 | I30: 1256 | J30: 1316 | K30: 1220 | L30: 1285 | M30: 1366 | N30: 1376 | O30: 1346 | P30: 1399 | Q30: 1453 | R30: 1443 | S30: 1334 | T30: 1365 | U30: 1484 | V30: 1502 | W30: 1493 | X30: -0.0060401492 | Y30: 0.0055406613 | Z30: 0.010487025 | AA30: 0.027968338
A31: 260203 | B31: VRNS | C31: United States | D31: Software - Infrastructure | E31: Dec'25 | F31: 2.4 | G31: 126.58 | H31: 96.26 | I31: 111.45 | J31: 123.31 | K31: 142.62 | L31: 107.34 | M31: 115.42 | N31: 122.31 | O31: 154.1 | P31: 114.02 | Q31: 130.35 | R31: 148.07 | S31: 158.51 | T31: 136.42 | U31: 152.16 | V31: 161.58 | W31: 173.37 | X31: 0.040657047 | Y31: 0.038039592 | Z31: 0.022699778 | AA31: 0.024413886
A32: 260203 | B32: BR | C32: United States | D32: Information Technology Services | E32: Mar'26 | F32: 2.4 | G32: 1193 | H32: 1260 | I32: 1534 | J32: 1723 | K32: 1283 | L32: 1293 | M32: 1646 | N32: 1839 | O32: 1431 | P32: 1405 | Q32: 1727 | R32: 1944 | S32: 1423 | T32: 1589 | U32: 1812 | V32: 2065 | W32: 1589 | X32: 0.028312048 | Y32: 0.012718839 | Z32: 0.017878251 | AA32: 0.024096386
A33: 260203 | B33: MDLZ | C33: United States | D33: Confectioners | E33: Dec'25 | F33: 2.4 | G33: 7658 | H33: 7764 | I33: 7274 | J33: 7763 | K33: 8695 | L33: 9166 | M33: 8507 | N33: 9029 | O33: 9314 | P33: 9290 | Q33: 8343 | R33: 9204 | S33: 9604 | T33: 9313 | U33: 8984 | V33: 9744 | W33: 10496 | X33: 0.00063115721 | Y33: 0.017578982 | Z33: 0.014553295 | AA33: 0.023695046
A34: 260203 | B34: ZWS | C34: United States | D34: Pollution & Treatment Controls | E34: Dec'25 | F34: 2.2 | G34: 232.3 | H34: 239.6 | I34: 284.2 | J34: 417.7 | K34: 340.3 | L34: 372.1 | M34: 403.2 | N34: 398.4 | O34: 356.8 | P34: 373.8 | Q34: 412 | R34: 410 | S34: 370.7 | T34: 388.8 | U34: 444.5 | V34: 455.4 | W34: 407.2 | X34: 0.0095754868 | Y34: 0.020550111 | Z34: 0.028128872 | AA34: 0.021995902
A35: 260203 | B35: AMGN | C35: United States | D35: Drug Manufacturers - General | E35: Dec'25 | F35: 2.2 | G35: 6846 | H35: 6238 | I35: 6594 | J35: 6652 | K35: 6839 | L35: 6105 | M35: 6986 | N35: 6903 | O35: 8196 | P35: 7447 | Q35: 8388 | R35: 8503 | S35: 9086 | T35: 8149 | U35: 9179 | V35: 9557 | W35: 9866 | X35: 0.021002872 | Y35: 0.023178808 | Z35: 0.030185869 | AA35: 0.021684134
A36: 260203 | B36: SWKS | C36: United States | D36: Semiconductors | E36: Dec'25 | F36: 1.9 | G36: 1311 | H36: 1510 | I36: 1336 | J36: 1233 | K36: 1407 | L36: 1329 | M36: 1153 | N36: 1071 | O36: 1219 | P36: 1202 | Q36: 1046 | R36: 905.5 | S36: 1025 | T36: 1069 | U36: 953.2 | V36: 965 | W36: 1100 | X36: -0.031829604 | Y36: -0.022939068 | Z36: 0.015053002 | AA36: 0.018692986
... A54: 260203 | B54: MLI | C54: United States | D54: Metal Fabrication | E54: Dec'25 | F54: 0.9 | G54: 956.36 | H54: 1010 | I54: 1150 | J54: 944.83 | K54: 877.58 | L54: 971.19 | M54: 896.98 | N54: 819.79 | O54: 732.38 | P54: 849.65 | Q54: 997.75 | R54: 997.83 | S54: 923.54 | T54: 1000 | U54: 1138 | V54: 1078 | W54: 962.39 | X54: 0.039893652 | Y54: 0.035786095 | Z54: 0.01974937 | AA54: 0.0093851008
A55: 260203 | B55: VLTO | C55: United States | D55: Pollution & Treatment Controls | E55: Dec'25 | F55: 0.9 | H55: 1172 | I55: 1231 | J55: 1219 | K55: 1248 | L55: 1225 | M55: 1253 | N55: 1255 | O55: 1288 | P55: 1246 | Q55: 1288 | R55: 1314 | S55: 1345 | T55: 1332 | U55: 1371 | V55: 1404 | W55: 1396 | X55: 0.016560755 | Y55: 0.015722675 | Z55: 0.016784782 | AA55: 0.0093543654
A56: 260203 | B56: POWL | C56: United States | D56: Electrical Equipment & Parts | E56: Mar'26 | F56: 0.9 | G56: 106.57 | H56: 127.85 | I56: 135.48 | J56: 162.68 | K56: 126.86 | L56: 171.44 | M56: 192.37 | N56: 208.64 | O56: 194.02 | P56: 255.11 | Q56: 288.17 | R56: 275.06 | S56: 241.43 | T56: 278.63 | U56: 286.27 | V56: 297.98 | W56: 251.18 | X56: 0.022193495 | Y56: -0.0017539163 | Z56: 0.021194944 | AA56: 0.0088290426
A57: 260203 | B57: CRVL | C57: United States | D57: Insurance Brokers | E57: Sep'26 | F57: 0.8 | G57: 164.51 | H57: 171.36 | I57: 176.31 | J57: 177.43 | K57: 179.39 | L57: 185.44 | M57: 190.25 | N57: 195.52 | O57: 202.3 | P57: 207.23 | Q57: 211.72 | R57: 224.38 | S57: 227.97 | T57: 231.51 | U57: 234.71 | V57: 239.64 | W57: 235.63 | X57: 0.027866407 | Y57: 0.025670515 | Z57: 0.016612779 | AA57: 0.0082027778
A58: 260203 | B58: FUBO | C58: United States | D58: Broadcasting | E58: Dec'25 | F58: 0.8 | P58: 1051 | Q58: 1076 | R58: 1058 | S58: 1058 | T58: 1116 | U58: 1125 | V58: 1091 | W58: 1091 | X58: 0.01531935 | Y58: 0.011374188 | Z58: 0.0075740188 | AA58: 0.0075170843
A59: 260203 | B59: IT | C59: United States | D59: Information Technology Services | E59: Dec'25 | F59: 0.6 | G59: 1306 | H59: 1263 | I59: 1377 | J59: 1332 | K59: 1505 | L59: 1409 | M59: 1503 | N59: 1409 | O59: 1586 | P59: 1473 | Q59: 1595 | R59: 1484 | S59: 1715 | T59: 1534 | U59: 1686 | V59: 1524 | W59: 1753 | X59: 0.0097335248 | Y59: 0.014380531 | Z59: 0.0062315002 | AA59: 0.0058832637
A60: 260203 | B60: BV | C60: United States | D60: Specialty Business Services | E60: Mar'26 | F60: 0.6 | G60: 591.8 | H60: 711.9 | I60: 747.4 | J60: 723.4 | K60: 655.9 | L60: 650.4 | M60: 766 | N60: 743.7 | O60: 626.7 | P60: 672.9 | Q60: 738.8 | R60: 728.7 | S60: 599.2 | T60: 662.5 | U60: 708.3 | V60: 702.8 | W60: 614.7 | X60: -0.0037961746 | Y60: -0.011175436 | Z60: -0.0095972135 | AA60: 0.0057991619
A61: 260203 | B61: HRB | C61: United States | D61: Personal Services | E61: Jun'26 | F61: 0.5 | G61: 158.82 | H61: 2062 | I61: 1050 | J61: 179.99 | K61: 166.41 | L61: 2094 | M61: 1032 | N61: 183.8 | O61: 179.08 | P61: 2185 | Q61: 1063 | R61: 193.81 | S61: 179.07 | T61: 2277 | U61: 1111 | V61: 203.55 | W61: 198.87 | X61: 0.025408188 | Y61: 0.01292797 | Z61: 0.0025898194 | AA61: 0.0052511258
A62: 260203 | B62: MTCH | C62: United States | D62: Internet Content & Information | E62: Dec'25 | F62: 0.5 | G62: 806.07 | H62: 798.63 | I62: 794.51 | J62: 809.55 | K62: 0 | L62: 787.12 | M62: 829.55 | N62: 881.6 | O62: 866.23 | P62: 859.65 | Q62: 864.07 | R62: 895.48 | S62: 860.18 | T62: 831.18 | U62: 863.74 | V62: 914.28 | W62: 878.01 | X62: -0.0081824923 | Y62: -9.5626951e-05 | Z62: 0.0054483594 | AA62: 0.0051392468
A63: 260203 | B63: MZTI | C63: United States | D63: Packaged Foods | E63: Jun'26 | F63: 0.4 | G63: 428.43 | H63: 403.49 | I63: 452.41 | J63: 425.54 | K63: 477.39 | L63: 464.94 | M63: 454.66 | N63: 461.57 | O63: 485.92 | P63: 471.45 | Q63: 452.83 | R63: 466.56 | S63: 509.3 | T63: 457.84 | U63: 475.43 | V63: 493.47 | W63: 517.95 | X63: -0.0071626301 | Y63: 0.011979666 | Z63: 0.014095426 | AA63: 0.0044678829
A64: 260203 | B64: SKY | C64: United States | D64: Residential Construction | E64: Sep'26 | F64: 0.4 | G64: 534.69 | H64: 638.12 | I64: 725.88 | J64: 806.83 | K64: 582.32 | L64: 491.53 | M64: 464.77 | N64: 464.24 | O64: 559.46 | P64: 536.36 | Q64: 627.78 | R64: 616.88 | S64: 644.93 | T64: 593.87 | U64: 701.32 | V64: 684.43 | W64: 656.61 | X64: 0.023706177 | Y64: 0.029611912 | Z64: 0.026417677 | AA64: 0.0044502867
A65: 260203 | B65: BRBR | C65: United States | D65: Packaged Foods | E65: Mar'26 | F65: 0.2 | G65: 306.5 | H65: 315.2 | I65: 370.6 | J65: 379.2 | K65: 362.7 | L65: 385.6 | M65: 445.9 | N65: 472.6 | O65: 430.4 | P65: 494.6 | Q65: 515.4 | R65: 555.8 | S65: 532.9 | T65: 588 | U65: 547.5 | V65: 648.2 | W65: 537.3 | X65: 0.04450374 | Y65: 0.014643493 | Z65: 0.041543027 | AA65: 0.0018993352
A66: 260203 | B66: GPK | C66: United States | D66: Packaging & Containers | E66: Dec'25 | F66: 0.1 | G66: 1988 | H66: 2245 | I66: 2358 | J66: 2451 | K66: 2386 | L66: 2438 | M66: 2392 | N66: 2349 | O66: 2249 | P66: 2259 | Q66: 2237 | R66: 2216 | S66: 2095 | T66: 2120 | U66: 2204 | V66: 2190 | W66: 2103 | X66: -0.0157829 | Y66: -0.0038071066 | Z66: -0.0030110017 | AA66: 0.00092926008
A67: 260203 | B67: ATI | C67: United States | D67: Metal Fabrication | E67: Dec'25 | F67: 0.1 | G67: 765.4 | H67: 834.1 | I67: 959.5 | J67: 1032 | K67: 1010 | L67: 1038 | M67: 1046 | N67: 1026 | O67: 1064 | P67: 1043 | Q67: 1095 | R67: 1051 | S67: 1173 | T67: 1144 | U67: 1140 | V67: 1126 | W67: 1177 | X67: 0.023154516 | Y67: 0.010082904 | Z67: 0.01663709 | AA67: 0.00087279075
A68: 260203 | B68: MPC | C68: United States | D68: Oil & Gas Refining & Marketing | E68: Dec'25 | F68: -0.1 | G68: 35438 | H68: 38260 | I68: 54052 | J68: 46006 | K68: 0 | L68: 34941 | M68: 36612 | N68: 41258 | O68: 36537 | P68: 32987 | Q68: 37990 | R68: 35156 | S68: 33203 | T68: 31620 | U68: 33883 | V68: 34875 | W68: 33049 | X68: -0.009810817 | Y68: -0.029767556 | Z68: -0.0020991768 | AA68: -0.0011528586
A69: 260203 | B69: CLX | C69: United States | D69: Household & Personal Products | E69: Jun'26 | F69: -0.2 | G69: 1691 | H69: 1809 | I69: 1801 | J69: 1740 | K69: 1715 | L69: 1915 | M69: 2019 | N69: 1386 | O69: 1990 | P69: 1814 | Q69: 1903 | R69: 1762 | S69: 1686 | T69: 1668 | U69: 1988 | V69: 1429 | W69: 1673 | X69: -0.020376832 | Y69: 0.012109987 | Z69: -0.046875 | AA69: -0.0019199527
A70: 260203 | B70: ATKR | C70: United States | D70: Electrical Equipment & Parts | E70: Mar'26 | F70: -0.2 | G70: 840.8 | H70: 982.57 | I70: 1062 | J70: 1029 | K70: 833.82 | L70: 895.93 | M70: 919.12 | N70: 869.89 | O70: 798.48 | P70: 792.91 | Q70: 822.36 | R70: 788.3 | S70: 661.6 | T70: 701.73 | U70: 735.05 | V70: 752.01 | W70: 655.55 | X70: -0.029747127 | Y70: -0.029357866 | Z70: -0.012571535 | AA70: -0.0021225166
... A93: 260203 | B93: KREF | C93: United States | D93: REIT - Mortgage | E93: Dec'25 | F93: -74.5 | G93: 47.81 | H93: 48.42 | I93: 38.18 | J93: -29.44 | K93: 34.24 | L93: -9.3 | M93: -5.41 | N93: 41.24 | O93: 1.17 | P93: 13.49 | Q93: 43.11 | R93: 8.82 | S93: 35.2 | T93: 10.35 | U93: -13.98 | V93: 30.44 | W93: -10.97 | X93: -0.03120652 | Y93: -0.5856586 | Z93: 0.53528101 | AA93: -0.74455733
A94: 260203 | B94: 7974 | C94: Japan | D94: =VLOOKUP(B94,[1]기업리스트!B:G,2,FALSE) -> Nintendo Co., Ltd. | E94: Jun'26 | F94: 16.8 | G94: 301625 | H94: 695947 | I94: 375125 | J94: 307460 | K94: 349514 | L94: 638204 | M94: 306499 | N94: 461341 | O94: 334896 | P94: 598559 | Q94: 277069 | R94: 246638 | S94: 276661 | T94: 432919 | U94: 208704 | V94: 572363 | W94: 527202 | X94: -0.11840503 | Y94: -0.055433164 | Z94: 0.279611 | AA94: 0.16807534
A95: 260203 | B95: 8386 | C95: Japan | D95: =VLOOKUP(B95,[1]기업리스트!B:G,2,FALSE) -> The Hyakujushi Bank, Ltd. | E95: Jun'26 | F95: 6 | G95: 17037 | H95: 18567 | I95: 15023 | J95: 21178 | K95: 20437 | L95: 19040 | M95: 14645 | N95: 16940 | O95: 14494 | P95: 17039 | Q95: 17520 | R95: 17247 | S95: 14292 | T95: 19913 | U95: 18479 | V95: 20602 | W95: 18703 | X95: 0.043480892 | Y95: 0.013904193 | Z95: 0.047975862 | AA95: 0.060188849
A96: 260203 | B96: 6471 | C96: Japan | D96: =VLOOKUP(B96,[1]기업리스트!B:G,2,FALSE) -> NSK Ltd. | E96: Sep'26 | F96: 5.8 | G96: 215015 | H96: 232386 | I96: 219387 | J96: 244436 | K96: 236356 | L96: 237918 | M96: 188247 | N96: 198443 | O96: 201368 | P96: 200808 | Q96: 200495 | R96: 197148 | S96: 199278 | T96: 199746 | U96: 195760 | V96: 216490 | W96: 246214 | X96: -0.0013312792 | Y96: -0.0059435122 | Z96: 0.024423814 | AA96: 0.057854683
A97: 260203 | B97: 8368 | C97: Japan | D97: =VLOOKUP(B97,[1]기업리스트!B:G,2,FALSE) -> The Hyakugo Bank, Ltd. | E97: Jun'26 | F97: 5.5 | G97: 20648 | H97: 21899 | I97: 28457 | J97: 22575 | K97: 22660 | L97: 21777 | M97: 24863 | N97: 27538 | O97: 24911 | P97: 24195 | Q97: 26499 | R97: 25578 | S97: 25223 | T97: 27680 | U97: 26419 | V97: 28942 | W97: 31175 | X97: 0.034336667 | Y97: -0.00076204991 | Z97: 0.032068637 | AA97: 0.054976724
A98: 260203 | B98: 3064 | C98: Japan | D98: =VLOOKUP(B98,[1]기업리스트!B:G,2,FALSE) -> MonotaRO Co., Ltd. | E98: Dec'25 | F98: 5 | G98: 51281 | H98: 54610 | I98: 55253 | J98: 56130 | K98: 59977 | L98: 62014 | M98: 62386 | N98: 62823 | O98: 67063 | P98: 69139 | Q98: 70258 | R98: 72112 | S98: 76610 | T98: 79106 | U98: 81126 | V98: 81168 | W98: 92480 | X98: 0.034593345 | Y98: 0.036459277 | Z98: 0.029311807 | AA98: 0.049904091
A99: 260203 | B99: 4062 | C99: Japan | D99: =VLOOKUP(B99,[1]기업리스트!B:G,2,FALSE) -> Ibiden Co.,Ltd. | E99: Sep'26 | F99: 3.8 | G99: 103402 | H99: 101904 | I99: 98318 | J99: 115261 | K99: 103102 | L99: 100868 | M99: 94601 | N99: 93039 | O99: 92527 | P99: 90344 | Q99: 88220 | R99: 93365 | S99: 88752 | T99: 99099 | U99: 97464 | V99: 98021 | W99: 103136 | X99: 0.024273527 | Y99: 0.025021925 | Z99: 0.012295342 | AA99: 0.037523217
A100: 260203 | B100: 8015 | C100: Japan | D100: =VLOOKUP(B100,[1]기업리스트!B:G,2,FALSE) -> Toyota Tsusho Corporation | E100: Jun'26 | F100: 2.9 | G100: 1872539 | H100: 2032046 | I100: 2251287 | J100: 2375630 | K100: 2532117 | L100: 2459654 | M100: 2481158 | N100: 2540752 | O100: 2594483 | P100: 2574946 | Q100: 2478798 | R100: 2541473 | S100: 2524447 | T100: 2581851 | U100: 2661779 | V100: 2593820 | W100: 2820564 | X100: 0.00068233491 | Y100: 0.018069397 | Z100: 0.0050775252 | AA100: 0.028577489
A101: 260203 | B101: 2331 | C101: Japan | D101: =VLOOKUP(B101,[1]기업리스트!B:G,2,FALSE) -> Alsok Co.,Ltd. | E101: Jun'26 | F101: 2.8 | G101: 128278 | H101: 118493 | I101: 125309 | J101: 114008 | K101: 122045 | L101: 121764 | M101: 134409 | N101: 121593 | O101: 124786 | P101: 132611 | Q101: 142410 | R101: 129011 | S101: 134269 | T101: 137221 | U101: 151380 | V101: 141154 | W101: 150183 | X101: 0.0085639819 | Y101: 0.016522045 | Z101: 0.022002932 | AA101: 0.028215111
A102: 260203 | B102: 5802 | C102: Japan | D102: =VLOOKUP(B102,[1]기업리스트!B:G,2,FALSE) -> Sumitomo Electric Industries, Ltd. | E102: Sep'26 | F102: 2.5 | G102: 868697 | H102: 928753 | I102: 877121 | J102: 1013955 | K102: 1020897 | L102: 1093588 | M102: 994123 | N102: 1077980 | O102: 1149823 | P102: 1180888 | Q102: 1115547 | R102: 1132231 | S102: 1193461 | T102: 1238550 | U102: 1148436 | V102: 1225025 | W102: 1313436 | X102: 0.012475209 | Y102: 0.007027881 | Z102: 0.019690291 | AA102: 0.02496633
A103: 260203 | B103: 6806 | C103: Japan | D103: =VLOOKUP(B103,[1]기업리스트!B:G,2,FALSE) -> Hirose Electric Co.,Ltd. | E103: Sep'26 | F103: 2.3 | G103: 42817 | H103: 41667 | I103: 46574 | J103: 48130 | K103: 47461 | L103: 41059 | M103: 40455 | N103: 42455 | O103: 42252 | P103: 40347 | Q103: 44871 | R103: 49648 | S103: 49903 | T103: 44998 | U103: 48972 | V103: 53053 | W103: 54524 | X103: 0.025171971 | Y103: 0.021650301 | Z103: 0.01759499 | AA103: 0.023465667
A104: 260203 | B104: 6724 | C104: Japan | D104: =VLOOKUP(B104,[1]기업리스트!B:G,2,FALSE) -> Seiko Epson Corporation | E104: Sep'26 | F104: 2 | G104: 296145 | H104: 282171 | I104: 297874 | J104: 335253 | K104: 361276 | L104: 335927 | M104: 314840 | N104: 323693 | O104: 353568 | P104: 321897 | Q104: 336614 | R104: 337584 | S104: 349620 | T104: 339125 | U104: 320879 | V104: 346473 | W104: 376473 | X104: 0.012802116 | Y104: -0.01154487 | Z104: 0.0065980903 | AA104: 0.019801681
A105: 260203 | B105: 9021 | C105: Japan | D105: =VLOOKUP(B105,[1]기업리스트!B:G,2,FALSE) -> West Japan Railway Company | E105: Sep'26 | F105: 1.9 | G105: 293156 | H105: 301113 | I105: 297144 | J105: 319561 | K105: 358140 | L105: 420686 | M105: 369270 | N105: 400632 | O105: 424420 | P105: 440701 | Q105: 402780 | R105: 408606 | S105: 434291 | T105: 462267 | U105: 427059 | V105: 444770 | W105: 467641 | X105: 0.012788355 | Y105: 0.014215337 | Z105: 0.02087722 | AA105: 0.018858994
... A128: 260203 | B128: 5857 | C128: Japan | D128: =VLOOKUP(B128,[1]기업리스트!B:G,2,FALSE) -> ARE Holdings, Inc. | E128: Jun'26 | F128: -8.5 | G128: 46436 | H128: 47626 | I128: 47955 | J128: 59749 | K128: 72903 | L128: 73173 | M128: 86622 | N128: 66523 | O128: 85372 | P128: 83236 | Q128: 0 | R128: 92300 | S128: 148057 | T128: 132612 | U128: 133242 | V128: 137120 | W128: 101119 | X128: 0.15258674 | Y128: 0.35724685 | Z128: 0.088540154 | AA128: -0.08518214
A129: 260203 | B129: NAZARA | C129: India | D129: =VLOOKUP(B129,[1]기업리스트!B:G,2,FALSE) -> Nazara Technologies Limited | E129: Jun'26 | F129: 11.1 | G129: 1296 | H129: 1858 | I129: 1775 | J129: 2231 | K129: 2638 | L129: 3148 | M129: 2894 | N129: 2544 | O129: 2972 | P129: 3204 | Q129: 2662 | R129: 2501 | S129: 3189 | T129: 5347 | U129: 5204 | V129: 4988 | W129: 5265 | X129: 0.18544479 | Y129: 0.18556099 | Z129: 0.15313096 | AA129: 0.11085006
A130: 260203 | B130: BAJFINANCE | C130: India | D130: =VLOOKUP(B130,[1]기업리스트!B:G,2,FALSE) -> Bajaj Finance Limited | E130: Sep'26 | F130: 10.4 | G130: 49494 | H130: 53691 | I130: 58829 | J130: 62671 | K130: 65934 | L130: 69240 | M130: 74028 | N130: 77699 | O130: 80506 | P130: 84870 | Q130: 87338 | R130: 90370 | S130: 96294 | T130: 96194 | U130: 104899 | V130: 109007 | W130: 138759 | X130: 0.031554426 | Y130: 0.047437033 | Z130: 0.048063607 | AA130: 0.10449219
A131: 260203 | B131: ABCAPITAL | C131: India | D131: =VLOOKUP(B131,[1]기업리스트!B:G,2,FALSE) -> Aditya Birla Capital Limited | E131: Sep'26 | F131: 6.9 | G131: 48367 | H131: 50157 | I131: 45186 | J131: 55593 | K131: 80767 | L131: 63486 | M131: 50712 | N131: 55548 | O131: 62544 | P131: 83338 | Q131: 60984 | R131: 76361 | S131: 65194 | T131: 92775 | U131: 63665 | V131: 73982 | W131: 85689 | X131: 0.0330107 | Y131: 0.0090784724 | Z131: -0.0079833554 | AA131: 0.069329806
A132: 260203 | B132: SOLARINDS | C132: India | D132: =VLOOKUP(B132,[1]기업리스트!B:G,2,FALSE) -> Solar Industries India Limited | E132: Sep'26 | F132: 6.9 | G132: 10179 | H132: 13169 | I132: 16156 | J132: 15666 | K132: 18118 | L132: 19285 | M132: 16822 | N132: 13475 | O132: 14291 | P132: 16107 | Q132: 16948 | R132: 17158 | S132: 19731 | T132: 21666 | U132: 21545 | V132: 20822 | W132: 25483 | X132: 0.079477868 | Y132: 0.060884998 | Z132: 0.045742821 | AA132: 0.068669118
A133: 260203 | B133: ADANIPORTS | C133: India | D133: =VLOOKUP(B133,[1]기업리스트!B:G,2,FALSE) -> Adani Ports and Special Economic Zone Limited | E133: Sep'26 | F133: 5 | G133: 37971 | H133: 50298 | I133: 46380 | J133: 52108 | K133: 47862 | L133: 57969 | M133: 62476 | N133: 66464 | O133: 69201 | P133: 68965 | Q133: 69563 | R133: 70670 | S133: 79636 | T133: 84884 | U133: 91261 | V133: 91675 | W133: 97046 | X133: 0.055114703 | Y133: 0.071198643 | Z133: 0.0643435 | AA133: 0.050107064
A134: 260203 | B134: BECTORFOOD | C134: India | D134: =VLOOKUP(B134,[1]기업리스트!B:G,2,FALSE) -> Mrs. Bectors Food Specialities Limited | E134: Jun'26 | F134: 2.9 | G134: 2463 | H134: 2632 | I134: 2523 | J134: 3008 | K134: 3474 | L134: 3679 | M134: 3461 | N134: 3742 | O134: 4145 | P134: 4289 | Q134: 4064 | R134: 4394 | S134: 4963 | T134: 4921 | U134: 4461 | V134: 4730 | W134: 5514 | X134: 0.035686053 | Y134: 0.021644314 | Z134: 0.017930519 | AA134: 0.028885976
A135: 260203 | B135: PILANIINVS | C135: India | D135: =VLOOKUP(B135,[1]기업리스트!B:G,2,FALSE) -> Pilani Investment and Industries Corporation Limited | E135: Jun'26 | F135: 2.4 | G135: 979.7 | H135: 516.31 | I135: 482.56 | J135: 597.49 | K135: 1124 | L135: 524.55 | M135: 527.86 | N135: 542.74 | O135: 1062 | P135: 611.97 | Q135: 646.59 | R135: 612.53 | S135: 1224 | T135: 609.36 | U135: 596.62 | V135: 495.8 | W135: 1295 | X135: -0.00084327112 | Y135: -0.016158552 | Z135: -0.038366349 | AA135: 0.024267033
A136: 260203 | B136: PIDILITIND | C136: India | D136: =VLOOKUP(B136,[1]기업리스트!B:G,2,FALSE) -> Pidilite Industries Limited | E136: Jun'26 | F136: 2.4 | G136: 26264 | H136: 28507 | I136: 25071 | J136: 31011 | K136: 30112 | L136: 29976 | M136: 26893 | N136: 32751 | O136: 30760 | P136: 31300 | Q136: 29019 | R136: 33954 | S136: 32349 | T136: 33689 | U136: 31411 | V136: 37531 | W136: 35544 | X136: 0.018867179 | Y136: 0.018541055 | Z136: 0.027221601 | AA136: 0.023670173
A137: 260203 | B137: RPOWER | C137: India | D137: =VLOOKUP(B137,[1]기업리스트!B:G,2,FALSE) -> Reliance Power Limited | E137: Sep'26 | F137: 0.3 | G137: 17959 | H137: 18461 | I137: 20630 | J137: 18638 | K137: 18861 | L137: 17011 | M137: 19218 | N137: 20523 | O137: 19466 | P137: 19719 | Q137: 19922 | R137: 17598 | S137: 18528 | T137: 19780 | U137: 18856 | V137: 19740 | W137: 18728 | X137: 0.00080509985 | Y137: -0.014058132 | Z137: 0.028650919 | AA137: 0.002600645
A138: 260203 | B138: CMSINFO | C138: India | D138: =VLOOKUP(B138,[1]기업리스트!B:G,2,FALSE) -> CMS Info Systems Limited | E138: Jun'26 | F138: -0.6 | G138: 3721 | H138: 4037 | I138: 4441 | J138: 4533 | K138: 4717 | L138: 4883 | M138: 5014 | N138: 5116 | O138: 5437 | P138: 5823 | Q138: 6271 | R138: 5994 | S138: 6245 | T138: 5815 | U138: 6191 | V138: 6274 | W138: 6086 | X138: -0.00032877163 | Y138: -0.0032887975 | Z138: 0.011548773 | AA138: -0.0064831804
A139: 260203 | B139: HGINFRA | C139: India | D139: N/A | E139: Jun'26 | F139: -13.1 | G139: 11059 | H139: 7957 | I139: 11850 | J139: 15354 | K139: 13512 | L139: 9545 | M139: 13645 | N139: 0 | O139: 0 | P139: 0 | Q139: 0 | R139: 9024 | S139: 12648 | T139: 0 | U139: 0 | V139: 14822 | W139: 9045 | X139: 0 | Y139: 0 | Z139: 0.26753415 | AA139: -0.13116127
A140: 260202 | B140: PLTR | C140: United States | D140: Software - Infrastructure | E140: Dec'25 | F140: 14.9 | G140: 432.87 | H140: 446.36 | I140: 473.01 | J140: 477.88 | K140: 508.62 | L140: 525.19 | M140: 533.32 | N140: 558.16 | O140: 608.35 | P140: 634.34 | Q140: 678.13 | R140: 725.52 | S140: 827.52 | T140: 883.86 | U140: 1004 | V140: 1181 | W140: 1407 | X140: 0.087076995 | Y140: 0.10461215 | Z140: 0.13237234 | AA140: 0.14872266
A141: 260202 | B141: TER | C141: United States | D141: Semiconductor Equipment & Materials | E141: Dec'25 | F141: 11.5 | G141: 885.05 | H141: 755.37 | I141: 840.77 | J141: 827.07 | K141: 731.84 | L141: 617.53 | M141: 684.44 | N141: 703.73 | O141: 670.6 | P141: 599.82 | Q141: 729.88 | R141: 737.3 | S141: 752.88 | T141: 685.68 | U141: 651.8 | V141: 769.21 | W141: 1083 | X141: 0.030448104 | Y141: -0.026870952 | Z141: 0.011284949 | AA141: 0.11544393
A142: 260202 | B142: FN | C142: United States | D142: Electronic Components | E142: Jun'26 | F142: 8.3 | G142: 566.63 | H142: 564.4 | I142: 587.87 | J142: 655.43 | K142: 668.66 | L142: 665.28 | M142: 655.87 | N142: 685.48 | O142: 712.69 | P142: 731.54 | Q142: 753.26 | R142: 804.23 | S142: 833.61 | T142: 871.8 | U142: 909.69 | V142: 978.13 | W142: 1133 | X142: 0.044917121 | Y142: 0.047942015 | Z142: 0.050857917 | AA142: 0.083320578
A143: 260202 | B143: WWD | C143: United States | D143: Aerospace & Defense | E143: Mar'26 | F143: 6.3 | G143: 541.59 | H143: 586.84 | I143: 614.33 | J143: 640.03 | K143: 618.62 | L143: 718.21 | M143: 800.66 | N143: 777.07 | O143: 786.73 | P143: 835.34 | Q143: 847.69 | R143: 854.49 | S143: 772.73 | T143: 883.63 | U143: 915.45 | V143: 995.26 | W143: 996.45 | X143: 0.014588022 | Y143: 0.020175433 | Z143: 0.041085136 | AA143: 0.062718141
A144: 260202 | B144: NJR | C144: United States | D144: Utilities - Regulated Gas | E144: Mar'26 | F144: 5.7 | G144: 675.84 | H144: 912.32 | I144: 552.34 | J144: 765.49 | K144: 723.57 | L144: 644.03 | M144: 264.08 | N144: 331.33 | O144: 467.21 | P144: 657.91 | Q144: 275.64 | R144: 395.78 | S144: 488.36 | T144: 913.03 | U144: 298.95 | V144: 336.08 | W144: 604.85 | X144: 0.14035397 | Y144: 0.011245604 | Z144: -0.028481194 | AA144: 0.057203327
A145: 260202 | B145: CSWC | C145: United States | D145: Asset Management | E145: Sep'26 | F145: 4.4 | G145: 22.31 | H145: 21.03 | I145: 22.54 | J145: 26.8 | K145: 32.77 | L145: 37.19 | M145: 40.36 | N145: 42.78 | O145: 48.57 | P145: 46.43 | Q145: 51.35 | R145: 48.71 | S145: 51.97 | T145: 52.41 | U145: 55.95 | V145: 56.95 | W145: 61.45 | X145: 0.030132017 | Y145: 0.022500489 | Z145: 0.039418293 | AA145: 0.043630339
A146: 260202 | B146: RMBS | C146: United States | D146: Semiconductors | E146: Dec'25 | F146: 4.3 | G146: 91.78 | H146: 99.05 | I146: 121.13 | J146: 112.24 | K146: 122.37 | L146: 113.76 | M146: 119.83 | N146: 105.3 | O146: 122.23 | P146: 117.87 | Q146: 132.14 | R146: 145.51 | S146: 161.1 | T146: 166.66 | U146: 172.21 | V146: 178.51 | W146: 190.24 | X146: 0.087654055 | Y146: 0.066186551 | Z146: 0.051124744 | AA146: 0.042948945
A147: 260202 | B147: TWST | C147: United States | D147: Diagnostics & Research | E147: Mar'26 | F147: 4 | G147: 42.02 | H147: 48.13 | I147: 56.11 | J147: 57.31 | K147: 54.24 | L147: 60.18 | M147: 63.74 | N147: 66.95 | O147: 71.5 | P147: 75.3 | Q147: 81.46 | R147: 84.71 | S147: 88.71 | T147: 92.79 | U147: 96.06 | V147: 99.01 | W147: 103.7 | X147: 0.052971107 | Y147: 0.041993845 | Z147: 0.039473321 | AA147: 0.039806676
A148: 260202 | B148: SPG | C148: United States | D148: REIT - Retail | E148: Dec'25 | F148: 3.4 | G148: 1324 | H148: 1296 | I148: 1280 | J148: 1316 | K148: 1400 | L148: 1351 | M148: 1370 | N148: 1411 | O148: 1527 | P148: 1443 | Q148: 1458 | R148: 1481 | S148: 1582 | T148: 1473 | U148: 1498 | V148: 1602 | W148: 1791 | X148: 0.0050301811 | Y148: 0.00667334 | Z148: 0.020053033 | AA148: 0.033956133
A149: 260202 | B149: IDXX | C149: United States | D149: Diagnostics & Research | E149: Dec'25 | F149: 3.3 | G149: 801.09 | H149: 836.55 | I149: 860.55 | J149: 841.66 | K149: 828.57 | L149: 900.2 | M149: 943.63 | N149: 915.53 | O149: 901.6 | P149: 964.1 | Q149: 1004 | R149: 975.54 | S149: 954.29 | T149: 998.43 | U149: 1109 | V149: 1105 | W149: 1091 | X149: 0.0088072387 | Y149: 0.026702202 | Z149: 0.032066302 | AA149: 0.03280998
A150: 260202 | B150: NSSC | C150: United States | D150: Security & Protection Services | E150: Jun'26 | F150: 2.8 | G150: 33.41 | H150: 35.91 | I150: 43.23 | J150: 39.49 | K150: 42.31 | L150: 43.53 | M150: 44.66 | N150: 41.68 | O150: 47.55 | P150: 49.27 | Q150: 50.33 | R150: 44 | S150: 42.93 | T150: 43.96 | U150: 50.72 | V150: 49.17 | W150: 48.17 | X150: -0.028467271 | Y150: 0.0021520803 | Z150: 0.028467595 | AA150: 0.028054396
... A164: 260202 | B164: TWO | C164: United States | D164: REIT - Mortgage | E164: Dec'25 | F164: -39.5 | G164: 166.7 | H164: -33.03 | I164: -88.9 | J164: 346.8 | K164: -146.17 | L164: -100.54 | M164: 239.29 | N164: 349.87 | O164: -233.74 | P164: 259.25 | Q164: 136.57 | R164: -73.11 | S164: 271.04 | T164: 7.89 | U164: 23.61 | V164: 201.36 | W164: 71.94 | X164: -0.42334316 | Y164: -0.32991618 | Z164: 1.1963126 | AA164: -0.39511808
A165: 260202 | B165: 8370 | C165: Japan | D165: The Kiyo Bank, Ltd. | E165: Sep'26 | F165: 8.7 | G165: 18255 | H165: 16336 | I165: 21599 | J165: 18351 | K165: 17959 | L165: 19789 | M165: 17504 | N165: 17837 | O165: 17614 | P165: 22750 | Q165: 21185 | R165: 17490 | S165: 23018 | T165: 23840 | U165: 22188 | V165: 17463 | W165: 30564 | X165: 0.012908116 | Y165: 0.011726468 | Z165: -0.00031200887 | AA165: 0.087227918
A166: 260202 | B166: 8601 | C166: Japan | D166: Daiwa Securities Group Inc. | E166: Sep'26 | F166: 8 | G166: 166602 | H166: 148323 | I166: 146604 | J166: 192551 | K166: 233022 | L166: 293864 | M166: 266255 | N166: 303827 | O166: 335377 | P166: 372008 | Q166: 176188 | R166: 159958 | S166: 160018 | T166: 876860 | U166: 160993 | V166: 194358 | W166: 271228 | X166: 0.5815115 | Y166: -0.011066813 | Z166: 0.02533456 | AA166: 0.0798791
A167: 260202 | B167: 8331 | C167: Japan | D167: The Chiba Bank, Ltd. | E167: Sep'26 | F167: 7 | G167: 52659 | H167: 49973 | I167: 61244 | J167: 63020 | K167: 60603 | L167: 55498 | M167: 60170 | N167: 60590 | O167: 61776 | P167: 55515 | Q167: 67905 | R167: 66474 | S167: 64252 | T167: 65179 | U167: 75955 | V167: 81359 | W167: 84291 | X167: 0.038025387 | Y167: 0.030514385 | Z167: 0.054752446 | AA167: 0.069884392
A168: 260202 | B168: 7337 | C168: Japan | D168: Hirogin Holdings, Inc. | E168: Sep'26 | F168: 6.9 | G168: 35473 | H168: 31052 | I168: 36024 | J168: 28051 | K168: 34042 | L168: 33564 | M168: 36058 | N168: 36180 | O168: 35605 | P168: 27550 | Q168: 38834 | R168: 38922 | S168: 42895 | T168: 37223 | U168: 42154 | V168: 39847 | W168: 54153 | X168: 0.065269465 | Y168: 0.021029429 | Z168: 0.005738427 | AA168: 0.069442817
A169: 260202 | B169: 8386 | C169: Japan | D169: The Hyakujushi Bank, Ltd. | E169: Jun'26 | F169: 6 | G169: 17037 | H169: 18567 | I169: 15023 | J169: 21178 | K169: 20437 | L169: 19040 | M169: 14645 | N169: 16940 | O169: 14494 | P169: 17039 | Q169: 17520 | R169: 17247 | S169: 14292 | T169: 19913 | U169: 18479 | V169: 20602 | W169: 18703 | X169: 0.043480892 | Y169: 0.013904193 | Z169: 0.047975862 | AA169: 0.060188849
A170: 260202 | B170: 3132 | C170: Japan | D170: Macnica Holdings, Inc. | E170: Sep'26 | F170: 4.6 | G170: 194802 | H170: 204678 | I170: 241320 | J170: 251242 | K170: 275442 | L170: 261259 | M170: 278562 | N170: 268399 | O170: 253342 | P170: 228415 | Q170: 256330 | R170: 262630 | S170: 262829 | T170: 252391 | U170: 281613 | V170: 293822 | W170: 312722 | X170: 0.02373382 | Y170: 0.024447388 | Z170: 0.02944133 | AA170: 0.045745905
A171: 260202 | B171: 6762 | C171: Japan | D171: TDK Corporation | E171: Sep'26 | F171: 4.1 | G171: 499670 | H171: 508269 | I171: 510504 | J171: 611489 | K171: 586972 | L171: 471852 | M171: 503399 | N171: 556312 | O171: 559250 | P171: 484915 | Q171: 518809 | R171: 570692 | S171: 581043 | T171: 534262 | U171: 535753 | V171: 647610 | W171: 675203 | X171: 0.022893964 | Y171: 0.0076850299 | Z171: 0.034620457 | AA171: 0.040962853
A172: 260202 | B172: 8346 | C172: Japan | D172: The Toho Bank, Ltd. | E172: Jun'26 | F172: 3.2 | G172: 14750 | H172: 14288 | I172: 14091 | J172: 14536 | K172: 13215 | L172: 13962 | M172: 13006 | N172: 14421 | O172: 13647 | P172: 15023 | Q172: 13888 | R172: 15806 | S172: 15618 | T172: 16217 | U172: 16230 | V172: 18249 | W172: 17757 | X172: 0.019789509 | Y172: 0.038063352 | Z172: 0.038248971 | AA172: 0.032255632
A173: 260202 | B173: 4768 | C173: Japan | D173: Otsuka Corporation | E173: Dec'25 | F173: 2.5 | G173: 192635 | H173: 210069 | I173: 235267 | J173: 207843 | K173: 207843 | L173: 242609 | M173: 278447 | N173: 219002 | O173: 237312 | P173: 266664 | Q173: 303058 | R173: 252540 | S173: 285406 | T173: 315541 | U173: 379591 | V173: 310587 | W173: 317072 | X173: 0.044126038 | Y173: 0.066173819 | Z173: 0.047074881 | AA173: 0.024525898
A174: 260202 | B174: 2222 | C174: Japan | D174: Kotobuki Spirits Co., Ltd. | E174: Sep'26 | F174: 2.4 | G174: 10963 | H174: 9270 | I174: 9515 | J174: 10584 | K174: 15271 | L174: 14785 | M174: 13853 | N174: 15038 | O174: 18145 | P174: 16999 | Q174: 15526 | R174: 17380 | S174: 20901 | T174: 18542 | U174: 16976 | V174: 18811 | W174: 22698 | X174: 0.021791939 | Y174: 0.020041742 | Z174: 0.019390507 | AA174: 0.023886747
A175: 260202 | B175: 9022 | C175: Japan | D175: Central Japan Railway Company | E175: Sep'26 | F175: 1.9 | G175: 299440 | H175: 248750 | I175: 309342 | J175: 324797 | K175: 385012 | L175: 381134 | M175: 395091 | N175: 422454 | O175: 455472 | P175: 437390 | Q175: 435290 | R175: 438575 | S175: 494172 | T175: 463810 | U175: 478283 | V175: 503919 | W175: 531950 | X175: 0.014633657 | Y175: 0.023469755 | Z175: 0.034853107 | AA175: 0.019471349
A176: 260202 | B176: 6971 | C176: Japan | D176: Kyocera Corporation | E176: Sep'26 | F176: 1.9 | G176: 479328 | H176: 483273 | I176: 491954 | J176: 520218 | K176: 514325 | L176: 498835 | M176: 479420 | N176: 505870 | O176: 507382 | P176: 511549 | Q176: 498868 | R176: 499720 | S176: 493467 | T176: 522399 | U176: 478038 | V176: 513347 | W176: 530611 | X176: 0.0054152417 | Y176: -0.010340271 | Z176: 0.0068352909 | AA176: 0.01850491
...

Sheet Operating Income
B1: 1 | C1: 2 | D1: 3 | E1: 4 | F1: 5 | G1: 6 | H1: 7 | I1: 8 | J1: 9 | K1: 10 | L1: 11 | M1: 12 | N1: 13 | O1: 14 | P1: 15 | Q1: 16 | R1: 17 | S1: 18 | T1: 19 | U1: 20 | V1: 21 | W1: 22
B2: Ticker | C2: Country | D2: Industry | E2: Latest_Date | F2: Growth_Rate | G2: 4Q21 | H2: 1Q22 | I2: 2Q22 | J2: 3Q22 | K2: 4Q22 | L2: 1Q23 | M2: 2Q23 | N2: 3Q23 | O2: 4Q23 | P2: 1Q24 | Q2: 2Q24 | R2: 3Q24 | S2: 4Q24 | T2: 1Q25 | U2: 2Q25 | V2: 3Q25 | W2: 4Q25 | X2: 1Q25 | Y2: 2Q25 | Z2: 3Q25 | AA2: 4Q25
A3: 260203 | B3: KREF | C3: United States | D3: REIT - Mortgage | E3: Dec'25 | F3: 1180.3 | G3: 35.67 | H3: 35.41 | I3: 25 | J3: -42.92 | K3: 18.86 | L3: -25.09 | M3: -19.95 | N3: 27 | O3: -12.91 | P3: -3.39 | Q3: 25.6 | R3: -7.24 | S3: 19.6 | T3: -5.75 | U3: -30.57 | V3: 12.77 | W3: -27.02 | X3: -0.068267284 | Y3: -1.7438684 | Z3: -0.8351419 | AA3: 11.802532
A4: 260203 | B4: INNV | C4: United States | D4: Medical Care Facilities | E4: Jun'26 | F4: 239.2 | G4: 2.95 | H4: -6.27 | I4: -12.35 | J4: -16.6 | K4: -13.68 | L4: -8.17 | M4: -10.94 | N4: -10.72 | O4: -1.79 | P4: -5.79 | Q4: -4.88 | R4: -4.9 | S4: -4.06 | T4: -10.16 | U4: 13.07 | V4: 8.39 | W4: 13.26 | X4: 0.22261844 | Y4: -0.74791667 | Z4: -2.1966942 | AA4: 2.3922652
A5: 260203 | B5: IAC | C5: United States | D5: Internet Content & Information | E5: Dec'25 | F5: 63.8 | G5: -4.52 | H5: -117.74 | I5: -106.37 | J5: -97.26 | K5: 0 | L5: -65.5 | M5: -51.8 | N5: -15.39 | O5: -105.06 | P5: -63.37 | Q5: -21.54 | R5: 8.15 | S5: 51.24 | T5: 35.67 | U5: 0.68 | V5: -20.4 | W5: 94.08 | X5: -3.8808777 | Y5: 0.30223069 | Z5: -0.29820347 | AA5: 0.63759488
A6: 260203 | B6: ATS | C6: United States | D6: Specialty Industrial Machinery | E6: Jun'26 | F6: 60.8 | G6: 43.65 | H6: 53.69 | I6: 66.61 | J6: 67.15 | K6: 58.72 | L6: 67.17 | M6: 69.13 | N6: 79.15 | O6: 84.22 | P6: 96.46 | Q6: 88.05 | R6: 69.89 | S6: 40.94 | T6: 39.54 | U6: -84.45 | V6: 60.58 | W6: 75.34 | X6: -0.19272703 | Y6: -0.72351313 | Z6: -0.1412318 | AA6: 0.60766649
A7: 260203 | B7: HTLD | C7: United States | D7: Trucking | E7: Dec'25 | F7: 59.2 | G7: 16.41 | H7: 18.14 | I7: 23.34 | J7: 27.91 | K7: 22.07 | L7: 16.1 | M7: 8.21 | N7: -8.51 | O7: -14.51 | P7: -14.29 | Q7: -0.86 | R7: -7.62 | S7: -4.98 | T7: -16.68 | U7: -15.2 | V7: -13.94 | W7: -35.04 | X7: 0.086126126 | Y7: 0.47577969 | Z7: 0.14208633 | AA7: 0.59173228
A8: 260203 | B8: PRU | C8: United States | D8: Insurance - Life | E8: Dec'25 | F8: 57.7 | G8: 2448 | H8: -657 | I8: -1061 | J8: -126 | K8: -1435 | L8: 1847 | M8: 621 | N8: -1058 | O8: 2069 | P8: 1390 | Q8: 1415 | R8: 553 | S8: -148 | T8: 920 | U8: 740 | V8: 1773 | W8: 1747 | X8: -0.14641745 | Y8: -0.24635036 | Z8: 0.59079903 | AA8: 0.57686454
A9: 260203 | B9: MPC | C9: United States | D9: Oil & Gas Refining & Marketing | E9: Dec'25 | F9: 28.4 | G9: 1610 | H9: 1613 | I9: 8110 | J9: 5462 | K9: 0 | L9: 3948 | M9: 3118 | N9: 4448 | O9: 2130 | P9: 1571 | Q9: 2161 | R9: 1140 | S9: 886 | T9: 452 | U9: 1973 | V9: 1733 | W9: 2321 | X9: -0.19433831 | Y9: -0.040525975 | Z9: 0.13322849 | AA9: 0.28449643
A10: 260203 | B10: AMD | C10: United States | D10: Semiconductors | E10: Dec'25 | F10: 22.899506 | G10: 1174 | H10: 951 | I10: 526 | J10: -64 | K10: -149 | L10: -145 | M10: -20 | N10: 224 | O10: 342 | P10: 36 | Q10: 269 | R10: 724 | S10: 1057 | T10: 806 | U10: -98 | V10: 1270 | W10: 1752 | X10: 0.36912752 | Y10: -0.1285014 | Z10: 0.21936521 | AA10: 0.22899506
A11: 260203 | B11: MSGE | C11: United States | D11: Leisure | E11: Jun'26 | F11: 19.8 | G11: 59.98 | H11: 21.19 | I11: -5.27 | J11: -11.31 | K11: 116.62 | L11: 27.42 | M11: -25.42 | N11: -20.48 | O11: 137.25 | P11: 18.31 | Q11: -6.9 | R11: -19.38 | S11: 138.11 | T11: 36.25 | U11: -23.19 | V11: -15.41 | W11: 164.94 | X11: 0.13785154 | Y11: -0.1100081 | Z11: 0.030123682 | AA11: 0.19762817
A12: 260203 | B12: SIMO | C12: United States | D12: Semiconductors | E12: Dec'25 | F12: 17.7 | G12: 68.87 | H12: 66.46 | I12: 67.85 | J12: 55.07 | K12: 24.93 | L12: 5.52 | M12: 5.04 | N12: 15.69 | O12: 14.94 | P12: 17.95 | Q12: 32.04 | R12: 24.46 | S12: 17.69 | T12: 9.77 | U12: 22.33 | V12: 29.23 | W12: 31.71 | X12: -0.088777947 | Y12: -0.11565031 | Z12: 0.064242424 | AA12: 0.17742344
A13: 260203 | B13: CPRI | C13: United States | D13: Luxury Goods | E13: Sep'26 | F13: 17.2 | G13: 343 | H13: 172 | I13: 233 | J13: 263 | K13: 237 | L13: 89 | M13: 78 | N13: 124 | O13: 141 | P13: 41 | Q13: 17 | R13: 25 | S13: 69 | T13: -39 | U13: 17 | V13: 11 | W13: 79 | X13: -0.52631579 | Y13: 0 | Z13: -0.19444444 | AA13: 0.17241379
A14: 260203 | B14: VRNS | C14: United States | D14: Software - Infrastructure | E14: Dec'25 | F14: 15.3 | G14: -17.83 | H14: -48.09 | I14: -37.57 | J14: -25.58 | K14: -9.99 | L14: -43.12 | M14: -39.72 | N14: -29.15 | O14: -5.24 | P14: -47.63 | Q14: -28.83 | R14: -23.64 | S14: -10.9 | T14: -43.16 | U14: -36.55 | V14: -35.93 | W14: -30.26 | X14: -0.04027027 | Y14: 0.072467849 | Z14: 0.10757112 | AA14: 0.1529951
... A55: 260203 | B55: J | C55: United States | D55: Engineering & Construction | E55: Mar'26 | F55: 0.5 | G55: 256.02 | H55: 266.2 | I55: 245.75 | J55: 252.13 | K55: 264.46 | L55: 299.52 | M55: 299.9 | N55: -184.71 | O55: 182.92 | P55: 149.36 | Q55: 219.4 | R55: 0 | S55: 227.9 | T55: 194.86 | U55: 264.61 | V55: 331.76 | W55: 232.56 | X55: 0.076257835 | Y55: 0.070403015 | Z55: 0.48265126 | AA55: 0.0045725275
A56: 260203 | B56: VLTO | C56: United States | D56: Pollution & Treatment Controls | E56: Dec'25 | F56: 0.4 | H56: 231 | I56: 311 | J56: 285 | K56: 295 | L56: 292 | M56: 295 | N56: 273 | O56: 299 | P56: 293 | Q56: 299 | R56: 308 | S56: 311 | T56: 322 | U56: 313 | V56: 326 | W56: 316 | X56: 0.023947151 | Y56: 0.011290323 | Z56: 0.014354067 | AA56: 0.0039308176
A57: 260203 | B57: JJSF | C57: United States | D57: Packaged Foods | E57: Mar'26 | F57: 0.2 | G57: 14.85 | H57: 4.09 | I57: 21.26 | J57: 25.72 | K57: 9.33 | L57: 10.19 | M57: 48.29 | N57: 43.38 | O57: 11.88 | P57: 17.9 | Q57: 50.12 | R57: 44.84 | S57: 5.74 | T57: 5.72 | U57: 51.48 | V57: 33.7 | W57: 5.95 | X57: -0.10269815 | Y57: 0.012779553 | Z57: -0.10335869 | AA57: 0.0021730132
A58: 260203 | B58: CMG | C58: United States | D58: Restaurants | E58: Dec'25 | F58: 0.1 | G58: 163 | H58: 194.53 | I58: 342.28 | J58: 342.62 | K58: 302.12 | L58: 375.97 | M58: 448.05 | N58: 402.19 | O58: 369.98 | P58: 446.77 | Q58: 591.82 | R58: 488.43 | S58: 426.36 | T58: 497.3 | U58: 564.52 | V58: 484.58 | W58: 428.78 | X58: 0.025867983 | Y58: -0.013623366 | Z58: -0.0019477793 | AA58: 0.0012267078
A59: 260203 | B59: PNR | C59: United States | D59: Specialty Industrial Machinery | E59: Dec'25 | F59: 0 | G59: 158.6 | H59: 153.2 | I59: 196 | J59: 175.5 | K59: 197.8 | L59: 195.2 | M59: 215.3 | N59: 182.1 | O59: 171.6 | P59: 203.2 | Q59: 265.1 | R59: 229.3 | S59: 204.8 | T59: 227.1 | U59: 286.9 | V59: 245.1 | W59: 205 | X59: 0.026484929 | Y59: 0.023534492 | Z59: 0.016664909 | AA59: 0.0002074904
A60: 260203 | B60: VOYA | C60: United States | D60: Financial Conglomerates | E60: Dec'25 | F60: -0.1 | G60: 20 | H60: 171 | I60: 198 | J60: 114 | K60: 232 | L60: 191 | M60: 369 | N60: 248 | O60: 252 | P60: 344 | Q60: 374 | R60: 185 | S60: 198 | T60: 240 | U60: 251 | V60: 367 | W60: 197 | X60: -0.094459582 | Y60: -0.12337011 | Z60: 0.20823799 | AA60: -0.0009469697
A61: 260203 | B61: MZTI | C61: United States | D61: Packaged Foods | E61: Jun'26 | F61: -0.3 | G61: 45.06 | H61: 13.81 | I61: 44.24 | J61: 49.3 | K61: 51.33 | L61: 29.41 | M61: 36.44 | N61: 56.78 | O61: 65.94 | P61: 50.07 | Q61: 43.87 | R61: 55.86 | S61: 77.47 | T61: 51.59 | U61: 44.09 | V61: 60.4 | W61: 76.85 | X61: 0.0066880803 | Y61: 0.00096158049 | Z61: 0.019824462 | AA61: -0.0026546778
A62: 260203 | B62: WTW | C62: United States | D62: Insurance Brokers | E62: Dec'25 | F62: -0.5 | G62: 0 | H62: 276 | I62: 300 | J62: 277 | K62: 958 | L62: 375 | M62: 270 | N62: 318 | O62: 965 | P62: 445 | Q62: 333 | R62: 380 | S62: 1045 | T62: 357 | U62: 383 | V62: 432 | W62: 1035 | X62: -0.039945529 | Y62: 0.023640662 | Z62: 0.024018476 | AA62: -0.0045105999
A63: 260203 | B63: HRB | C63: United States | D63: Personal Services | E63: Jun'26 | F63: -0.7 | G63: -277.3 | H63: 885.37 | I63: 311.6 | J63: -209.11 | K63: -283.2 | L63: 864.5 | M63: 376.51 | N63: -206.33 | O63: -267.43 | P63: 928.2 | Q63: 350.83 | R63: -228.33 | S63: -293.29 | T63: 978.31 | U63: 371.28 | V63: -207.03 | W63: -298.88 | X63: 0.066159676 | Y63: 0.02532445 | Z63: 0.02572557 | AA63: -0.0065821235
A64: 260203 | B64: ATI | C64: United States | D64: Metal Fabrication | E64: Dec'25 | F64: -1 | G64: 58.1 | H64: 88.4 | I64: 96.4 | J64: 104.1 | K64: 266.2 | L64: 110.2 | M64: 121.2 | N64: 122.4 | O64: 62.7 | P64: 114.6 | Q64: 142.1 | R64: 140.8 | S64: 154.6 | T64: 150.9 | U64: 164.3 | V64: 170.1 | W64: 148 | X64: 0.065748959 | Y64: 0.037729436 | Z64: 0.047985588 | AA64: -0.010314112
A65: 260203 | B65: GWW | C65: United States | D65: Industrial Distribution | E65: Dec'25 | F65: -1.2 | G65: 588 | H65: 534 | I65: 534 | J65: 603 | K65: 546 | L65: 680 | M65: 661 | N65: 667 | O65: 601 | P65: 669 | Q65: 649 | R65: 686 | S65: 668 | T65: 672 | U65: 678 | V65: 707 | W65: 634 | X65: 0.0011227545 | Y65: 0.010841121 | Z65: 0.0077662722 | AA65: -0.012477064
A66: 260203 | B66: ADM | C66: United States | D66: Farm Products | E66: Dec'25 | F66: -1.4 | G66: 880 | H66: 1074 | I66: 1292 | J66: 1000 | K66: 805 | L66: 1203 | M66: 1047 | N66: 999 | O66: 751 | P66: 708 | Q66: 489 | R66: 460 | S66: 340 | T66: 248 | U66: 459 | V66: 397 | W66: 320 | X66: -0.23034552 | Y66: -0.019518543 | Z66: -0.04180491 | AA66: -0.013850416
A67: 260203 | B67: FUBO | C67: United States | D67: Broadcasting | E67: Dec'25 | F67: -1.5 | P67: -38.78 | Q67: -43.98 | R67: -40.75 | S67: -40.75 | T67: -39.75 | U67: -40.91 | V67: -38.39 | W67: -38.39 | X67: 0.0059052721 | Y67: -0.018580161 | Z67: -0.014553527 | AA67: -0.014768461
A68: 260203 | B68: INGR | C68: United States | D68: Packaged Foods | E68: Dec'25 | F68: -1.9 | G68: 113 | H68: 213 | I68: 215 | J68: 186 | K68: 150 | L68: 291 | M68: 249 | N68: 222 | O68: 200 | P68: 216 | Q68: 263 | R68: 277 | S68: 250 | T68: 283 | U68: 274 | V68: 251 | W68: 230 | X68: 0.066600398 | Y68: 0.010251631 | Z68: -0.02398524 | AA68: -0.018903592
A69: 260203 | B69: SKY | C69: United States | D69: Residential Construction | E69: Sep'26 | F69: -3.8 | G69: 91.41 | H69: 116 | I69: 157.05 | J69: 190.19 | K69: 102.27 | L69: 68.77 | M69: 59.23 | N69: 52.04 | O69: 56.18 | P69: 7.76 | Q69: 63.3 | R69: 66.68 | S69: 72.81 | T69: 42.87 | U69: 81.42 | V69: 74.82 | W69: 62.47 | X69: 0.16675374 | Y69: 0.073760482 | Z69: 0.030859049 | AA69: -0.03802589
A70: 260203 | B70: BV | C70: United States | D70: Specialty Business Services | E70: Mar'26 | F70: -4 | G70: -3.6 | H70: 17.3 | I70: 48.2 | J70: 46.1 | K70: -1.9 | L70: -2.6 | M70: 51.2 | N70: 78.1 | O70: -6.2 | P70: 18.3 | Q70: 66 | R70: 62.5 | S70: -0.6 | T70: 39.4 | U70: 61.8 | V70: 60.1 | W70: -7.1 | X70: 0.14432285 | Y70: -0.025104603 | Z70: -0.014714899 | AA70: -0.04044804
A71: 260203 | B71: CBT | C71: United States | D71: Specialty Chemicals | E71: Mar'26 | F71: -4.1 | G71: 119 | H71: 144 | I71: 170 | J71: 125 | K71: 108 | L71: 130 | M71: 151 | N71: 135 | O71: 136 | P71: 157 | Q71: 172 | R71: 163 | S71: 155 | T71: 163 | U71: 167 | V71: 146 | W71: 129 | X71: 0.0092735703 | Y71: -0.0076569678 | Z71: -0.026234568 | AA71: -0.041204437
A72: 260203 | B72: AAT | C72: United States | D72: REIT - Diversified | E72: Dec'25 | F72: -6.3 | G72: 25.72 | H72: 28.34 | I72: 28.32 | J72: 31 | K72: 27.07 | L72: 29.72 | M72: 31.49 | N72: 31.14 | O72: 29.4 | P72: 30.55 | Q72: 30.79 | R72: 37.81 | S72: 30.05 | T72: 27.5 | U72: 25.98 | V72: 24.77 | W72: 23.22 | X72: -0.023606811 | Y72: -0.038129211 | Z72: -0.10746662 | AA72: -0.063065559
A73: 260203 | B73: COLM | C73: United States | D73: Apparel Manufacturing | E73: Dec'25 | F73: -8 | G73: 212.57 | H73: 83.67 | I73: 8.77 | J73: 145.26 | K73: 191.8 | L73: 56.43 | M73: 6.23 | N73: 134.55 | O73: 138.07 | P73: 44.68 | Q73: -23.8 | R73: 112.54 | S73: 137.32 | T73: 46.51 | U73: -23.59 | V73: 96.39 | W73: 116.74 | X73: 0.0067592524 | Y73: 0.00077044429 | Z73: -0.05920522 | AA73: -0.080193274
A74: 260203 | B74: INTA | C74: United States | D74: Software - Application | E74: Jun'26 | F74: -9 | G74: -23.91 | H74: -28.7 | I74: -21.62 | J74: -17.2 | K74: -20.01 | L74: -18.89 | M74: -11.97 | N74: -15.4 | O74: -11.08 | P74: -7.45 | Q74: 0.34 | R74: -8.17 | S74: -10.19 | T74: -5.7 | U74: -3.74 | V74: -13.95 | W74: -7.18 | X74: -0.068708284 | Y74: 0.17200675 | Z74: 0.20791367 | AA74: -0.089636689
A75: 260203 | B75: RES | C75: United States | D75: Oil & Gas Equipment & Services | E75: Dec'25 | F75: -9.9 | G75: 16.58 | H75: 20.08 | I75: 58.62 | J75: 90.63 | K75: 112.73 | L75: 105.1 | M75: 80.27 | N75: 20.93 | O75: 47.6 | P75: 31.14 | Q75: 32.13 | R75: 17.41 | S75: 8.66 | T75: 10.86 | U75: 19.89 | V75: 23.7 | W75: 2.4 | X75: -0.22699799 | Y75: -0.17723719 | Z75: 0.11070046 | AA75: -0.099191887
A76: 260203 | B76: BRBR | C76: United States | D76: Packaged Foods | E76: Mar'26 | F76: -10.3 | G76: 52.6 | H76: 43.5 | I76: 68.4 | J76: 62.4 | K76: 75.2 | L76: 58 | M76: 76 | N76: 85.2 | O76: 90.4 | P76: 91 | Q76: 111.6 | R76: 112.1 | S76: 115.3 | T76: 95.1 | U76: 44.8 | V76: 102.2 | W76: 78.5 | X76: 0.0095348837 | Y76: -0.15388159 | Z76: -0.026953444 | AA76: -0.10296586
A77: 260203 | B77: SWKS | C77: United States | D77: Semiconductors | E77: Dec'25 | F77: -13.4 | G77: 376.6 | H77: 448.3 | I77: 372 | J77: 327.9 | K77: 409.5 | L77: 367.4 | M77: 296.4 | N77: 235.1 | O77: 254.3 | P77: 274.5 | Q77: 188.9 | R77: 132 | S77: 191.9 | T77: 182.7 | U77: 104.4 | V77: 112.1 | W77: 112.6 | X77: -0.11660104 | Y77: -0.12149533 | Z77: -0.032569558 | AA77: -0.13415666
A78: 260203 | B78: MDLZ | C78: United States | D78: Confectioners | E78: Dec'25 | F78: -14.2 | G78: 1111 | H78: 1344 | I78: 1003 | J78: 1037 | K78: 1219 | L78: 1619 | M78: 1492 | N78: 1521 | O78: 1339 | P78: 2838 | Q78: 930 | R78: 1026 | S78: 1651 | T78: 723 | U78: 1168 | V78: 1056 | W78: 1000 | X78: -0.32816137 | Y78: 0.054965358 | Z78: 0.0065674256 | AA78: -0.1415833
A79: 260203 | B79: AMGN | C79: United States | D79: Drug Manufacturers - General | E79: Dec'25 | F79: -14.9 | G79: 2355 | H79: 2490 | I79: 2176 | J79: 2654 | K79: 2138 | L79: 2069 | M79: 2661 | N79: 1874 | O79: 3197 | P79: 1752 | Q79: 2707 | R79: 2708 | S79: 4707 | T79: 2341 | U79: 3004 | V79: 3264 | W79: 2720 | X79: 0.049604177 | Y79: 0.023830538 | Z79: 0.043573668 | AA79: -0.14921898
... A93: 260203 | B93: MRCY | C93: United States | D93: Aerospace & Defense | E93: Jun'26 | F93: -826.5 | G93: 6.08 | H93: 19.03 | I93: 36.54 | J93: -3.19 | K93: -4.54 | L93: 6.34 | M93: -4.87 | N93: -29.69 | O93: -53.7 | P93: -35.61 | Q93: -0.88 | R93: -10.98 | S93: -12.2 | T93: -12.1 | U93: 24.87 | V93: -1.25 | W93: -6.58 | X93: -0.39400034 | Y93: -0.71211283 | Z93: -0.93467819 | AA93: -8.2647059
A94: 260203 | B94: 4676 | C94: Japan | D94: Fuji Media Holdings, Inc. | E94: Jun'26 | F94: 725.3 | G94: 6932 | H94: 14758 | I94: 7005 | J94: 7852 | K94: 4306 | L94: 10282 | M94: 8962 | N94: 5600 | O94: 7421 | P94: 10581 | Q94: 9919 | R94: 6555 | S94: 7325 | T94: 13291 | U94: -8877 | V94: -12778 | W94: -211 | X94: 0.078824898 | Y94: -0.50676732 | Z94: -1.0567946 | AA94: 7.253128
A95: 260203 | B95: 5857 | C95: Japan | D95: ARE Holdings, Inc. | E95: Jun'26 | F95: 20.6 | G95: 6715 | H95: 5508 | I95: 7706 | J95: 5665 | K95: 6473 | L95: 5987 | M95: 3236 | N95: 3051 | O95: 3931 | P95: 3061 | Q95: 0 | R95: 3146 | S95: 4201 | T95: 5837 | U95: 7279 | V95: 5543 | W95: 8913 | X95: 0.26671791 | Y95: 0.55210862 | Z95: 0.11713825 | AA95: 0.20612423
A96: 260203 | B96: 6471 | C96: Japan | D96: NSK Ltd. | E96: Sep'26 | F96: 19.4 | G96: 4784 | H96: 6222 | I96: 3899 | J96: 8194 | K96: 8195 | L96: 12474 | M96: 3410 | N96: 6363 | O96: 7898 | P96: 7002 | Q96: 5642 | R96: 4220 | S96: 3841 | T96: 12789 | U96: 3729 | V96: 11038 | W96: 9945 | X96: 0.27949771 | Y96: -0.072210479 | Z96: 0.27739127 | AA96: 0.19441348
A97: 260203 | B97: 5482 | C97: Japan | D97: Aichi Steel Corporation | E97: Jun'26 | F97: 15.5 | G97: 257 | H97: -97 | I97: 629 | J97: -1186 | K97: 1479 | L97: 314 | M97: 3436 | N97: 3068 | O97: 1655 | P97: 4382 | Q97: 3373 | R97: 1487 | S97: 1811 | T97: 4411 | U97: 4999 | V97: 4529 | W97: 4255 | X97: 0.0026237221 | Y97: 0.14672442 | Z97: 0.23937677 | AA97: 0.1551746
A98: 260203 | B98: 8386 | C98: Japan | D98: The Hyakujushi Bank, Ltd. | E98: Jun'26 | F98: 15.4 | G98: 4702 | H98: 4792 | I98: 479 | J98: 5110 | K98: 3616 | L98: 2197 | M98: 2285 | N98: 5688 | O98: 1616 | P98: 3488 | Q98: 3489 | R98: 4955 | S98: 3016 | T98: 5576 | U98: 4050 | V98: 6603 | W98: 5971 | X98: 0.13968424 | Y98: 0.032930265 | Z98: 0.093652327 | AA98: 0.15354638
A99: 260203 | B99: 8368 | C99: Japan | D99: The Hyakugo Bank, Ltd. | E99: Jun'26 | F99: 14.7 | G99: 5261 | H99: 5427 | I99: 3834 | J99: 5210 | K99: 5240 | L99: 4225 | M99: 5782 | N99: 6980 | O99: 4605 | P99: 4937 | Q99: 3359 | R99: 7262 | S99: 5493 | T99: 7444 | U99: 5244 | V99: 5097 | W99: 8924 | X99: 0.11909173 | Y99: 0.080015281 | Z99: -0.085092167 | AA99: 0.14739239
A100: 260203 | B100: 8367 | C100: Japan | D100: The Nanto Bank, Ltd. | E100: Jun'26 | F100: 11.9 | G100: 3887 | H100: 5671 | I100: 3207 | J100: 4012 | K100: 5188 | L100: 3948 | M100: -6833 | N100: 4137 | O100: 4132 | P100: 4163 | Q100: 4192 | R100: 6660 | S100: 3394 | T100: 6461 | U100: 2967 | V100: 5674 | W100: 5591 | X100: 0.12483025 | Y100: -0.059158739 | Z100: -0.05061082 | AA100: 0.11878244
A101: 260203 | B101: 4062 | C101: Japan | D101: Ibiden Co.,Ltd. | E101: Sep'26 | F101: 11.1 | G101: 20071 | H101: 16391 | I101: 18090 | J101: 23316 | K101: 19769 | L101: 11189 | M101: 8182 | N101: 15892 | O101: 12874 | P101: 10621 | Q101: 11295 | R101: 17217 | S101: 5656 | T101: 11711 | U101: 16670 | V101: 13968 | W101: 10986 | X101: 0.024336333 | Y101: 0.117156 | Z101: -0.063390174 | AA101: 0.1110301
A102: 260203 | B102: 6486 | C102: Japan | D102: Eagle Industry Co.,Ltd. | E102: Jun'26 | F102: 10.3 | G102: 1411 | H102: 1319 | I102: 2320 | J102: 1946 | K102: 1817 | L102: 3750 | M102: 1752 | N102: 1497 | O102: 1588 | P102: 2867 | Q102: 2156 | R102: 2625 | S102: 1640 | T102: 2065 | U102: 2164 | V102: 2999 | W102: 2549 | X102: -0.086347976 | Y102: 0.0009427292 | Z102: 0.044031081 | AA102: 0.10250338
A103: 260203 | B103: 2331 | C103: Japan | D103: Alsok Co.,Ltd. | E103: Jun'26 | F103: 9 | G103: 15072 | H103: 9851 | I103: 7131 | J103: 6924 | K103: 7779 | L103: 9213 | M103: 12046 | N103: 8449 | O103: 8875 | P103: 8911 | Q103: 11845 | R103: 7095 | S103: 8163 | T103: 11331 | U103: 13614 | V103: 10438 | W103: 12083 | X103: 0.06719609 | Y103: 0.046026955 | Z103: 0.083152999 | AA103: 0.090019749
A104: 260203 | B104: 5802 | C104: Japan | D104: Sumitomo Electric Industries, Ltd. | E104: Sep'26 | F104: 8.6 | G104: 30372 | H104: 45698 | I104: 19001 | J104: 30738 | K104: 45086 | L104: 82618 | M104: 18936 | N104: 48393 | O104: 81003 | P104: 78286 | Q104: 53285 | R104: 66030 | S104: 87524 | T104: 113824 | U104: 60301 | V104: 92720 | W104: 118024 | X104: 0.12464007 | Y104: 0.021879668 | Z104: 0.081451665 | AA104: 0.086068477
A105: 260203 | B105: 6472 | C105: Japan | D105: NTN Corporation | E105: Sep'26 | F105: 8.4 | G105: 934 | H105: 4338 | I105: -784 | J105: 4645 | K105: 6031 | L105: 7255 | M105: 1490 | N105: 5275 | O105: 8629 | P105: 12755 | Q105: 4533 | R105: 5417 | S105: 4264 | T105: 8746 | U105: 6978 | V105: 5889 | W105: 6435 | X105: -0.14865216 | Y105: 0.10648955 | Z105: 0.01857902 | AA105: 0.083896897
... A128: 260203 | B128: 9107 | C128: Japan | D128: Kawasaki Kisen Kaisha, Ltd. | E128: Jun'26 | F128: -7.9 | G128: 7781 | H128: 13122 | I128: -5640 | J128: 18879 | K128: 34120 | L128: 27595 | M128: -1735 | N128: 19638 | O128: 25019 | P128: 25497 | Q128: 14610 | R128: 30718 | S128: 30423 | T128: 31105 | U128: 10609 | V128: 19843 | W128: 23113 | X128: 0.055388748 | Y128: -0.037442914 | Z128: -0.10573137 | AA128: -0.079473799
A129: 260203 | B129: NAZARA | C129: India | D129: Nazara Technologies Limited | E129: Jun'26 | F129: 45.8 | G129: 99 | H129: 168 | I129: 80 | J129: 165 | K129: 110 | L129: 180 | M129: 77.2 | N129: 178.8 | O129: 128 | P129: 225 | Q129: 116.8 | R129: 97.2 | S129: -5.8 | T129: 218.3 | U129: -3.3 | V129: -170.8 | W129: 11.8 | X129: -0.015466297 | Y129: -0.28159437 | Z129: -0.87467363 | AA129: 0.45833333
A130: 260203 | B130: SOLARINDS | C130: India | D130: Solar Industries India Limited | E130: Sep'26 | F130: 8.7 | G130: 1508 | H130: 2839 | I130: 2524 | J130: 2686 | K130: 3175 | L130: 4277 | M130: 2890 | N130: 3025 | O130: 3176 | P130: 5135 | Q130: 4094 | R130: 4012 | S130: 4791 | T130: 4720 | U130: 4789 | V130: 4922 | W130: 6454 | X130: -0.023014641 | Y130: 0.039450531 | Z130: 0.04969419 | AA130: 0.086515451
A131: 260203 | B131: ABCAPITAL | C131: India | D131: Aditya Birla Capital Limited | E131: Sep'26 | F131: 7.6 | G131: 6591 | H131: 5287 | I131: 5619 | J131: 5933 | K131: 34391 | L131: 7682 | M131: 8479 | N131: 9568 | O131: 9958 | P131: 14470 | Q131: 9635 | R131: 13284 | S131: 9675 | T131: 11665 | U131: 10710 | V131: 11344 | W131: 12994 | X131: -0.059599694 | Y131: 0.024288845 | Z131: -0.042793488 | AA131: 0.076485228
A132: 260203 | B132: RPOWER | C132: India | D132: Reliance Power Limited | E132: Sep'26 | F132: 6.2 | G132: 5594 | H132: -550.9 | I132: 5551 | J132: 3126 | K132: 4093 | L132: -4165 | M132: 3594 | N132: 4693 | O132: -6258 | P132: -896.8 | Q132: 4004 | R132: 1324 | S132: 2874 | T132: 6794 | U132: 3584 | V132: 4102 | W132: 3945 | X132: 1.0527843 | Y132: -0.028007469 | Z132: 0.19058727 | AA132: 0.061714878
A133: 260203 | B133: ADANIPORTS | C133: India | D133: Adani Ports and Special Economic Zone Limited | E133: Sep'26 | F133: 4.4 | G133: 17375 | H133: 20989 | I133: 22817 | J133: 24060 | K133: 21277 | L133: 24814 | M133: 28041 | N133: 29060 | O133: 32006 | P133: 31175 | Q133: 32326 | R133: 32923 | S133: 36963 | T133: 38227 | U133: 42404 | V133: 42868 | W133: 44017 | X133: 0.05286872 | Y133: 0.071760693 | Z133: 0.066072271 | AA133: 0.043960564
A134: 260203 | B134: PIDILITIND | C134: India | D134: Pidilite Industries Limited | E134: Jun'26 | F134: 2.5 | G134: 4893 | H134: 4886 | I134: 3698 | J134: 4682 | K134: 4362 | L134: 4272 | M134: 4190 | N134: 6335 | O134: 6045 | P134: 6630 | Q134: 4974 | R134: 7283 | S134: 6809 | T134: 7089 | U134: 5539 | V134: 8443 | W134: 7508 | X134: 0.017862702 | Y134: 0.021601988 | Z134: 0.043413174 | AA134: 0.025071736
A135: 260203 | B135: PILANIINVS | C135: India | D135: Pilani Investment and Industries Corporation Limited | E135: Jun'26 | F135: 0.7 | G135: 968.72 | H135: 506.35 | I135: 493.08 | J135: 580.52 | K135: 1112 | L135: 511 | M135: 522.03 | N135: 527.46 | O135: 1042 | P135: 568.23 | Q135: 621.28 | R135: 599.96 | S135: 1224 | T135: 570.92 | U135: 533.51 | V135: 460.44 | W135: 1243 | X135: 0.00089265863 | Y135: -0.029099915 | Z135: -0.047643927 | AA135: 0.0068127951
A136: 260203 | B136: BAJFINANCE | C136: India | D136: Bajaj Finance Limited | E136: Sep'26 | F136: -0.3 | G136: 28680 | H136: 32902 | I136: 35028 | J136: 37523 | K136: 40116 | L136: 42595 | M136: 45484 | N136: 47576 | O136: 48939 | P136: 51146 | Q136: 52628 | R136: 53980 | S136: 57624 | T136: 56481 | U136: 63668 | V136: 66048 | W136: 56941 | X136: 0.024770404 | Y136: 0.050019709 | Z136: 0.052072681 | AA136: -0.0028012353
A137: 260203 | B137: BECTORFOOD | C137: India | D137: Mrs. Bectors Food Specialities Limited | E137: Jun'26 | F137: -3.3 | G137: 237.7 | H137: 212.26 | I137: 134.57 | J137: 186.97 | K137: 309.14 | L137: 374.95 | M137: 348.21 | N137: 440.54 | O137: 496.63 | P137: 450.4 | Q137: 421.78 | R137: 466.75 | S137: 511.16 | T137: 420.15 | U137: 357.04 | V137: 369.47 | W137: 455.93 | X137: -0.016350556 | Y137: -0.035574556 | Z137: -0.055427041 | AA137: -0.033314835
A138: 260203 | B138: CMSINFO | C138: India | D138: CMS Info Systems Limited | E138: Jun'26 | F138: -5.3 | G138: 716.82 | H138: 826.72 | I138: 885.74 | J138: 942.13 | K138: 1000 | L138: 1031 | M138: 1099 | N138: 1112 | O138: 1093 | P138: 1131 | Q138: 1157 | R138: 1135 | S138: 1140 | T138: 1184 | U138: 1194 | V138: 1134 | W138: 892.3 | X138: 0.011615165 | Y138: 0.0080155979 | Z138: -0.00021491511 | AA138: -0.053245916
A139: 260203 | B139: HGINFRA | C139: India | D139: H.G. Infra Engineering Limited | E139: Jun'26 | F139: -9.4 | G139: 1789 | H139: 1370 | I139: 2123 | J139: 2746 | K139: 2497 | L139: 1848 | M139: 1916 | N139: 3000 | O139: 3000 | P139: 2775 | Q139: 2775 | R139: 1836 | S139: 2507 | T139: 2044 | U139: 2044 | V139: 2350 | W139: 1662 | X139: -0.07389063 | Y139: -0.079786073 | Z139: 0.060965485 | AA139: -0.094466182
A140: 260202 | B140: PLTR | C140: United States | D140: Software - Infrastructure | E140: Dec'25 | F140: 66.4 | G140: -58.94 | H140: -39.44 | I140: -41.75 | J140: -62.19 | K140: -17.83 | L140: 4.12 | M140: 10.07 | N140: 39.98 | O140: 65.79 | P140: 80.88 | Q140: 105.34 | R140: 113.14 | S140: 11.04 | T140: 176.05 | U140: 269.32 | V140: 393.26 | W140: 575.39 | X140: 0.30660438 | Y140: 0.40431985 | Z140: 0.49182688 | AA140: 0.66419904
... A164: 260202 | B164: TWO | C164: United States | D164: REIT - Mortgage | E164: Dec'25 | F164: -129.4 | G164: 1.48 | H164: 334.76 | I164: -44.08 | J164: 303.66 | K164: -269.09 | L164: -175.3 | M164: 222.16 | N164: 354.05 | O164: -459.45 | P164: 216.76 | Q164: 69.71 | R164: -248.84 | S164: 308.94 | T164: -78.52 | U164: -57.45 | V164: 52.41 | W164: 17.29 | X164: -0.85200681 | Y164: -2.4792357 | Z164: -3.9706076 | AA164: -1.2940367
A165: 260202 | B165: 2811 | C165: Japan | D165: Kagome Co., Ltd. | E165: Dec'25 | F165: 107 | G165: 2180 | H165: 2149 | I165: 3159 | J165: 4253 | K165: 2390 | L165: 3144 | M165: 5039 | N165: 6011 | O165: 3327 | P165: 15195 | Q165: 10110 | R165: 8169 | S165: -6737 | T165: 4791 | U165: 5734 | V165: 6992 | W165: 4795 | X165: -0.38912369 | Y165: -0.26792384 | Z165: -0.098436063 | AA165: 1.0697588
A166: 260202 | B166: 6971 | C166: Japan | D166: Kyocera Corporation | E166: Sep'26 | F166: 75.9 | G166: 42779 | H166: 30452 | I166: 41428 | J166: 35060 | K166: 37396 | L166: 14633 | M166: 25677 | N166: 28325 | O166: 25842 | P166: 13079 | Q166: 20956 | R166: 16920 | S166: -25601 | T166: 55172 | U166: 18550 | V166: 23395 | W166: 28676 | X166: 1.6602114 | Y166: -0.035672454 | Z166: 0.09955259 | AA166: 0.75894905
A167: 260202 | B167: 7241 | C167: Japan | D167: Futaba Industrial Co., Ltd. | E167: Jun'26 | F167: 16.4 | G167: -1909 | H167: 940 | I167: 3878 | J167: -2008 | K167: 1718 | L167: 2764 | M167: 5208 | N167: 4730 | O167: 4716 | P167: 6565 | Q167: 3202 | R167: 3615 | S167: 1832 | T167: 4466 | U167: 5265 | V167: 4192 | W167: 4417 | X167: -0.13796503 | Y167: 0.1573008 | Z167: 0.038015549 | AA167: 0.1640749
A168: 260202 | B168: 8386 | C168: Japan | D168: The Hyakujushi Bank, Ltd. | E168: Jun'26 | F168: 15.4 | G168: 4702 | H168: 4792 | I168: 479 | J168: 5110 | K168: 3616 | L168: 2197 | M168: 2285 | N168: 5688 | O168: 1616 | P168: 3488 | Q168: 3489 | R168: 4955 | S168: 3016 | T168: 5576 | U168: 4050 | V168: 6603 | W168: 5971 | X168: 0.13968424 | Y168: 0.032930265 | Z168: 0.093652327 | AA168: 0.15354638
A169: 260202 | B169: 2281 | C169: Japan | D169: Prima Meat Packers, Ltd. | E169: Sep'26 | F169: 14.4 | G169: 3521 | H169: 1450 | I169: 3406 | J169: 2066 | K169: 3291 | L169: 919 | M169: 3608 | N169: 3223 | O169: 3561 | P169: 1428 | Q169: 3347 | R169: 2839 | S169: 2088 | T169: 675 | U169: 2530 | V169: 2381 | W169: 3190 | X169: -0.077612863 | Y169: -0.091295117 | Z169: -0.056320708 | AA169: 0.14360177
A170: 260202 | B170: 8370 | C170: Japan | D170: The Kiyo Bank, Ltd. | E170: Sep'26 | F170: 12.6 | G170: 7447 | H170: 3014 | I170: 6694 | J170: 6340 | K170: 6734 | L170: -14901 | M170: 4787 | N170: 4747 | O170: 5654 | P170: 4845 | Q170: 5175 | R170: 5267 | S170: 6006 | T170: 6925 | U170: 6407 | V170: 4039 | W170: 8952 | X170: 0.097684685 | Y170: 0.052710392 | Z170: -0.049908555 | AA170: 0.1260213
A171: 260202 | B171: 7981 | C171: Japan | D171: Takara Standard Co.,Ltd. | E171: Jun'26 | F171: 9.9 | G171: 3990 | H171: 5837 | I171: 877 | J171: 3225 | K171: 2861 | L171: 3886 | M171: 969 | N171: 2684 | O171: 2624 | P171: 5411 | Q171: 1709 | R171: 3098 | S171: 2860 | T171: 6885 | U171: 2793 | V171: 4196 | W171: 4519 | X171: 0.11270837 | Y171: 0.074491479 | Z171: 0.070222563 | AA171: 0.099139477
A172: 260202 | B172: 2282 | C172: Japan | D172: NH Foods Ltd. | E172: Sep'26 | F172: 9.4 | G172: 20357 | H172: 0 | I172: 13202 | J172: 6423 | K172: 1760 | L172: -10848 | M172: 17632 | N172: 13023 | O172: 12269 | P172: -11247 | Q172: 19099 | R172: 9780 | S172: 14203 | T172: -6510 | U172: 18261 | V172: 20694 | W172: 18565 | X172: 0.14879849 | Y172: -0.022913704 | Z172: 0.30542341 | AA172: 0.093508832
A173: 260202 | B173: 8331 | C173: Japan | D173: The Chiba Bank, Ltd. | E173: Sep'26 | F173: 8.9 | G173: 19452 | H173: 13461 | I173: 23942 | J173: 26698 | K173: 19092 | L173: 16937 | M173: 25921 | N173: 24001 | O173: 22592 | P173: 18153 | Q173: 28626 | R173: 25631 | S173: 25108 | T173: 27460 | U173: 30960 | V173: 31799 | W173: 35358 | X173: 0.095438791 | Y173: 0.021848818 | Z173: 0.056504732 | AA173: 0.088877713
A174: 260202 | B174: 8346 | C174: Japan | D174: The Toho Bank, Ltd. | E174: Jun'26 | F174: 8.5 | G174: 2851 | H174: 2876 | I174: 1558 | J174: 2478 | K174: 1533 | L174: 2341 | M174: 711 | N174: 2858 | O174: 2201 | P174: 3211 | Q174: -276 | R174: 3291 | S174: 3211 | T174: 2872 | U174: 1250 | V174: 4545 | W174: 4222 | X174: -0.035922433 | Y174: 0.16772917 | Z174: 0.11803464 | AA174: 0.085115339
A175: 260202 | B175: 7337 | C175: Japan | D175: Hirogin Holdings, Inc. | E175: Sep'26 | F175: 5 | G175: 12515 | H175: 4371 | I175: 12885 | J175: 1687 | K175: 5896 | L175: -2214 | M175: 13684 | N175: 10157 | O175: 9513 | P175: 6590 | Q175: 15232 | R175: 11141 | S175: 15310 | T175: 9358 | U175: 16518 | V175: 12526 | W175: 17990 | X175: 0.057340542 | Y175: 0.025195431 | Z175: 0.026468171 | AA175: 0.04989574
A176: 260202 | B176: 9064 | C176: Japan | D176: Yamato Holdings Co., Ltd. | E176: Sep'26 | F176: 4.3 | G176: 47482 | H176: -1973 | I176: 2418 | J176: 15631 | K176: 48352 | L176: -6315 | M176: 1598 | N176: 10761 | O176: 38004 | P176: -10303 | Q176: -14205 | R176: -797 | S176: 41267 | T176: -12058 | U176: -6494 | V176: 2712 | W176: 42368 | X176: -0.10994863 | Y176: 0.54276061 | Z176: 0.16009672 | AA176: 0.043300429
... A191: 260202 | B191: 5992 | C191: Japan | D191: Chuo Spring Co.,Ltd. | E191: Sep'26 | F191: -15.6 | G191: 809 | H191: 786 | I191: -391 | J191: 732 | K191: 144 | L191: -149 | M191: -54 | N191: 735 | O191: 311 | P191: 69 | Q191: 136 | R191: 1625 | S191: 1235 | T191: 1383 | U191: 602 | V191: 893 | W191: 592 | X191: 0.42871126 | Y191: 0.10641699 | Z191: -0.15108359 | AA191: -0.15633358
A192: 260202 | B192: POLICYBZR | C192: India | D192: PB Fintech Limited | E192: Sep'26 | F192: 155.7 | G192: -3280 | H192: -2669 | I192: -2475 | J192: -2416 | K192: -1507 | L192: -854.94 | M192: -966.21 | N192: -1114 | O192: -485.8 | P192: -183.38 | Q192: -642.7 | R192: -371.8 | S192: -58.9 | T192: 795.8 | U192: 9.1 | V192: 639.6 | W192: 2099 | X192: -0.77911806 | Y192: -2.3479827 | Z192: 2.7028327 | AA192: 1.5573759
A193: 260202 | B193: APOLLO | C193: India | D193: Apollo Micro Systems Limited | E193: Jun'26 | F193: 19.1 | G193: 78.27 | H193: 95.5 | I193: 140.6 | J193: 73.76 | K193: 94.07 | L193: 169.63 | M193: 202.4 | N193: 101.33 | O193: 156.61 | P193: 211.74 | Q193: 257.74 | R193: 189.18 | S193: 291.47 | T193: 339.68 | U193: 327.72 | V193: 364.42 | W193: 544.42 | X193: 0.13465526 | Y193: 0.064912297 | Z193: 0.15264144 | AA193: 0.19115236
A194: 260202 | B194: PCJEWELLER | C194: India | D194: PC Jeweller Limited | E194: Sep'26 | F194: 16.4 | G194: 294.7 | H194: -1965 | I194: 779.5 | J194: 1405 | K194: 292.9 | L194: -267.7 | M194: -496.4 | N194: -585.2 | O194: -778.6 | P194: -49 | Q194: 478 | R194: 814.8 | S194: 1071 | T194: 1419 | U194: 1223 | V194: 1727 | W194: 1962 | X194: 0.63418006 | Y194: 0.19694406 | Z194: 0.2014665 | AA194: 0.16378676
A195: 260202 | B195: THERMAX | C195: India | D195: Thermax Limited | E195: Sep'26 | F195: 15.6 | G195: 841.3 | H195: 1078 | I195: 674.8 | J195: 1108 | K195: 1320 | L195: 1743 | M195: 1028 | N195: 1717 | O195: 1516 | P195: 2379 | Q195: 1051 | R195: 2359 | S195: 1539 | T195: 2585 | U195: 1762 | V195: 1206 | W195: 2643 | X195: 0.028111354 | Y195: 0.094372179 | Z195: -0.13984233 | AA195: 0.15566836
A196: 260202 | B196: SHRIPISTON | C196: India | D196: Shriram Pistons & Rings Limited | E196: Sep'26 | F196: 10 | G196: 470.3 | H196: 612.35 | I196: 696.4 | J196: 910.5 | K196: 937.8 | L196: 1112 | M196: 1235 | N196: 1351 | O196: 1323 | P196: 1437 | Q196: 1359 | R196: 1469 | S196: 1397 | T196: 1828 | U196: 1636 | V196: 1747 | W196: 2061 | X196: 0.06905687 | Y196: 0.045762432 | Z196: 0.043917852 | AA196: 0.10048426
A197: 260202 | B197: APLLTD | C197: India | D197: Alembic Pharmaceuticals Limited | E197: Jun'26 | F197: 9.2 | G197: 2026 | H197: 1997 | I197: 23.6 | J197: -524.4 | K197: 1651 | L197: 1822 | M197: 1430 | N197: 1325 | O197: 1407 | P197: 1969 | Q197: 1906 | R197: 1678 | S197: 1688 | T197: 1902 | U197: 2031 | V197: 2076 | W197: 2396 | X197: -0.0092528656 | Y197: 0.017424031 | Z197: 0.054528018 | AA197: 0.09198389
A198: 260202 | B198: SUNDARMFIN | C198: India | D198: Sundaram Finance Limited | E198: Sep'26 | F198: 6 | G198: 3434 | H198: 4511 | I198: 3460 | J198: 3974 | K198: 4241 | L198: 5073 | M198: 4220 | N198: 4681 | O198: 5134 | P198: 7111 | Q198: 5165 | R198: 5462 | S198: 5837 | T198: 6834 | U198: 5712 | V198: 6351 | W198: 7331 | X198: -0.011749735 | Y198: 0.02347841 | Z198: 0.037282449 | AA198: 0.060402685
A199: 260202 | B199: GICRE | C199: India | D199: General Insurance Corporation of India | E199: Jun'26 | F199: 5.9 | G199: 15372 | H199: -837.5 | I199: 35245 | J199: 5345 | K199: 21655 | L199: 9858 | M199: 34945 | N199: 9662 | O199: 14646 | P199: 13479 | Q199: 40865 | R199: 14731 | S199: 23802 | T199: 19289 | U199: 31921 | V199: 27485 | W199: 29807 | X199: 0.062555853 | Y199: -0.090629972 | Z199: 0.14211693 | AA199: 0.058587081
A200: 260202 | B200: FINEORG | C200: India | D200: Fine Organic Industries Limited | E200: Jun'26 | F200: -3.6 | G200: 632.89 | H200: 697.27 | I200: 1503 | J200: 2035 | K200: 2424 | L200: 1478 | M200: 1894 | N200: 1295 | O200: 1167 | P200: 1035 | Q200: 1282 | R200: 1280 | S200: 1382 | T200: 859.88 | U200: 1084 | V200: 1118 | W200: 1223 | X200: -0.035171721 | Y200: -0.041216683 | Z200: -0.035172432 | AA200: -0.035779544
A201: 260202 | B201: RELIGARE | C201: India | D201: Religare Enterprises Limited | E201: Jun'26 | F201: -5.8 | G201: -1829 | H201: -534.73 | I201: 1197 | J201: 1140 | K201: 338.99 | L201: 1309 | M201: 2441 | N201: 1193 | O201: 830.83 | P201: 649.59 | Q201: 84.87 | R201: 410.9 | S201: 612.25 | T201: -737.81 | U201: 2252 | V201: 27.52 | W201: 487.32 | X201: -0.78936738 | Y201: 5.8537857 | Z201: -0.15109524 | AA201: -0.058000149
A202: 260202 | B202: MIDHANI | C202: India | D202: Mishra Dhatu Nigam Limited | E202: Jun'26 | F202: -9.7 | G202: 448.47 | H202: 559.92 | I202: 1134 | J202: 206.46 | K202: 453.13 | L202: 520.96 | M202: 997.96 | N202: 273.51 | O202: 218.63 | P202: 214.42 | Q202: 773.29 | R202: 80.32 | S202: 332.72 | T202: 362.71 | U202: 911.78 | V202: 180.53 | W202: 159.85 | X202: 0.10586472 | Y202: 0.08940376 | Z202: 0.059382648 | AA202: -0.096697506
A203: 260202 | B203: INDUSTOWER | C203: India | D203: Indus Towers Limited | E203: Sep'26 | F203: -19.5 | G203: 23797 | H203: 27643 | I203: 9829 | J203: 15057 | K203: -1719 | L203: 23839 | M203: 21397 | N203: 19303 | O203: 20259 | P203: 28283 | Q203: 29848 | R203: 33270 | S203: 54286 | T203: 29899 | U203: 26858 | V203: 28119 | W203: 27106 | X203: 0.011092273 | Y203: -0.020298297 | Z203: -0.03569325 | AA203: -0.19531194
A204: 260202 | B204: 1060 | C204: Hong Kong | D204: Saudi Awwal Bank | E204: H1 2026 | F204: 7.6 | N204: 428.02 | O204: -192.25 | P204: 209.71 | Q204: 4.64 | R204: 0 | S204: 333.66 | T204: 0 | U204: 538.05 | V204: 261.56 | W204: 419.31 | X204: -0.3826755 | Y204: 1.5767366 | Z204: 0.30005392 | AA204: 0.075577753
A205: 260202 | B205: 1140 | C205: Hong Kong | D205: Bank Albilad | E205: H1 2026 | F205: -2 | N205: 94.16 | O205: 55.58 | P205: 32.74 | Q205: 50.31 | R205: 78.01 | S205: 114.57 | T205: 129.93 | U205: 111.4 | V205: 123.49 | W205: 105.03 | X205: 0.35261038 | Y205: 0.16385924 | Z205: 0.10481436 | AA205: -0.01990029
A206: 260130 | B206: TMP | C206: United States | D206: Banks - Regional | E206: Dec'25 | F206: 102.8 | G206: 24.9 | H206: 30.28 | I206: 27.23 | J206: 28.15 | K206: 24.06 | L206: 25.31 | M206: 10.29 | N206: -41.63 | O206: 18.15 | P206: 22.1 | Q206: 20.62 | R206: 24.53 | S206: 25.73 | T206: 25.8 | U206: 28.24 | V206: 31.11 | W206: 139.71 | X206: 0.039793504 | Y206: 0.078816715 | Z206: 0.063087248 | AA206: 1.0279582
A207: 260130 | B207: LPG | C207: United States | D207: Oil & Gas Midstream | E207: Jun'26 | F207: 55.3 | G207: 15.65 | H207: 22.55 | I207: 33.69 | J207: 28.95 | K207: 28.14 | L207: 57.49 | M207: 83.78 | N207: 55.62 | O207: 80.49 | P207: 110.34 | Q207: 82.38 | R207: 55.47 | S207: 19.1 | T207: 23.38 | U207: 14.69 | V207: 15.59 | W207: 59.34 | X207: -0.32533952 | Y207: -0.37536738 | Z207: -0.3540483 | AA207: 0.55305113
A208: 260130 | B208: JHG | C208: United States | D208: Asset Management | E208: Dec'25 | F208: 42.7 | G208: 235.1 | H208: 157.4 | I208: 143.9 | J208: 120.7 | K208: 103.6 | L208: 100.4 | M208: 117.9 | N208: 121.7 | O208: 143.7 | P208: 119.2 | Q208: 164.3 | R208: 164.7 | S208: 192.8 | T208: 153.6 | U208: 163.8 | V208: 180.1 | W208: 487.4 | X208: 0.053666147 | Y208: -0.00074030204 | Z208: 0.022818195 | AA208: 0.42677097
A209: 260130 | B209: MCHB | C209: United States | D209: Banks - Regional | E209: Dec'25 | F209: 37.3 | P209: -157.4 | Q209: 70.42 | R209: 55.48 | S209: 67.19 | T209: 61.46 | U209: 59.04 | V209: 45.1 | W209: 153.95 | X209: 6.1322499 | Y209: -0.044706345 | Z209: -0.042686187 | AA209: 0.37269642
A210: 260130 | B210: SOFI | C210: United States | D210: Credit Services | E210: Dec'25 | F210: 31.3 | G210: -107.35 | H210: -93.07 | I210: -94.91 | J210: -74.35 | K210: -37.08 | L210: -36.06 | M210: -49.15 | N210: -19.75 | O210: 51.3 | P210: 94.23 | Q210: 15.34 | R210: 63.86 | S210: 59.92 | T210: 79.78 | U210: 112.19 | V210: 148.55 | W210: 185.33 | X210: -0.061924148 | Y210: 0.44243947 | Z210: 0.26821853 | AA210: 0.3131805
A211: 260130 | B211: OPY | C211: United States | D211: Capital Markets | E211: Dec'25 | F211: 29.3 | G211: 141.12 | H211: 35.23 | I211: 13.94 | J211: 64.3 | K211: 75.63 | L211: 57.64 | M211: 56.36 | N211: 51.32 | O211: 66.17 | P211: 64.61 | Q211: 40.93 | R211: 63.35 | S211: 66.09 | T211: 69.4 | U211: 62.75 | V211: 62.96 | W211: 142.59 | X211: 0.020384714 | Y211: 0.091003879 | Z211: -0.0014908827 | AA211: 0.29287902
A212: 260130 | B212: WT | C212: United States | D212: Asset Management | E212: Dec'25 | F212: 16.3 | G212: 22.56 | H212: 17.69 | I212: 15.8 | J212: 14.87 | K212: 11.72 | L212: 16.57 | M212: 18.18 | N212: 26.71 | O212: 26.04 | P212: 27.95 | Q212: 33.51 | R212: 40.79 | S212: 35.04 | T212: 34.16 | U212: 36.6 | V212: 48.06 | W212: 60.06 | X212: 0.045232719 | Y212: 0.021533101 | Z212: 0.049594106 | AA212: 0.16261536
...

Sheet 빨간줄
B2: (단위: mil $)
B4: XOM | C4: 6 | D4: 7 | E4: 8 | F4: 9 | G4: 10 | H4: 11 | I4: 12 | J4: 13 | K4: 14 | L4: 15 | M4: 16 | N4: 17 | O4: 18 | P4: 19 | Q4: 20 | R4: 21 | S4: 22
C6: 4Q21 | D6: 1Q22 | E6: 2Q22 | F6: 3Q22 | G6: 4Q22 | H6: 1Q23 | I6: 2Q23 | J6: 3Q23 | K6: 4Q23 | L6: 1Q24 | M6: 2Q24 | N6: 3Q24 | O6: 4Q24 | P6: 1Q25 | Q6: 2Q25 | R6: 3Q25 | S6: 4Q25 | T6: 1Q26 | U6: 2Q26 | V6: 3Q26 | W6: 4Q26
B7: Revenue | C7: =VLOOKUP($B$4,Revenue!$B:$W,C4,FALSE) -> 82885 | D7: =VLOOKUP($B$4,Revenue!$B:$W,D4,FALSE) -> 87962 | E7: =VLOOKUP($B$4,Revenue!$B:$W,E4,FALSE) -> 111993 | F7: =VLOOKUP($B$4,Revenue!$B:$W,F4,FALSE) -> 107438 | G7: =VLOOKUP($B$4,Revenue!$B:$W,G4,FALSE) -> 93790 | H7: =VLOOKUP($B$4,Revenue!$B:$W,H4,FALSE) -> 84183 | I7: =VLOOKUP($B$4,Revenue!$B:$W,I4,FALSE) -> 80256 | J7: =VLOOKUP($B$4,Revenue!$B:$W,J4,FALSE) -> 88570 | ... S7: =VLOOKUP($B$4,Revenue!$B:$W,S4,FALSE) -> 80039
B8: OP | C8: =VLOOKUP($B$4,'Operating Income'!$B:$W,C4,FALSE) -> 11128 | D8: =VLOOKUP($B$4,'Operating Income'!$B:$W,D4,FALSE) -> 9181 | E8: =VLOOKUP($B$4,'Operating Income'!$B:$W,E4,FALSE) -> 21439 | F8: =VLOOKUP($B$4,'Operating Income'!$B:$W,F4,FALSE) -> 21696 | G8: =VLOOKUP($B$4,'Operating Income'!$B:$W,G4,FALSE) -> 13738 | H8: =VLOOKUP($B$4,'Operating Income'!$B:$W,H4,FALSE) -> 14581 | I8: =VLOOKUP($B$4,'Operating Income'!$B:$W,I4,FALSE) -> 9247 | J8: =VLOOKUP($B$4,'Operating Income'!$B:$W,J4,FALSE) -> 11678 | ... S8: =VLOOKUP($B$4,'Operating Income'!$B:$W,S4,FALSE) -> 7780
B9: Trailing 4Q OP avg. | C9: =AVERAGE(C8:C8) -> 11128 | D9: =AVERAGE(C8:D8) -> 10154.5 | E9: =AVERAGE(C8:E8) -> 13916 | F9: =AVERAGE(C8:F8) -> 15861 | G9: =AVERAGE(D8:G8) -> 16513.5 | H9: =AVERAGE(E8:H8) -> 17863.5 | I9: =AVERAGE(F8:I8) -> 14815.5 | J9: =AVERAGE(G8:J8) -> 12311 | K9: =AVERAGE(H8:K8) -> 11761.75 | L9: =AVERAGE(I8:L8) -> 10596 | M9: =AVERAGE(J8:M8) -> 10999.75 | ... S9: =AVERAGE(P8:S8) -> 8887
B10: Trailing 4Q OP sum. | C10: =SUM(C8:C8) -> 11128 | D10: =SUM(C8:D8) -> 20309 | E10: =SUM(C8:E8) -> 41748 | F10: =SUM(C8:F8) -> 63444 | G10: =SUM(D8:G8) -> 66054 | H10: =SUM(E8:H8) -> 71454 | I10: =SUM(F8:I8) -> 59262 | J10: =SUM(G8:J8) -> 49244 | K10: =SUM(H8:K8) -> 47047 | L10: =SUM(I8:L8) -> 42384 | M10: =SUM(J8:M8) -> 43999 | ... S10: =SUM(P8:S8) -> 35548
B11: Trailing OP Delta | D11: =D9/C9-1 -> -0.087482027 | E11: =E9/D9-1 -> 0.3704269 | F11: =F9/E9-1 -> 0.13976717 | G11: =G9/F9-1 -> 0.041138642 | H11: =H9/G9-1 -> 0.081751294 | I11: =I9/H9-1 -> -0.17062726 | J11: =J9/I9-1 -> -0.16904593 | K11: =K9/J9-1 -> -0.044614572 | ... S11: =S9/R9-1 -> -0.015781605
B12: opm | C12: =IFERROR(C8/C7,"-") -> 0.13425831 | D12: =IFERROR(D8/D7,"-") -> 0.10437462 | E12: =IFERROR(E8/E7,"-") -> 0.19143161 | F12: =IFERROR(F8/F7,"-") -> 0.20193972 | G12: =IFERROR(G8/G7,"-") -> 0.14647617 | H12: =IFERROR(H8/H7,"-") -> 0.17320599 | I12: =IFERROR(I8/I7,"-") -> 0.1152188 | J12: =IFERROR(J8/J7,"-") -> 0.13185051 | ... S12: =IFERROR(S8/S7,"-") -> 0.097202614
B13: op yoy | C13: =C8/#REF!-1 -> #REF! | D13: =D8/#REF!-1 -> #REF! | E13: =E8/#REF!-1 -> #REF! | F13: =F8/#REF!-1 -> #REF! | G13: =G8/C8-1 -> 0.23454349 | H13: =H8/D8-1 -> 0.58817122 | I13: =I8/E8-1 -> -0.56868324 | J13: =J8/F8-1 -> -0.4617441 | K13: =K8/G8-1 -> -0.15992139 | L13: =L8/H8-1 -> -0.31979974 | M13: =M8/I8-1 -> 0.17465124 | N13: =N8/J8-1 -> -0.057287207 | ... S13: =S8/O8-1 -> -0.068263473
B14: rv yoy | G14: =G7/C7-1 -> 0.13156783 | H14: =H9/D9-1 -> 0.75917081 | I14: =I9/E9-1 -> 0.064637827 | J14: =J9/F9-1 -> -0.22381943 | K14: =K9/G9-1 -> -0.28774942 | L14: =L9/H9-1 -> -0.40683517 | M14: =M9/I9-1 -> -0.25755121 | N14: =N9/J9-1 -> -0.12009585 | O14: =O9/K9-1 -> -0.14683189 | ... S14: =S9/O9-1 -> -0.11437754
