Workbook

Sheet 기업리스트
B2: 실적 기업 정보
B3: Ticker | C3: Company | D3: Date | E3: Time | F3: Quarter Ending | G3: Market Cap (mil$)
B4: XOM | C4: Exxon Mobil Corporation | D4: 30-Jan-26 | E4: Pre Market | F4: 25-Dec | G4: 590910.6
B5: CVX | C5: Chevron Corporation | D5: 30-Jan-26 | E5: Pre Market | F5: 25-Dec | G5: 350262
B6: AXP | C6: American Express Company | D6: 30-Jan-26 | E6: Pre Market | F6: 25-Dec | G6: 241588.62
B7: VZ | C7: Verizon Communications Inc. | D7: 30-Jan-26 | E7: Pre Market | F7: 25-Dec | G7: 187740.84
B8: 8316 | C8: Sumitomo Mitsui Financial Group, Inc. | D8: 30-Jan-26 | F8: 25-Dec | G8: 136109.76
B9: CABK | C9: CaixaBank, S.A. | D9: 30-Jan-26 | F9: 25-Dec | G9: 93154.76
B10: REGN | C10: Regeneron Pharmaceuticals, Inc. | D10: 30-Jan-26 | E10: Pre Market | F10: 25-Dec | G10: 76072.37
B11: AON | C11: Aon plc | D11: 30-Jan-26 | E11: Pre Market | F11: 25-Dec | G11: 74997.78
B12: CL | C12: Colgate-Palmolive Company | D12: 30-Jan-26 | E12: Pre Market | F12: 25-Dec | G12: 72779.6
B13: APD | C13: Air Products and Chemicals, Inc. | D13: 30-Jan-26 | E13: Pre Market | F13: 25-Dec | G13: 60673.76
B14: CNR | C14: Canadian National Railway Company | D14: 30-Jan-26 | E14: Pre Market | F14: 25-Dec | G14: 59000
B15: IMO | C15: Imperial Oil Limited | D15: 30-Jan-26 | E15: Pre Market | F15: 25-Dec | G15: 48855.78
B16: SUNPHARMA | C16: Sun Pharmaceutical Industries Limited | D16: 31-Jan-26 | F16: 25-Dec | G16: 44129.9
B17: NTPC | C17: NTPC Limited | D17: 30-Jan-26 | F17: 25-Dec | G17: 37012.58
B18: SOFI | C18: SoFi Technologies, Inc. | D18: 30-Jan-26 | F18: 25-Dec | G18: 33019.38
B19: 6301 | C19: Komatsu Ltd. | D19: 30-Jan-26 | F19: 25-Dec | G19: 32397.54
B20: HEXA B | C20: Hexagon AB (publ) | D20: 30-Jan-26 | F20: 25-Dec | G20: 30885.71
B21: BAJAJ-AUTO | C21: Bajaj Auto Limited | D21: 30-Jan-26 | F21: 25-Dec | G21: 29228.78
B22: 8604 | C22: Nomura Holdings, Inc. | D22: 30-Jan-26 | F22: 25-Dec | G22: 27415.64
B23: POWERGRID | C23: Power Grid Corporation of India Limited | D23: 30-Jan-26 | F23: 25-Dec | G23: 26373.19
B24: 8308 | C24: Resona Holdings, Inc. | D24: 30-Jan-26 | F24: 25-Dec | G24: 25655.07
B25: CHTR | C25: Charter Communications, Inc. | D25: 30-Jan-26 | E25: Pre Market | F25: 25-Dec | G25: 24556.72
B26: 8309 | C26: Sumitomo Mitsui Trust Group, Inc. | D26: 30-Jan-26 | F26: 25-Dec | G26: 22710.76
B27: CHD | C27: Church & Dwight Co., Inc. | D27: 30-Jan-26 | F27: 25-Dec | G27: 21758.19
B28: BEP.UN | C28: Brookfield Renewable Partners L.P. | D28: 30-Jan-26 | E28: Pre Market | F28: 25-Dec | G28: 17579.82
B29: A086790 | C29: Hana Financial Group Inc. | D29: 30-Jan-26 | F29: 25-Dec | G29: 17568.25
B30: A064350 | C30: Hyundai Rotem Company | D30: 30-Jan-26 | F30: 25-Dec | G30: 17553.24
B31: 500425 | C31: Ambuja Cements Limited | D31: 30-Jan-26 | F31: 25-Dec | G31: 16030.23
B32: LYB | C32: LyondellBasell Industries N.V. | D32: 30-Jan-26 | F32: 25-Dec | G32: 15911.95
B33: 9503 | C33: The Kansai Electric Power Company, Incorporated | D33: 30-Jan-26 | F33: 25-Dec | G33: 15905.22
B34: BANKBARODA | C34: Bank of Baroda Limited | D34: 30-Jan-26 | F34: 25-Dec | G34: 15374.99
B35: AAF | C35: Airtel Africa Plc | D35: 30-Jan-26 | F35: 25-Dec | G35: 14965.4
B36: 511243 | C36: Cholamandalam Investment and Finance Company Limited | D36: 30-Jan-26 | F36: 25-Dec | G36: 14880.03
B37: 300803 | C37: Beijing Compass Technology Development Co., Ltd. | D37: 31-Jan-26 | F37: 25-Dec | G37: 14276.91
B38: A010140 | C38: Samsung Heavy Industries Co., Ltd. | D38: 30-Jan-26 | F38: 25-Dec | G38: 13281.33
B39: GAIL | C39: GAIL (India) Limited | D39: 31-Jan-26 | F39: 25-Dec | G39: 13135.49
B40: LTM | C40: LATAM Airlines Group S.A. | D40: 30-Jan-26 | F40: 25-Dec | G40: 12909.86
B41: RBI | C41: Raiffeisen Bank International AG | D41: 30-Jan-26 | F41: 25-Dec | G41: 12454.45
B42: JINDALSTEL | C42: Jindal Steel Limited | D42: 30-Jan-26 | F42: 25-Dec | G42: 12369.15
B43: BEN | C43: Franklin Resources, Inc. | D43: 30-Jan-26 | E43: Pre Market | F43: 25-Dec | G43: 12356.85
B44: 6920 | C44: Lasertec Corporation | D44: 30-Jan-26 | F44: 25-Dec | G44: 12223.53
B45: BEPC | C45: Brookfield Renewable Corporation | D45: 30-Jan-26 | E45: Pre Market | F45: 25-Dec | G45: 12162.18
B46: 9531 | C46: Tokyo Gas Co.,Ltd. | D46: 30-Jan-26 | F46: 25-Dec | G46: 12076.93
B47: SKF B | C47: AB SKF (publ) | D47: 30-Jan-26 | F47: 25-Dec | G47: 11664.84
B48: UHR | C48: The Swatch Group AG | D48: 30-Jan-26 | F48: 25-Dec | G48: 11610.65
B49: ALV | C49: Autoliv, Inc. | D49: 30-Jan-26 | E49: Pre Market | F49: 25-Dec | G49: 9832.09
B50: BCI | C50: Banco de Crédito e Inversiones | D50: 30-Jan-26 | F50: 25-Dec | G50: 9750.32
B51: SCA B | C51: Svenska Cellulosa Aktiebolaget SCA (publ) | D51: 30-Jan-26 | F51: 25-Dec | G51: 9462.3
B52: A298040 | C52: Hyosung Heavy Industries Corporation | D52: 30-Jan-26 | F52: 25-Dec | G52: 9356.67
B53: A066570 | C53: LG Electronics Inc. | D53: 30-Jan-26 | F53: 25-Dec | G53: 9317.39
B54: 7735 | C54: SCREEN Holdings Co., Ltd. | D54: 30-Jan-26 | F54: 25-Dec | G54: 9209.1
B55: 9719 | C55: SCSK Corporation | D55: 30-Jan-26 | F55: 25-Dec | G55: 8974.46
B56: 9202 | C56: ANA Holdings Inc. | D56: 30-Jan-26 | F56: 25-Dec | G56: 8964.9
B57: MOG.A | C57: Moog Inc. | D57: 30-Jan-26 | F57: 25-Dec | G57: 8468.98
B58: ELISA | C58: Elisa Oyj | D58: 30-Jan-26 | F58: 25-Dec | G58: 8373.47
B59: 3092 | C59: ZOZO, Inc. | D59: 30-Jan-26 | F59: 25-Dec | G59: 8164.87
B60: BEIJ B | C60: Beijer Ref AB (publ) | D60: 30-Jan-26 | F60: 25-Dec | G60: 8117.9
B61: 539437 | C61: IDFC First Bank Limited | D61: 31-Jan-26 | F61: 25-Dec | G61: 8112.01
B62: 5334 | C62: Niterra Co., Ltd. | D62: 30-Jan-26 | F62: 25-Dec | G62: 7778.27
B63: IESC | C63: IES Holdings, Inc. | D63: 30-Jan-26 | F63: 25-Dec | G63: 7728.35
B64: JHG | C64: Janus Henderson Group plc | D64: 30-Jan-26 | E64: Pre Market | F64: 25-Dec | G64: 7377.17
B65: SAIL | C65: Steel Authority of India Limited | D65: 30-Jan-26 | F65: 25-Dec | G65: 6924.5
B66: KBCA | C66: KBC Ancora SA | D66: 30-Jan-26 | F66: 25-Dec | G66: 6819.37
B67: BBU | C67: Brookfield Business Partners L.P. | D67: 30-Jan-26 | E67: Pre Market | F67: 25-Dec | G67: 6720.31
B68: 5844 | C68: Kyoto Financial Group,Inc. | D68: 30-Jan-26 | F68: 25-Dec | G68: 6281.7
B69: BDL | C69: Bharat Dynamics Limited | D69: 31-Jan-26 | F69: 25-Dec | G69: 6280.78
B70: 9042 | C70: Hankyu Hanshin Holdings, Inc. | D70: 30-Jan-26 | F70: 25-Dec | G70: 6078.29
B71: A307950 | C71: Hyundai Autoever Corporation | D71: 30-Jan-26 | F71: 25-Dec | G71: 5926.57
B72: HOLM B | C72: Holmen AB (publ) | D72: 30-Jan-26 | F72: 25-Dec | G72: 5825.35
B73: 101 | C73: Hang Lung Properties Limited | D73: 30-Jan-26 | F73: 25-Dec | G73: 5607.92
B74: 500163 | C74: Godfrey Phillips India Limited | D74: 30-Jan-26 | F74: 25-Dec | G74: 5303.29
B75: GNTX | C75: Gentex Corporation | D75: 30-Jan-26 | E75: Pre Market | F75: 25-Dec | G75: 5101.37
B76: 4506 | C76: Sumitomo Pharma Co., Ltd. | D76: 30-Jan-26 | F76: 25-Dec | G76: 4835.17
B77: 8572 | C77: Acom Co., Ltd. | D77: 30-Jan-26 | F77: 25-Dec | G77: 4754.59
B78: 9508 | C78: Kyushu Electric Power Company, Incorporated | D78: 30-Jan-26 | F78: 25-Dec | G78: 4746.06
B79: 500459 | C79: Procter & Gamble Hygiene and Health Care Limited | D79: 30-Jan-26 | F79: 25-Dec | G79: 4729.02
B80: FLG | C80: Flagstar Bank, National Association | D80: 30-Jan-26 | F80: 25-Dec | G80: 4580
B81: NATIONALUM | C81: National Aluminium Company Limited | D81: 30-Jan-26 | F81: 25-Dec | G81: 4575.27
B82: 9009 | C82: Keisei Electric Railway Co., Ltd. | D82: 30-Jan-26 | F82: 25-Dec | G82: 4465.49
B83: 2327 | C83: NS Solutions Corporation | D83: 30-Jan-26 | F83: 25-Dec | G83: 4432.63
B84: 5332 | C84: TOTO LTD. | D84: 30-Jan-26 | F84: 25-Dec | G84: 4354.9
B85: 9962 | C85: MISUMI Group Inc. | D85: 30-Jan-26 | F85: 25-Dec | G85: 4112.61
B86: 7276 | C86: Koito Manufacturing Co., Ltd. | D86: 30-Jan-26 | F86: 25-Dec | G86: 3919.28
B87: AIAENG | C87: AIA Engineering Limited | D87: 30-Jan-26 | F87: 25-Dec | G87: 3831.88
B88: AJANTPHARM | C88: Ajanta Pharma Limited | D88: 30-Jan-26 | F88: 25-Dec | G88: 3687.49
B89: ASTERDM | C89: Aster DM Healthcare Limited | D89: 30-Jan-26 | F89: 25-Dec | G89: 3620.66
B90: 9506 | C90: Tohoku Electric Power Company, Incorporated | D90: 30-Jan-26 | F90: 25-Dec | G90: 3547.07
B91: 9513 | C91: Electric Power Development Co., Ltd. | D91: 30-Jan-26 | F91: 25-Dec | G91: 3534.53
B92: 8341 | C92: The 77 Bank, Ltd. | D92: 30-Jan-26 | F92: 25-Dec | G92: 3513.63
B93: 500086 | C93: Exide Industries Limited | D93: 30-Jan-26 | F93: 25-Dec | G93: 3504.98
B94: 1959 | C94: Kraftia Corporation | D94: 30-Jan-26 | F94: 25-Dec | G94: 3449.45
B95: 2002 | C95: Nisshin Seifun Group Inc. | D95: 30-Jan-26 | F95: 25-Dec | G95: 3437.03
B96: 8377 | C96: Hokuhoku Financial Group, Inc. | D96: 30-Jan-26 | F96: 25-Dec | G96: 3410.19
B97: 4816 | C97: Toei Animation Co.,Ltd. | D97: 30-Jan-26 | F97: 25-Dec | G97: 3350.72
B98: MSUMI | C98: Motherson Sumi Wiring India Limited | D98: 30-Jan-26 | F98: 25-Dec | G98: 3283.4
B99: LICHSGFIN | C99: LIC Housing Finance Limited | D99: 30-Jan-26 | F99: 25-Dec | G99: 3251.46
B100: AEGISLOG | C100: Aegis Logistics Limited | D100: 30-Jan-26 | F100: 25-Dec | G100: 3169.27
B101: FHB | C101: First Hawaiian, Inc. | D101: 30-Jan-26 | E101: Pre Market | F101: 25-Dec | G101: 3065.77
...

Sheet Revenue
B2: Ticker | C2: Country | D2: Industry | E2: Latest_Date | F2: Growth_Rate | G2: 4Q21 | H2: 1Q22 | I2: 2Q22 | J2: 3Q22 | K2: 4Q22 | L2: 1Q23 | M2: 2Q23 | N2: 3Q23 | O2: 4Q23 | P2: 1Q24 | Q2: 2Q24 | R2: 3Q24 | S2: 4Q24 | T2: 1Q25 | U2: 2Q25 | V2: 3Q25 | W2: 4Q25 | X2: 1Q25 | Y2: 2Q25 | Z2: 3Q25 | AA2: 4Q25
B3: TMP | C3: United States | D3: Banks - Regional | E3: Dec'25 | F3: 37.3 | G3: 73.05 | H3: 77.12 | I3: 76.35 | J3: 77.75 | K3: 74.25 | L3: 75.47 | M3: 62.26 | N3: 8.24 | O3: 69.45 | P3: 71.96 | Q3: 70.56 | R3: 74.4 | S3: 75.7 | T3: 76.41 | U3: 79.86 | V3: 84.95 | W3: 193.85 | X3: 0.015207436 | Y3: 0.031305753 | Z3: 0.034435487 | AA3: 0.37280702
B4: JHG | C4: United States | D4: Asset Management | E4: Dec'25 | F4: 16.3 | G4: 697.2 | H4: 620 | I4: 555.5 | J4: 512.9 | K4: 515.2 | L4: 495.8 | M4: 516.5 | N4: 521 | O4: 568.5 | P4: 551.7 | Q4: 588.4 | R4: 624.8 | S4: 708.3 | T4: 621.4 | U4: 633.2 | V4: 700.4 | W4: 1142 | X4: 0.028182112 | Y4: 0.017617681 | Z4: 0.029215133 | AA4: 0.16284309
B5: MCHB | C5: United States | D5: Banks - Regional | E5: Dec'25 | F5: 13.4 | P5: -68.66 | Q5: 157.95 | R5: 141.14 | S5: 151.18 | T5: 147.19 | U5: 149.4 | V5: 119.03 | W5: 227.05 | X5: 0.56562983 | Y5: -0.014310581 | Z5: -0.037543937 | AA5: 0.13385674
B6: LPG | C6: United States | D6: Oil & Gas Midstream | E6: Jun'26 | F6: 11.9 | G6: 61.99 | H6: 68.16 | I6: 83.57 | J6: 76.41 | K6: 75.78 | L6: 102.53 | M6: 132.53 | N6: 110.81 | O6: 144.33 | P6: 162.33 | Q6: 141.36 | R6: 112.82 | S6: 82.31 | T6: 80.46 | U6: 74.08 | V6: 83.84 | W6: 120.63 | X6: -0.16412734 | Y6: -0.16136227 | Z6: -0.082878142 | AA6: 0.11949234
B7: SOFI | C7: United States | D7: Credit Services | E7: Dec'25 | F7: 8.7 | G7: 280.92 | H7: 317.38 | I7: 352.42 | J7: 407.66 | K7: 441.73 | L7: 463.75 | M7: 485.4 | N7: 515.38 | O7: 603.31 | P7: 637.81 | Q7: 586.98 | R7: 691.11 | S7: 734.13 | T7: 766.08 | U7: 844.91 | V7: 952.4 | W7: 1020 | X7: 0.048403226 | Y7: 0.092837347 | Z7: 0.08605738 | AA7: 0.086692423
B8: WT | C8: United States | D8: Asset Management | E8: Dec'25 | F8: 8 | G8: 79.18 | H8: 78.37 | I8: 77.25 | J8: 72.41 | K8: 73.31 | L8: 82.04 | M8: 85.72 | N8: 90.42 | O8: 90.84 | P8: 96.84 | Q8: 107.03 | R8: 113.17 | S8: 110.7 | T8: 108.08 | U8: 112.62 | V8: 125.62 | W8: 147.43 | X8: 0.026277645 | Y8: 0.012734065 | Z8: 0.028004589 | AA8: 0.080368474
B9: OPY | C9: United States | D9: Capital Markets | E9: Dec'25 | F9: 6.8 | G9: 362.84 | H9: 263.52 | I9: 233.61 | J9: 287.09 | K9: 302.9 | L9: 308.54 | M9: 288.73 | N9: 292.92 | O9: 289.97 | P9: 332.59 | Q9: 308.63 | R9: 349.25 | S9: 354.04 | T9: 346.43 | U9: 350.65 | V9: 401.94 | W9: 452.49 | X9: 0.010293713 | Y9: 0.03093459 | Z9: 0.03762577 | AA9: 0.067753568
B10: TOWN | C10: United States | D10: Banks - Regional | E10: Dec'25 | F10: 5.8 | G10: 161.53 | H10: 166.86 | I10: 166.92 | J10: 175.31 | K10: 168.04 | L10: 172.47 | M10: 178.01 | N10: 171.86 | O10: 153.1 | P10: 167.98 | Q10: 175.15 | R10: 175.62 | S10: 175.55 | T10: 189.62 | U10: 201.03 | V10: 200.39 | W10: 220.11 | X10: 0.031168083 | Y10: 0.036148281 | Z10: 0.03339085 | AA10: 0.058127552
B11: SAIL | C11: United States | D11: Software - Infrastructure | E11: Sep'26 | F11: 4.8 | P11: 202.71 | Q11: 187.66 | R11: 198.58 | S11: 235.26 | T11: 240.12 | U11: 230.47 | V11: 264.36 | W11: 281.94 | X11: 0.045388918 | Y11: 0.049685476 | Z11: 0.072730891 | AA11: 0.048113295
B12: GNTX | C12: United States | D12: Auto Parts | E12: Dec'25 | F12: 4.2 | G12: 419.84 | H12: 468.25 | I12: 463.42 | J12: 493.64 | K12: 493.65 | L12: 550.76 | M12: 583.47 | N12: 575.85 | O12: 589.13 | P12: 590.23 | Q12: 572.93 | R12: 608.53 | S12: 541.64 | T12: 576.77 | U12: 657.86 | V12: 655.24 | W12: 644.4 | X12: -0.0058184522 | Y12: 0.036928174 | Z12: 0.019586548 | AA12: 0.042261804
B13: FLG | C13: United States | D13: Banks - Regional | E13: Dec'25 | F13: 4.1 | G13: 334 | H13: 348 | I13: 368 | J13: 341 | K13: 294 | L13: 482 | M13: 1012 | N13: 980 | O13: 326 | P13: 439 | Q13: 281 | R13: 381 | S13: 480 | T13: 411 | U13: 432 | V13: 481 | W13: 554 | X13: -0.01771031 | Y13: 0.097231165 | Z13: 0.058685446 | AA13: 0.041019956
B14: IESC | C14: United States | D14: Engineering & Construction | E14: Mar'26 | F14: 3.6 | G14: 480.51 | H14: 501.59 | I14: 567.3 | J14: 617.41 | K14: 574.87 | L14: 568.88 | M14: 584.45 | N14: 649.02 | O14: 634.44 | P14: 705.73 | Q14: 768.42 | R14: 775.77 | S14: 749.55 | T14: 833.96 | U14: 890.16 | V14: 897.8 | W14: 870.96 | X14: 0.042750886 | Y14: 0.03892317 | Z14: 0.037554163 | AA14: 0.036010998
B15: FHB | C15: United States | D15: Banks - Regional | E15: Dec'25 | F15: 3.6 | G15: 178.9 | H15: 181 | I15: 188.28 | J15: 205.41 | K15: 216.99 | L15: 207.47 | M15: 202.29 | N15: 195.75 | O15: 204.81 | P15: 199.5 | Q15: 202.82 | R15: 202.6 | S15: 188.88 | T15: 200.5 | U15: 213.04 | V15: 221.89 | W15: 218.15 | X15: 0.0012597632 | Y15: 0.012858581 | Z15: 0.023962138 | AA15: 0.035508486
B16: RRBI | C16: United States | D16: Banks - Regional | E16: Dec'25 | F16: 3.3 | G16: 24.3 | H16: 22.98 | I16: 25.76 | J16: 27.36 | K16: 27.54 | L16: 27.25 | M16: 27.22 | N16: 26.12 | O16: 26.23 | P16: 25.85 | Q16: 26.59 | R16: 27.58 | S16: 28.38 | T16: 29.43 | U16: 30.09 | V16: 31.26 | W16: 32.31 | X16: 0.03302583 | Y16: 0.031255581 | Z16: 0.03186699 | AA16: 0.032980866
B17: AXP | C17: United States | D17: Credit Services | E17: Dec'25 | F17: 2.6 | G17: 12092 | H17: 11768 | I17: 12985 | J17: 12778 | K17: 13149 | L17: 13226 | M17: 13856 | N17: 14148 | O17: 14362 | P17: 14532 | Q17: 15065 | R17: 15280 | S17: 15887 | T17: 15817 | U17: 16451 | V17: 17139 | W17: 17566 | X17: 0.02114739 | Y17: 0.022337185 | Z17: 0.029305588 | AA17: 0.025714461
B18: BDL | C18: United States | D18: Restaurants | E18: Dec'25 | F18: 2.1 | G18: 33.6 | H18: 37.37 | I18: 40.27 | J18: 40.63 | K18: 39.69 | L18: 41.83 | M18: 43.76 | N18: 45.32 | O18: 43.33 | P18: 45.09 | Q18: 48.07 | R18: 49.05 | S18: 45.97 | T18: 50.22 | U18: 53.63 | V18: 52.1 | W18: 50.2 | X18: 0.027261133 | Y18: 0.028762092 | Z18: 0.015336652 | AA18: 0.020948891
B19: ALV | C19: United States | D19: Auto Parts | E19: Dec'25 | F19: 1.9 | G19: 2119 | H19: 2124 | I19: 2081 | J19: 2302 | K19: 2335 | L19: 2493 | M19: 2635 | N19: 2596 | O19: 2751 | P19: 2615 | Q19: 2605 | R19: 2555 | S19: 2616 | T19: 2578 | U19: 2714 | V19: 2706 | W19: 2817 | X19: -0.0035607737 | Y19: 0.010527332 | Z19: 0.014431807 | AA19: 0.018937253
B20: APD | C20: United States | D20: Specialty Chemicals | E20: Mar'26 | F20: 1.4 | G20: 2994 | H20: 2945 | I20: 3189 | J20: 0 | K20: 3175 | L20: 3200 | M20: 3034 | N20: 0 | O20: 2997 | P20: 2930 | Q20: 2986 | R20: 0 | S20: 2932 | T20: 2916 | U20: 3023 | V20: 3167 | W20: 3103 | X20: -0.0015822785 | Y20: 0.0041883631 | Z20: 0.35700597 | AA20: 0.014205017
B21: CL | C21: United States | D21: Household & Personal Products | E21: Dec'25 | F21: 1.4 | G21: 4403 | H21: 4399 | I21: 4484 | J21: 4455 | K21: 4629 | L21: 4770 | M21: 4822 | N21: 4915 | O21: 4950 | P21: 5065 | Q21: 5058 | R21: 5033 | S21: 4945 | T21: 4911 | U21: 5110 | V21: 5131 | W21: 5230 | X21: -0.0076613104 | Y21: 0.0026069083 | Z21: 0.004900245 | AA21: 0.014181221
B22: BEPC | C22: United States | D22: Utilities - Renewable | E22: Dec'25 | F22: 1.3 | G22: 917 | H22: 993 | I22: 1003 | J22: 905 | K22: 970 | L22: 1079 | M22: 940 | N22: 1029 | O22: 919 | P22: 1149 | Q22: 965 | R22: 1041 | S22: 891 | T22: 930 | U22: 929 | V22: 931 | W22: 938 | X22: -0.054127533 | Y22: -0.0094068461 | Z22: -0.029016091 | AA22: 0.012768269
B23: CHD | C23: United States | D23: Household & Personal Products | E23: Dec'25 | F23: 1 | G23: 1369 | H23: 1297 | I23: 1325 | J23: 1317 | K23: 1436 | L23: 1430 | M23: 1454 | N23: 1456 | O23: 1528 | P23: 1503 | Q23: 1511 | R23: 1511 | S23: 1582 | T23: 1467 | U23: 1506 | V23: 1586 | W23: 1644 | X23: -0.0058948747 | Y23: -0.00082358755 | Z23: 0.012363996 | AA23: 0.010096076
... B33: IMO | C33: United States | D33: Oil & Gas Integrated | E33: Dec'25 | F33: -2.9 | G33: 12295 | H33: 12657 | I33: 17285 | J33: 15071 | K33: 14400 | L33: 12057 | M33: 11764 | N33: 13873 | O33: 13202 | P33: 12249 | Q33: 13348 | R33: 13215 | S33: 12702 | T33: 12466 | U33: 11208 | V33: 11994 | W33: 11280 | X33: 0.0042124471 | Y33: -0.041367845 | Z33: -0.024621403 | AA33: -0.029398387
B34: 8550 | C34: Japan | D34: =VLOOKUP(B34,기업리스트!$B:$G,2,FALSE) -> The Tochigi Bank, Ltd. | E34: Sep'26 | F34: 33.4 | G34: 9261 | H34: 9547 | I34: 11915 | J34: 10457 | K34: 11143 | L34: 8064 | M34: 9243 | N34: 10474 | O34: 10896 | P34: 8660 | Q34: 10606 | R34: 7289 | S34: 11295 | T34: -26917 | U34: 9687 | V34: 11199 | W34: 13055 | X34: -0.93994716 | Y34: -0.40431148 | Z34: 2.88774 | AA34: 0.3343465
B35: 6777 | C35: Japan | D35: =VLOOKUP(B35,기업리스트!$B:$G,2,FALSE) -> santec Holdings Corporation | E35: Sep'26 | F35: 12.7 | G35: 2188 | H35: 3070 | I35: 3188 | J35: 3487 | K35: 3914 | L35: 4657 | M35: 3583 | N35: 4064 | O35: 4327 | P35: 6893 | Q35: 6306 | R35: 5691 | S35: 5316 | T35: 6713 | U35: 6186 | V35: 6592 | W35: 8470 | X35: -0.0074361728 | Y35: -0.0049945892 | Z35: 0.037689283 | AA35: 0.12714153
B36: 6331 | C36: Japan | D36: =VLOOKUP(B36,기업리스트!$B:$G,2,FALSE) -> Mitsubishi Kakoki Kaisha, Ltd. | E36: Sep'26 | F36: 12.3 | G36: 10538 | H36: 13501 | I36: 8957 | J36: 12243 | K36: 10175 | L36: 13215 | M36: 9243 | N36: 12902 | O36: 12075 | P36: 13554 | Q36: 11944 | R36: 14679 | S36: 14690 | T36: 17889 | U36: 15813 | V36: 20310 | W36: 23150 | X36: 0.079009241 | Y36: 0.065352522 | Z36: 0.089280335 | AA36: 0.12314052
B37: 8345 | C37: Japan | D37: =VLOOKUP(B37,기업리스트!$B:$G,2,FALSE) -> The Bank of Iwate, Ltd. | E37: Sep'26 | F37: 11.3 | G37: 10189 | H37: 8142 | I37: 11594 | J37: 11452 | K37: 13951 | L37: 2403 | M37: 10474 | N37: 10609 | O37: 10051 | P37: 9375 | Q37: 11508 | R37: 10888 | S37: 12165 | T37: 9396 | U37: 12494 | V37: 14761 | W37: 17685 | X37: 0.00047796795 | Y37: 0.022431012 | Z37: 0.086175823 | AA37: 0.11307768
B38: 6946 | C38: Japan | D38: =VLOOKUP(B38,기업리스트!$B:$G,2,FALSE) -> Nippon Avionics Co., Ltd. | E38: Sep'26 | F38: 10.4 | G38: 4532 | H38: 5050 | I38: 3263 | J38: 4599 | K38: 4762 | L38: 5130 | M38: 3605 | N38: 5064 | O38: 4584 | P38: 4802 | Q38: 4087 | R38: 5019 | S38: 4564 | T38: 6452 | U38: 5037 | V38: 7666 | W38: 7023 | X38: 0.089324383 | Y38: 0.047212007 | Z38: 0.12561693 | AA38: 0.10367216
B39: 8316 | C39: Japan | D39: =VLOOKUP(B39,기업리스트!$B:$G,2,FALSE) -> Sumitomo Mitsui Financial Group, Inc. | E39: Sep'26 | F39: 8.3 | G39: 942800 | H39: 82233 | I39: 994279 | J39: 1039205 | K39: 1013583 | L39: 479754 | M39: 1040727 | N39: 1129858 | O39: 1210013 | P39: 122089 | Q39: 1286487 | R39: 1534002 | S39: 1296678 | T39: -842478 | U39: 1358238 | V39: 1611881 | W39: 1579788 | X39: -0.22753214 | Y39: 0.021910783 | Z39: 0.023272194 | AA39: 0.082676293
B40: 9719 | C40: Japan | D40: =VLOOKUP(B40,기업리스트!$B:$G,2,FALSE) -> SCSK Corporation | E40: Sep'26 | F40: 8.2 | G40: 102729 | H40: 111396 | I40: 104417 | J40: 108682 | K40: 109924 | L40: 122888 | M40: 113371 | N40: 117824 | O40: 120167 | P40: 128944 | Q40: 122543 | R40: 128980 | S40: 133317 | T40: 211225 | U40: 177474 | V40: 193805 | W40: 191813 | X40: 0.16014707 | Y40: 0.092156057 | Z40: 0.099578185 | AA40: 0.081718754
B41: 2127 | C41: Japan | D41: =VLOOKUP(B41,기업리스트!$B:$G,2,FALSE) -> Nihon M&A Center Holdings Inc. | E41: Sep'26 | F41: 8.1 | G41: 10853 | H41: 6128 | I41: 9068 | J41: 11031 | K41: 9777 | L41: 11439 | M41: 8246 | N41: 10925 | O41: 11976 | P41: 12989 | Q41: 7638 | R41: 10953 | S41: 11252 | T41: 14234 | U41: 9018 | V41: 13569 | W41: 15151 | X41: 0.029067053 | Y41: 0.031308846 | Z41: 0.057548892 | AA41: 0.081105818
B42: 8803 | C42: Japan | D42: =VLOOKUP(B42,기업리스트!$B:$G,2,FALSE) -> Heiwa Real Estate Co., Ltd. | E42: Sep'26 | F42: 6.1 | G42: 7105 | H42: 9432 | I42: 17385 | J42: 7569 | K42: 7179 | L42: 12389 | M42: 15028 | N42: 13163 | O42: 7524 | P42: 8718 | Q42: 10579 | R42: 8182 | S42: 8186 | T42: 15128 | U42: 13123 | V42: 8697 | W42: 10952 | X42: 0.17972802 | Y42: 0.060463458 | Z42: 0.011542168 | AA42: 0.061284176
B43: 6961 | C43: Japan | D43: =VLOOKUP(B43,기업리스트!$B:$G,2,FALSE) -> Enplas Corporation | E43: Sep'26 | F43: 6 | G43: 7755 | H43: 9021 | I43: 10115 | J43: 10982 | K43: 11173 | L43: 9970 | M43: 9715 | N43: 9485 | O43: 8754 | P43: 9851 | Q43: 10601 | R43: 9099 | S43: 9105 | T43: 9264 | U43: 8999 | V43: 11902 | W43: 11473 | X43: -0.015185224 | Y43: -0.042081484 | Z43: 0.076864014 | AA43: 0.060300484
B44: 6196 | C44: Japan | D44: =VLOOKUP(B44,기업리스트!$B:$G,2,FALSE) -> Strike Company,Limited | E44: Mar'26 | F44: 5.8 | G44: 2355 | H44: 2861 | I44: 1916 | J44: 3595 | K44: 1969 | L44: 4113 | M44: 3050 | N44: 4694 | O44: 3676 | P44: 5554 | Q44: 4042 | R44: 4866 | S44: 3665 | T44: 5286 | U44: 5490 | V44: 5873 | W44: 4842 | X44: -0.014784575 | Y44: 0.081079568 | Z44: 0.052157249 | AA44: 0.057940337
B45: 8308 | C45: Japan | D45: =VLOOKUP(B45,기업리스트!$B:$G,2,FALSE) -> Resona Holdings, Inc. | E45: Sep'26 | F45: 5.7 | G45: 173983 | H45: 178409 | I45: 194300 | J45: 217183 | K45: 195938 | L45: 193615 | M45: 178656 | N45: 210154 | O45: 187334 | P45: 236919 | Q45: 219748 | R45: 243077 | S45: 230960 | T45: 259613 | U45: 248800 | V45: 251222 | W45: 286985 | X45: 0.024383692 | Y45: 0.030472059 | Z45: 0.0082904982 | AA45: 0.056556918
B46: 8341 | C46: Japan | D46: =VLOOKUP(B46,기업리스트!$B:$G,2,FALSE) -> The 77 Bank, Ltd. | E46: Sep'26 | F46: 5.5 | G46: 27470 | H46: 26921 | I46: 30911 | J46: 27118 | K46: 30476 | L46: 31502 | M46: 36678 | N46: 35841 | O46: 32103 | P46: 40464 | Q46: 43379 | R46: 38316 | S46: 40171 | T46: 42126 | U46: 40982 | V46: 44774 | W46: 49467 | X46: 0.010238403 | Y46: -0.014616567 | Z46: 0.039964108 | AA46: 0.055315882
B47: 6526 | C47: Japan | D47: =VLOOKUP(B47,기업리스트!$B:$G,2,FALSE) -> Socionext Inc. | E47: Sep'26 | F47: 5 | I47: 39934 | J47: 42833 | K47: 56074 | L47: 53926 | M47: 61447 | N47: 55541 | O47: 52650 | P47: 51608 | Q47: 52783 | R47: 46398 | S47: 46083 | T47: 43271 | U47: 34553 | V47: 52656 | W47: 54931 | X47: -0.042347312 | Y47: -0.096692922 | Z47: 0.036745838 | AA47: 0.050112424
B48: 2121 | C48: Japan | D48: =VLOOKUP(B48,기업리스트!$B:$G,2,FALSE) -> MIXI, Inc. | E48: Sep'26 | F48: 4.9 | G48: 29502 | H48: 37010 | I48: 31022 | J48: 34712 | K48: 39068 | L48: 42065 | M48: 29207 | N48: 34761 | O48: 41241 | P48: 41659 | Q48: 30087 | R48: 38733 | S48: 41532 | T48: 44495 | U48: 31323 | V48: 36105 | W48: 48997 | X48: 0.018656545 | Y48: 0.0079820726 | Z48: -0.016837196 | AA48: 0.048646183
B49: 7327 | C49: Japan | D49: =VLOOKUP(B49,기업리스트!$B:$G,2,FALSE) -> Daishi Hokuetsu Financial Group, Inc. | E49: Sep'26 | F49: 4.7 | G49: 30022 | H49: 30809 | I49: 37378 | J49: 33124 | K49: 30140 | L49: 28562 | M49: 38919 | N49: 34477 | O49: 31639 | P49: 31389 | Q49: 41750 | R49: 31320 | S49: 38855 | T49: 35784 | U49: 45728 | V49: 71647 | W49: 47817 | X49: 0.030666927 | Y49: 0.026931331 | Z49: 0.26585667 | AA49: 0.04667368
B50: 8388 | C50: Japan | D50: =VLOOKUP(B50,기업리스트!$B:$G,2,FALSE) -> The Awa Bank, Ltd. | E50: Sep'26 | F50: 4.6 | G50: 16114 | H50: 16398 | I50: 18816 | J50: 18049 | K50: 26480 | L50: 15872 | M50: 15521 | N50: 15706 | O50: 17162 | P50: 15543 | Q50: 17950 | R50: 16573 | S50: 18265 | T50: 15297 | U50: 21196 | V50: 21441 | W50: 21746 | X50: -0.0036001229 | Y50: 0.047675699 | Z50: 0.068245223 | AA50: 0.045683014
B51: 8377 | C51: Japan | D51: =VLOOKUP(B51,기업리스트!$B:$G,2,FALSE) -> Hokuhoku Financial Group, Inc. | E51: Sep'26 | F51: 4.4 | G51: 40966 | H51: 34196 | I51: 39737 | J51: 40851 | K51: 36945 | L51: 51481 | M51: 38901 | N51: 48546 | O51: 45239 | P51: 38244 | Q51: 41538 | R51: 43956 | S51: 45085 | T51: 42665 | U51: 50206 | V51: 55838 | W51: 53614 | X51: 0.02618719 | Y51: 0.050033479 | Z51: 0.065317296 | AA51: 0.04401065
B52: 6135 | C52: Japan | D52: =VLOOKUP(B52,기업리스트!$B:$G,2,FALSE) -> Makino Milling Machine Co., Ltd. | E52: Sep'26 | F52: 4.1 | G52: 47532 | H52: 63719 | I52: 46481 | J52: 56558 | K52: 62459 | L52: 62487 | M52: 53850 | N52: 54665 | O52: 54477 | P52: 62368 | Q52: 51868 | R52: 56369 | S52: 60557 | T52: 65422 | U52: 55397 | V52: 64024 | W52: 70711 | X52: 0.013211514 | Y52: 0.015067288 | Z52: 0.032198364 | AA52: 0.041377343
B53: 2326 | C53: Japan | D53: =VLOOKUP(B53,기업리스트!$B:$G,2,FALSE) -> Digital Arts Inc. | E53: Sep'26 | F53: 4 | G53: 2134 | H53: 2365 | I53: 2386 | J53: 2698 | K53: 2574 | L53: 2778 | M53: 2541 | N53: 3022 | O53: 2759 | P53: 3190 | Q53: 2234 | R53: 2604 | S53: 2436 | T53: 2708 | U53: 2270 | V53: 2722 | W53: 2843 | X53: -0.046062691 | Y53: 0.0036064917 | Z53: 0.011778798 | AA53: 0.040153907
B54: 4547 | C54: Japan | D54: =VLOOKUP(B54,기업리스트!$B:$G,2,FALSE) -> Kissei Pharmaceutical Co., Ltd. | E54: Sep'26 | F54: 3.9 | G54: 17697 | H54: 15296 | I54: 16285 | J54: 16579 | K54: 18771 | L54: 15858 | M54: 19313 | N54: 17665 | O54: 20881 | P54: 17720 | Q54: 21164 | R54: 21302 | S54: 23203 | T54: 22661 | U54: 22191 | V54: 23640 | W54: 26802 | X54: 0.059252419 | Y54: 0.011626854 | Z54: 0.02616471 | AA54: 0.039249686
B55: 2327 | C55: Japan | D55: =VLOOKUP(B55,기업리스트!$B:$G,2,FALSE) -> NS Solutions Corporation | E55: Sep'26 | F55: 3.7 | G55: 64831 | H55: 74714 | I55: 65132 | J55: 69552 | K55: 72094 | L55: 84908 | M55: 68773 | N55: 76000 | O55: 75345 | P55: 90513 | Q55: 76826 | R55: 79786 | S55: 83682 | T55: 98007 | U55: 82684 | V55: 95691 | W55: 97020 | X55: 0.022653692 | Y55: 0.017315941 | Z55: 0.046214105 | AA55: 0.037043415
B56: 9708 | C56: Japan | D56: =VLOOKUP(B56,기업리스트!$B:$G,2,FALSE) -> Imperial Hotel, Ltd. | E56: Sep'26 | F56: 3.6 | G56: 9435 | H56: 6892 | I56: 9434 | J56: 9173 | K56: 13082 | L56: 12083 | M56: 12472 | N56: 11766 | O56: 15528 | P56: 13569 | Q56: 13326 | R56: 11413 | S56: 14624 | T56: 13247 | U56: 13584 | V56: 11842 | W56: 16547 | X56: -0.0060832767 | Y56: 0.0049040106 | Z56: 0.0081145494 | AA56: 0.03608083
B57: 5844 | C57: Japan | D57: =VLOOKUP(B57,기업리스트!$B:$G,2,FALSE) -> Kyoto Financial Group,Inc. | E57: Sep'26 | F57: 3.6 | G57: 44138 | H57: 14686 | I57: 40416 | J57: 22321 | K57: 29984 | L57: 21488 | M57: 37856 | N57: 24361 | O57: 35514 | P57: 23192 | Q57: 35242 | R57: 28662 | S57: 38748 | T57: 29352 | U57: 42499 | V57: 41796 | W57: 44186 | X57: 0.048949493 | Y57: 0.054975607 | Z57: 0.094312119 | AA57: 0.035683585
B58: 9202 | C58: Japan | D58: =VLOOKUP(B58,기업리스트!$B:$G,2,FALSE) -> ANA Holdings Inc. | E58: Sep'26 | F58: 3.6 | G58: 306921 | H58: 282278 | I58: 350419 | J58: 440297 | K58: 467939 | L58: 448829 | M58: 461026 | N58: 541703 | O58: 540852 | P58: 512347 | Q58: 516775 | R58: 582812 | S58: 603197 | T58: 559072 | U58: 548701 | V58: 641699 | W58: 686984 | X58: 0.021093561 | Y58: 0.014114957 | Z58: 0.025672448 | AA58: 0.035613595
B59: 1950 | C59: Japan | D59: =VLOOKUP(B59,기업리스트!$B:$G,2,FALSE) -> Nippon Densetsu Kogyo Co., Ltd. | E59: Sep'26 | F59: 3.4 | G59: 41580 | H59: 68306 | I59: 25506 | J59: 35383 | K59: 40833 | L59: 70378 | M59: 28577 | N59: 42462 | O59: 46472 | P59: 76520 | Q59: 33011 | R59: 42614 | S59: 49388 | T59: 91909 | U59: 30234 | V59: 48185 | W59: 56872 | X59: 0.076359703 | Y59: -0.012801837 | Z59: 0.026015083 | AA59: 0.034062153
... B128: 2782 | C128: Japan | D128: =VLOOKUP(B128,기업리스트!$B:$G,2,FALSE) -> Seria Co., Ltd. | E128: Sep'26 | F128: -30.4 | G128: 52506 | H128: 51951 | I128: 56241 | J128: 51661 | K128: 53848 | L128: 53280 | M128: 166469 | N128: 166469 | O128: 56733 | P128: 58115 | Q128: 57784 | R128: 178047 | S128: 178047 | T128: 60214 | U128: 60498 | V128: 60884 | W128: 68716 | X128: 0.0044470999 | Y128: 0.0057246273 | Z128: -0.24572468 | AA128: -0.30399869
B129: RRKABEL | C129: India | D129: =VLOOKUP(B129,기업리스트!$B:$G,2,FALSE) -> R R Kabel Limited | E129: Sep'26 | F129: 9.2 | H129: 13974 | I129: 12359 | J129: 13672 | K129: 14795 | L129: 15165 | M129: 15973 | N129: 16097 | O129: 16335 | P129: 17541 | Q129: 18081 | R129: 18101 | S129: 17822 | T129: 22178 | U129: 20586 | V129: 21638 | W129: 25359 | X129: 0.064812356 | Y129: 0.032881783 | Z129: 0.044950246 | AA129: 0.091664234
B130: MSUMI | C130: India | D130: =VLOOKUP(B130,기업리스트!$B:$G,2,FALSE) -> Motherson Sumi Wiring India Limited | E130: Sep'26 | F130: 5.8 | G130: 14449 | H130: 16563 | I130: 16617 | J130: 18270 | K130: 16766 | L130: 18573 | M130: 18530 | N130: 20970 | O130: 21111 | P130: 22129 | Q130: 21660 | R130: 23230 | S130: 22823 | T130: 25003 | U130: 24808 | V130: 27539 | W130: 28658 | X130: 0.031989493 | Y130: 0.033953147 | Z130: 0.044949095 | AA130: 0.058249229
B131: AJANTPHARM | C131: India | D131: =VLOOKUP(B131,기업리스트!$B:$G,2,FALSE) -> Ajanta Pharma Limited | E131: Sep'26 | F131: 4.6 | G131: 8379 | H131: 8703 | I131: 9509 | J131: 9381 | K131: 9718 | L131: 8818 | M131: 10210 | N131: 10284 | O131: 11052 | P131: 10541 | Q131: 11449 | R131: 11866 | S131: 11461 | T131: 11704 | U131: 13027 | V131: 13537 | W131: 13748 | X131: 0.025663658 | Y131: 0.033950086 | Z131: 0.034770486 | AA131: 0.045989262
B132: INTELLECT | C132: India | D132: =VLOOKUP(B132,기업리스트!$B:$G,2,FALSE) -> Intellect Design Arena Limited | E132: Sep'26 | F132: 4.4 | G132: 5083 | H132: 5094 | I132: 5413 | J132: 5275 | K132: 5469 | L132: 6155 | M132: 6394 | N132: 6190 | O132: 6343 | P132: 6137 | Q132: 6063 | R132: 5581 | S132: 6096 | T132: 7259 | U132: 7017 | V132: 7581 | W132: 7314 | X132: 0.046990828 | Y132: 0.038161526 | Z132: 0.077062382 | AA132: 0.043573141
B133: JPPOWER | C133: India | D133: =VLOOKUP(B133,기업리스트!$B:$G,2,FALSE) -> Jaiprakash Power Ventures Limited | E133: Jun'26 | F133: 4 | G133: 9019 | H133: 14014 | I133: 14062 | J133: 18204 | K133: 13854 | L133: 12011 | M133: 13799 | N133: 17078 | O133: 13498 | P133: 21903 | Q133: 15148 | R133: 17547 | S133: 12264 | T133: 11402 | U133: 13409 | V133: 15832 | W133: 14383 | X133: -0.15705483 | Y133: -0.030854669 | Z133: -0.031397605 | AA133: 0.040051411
B134: AADHARHFC | C134: India | D134: =VLOOKUP(B134,기업리스트!$B:$G,2,FALSE) -> Aadhar Housing Finance Limited | E134: Jun'26 | F134: 4 | G134: 1642 | H134: 2111 | I134: 2613 | J134: 2658 | K134: 2658 | L134: 3395 | M134: 3395 | N134: 3263 | O134: 3739 | P134: 4102 | Q134: 4493 | R134: 4175 | S134: 4658 | T134: 4821 | U134: 5284 | V134: 4927 | W134: 5445 | X134: 0.041255451 | Y134: 0.043588472 | Z134: 0.039708523 | AA134: 0.039969528
B135: MEDPLUS | C135: India | D135: =VLOOKUP(B135,기업리스트!$B:$G,2,FALSE) -> MedPlus Health Services Limited | E135: Sep'26 | F135: 3.9 | G135: 9335 | H135: 9659 | I135: 9937 | J135: 11206 | K135: 11903 | L135: 12530 | M135: 12843 | N135: 14086 | O135: 14415 | P135: 14905 | Q135: 14888 | R135: 15762 | S135: 15614 | T135: 15096 | U135: 15426 | V135: 16793 | W135: 18061 | X135: 0.0031224967 | Y135: 0.008767927 | Z135: 0.016656435 | AA135: 0.038885093
B136: SUNPHARMA | C136: India | D136: =VLOOKUP(B136,기업리스트!$B:$G,2,FALSE) -> Sun Pharmaceutical Industries Limited | E136: Sep'26 | F136: 3.4 | G136: 98631 | H136: 94468 | I136: 107618 | J136: 109523 | K136: 112410 | L136: 109307 | M136: 119408 | N136: 121924 | O136: 123807 | P136: 119829 | Q136: 126528 | R136: 132914 | S136: 136755 | T136: 129588 | U136: 138514 | V136: 144783 | W136: 155205 | X136: 0.018911838 | Y136: 0.02279639 | Z136: 0.022070733 | AA136: 0.033567426
B137: ASTERDM | C137: India | D137: =VLOOKUP(B137,기업리스트!$B:$G,2,FALSE) -> Aster DM Healthcare Limited | E137: Sep'26 | F137: 3.1 | G137: 26496 | H137: 27278 | I137: 26621 | J137: 28163 | K137: 31921 | L137: 0 | M137: 32154 | N137: 33166 | O137: 37106 | P137: 0 | Q137: 10019 | R137: 10864 | S137: 10498 | T137: 10003 | U137: 10779 | V137: 11972 | W137: 11858 | X137: 0.31875976 | Y137: 0.018364585 | Z137: 0.026290812 | AA137: 0.031443633
B138: NIACL | C138: India | D138: =VLOOKUP(B138,기업리스트!$B:$G,2,FALSE) -> The New India Assurance Company Limited | E138: Sep'26 | F138: 2.9 | G138: 94626 | H138: 85666 | I138: 85774 | J138: 115793 | K138: 105488 | L138: 102627 | M138: 98889 | N138: 105568 | O138: 113564 | P138: 113262 | Q138: 104179 | R138: 107770 | S138: 107058 | T138: 110260 | U138: 117190 | V138: 134433 | W138: 120629 | X138: -0.0069447497 | Y138: 0.030309807 | Z138: 0.060285612 | AA138: 0.028939675
B139: JINDALSTEL | C139: India | D139: =VLOOKUP(B139,기업리스트!$B:$G,2,FALSE) -> Jindal Steel Limited | E139: Sep'26 | F139: 2.6 | G139: 125249 | H139: 143395 | I139: 130454 | J139: 135214 | K139: 124524 | L139: 136919 | M139: 125883 | N139: 122502 | O139: 117013 | P139: 134870 | Q139: 136178 | R139: 112133 | S139: 117507 | T139: 131832 | U139: 122945 | V139: 116859 | W139: 130266 | X139: -0.0060676509 | Y139: -0.026590978 | Z139: 0.0097560573 | AA139: 0.026084397
B140: POWERGRID | C140: India | D140: =VLOOKUP(B140,기업리스트!$B:$G,2,FALSE) -> Power Grid Corporation of India Limited | E140: Sep'26 | F140: 2.5 | G140: 104469 | H140: 106913 | I140: 109052 | J140: 111506 | K140: 112618 | L140: 122856 | M140: 110481 | N140: 112671 | O140: 115498 | P140: 119781 | Q140: 110062 | R140: 112778 | S140: 112330 | T140: 122754 | U140: 111962 | V140: 114760 | W140: 123951 | X140: 0.0065347697 | Y140: 0.0041491601 | Z140: 0.0043103448 | AA140: 0.025164246
B141: LALPATHLAB | C141: India | D141: =VLOOKUP(B141,기업리스트!$B:$G,2,FALSE) -> Dr. Lal PathLabs Limited | E141: Sep'26 | F141: 2.4 | G141: 4969 | H141: 4855 | I141: 5027 | J141: 5338 | K141: 4894 | L141: 4910 | M141: 5410 | N141: 6013 | O141: 5389 | P141: 5454 | Q141: 6019 | R141: 6602 | S141: 5967 | T141: 6026 | U141: 6698 | V141: 7306 | W141: 6598 | X141: 0.023791698 | Y141: 0.027585927 | Z141: 0.027833788 | AA141: 0.024272031
... B148: FINPIPE | C148: India | D148: =VLOOKUP(B148,기업리스트!$B:$G,2,FALSE) -> Finolex Industries Limited | E148: Sep'26 | F148: -2.5 | G148: 10053 | H148: 15934 | I148: 11898 | J148: 9411 | K148: 11248 | L148: 11411 | M148: 11792 | N148: 8832 | O148: 10197 | P148: 12354 | Q148: 11405 | R148: 8284 | S148: 10012 | T148: 11718 | U148: 10432 | V148: 8587 | W148: 8977 | X148: -0.015123053 | Y148: -0.023491634 | Z148: 0.0074914701 | AA148: -0.025399396
B149: CNR | C149: United States | D149: Thermal Coal | E149: Sep'25 | F149: 13.9 | G149: 295.56 | H149: 340.19 | I149: 539.5 | J149: 611.61 | K149: 533.61 | L149: 612.15 | M149: 680.88 | N149: 657.96 | O149: 564.52 | P149: 624.46 | Q149: 546.69 | R149: 490.72 | S149: 553.43 | T149: 573.17 | U149: 1017 | V149: 1102 | W149: 1003 | X149: -0.02315262 | Y149: 0.21733264 | Z149: 0.2320447 | AA149: 0.13851676
B150: LTM | C150: United States | D150: Airlines | E150: Sep'25 | F150: 4.2 | G150: 1276 | H150: 1940 | I150: 1917 | J150: 2176 | K150: 2558 | L150: 2712 | M150: 2772 | N150: 2633 | O150: 3025 | P150: 3212 | Q150: 3267 | R150: 2983 | S150: 3245 | T150: 3337 | U150: 3348 | V150: 3243 | W150: 3799 | X150: 0.0098370977 | Y150: 0.0063123441 | Z150: 0.020134748 | AA150: 0.04205572
B151: HMN | C151: United States | D151: Insurance - Property & Casualty | E151: Sep'25 | F151: 1.6 | G151: 329.6 | H151: 331.4 | I151: 346.7 | J151: 345.9 | K151: 342.6 | L151: 346.4 | M151: 353.9 | N151: 356.4 | O151: 378.7 | P151: 402.9 | Q151: 386 | R151: 388.1 | S151: 412.1 | T151: 409 | U151: 416.4 | V151: 411.7 | W151: 438.5 | X151: 0.0038386508 | Y151: 0.019057172 | Z151: 0.014517717 | AA151: 0.016007761
B152: LYB | C152: United States | D152: Specialty Chemicals | E152: Sep'25 | F152: -2.6 | G152: 12700 | H152: 12830 | I152: 13157 | J152: 14838 | K152: 12250 | L152: 10206 | M152: 10247 | N152: 10306 | O152: 10625 | P152: 9929 | Q152: 8304 | R152: 8678 | S152: 8604 | T152: 9497 | U152: 7677 | V152: 7658 | W152: 7727 | X152: -0.012163874 | Y152: -0.017871904 | Z152: -0.029602972 | AA152: -0.026229214
B153: 5191 | C153: Japan | D153: N/A | E153: Sep'25 | F153: 1.6 | G153: 98585 | H153: 113172 | I153: 124442 | J153: 117255 | K153: 138354 | L153: 139497 | M153: 145904 | N153: 145637 | O153: 152241 | P153: 159243 | Q153: 158328 | R153: 157615 | S153: 151554 | T153: 162102 | U153: 162060 | V153: 154783 | W153: 161550 | X153: 0.0045617002 | Y153: 0.0059275825 | Z153: -0.0044715954 | AA153: 0.015854109
B154: JLHL | C154: Unknown | D154: Building Products & Equipment | E154: H1 2025 | F154: 22.2 | S154: 37.25 | T154: 81.84 | U154: 92.85 | V154: 80.8 | W154: 102.18 | AA154: 0.22180092
B155: BAIN | C155: France | D155: =VLOOKUP(B155,기업리스트!$B:$G,2,FALSE) -> Société Anonyme des Bains de Mer et du Cercle des Étrangers à Monaco | E155: H1 2026 | F155: 6.6 | N155: 168.13 | O155: 311.41 | P155: 219.1 | Q155: 432.35 | R155: 234.64 | S155: 445.57 | T155: 258.43 | U155: 495.14 | V155: 272.88 | W155: 542.46 | X155: 0.029534566 | Y155: 0.045799021 | Z155: 0.026670758 | AA155: 0.065821117

Sheet Operating Income
B2: Ticker | C2: Country | D2: Industry | E2: Latest_Date | F2: Growth_Rate | G2: 4Q21 | H2: 1Q22 | I2: 2Q22 | J2: 3Q22 | K2: 4Q22 | L2: 1Q23 | M2: 2Q23 | N2: 3Q23 | O2: 4Q23 | P2: 1Q24 | Q2: 2Q24 | R2: 3Q24 | S2: 4Q24 | T2: 1Q25 | U2: 2Q25 | V2: 3Q25 | W2: 4Q25 | X2: 1Q25 | Y2: 2Q25 | Z2: 3Q25 | AA2: 4Q25
B3: TMP | C3: United States | D3: Banks - Regional | E3: Dec'25 | F3: 102.8 | G3: 24.9 | H3: 30.28 | I3: 27.23 | J3: 28.15 | K3: 24.06 | L3: 25.31 | M3: 10.29 | N3: -41.63 | O3: 18.15 | P3: 22.1 | Q3: 20.62 | R3: 24.53 | S3: 25.73 | T3: 25.8 | U3: 28.24 | V3: 31.11 | W3: 139.71 | X3: 0.039793504 | Y3: 0.078816715 | Z3: 0.063087248 | AA3: 1.0279582
B4: LPG | C4: United States | D4: Oil & Gas Midstream | E4: Jun'26 | F4: 55.3 | G4: 15.65 | H4: 22.55 | I4: 33.69 | J4: 28.95 | K4: 28.14 | L4: 57.49 | M4: 83.78 | N4: 55.62 | O4: 80.49 | P4: 110.34 | Q4: 82.38 | R4: 55.47 | S4: 19.1 | T4: 23.38 | U4: 14.69 | V4: 15.59 | W4: 59.34 | X4: -0.32533952 | Y4: -0.37536738 | Z4: -0.3540483 | AA4: 0.55305113
B5: JHG | C5: United States | D5: Asset Management | E5: Dec'25 | F5: 42.7 | G5: 235.1 | H5: 157.4 | I5: 143.9 | J5: 120.7 | K5: 103.6 | L5: 100.4 | M5: 117.9 | N5: 121.7 | O5: 143.7 | P5: 119.2 | Q5: 164.3 | R5: 164.7 | S5: 192.8 | T5: 153.6 | U5: 163.8 | V5: 180.1 | W5: 487.4 | X5: 0.053666147 | Y5: -0.00074030204 | Z5: 0.022818195 | AA5: 0.42677097
B6: MCHB | C6: United States | D6: Banks - Regional | E6: Dec'25 | F6: 37.3 | P6: -157.4 | Q6: 70.42 | R6: 55.48 | S6: 67.19 | T6: 61.46 | U6: 59.04 | V6: 45.1 | W6: 153.95 | X6: 6.1322499 | Y6: -0.044706345 | Z6: -0.042686187 | AA6: 0.37269642
B7: SOFI | C7: United States | D7: Credit Services | E7: Dec'25 | F7: 31.3 | G7: -107.35 | H7: -93.07 | I7: -94.91 | J7: -74.35 | K7: -37.08 | L7: -36.06 | M7: -49.15 | N7: -19.75 | O7: 51.3 | P7: 94.23 | Q7: 15.34 | R7: 63.86 | S7: 59.92 | T7: 79.78 | U7: 112.19 | V7: 148.55 | W7: 185.33 | X7: -0.061924148 | Y7: 0.44243947 | Z7: 0.26821853 | AA7: 0.3131805
B8: OPY | C8: United States | D8: Capital Markets | E8: Dec'25 | F8: 29.3 | G8: 141.12 | H8: 35.23 | I8: 13.94 | J8: 64.3 | K8: 75.63 | L8: 57.64 | M8: 56.36 | N8: 51.32 | O8: 66.17 | P8: 64.61 | Q8: 40.93 | R8: 63.35 | S8: 66.09 | T8: 69.4 | U8: 62.75 | V8: 62.96 | W8: 142.59 | X8: 0.020384714 | Y8: 0.091003879 | Z8: -0.0014908827 | AA8: 0.29287902
B9: WT | C9: United States | D9: Asset Management | E9: Dec'25 | F9: 16.3 | G9: 22.56 | H9: 17.69 | I9: 15.8 | J9: 14.87 | K9: 11.72 | L9: 16.57 | M9: 18.18 | N9: 26.71 | O9: 26.04 | P9: 27.95 | Q9: 33.51 | R9: 40.79 | S9: 35.04 | T9: 34.16 | U9: 36.6 | V9: 48.06 | W9: 60.06 | X9: 0.045232719 | Y9: 0.021533101 | Z9: 0.049594106 | AA9: 0.16261536
B10: BDL | C10: United States | D10: Restaurants | E10: Dec'25 | F10: 13.6 | G10: 1.98 | H10: 0.77 | I10: 1.85 | J10: 2.08 | K10: 2.23 | L10: 1.2 | M10: 2.71 | N10: 2.7 | O10: 0.42 | P10: 0.79 | Q10: 2.69 | R10: 2.29 | S10: 0.63 | T10: 0.86 | U10: 3.64 | V10: 2.97 | W10: 1.73 | X10: 0.0109375 | Y10: 0.14683153 | Z10: 0.091644205 | AA10: 0.13580247
B11: BEPC | C11: United States | D11: Utilities - Renewable | E11: Dec'25 | F11: 11.5 | G11: 264 | H11: 354 | I11: 378 | J11: 287 | K11: 330 | L11: 433 | M11: 273 | N11: 295 | O11: 70 | P11: 299 | Q11: 212 | R11: 293 | S11: 107 | T11: 232 | U11: 231 | V11: 222 | W11: 198 | X11: -0.073545554 | Y11: 0.022511848 | Z11: -0.082271147 | AA11: 0.11489899
B12: FHB | C12: United States | D12: Banks - Regional | E12: Dec'25 | F12: 8.7 | G12: 70.15 | H12: 76.96 | I12: 79.11 | J12: 92.08 | K12: 103.07 | L12: 88.9 | M12: 81.41 | N12: 76.36 | O12: 62.5 | P12: 70.69 | Q12: 80.73 | R12: 76.45 | S12: 64.74 | T12: 76.94 | U12: 88.1 | V12: 96.15 | W12: 93.05 | X12: 0.021359489 | Y12: 0.024660376 | Z12: 0.064330732 | AA12: 0.086859142
B13: SAIL | C13: United States | D13: Software - Infrastructure | E13: Sep'26 | F13: 6.1 | P13: -65.16 | Q13: -68.19 | R13: -65.83 | S13: -24.5 | T13: -30.21 | U13: -184.97 | V13: -39.19 | W13: -41.62 | X13: -0.15625 | Y13: 0.61876755 | Z13: -0.087198455 | AA13: 0.061390612
B14: IESC | C14: United States | D14: Engineering & Construction | E14: Mar'26 | F14: 6 | G14: 20.33 | H14: -4.92 | I14: 15.71 | J14: 25.1 | K14: 27.67 | L14: 31.58 | M14: 33.31 | N14: 56.96 | O14: 57.95 | P14: 76.34 | Q14: 90.09 | R14: 75.52 | S14: 74.99 | T14: 92.83 | U14: 112.26 | V14: 104.44 | W14: 98.2 | X14: 0.052028775 | Y14: 0.066490718 | Z14: 0.081327334 | AA14: 0.06036097
B15: RRBI | C15: United States | D15: Banks - Regional | E15: Dec'25 | F15: 5.3 | G15: 10.28 | H15: 8.92 | I15: 11.29 | J15: 12.31 | K15: 12.46 | L15: 11.76 | M15: 11.09 | N15: 9.89 | O15: 10.21 | P15: 10.12 | Q15: 9.9 | R15: 10.82 | S15: 11.54 | T15: 12.84 | U15: 12.72 | V15: 13.37 | W15: 14.19 | X15: 0.064181218 | Y15: 0.062527716 | Z15: 0.053213689 | AA15: 0.052506439
B16: GNTX | C16: United States | D16: Auto Parts | E16: Dec'25 | F16: 4.6 | G16: 87.96 | H16: 103.31 | I16: 85.79 | J16: 86.79 | K16: 94.12 | L16: 113.25 | M16: 127.29 | N16: 122.42 | O16: 132.77 | P16: 129.35 | Q16: 114.88 | R16: 125.73 | S16: 98.63 | T16: 115.88 | U16: 125.3 | V16: 122.85 | W16: 120.1 | X16: -0.028745812 | Y16: 0.022895061 | Z16: -0.0061863642 | AA16: 0.046405568
B17: CHD | C17: United States | D17: Household & Personal Products | E17: Dec'25 | F17: 2.9 | G17: 187.7 | H17: 280.7 | I17: 261.6 | J17: 253.9 | K17: 212.6 | L17: 291.9 | M17: 293.6 | N17: 255.8 | O17: 216.1 | P17: 305 | Q17: 336.9 | R17: 265.6 | S17: 256.7 | T17: 295.3 | U17: 312.7 | V17: 254.6 | W17: 289.7 | X17: -0.0083319017 | Y17: -0.020961455 | Z17: -0.0097319296 | AA17: 0.029482712
B18: TOWN | C18: United States | D18: Banks - Regional | E18: Dec'25 | F18: 2.6 | G18: 51.07 | H18: 57.48 | I18: 58.2 | J18: 63.28 | K18: 58.09 | L18: 48.08 | M18: 52.78 | N18: 54.16 | O18: 31.21 | P18: 42.39 | Q18: 51.16 | R18: 48.72 | S18: 48.11 | T18: 59.09 | U18: 50.37 | V18: 46.65 | W18: 53.49 | X18: 0.087719298 | Y18: -0.0038149507 | Z18: -0.010034418 | AA18: 0.026344139
B19: BBU | C19: United States | D19: Conglomerates | E19: Dec'25 | F19: 2.1 | G19: 750 | H19: 538 | I19: 623 | J19: 801 | K19: 953 | L19: 891 | M19: 778 | N19: 980 | O19: 860 | P19: 820 | Q19: 711 | R19: 1844 | S19: 1095 | T19: 1036 | U19: 959 | V19: 978 | W19: 1182 | X19: 0.048322148 | Y19: 0.052923602 | Z19: -0.17551682 | AA19: 0.021386431
B20: AXP | C20: United States | D20: Credit Services | E20: Dec'25 | F20: 1.9 | G20: 2535 | H20: 2723 | I20: 2554 | J20: 2483 | K20: 2258 | L20: 2257 | M20: 2719 | N20: 3091 | O20: 2667 | P20: 3129 | Q20: 3176 | R20: 3199 | S20: 2833 | T20: 3354 | U20: 3455 | V20: 3780 | W20: 3090 | X20: 0.018237821 | Y20: 0.022209839 | Z20: 0.045245697 | AA20: 0.019147668
B21: CL | C21: United States | D21: Household & Personal Products | E21: Dec'25 | F21: 1.2 | G21: 906 | H21: 904 | I21: 880 | J21: 904 | K21: 894 | L21: 913 | M21: 966 | N21: 1016 | O21: 1047 | P21: 1061 | Q21: 1097 | R21: 1057 | S21: 1035 | T21: 1069 | U21: 1066 | V21: 1038 | W21: 1085 | X21: 0.0018823529 | Y21: -0.0072804133 | Z21: -0.0044949137 | AA21: 0.011882129
B22: CHTR | C22: United States | D22: Telecom Services | E22: Dec'25 | F22: -0.5 | G22: 3130 | H22: 2789 | I22: 3182 | J22: 3333 | K22: 3193 | L22: 2938 | M22: 3183 | N22: 3157 | O22: 3012 | P22: 3094 | Q22: 3343 | R22: 3358 | S22: 3427 | T22: 3360 | U22: 3360 | V22: 3262 | W22: 3365 | X22: 0.020117985 | Y22: 0.0012603796 | Z22: -0.0071084783 | AA22: -0.0046237602
B23: ALV | C23: United States | D23: Auto Parts | E23: Dec'25 | F23: -1.5 | G23: 177 | H23: 56 | I23: 102 | J23: 172 | K23: 224 | L23: 128 | M23: 198 | N23: 235 | O23: 544 | P23: 195 | Q23: 220 | R23: 234 | S23: 353 | T23: 242 | U23: 249 | V23: 269 | W23: 336 | X23: 0.046906188 | Y23: 0.027645377 | Z23: 0.032467532 | AA23: -0.015274034
B24: XOM | C24: United States | D24: Oil & Gas Integrated | E24: Dec'25 | F24: -1.6 | G24: 11128 | H24: 9181 | I24: 21439 | J24: 21696 | K24: 13738 | L24: 14581 | M24: 9247 | N24: 11678 | O24: 11541 | P24: 9918 | Q24: 10862 | R24: 11009 | S24: 8350 | T24: 9733 | U24: 8821 | V24: 9214 | W24: 7780 | X24: -0.0046089838 | Y24: -0.051083746 | Z24: -0.047345238 | AA24: -0.015781605
B25: APD | C25: United States | D25: Specialty Chemicals | E25: Mar'26 | F25: -2.5 | G25: 535.3 | H25: 573.9 | I25: 634.8 | J25: 0 | K25: 632.8 | L25: 623 | M25: 681.5 | N25: 0 | O25: 645.1 | P25: 609.1 | Q25: 710.5 | R25: 0 | S25: 659 | T25: -2310 | U25: 734.4 | V25: -2824 | W25: 753.3 | X25: -1.4753361 | Y25: -0.025412015 | Z25: 3.0809513 | AA25: -0.025209859
... B33: FLG | C33: United States | D33: Banks - Regional | E33: Dec'25 | F33: -58.8 | G33: 199 | H33: 207 | I33: 230 | J33: 205 | K33: 184 | L33: 2007 | M33: 492 | N33: 268 | O33: -2817 | P33: -381 | Q33: -424 | R33: -335 | S33: -238 | T33: -121 | U33: -81 | V33: -41 | W33: 45 | X33: -0.18867925 | Y33: -0.30679785 | Z33: -0.37935484 | AA33: -0.58835759
B34: 9708 | C34: Japan | D34: =VLOOKUP(B34,기업리스트!$B:$G,2,FALSE) -> Imperial Hotel, Ltd. | E34: Sep'26 | F34: 40.4 | G34: -1347 | H34: -4311 | I34: -551 | J34: -462 | K34: 1553 | L34: -191 | M34: 748 | N34: 20 | O34: 2256 | P34: -183 | Q34: 630 | R34: -556 | S34: 1503 | T34: 14 | U34: 763 | V34: -443 | W34: 2245 | X34: 0.14131994 | Y34: 0.083595223 | Z34: 0.065545244 | AA34: 0.40391943
B35: 3189 | C35: Japan | D35: =VLOOKUP(B35,기업리스트!$B:$G,2,FALSE) -> Kinsus Interconnect Technology Corp. | E35: Mar'26 | F35: 29.6 | G35: 7 | H35: -23 | I35: -257 | J35: -204 | K35: -160 | L35: -61 | M35: -188 | N35: -5 | O35: -171 | P35: -155 | Q35: -216 | R35: -169 | S35: -200 | T35: -200 | U35: -303 | V35: -620 | W35: -592 | X35: 0.060810811 | Y35: 0.11082803 | Z35: 0.51720183 | AA35: 0.2962963
B36: 6961 | C36: Japan | D36: =VLOOKUP(B36,기업리스트!$B:$G,2,FALSE) -> Enplas Corporation | E36: Sep'26 | F36: 28.5 | G36: 564 | H36: 1382 | I36: 1959 | J36: 2397 | K36: 2710 | L36: 1754 | M36: 1412 | N36: 1205 | O36: 939 | P36: 1090 | Q36: 2154 | R36: 1201 | S36: 729 | T36: 1204 | U36: 906 | V36: 2146 | W36: 2149 | X36: 0.022033243 | Y36: -0.23600605 | Z36: 0.23391089 | AA36: 0.28485456
B37: 6946 | C37: Japan | D37: =VLOOKUP(B37,기업리스트!$B:$G,2,FALSE) -> Nippon Avionics Co., Ltd. | E37: Sep'26 | F37: 24.2 | G37: 373 | H37: 527 | I37: 34 | J37: 545 | K37: 566 | L37: 807 | M37: 276 | N37: 635 | O37: 599 | P37: 669 | Q37: 325 | R37: 825 | S37: 516 | T37: 1131 | U37: 583 | V37: 1395 | W37: 1393 | X37: 0.19785867 | Y37: 0.092241688 | Z37: 0.18657938 | AA37: 0.24193103
B38: 1950 | C38: Japan | D38: =VLOOKUP(B38,기업리스트!$B:$G,2,FALSE) -> Nippon Densetsu Kogyo Co., Ltd. | E38: Sep'26 | F38: 18.6 | G38: 2334 | H38: 6659 | I38: -1798 | J38: 578 | K38: 1284 | L38: 9596 | M38: -1274 | N38: 1596 | O38: 2842 | P38: 10285 | Q38: -773 | R38: 1113 | S38: 3369 | T38: 14226 | U38: -858 | V38: 3581 | W38: 7143 | X38: 0.28162069 | Y38: -0.0047393365 | Z38: 0.13826331 | AA38: 0.18574663
B39: 6727 | C39: Japan | D39: =VLOOKUP(B39,기업리스트!$B:$G,2,FALSE) -> Wacom Co., Ltd. | E39: Sep'26 | F39: 18 | G39: 4781 | H39: 683 | I39: 1846 | J39: 437 | K39: 2014 | L39: -2284 | M39: 847 | N39: 1610 | O39: 2812 | P39: 1789 | Q39: 2525 | R39: 2951 | S39: 2127 | T39: 2607 | U39: 2730 | V39: 3125 | W39: 4030 | X39: 0.0870954 | Y39: 0.020078355 | Z39: 0.016706673 | AA39: 0.1797148
B40: 9997 | C40: Japan | D40: =VLOOKUP(B40,기업리스트!$B:$G,2,FALSE) -> Belluna Co., Ltd. | E40: Sep'26 | F40: 17 | G40: 5458 | H40: 3603 | I40: 1754 | J40: 1925 | K40: 4181 | L40: 3337 | M40: 1158 | N40: 1928 | O40: 2623 | P40: 4057 | Q40: 983 | R40: 2577 | S40: 3765 | T40: 4541 | U40: 1592 | V40: 3274 | W40: 6004 | X40: 0.042523282 | Y40: 0.051323108 | Z40: 0.055871743 | AA40: 0.16998178
B41: 6777 | C41: Japan | D41: =VLOOKUP(B41,기업리스트!$B:$G,2,FALSE) -> santec Holdings Corporation | E41: Sep'26 | F41: 15.1 | G41: 378 | H41: 633 | I41: 867 | J41: 864 | K41: 916 | L41: 1336 | M41: 785 | N41: 968 | O41: 1292 | P41: 2519 | Q41: 2045 | R41: 1820 | S41: 1558 | T41: 2006 | U41: 2077 | V41: 2043 | W41: 2718 | X41: -0.064593301 | Y41: 0.0043074438 | Z41: 0.029888755 | AA41: 0.15096304
B42: 6331 | C42: Japan | D42: =VLOOKUP(B42,기업리스트!$B:$G,2,FALSE) -> Mitsubishi Kakoki Kaisha, Ltd. | E42: Sep'26 | F42: 14.9 | G42: 68 | H42: 1334 | I42: 344 | J42: 1560 | K42: 200 | L42: 418 | M42: 336 | N42: 1842 | O42: 1128 | P42: 1106 | Q42: 1101 | R42: 1165 | S42: 1363 | T42: 2067 | U42: 1442 | V42: 2240 | W42: 2424 | X42: 0.20295671 | Y42: 0.059866573 | Z42: 0.17806858 | AA42: 0.14918448
B43: 2127 | C43: Japan | D43: =VLOOKUP(B43,기업리스트!$B:$G,2,FALSE) -> Nihon M&A Center Holdings Inc. | E43: Sep'26 | F43: 13.6 | G43: 3993 | H43: 888 | I43: 3617 | J43: 4382 | K43: 3117 | L43: 4182 | M43: 1716 | N43: 4388 | O43: 5130 | P43: 4833 | Q43: 1603 | R43: 4322 | S43: 4628 | T43: 6162 | U43: 2510 | V43: 5889 | W43: 7243 | X43: 0.086377226 | Y43: 0.054262638 | Z43: 0.088922937 | AA43: 0.13627599
B44: 9202 | C44: Japan | D44: =VLOOKUP(B44,기업리스트!$B:$G,2,FALSE) -> ANA Holdings Inc. | E44: Sep'26 | F44: 12.8 | G44: 190 | H44: -57310 | I44: -1321 | J44: 32768 | K44: 67535 | L44: 21048 | M44: 43784 | N44: 85953 | O44: 80377 | P44: -2203 | Q44: 30354 | R44: 78020 | S44: 59261 | T44: 29004 | U44: 36786 | V44: 60842 | W44: 83086 | X44: 0.18863944 | Y44: 0.032709686 | Z44: -0.084591104 | AA44: 0.12816513
B45: 7327 | C45: Japan | D45: =VLOOKUP(B45,기업리스트!$B:$G,2,FALSE) -> Daishi Hokuetsu Financial Group, Inc. | E45: Sep'26 | F45: 12.5 | G45: 5476 | H45: 6490 | I45: 11503 | J45: 6157 | K45: 3822 | L45: 3467 | M45: 14772 | N45: 4286 | O45: 6881 | P45: 3818 | Q45: 15101 | R45: 5519 | S45: 9208 | T45: 11346 | U45: 17701 | V45: 14472 | W45: 15779 | X45: 0.22374131 | Y45: 0.063146646 | Z45: 0.2045278 | AA45: 0.12462306
... B117: 9507 | C117: Japan | D117: =VLOOKUP(B117,기업리스트!$B:$G,2,FALSE) -> Shikoku Electric Power Company, Incorporated | E117: Sep'26 | F117: -11.3 | G117: -15795 | H117: 1079 | I117: 2839 | J117: 7721 | K117: -11363 | L117: -11483 | M117: 16660 | N117: 48791 | O117: 13125 | P117: -49 | Q117: 30764 | R117: 22818 | S117: 11754 | T117: 23737 | U117: 33153 | V117: 43662 | W117: -967 | X117: 0.36432981 | Y117: 0.026820698 | Z117: 0.22789792 | AA117: -0.11327088
B118: 6526 | C118: Japan | D118: =VLOOKUP(B118,기업리스트!$B:$G,2,FALSE) -> Socionext Inc. | E118: Sep'26 | F118: -12.6 | I118: 5594 | J118: 4862 | K118: 6292 | L118: 4963 | M118: 10109 | N118: 8567 | O118: 9268 | P118: 7566 | Q118: 10265 | R118: 5291 | S118: 5104 | T118: 4340 | U118: 1440 | V118: 2327 | W118: 3437 | X118: -0.11429179 | Y118: -0.353 | Z118: -0.18324575 | AA118: -0.12618273
B119: 4216 | C119: Japan | D119: =VLOOKUP(B119,기업리스트!$B:$G,2,FALSE) -> Asahi Yukizai Corporation | E119: Sep'26 | F119: -13.6 | G119: 2317 | H119: 1766 | I119: 2069 | J119: 3271 | K119: 3132 | L119: 3476 | M119: 4074 | N119: 4216 | O119: 4165 | P119: 3120 | Q119: 2803 | R119: 3084 | S119: 2846 | T119: 2388 | U119: 2152 | V119: 2200 | W119: 1538 | X119: -0.061756517 | Y119: -0.058537901 | Z119: -0.08443171 | AA119: -0.13644899
B120: 9301 | C120: Japan | D120: =VLOOKUP(B120,기업리스트!$B:$G,2,FALSE) -> Mitsubishi Logistics Corporation | E120: Sep'26 | F120: -13.8 | G120: 5237 | H120: 5129 | I120: 6119 | J120: 5611 | K120: 6386 | L120: 4913 | M120: 4899 | N120: 5023 | O120: 5859 | P120: 3161 | Q120: 4069 | R120: 4928 | S120: 7164 | T120: 4151 | U120: 3964 | V120: 3578 | W120: 4554 | X120: 0.051236932 | Y120: -0.005169358 | Z120: -0.066808532 | AA120: -0.13841014
B121: 6080 | C121: Japan | D121: =VLOOKUP(B121,기업리스트!$B:$G,2,FALSE) -> M&A Capital Partners Co.,Ltd. | E121: Mar'26 | F121: -14.2 | G121: 2572 | H121: 1694 | I121: 2481 | J121: 2966 | K121: 330 | L121: 5142 | M121: 342 | N121: 1636 | O121: 592 | P121: 1073 | Q121: 1223 | R121: 3486 | S121: 3345 | T121: 888.8 | U121: 1403 | V121: 2311 | W121: 2216 | X121: -0.020181878 | Y121: 0.020127924 | Z121: -0.12879818 | AA121: -0.14205189
B122: 8871 | C122: Japan | D122: =VLOOKUP(B122,기업리스트!$B:$G,2,FALSE) -> GOLDCREST Co.,Ltd. | E122: Sep'26 | F122: -14.2 | G122: 8296 | H122: 859 | I122: 8766 | J122: 1205 | K122: 261 | L122: 323 | M122: -211 | N122: 594 | O122: 1040 | P122: 4313 | Q122: 1770 | R122: 1878 | S122: 3200 | T122: 671 | U122: 3820 | V122: 1411 | W122: 1903 | X122: -0.32631485 | Y122: 0.27264264 | Z122: -0.048803428 | AA122: -0.14249615
B123: 8892 | C123: Japan | D123: =VLOOKUP(B123,기업리스트!$B:$G,2,FALSE) -> ES-CON JAPAN Ltd. | E123: Sep'26 | F123: -17.3 | G123: 2286 | H123: 5533 | I123: 864 | J123: 4778 | K123: 571 | L123: 9280 | M123: 4880 | N123: 1964 | O123: 1246 | P123: 8754 | Q123: 3290 | R123: 1026 | S123: 9437 | T123: 7559 | U123: 2184 | V123: 2722 | W123: 5641 | X123: -0.053094593 | Y123: -0.051895646 | Z123: 0.083935465 | AA123: -0.17331751
B124: 6737 | C124: Japan | D124: =VLOOKUP(B124,기업리스트!$B:$G,2,FALSE) -> EIZO Corporation | E124: Sep'26 | F124: -19.2 | G124: 1800 | H124: 2890 | I124: 878 | J124: 1335 | K124: 490 | L124: 2300 | M124: 1059 | N124: 578 | O124: 923 | P124: 1349 | Q124: 39 | R124: 792 | S124: 1338 | T124: 1538 | U124: -115 | V124: 776 | W124: 659 | X124: 0.053723707 | Y124: -0.041543027 | Z124: -0.0045032367 | AA124: -0.1919706
B125: 2782 | C125: Japan | D125: =VLOOKUP(B125,기업리스트!$B:$G,2,FALSE) -> Seria Co., Ltd. | E125: Sep'26 | F125: -22.9 | G125: 4374 | H125: 3679 | I125: 4822 | J125: 2571 | K125: 3146 | L125: 3035 | M125: 11258 | N125: 11258 | O125: 3863 | P125: 3968 | Q125: 3680 | R125: 13166 | S125: 13166 | T125: 4595 | U125: 4146 | V125: 4206 | W125: 7195 | X125: 0.018452031 | Y125: 0.013465484 | Z125: -0.25546717 | AA125: -0.22866005
B126: 4547 | C126: Japan | D126: =VLOOKUP(B126,기업리스트!$B:$G,2,FALSE) -> Kissei Pharmaceutical Co., Ltd. | E126: Sep'26 | F126: -24.6 | G126: -564 | H126: -1109 | I126: 131 | J126: -772 | K126: 1120 | L126: -1622 | M126: 1634 | N126: 383 | O126: 2148 | P126: -148 | Q126: 2158 | R126: -376 | S126: 2456 | T126: 1536 | U126: 2109 | V126: -8946 | W126: 3155 | X126: 0.41173594 | Y126: -0.008486318 | Z126: -1.4969432 | AA126: -0.2456942
B127: 6104 | C127: Japan | D127: =VLOOKUP(B127,기업리스트!$B:$G,2,FALSE) -> Shibaura Machine Co.,Ltd. | E127: Sep'26 | F127: -62.9 | G127: 683 | H127: 1176 | I127: 423 | J127: 1249 | K127: 1670 | L127: 2425 | M127: 2626 | N127: 5539 | O127: 1491 | P127: 3959 | Q127: 3956 | R127: 4479 | S127: 4682 | T127: 979 | U127: 923 | V127: 1115 | W127: -162 | X127: -0.17451394 | Y127: -0.21516742 | Z127: -0.30407665 | AA127: -0.62917262
B128: 8585 | C128: Japan | D128: =VLOOKUP(B128,기업리스트!$B:$G,2,FALSE) -> Orient Corporation | E128: Sep'26 | F128: -115.8 | G128: 6509 | H128: 8878 | I128: 5325 | J128: 9856 | K128: 1170 | L128: 6719 | M128: 3501 | N128: 2404 | O128: 4143 | P128: 6071 | Q128: 9960 | R128: -2785 | S128: 6648 | T128: -11649 | U128: 9314 | V128: -2110 | W128: 4098 | X128: -0.89072082 | Y128: -0.29714811 | Z128: 0.44175393 | AA128: -1.1575125
B129: NIACL | C129: India | D129: =VLOOKUP(B129,기업리스트!$B:$G,2,FALSE) -> The New India Assurance Company Limited | E129: Sep'26 | F129: 33.6 | G129: 6982 | H129: -9658 | I129: 2623 | J129: 27295 | K129: 15257 | L129: 2016 | M129: 4434 | N129: -1341 | O129: 9832 | P129: 1327 | Q129: 2912 | R129: 1401 | S129: 1764 | T129: 4520 | U129: 3545 | V129: 1311 | W129: 5512 | X129: 0.43125338 | Y129: 0.059733887 | Z129: -0.0080142476 | AA129: 0.33644524
B130: RRKABEL | C130: India | D130: =VLOOKUP(B130,기업리스트!$B:$G,2,FALSE) -> R R Kabel Limited | E130: Sep'26 | F130: 16.1 | H130: 650.83 | I130: 254.93 | J130: 494.36 | K130: 1010 | L130: 866.53 | M130: 968.62 | N130: 1043 | O130: 960.73 | P130: 1003 | Q130: 787.48 | R130: 683.07 | S130: 927.43 | T130: 1759 | U130: 1218 | V130: 1539 | W130: 1804 | X130: 0.22228887 | Y130: 0.10356557 | Z130: 0.18657875 | AA130: 0.16103266
B131: FINPIPE | C131: India | D131: =VLOOKUP(B131,기업리스트!$B:$G,2,FALSE) -> Finolex Industries Limited | E131: Sep'26 | F131: 10.9 | G131: 2207 | H131: 2526 | I131: 1046 | J131: -1642 | K131: 693.7 | L131: 2262 | M131: 1181 | N131: 756 | O131: 923.3 | P131: 1823 | Q131: 1806 | R131: -158.6 | S131: 561.2 | T131: 1471 | U131: 669.8 | V131: 1027 | W131: 965.9 | X131: -0.087310249 | Y131: -0.30878356 | Z131: 0.46614768 | AA131: 0.10852776
B132: JPPOWER | C132: India | D132: =VLOOKUP(B132,기업리스트!$B:$G,2,FALSE) -> Jaiprakash Power Ventures Limited | E132: Jun'26 | F132: 7 | G132: 962.2 | H132: 2432 | I132: 1626 | J132: 5127 | K132: 1390 | L132: -1073 | M132: 1570 | N132: 4063 | O132: 2944 | P132: 4600 | Q132: 6111 | R132: 6724 | S132: 2660 | T132: 1735 | U132: 3070 | V132: 4840 | W132: 3516 | X132: -0.14257278 | Y132: -0.17649449 | Z132: -0.13277891 | AA132: 0.069565217
B133: MEDPLUS | C133: India | D133: =VLOOKUP(B133,기업리스트!$B:$G,2,FALSE) -> MedPlus Health Services Limited | E133: Sep'26 | F133: 5.3 | G133: 309.48 | H133: 278.63 | I133: 145.46 | J133: 177.96 | K133: 259.34 | L133: 378.09 | M133: 189.29 | N133: 296.18 | O133: 346.69 | P133: 590.53 | Q133: 337.33 | R133: 613.04 | S133: 700.55 | T133: 851.46 | U133: 651.12 | V133: 802.85 | W133: 858.75 | X133: 0.11641125 | Y133: 0.12539662 | Z133: 0.06740005 | AA133: 0.052628427
B134: AEGISLOG | C134: India | D134: =VLOOKUP(B134,기업리스트!$B:$G,2,FALSE) -> Aegis Logistics Limited | E134: Sep'26 | F134: 4.8 | G134: 1284 | H134: 1241 | I134: 556 | J134: 1353 | K134: 1817 | L134: 1795 | M134: 1626 | N134: 1742 | O134: 1773 | P134: 2736 | Q134: 1955 | R134: 1866 | S134: 1956 | T134: 3753 | U134: 1982 | V134: 2385 | W134: 2444 | X134: 0.11946435 | Y134: 0.0028331584 | Z134: 0.054305744 | AA134: 0.048431917
B135: AJANTPHARM | C135: India | D135: =VLOOKUP(B135,기업리스트!$B:$G,2,FALSE) -> Ajanta Pharma Limited | E135: Sep'26 | F135: 4.5 | G135: 2079 | H135: 1794 | I135: 1900 | J135: 1636 | K135: 1732 | L135: 1466 | M135: 2481 | N135: 2570 | O135: 2874 | P135: 2532 | Q135: 2964 | R135: 3024 | S135: 2849 | T135: 2566 | U135: 3352 | V135: 3258 | W135: 3387 | X135: 0.0029905884 | Y135: 0.034026133 | Z135: 0.019845645 | AA135: 0.044740125
B136: AADHARHFC | C136: India | D136: =VLOOKUP(B136,기업리스트!$B:$G,2,FALSE) -> Aadhar Housing Finance Limited | E136: Jun'26 | F136: 4.1 | G136: 610.83 | H136: 1017 | I136: 1317 | J136: 1568 | K136: 1568 | L136: 2036 | M136: 2036 | N136: 1874 | O136: 2530 | P136: 2606 | Q136: 2590 | R136: 2572 | S136: 2924 | T136: 3077 | U136: 3162 | V136: 3052 | W136: 3427 | X136: 0.044051627 | Y136: 0.051240706 | Z136: 0.040903281 | AA136: 0.041178878
B137: SUNPHARMA | C137: India | D137: =VLOOKUP(B137,기업리스트!$B:$G,2,FALSE) -> Sun Pharmaceutical Industries Limited | E137: Sep'26 | F137: 3.8 | G137: 20632 | H137: 16789 | I137: 21507 | J137: 25881 | K137: 23469 | L137: 22201 | M137: 26784 | N137: 25807 | O137: 27301 | P137: 25310 | Q137: 30029 | R137: 31850 | S137: 35618 | T137: 28558 | U137: 33721 | V137: 33671 | W137: 40622 | X137: 0.026448004 | Y137: 0.029288803 | Z137: 0.014035007 | AA137: 0.038033564
B138: POWERGRID | C138: India | D138: =VLOOKUP(B138,기업리스트!$B:$G,2,FALSE) -> Power Grid Corporation of India Limited | E138: Sep'26 | F138: 3.7 | G138: 58318 | H138: 64903 | I138: 59540 | J138: 61085 | K138: 64866 | L138: 83157 | M138: 64169 | N138: 66313 | O138: 69194 | P138: 71784 | Q138: 64021 | R138: 64093 | S138: 63218 | T138: 75999 | U138: 60163 | V138: 58906 | W138: 72715 | X138: 0.01601955 | Y138: -0.014431547 | Z138: -0.019687027 | AA138: 0.036769318
B139: LALPATHLAB | C139: India | D139: =VLOOKUP(B139,기업리스트!$B:$G,2,FALSE) -> Dr. Lal PathLabs Limited | E139: Sep'26 | F139: 3.1 | G139: 785 | H139: 855.08 | I139: 816 | J139: 1050 | K139: 751 | L139: 784.53 | M139: 1111 | N139: 1419 | O139: 1046 | P139: 1105 | Q139: 1353 | R139: 1672 | S139: 1185 | T139: 1383 | U139: 1577 | V139: 1836 | W139: 1372 | X139: 0.052304798 | Y139: 0.040050063 | Z139: 0.028193227 | AA139: 0.031265675
B140: ASTERDM | C140: India | D140: =VLOOKUP(B140,기업리스트!$B:$G,2,FALSE) -> Aster DM Healthcare Limited | E140: Sep'26 | F140: 2.8 | G140: 2362 | H140: 2934 | I140: 1171 | J140: 1295 | K140: 2512 | L140: 0 | M140: 1703 | N140: 2045 | O140: 3326 | P140: 0 | Q140: 1031 | R140: 1575 | S140: 1270 | T140: 1291 | U140: 1441 | V140: 1837 | W140: 1436 | X140: 0.33307534 | Y140: 0.079349719 | Z140: 0.046978662 | AA140: 0.028429526
B141: MSUMI | C141: India | D141: =VLOOKUP(B141,기업리스트!$B:$G,2,FALSE) -> Motherson Sumi Wiring India Limited | E141: Sep'26 | F141: 1.9 | G141: 1964 | H141: 1516 | I141: 1751 | J141: 1513 | K141: 1473 | L141: 1832 | M141: 1603 | N141: 2118 | O141: 2243 | P141: 2391 | Q141: 1989 | R141: 2052 | S141: 1906 | T141: 2048 | U141: 1951 | V141: 2266 | W141: 2058 | X141: -0.041136963 | Y141: -0.0047529706 | Z141: 0.026894558 | AA141: 0.018602374
B142: AIAENG | C142: India | D142: =VLOOKUP(B142,기업리스트!$B:$G,2,FALSE) -> AIA Engineering Limited | E142: Sep'26 | F142: 0.5 | G142: 1363 | H142: 2048 | I142: 2264 | J142: 2874 | K142: 3413 | L142: 2925 | M142: 3188 | N142: 3576 | O142: 2842 | P142: 2749 | Q142: 2635 | R142: 2521 | S142: 2569 | T142: 2737 | U142: 2787 | V142: 2689 | W142: 2622 | X142: -0.0011456941 | Y142: 0.014528771 | Z142: 0.015828151 | AA142: 0.0049156001
... B148: JINDALSTEL | C148: India | D148: =VLOOKUP(B148,기업리스트!$B:$G,2,FALSE) -> Jindal Steel Limited | E148: Sep'26 | F148: -12.8 | G148: 26968 | H148: 26538 | I148: 28426 | J148: 13171 | K148: 17698 | L148: 11720 | M148: 20405 | N148: 16820 | O148: 22069 | P148: 14044 | Q148: 21564 | R148: 15043 | S148: 14858 | T148: 2987 | U148: 22841 | V148: 13316 | W148: 7951 | X148: -0.16878597 | Y148: 0.023451847 | Z148: -0.030989252 | AA148: -0.12790267
B149: HMN | C149: United States | D149: Insurance - Property & Casualty | E149: Sep'25 | F149: 13.8 | G149: 22.4 | H149: 53.1 | I149: 28.9 | J149: -1.7 | K149: 28.7 | L149: -15.2 | M149: 14.8 | N149: -8.7 | O149: 21.1 | P149: 55.8 | Q149: 41.7 | R149: 13.3 | S149: 51.4 | T149: 56.8 | U149: 56.4 | V149: 45.1 | W149: 80.4 | X149: 0.0061652281 | Y149: 0.090073529 | Z149: 0.17875211 | AA149: 0.1382928
B150: LTM | C150: United States | D150: Airlines | E150: Sep'25 | F150: 13.5 | G150: -480.26 | H150: 64.6 | I150: -135.85 | J150: -203.71 | K150: 59.16 | L150: 157.45 | M150: 243.35 | N150: 227.07 | O150: 324.94 | P150: 282.81 | Q150: 394.33 | R150: 260.4 | S150: 435.82 | T150: 450.5 | U150: 558.3 | V150: 431.58 | W150: 689.15 | X150: 0.122102 | Y150: 0.10640148 | Z150: 0.10039765 | AA150: 0.13502292
B151: LYB | C151: United States | D151: Specialty Chemicals | E151: Sep'25 | F151: -23.6 | G151: 2233 | H151: 1544 | I151: 1653 | J151: 2109 | K151: 800 | L151: 596 | M151: 962 | N151: 1009 | O151: 1036 | P151: 555 | Q151: 647 | R151: 995 | S151: 865 | T151: 280 | U151: 227 | V151: 313 | W151: 467 | X151: -0.089810581 | Y151: -0.15069968 | Z151: -0.28812843 | AA151: -0.23620178
B152: CNR | C152: United States | D152: Thermal Coal | E152: Sep'25 | F152: -79.5 | G152: -138.63 | H152: 154.64 | I152: 1.32 | J152: 162.84 | K152: 176.08 | L152: 246.61 | M152: 275.9 | N152: 210.13 | O152: 123.72 | P152: 161.25 | Q152: 113.56 | R152: 67.45 | S152: 112.82 | T152: 94.81 | U152: -16.75 | V152: -25.79 | W152: -18.37 | X152: -0.14599631 | Y152: -0.33529745 | Z152: -0.36093369 | AA152: -0.79465746
B153: 5191 | C153: Japan | D153: N/A | E153: Sep'25 | F153: 2.6 | G153: -3158 | H153: 1129 | I153: 98 | J153: -2254 | K153: 633 | L153: 6456 | M153: 11725 | N153: 6586 | O153: 5602 | P153: 12268 | Q153: 9521 | R153: 8380 | S153: 8665 | T153: 15384 | U153: 10230 | V153: 9604 | W153: 9785 | X153: 0.080238966 | Y153: 0.016901073 | Z153: 0.028692656 | AA153: 0.025522412
B154: JLHL | C154: Unknown | D154: Building Products & Equipment | E154: H1 2025 | F154: 31.6 | S154: 3.12 | T154: 10.11 | U154: 10.47 | V154: 9.54 | W154: 13.61 | AA154: 0.31558363
B155: BAIN | C155: France | D155: =VLOOKUP(B155,기업리스트!$B:$G,2,FALSE) -> Société Anonyme des Bains de Mer et du Cercle des Étrangers à Monaco | E155: H1 2026 | F155: 10.8 | N155: -34.87 | O155: 50.23 | P155: -13.48 | Q155: 92.12 | R155: -19.85 | S155: 89.23 | T155: -16.02 | U155: 93.98 | V155: -18.84 | W155: 105.32 | X155: -0.017159843 | Y155: 0.012785263 | Z155: 0.0068548934 | AA155: 0.10845972

Sheet 빨간줄
B2: (단위: mil $)
B4: 8341 | C4: 6 | D4: 7 | E4: 8 | F4: 9 | G4: 10 | H4: 11 | I4: 12 | J4: 13 | K4: 14 | L4: 15 | M4: 16 | N4: 17 | O4: 18 | P4: 19 | Q4: 20 | R4: 21 | S4: 22
C6: 4Q21 | D6: 1Q22 | E6: 2Q22 | F6: 3Q22 | G6: 4Q22 | H6: 1Q23 | I6: 2Q23 | J6: 3Q23 | K6: 4Q23 | L6: 1Q24 | M6: 2Q24 | N6: 3Q24 | O6: 4Q24 | P6: 1Q25 | Q6: 2Q25 | R6: 3Q25 | S6: 4Q25 | T6: 1Q26 | U6: 2Q26 | V6: 3Q26 | W6: 4Q26
B7: Revenue | C7: =IFERROR(VLOOKUP($B$4,Revenue!$B$2:$X$500,C$4,FALSE),"-") -> 27470 | D7: =IFERROR(VLOOKUP($B$4,Revenue!$B$2:$X$500,D$4,FALSE),"-") -> 26921 | E7: =IFERROR(VLOOKUP($B$4,Revenue!$B$2:$X$500,E$4,FALSE),"-") -> 30911 | F7: =IFERROR(VLOOKUP($B$4,Revenue!$B$2:$X$500,F$4,FALSE),"-") -> 27118 | G7: =IFERROR(VLOOKUP($B$4,Revenue!$B$2:$X$500,G$4,FALSE),"-") -> 30476 | H7: =IFERROR(VLOOKUP($B$4,Revenue!$B$2:$X$500,H$4,FALSE),"-") -> 31502 | I7: =IFERROR(VLOOKUP($B$4,Revenue!$B$2:$X$500,I$4,FALSE),"-") -> 36678 | J7: =IFERROR(VLOOKUP($B$4,Revenue!$B$2:$X$500,J$4,FALSE),"-") -> 35841 | ... S7: =IFERROR(VLOOKUP($B$4,Revenue!$B$2:$X$500,S$4,FALSE),"-") -> 49467
B8: OP | C8: =IFERROR(VLOOKUP($B$4,'Operating Income'!$B$2:$X$500,C$4,FALSE),"-") -> 7952 | D8: =IFERROR(VLOOKUP($B$4,'Operating Income'!$B$2:$X$500,D$4,FALSE),"-") -> 6495 | E8: =IFERROR(VLOOKUP($B$4,'Operating Income'!$B$2:$X$500,E$4,FALSE),"-") -> 11640 | F8: =IFERROR(VLOOKUP($B$4,'Operating Income'!$B$2:$X$500,F$4,FALSE),"-") -> 7840 | G8: =IFERROR(VLOOKUP($B$4,'Operating Income'!$B$2:$X$500,G$4,FALSE),"-") -> 9468 | H8: =IFERROR(VLOOKUP($B$4,'Operating Income'!$B$2:$X$500,H$4,FALSE),"-") -> 6463 | I8: =IFERROR(VLOOKUP($B$4,'Operating Income'!$B$2:$X$500,I$4,FALSE),"-") -> 12564 | J8: =IFERROR(VLOOKUP($B$4,'Operating Income'!$B$2:$X$500,J$4,FALSE),"-") -> 12810 | ... S8: =IFERROR(VLOOKUP($B$4,'Operating Income'!$B$2:$X$500,S$4,FALSE),"-") -> 22551
B9: Trailing 4Q OP avg. | C9: =IFERROR(AVERAGE(C8:C8),"-") -> 7952 | D9: =IFERROR(AVERAGE(C8:D8),"-") -> 7223.5 | E9: =IFERROR(AVERAGE(C8:E8),"-") -> 8695.6667 | F9: =IFERROR(AVERAGE(C8:F8),"-") -> 8481.75 | G9: =IFERROR(AVERAGE(D8:G8),"-") -> 8860.75 | H9: =IFERROR(AVERAGE(E8:H8),"-") -> 8852.75 | I9: =IFERROR(AVERAGE(F8:I8),"-") -> 9083.75 | J9: =IFERROR(AVERAGE(G8:J8),"-") -> 10326.25 | K9: =IFERROR(AVERAGE(H8:K8),"-") -> 10619.75 | L9: =IFERROR(AVERAGE(I8:L8),"-") -> 11051.5 | M9: =IFERROR(AVERAGE(J8:M8),"-") -> 12040.75 | ... S9: =IFERROR(AVERAGE(P8:S8),"-") -> 17285.75
B10: Trailing 4Q OP sum. | C10: =IFERROR(SUM(C8:C8),"-") -> 7952 | D10: =IFERROR(SUM(C8:D8),"-") -> 14447 | E10: =IFERROR(SUM(C8:E8),"-") -> 26087 | F10: =IFERROR(SUM(C8:F8),"-") -> 33927 | G10: =IFERROR(SUM(D8:G8),"-") -> 35443 | H10: =IFERROR(SUM(E8:H8),"-") -> 35411 | I10: =IFERROR(SUM(F8:I8),"-") -> 36335 | J10: =IFERROR(SUM(G8:J8),"-") -> 41305 | K10: =IFERROR(SUM(H8:K8),"-") -> 42479 | L10: =IFERROR(SUM(I8:L8),"-") -> 44206 | M10: =IFERROR(SUM(J8:M8),"-") -> 48163 | ... S10: =IFERROR(SUM(P8:S8),"-") -> 69143
B11: Trailing OP Delta | D11: =IFERROR(D9/C9-1,"-") -> -0.091612173 | E11: =IFERROR(E9/D9-1,"-") -> 0.2038024 | F11: =IFERROR(F9/E9-1,"-") -> -0.024600376 | G11: =IFERROR(G9/F9-1,"-") -> 0.044684175 | H11: =IFERROR(H9/G9-1,"-") -> -0.00090285811 | I11: =IFERROR(I9/H9-1,"-") -> 0.026093587 | J11: =IFERROR(J9/I9-1,"-") -> 0.13678272 | K11: =IFERROR(K9/J9-1,"-") -> 0.028422709 | ... S11: =IFERROR(S9/R9-1,"-") -> 0.10270641
B12: OPM | C12: =IFERROR(C8/C7,"-") -> 0.28947943 | D12: =IFERROR(D8/D7,"-") -> 0.24126147 | E12: =IFERROR(E8/E7,"-") -> 0.37656498 | F12: =IFERROR(F8/F7,"-") -> 0.28910687 | G12: =IFERROR(G8/G7,"-") -> 0.31067069 | H12: =IFERROR(H8/H7,"-") -> 0.20516158 | I12: =IFERROR(I8/I7,"-") -> 0.34254867 | J12: =IFERROR(J8/J7,"-") -> 0.3574119 | ... S12: =IFERROR(S8/S7,"-") -> 0.45587968
B13: OP YoY | G13: =IFERROR(G8/C8-1,"-") -> 0.19064386 | H13: =IFERROR(H8/D8-1,"-") -> -0.0049268668 | I13: =IFERROR(I8/E8-1,"-") -> 0.079381443 | J13: =IFERROR(J8/F8-1,"-") -> 0.63392857 | K13: =IFERROR(K8/G8-1,"-") -> 0.12399662 | L13: =IFERROR(L8/H8-1,"-") -> 0.26721337 | M13: =IFERROR(M8/I8-1,"-") -> 0.31494747 | N13: =IFERROR(N8/J8-1,"-") -> -0.050663544 | ... S13: =IFERROR(S8/O8-1,"-") -> 0.39972689
B14: 매출 YoY | G14: =IFERROR(G7/C7-1,"-") -> 0.10942847 | H14: =IFERROR(H7/D7-1,"-") -> 0.17016456 | I14: =IFERROR(I7/E7-1,"-") -> 0.18656789 | J14: =IFERROR(J7/F7-1,"-") -> 0.32166826 | K14: =IFERROR(K7/G7-1,"-") -> 0.053386271 | L14: =IFERROR(L7/H7-1,"-") -> 0.28448987 | M14: =IFERROR(M7/I7-1,"-") -> 0.18269808 | N14: =IFERROR(N7/J7-1,"-") -> 0.069054993 | ... S14: =IFERROR(S7/O7-1,"-") -> 0.23141072
