Workbook

Sheet 실적 기업 정보
B2: 260128 실적 기업 정보
B4: Ticker | C4: Company | D4: Date | E4: Time | F4: Quarter Ending | G4: Market Cap (mil$)
B5: MSFT | C5: Microsoft Corporation | D5: 46050 | E5: After Hours | F5: 46381 | G5: 3417853190000
B6: META | C6: Meta Platforms, Inc. | D6: 46050 | E6: After Hours | F6: 46381 | G6: 1563357240000
B7: TSLA | C7: Tesla, Inc. | D7: 46050 | F7: 46381 | G7: 1455045890000
B8: ASML | C8: ASML Holding N.V. | D8: 46050 | E8: Pre Market | F8: 46381 | G8: 522992700000
B9: A000660 | C9: SK hynix Inc. | D9: 46050 | F9: 46381 | G9: 354526930000
B10: LRCX | C10: Lam Research Corporation | D10: 46050 | E10: After Hours | F10: 46381 | G10: 273739180000
B11: IBM | C11: International Business Machines Corporation | D11: 46050 | E11: After Hours | F11: 46381 | G11: 273353960000
B12: APH | C12: Amphenol Corporation | D12: 46050 | E12: Pre Market | F12: 46381 | G12: 184820140000
B13: GEV | C13: GE Vernova Inc. | D13: 46050 | E13: Pre Market | F13: 46381 | G13: 178469170000
B14: T | C14: AT&T Inc. | D14: 46050 | E14: Pre Market | F14: 46381 | G14: 167240110000
B15: DHR | C15: Danaher Corporation | D15: 46050 | E15: Pre Market | F15: 46381 | G15: 165999210000
B16: NOW | C16: ServiceNow, Inc. | D16: 46050 | E16: After Hours | F16: 46381 | G16: 138089320000
B17: PGR | C17: The Progressive Corporation | D17: 46050 | F17: 46351 | G17: 120815420000
B18: SBUX | C18: Starbucks Corporation | D18: 46050 | E18: Pre Market | F18: 46381 | G18: 111003700000
B19: 6857 | C19: Advantest Corporation | D19: 46050 | F19: 46381 | G19: 109823180000
B20: ADP | C20: Automatic Data Processing, Inc. | D20: 46050 | E20: Pre Market | F20: 46381 | G20: 104295200000
B21: GD | C21: General Dynamics Corporation | D21: 46050 | E21: Pre Market | F21: 46381 | G21: 97979740000
B22: WM | C22: Waste Management, Inc. | D22: 46050 | E22: After Hours | F22: 46381 | G22: 92349210000
B23: ELV | C23: Elevance Health, Inc. | D23: 46050 | E23: Pre Market | F23: 46381 | G23: 82463920000
B24: GLW | C24: Corning Incorporated | D24: 46050 | E24: Pre Market | F24: 46381 | G24: 79991720000
B25: VOLV B | C25: AB Volvo (publ) | D25: 46050 | F25: 46381 | G25: 71617480000
B26: NDA FI | C26: Nordea Bank Abp | D26: 46050 | F26: 46381 | G26: 67136190000
B27: CP | C27: Canadian Pacific Kansas City Limited | D27: 46050 | E27: After Hours | F27: 46381 | G27: 65616280000
B28: URI | C28: United Rentals, Inc. | D28: 46050 | E28: After Hours | F28: 46381 | G28: 58478010000
B29: 500510 | C29: Larsen & Toubro Limited | D29: 46050 | F29: 46381 | G29: 56215870000
B30: MARUTI | C30: Maruti Suzuki India Limited | D30: 46050 | F30: 46381 | G30: 53078970000
B31: LONN | C31: Lonza Group AG | D31: 46050 | F31: 46381 | G31: 49897270000
B32: MSCI | C32: MSCI Inc. | D32: 46050 | E32: Pre Market | F32: 46381 | G32: 44314290000
B33: LVS | C33: Las Vegas Sands Corp. | D33: 46050 | E33: After Hours | F33: 46381 | G33: 39856880000
B34: FICO | C34: Fair Isaac Corporation | D34: 46050 | E34: After Hours | F34: 46381 | G34: 37244980000
B35: TEVA | C35: Teva Pharmaceutical Industries Limited | D35: 46050 | E35: Pre Market | F35: 46381 | G35: 36437690000
B36: CLS | C36: Celestica Inc. | D36: 46050 | F36: 46381 | G36: 36111000000
B37: OTIS | C37: Otis Worldwide Corporation | D37: 46050 | E37: Pre Market | F37: 46381 | G37: 35136780000
B38: RJF | C38: Raymond James Financial, Inc. | D38: 46050 | E38: After Hours | F38: 46381 | G38: 33876710000
B39: 500049 | C39: Bharat Electronics Limited | D39: 46050 | F39: 46381 | G39: 33041420000
B40: GIB.A | C40: CGI Inc. | D40: 46050 | E40: Pre Market | F40: 46381 | G40: 20241470000
B41: SBILIFE | C41: SBI Life Insurance Company Limited | D41: 46050 | F41: 46381 | G41: 20158800000
B42: A012330 | C42: Hyundai Mobis Co.,Ltd | D42: 46050 | F42: 46381 | G42: 18872010000
B43: 532343 | C43: TVS Motor Company Limited | D43: 46050 | F43: 46381 | G43: 18491780000
B44: KPN | C44: Koninklijke KPN N.V. | D44: 46050 | F44: 46381 | G44: 18165700000
B45: 2303 | C45: United Microelectronics Corporation | D45: 46050 | E45: Pre Market | F45: 46381 | G45: 18106320000
B46: LII | C46: Lennox International Inc. | D46: 46050 | F46: 46381 | G46: 17261420000
B47: LUV | C47: Southwest Airlines Co. | D47: 46050 | F47: 46381 | G47: 17079100000
B48: EVO | C48: Evolution AB (publ) | D48: 46050 | F48: 46381 | G48: 16204390000
B49: CHRW | C49: C.H. Robinson Worldwide, Inc. | D49: 46050 | E49: After Hours | F49: 46381 | G49: 15989540000
B50: TXT | C50: Textron Inc. | D50: 46050 | E50: Pre Market | F50: 46381 | G50: 15477130000
B51: HLI | C51: Houlihan Lokey, Inc. | D51: 46050 | E51: After Hours | F51: 46381 | G51: 14161450000
B52: NLY | C52: Annaly Capital Management, Inc. | D52: 46050 | F52: 46381 | G52: 13329500000
B53: LODHA | C53: Lodha Developers Limited | D53: 46050 | F53: 46381 | G53: 12517770000
B54: ELS | C54: Equity LifeStyle Properties, Inc. | D54: 46050 | F54: 46381 | G54: 12042560000
B55: TEL2 B | C55: Tele2 AB (publ) | D55: 46050 | F55: 46381 | G55: 11723820000
B56: SF | C56: Stifel Financial Corp. | D56: 46050 | F56: 46048 | G56: 11384160000
B57: SEIC | C57: SEI Investments Company | D57: 46050 | E57: After Hours | F57: 46381 | G57: 10584780000
B58: 3008 | C58: LARGAN Precision Co.,Ltd | D58: 46050 | F58: 46381 | G58: 10468010000
B59: LEVI | C59: Levi Strauss & Co. | D59: 46050 | E59: After Hours | F59: 46351 | G59: 9673750000
B60: SBICARD | C60: SBI Cards and Payment Services Limited | D60: 46050 | F60: 46381 | G60: 9561100000
B61: TTEK | C61: Tetra Tech, Inc. | D61: 46050 | E61: After Hours | F61: 46381 | G61: 8865970000
B62: SCC | C62: The Siam Cement Public Company Limited | D62: 46050 | F62: 46381 | G62: 8501160000
B63: EDU | C63: New Oriental Education & Technology Group Inc. | D63: 46050 | F63: 46381 | G63: 8337650000
B64: SSAB A | C64: SSAB AB (publ) | D64: 46050 | F64: 46381 | G64: 7991810000
B65: AXS | C65: AXIS Capital Holdings Limited | D65: 46050 | F65: 46381 | G65: 7829350000
B66: NFG | C66: National Fuel Gas Company | D66: 46050 | E66: After Hours | F66: 46381 | G66: 7788580000
B67: SAVE | C67: Nordnet AB (publ) | D67: 46050 | F67: 46381 | G67: 7445120000
B68: VFC | C68: V.F. Corporation | D68: 46050 | E68: Pre Market | F68: 46381 | G68: 7361250000
B69: 503100 | C69: The Phoenix Mills Limited | D69: 46050 | F69: 46381 | G69: 6987710000
B70: PB | C70: Prosperity Bancshares, Inc. | D70: 46050 | E70: Pre Market | F70: 46381 | G70: 6846550000
B71: 1942 | C71: Kandenko Co.,Ltd. | D71: 46050 | F71: 46381 | G71: 6797320000
B72: LFUS | C72: Littelfuse, Inc. | D72: 46050 | E72: Pre Market | F72: 46381 | G72: 6736650000
B73: HXL | C73: Hexcel Corporation | D73: 46050 | E73: After Hours | F73: 46381 | G73: 6101790000
B74: KALYANKJIL | C74: Kalyan Jewellers India Limited | D74: 46050 | F74: 46381 | G74: 5786270000
B75: BMI | C75: Badger Meter, Inc. | D75: 46050 | E75: Pre Market | F75: 46381 | G75: 5217040000
B76: 502355 | C76: Balkrishna Industries Limited | D76: 46050 | F76: 46381 | G76: 5179890000
B77: LSTR | C77: Landstar System, Inc. | D77: 46050 | E77: After Hours | F77: 46381 | G77: 5108770000
B78: 3231 | C78: Nomura Real Estate Holdings, Inc. | D78: 46050 | F78: 46381 | G78: 5069760000
B79: EAT | C79: Brinker International, Inc. | D79: 46050 | E79: Pre Market | F79: 46381 | G79: 5052270000
B80: ME8U | C80: Mapletree Industrial Trust | D80: 46050 | F80: 46381 | G80: 4780890000
B81: MTH | C81: Meritage Homes Corporation | D81: 46050 | E81: After Hours | F81: 46381 | G81: 4774980000
B82: A034220 | C82: LG Display Co., Ltd. | D82: 46050 | E82: Pre Market | F82: 46381 | G82: 4631210000
B83: WHR | C83: Whirlpool Corporation | D83: 46050 | E83: After Hours | F83: 46381 | G83: 4474350000
B84: 4190 | C84: Jarir Marketing Company | D84: 46050 | F84: 46381 | G84: 4428210000
B85: 8060 | C85: Canon Marketing Japan Inc. | D85: 46050 | F85: 46381 | G85: 4395270000
B86: PLXS | C86: Plexus Corp. | D86: 46050 | E86: After Hours | F86: 46381 | G86: 4387260000
B87: MPHC | C87: Mesaieed Petrochemical Holding Company Q.P.S.C. | D87: 46050 | F87: 46381 | G87: 4375800000
B88: MUR | C88: Murphy Oil Corporation | D88: 46050 | E88: After Hours | F88: 46381 | G88: 4346180000
B89: AVT | C89: Avnet, Inc. | D89: 46050 | E89: Pre Market | F89: 46381 | G89: 4328380000
B90: PROT | C90: Protector Forsikring ASA | D90: 46050 | F90: 46381 | G90: 4046090000
B91: VIAV | C91: Viavi Solutions Inc. | D91: 46050 | E91: After Hours | F91: 46381 | G91: 4017580000
B92: Q * | C92: Quálitas Controladora, S.A.B. de C.V. | D92: 46050 | F92: 46381 | G92: 3868510000
B93: DFM | C93: Dubai Financial Market P.J.S.C. | D93: 46050 | F93: 46381 | G93: 3765940000
B94: ACC | C94: ACC Limited | D94: 46050 | F94: 46381 | G94: 3722980000
B95: CALX | C95: Calix, Inc. | D95: 46050 | F95: 46381 | G95: 3712810000
B96: AJANTPHARM | C96: Ajanta Pharma Limited | D96: 46050 | F96: 46381 | G96: 3687490000
B97: FIBK | C97: First Interstate BancSystem, Inc. | D97: 46050 | E97: After Hours | F97: 46381 | G97: 3665480000
B98: MHO | C98: M/I Homes, Inc. | D98: 46050 | E98: Pre Market | F98: 46381 | G98: 3521160000
B99: ATGE | C99: Adtalem Global Education Inc. | D99: 46050 | E99: After Hours | F99: 46381 | G99: 3379280000
B100: SMG | C100: The Scotts Miracle-Gro Company | D100: 46050 | F100: 46381 | G100: 3144440000
B101: SLG | C101: SL Green Realty Corp. | D101: 46050 | F101: 46381 | G101: 3141470000
B102: LBRT | C102: Liberty Energy Inc. | D102: 46050 | E102: After Hours | F102: 46381 | G102: 3119480000
...

Sheet Revenue
B1: 1 | C1: 2 | D1: 3 | E1: 4 | F1: 5 | G1: 6 | H1: 7 | I1: 8 | J1: 9 | K1: 10 | L1: 11 | M1: 12 | N1: 13 | O1: 14 | P1: 15 | Q1: 16 | R1: 17 | S1: 18 | T1: 19 | U1: 20 | V1: 21 | W1: 22
B2: Ticker | C2: Country | D2: Industry | E2: Latest_Date | F2: Growth_Rate | G2: 4Q21 | H2: 1Q22 | I2: 2Q22 | J2: 3Q22 | K2: 4Q22 | L2: 1Q23 | M2: 2Q23 | N2: 3Q23 | O2: 4Q23 | P2: 1Q24 | Q2: 2Q24 | R2: 3Q24 | S2: 4Q24 | T2: 1Q25 | U2: 2Q25 | V2: 3Q25 | W2: 4Q25 | X2: 1Q25 | Y2: 2Q25 | Z2: 3Q25 | AA2: 4Q25
A3: 260130 | B3: TMP | C3: United States | D3: Banks - Regional | E3: Dec'25 | F3: 37.3 | G3: 73.05 | H3: 77.12 | I3: 76.35 | J3: 77.75 | K3: 74.25 | L3: 75.47 | M3: 62.26 | N3: 8.24 | O3: 69.45 | P3: 71.96 | Q3: 70.56 | R3: 74.4 | S3: 75.7 | T3: 76.41 | U3: 79.86 | V3: 84.95 | W3: 193.85 | X3: 0.015207436 | Y3: 0.031305753 | Z3: 0.034435487 | AA3: 0.37280702
A4: 260130 | B4: JHG | C4: United States | D4: Asset Management | E4: Dec'25 | F4: 16.3 | G4: 697.2 | H4: 620 | I4: 555.5 | J4: 512.9 | K4: 515.2 | L4: 495.8 | M4: 516.5 | N4: 521 | O4: 568.5 | P4: 551.7 | Q4: 588.4 | R4: 624.8 | S4: 708.3 | T4: 621.4 | U4: 633.2 | V4: 700.4 | W4: 1142 | X4: 0.028182112 | Y4: 0.017617681 | Z4: 0.029215133 | AA4: 0.16284309
A5: 260130 | B5: MCHB | C5: United States | D5: Banks - Regional | E5: Dec'25 | F5: 13.4 | P5: -68.66 | Q5: 157.95 | R5: 141.14 | S5: 151.18 | T5: 147.19 | U5: 149.4 | V5: 119.03 | W5: 227.05 | X5: 0.56562983 | Y5: -0.014310581 | Z5: -0.037543937 | AA5: 0.13385674
A6: 260130 | B6: LPG | C6: United States | D6: Oil & Gas Midstream | E6: Jun'26 | F6: 11.9 | G6: 61.99 | H6: 68.16 | I6: 83.57 | J6: 76.41 | K6: 75.78 | L6: 102.53 | M6: 132.53 | N6: 110.81 | O6: 144.33 | P6: 162.33 | Q6: 141.36 | R6: 112.82 | S6: 82.31 | T6: 80.46 | U6: 74.08 | V6: 83.84 | W6: 120.63 | X6: -0.16412734 | Y6: -0.16136227 | Z6: -0.082878142 | AA6: 0.11949234
A7: 260130 | B7: SOFI | C7: United States | D7: Credit Services | E7: Dec'25 | F7: 8.7 | G7: 280.92 | H7: 317.38 | I7: 352.42 | J7: 407.66 | K7: 441.73 | L7: 463.75 | M7: 485.4 | N7: 515.38 | O7: 603.31 | P7: 637.81 | Q7: 586.98 | R7: 691.11 | S7: 734.13 | T7: 766.08 | U7: 844.91 | V7: 952.4 | W7: 1020 | X7: 0.048403226 | Y7: 0.092837347 | Z7: 0.08605738 | AA7: 0.086692423
A8: 260130 | B8: WT | C8: United States | D8: Asset Management | E8: Dec'25 | F8: 8 | G8: 79.18 | H8: 78.37 | I8: 77.25 | J8: 72.41 | K8: 73.31 | L8: 82.04 | M8: 85.72 | N8: 90.42 | O8: 90.84 | P8: 96.84 | Q8: 107.03 | R8: 113.17 | S8: 110.7 | T8: 108.08 | U8: 112.62 | V8: 125.62 | W8: 147.43 | X8: 0.026277645 | Y8: 0.012734065 | Z8: 0.028004589 | AA8: 0.080368474
A9: 260130 | B9: OPY | C9: United States | D9: Capital Markets | E9: Dec'25 | F9: 6.8 | G9: 362.84 | H9: 263.52 | I9: 233.61 | J9: 287.09 | K9: 302.9 | L9: 308.54 | M9: 288.73 | N9: 292.92 | O9: 289.97 | P9: 332.59 | Q9: 308.63 | R9: 349.25 | S9: 354.04 | T9: 346.43 | U9: 350.65 | V9: 401.94 | W9: 452.49 | X9: 0.010293713 | Y9: 0.03093459 | Z9: 0.03762577 | AA9: 0.067753568
A10: 260130 | B10: TOWN | C10: United States | D10: Banks - Regional | E10: Dec'25 | F10: 5.8 | G10: 161.53 | H10: 166.86 | I10: 166.92 | J10: 175.31 | K10: 168.04 | L10: 172.47 | M10: 178.01 | N10: 171.86 | O10: 153.1 | P10: 167.98 | Q10: 175.15 | R10: 175.62 | S10: 175.55 | T10: 189.62 | U10: 201.03 | V10: 200.39 | W10: 220.11 | X10: 0.031168083 | Y10: 0.036148281 | Z10: 0.03339085 | AA10: 0.058127552
A11: 260130 | B11: SAIL | C11: United States | D11: Software - Infrastructure | E11: Sep'26 | F11: 4.8 | P11: 202.71 | Q11: 187.66 | R11: 198.58 | S11: 235.26 | T11: 240.12 | U11: 230.47 | V11: 264.36 | W11: 281.94 | X11: 0.045388918 | Y11: 0.049685476 | Z11: 0.072730891 | AA11: 0.048113295
A12: 260130 | B12: GNTX | C12: United States | D12: Auto Parts | E12: Dec'25 | F12: 4.2 | G12: 419.84 | H12: 468.25 | I12: 463.42 | J12: 493.64 | K12: 493.65 | L12: 550.76 | M12: 583.47 | N12: 575.85 | O12: 589.13 | P12: 590.23 | Q12: 572.93 | R12: 608.53 | S12: 541.64 | T12: 576.77 | U12: 657.86 | V12: 655.24 | W12: 644.4 | X12: -0.0058184522 | Y12: 0.036928174 | Z12: 0.019586548 | AA12: 0.042261804
A13: 260130 | B13: FLG | C13: United States | D13: Banks - Regional | E13: Dec'25 | F13: 4.1 | G13: 334 | H13: 348 | I13: 368 | J13: 341 | K13: 294 | L13: 482 | M13: 1012 | N13: 980 | O13: 326 | P13: 439 | Q13: 281 | R13: 381 | S13: 480 | T13: 411 | U13: 432 | V13: 481 | W13: 554 | X13: -0.01771031 | Y13: 0.097231165 | Z13: 0.058685446 | AA13: 0.041019956
A14: 260130 | B14: IESC | C14: United States | D14: Engineering & Construction | E14: Mar'26 | F14: 3.6 | G14: 480.51 | H14: 501.59 | I14: 567.3 | J14: 617.41 | K14: 574.87 | L14: 568.88 | M14: 584.45 | N14: 649.02 | O14: 634.44 | P14: 705.73 | Q14: 768.42 | R14: 775.77 | S14: 749.55 | T14: 833.96 | U14: 890.16 | V14: 897.8 | W14: 870.96 | X14: 0.042750886 | Y14: 0.03892317 | Z14: 0.037554163 | AA14: 0.036010998
A15: 260130 | B15: FHB | C15: United States | D15: Banks - Regional | E15: Dec'25 | F15: 3.6 | G15: 178.9 | H15: 181 | I15: 188.28 | J15: 205.41 | K15: 216.99 | L15: 207.47 | M15: 202.29 | N15: 195.75 | O15: 204.81 | P15: 199.5 | Q15: 202.82 | R15: 202.6 | S15: 188.88 | T15: 200.5 | U15: 213.04 | V15: 221.89 | W15: 218.15 | X15: 0.0012597632 | Y15: 0.012858581 | Z15: 0.023962138 | AA15: 0.035508486
A16: 260130 | B16: RRBI | C16: United States | D16: Banks - Regional | E16: Dec'25 | F16: 3.3 | G16: 24.3 | H16: 22.98 | I16: 25.76 | J16: 27.36 | K16: 27.54 | L16: 27.25 | M16: 27.22 | N16: 26.12 | O16: 26.23 | P16: 25.85 | Q16: 26.59 | R16: 27.58 | S16: 28.38 | T16: 29.43 | U16: 30.09 | V16: 31.26 | W16: 32.31 | X16: 0.03302583 | Y16: 0.031255581 | Z16: 0.03186699 | AA16: 0.032980866
A17: 260130 | B17: AXP | C17: United States | D17: Credit Services | E17: Dec'25 | F17: 2.6 | G17: 12092 | H17: 11768 | I17: 12985 | J17: 12778 | K17: 13149 | L17: 13226 | M17: 13856 | N17: 14148 | O17: 14362 | P17: 14532 | Q17: 15065 | R17: 15280 | S17: 15887 | T17: 15817 | U17: 16451 | V17: 17139 | W17: 17566 | X17: 0.02114739 | Y17: 0.022337185 | Z17: 0.029305588 | AA17: 0.025714461
A18: 260130 | B18: BDL | C18: United States | D18: Restaurants | E18: Dec'25 | F18: 2.1 | G18: 33.6 | H18: 37.37 | I18: 40.27 | J18: 40.63 | K18: 39.69 | L18: 41.83 | M18: 43.76 | N18: 45.32 | O18: 43.33 | P18: 45.09 | Q18: 48.07 | R18: 49.05 | S18: 45.97 | T18: 50.22 | U18: 53.63 | V18: 52.1 | W18: 50.2 | X18: 0.027261133 | Y18: 0.028762092 | Z18: 0.015336652 | AA18: 0.020948891
A19: 260130 | B19: ALV | C19: United States | D19: Auto Parts | E19: Dec'25 | F19: 1.9 | G19: 2119 | H19: 2124 | I19: 2081 | J19: 2302 | K19: 2335 | L19: 2493 | M19: 2635 | N19: 2596 | O19: 2751 | P19: 2615 | Q19: 2605 | R19: 2555 | S19: 2616 | T19: 2578 | U19: 2714 | V19: 2706 | W19: 2817 | X19: -0.0035607737 | Y19: 0.010527332 | Z19: 0.014431807 | AA19: 0.018937253
A20: 260130 | B20: APD | C20: United States | D20: Specialty Chemicals | E20: Mar'26 | F20: 1.4 | G20: 2994 | H20: 2945 | I20: 3189 | J20: 0 | K20: 3175 | L20: 3200 | M20: 3034 | N20: 0 | O20: 2997 | P20: 2930 | Q20: 2986 | R20: 0 | S20: 2932 | T20: 2916 | U20: 3023 | V20: 3167 | W20: 3103 | X20: -0.0015822785 | Y20: 0.0041883631 | Z20: 0.35700597 | AA20: 0.014205017
A21: 260130 | B21: CL | C21: United States | D21: Household & Personal Products | E21: Dec'25 | F21: 1.4 | G21: 4403 | H21: 4399 | I21: 4484 | J21: 4455 | K21: 4629 | L21: 4770 | M21: 4822 | N21: 4915 | O21: 4950 | P21: 5065 | Q21: 5058 | R21: 5033 | S21: 4945 | T21: 4911 | U21: 5110 | V21: 5131 | W21: 5230 | X21: -0.0076613104 | Y21: 0.0026069083 | Z21: 0.004900245 | AA21: 0.014181221
A22: 260130 | B22: BEPC | C22: United States | D22: Utilities - Renewable | E22: Dec'25 | F22: 1.3 | G22: 917 | H22: 993 | I22: 1003 | J22: 905 | K22: 970 | L22: 1079 | M22: 940 | N22: 1029 | O22: 919 | P22: 1149 | Q22: 965 | R22: 1041 | S22: 891 | T22: 930 | U22: 929 | V22: 931 | W22: 938 | X22: -0.054127533 | Y22: -0.0094068461 | Z22: -0.029016091 | AA22: 0.012768269
A23: 260130 | B23: CHD | C23: United States | D23: Household & Personal Products | E23: Dec'25 | F23: 1 | G23: 1369 | H23: 1297 | I23: 1325 | J23: 1317 | K23: 1436 | L23: 1430 | M23: 1454 | N23: 1456 | O23: 1528 | P23: 1503 | Q23: 1511 | R23: 1511 | S23: 1582 | T23: 1467 | U23: 1506 | V23: 1586 | W23: 1644 | X23: -0.0058948747 | Y23: -0.00082358755 | Z23: 0.012363996 | AA23: 0.010096076
... A33: 260130 | B33: IMO | C33: United States | D33: Oil & Gas Integrated | E33: Dec'25 | F33: -2.9 | G33: 12295 | H33: 12657 | I33: 17285 | J33: 15071 | K33: 14400 | L33: 12057 | M33: 11764 | N33: 13873 | O33: 13202 | P33: 12249 | Q33: 13348 | R33: 13215 | S33: 12702 | T33: 12466 | U33: 11208 | V33: 11994 | W33: 11280 | X33: 0.0042124471 | Y33: -0.041367845 | Z33: -0.024621403 | AA33: -0.029398387
A34: 260130 | B34: 8550 | C34: Japan | D34: The Tochigi Bank, Ltd. | E34: Sep'26 | F34: 33.4 | G34: 9261 | H34: 9547 | I34: 11915 | J34: 10457 | K34: 11143 | L34: 8064 | M34: 9243 | N34: 10474 | O34: 10896 | P34: 8660 | Q34: 10606 | R34: 7289 | S34: 11295 | T34: -26917 | U34: 9687 | V34: 11199 | W34: 13055 | X34: -0.93994716 | Y34: -0.40431148 | Z34: 2.88774 | AA34: 0.3343465
A35: 260130 | B35: 6777 | C35: Japan | D35: santec Holdings Corporation | E35: Sep'26 | F35: 12.7 | G35: 2188 | H35: 3070 | I35: 3188 | J35: 3487 | K35: 3914 | L35: 4657 | M35: 3583 | N35: 4064 | O35: 4327 | P35: 6893 | Q35: 6306 | R35: 5691 | S35: 5316 | T35: 6713 | U35: 6186 | V35: 6592 | W35: 8470 | X35: -0.0074361728 | Y35: -0.0049945892 | Z35: 0.037689283 | AA35: 0.12714153
A36: 260130 | B36: 6331 | C36: Japan | D36: Mitsubishi Kakoki Kaisha, Ltd. | E36: Sep'26 | F36: 12.3 | G36: 10538 | H36: 13501 | I36: 8957 | J36: 12243 | K36: 10175 | L36: 13215 | M36: 9243 | N36: 12902 | O36: 12075 | P36: 13554 | Q36: 11944 | R36: 14679 | S36: 14690 | T36: 17889 | U36: 15813 | V36: 20310 | W36: 23150 | X36: 0.079009241 | Y36: 0.065352522 | Z36: 0.089280335 | AA36: 0.12314052
A37: 260130 | B37: 8345 | C37: Japan | D37: The Bank of Iwate, Ltd. | E37: Sep'26 | F37: 11.3 | G37: 10189 | H37: 8142 | I37: 11594 | J37: 11452 | K37: 13951 | L37: 2403 | M37: 10474 | N37: 10609 | O37: 10051 | P37: 9375 | Q37: 11508 | R37: 10888 | S37: 12165 | T37: 9396 | U37: 12494 | V37: 14761 | W37: 17685 | X37: 0.00047796795 | Y37: 0.022431012 | Z37: 0.086175823 | AA37: 0.11307768
A38: 260130 | B38: 6946 | C38: Japan | D38: Nippon Avionics Co., Ltd. | E38: Sep'26 | F38: 10.4 | G38: 4532 | H38: 5050 | I38: 3263 | J38: 4599 | K38: 4762 | L38: 5130 | M38: 3605 | N38: 5064 | O38: 4584 | P38: 4802 | Q38: 4087 | R38: 5019 | S38: 4564 | T38: 6452 | U38: 5037 | V38: 7666 | W38: 7023 | X38: 0.089324383 | Y38: 0.047212007 | Z38: 0.12561693 | AA38: 0.10367216
A39: 260130 | B39: 8316 | C39: Japan | D39: Sumitomo Mitsui Financial Group, Inc. | E39: Sep'26 | F39: 8.3 | G39: 942800 | H39: 82233 | I39: 994279 | J39: 1039205 | K39: 1013583 | L39: 479754 | M39: 1040727 | N39: 1129858 | O39: 1210013 | P39: 122089 | Q39: 1286487 | R39: 1534002 | S39: 1296678 | T39: -842478 | U39: 1358238 | V39: 1611881 | W39: 1579788 | X39: -0.22753214 | Y39: 0.021910783 | Z39: 0.023272194 | AA39: 0.082676293
A40: 260130 | B40: 9719 | C40: Japan | D40: SCSK Corporation | E40: Sep'26 | F40: 8.2 | G40: 102729 | H40: 111396 | I40: 104417 | J40: 108682 | K40: 109924 | L40: 122888 | M40: 113371 | N40: 117824 | O40: 120167 | P40: 128944 | Q40: 122543 | R40: 128980 | S40: 133317 | T40: 211225 | U40: 177474 | V40: 193805 | W40: 191813 | X40: 0.16014707 | Y40: 0.092156057 | Z40: 0.099578185 | AA40: 0.081718754
A41: 260130 | B41: 2127 | C41: Japan | D41: Nihon M&A Center Holdings Inc. | E41: Sep'26 | F41: 8.1 | G41: 10853 | H41: 6128 | I41: 9068 | J41: 11031 | K41: 9777 | L41: 11439 | M41: 8246 | N41: 10925 | O41: 11976 | P41: 12989 | Q41: 7638 | R41: 10953 | S41: 11252 | T41: 14234 | U41: 9018 | V41: 13569 | W41: 15151 | X41: 0.029067053 | Y41: 0.031308846 | Z41: 0.057548892 | AA41: 0.081105818
A42: 260130 | B42: 8803 | C42: Japan | D42: Heiwa Real Estate Co., Ltd. | E42: Sep'26 | F42: 6.1 | G42: 7105 | H42: 9432 | I42: 17385 | J42: 7569 | K42: 7179 | L42: 12389 | M42: 15028 | N42: 13163 | O42: 7524 | P42: 8718 | Q42: 10579 | R42: 8182 | S42: 8186 | T42: 15128 | U42: 13123 | V42: 8697 | W42: 10952 | X42: 0.17972802 | Y42: 0.060463458 | Z42: 0.011542168 | AA42: 0.061284176
A43: 260130 | B43: 6961 | C43: Japan | D43: Enplas Corporation | E43: Sep'26 | F43: 6 | G43: 7755 | H43: 9021 | I43: 10115 | J43: 10982 | K43: 11173 | L43: 9970 | M43: 9715 | N43: 9485 | O43: 8754 | P43: 9851 | Q43: 10601 | R43: 9099 | S43: 9105 | T43: 9264 | U43: 8999 | V43: 11902 | W43: 11473 | X43: -0.015185224 | Y43: -0.042081484 | Z43: 0.076864014 | AA43: 0.060300484
A44: 260130 | B44: 6196 | C44: Japan | D44: Strike Company,Limited | E44: Mar'26 | F44: 5.8 | G44: 2355 | H44: 2861 | I44: 1916 | J44: 3595 | K44: 1969 | L44: 4113 | M44: 3050 | N44: 4694 | O44: 3676 | P44: 5554 | Q44: 4042 | R44: 4866 | S44: 3665 | T44: 5286 | U44: 5490 | V44: 5873 | W44: 4842 | X44: -0.014784575 | Y44: 0.081079568 | Z44: 0.052157249 | AA44: 0.057940337
A45: 260130 | B45: 8308 | C45: Japan | D45: Resona Holdings, Inc. | E45: Sep'26 | F45: 5.7 | G45: 173983 | H45: 178409 | I45: 194300 | J45: 217183 | K45: 195938 | L45: 193615 | M45: 178656 | N45: 210154 | O45: 187334 | P45: 236919 | Q45: 219748 | R45: 243077 | S45: 230960 | T45: 259613 | U45: 248800 | V45: 251222 | W45: 286985 | X45: 0.024383692 | Y45: 0.030472059 | Z45: 0.0082904982 | AA45: 0.056556918
A46: 260130 | B46: 8341 | C46: Japan | D46: The 77 Bank, Ltd. | E46: Sep'26 | F46: 5.5 | G46: 27470 | H46: 26921 | I46: 30911 | J46: 27118 | K46: 30476 | L46: 31502 | M46: 36678 | N46: 35841 | O46: 32103 | P46: 40464 | Q46: 43379 | R46: 38316 | S46: 40171 | T46: 42126 | U46: 40982 | V46: 44774 | W46: 49467 | X46: 0.010238403 | Y46: -0.014616567 | Z46: 0.039964108 | AA46: 0.055315882
A47: 260130 | B47: 6526 | C47: Japan | D47: Socionext Inc. | E47: Sep'26 | F47: 5 | I47: 39934 | J47: 42833 | K47: 56074 | L47: 53926 | M47: 61447 | N47: 55541 | O47: 52650 | P47: 51608 | Q47: 52783 | R47: 46398 | S47: 46083 | T47: 43271 | U47: 34553 | V47: 52656 | W47: 54931 | X47: -0.042347312 | Y47: -0.096692922 | Z47: 0.036745838 | AA47: 0.050112424
A48: 260130 | B48: 2121 | C48: Japan | D48: MIXI, Inc. | E48: Sep'26 | F48: 4.9 | G48: 29502 | H48: 37010 | I48: 31022 | J48: 34712 | K48: 39068 | L48: 42065 | M48: 29207 | N48: 34761 | O48: 41241 | P48: 41659 | Q48: 30087 | R48: 38733 | S48: 41532 | T48: 44495 | U48: 31323 | V48: 36105 | W48: 48997 | X48: 0.018656545 | Y48: 0.0079820726 | Z48: -0.016837196 | AA48: 0.048646183
A49: 260130 | B49: 7327 | C49: Japan | D49: Daishi Hokuetsu Financial Group, Inc. | E49: Sep'26 | F49: 4.7 | G49: 30022 | H49: 30809 | I49: 37378 | J49: 33124 | K49: 30140 | L49: 28562 | M49: 38919 | N49: 34477 | O49: 31639 | P49: 31389 | Q49: 41750 | R49: 31320 | S49: 38855 | T49: 35784 | U49: 45728 | V49: 71647 | W49: 47817 | X49: 0.030666927 | Y49: 0.026931331 | Z49: 0.26585667 | AA49: 0.04667368
A50: 260130 | B50: 8388 | C50: Japan | D50: The Awa Bank, Ltd. | E50: Sep'26 | F50: 4.6 | G50: 16114 | H50: 16398 | I50: 18816 | J50: 18049 | K50: 26480 | L50: 15872 | M50: 15521 | N50: 15706 | O50: 17162 | P50: 15543 | Q50: 17950 | R50: 16573 | S50: 18265 | T50: 15297 | U50: 21196 | V50: 21441 | W50: 21746 | X50: -0.0036001229 | Y50: 0.047675699 | Z50: 0.068245223 | AA50: 0.045683014
A51: 260130 | B51: 8377 | C51: Japan | D51: Hokuhoku Financial Group, Inc. | E51: Sep'26 | F51: 4.4 | G51: 40966 | H51: 34196 | I51: 39737 | J51: 40851 | K51: 36945 | L51: 51481 | M51: 38901 | N51: 48546 | O51: 45239 | P51: 38244 | Q51: 41538 | R51: 43956 | S51: 45085 | T51: 42665 | U51: 50206 | V51: 55838 | W51: 53614 | X51: 0.02618719 | Y51: 0.050033479 | Z51: 0.065317296 | AA51: 0.04401065
A52: 260130 | B52: 6135 | C52: Japan | D52: Makino Milling Machine Co., Ltd. | E52: Sep'26 | F52: 4.1 | G52: 47532 | H52: 63719 | I52: 46481 | J52: 56558 | K52: 62459 | L52: 62487 | M52: 53850 | N52: 54665 | O52: 54477 | P52: 62368 | Q52: 51868 | R52: 56369 | S52: 60557 | T52: 65422 | U52: 55397 | V52: 64024 | W52: 70711 | X52: 0.013211514 | Y52: 0.015067288 | Z52: 0.032198364 | AA52: 0.041377343
A53: 260130 | B53: 2326 | C53: Japan | D53: Digital Arts Inc. | E53: Sep'26 | F53: 4 | G53: 2134 | H53: 2365 | I53: 2386 | J53: 2698 | K53: 2574 | L53: 2778 | M53: 2541 | N53: 3022 | O53: 2759 | P53: 3190 | Q53: 2234 | R53: 2604 | S53: 2436 | T53: 2708 | U53: 2270 | V53: 2722 | W53: 2843 | X53: -0.046062691 | Y53: 0.0036064917 | Z53: 0.011778798 | AA53: 0.040153907
A54: 260130 | B54: 4547 | C54: Japan | D54: Kissei Pharmaceutical Co., Ltd. | E54: Sep'26 | F54: 3.9 | G54: 17697 | H54: 15296 | I54: 16285 | J54: 16579 | K54: 18771 | L54: 15858 | M54: 19313 | N54: 17665 | O54: 20881 | P54: 17720 | Q54: 21164 | R54: 21302 | S54: 23203 | T54: 22661 | U54: 22191 | V54: 23640 | W54: 26802 | X54: 0.059252419 | Y54: 0.011626854 | Z54: 0.02616471 | AA54: 0.039249686
A55: 260130 | B55: 2327 | C55: Japan | D55: NS Solutions Corporation | E55: Sep'26 | F55: 3.7 | G55: 64831 | H55: 74714 | I55: 65132 | J55: 69552 | K55: 72094 | L55: 84908 | M55: 68773 | N55: 76000 | O55: 75345 | P55: 90513 | Q55: 76826 | R55: 79786 | S55: 83682 | T55: 98007 | U55: 82684 | V55: 95691 | W55: 97020 | X55: 0.022653692 | Y55: 0.017315941 | Z55: 0.046214105 | AA55: 0.037043415
A56: 260130 | B56: 9708 | C56: Japan | D56: Imperial Hotel, Ltd. | E56: Sep'26 | F56: 3.6 | G56: 9435 | H56: 6892 | I56: 9434 | J56: 9173 | K56: 13082 | L56: 12083 | M56: 12472 | N56: 11766 | O56: 15528 | P56: 13569 | Q56: 13326 | R56: 11413 | S56: 14624 | T56: 13247 | U56: 13584 | V56: 11842 | W56: 16547 | X56: -0.0060832767 | Y56: 0.0049040106 | Z56: 0.0081145494 | AA56: 0.03608083
A57: 260130 | B57: 5844 | C57: Japan | D57: Kyoto Financial Group,Inc. | E57: Sep'26 | F57: 3.6 | G57: 44138 | H57: 14686 | I57: 40416 | J57: 22321 | K57: 29984 | L57: 21488 | M57: 37856 | N57: 24361 | O57: 35514 | P57: 23192 | Q57: 35242 | R57: 28662 | S57: 38748 | T57: 29352 | U57: 42499 | V57: 41796 | W57: 44186 | X57: 0.048949493 | Y57: 0.054975607 | Z57: 0.094312119 | AA57: 0.035683585
A58: 260130 | B58: 9202 | C58: Japan | D58: ANA Holdings Inc. | E58: Sep'26 | F58: 3.6 | G58: 306921 | H58: 282278 | I58: 350419 | J58: 440297 | K58: 467939 | L58: 448829 | M58: 461026 | N58: 541703 | O58: 540852 | P58: 512347 | Q58: 516775 | R58: 582812 | S58: 603197 | T58: 559072 | U58: 548701 | V58: 641699 | W58: 686984 | X58: 0.021093561 | Y58: 0.014114957 | Z58: 0.025672448 | AA58: 0.035613595
A59: 260130 | B59: 1950 | C59: Japan | D59: Nippon Densetsu Kogyo Co., Ltd. | E59: Sep'26 | F59: 3.4 | G59: 41580 | H59: 68306 | I59: 25506 | J59: 35383 | K59: 40833 | L59: 70378 | M59: 28577 | N59: 42462 | O59: 46472 | P59: 76520 | Q59: 33011 | R59: 42614 | S59: 49388 | T59: 91909 | U59: 30234 | V59: 48185 | W59: 56872 | X59: 0.076359703 | Y59: -0.012801837 | Z59: 0.026015083 | AA59: 0.034062153
... A128: 260130 | B128: 2782 | C128: Japan | D128: Seria Co., Ltd. | E128: Sep'26 | F128: -30.4 | G128: 52506 | H128: 51951 | I128: 56241 | J128: 51661 | K128: 53848 | L128: 53280 | M128: 166469 | N128: 166469 | O128: 56733 | P128: 58115 | Q128: 57784 | R128: 178047 | S128: 178047 | T128: 60214 | U128: 60498 | V128: 60884 | W128: 68716 | X128: 0.0044470999 | Y128: 0.0057246273 | Z128: -0.24572468 | AA128: -0.30399869
A129: 260130 | B129: RRKABEL | C129: India | D129: R R Kabel Limited | E129: Sep'26 | F129: 9.2 | H129: 13974 | I129: 12359 | J129: 13672 | K129: 14795 | L129: 15165 | M129: 15973 | N129: 16097 | O129: 16335 | P129: 17541 | Q129: 18081 | R129: 18101 | S129: 17822 | T129: 22178 | U129: 20586 | V129: 21638 | W129: 25359 | X129: 0.064812356 | Y129: 0.032881783 | Z129: 0.044950246 | AA129: 0.091664234
A130: 260130 | B130: MSUMI | C130: India | D130: Motherson Sumi Wiring India Limited | E130: Sep'26 | F130: 5.8 | G130: 14449 | H130: 16563 | I130: 16617 | J130: 18270 | K130: 16766 | L130: 18573 | M130: 18530 | N130: 20970 | O130: 21111 | P130: 22129 | Q130: 21660 | R130: 23230 | S130: 22823 | T130: 25003 | U130: 24808 | V130: 27539 | W130: 28658 | X130: 0.031989493 | Y130: 0.033953147 | Z130: 0.044949095 | AA130: 0.058249229
A131: 260130 | B131: AJANTPHARM | C131: India | D131: Ajanta Pharma Limited | E131: Sep'26 | F131: 4.6 | G131: 8379 | H131: 8703 | I131: 9509 | J131: 9381 | K131: 9718 | L131: 8818 | M131: 10210 | N131: 10284 | O131: 11052 | P131: 10541 | Q131: 11449 | R131: 11866 | S131: 11461 | T131: 11704 | U131: 13027 | V131: 13537 | W131: 13748 | X131: 0.025663658 | Y131: 0.033950086 | Z131: 0.034770486 | AA131: 0.045989262
A132: 260130 | B132: INTELLECT | C132: India | D132: Intellect Design Arena Limited | E132: Sep'26 | F132: 4.4 | G132: 5083 | H132: 5094 | I132: 5413 | J132: 5275 | K132: 5469 | L132: 6155 | M132: 6394 | N132: 6190 | O132: 6343 | P132: 6137 | Q132: 6063 | R132: 5581 | S132: 6096 | T132: 7259 | U132: 7017 | V132: 7581 | W132: 7314 | X132: 0.046990828 | Y132: 0.038161526 | Z132: 0.077062382 | AA132: 0.043573141
A133: 260130 | B133: JPPOWER | C133: India | D133: Jaiprakash Power Ventures Limited | E133: Jun'26 | F133: 4 | G133: 9019 | H133: 14014 | I133: 14062 | J133: 18204 | K133: 13854 | L133: 12011 | M133: 13799 | N133: 17078 | O133: 13498 | P133: 21903 | Q133: 15148 | R133: 17547 | S133: 12264 | T133: 11402 | U133: 13409 | V133: 15832 | W133: 14383 | X133: -0.15705483 | Y133: -0.030854669 | Z133: -0.031397605 | AA133: 0.040051411
A134: 260130 | B134: AADHARHFC | C134: India | D134: Aadhar Housing Finance Limited | E134: Jun'26 | F134: 4 | G134: 1642 | H134: 2111 | I134: 2613 | J134: 2658 | K134: 2658 | L134: 3395 | M134: 3395 | N134: 3263 | O134: 3739 | P134: 4102 | Q134: 4493 | R134: 4175 | S134: 4658 | T134: 4821 | U134: 5284 | V134: 4927 | W134: 5445 | X134: 0.041255451 | Y134: 0.043588472 | Z134: 0.039708523 | AA134: 0.039969528
A135: 260130 | B135: MEDPLUS | C135: India | D135: MedPlus Health Services Limited | E135: Sep'26 | F135: 3.9 | G135: 9335 | H135: 9659 | I135: 9937 | J135: 11206 | K135: 11903 | L135: 12530 | M135: 12843 | N135: 14086 | O135: 14415 | P135: 14905 | Q135: 14888 | R135: 15762 | S135: 15614 | T135: 15096 | U135: 15426 | V135: 16793 | W135: 18061 | X135: 0.0031224967 | Y135: 0.008767927 | Z135: 0.016656435 | AA135: 0.038885093
A136: 260130 | B136: SUNPHARMA | C136: India | D136: Sun Pharmaceutical Industries Limited | E136: Sep'26 | F136: 3.4 | G136: 98631 | H136: 94468 | I136: 107618 | J136: 109523 | K136: 112410 | L136: 109307 | M136: 119408 | N136: 121924 | O136: 123807 | P136: 119829 | Q136: 126528 | R136: 132914 | S136: 136755 | T136: 129588 | U136: 138514 | V136: 144783 | W136: 155205 | X136: 0.018911838 | Y136: 0.02279639 | Z136: 0.022070733 | AA136: 0.033567426
A137: 260130 | B137: ASTERDM | C137: India | D137: Aster DM Healthcare Limited | E137: Sep'26 | F137: 3.1 | G137: 26496 | H137: 27278 | I137: 26621 | J137: 28163 | K137: 31921 | L137: 0 | M137: 32154 | N137: 33166 | O137: 37106 | P137: 0 | Q137: 10019 | R137: 10864 | S137: 10498 | T137: 10003 | U137: 10779 | V137: 11972 | W137: 11858 | X137: 0.31875976 | Y137: 0.018364585 | Z137: 0.026290812 | AA137: 0.031443633
A138: 260130 | B138: NIACL | C138: India | D138: The New India Assurance Company Limited | E138: Sep'26 | F138: 2.9 | G138: 94626 | H138: 85666 | I138: 85774 | J138: 115793 | K138: 105488 | L138: 102627 | M138: 98889 | N138: 105568 | O138: 113564 | P138: 113262 | Q138: 104179 | R138: 107770 | S138: 107058 | T138: 110260 | U138: 117190 | V138: 134433 | W138: 120629 | X138: -0.0069447497 | Y138: 0.030309807 | Z138: 0.060285612 | AA138: 0.028939675
A139: 260130 | B139: JINDALSTEL | C139: India | D139: Jindal Steel Limited | E139: Sep'26 | F139: 2.6 | G139: 125249 | H139: 143395 | I139: 130454 | J139: 135214 | K139: 124524 | L139: 136919 | M139: 125883 | N139: 122502 | O139: 117013 | P139: 134870 | Q139: 136178 | R139: 112133 | S139: 117507 | T139: 131832 | U139: 122945 | V139: 116859 | W139: 130266 | X139: -0.0060676509 | Y139: -0.026590978 | Z139: 0.0097560573 | AA139: 0.026084397
A140: 260130 | B140: POWERGRID | C140: India | D140: Power Grid Corporation of India Limited | E140: Sep'26 | F140: 2.5 | G140: 104469 | H140: 106913 | I140: 109052 | J140: 111506 | K140: 112618 | L140: 122856 | M140: 110481 | N140: 112671 | O140: 115498 | P140: 119781 | Q140: 110062 | R140: 112778 | S140: 112330 | T140: 122754 | U140: 111962 | V140: 114760 | W140: 123951 | X140: 0.0065347697 | Y140: 0.0041491601 | Z140: 0.0043103448 | AA140: 0.025164246
A141: 260130 | B141: LALPATHLAB | C141: India | D141: Dr. Lal PathLabs Limited | E141: Sep'26 | F141: 2.4 | G141: 4969 | H141: 4855 | I141: 5027 | J141: 5338 | K141: 4894 | L141: 4910 | M141: 5410 | N141: 6013 | O141: 5389 | P141: 5454 | Q141: 6019 | R141: 6602 | S141: 5967 | T141: 6026 | U141: 6698 | V141: 7306 | W141: 6598 | X141: 0.023791698 | Y141: 0.027585927 | Z141: 0.027833788 | AA141: 0.024272031
... A148: 260130 | B148: FINPIPE | C148: India | D148: Finolex Industries Limited | E148: Sep'26 | F148: -2.5 | G148: 10053 | H148: 15934 | I148: 11898 | J148: 9411 | K148: 11248 | L148: 11411 | M148: 11792 | N148: 8832 | O148: 10197 | P148: 12354 | Q148: 11405 | R148: 8284 | S148: 10012 | T148: 11718 | U148: 10432 | V148: 8587 | W148: 8977 | X148: -0.015123053 | Y148: -0.023491634 | Z148: 0.0074914701 | AA148: -0.025399396
A149: 260130 | B149: BAIN | C149: France | D149: Société Anonyme des Bains de Mer et du Cercle des Étrangers à Monaco | E149: H1 2026 | F149: 6.6 | N149: 168.13 | O149: 311.41 | P149: 219.1 | Q149: 432.35 | R149: 234.64 | S149: 445.57 | T149: 258.43 | U149: 495.14 | V149: 272.88 | W149: 542.46 | X149: 0.029534566 | Y149: 0.045799021 | Z149: 0.026670758 | AA149: 0.065821117
A150: 260129 | B150: FISI | C150: United States | D150: Banks - Regional | E150: Dec '25 Dec 31, 2025 | F150: 99.862943 | G150: 53.73 | H150: 48.56 | I150: 52.39 | J150: 51.41 | K150: 47.97 | L150: 48.53 | M150: 50.57 | N150: 51.2 | O150: 49.98 | P150: 56.44 | Q150: 63.17 | R150: 47.02 | S150: -55.86 | T150: 54.31 | U150: 57.18 | V150: 61.11 | W150: 60.72 | X150: -0.019229033 | Y150: -0.05513623 | Z150: 0.13726254 | AA150: 0.99862943
A151: 260129 | B151: IVR | C151: United States | D151: REIT - Mortgage | E151: Dec '25 Dec 31, 2025 | F151: 65.753804 | G151: -57.46 | H151: -221.12 | I151: -102.4 | J151: -95.57 | K151: 41.5 | L151: 26.53 | M151: 9.38 | N151: -63.78 | O151: 32.06 | P151: 33.82 | Q151: -8.32 | R151: 45.33 | S151: 8.52 | T151: 24.3 | U151: -18.46 | V151: 57.94 | W151: 56.06 | X151: -0.1199748 | Y151: -0.1452098 | Z151: 0.21125817 | AA151: 0.65753804
A152: 260129 | B152: WDC | C152: United States | D152: Computer Hardware | E152: Jan '26 Jan 2, 2026 | F152: 39.095503 | G152: 4833 | H152: 4381 | I152: 4528 | J152: 3736 | K152: 3107 | L152: 2803 | M152: 2672 | N152: 2750 | O152: 0 | P152: 1752 | Q152: 0 | R152: 2212 | S152: 0 | T152: 2294 | U152: 2605 | V152: 2818 | W152: 3017 | X152: 0.13673058 | Y152: 0.57811806 | Z152: 0.085220082 | AA152: 0.39095503
A153: 260129 | B153: PFSI | C153: United States | D153: Mortgage Finance | E153: Dec '25 Dec 31, 2025 | F153: 24.722392 | G153: 848.95 | H153: 444.05 | I153: 398.6 | J153: 380.35 | K153: 405.49 | L153: 539.17 | M153: 499.51 | N153: 602.23 | O153: 364.77 | P153: 333.84 | Q153: 507.25 | R153: 1040 | S153: -79.81 | T153: 862.08 | U153: 690.76 | V153: 1026 | W153: 538.01 | X153: 0.29325813 | Y153: 0.078775885 | Z153: -0.0055709641 | AA153: 0.24722392
A154: 260129 | B154: SNDK | C154: United States | D154: Computer Hardware | E154: Jan '26 Jan 2, 2026 | F154: 14.768638 | G154: 1746 | H154: 1735 | I154: 1332 | J154: 1237 | K154: 1452 | N154: 1533 | O154: 1665 | P154: 1705 | Q154: 1760 | R154: 1883 | S154: 1876 | T154: 1695 | U154: 1901 | V154: 2308 | W154: 3025 | X154: -0.0013842746 | Y154: 0.019545329 | Z154: 0.057783821 | AA154: 0.14768638
A155: 260129 | B155: CNX | C155: United States | D155: Oil & Gas E&P | E155: Dec '25 Dec 31, 2025 | F155: 14.671467 | G155: 908.93 | H155: 812.5 | I155: 1072 | J155: 1179 | K155: 860.84 | L155: 513.7 | M155: 295.89 | N155: 302.46 | O155: 350.62 | P155: 376.78 | Q155: 307.12 | R155: 334.72 | S155: 327.24 | T155: 610.55 | U155: 541.91 | V155: 450.85 | W155: 610.48 | X155: 0.17369563 | Y155: 0.14863607 | Z155: 0.064003924 | AA155: 0.14671467
A156: 260129 | B156: PMT | C156: United States | D156: REIT - Mortgage | E156: Dec '25 Dec 31, 2025 | F156: 13.97301 | G156: 221.21 | H156: -221.88 | I156: -112.28 | J156: 84.09 | K156: 104.41 | L156: 227.81 | M156: 178.45 | N156: 2.5 | O156: 317.11 | P156: 102.41 | Q156: 121.75 | R156: 265.78 | S156: 14.66 | T156: 189.06 | U156: 145.33 | V156: 215.61 | W156: 93.56 | X156: 0.17172017 | Y156: 0.039881607 | Z156: -0.081599792 | AA156: 0.1397301
A157: 260129 | B157: BX | C157: United States | D157: Asset Management | E157: Dec '25 Dec 31, 2025 | F157: 11.109374 | G157: 5655 | H157: 4987 | I157: 404.08 | J157: 778.23 | K157: 1847 | L157: 1292 | M157: 2738 | N157: 2367 | O157: 1287 | P157: 3535 | Q157: 2668 | R157: 3648 | S157: 2811 | T157: 3245 | U157: 3801 | V157: 2934 | W157: 4232 | X157: -0.022903175 | Y157: 0.091577756 | Z157: -0.052869308 | AA157: 0.11109374
A158: 260129 | B158: MXL | C158: United States | D158: Semiconductors | E158: Dec '25 Dec 31, 2025 | F158: 10.456575 | G158: 247.89 | H158: 263.93 | I158: 280.01 | J158: 285.73 | K158: 290.59 | L158: 248.44 | M158: 183.94 | N158: 135.53 | O158: 125.35 | P158: 95.27 | Q158: 91.99 | R158: 81.1 | S158: 92.17 | T158: 95.93 | U158: 108.81 | V158: 126.46 | W158: 136.44 | X158: 0.0018306382 | Y158: 0.046568288 | Z158: 0.11999683 | AA158: 0.10456575
A159: 260129 | B159: LPLA | C159: United States | D159: Capital Markets | E159: Dec '25 Dec 31, 2025 | F159: 9.3846864 | G159: 2067 | H159: 2038 | I159: 2010 | J159: 2130 | K159: 2296 | L159: 2379 | M159: 2424 | N159: 2474 | O159: 2589 | P159: 2773 | Q159: 2867 | R159: 3041 | S159: 3404 | T159: 3584 | U159: 3729 | V159: 4446 | W159: 4827 | X159: 0.067107985 | Y159: 0.066842432 | Z159: 0.1021224 | AA159: 0.093846864
A160: 260129 | B160: AJG | C160: United States | D160: Insurance Brokers | E160: Dec '25 Dec 31, 2025 | F160: 9.057791 | G160: 1904 | H160: 2385 | I160: 1982 | J160: 1976 | K160: 1927 | L160: 2607 | M160: 2326 | N160: 2352 | O160: 2274 | P160: 3125 | Q160: 2637 | R160: 2631 | S160: 2534 | T160: 3441 | U160: 2945 | V160: 3158 | W160: 3628 | X160: 0.028919191 | Y160: 0.027394823 | Z160: 0.045623756 | AA160: 0.09057791
A161: 260129 | B161: IP | C161: United States | D161: Packaging & Containers | E161: Dec '25 Dec 31, 2025 | F161: 8.5373885 | G161: 5086 | H161: 5237 | I161: 5389 | J161: 5402 | K161: 5133 | L161: 5020 | M161: 4682 | N161: 4613 | O161: 4601 | P161: 4619 | Q161: 0 | R161: 3979 | S161: 4580 | T161: 5901 | U161: 0 | V161: 6222 | W161: 6006 | X161: 0.097283351 | Y161: 0 | Z161: 0.15511757 | AA161: 0.085373885
A162: 260129 | B162: VLY | C162: United States | D162: Banks - Regional | E162: Dec '25 Dec 31, 2025 | F162: 8.2156332 | G162: 339.71 | H162: 350.49 | I162: 429.5 | J162: 505.06 | K162: 508.16 | L162: 468.93 | M162: 471.47 | N162: 457.77 | O162: 424.84 | P162: 404.2 | Q162: 365.04 | R162: 382.96 | S162: 365.9 | T162: 406.42 | U162: 448.08 | V162: 483.79 | W162: 505.91 | X162: 0.0014623543 | Y162: 0.05462008 | Z162: 0.062886688 | AA162: 0.082156332
A163: 260129 | B163: SBCF | C163: United States | D163: Banks - Regional | E163: Dec '25 Dec 31, 2025 | F163: 8.0549816 | G163: 94.94 | H163: 85.34 | I163: 97.79 | J163: 99.71 | K163: 123.23 | L163: 119.88 | M163: 149.3 | N163: 134.41 | O163: 124.17 | P163: 124.21 | Q163: 121.69 | R163: 124.07 | S163: 129.17 | T163: 134.45 | U163: 144.01 | V163: 148.92 | W163: 174 | X163: 0.020515286 | Y163: 0.043817975 | Z163: 0.046736882 | AA163: 0.080549816
A164: 260129 | B164: FFWM | C164: United States | D164: Banks - Regional | E164: Dec '25 Dec 31, 2025 | F164: 6.7978197 | G164: 71.91 | H164: 90.71 | I164: 95.03 | J164: 99.88 | K164: 80.77 | L164: 70.04 | M164: 60.18 | N164: 65.79 | O164: 56.14 | P164: 50.49 | Q164: 58.29 | R164: -56.74 | S164: 44.03 | T164: 67.98 | U164: 49.05 | V164: -1.45 | W164: 54.88 | X164: 0.18205475 | Y164: -0.081366678 | Z164: 0.53000383 | AA164: 0.067978197
A165: 260129 | B165: ALGM | C165: United States | D165: Semiconductors | E165: Dec '25 Dec 26, 2025 | F165: 6.5120055 | G165: 186.63 | H165: 200.29 | I165: 217.75 | J165: 237.67 | K165: 248.79 | L165: 269.45 | M165: 278.29 | N165: 275.51 | O165: 254.98 | P165: 240.58 | Q165: 166.92 | R165: 187.39 | S165: 177.87 | T165: 192.82 | U165: 203.41 | V165: 214.29 | W165: 229.21 | X165: -0.061804441 | Y165: 0.050331034 | Z165: 0.03532548 | AA165: 0.065120055
A166: 260129 | B166: TAL | C166: United States | D166: Education & Training Services | E166: Nov '25 Nov 30, 2025 | F166: 6.171034 | G166: 1021 | H166: 541.15 | I166: 224.05 | J166: 294.06 | K166: 232.68 | L166: 268.99 | M166: 275.44 | N166: 411.93 | O166: 373.51 | P166: 429.56 | Q166: 414.19 | R166: 619.36 | S166: 606.45 | T166: 610.24 | U166: 575 | V166: 861.35 | W166: 770.17 | X166: 0.087303581 | Y166: 0.071463488 | Z166: 0.10036706 | AA166: 0.06171034
... A239: 260129 | B239: INDT | C239: Sweden | D239: Indutrade AB (publ) | E239: Dec '25 Dec 31, 2025 | F239: -0.34014657 | G239: 5726 | H239: 6398 | I239: 6683 | J239: 6707 | K239: 7228 | L239: 8063 | M239: 8100 | N239: 7851 | O239: 7821 | P239: 7744 | Q239: 8491 | R239: 7973 | S239: 8336 | T239: 8036 | U239: 8121 | V239: 7846 | W239: 8226 | X239: 0.008972468 | Y239: -0.01126812 | Z239: -0.0039117846 | AA239: -0.0034014657
A240: 260129 | B240: 8421 | C240: Japan | D240: Shinkin Central Bank | E240: Dec '25 Dec 31, 2025 | F240: 6.8295977 | G240: 34923 | H240: 38607 | I240: 70037 | J240: 42358 | K240: 74298 | L240: 80940 | M240: 61334 | N240: 52580 | O240: 71705 | P240: 64359 | Q240: 42965 | R240: 34312 | S240: 41711 | T240: 44628 | U240: 47771 | V240: 48053 | W240: 54152 | X240: -0.10761561 | Y240: 0.029373655 | Z240: 0.081586729 | AA240: 0.068295977
A241: 260129 | B241: 6952 | C241: Japan | D241: Casio Computer Co.,Ltd. | E241: Dec '25 Dec 31, 2025 | F241: 6.4196131 | G241: 68299 | H241: 58111 | I241: 61269 | J241: 72041 | K241: 67883 | L241: 62638 | M241: 62681 | N241: 70862 | O241: 67742 | P241: 67543 | Q241: 65217 | R241: 71730 | S241: 58826 | T241: 65984 | U241: 62191 | V241: 70460 | W241: 75354 | X241: -0.0059206429 | Y241: -0.01156034 | Z241: -0.004908573 | AA241: 0.064196131
A242: 260129 | B242: 4373 | C242: Japan | D242: Simplex Holdings, Inc. | E242: Dec '25 Dec 31, 2025 | F242: 4.6681296 | G242: 7648 | H242: 7317 | I242: 8048 | J242: 8819 | K242: 8941 | L242: 9138 | M242: 9404 | N242: 10139 | O242: 10408 | P242: 10757 | Q242: 10954 | R242: 10922 | S242: 12242 | T242: 13276 | U242: 13464 | V242: 14337 | W242: 14731 | X242: 0.056133705 | Y242: 0.05296029 | Z242: 0.068431388 | AA242: 0.046681296
A243: 260129 | B243: 4519 | C243: Japan | D243: Chugai Pharmaceutical Co., Ltd. | E243: Dec '25 Dec 31, 2025 | F243: 3.6440276 | G243: 322266 | H243: 360554 | I243: 235612 | J243: 225284 | K243: 438496 | L243: 312240 | M243: 267417 | N243: 257897 | O243: 273812 | P243: 236949 | Q243: 315911 | R243: 315678 | S243: 302073 | T243: 288459 | U243: 290004 | V243: 333176 | W243: 346301 | X243: 0.044002662 | Y243: -0.021198392 | Z243: 0.014627817 | AA243: 0.036440276
A244: 260129 | B244: 6861 | C244: Japan | D244: Keyence Corporation | E244: Dec '25 Dec 20, 2025 | F244: 2.7243214 | G244: 199978 | H244: 199978 | I244: 192007 | J244: 251993 | K244: 236618 | L244: 241804 | M244: 222274 | N244: 243806 | O244: 241109 | P244: 260099 | Q244: 247223 | R244: 268327 | S244: 259640 | T244: 283955 | U244: 261076 | V244: 284224 | W244: 289305 | X244: 0.023042841 | Y244: 0.013079418 | Z244: 0.014815498 | AA244: 0.027243214
A245: 260129 | B245: 7380 | C245: Japan | D245: Juroku Financial Group,Inc. | E245: Dec '25 Dec 31, 2025 | F245: 2.1199224 | G245: 26846 | H245: 33713 | I245: 29047 | J245: 28538 | K245: 25509 | L245: 25228 | M245: 29318 | N245: 30091 | O245: 32864 | P245: 29151 | Q245: 29002 | R245: 28920 | S245: 29702 | T245: 37379 | U245: 32161 | V245: 36329 | W245: 32576 | X245: 0.070460287 | Y245: 0.025271393 | Z245: 0.057809647 | AA245: 0.021199224
A246: 260129 | B246: 4290 | C246: Japan | D246: Prestige International Inc. | E246: Dec '25 Dec 31, 2025 | F246: 2.0638762 | G246: 11967 | H246: 12484 | I246: 12611 | J246: 13568 | K246: 14273 | L246: 14110 | M246: 13917 | N246: 14846 | O246: 14981 | P246: 14994 | Q246: 15048 | R246: 15722 | S246: 16831 | T246: 16118 | U246: 16724 | V246: 17676 | W246: 18221 | X246: 0.017956706 | Y246: 0.026302987 | Z246: 0.02987996 | AA246: 0.020638762
A247: 260129 | B247: 9044 | C247: Japan | D247: Nankai Electric Railway Co., Ltd. | E247: Dec '25 Dec 31, 2025 | F247: 2.0252233 | G247: 56743 | H247: 53436 | I247: 51842 | J247: 56398 | K247: 55548 | L247: 57492 | M247: 54845 | N247: 62827 | O247: 66417 | P247: 57505 | Q247: 59722 | R247: 63857 | S247: 63535 | T247: 73673 | U247: 62713 | V247: 63803 | W247: 68876 | X247: 0.066094621 | Y247: 0.01146913 | Z247: -0.0002047176 | AA247: 0.020252233
A248: 260129 | B248: 4307 | C248: Japan | D248: Nomura Research Institute, Ltd. | E248: Dec '25 Dec 31, 2025 | F248: 1.7578652 | G248: 155973 | H248: 163687 | I248: 167537 | J248: 171516 | K248: 177005 | L248: 176106 | M248: 176709 | N248: 185355 | O248: 187954 | P248: 186537 | Q248: 188110 | R248: 188668 | S248: 191467 | T248: 196568 | U248: 195770 | V248: 201295 | W248: 205268 | X248: 0.01328993 | Y248: 0.01001552 | Z248: 0.016346202 | AA248: 0.017578652
A249: 260129 | B249: 6754 | C249: Japan | D249: Anritsu Corporation | E249: Dec '25 Dec 31, 2025 | F249: 1.6576421 | G249: 24632 | H249: 29523 | I249: 26180 | J249: 27783 | K249: 27719 | L249: 29236 | M249: 22742 | N249: 28153 | O249: 26886 | P249: 32171 | Q249: 25229 | R249: 28080 | S249: 27531 | T249: 32139 | U249: 23620 | V249: 28073 | W249: 29377 | X249: -0.00028315828 | Y249: -0.014241585 | Z249: -6.2853551e-05 | AA249: 0.016576421
A250: 260129 | B250: 1944 | C250: Japan | D250: Kinden Corporation | E250: Dec '25 Dec 31, 2025 | F250: 1.5573946 | G250: 131054 | H250: 191596 | I250: 115451 | J250: 142657 | K250: 144565 | L250: 206459 | M250: 112798 | N250: 157872 | O250: 156442 | P250: 227404 | Q250: 133244 | R250: 164796 | S250: 166545 | T250: 240473 | U250: 141412 | V250: 179966 | W250: 177889 | X250: 0.018886138 | Y250: 0.011584863 | Z250: 0.021269556 | AA250: 0.015573946
A251: 260129 | B251: 6504 | C251: Japan | D251: Fuji Electric Co., Ltd. | E251: Dec '25 Dec 31, 2025 | F251: 1.2152003 | G251: 222296 | H251: 290245 | I251: 203940 | J251: 243198 | K251: 243638 | L251: 318671 | M251: 234148 | N251: 257544 | O251: 267969 | P251: 343553 | Q251: 236387 | R251: 260990 | S251: 293687 | T251: 332343 | U251: 247916 | V251: 295244 | W251: 307895 | X251: -0.0098799859 | Y251: 0.010262532 | Z251: 0.030181438 | AA251: 0.012152003
... A271: 260129 | B271: 7148 | C271: Japan | D271: Financial Partners Group Co.,Ltd. | E271: Dec '25 Dec 31, 2025 | F271: -9.9919855 | G271: 15673 | H271: 15462 | I271: 16346 | J271: 11712 | K271: 17416 | L271: 14944 | M271: 15676 | N271: 23113 | O271: 24393 | P271: 26303 | Q271: 30620 | R271: 26465 | S271: 27963 | T271: 35508 | U271: 27227 | V271: 39066 | W271: 14997 | X271: 0.082666523 | Y271: -0.028144597 | Z271: 0.10755102 | AA271: -0.099919855
A272: 260129 | B272: PRESTIGE | C272: India | D272: Prestige Estates Projects Limited | E272: Dec '25 Dec 31, 2025 | F272: 26.065199 | G272: 13776 | H272: 22516 | I272: 19385 | J272: 14277 | K272: 23170 | L272: 26318 | M272: 16809 | N272: 22364 | O272: 17958 | P272: 21640 | Q272: 18621 | R272: 25862 | S272: 16979 | T272: 15284 | U272: 23073 | V272: 28592 | W272: 38855 | X272: -0.07648432 | Y272: 0.058009538 | Z272: 0.033621518 | AA272: 0.26065199
A273: 260129 | B273: PAYTM | C273: India | D273: One97 Communications Limited | E273: Dec '25 Dec 31, 2025 | F273: 7.4917723 | G273: 14561 | H273: 15409 | I273: 16796 | J273: 19140 | K273: 20622 | L273: 23345 | M273: 23416 | N273: 25186 | O273: 28505 | P273: 22671 | Q273: 15016 | R273: 16595 | S273: 18278 | T273: 19115 | U273: 19175 | V273: 20610 | W273: 24060 | X273: -0.049007718 | Y273: 0.060271868 | Z273: 0.054877465 | AA273: 0.074917723
A274: 260129 | B274: COROMANDEL | C274: India | D274: Coromandel International Limited | E274: Dec '25 Dec 31, 2025 | F274: 6.444095 | G274: 50736 | H274: 42259 | I274: 57291 | J274: 101134 | K274: 83096 | L274: 54758 | M274: 56934 | N274: 69881 | O274: 54642 | P274: 39127 | Q274: 47288 | R274: 74328 | S274: 69352 | T274: 49884 | U274: 70423 | V274: 96541 | W274: 87795 | X274: 0.046750255 | Y274: 0.096054839 | Z274: 0.084144295 | AA274: 0.06444095
...

Sheet Operating Income
B1: 1 | C1: 2 | D1: 3 | E1: 4 | F1: 5 | G1: 6 | H1: 7 | I1: 8 | J1: 9 | K1: 10 | L1: 11 | M1: 12 | N1: 13 | O1: 14 | P1: 15 | Q1: 16 | R1: 17 | S1: 18 | T1: 19 | U1: 20 | V1: 21 | W1: 22
B2: Ticker | C2: Country | D2: Industry | E2: Latest_Date | F2: Growth_Rate | G2: 4Q21 | H2: 1Q22 | I2: 2Q22 | J2: 3Q22 | K2: 4Q22 | L2: 1Q23 | M2: 2Q23 | N2: 3Q23 | O2: 4Q23 | P2: 1Q24 | Q2: 2Q24 | R2: 3Q24 | S2: 4Q24 | T2: 1Q25 | U2: 2Q25 | V2: 3Q25 | W2: 4Q25 | X2: 1Q25 | Y2: 2Q25 | Z2: 3Q25 | AA2: 4Q25
A3: 260129 | B3: SNDK | C3: United States | D3: Computer Hardware | E3: Jan '26 Jan 2, 2026 | F3: 230.56995 | N3: -546 | O3: -198 | P3: 79 | Q3: 185 | R3: 313 | S3: 185 | T3: -42 | U3: 51 | V3: 192 | W3: 1075 | X3: -0.15879265 | Y3: -0.20904836 | Z3: -0.23865878 | AA3: 2.3056995
A4: 260129 | B4: TAL | C4: United States | D4: Education & Training Services | E4: Nov '25 Nov 30, 2025 | F4: 143.57143 | G4: -62.18 | H4: 33.26 | I4: -28.32 | J4: 14.89 | K4: -32.88 | L4: -44.42 | M4: -57.77 | N4: 31.79 | O4: -32.19 | P4: -11.06 | Q4: -17.33 | R4: 47.62 | S4: -17.43 | T4: -16.02 | U4: 14.35 | V4: 96.1 | W4: 93.12 | X4: -2.7555556 | Y4: -10.025316 | Z4: 1.6998597 | AA4: 1.4357143
A5: 260129 | B5: CNX | C5: United States | D5: Oil & Gas E&P | E5: Dec '25 Dec 31, 2025 | F5: 106.10558 | G5: 939.41 | H5: -1236 | I5: 90.52 | J5: -207.27 | K5: 1293 | L5: 955.26 | M5: 567.73 | N5: 50.32 | O5: 664.58 | P5: 65.45 | Q5: 20.67 | R5: 104.8 | S5: -189.17 | T5: -236.88 | U5: 616.3 | V5: 241.65 | W5: 269.1 | X5: -172.76 | Y5: -1.9816022 | Z5: 0.46381969 | AA5: 1.0610558
A6: 260129 | B6: IVR | C6: United States | D6: REIT - Mortgage | E6: Dec '25 Dec 31, 2025 | F6: 89.218984 | G6: -64.65 | H6: -228.42 | I6: -109.54 | J6: -101.43 | K6: 36.46 | L6: 21.46 | M6: 4.25 | N6: -68.56 | O6: 27.31 | P6: 29.16 | Q6: -13.2 | R6: 40.64 | S6: 3.74 | T6: 19.64 | U6: -23.33 | V6: 53.47 | W6: 51.49 | X6: -0.15777262 | Y6: -0.19933097 | Z6: 0.31531089 | AA6: 0.89218984
A7: 260129 | B7: WDC | C7: United States | D7: Computer Hardware | E7: Jan '26 Jan 2, 2026 | F7: 47.159647 | G7: 729 | H7: 524 | I7: 611 | J7: 182 | K7: -245 | L7: -432 | M7: -574 | N7: -539 | O7: 0 | P7: 100 | Q7: 0 | R7: 340 | S7: 0 | T7: 559 | U7: 688 | V7: 795 | W7: 963 | X7: 1.0431818 | Y7: 0.76529477 | Z7: 0.28670447 | AA7: 0.47159647
A8: 260129 | B8: VLO | C8: United States | D8: Oil & Gas Refining & Marketing | E8: Dec '25 Dec 31, 2025 | F8: 35.295841 | G8: 1601 | H8: 1400 | I8: 6237 | J8: 3796 | K8: 4383 | L8: 4067 | M8: 2785 | N8: 3529 | O8: 1575 | P8: 1703 | Q8: 1245 | R8: 527 | S8: 370 | T8: 250 | U8: 1117 | V8: 1677 | W8: 1575 | X8: -0.37789337 | Y8: -0.053511706 | Z8: 0.50795053 | AA8: 0.35295841
A9: 260129 | B9: VLY | C9: United States | D9: Banks - Regional | E9: Dec '25 Dec 31, 2025 | F9: 21.700506 | G9: 157.31 | H9: 156.04 | I9: 132.97 | J9: 246.52 | K9: 245.14 | L9: 203.72 | M9: 190.82 | N9: 194.83 | O9: 88.97 | P9: 129.45 | Q9: 93.33 | R9: 126.67 | S9: 89.06 | T9: 139.12 | U9: 173.09 | V9: 209.96 | W9: 221.7 | X9: 0.022051949 | Y9: 0.17796421 | Z9: 0.15776414 | AA9: 0.21700506
A10: 260129 | B10: KEX | C10: United States | D10: Marine Shipping | E10: Dec '25 Dec 31, 2025 | F10: 17.982016 | G10: 33.21 | H10: 28.25 | I10: 47.29 | J10: 62.03 | K10: 59.54 | L10: 60.42 | M10: 88.03 | N10: 93.2 | O10: 93.24 | P10: 103.8 | Q10: 122.68 | R10: 127.91 | S10: 52.65 | T10: 110.22 | U10: 134.46 | V10: 130.82 | W10: 129.64 | X10: 0.015772406 | Y10: 0.028491269 | Z10: 0.0068431944 | AA10: 0.17982016
A11: 260129 | B11: LMT | C11: United States | D11: Aerospace & Defense | E11: Dec '25 Dec 31, 2025 | F11: 17.90892 | G11: 2498 | H11: 2099 | I11: 654 | J11: 2247 | K11: 2499 | L11: 2161 | M11: 2241 | N11: 2151 | O11: 2490 | P11: 2030 | Q11: 2240 | R11: 2151 | S11: 703 | T11: 2279 | U11: 705 | V11: 2176 | W11: 1753 | X11: 0.034952274 | Y11: -0.20819205 | Z11: 0.0042822885 | AA11: 0.1790892
A12: 260129 | B12: APPF | C12: United States | D12: Software - Application | E12: Dec '25 Dec 31, 2025 | F12: 14.977444 | G12: -7.34 | H12: -14.67 | I12: -10.53 | J12: -7.82 | K12: -17.72 | L12: -26.53 | M12: -2.58 | N12: -0.07 | O12: 43.14 | P12: 34.09 | Q12: 36.03 | R12: 42.57 | S12: 23.66 | T12: 33.78 | U12: 40.51 | V12: 35.05 | W12: 43.58 | X12: -0.0022735607 | Y12: 0.032931491 | Z12: -0.053515514 | AA12: 0.14977444
A13: 260129 | B13: BFH | C13: United States | D13: Credit Services | E13: Dec '25 Dec 31, 2025 | F13: 13.703704 | G13: 0 | H13: 302 | I13: 16 | J13: 189 | K13: -208 | L13: 638 | M13: 86 | N13: 225 | O13: 18 | P13: 188 | Q13: 180 | R13: 40 | S13: -27 | T13: 197 | U13: 174 | V13: 196 | W13: 47 | X13: 0.023622047 | Y13: -0.015384615 | Z13: 0.40625 | AA13: 0.13703704
A14: 260129 | B14: VIRT | C14: United States | D14: Capital Markets | E14: Dec '25 Dec 31, 2025 | F14: 13.336436 | G14: 250.76 | H14: 242.52 | I14: 172.22 | J14: 101.62 | K14: 51.49 | L14: 137.21 | M14: 34.49 | N14: 139.02 | O14: 21.87 | P14: 139.62 | Q14: 155.48 | R14: 150.47 | S14: 220.86 | T14: 226.93 | U14: 284.22 | V14: 192 | W14: 344.09 | X14: 0.13101151 | Y14: 0.1708016 | Z14: 0.047060557 | AA14: 0.13336436
A15: 260129 | B15: BX | C15: United States | D15: Asset Management | E15: Dec '25 Dec 31, 2025 | F15: 13.013368 | G15: 3213 | H15: 2857 | I15: -270.39 | J15: -102.63 | K15: 876.81 | L15: 206.65 | M15: 1371 | N15: 1103 | O15: 454.33 | P15: 1853 | Q15: 1144 | R15: 1863 | S15: 1427 | T15: 1469 | U15: 2004 | V15: 1309 | W15: 2235 | X15: -0.061078416 | Y15: 0.14568863 | Z15: -0.081916309 | AA15: 0.13013368
... A92: 260129 | B92: INDT | C92: Sweden | D92: Indutrade AB (publ) | E92: Dec '25 Dec 31, 2025 | F92: -2.9765013 | G92: 802 | H92: 830 | I92: 908 | J92: 912 | K92: 877 | L92: 1077 | M92: 1061 | N92: 1031 | O92: 974 | P92: 860 | Q92: 1087 | R92: 1015 | S92: 1032 | T92: 874 | U92: 950 | V92: 974 | W92: 918 | X92: 0.0035052579 | Y92: -0.034181637 | Z92: -0.010591578 | AA92: -0.029765013
A93: 260129 | B93: 6952 | C93: Japan | D93: Casio Computer Co.,Ltd. | E93: Dec '25 Dec 31, 2025 | F93: 58.140925 | G93: 8009 | H93: 1969 | I93: 4835 | J93: 5244 | K93: 6411 | L93: 1674 | M93: 4327 | N93: 3850 | O93: 3643 | P93: 2388 | Q93: 4529 | R93: 5812 | S93: 888 | T93: 3007 | U93: 3730 | V93: 5758 | W93: 8669 | X93: 0.045457884 | Y93: -0.056125316 | Z93: -0.0040187542 | AA93: 0.58140925
A94: 260129 | B94: 6702 | C94: Japan | D94: Fujitsu Limited | E94: Dec '25 Dec 31, 2025 | F94: 21.112508 | G94: 65185 | H94: 113339 | I94: 25602 | J94: 75367 | K94: 72316 | L94: 105062 | M94: -1665 | N94: 46445 | O94: 3309 | P94: 207286 | Q94: 21387 | R94: 35008 | S94: 68874 | T94: 0 | U94: 33486 | V94: 71859 | W94: 105656 | X94: -0.62331344 | Y94: 0.096584151 | Z94: 0.26826481 | AA94: 0.21112508
A95: 260129 | B95: 4519 | C95: Japan | D95: Chugai Pharmaceutical Co., Ltd. | E95: Dec '25 Dec 31, 2025 | F95: 8.2434516 | G95: 139062 | H95: 187007 | I95: 99939 | J95: 96887 | K95: 149475 | L95: 98296 | M95: 112614 | N95: 106686 | O95: 121576 | P95: 99873 | Q95: 158321 | R95: 160406 | S95: 123401 | T95: 136650 | U95: 136691 | V95: 156485 | W95: 169006 | X95: 0.067854118 | Y95: -0.037371842 | Z95: -0.0070376273 | AA95: 0.082434516
A96: 260129 | B96: 7380 | C96: Japan | D96: Juroku Financial Group,Inc. | E96: Dec '25 Dec 31, 2025 | F96: 6.0038191 | G96: 7798 | H96: 3765 | I96: 8429 | J96: 7078 | K96: 5716 | L96: 5772 | M96: 7490 | N96: 6522 | O96: 6921 | P96: 6867 | Q96: 8834 | R96: 6915 | S96: 7689 | T96: 7185 | U96: 8874 | V96: 7149 | W96: 9544 | X96: 0.010493318 | Y96: 0.0013062078 | Z96: 0.0076313472 | AA96: 0.060038191
A97: 260129 | B97: 7205 | C97: Japan | D97: Hino Motors, Ltd. | E97: Dec '25 Dec 31, 2025 | F97: 5.2065988 | G97: 18021 | H97: -16022 | I97: 4317 | J97: 12299 | K97: 9020 | L97: -8229 | M97: 1135 | N97: 5632 | O97: -2098 | P97: -12772 | Q97: 6384 | R97: 17713 | S97: 20972 | T97: 12422 | U97: 16946 | V97: 21127 | W97: 24693 | X97: 0.78007245 | Y97: 0.18371571 | Z97: 0.050166782 | AA97: 0.052065988
A98: 260129 | B98: 4373 | C98: Japan | D98: Simplex Holdings, Inc. | E98: Dec '25 Dec 31, 2025 | F98: 4.7802237 | G98: 1602 | H98: 1140 | I98: 1340 | J98: 2010 | K98: 2017 | L98: 1971 | M98: 1707 | N98: 2292 | O98: 2386 | P98: 2516 | Q98: 1625 | R98: 2292 | S98: 3090 | T98: 3892 | U98: 3213 | V98: 3842 | W98: 3761 | X98: 0.14449228 | Y98: 0.14570144 | Z98: 0.12412909 | AA98: 0.047802237
A99: 260129 | B99: 9044 | C99: Japan | D99: Nankai Electric Railway Co., Ltd. | E99: Dec '25 Dec 31, 2025 | F99: 4.0385474 | G99: 6065 | H99: 2328 | I99: 4798 | J99: 4649 | K99: 6442 | L99: 5135 | M99: 6828 | N99: 7411 | O99: 12522 | P99: 4060 | Q99: 9877 | R99: 8380 | S99: 10950 | T99: 5449 | U99: 11296 | V99: 10388 | W99: 12488 | X99: 0.041753089 | Y99: 0.040945291 | Z99: 0.055661816 | AA99: 0.040385474
A100: 260129 | B100: 6754 | C100: Japan | D100: Anritsu Corporation | E100: Dec '25 Dec 31, 2025 | F100: 3.9750816 | G100: 3459 | H100: 5891 | I100: 3019 | J100: 2397 | K100: 2586 | L100: 3701 | M100: -57 | N100: 2994 | O100: 2227 | P100: 4337 | Q100: 624 | R100: 2954 | S100: 2842 | T100: 5607 | U100: 1341 | V100: 3694 | W100: 3378 | X100: 0.11806266 | Y100: 0.059615864 | Z100: 0.058066541 | AA100: 0.039750816
A101: 260129 | B101: 1944 | C101: Japan | D101: Kinden Corporation | E101: Dec '25 Dec 31, 2025 | F101: 2.7990649 | G101: 8303 | H101: 17228 | I101: 354 | J101: 6246 | K101: 6968 | L101: 23863 | M101: 869 | N101: 8267 | O101: 11485 | P101: 22057 | Q101: 1964 | R101: 10913 | S101: 17831 | T101: 30272 | U101: 7245 | V101: 24643 | W101: 20070 | X101: 0.15569033 | Y101: 0.086602165 | Z101: 0.20721088 | AA101: 0.027990649
A102: 260129 | B102: 6504 | C102: Japan | D102: Fuji Electric Co., Ltd. | E102: Dec '25 Dec 31, 2025 | F102: 2.3697199 | G102: 16368 | H102: 41580 | I102: 9873 | J102: 16847 | K102: 15716 | L102: 45979 | M102: 14664 | N102: 20331 | O102: 22663 | P102: 48012 | Q102: 17254 | R102: 23083 | S102: 28095 | T102: 49115 | U102: 17777 | V102: 24352 | W102: 30923 | X102: 0.0094723644 | Y102: 0.0044492841 | Z102: 0.010747861 | AA102: 0.023697199
A103: 260129 | B103: 4307 | C103: Japan | D103: Nomura Research Institute, Ltd. | E103: Dec '25 Dec 31, 2025 | F103: 2.3444311 | G103: 27290 | H103: 21453 | I103: 27992 | J103: 27139 | K103: 28403 | L103: 26044 | M103: 26880 | N103: 31696 | O103: 32043 | P103: 28318 | Q103: 32491 | R103: 32815 | S103: 36288 | T103: 32235 | U103: 36962 | V103: 41331 | W103: 39730 | X103: 0.030151179 | Y103: 0.033408305 | Z103: 0.061576283 | AA103: 0.023444311
A104: 260129 | B104: 4290 | C104: Japan | D104: Prestige International Inc. | E104: Dec '25 Dec 31, 2025 | F104: 2.0774315 | G104: 1860 | H104: 1918 | I104: 1886 | J104: 1953 | K104: 2202 | L104: 1788 | M104: 1890 | N104: 1968 | O104: 1996 | P104: 2067 | Q104: 1730 | R104: 2000 | S104: 2249 | T104: 1967 | U104: 1935 | V104: 2321 | W104: 2425 | X104: -0.012428536 | Y104: 0.025799144 | Z104: 0.039381671 | AA104: 0.020774315
... A124: 260129 | B124: 3593 | C124: Japan | D124: Hogy Medical Co.,Ltd. | E124: Dec '25 Dec 31, 2025 | F124: -17.130406 | G124: 1814 | H124: 1334 | I124: 1858 | J124: 1328 | K124: 1878 | L124: 1571 | M124: 1303 | N124: 1073 | O124: 1111 | P124: 682 | Q124: 1337 | R124: 586 | S124: 1322 | T124: 383 | U124: 951 | V124: 327 | W124: 811 | X124: -0.076139547 | Y124: -0.10639471 | Z124: -0.079888957 | AA124: -0.17130406
A125: 260129 | B125: PRESTIGE | C125: India | D125: Prestige Estates Projects Limited | E125: Dec '25 Dec 31, 2025 | F125: 8.1999766 | G125: 2907 | H125: 2742 | I125: 3149 | J125: 2060 | K125: 4044 | L125: 5173 | M125: 3612 | N125: 4184 | O125: 3718 | P125: 6526 | Q125: 6058 | R125: 7127 | S125: 4288 | T125: 3432 | U125: 6776 | V125: 11187 | W125: 6394 | X125: -0.12892204 | Y125: 0.03434585 | Z125: 0.18776303 | AA125: 0.081999766
A126: 260129 | B126: CANBK | C126: India | D126: Canara Bank | E126: Dec '25 Dec 31, 2025 | F126: 5.5355681 | G126: 24224 | H126: 29307 | I126: 30960 | J126: 34870 | K126: 40209 | L126: 43595 | M126: 51142 | N126: 52495 | O126: 50969 | P126: -596.52 | Q126: 55431 | R126: 56389 | S126: 56092 | T126: 9007 | U126: 65378 | V126: 63812 | W126: 66847 | X126: 0.057397678 | Y126: 0.056223469 | Z126: 0.039723652 | AA126: 0.055355681
A127: 260129 | B127: CONCOR | C127: India | D127: Container Corporation of India Limited | E127: Dec '25 Dec 31, 2025 | F127: 5.3415698 | G127: 3212 | H127: 3205 | I127: 3415 | J127: 3670 | K127: 2905 | L127: 3591 | M127: 2537 | N127: 3934 | O127: 3586 | P127: 3497 | Q127: 2722 | R127: 4157 | S127: 3795 | T127: 2970 | U127: 2711 | V127: 4284 | W127: 4530 | X127: -0.037188625 | Y127: -0.00080621519 | Z127: 0.0093156312 | AA127: 0.053415698
A128: 260129 | B128: VOLTAS | C128: India | D128: Voltas Limited | E128: Dec '25 Dec 31, 2025 | F128: 3.4432981 | G128: 1459 | H128: 2771 | I128: 1685 | J128: 911.4 | K128: 653.2 | L128: 2343 | M128: 1741 | N128: 585.9 | O128: 155.8 | P128: 2061 | Q128: 4104 | R128: 1458 | S128: 1795 | T128: 3695 | U128: 1601 | V128: 459.9 | W128: 2055 | X128: 0.17349756 | Y128: -0.22647485 | Z128: -0.1167505 | AA128: 0.034432981
A129: 260129 | B129: JSWHL | C129: India | D129: JSW Holdings Limited | E129: Dec '25 Dec 31, 2025 | F129: 1.9810574 | G129: 149.09 | H129: 181.65 | I129: 175.48 | J129: 3354 | K129: 247.37 | L129: 232.17 | M129: 231.96 | N129: 861.33 | O129: 245.84 | P129: 235.77 | Q129: 240.34 | R129: 1585 | S129: 259.48 | T129: 255.96 | U129: 263.46 | V129: 799.55 | W129: 290.75 | X129: 0.0087003736 | Y129: 0.0098770495 | Z129: -0.33226871 | AA129: 0.019810574
A130: 260129 | B130: COROMANDEL | C130: India | D130: Coromandel International Limited | E130: Dec '25 Dec 31, 2025 | F130: 0.075412073 | G130: 5020 | H130: 4022 | I130: 6408 | J130: 10112 | K130: 7335 | L130: 5250 | M130: 6611 | N130: 10048 | O130: 2943 | P130: 2557 | Q130: 4405 | R130: 9058 | S130: 6510 | T130: 4274 | U130: 6615 | V130: 10448 | W130: 6531 | X130: 0.076209498 | Y130: 0.091145296 | Z130: 0.052538081 | AA130: 0.00075412073
A131: 260129 | B131: EQUITASBNK | C131: India | D131: Equitas Small Finance Bank Limited | E131: Dec '25 Dec 31, 2025 | F131: -2.0977879 | G131: 2247 | H131: 3926 | I131: 2682 | J131: 2423 | K131: 2791 | L131: 4247 | M131: 3121 | N131: 3302 | O131: 3603 | P131: 4139 | Q131: 3404 | R131: 3497 | S131: 3329 | T131: 3368 | U131: 3148 | V131: 2406 | W131: 3072 | X131: -0.053657179 | Y131: -0.018826298 | Z131: -0.081771848 | AA131: -0.020977879
A132: 260129 | B132: ADANIPOWER | C132: India | D132: Adani Power Limited | E132: Dec '25 Dec 31, 2025 | F132: -4.6059661 | G132: 9864 | H132: 45900 | I132: 49037 | J132: 1148 | K132: 6321 | L132: 12776 | M132: 25796 | N132: 41669 | O132: 36431 | P132: 39329 | Q132: 51987 | R132: 42170 | S132: 38529 | T132: 38789 | U132: 45967 | V132: 39569 | W132: 31028 | X132: -0.0031392611 | Y132: -0.035107158 | Z132: -0.015720286 | AA132: -0.046059661
A133: 260129 | B133: CARBORUNIV | C133: India | D133: Carborundum Universal Limited | E133: Dec '25 Dec 31, 2025 | F133: -7.5148037 | G133: 1297 | H133: 803.88 | I133: 846.4 | J133: 1185 | K133: 1237 | L133: 1409 | M133: 1237 | N133: 1217 | O133: 1443 | P133: 1607 | Q133: 1422 | R133: 1430 | S133: 1244 | T133: 975.13 | U133: 623.6 | V133: 941.8 | W133: 959.6 | X133: -0.11079607 | Y133: -0.15744025 | Z133: -0.1142595 | AA133: -0.075148037
A134: 260129 | B134: PAYTM | C134: India | D134: One97 Communications Limited | E134: Dec '25 Dec 31, 2025 | F134: -170.50931 | G134: -8488 | H134: -8163 | I134: -7311 | J134: -6421 | K134: -4547 | L134: -2872 | M134: -4518 | N134: -4111 | O134: -3604 | P134: -3028 | Q134: -9706 | R134: -5819 | S134: -3877 | T134: 887 | U134: -702 | V134: 40 | W134: 2350 | X134: -0.17454302 | Y134: -0.4863084 | Z134: -0.61602355 | AA134: -1.7050931
A135: 260128 | B135: BBT | C135: United States | D135: Banks - Regional | E135: Dec '25 Dec 31, 2025 | F135: 731.76638 | G135: 38.5 | H135: 33.05 | I135: 33.7 | J135: 37.07 | K135: 36.14 | L135: 8.67 | M135: 27.82 | N135: 28.87 | O135: 28.56 | P135: 19.48 | Q135: 21.65 | R135: 26.75 | S135: 23.82 | T135: 25.48 | U135: 29.59 | V135: -71.87 | W135: 75.19 | X135: =SUM(Q135:T135)/SUM(P135:S135)-1 -> 0.065430752 | Y135: =SUM(R135:U135)/SUM(Q135:T135)-1 -> 0.081269191 | Z135: =SUM(S135:V135)/SUM(R135:U135)-1 -> -0.9335479 | AA135: =SUM(T135:W135)/SUM(S135:V135)-1 -> 7.3176638
A136: 260128 | B136: LC | C136: United States | D136: Banks - Regional | E136: Dec '25 Dec 31, 2025 | F136: 91.618371 | G136: 40.47 | H136: 54.15 | I136: 56.14 | J136: 40.22 | K136: 24.09 | L136: 19.62 | M136: 16.08 | N136: 9.23 | O136: 14.27 | P136: 16.87 | Q136: 19.64 | R136: 18.14 | S136: 11.12 | T136: 15.7 | U136: 53.98 | V136: 57.24 | W136: 137.59 | X136: =SUM(Q136:T136)/SUM(P136:S136)-1 -> -0.017789266 | Y136: =SUM(R136:U136)/SUM(Q136:T136)-1 -> 0.53157895 | Z136: =SUM(S136:V136)/SUM(R136:U136)-1 -> 0.395189 | AA136: =SUM(T136:W136)/SUM(S136:V136)-1 -> 0.91618371
A137: 260128 | B137: LUV | C137: United States | D137: Airlines | E137: Dec '25 Dec 31, 2025 | F137: 36.111111 | G137: 80 | H137: -151 | I137: 1158 | J137: 421 | K137: -350 | L137: -284 | M137: 795 | N137: 128 | O137: 239 | P137: -393 | Q137: 398 | R137: 19 | S137: 261 | T137: -161 | U137: 225 | V137: 35 | W137: 391 | X137: =SUM(Q137:T137)/SUM(P137:S137)-1 -> 0.81403509 | Y137: =SUM(R137:U137)/SUM(Q137:T137)-1 -> -0.33462282 | Z137: =SUM(S137:V137)/SUM(R137:U137)-1 -> 0.046511628 | AA137: =SUM(T137:W137)/SUM(S137:V137)-1 -> 0.36111111
A138: 260128 | B138: OBK | C138: United States | D138: Banks - Regional | E138: Dec '25 Dec 31, 2025 | F138: 25.528285 | G138: 33.18 | H138: 25.96 | I138: 26.12 | J138: 19.06 | K138: 36.3 | L138: 30.57 | M138: 27.73 | N138: 30.07 | O138: 17.54 | P138: 28.86 | Q138: 26.74 | R138: 23.67 | S138: 18 | T138: 28.55 | U138: 18.66 | V138: 10.98 | W138: 37.45 | X138: =SUM(Q138:T138)/SUM(P138:S138)-1 -> -0.0031870052 | Y138: =SUM(R138:U138)/SUM(Q138:T138)-1 -> -0.083333333 | Z138: =SUM(S138:V138)/SUM(R138:U138)-1 -> -0.14277678 | AA138: =SUM(T138:W138)/SUM(S138:V138)-1 -> 0.25528285
B139: CIA | C139: United States | D139: Insurance - Life | E139: Sep '25 Sep 30, 2025 | F139: 12.121212 | G139: -2.73 | H139: 5.81 | I139: 7.18 | J139: 3.97 | K139: 4.82 | L139: 11.41 | M139: 6.72 | N139: 6.04 | O139: 4.64 | P139: 8.77 | Q139: 4.93 | R139: 3.3 | S139: 3.04 | T139: 3.72 | U139: -1.79 | V139: 6.91 | W139: 4.48 | X139: =SUM(Q139:T139)/SUM(P139:S139)-1 -> -0.25199601 | Y139: =SUM(R139:U139)/SUM(Q139:T139)-1 -> -0.44829887 | Z139: =SUM(S139:V139)/SUM(R139:U139)-1 -> 0.43651753 | AA139: =SUM(T139:W139)/SUM(S139:V139)-1 -> 0.12121212
A140: 260128 | B140: MNRO | C140: United States | D140: Auto Parts | E140: Dec '25 Dec 27, 2025 | F140: 23.145695 | G140: 27.44 | H140: 11.47 | I140: 26.26 | J140: 24.57 | K140: 24.54 | L140: 5.93 | M140: 18.19 | N140: 22.95 | O140: 21.49 | P140: 14.87 | Q140: 14.67 | R140: 12.55 | S140: 11.58 | T140: -1.13 | U140: 14.03 | V140: 5.72 | W140: 18.57 | X140: =SUM(Q140:T140)/SUM(P140:S140)-1 -> -0.29811813 | Y140: =SUM(R140:U140)/SUM(Q140:T140)-1 -> -0.016989647 | Z140: =SUM(S140:V140)/SUM(R140:U140)-1 -> -0.18444504 | AA140: =SUM(T140:W140)/SUM(S140:V140)-1 -> 0.23145695
A141: 260128 | B141: FIBK | C141: United States | D141: Banks - Regional | E141: Dec '25 Dec 31, 2025 | F141: 22.713033 | G141: 66.5 | H141: -41.3 | I141: 80.3 | J141: 108.1 | K141: 110 | L141: 74.3 | M141: 86.9 | N141: 94.7 | O141: 80.9 | P141: 76.7 | Q141: 78.4 | R141: 72.7 | S141: 66.7 | T141: 66.4 | U141: 93.5 | V141: 92.6 | W141: 139.2 | X141: =SUM(Q141:T141)/SUM(P141:S141)-1 -> -0.034974533 | Y141: =SUM(R141:U141)/SUM(Q141:T141)-1 -> 0.053131597 | Z141: =SUM(S141:V141)/SUM(R141:U141)-1 -> 0.066488473 | AA141: =SUM(T141:W141)/SUM(S141:V141)-1 -> 0.22713033
B142: FFBC | C142: United States | D142: Banks - Regional | E142: Sep '25 Sep 30, 2025 | F142: 9.1085613 | G142: 67.03 | H142: 54.59 | I142: 50.65 | J142: 64.54 | K142: 47.07 | L142: 79.46 | M142: 87.69 | N142: 81.15 | O142: 78.37 | P142: 71.39 | Q142: 61.74 | R142: 74.8 | S142: 64.88 | T142: 66.91 | U142: 63.6 | V142: 87.86 | W142: 90.68 | X142: =SUM(Q142:T142)/SUM(P142:S142)-1 -> -0.016421685 | Y142: =SUM(R142:U142)/SUM(Q142:T142)-1 -> 0.0069317631 | Z142: =SUM(S142:V142)/SUM(R142:U142)-1 -> 0.048336356 | AA142: =SUM(T142:W142)/SUM(S142:V142)-1 -> 0.091085613
A143: 260128 | B143: CPF | C143: United States | D143: Banks - Regional | E143: Dec '25 Dec 31, 2025 | F143: 17.742902 | G143: 29.93 | H143: 25.48 | I143: 23.78 | J143: 22.63 | K143: 26.88 | L143: 21.25 | M143: 18.95 | N143: 17.49 | O143: 19.14 | P143: 16.92 | Q143: 20.65 | R143: 17.07 | S143: 13.4 | T143: 22.55 | U143: 23.88 | V143: 23.64 | W143: 28.21 | X143: =SUM(Q143:T143)/SUM(P143:S143)-1 -> 0.082745444 | Y143: =SUM(R143:U143)/SUM(Q143:T143)-1 -> 0.04384417 | Z143: =SUM(S143:V143)/SUM(R143:U143)-1 -> 0.085435631 | AA143: =SUM(T143:W143)/SUM(S143:V143)-1 -> 0.17742902
A144: 260128 | B144: APH | C144: United States | D144: Electronic Components | E144: Dec '25 Dec 31, 2025 | F144: 15.33036 | G144: 600.9 | H144: 589.8 | I144: 648.8 | J144: 693.1 | K144: 674 | L144: 597.1 | M144: 623.9 | N144: 666.9 | O144: 705.8 | P144: 684.8 | Q144: 768.8 | R144: 883.1 | S144: 965.8 | T144: 1130 | U144: 1448 | V144: 1702 | W144: 1770 | X144: =SUM(Q144:T144)/SUM(P144:S144)-1 -> 0.13480696 | Y144: =SUM(R144:U144)/SUM(Q144:T144)-1 -> 0.18123116 | Z144: =SUM(S144:V144)/SUM(R144:U144)-1 -> 0.18498272 | AA144: =SUM(T144:W144)/SUM(S144:V144)-1 -> 0.1533036
B145: STARHEALTH | C145: India | D145: N/A | E145: Sep '25 Sep 30, 2025 | F145: -8.1592153 | G145: -2344 | H145: -7520 | I145: -716.19 | J145: 3048 | K145: 1315 | L145: 3008 | M145: 1779 | N145: 3947 | O145: 1778 | P145: 4088 | Q145: 2089 | R145: 4365 | S145: 1597 | T145: 2860 | U145: 649 | V145: 3662 | W145: 881.6 | X145: =SUM(Q145:T145)/SUM(P145:S145)-1 -> -0.10116155 | Y145: =SUM(R145:U145)/SUM(Q145:T145)-1 -> -0.1319769 | Z145: =SUM(S145:V145)/SUM(R145:U145)-1 -> -0.074226586 | AA145: =SUM(T145:W145)/SUM(S145:V145)-1 -> -0.081592153
A146: 260128 | B146: CLS | C146: United States | D146: Electronic Components | E146: Dec '25 Dec 31, 2025 | F146: 13.40403 | G146: 56.9 | H146: 49.4 | I146: 60.2 | J146: 80 | K146: 148.4 | L146: 64 | M146: 93 | N146: 122.2 | O146: 68.8 | P146: 130.3 | Q146: 144.1 | R146: 138.7 | S146: 194.4 | T146: 132.6 | U146: 286.3 | V146: 329.7 | W146: 320.8 | X146: =SUM(Q146:T146)/SUM(P146:S146)-1 -> 0.0037860082 | Y146: =SUM(R146:U146)/SUM(Q146:T146)-1 -> 0.23319121 | Z146: =SUM(S146:V146)/SUM(R146:U146)-1 -> 0.25398936 | AA146: =SUM(T146:W146)/SUM(S146:V146)-1 -> 0.1340403
B147: CMPR | C147: United States | D147: Specialty Business Services | E147: Sep '25 Sep 30, 2025 | F147: 4.2407248 | G147: 16.63 | H147: 86.29 | I147: -25.02 | J147: -16.11 | K147: -16.15 | L147: 44.79 | M147: 17.92 | N147: 60.12 | O147: 33.77 | P147: 108.16 | Q147: 39.37 | R147: 66.48 | S147: 39.44 | T147: 81.11 | U147: 41.01 | V147: 70.24 | W147: 49.27 | X147: =SUM(Q147:T147)/SUM(P147:S147)-1 -> -0.10672717 | Y147: =SUM(R147:U147)/SUM(Q147:T147)-1 -> 0.0072438163 | Z147: =SUM(S147:V147)/SUM(R147:U147)-1 -> 0.016488335 | AA147: =SUM(T147:W147)/SUM(S147:V147)-1 -> 0.042407248
A148: 260128 | B148: TEVA | C148: United States | D148: Drug Manufacturers - Specialty & Generic | E148: Dec '25 Dec 31, 2025 | F148: 11.25772 | G148: 837 | H148: 665 | I148: 651 | J148: 673 | K148: 639 | L148: 499 | M148: 670 | N148: 761 | O148: 1251 | P148: 660 | Q148: 817 | R148: 983 | S148: 893 | T148: 709 | U148: 894 | V148: 1066 | W148: 1294 | X148: =SUM(Q148:T148)/SUM(P148:S148)-1 -> 0.014613779 | Y148: =SUM(R148:U148)/SUM(Q148:T148)-1 -> 0.022633745 | Z148: =SUM(S148:V148)/SUM(R148:U148)-1 -> 0.02385743 | AA148: =SUM(T148:W148)/SUM(S148:V148)-1 -> 0.1125772
A149: 260128 | B149: GLW | C149: United States | D149: Electronic Components | E149: Dec '25 Dec 31, 2025 | F149: 11.175617 | G149: 588 | H149: 594 | I149: 491 | J149: 319 | K149: 501 | L149: 296 | M149: 278 | N149: 288 | O149: 164 | P149: 257 | Q149: 331 | R149: 384 | S149: 441 | T149: 451 | U149: 578 | V149: 597 | W149: 672 | X149: =SUM(Q149:T149)/SUM(P149:S149)-1 -> 0.13729653 | Y149: =SUM(R149:U149)/SUM(Q149:T149)-1 -> 0.15370255 | Z149: =SUM(S149:V149)/SUM(R149:U149)-1 -> 0.11488673 | AA149: =SUM(T149:W149)/SUM(S149:V149)-1 -> 0.11175617
A150: 260128 | B150: LFUS | C150: United States | D150: Electronic Components | E150: Dec '25 Dec 27, 2025 | F150: 10.566449 | G150: 98.26 | H150: 155.24 | I150: 134.45 | J150: 131.71 | K150: 112.84 | L150: 113.41 | M150: 98.42 | N150: 97.66 | O150: 69.28 | P150: 57.77 | Q150: 70.25 | R150: 89.18 | S150: 50.13 | T150: 78.11 | U150: 94.66 | V150: 98.4 | W150: 84.08 | X150: =SUM(Q150:T150)/SUM(P150:S150)-1 -> 0.076085737 | Y150: =SUM(R150:U150)/SUM(Q150:T150)-1 -> 0.084854173 | Z150: =SUM(S150:V150)/SUM(R150:U150)-1 -> 0.029543707 | AA150: =SUM(T150:W150)/SUM(S150:V150)-1 -> 0.10566449
A151: 260128 | B151: DLX | C151: United States | D151: Conglomerates | E151: Dec '25 Dec 31, 2025 | F151: 9.9700488 | G151: 59.46 | H151: 48.9 | I151: 50.96 | J151: 56.84 | K151: 57.21 | L151: 49.35 | M151: 60.79 | N151: 56.38 | O151: 51.48 | P151: 55.13 | Q151: 63.44 | R151: 62.87 | S151: 37.8 | T151: 58.37 | U151: 66.91 | V151: 80.65 | W151: 62.1 | X151: =SUM(Q151:T151)/SUM(P151:S151)-1 -> 0.014778325 | Y151: =SUM(R151:U151)/SUM(Q151:T151)-1 -> 0.015596908 | Z151: =SUM(S151:V151)/SUM(R151:U151)-1 -> 0.078689976 | AA151: =SUM(T151:W151)/SUM(S151:V151)-1 -> 0.099700488
B152: AJANTPHARM | C152: India | D152: N/A | E152: Sep '25 Sep 30, 2025 | F152: 1.9845645 | G152: 2313 | H152: 2079 | I152: 1794 | J152: 1900 | K152: 1636 | L152: 1732 | M152: 1466 | N152: 2481 | O152: 2570 | P152: 2874 | Q152: 2532 | R152: 2964 | S152: 3024 | T152: 2849 | U152: 2566 | V152: 3352 | W152: 3258 | X152: =SUM(Q152:T152)/SUM(P152:S152)-1 -> -0.0021941373 | Y152: =SUM(R152:U152)/SUM(Q152:T152)-1 -> 0.0029905884 | Z152: =SUM(S152:V152)/SUM(R152:U152)-1 -> 0.034026133 | AA152: =SUM(T152:W152)/SUM(S152:V152)-1 -> 0.019845645
A153: 260128 | B153: LVS | C153: United States | D153: Resorts & Casinos | E153: Dec '25 Dec 31, 2025 | F153: 9.7386323 | G153: -129 | H153: -296 | I153: -147 | J153: -175 | K153: -165 | L153: 392 | M153: 541 | N153: 692 | O153: 715 | P153: 731 | Q153: 607 | R153: 515 | S153: 599 | T153: 616 | U153: 791 | V153: 787 | W153: 871 | X153: =SUM(Q153:T153)/SUM(P153:S153)-1 -> -0.046900489 | Y153: =SUM(R153:U153)/SUM(Q153:T153)-1 -> 0.078733419 | Z153: =SUM(S153:V153)/SUM(R153:U153)-1 -> 0.10789369 | AA153: =SUM(T153:W153)/SUM(S153:V153)-1 -> 0.097386323
A154: 260128 | B154: EDU | C154: United States | D154: Education & Training Services | E154: Nov '25 Nov 30, 2025 | F154: 9.2940107 | G154: -768.1 | H154: -141.19 | I154: 349.59 | J154: 77.99 | K154: -2.49 | L154: 66.49 | M154: 48.05 | N154: 205.12 | O154: 21.34 | P154: 113.43 | Q154: 10.53 | R154: 293.15 | S154: 19.26 | T154: 124.52 | U154: 51.63 | V154: 310.83 | W154: 66.31 | X154: =SUM(Q154:T154)/SUM(P154:S154)-1 -> 0.025414213 | Y154: =SUM(R154:U154)/SUM(Q154:T154)-1 -> 0.091851786 | Z154: =SUM(S154:V154)/SUM(R154:U154)-1 -> 0.036187981 | AA154: =SUM(T154:W154)/SUM(S154:V154)-1 -> 0.092940107
A155: 260128 | B155: EXTR | C155: United States | D155: Communication Equipment | E155: Dec '25 Dec 31, 2025 | F155: 9.2697466 | G155: 20.46 | H155: 20.55 | I155: 11.78 | J155: 18.27 | K155: 23.91 | L155: 30.95 | M155: 38.44 | N155: 38.62 | O155: 19.49 | P155: -48.05 | Q155: -38.94 | R155: -3.44 | S155: 13.7 | T155: 9.94 | U155: -1.76 | V155: 11.67 | W155: 16.81 | X155: =SUM(Q155:T155)/SUM(P155:S155)-1 -> -0.75576698 | Y155: =SUM(R155:U155)/SUM(Q155:T155)-1 -> -1.9839915 | Z155: =SUM(S155:V155)/SUM(R155:U155)-1 -> 0.81941432 | AA155: =SUM(T155:W155)/SUM(S155:V155)-1 -> 0.092697466
B156: MUR | C156: United States | D156: Oil & Gas E&P | E156: Sep '25 Sep 30, 2025 | F156: -12.42601 | G156: 245.3 | H156: 0 | I156: 51.75 | J156: 573.47 | K156: 698.03 | L156: 308.89 | M156: 296.16 | N156: 160.23 | O156: 368.73 | P156: 216.72 | Q156: 184.16 | R156: 179.69 | S156: 169.66 | T156: 57.51 | U156: 139.97 | V156: 89 | W156: 112.98 | X156: =SUM(Q156:T156)/SUM(P156:S156)-1 -> -0.21221492 | Y156: =SUM(R156:U156)/SUM(Q156:T156)-1 -> -0.074769043 | Z156: =SUM(S156:V156)/SUM(R156:U156)-1 -> -0.16584679 | AA156: =SUM(T156:W156)/SUM(S156:V156)-1 -> -0.1242601
B157: PLXS | C157: United States | D157: Electronic Components | E157: Sep '25 Sep 27, 2025 | F157: -0.40444894 | G157: 42.34 | H157: 32.49 | I157: 35.85 | J157: 49.59 | K157: 62.41 | L157: 57.34 | M157: 56.81 | N157: 51.24 | O157: 53.24 | P157: 45.32 | Q157: 40.56 | R157: 48.49 | S157: 53.85 | T157: 51.39 | U157: 48.7 | V157: 53.75 | W157: 53.01 | X157: =SUM(Q157:T157)/SUM(P157:S157)-1 -> 0.032249495 | Y157: =SUM(R157:U157)/SUM(Q157:T157)-1 -> 0.041896135 | Z157: =SUM(S157:V157)/SUM(R157:U157)-1 -> 0.025984291 | AA157: =SUM(T157:W157)/SUM(S157:V157)-1 -> -0.0040444894
A158: 260128 | B158: LRCX | C158: United States | D158: Semiconductor Equipment & Materials | E158: Dec '25 Dec 28, 2025 | F158: 7.3615837 | G158: 1338 | H158: 1192 | I158: 1479 | J158: 1698 | K158: 1680 | L158: 1049 | M158: 867.79 | N158: 1033 | O158: 1074 | P158: 1088 | Q158: 1131 | R158: 1264 | S158: 1334 | T158: 1562 | U158: 1741 | V158: 1829 | W158: 1810 | X158: =SUM(Q158:T158)/SUM(P158:S158)-1 -> 0.098401495 | Y158: =SUM(R158:U158)/SUM(Q158:T158)-1 -> 0.11529012 | Z158: =SUM(S158:V158)/SUM(R158:U158)-1 -> 0.095746484 | AA158: =SUM(T158:W158)/SUM(S158:V158)-1 -> 0.073615837
A159: 260128 | B159: CFFN | C159: United States | D159: Banks - Regional | E159: Dec '25 Dec 31, 2025 | F159: 7.3596724 | G159: 27.87 | H159: 27.75 | I159: 26.77 | J159: 24.82 | K159: 19.75 | L159: 17.52 | M159: 9.9 | N159: -186.13 | O159: 2.07 | P159: 17.22 | Q159: 15.61 | R159: 19.21 | S159: 19.1 | T159: 19.25 | U159: 21.63 | V159: 23.04 | W159: 25.21 | X159: =SUM(Q159:T159)/SUM(P159:S159)-1 -> 0.028535283 | Y159: =SUM(R159:U159)/SUM(Q159:T159)-1 -> 0.082274156 | Z159: =SUM(S159:V159)/SUM(R159:U159)-1 -> 0.048364693 | AA159: =SUM(T159:W159)/SUM(S159:V159)-1 -> 0.073596724
A160: 260128 | B160: IBM | C160: United States | D160: Information Technology Services | E160: Dec '25 Dec 31, 2025 | F160: 6.1861914 | G160: 2810 | H160: 988 | I160: 1770 | J160: 1393 | K160: 3414 | L160: 1445 | M160: 2285 | N160: 2140 | O160: 4031 | P160: 1478 | Q160: 2354 | R160: 2115 | S160: 3841 | T160: 1803 | U160: 3110 | V160: 2804 | W160: 4556 | X160: =SUM(Q160:T160)/SUM(P160:S160)-1 -> 0.033203923 | Y160: =SUM(R160:U160)/SUM(Q160:T160)-1 -> 0.074755265 | Z160: =SUM(S160:V160)/SUM(R160:U160)-1 -> 0.063391296 | AA160: =SUM(T160:W160)/SUM(S160:V160)-1 -> 0.061861914
B161: MTH | C161: United States | D161: Residential Construction | E161: Sep '25 Sep 30, 2025 | F161: -15.278366 | G161: 260.52 | H161: 312.25 | I161: 286.24 | J161: 332.15 | K161: 329.57 | L161: 338.69 | M161: 156.46 | N161: 226.66 | O161: 273.31 | P161: 245.96 | Q161: 224.99 | R161: 286.49 | S161: 239.25 | T161: 207.61 | U161: 150.66 | V161: 182.21 | W161: 120.12 | X161: =SUM(Q161:T161)/SUM(P161:S161)-1 -> -0.03847736 | Y161: =SUM(R161:U161)/SUM(Q161:T161)-1 -> -0.0775612 | Z161: =SUM(S161:V161)/SUM(R161:U161)-1 -> -0.11796247 | AA161: =SUM(T161:W161)/SUM(S161:V161)-1 -> -0.15278366
A162: 260128 | B162: LBRT | C162: United States | D162: Oil & Gas Equipment & Services | E162: Dec '25 Dec 31, 2025 | F162: 6.0648801 | G162: -58.62 | H162: 9.85 | I162: 109.36 | J162: 180.47 | K162: 197.45 | L162: 226.22 | M162: 203.8 | N162: 201.62 | O162: 123.99 | P162: 114.27 | Q162: 143.08 | R162: 113.3 | S162: 13.48 | T162: 32.53 | U162: 42.7 | V162: -3.63 | W162: 18.64 | X162: =SUM(Q162:T162)/SUM(P162:S162)-1 -> -0.21279254 | Y162: =SUM(R162:U162)/SUM(Q162:T162)-1 -> -0.33195542 | Z162: =SUM(S162:V162)/SUM(R162:U162)-1 -> -0.57883273 | AA162: =SUM(T162:W162)/SUM(S162:V162)-1 -> 0.060648801
A163: 260128 | B163: FICO | C163: United States | D163: Software - Application | E163: Dec '25 Dec 31, 2025 | F163: 5.8261557 | G163: 115.59 | H163: 152.06 | I163: 140.62 | J163: 134.16 | K163: 138.4 | L163: 159.76 | M163: 177.03 | N163: 165.7 | O163: 151.36 | P163: 194.84 | Q163: 190.25 | R163: 197.18 | S163: 179.53 | T163: 245.65 | U163: 262.52 | V163: 248.08 | W163: 234.05 | X163: =SUM(Q163:T163)/SUM(P163:S163)-1 -> 0.066697296 | Y163: =SUM(R163:U163)/SUM(Q163:T163)-1 -> 0.088935652 | Z163: =SUM(S163:V163)/SUM(R163:U163)-1 -> 0.057521924 | AA163: =SUM(T163:W163)/SUM(S163:V163)-1 -> 0.058261557
B164: HONE | C164: United States | D164: N/A | E164: Jun '25 Jun 30, 2025 | F164: 3.5387046 | G164: 19.92 | H164: 18.26 | I164: 16.4 | J164: 17.16 | K164: 13.8 | L164: 18.44 | M164: 12.34 | N164: 9.71 | O164: 9.75 | P164: 10.92 | Q164: -5.26 | R164: 9.74 | S164: 9.51 | T164: 4.29 | U164: 10.72 | V164: 7.13 | W164: 10.63 | X164: =SUM(Q164:T164)/SUM(P164:S164)-1 -> -0.26615817 | Y164: =SUM(R164:U164)/SUM(Q164:T164)-1 -> 0.87417943 | Z164: =SUM(S164:V164)/SUM(R164:U164)-1 -> -0.076182137 | AA164: =SUM(T164:W164)/SUM(S164:V164)-1 -> 0.035387046
A165: 260128 | B165: TXT | C165: United States | D165: Aerospace & Defense | E165: Jan '26 Jan 3, 2026 | F165: 5.6683587 | G165: 281 | H165: 260 | I165: 291 | J165: 285 | K165: 274 | L165: 244 | M165: 345 | N165: 317 | O165: 0 | P165: 266 | Q165: 356 | R165: 272 | S165: 243 | T165: 266 | U165: 331 | V165: 342 | W165: 310 | X165: =SUM(Q165:T165)/SUM(P165:S165)-1 -> 0 | Y165: =SUM(R165:U165)/SUM(Q165:T165)-1 -> -0.021987687 | Z165: =SUM(S165:V165)/SUM(R165:U165)-1 -> 0.06294964 | AA165: =SUM(T165:W165)/SUM(S165:V165)-1 -> 0.056683587
B166: 6345 | C166: Japan | D166: N/A | E166: Sep '25 Sep 30, 2025 | F166: 3.2443579 | G166: 2082 | H166: 1582 | I166: 2678 | J166: 702 | K166: 1752 | L166: 1128 | M166: 3769 | N166: 729 | O166: 1814 | P166: 1566 | Q166: 2233 | R166: 985.04 | S166: 1773 | T166: 1506 | U166: 3176 | V166: 295.18 | W166: 1992 | X166: =SUM(Q166:T166)/SUM(P166:S166)-1 -> -0.0091504703 | Y166: =SUM(R166:U166)/SUM(Q166:T166)-1 -> 0.14514302 | Z166: =SUM(S166:V166)/SUM(R166:U166)-1 -> -0.09272262 | AA166: =SUM(T166:W166)/SUM(S166:V166)-1 -> 0.032443579
A167: 260128 | B167: PGR | C167: United States | D167: Insurance - Property & Casualty | E167: Dec '25 Dec 31, 2025 | F167: 5.1711633 | G167: 1256 | H167: 444.5 | I167: -348.1 | J167: 205.6 | K167: 1088 | L167: 617.7 | M167: 501.4 | N167: 1480 | O167: 2573 | P167: 3010 | Q167: 1929 | R167: 3016 | S167: 3038 | T167: 3306 | U167: 4051 | V167: 3393 | W167: 3751 | X167: =SUM(Q167:T167)/SUM(P167:S167)-1 -> 0.026926226 | Y167: =SUM(R167:U167)/SUM(Q167:T167)-1 -> 0.18797059 | Z167: =SUM(S167:V167)/SUM(R167:U167)-1 -> 0.028111252 | AA167: =SUM(T167:W167)/SUM(S167:V167)-1 -> 0.051711633
A168: 260128 | B168: SF | C168: United States | D168: Capital Markets | E168: Dec '25 Dec 31, 2025 | F168: 4.9530346 | G168: 334.9 | H168: 241.9 | I168: 235.33 | J168: 217.73 | K168: 257.2 | L168: 227.27 | M168: 196.53 | N168: 176.43 | O168: 269.2 | P168: 230.85 | Q168: 226.89 | R168: 216.66 | S168: 266.2 | T168: 76.04 | U168: 213.82 | V168: 286.05 | W168: 307.91 | X168: =SUM(Q168:T168)/SUM(P168:S168)-1 -> -0.16458643 | Y168: =SUM(R168:U168)/SUM(Q168:T168)-1 -> -0.016632943 | Z168: =SUM(S168:V168)/SUM(R168:U168)-1 -> 0.089799669 | AA168: =SUM(T168:W168)/SUM(S168:V168)-1 -> 0.049530346
B169: ETD | C169: United States | D169: Furnishings, Fixtures & Appliances | E169: Sep '25 Sep 30, 2025 | F169: -11.711856 | G169: 27.62 | H169: 32.66 | I169: 31.19 | J169: 42.33 | K169: 37.65 | L169: 36.87 | M169: 28.32 | N169: 30.63 | O169: 19.84 | P169: 21.45 | Q169: 14.57 | R169: 22.05 | S169: 17.8 | T169: 18.16 | U169: 11.1 | V169: 15.27 | W169: 10.5 | X169: =SUM(Q169:T169)/SUM(P169:S169)-1 -> -0.043363648 | Y169: =SUM(R169:U169)/SUM(Q169:T169)-1 -> -0.047809314 | Z169: =SUM(S169:V169)/SUM(R169:U169)-1 -> -0.098104471 | AA169: =SUM(T169:W169)/SUM(S169:V169)-1 -> -0.11711856
B170: 6104 | C170: Japan | D170: N/A | E170: Sep '25 Sep 30, 2025 | F170: -30.407665 | G170: 1954 | H170: 683 | I170: 1176 | J170: 423 | K170: 1249 | L170: 1670 | M170: 2425 | N170: 2626 | O170: 5539 | P170: 1491 | Q170: 3959 | R170: 3956 | S170: 4479 | T170: 4682 | U170: 979 | V170: 923 | W170: 1115 | X170: =SUM(Q170:T170)/SUM(P170:S170)-1 -> 0.22981635 | Y170: =SUM(R170:U170)/SUM(Q170:T170)-1 -> -0.17451394 | Z170: =SUM(S170:V170)/SUM(R170:U170)-1 -> -0.21516742 | AA170: =SUM(T170:W170)/SUM(S170:V170)-1 -> -0.30407665
B171: 5440 | C171: Japan | D171: N/A | E171: Sep '25 Sep 30, 2025 | F171: 12.585384 | G171: 3414 | H171: 1247 | I171: 1973 | J171: 3029 | K171: 3056 | L171: 3005 | M171: 5729 | N171: 4877 | O171: 5064 | P171: 4807 | Q171: 6307 | R171: 3091 | S171: 2824 | T171: 3784 | U171: 5633 | V171: 4302 | W171: 4906 | X171: =SUM(Q171:T171)/SUM(P171:S171)-1 -> -0.060073991 | Y171: =SUM(R171:U171)/SUM(Q171:T171)-1 -> -0.042109209 | Z171: =SUM(S171:V171)/SUM(R171:U171)-1 -> 0.078985129 | AA171: =SUM(T171:W171)/SUM(S171:V171)-1 -> 0.12585384
B172: GREENLAM | C172: India | D172: N/A | E172: Sep '25 Sep 30, 2025 | F172: 10.795884 | G172: 314.47 | H172: 380.4 | I172: 358.92 | J172: 356.08 | K172: 382.51 | L172: 385.66 | M172: 576.3 | N172: 469.53 | O172: 561.4 | P172: 466.61 | Q172: 591.08 | R172: 377 | S172: 546.2 | T172: 362.7 | U172: 323.3 | V172: 89.6 | W172: 688.9 | X172: =SUM(Q172:T172)/SUM(P172:S172)-1 -> -0.052456219 | Y172: =SUM(R172:U172)/SUM(Q172:T172)-1 -> -0.14266535 | Z172: =SUM(S172:V172)/SUM(R172:U172)-1 -> -0.17859806 | AA172: =SUM(T172:W172)/SUM(S172:V172)-1 -> 0.10795884
B173: VOLTAMP | C173: India | D173: N/A | E173: Sep '25 Sep 30, 2025 | F173: 5.1582211 | G173: 293.55 | H173: 324.07 | I173: 644.99 | J173: 340.71 | K173: 439.62 | L173: 529.01 | M173: 924.99 | N173: 456.75 | O173: 660.34 | P173: 1019 | Q173: 1001 | R173: 728.2 | S173: 718.13 | T173: 956.62 | U173: 1164 | V173: 692.7 | W173: 900.29 | X173: =SUM(Q173:T173)/SUM(P173:S173)-1 -> -0.017995978 | Y173: =SUM(R173:U173)/SUM(Q173:T173)-1 -> 0.047885545 | Z173: =SUM(S173:V173)/SUM(R173:U173)-1 -> -0.0099524804 | AA173: =SUM(T173:W173)/SUM(S173:V173)-1 -> 0.051582211
A174: 260128 | B174: HLI | C174: United States | D174: Capital Markets | E174: Dec '25 Dec 31, 2025 | F174: 4.8803907 | G174: 249.17 | H174: 102.72 | I174: 77.53 | J174: 89.58 | K174: 84.74 | L174: 89.99 | M174: 73.22 | N174: 100.84 | O174: 106.21 | P174: 111.84 | Q174: 110.11 | R174: 135.3 | S174: 148.82 | T174: 158.89 | U174: 127.36 | V174: 168.98 | W174: 178.3 | X174: =SUM(Q174:T174)/SUM(P174:S174)-1 -> 0.092971328 | Y174: =SUM(R174:U174)/SUM(Q174:T174)-1 -> 0.031186723 | Z174: =SUM(S174:V174)/SUM(R174:U174)-1 -> 0.059049389 | AA174: =SUM(T174:W174)/SUM(S174:V174)-1 -> 0.048803907
B175: CARTRADE | C175: India | D175: N/A | E175: Sep '25 Sep 30, 2025 | F175: 24.194191 | G175: -345.84 | H175: -342.15 | I175: -323.89 | J175: -43.44 | K175: 10.49 | L175: 33.63 | M175: 57.88 | N175: -29.03 | O175: 18.25 | P175: 157.8 | Q175: 170.38 | R175: 115.16 | S175: 220.64 | T175: 395.67 | U175: 368.34 | V175: 344.76 | W175: 542.28 | X175: =SUM(Q175:T175)/SUM(P175:S175)-1 -> 0.35824874 | Y175: =SUM(R175:U175)/SUM(Q175:T175)-1 -> 0.21950435 | Z175: =SUM(S175:V175)/SUM(R175:U175)-1 -> 0.20876333 | AA175: =SUM(T175:W175)/SUM(S175:V175)-1 -> 0.24194191
A176: 260128 | B176: MSFT | C176: United States | D176: Software - Infrastructure | E176: Dec '25 Dec 31, 2025 | F176: 4.8713742 | G176: 22247 | H176: 20364 | I176: 20534 | J176: 21518 | K176: 20551 | L176: 22352 | M176: 24254 | N176: 26895 | O176: 27032 | P176: 27581 | Q176: 27925 | R176: 30552 | S176: 31653 | T176: 32000 | U176: 34323 | V176: 37961 | W176: 38275 | X176: =SUM(Q176:T176)/SUM(P176:S176)-1 -> 0.037541096 | Y176: =SUM(R176:U176)/SUM(Q176:T176)-1 -> 0.052386801 | Z176: =SUM(S176:V176)/SUM(R176:U176)-1 -> 0.057645027 | AA176: =SUM(T176:W176)/SUM(S176:V176)-1 -> 0.048713742
A177: 260128 | B177: ATGE | C177: United States | D177: Education & Training Services | E177: Dec '25 Dec 31, 2025 | F177: 4.6018931 | G177: 32.34 | H177: 49.39 | I177: 60.06 | J177: 48.24 | K177: 61.73 | L177: 58.74 | M177: 57.63 | N177: 52.63 | O177: 65.59 | P177: 80.65 | Q177: 72.77 | R177: 72.33 | S177: 98.64 | T177: 97.46 | U177: 77.31 | V177: 85.79 | W177: 115.17 | X177: =SUM(Q177:T177)/SUM(P177:S177)-1 -> 0.05182034 | Y177: =SUM(R177:U177)/SUM(Q177:T177)-1 -> 0.013305979 | Z177: =SUM(S177:V177)/SUM(R177:U177)-1 -> 0.038930989 | AA177: =SUM(T177:W177)/SUM(S177:V177)-1 -> 0.046018931
B178: 9551 | C178: Japan | D178: N/A | E178: Sep '25 Sep 30, 2025 | F178: 14.472378 | G178: -381 | H178: 568 | I178: 10789 | J178: -1932 | K178: -1053 | L178: 961 | M178: 10714 | N178: -2523 | O178: -259 | P178: 2874 | Q178: 9812 | R178: -2068 | S178: -1 | T178: 1717 | U178: 10979 | V178: -603 | W178: 1749 | X178: =SUM(Q178:T178)/SUM(P178:S178)-1 -> -0.10897617 | Y178: =SUM(R178:U178)/SUM(Q178:T178)-1 -> 0.12336152 | Z178: =SUM(S178:V178)/SUM(R178:U178)-1 -> 0.1378564 | AA178: =SUM(T178:W178)/SUM(S178:V178)-1 -> 0.14472378
B179: 8336 | C179: Japan | D179: N/A | E179: Sep '25 Sep 30, 2025 | F179: 6.1854589 | G179: 2570 | H179: 2725 | I179: 2981 | J179: 3350 | K179: 3773 | L179: 4278 | M179: 4146 | N179: 3817 | O179: 4169 | P179: 3384 | Q179: 4861 | R179: 4721 | S179: 4798 | T179: 4447 | U179: 4114 | V179: 5718 | W179: 5978 | X179: =SUM(Q179:T179)/SUM(P179:S179)-1 -> 0.059840126 | Y179: =SUM(R179:U179)/SUM(Q179:T179)-1 -> -0.03967706 | Z179: =SUM(S179:V179)/SUM(R179:U179)-1 -> 0.055143805 | AA179: =SUM(T179:W179)/SUM(S179:V179)-1 -> 0.061854589
A180: 260128 | B180: UVSP | C180: United States | D180: Banks - Regional | E180: Dec '25 Dec 31, 2025 | F180: 4.5756458 | G180: 21.99 | H180: 25.17 | I180: 16.42 | J180: 25.99 | K180: 29.63 | L180: 26.08 | M180: 20.94 | N180: 21.27 | O180: 20.4 | P180: 25.56 | Q180: 22.59 | R180: 23.39 | S180: 23.76 | T180: 27.56 | U180: 25.02 | V180: 32.06 | W180: 28.72 | X180: =SUM(Q180:T180)/SUM(P180:S180)-1 -> 0.020986359 | Y180: =SUM(R180:U180)/SUM(Q180:T180)-1 -> 0.024974306 | Z180: =SUM(S180:V180)/SUM(R180:U180)-1 -> 0.086934724 | AA180: =SUM(T180:W180)/SUM(S180:V180)-1 -> 0.045756458
B181: ASA | C181: United States | D181: Asset Management | E181: Aug '25 Aug 31, 2025 | F181: -79.906542 | G181: -0.82 | H181: -0.21 | I181: -0.72 | J181: -0.24 | K181: -0.45 | L181: -0.01 | M181: -0.41 | N181: -0.31 | O181: -0.01 | P181: -0.35 | Q181: -0.83 | R181: -0.11 | S181: -0.32 | T181: -0.38 | U181: 0.92 | V181: -4.5 | W181: 3.1 | X181: =SUM(Q181:T181)/SUM(P181:S181)-1 -> 0.01863354 | Y181: =SUM(R181:U181)/SUM(Q181:T181)-1 -> -1.0670732 | Z181: =SUM(S181:V181)/SUM(R181:U181)-1 -> -39.909091 | AA181: =SUM(T181:W181)/SUM(S181:V181)-1 -> -0.79906542
A182: 260128 | B182: VFC | C182: United States | D182: Apparel Manufacturing | E182: Dec '25 Dec 27, 2025 | F182: 4.3207958 | G182: 635.72 | H182: 376.65 | I182: 72.09 | J182: 331.33 | K182: 516.29 | L182: 138.45 | M182: -32.48 | N182: 351.06 | O182: 216.78 | P182: -63.97 | Q182: -110.28 | R182: 284.57 | S182: 296.14 | T182: 3.91 | U182: -69.47 | V182: 316.31 | W182: 319.77 | X182: =SUM(Q182:T182)/SUM(P182:S182)-1 -> 0.1670029 | Y182: =SUM(R182:U182)/SUM(Q182:T182)-1 -> 0.086035333 | Z182: =SUM(S182:V182)/SUM(R182:U182)-1 -> 0.061613122 | AA182: =SUM(T182:W182)/SUM(S182:V182)-1 -> 0.043207958
A183: 260128 | B183: NFG | C183: United States | D183: Oil & Gas Integrated | E183: Dec '25 Dec 31, 2025 | F183: 4.101515 | G183: 206.71 | H183: 241.39 | I183: 166.86 | J183: 179.49 | K183: 257.79 | L183: 225.12 | M183: 157.51 | N183: 128.53 | O183: 210.7 | P183: 254.68 | Q183: 152.84 | R183: 125.19 | S183: 235.62 | T183: 331.09 | U183: 237.35 | V183: 183.38 | W183: 276.12 | X183: =SUM(Q183:T183)/SUM(P183:S183)-1 -> 0.099449455 | Y183: =SUM(R183:U183)/SUM(Q183:T183)-1 -> 0.10004262 | Z183: =SUM(S183:V183)/SUM(R183:U183)-1 -> 0.062620393 | AA183: =SUM(T183:W183)/SUM(S183:V183)-1 -> 0.04101515
A184: 260128 | B184: SMG | C184: United States | D184: Agricultural Inputs | E184: Dec '25 Dec 27, 2025 | F184: 3.9531142 | G184: -34.6 | H184: 389.3 | I184: 150.4 | J184: -103.6 | K184: -11.7 | L184: 352 | M184: 114.7 | N184: -148.5 | O184: -55.4 | P184: 347.8 | Q184: 203.9 | R184: -128.8 | S184: -39 | T184: 365.9 | U184: 231.5 | V184: -123.3 | W184: -21.8 | X184: =SUM(Q184:T184)/SUM(P184:S184)-1 -> 0.047147695 | Y184: =SUM(R184:U184)/SUM(Q184:T184)-1 -> 0.068656716 | Z184: =SUM(S184:V184)/SUM(R184:U184)-1 -> 0.012802607 | AA184: =SUM(T184:W184)/SUM(S184:V184)-1 -> 0.039531142
B185: CNMD | C185: United States | D185: Medical Devices | E185: Sep '25 Sep 30, 2025 | F185: -1.2977099 | G185: 26.72 | H185: 36.81 | I185: 22.44 | J185: 28.3 | K185: 26.35 | L185: 14.98 | M185: 21.34 | N185: 29.02 | O185: 35.7 | P185: 42.12 | Q185: 30.11 | R185: 38.43 | S185: 38.66 | T185: 53.72 | U185: 23.36 | V185: 41.46 | W185: 36.62 | X185: =SUM(Q185:T185)/SUM(P185:S185)-1 -> 0.077685508 | Y185: =SUM(R185:U185)/SUM(Q185:T185)-1 -> -0.041946309 | Z185: =SUM(S185:V185)/SUM(R185:U185)-1 -> 0.019653629 | AA185: =SUM(T185:W185)/SUM(S185:V185)-1 -> -0.012977099
B186: MANYAVAR | C186: India | D186: N/A | E186: Sep '25 Sep 30, 2025 | F186: -3.15081 | G186: 689.91 | H186: 1671 | I186: 1171 | J186: 1367 | K186: 905.4 | L186: 1994 | M186: 1405 | N186: 1182 | O186: 603.49 | P186: 2076 | Q186: 1373 | R186: 755.17 | S186: 846.97 | T186: 2031 | U186: 1266 | V186: 808.09 | W186: 690.94 | X186: =SUM(Q186:T186)/SUM(P186:S186)-1 -> -0.00890888 | Y186: =SUM(R186:U186)/SUM(Q186:T186)-1 -> -0.021373753 | Z186: =SUM(S186:V186)/SUM(R186:U186)-1 -> 0.010801896 | AA186: =SUM(T186:W186)/SUM(S186:V186)-1 -> -0.0315081
A187: 260128 | B187: MSCI | C187: United States | D187: Financial Data & Stock Exchanges | E187: Dec '25 Dec 31, 2025 | F187: 3.6789318 | G187: 288.06 | H187: 290.29 | I187: 302.2 | J187: 310.46 | K187: 307.74 | L187: 314.6 | M187: 345.95 | N187: 354.32 | O187: 371.53 | P187: 340.89 | Q187: 385.34 | R187: 404.43 | S187: 402.95 | T187: 377.02 | U187: 421.46 | V187: 447.69 | W187: 463.62 | X187: =SUM(Q187:T187)/SUM(P187:S187)-1 -> 0.023558793 | Y187: =SUM(R187:U187)/SUM(Q187:T187)-1 -> 0.02301018 | Z187: =SUM(S187:V187)/SUM(R187:U187)-1 -> 0.026938837 | AA187: =SUM(T187:W187)/SUM(S187:V187)-1 -> 0.036789318
A188: 260128 | B188: META | C188: United States | D188: Internet Content & Information | E188: Dec '25 Dec 31, 2025 | F188: 3.5268962 | G188: 12585 | H188: 8524 | I188: 8358 | J188: 5664 | K188: 11010 | L188: 7848 | M188: 9576 | N188: 14092 | O188: 17491 | P188: 13818 | Q188: 14847 | R188: 17350 | S188: 21908 | T188: 17555 | U188: 20441 | V188: 20535 | W188: 24745 | X188: =SUM(Q188:T188)/SUM(P188:S188)-1 -> 0.055018182 | Y188: =SUM(R188:U188)/SUM(Q188:T188)-1 -> 0.078063076 | Z188: =SUM(S188:V188)/SUM(R188:U188)-1 -> 0.041227639 | AA188: =SUM(T188:W188)/SUM(S188:V188)-1 -> 0.035268962
A189: 260128 | B189: HXL | C189: United States | D189: Aerospace & Defense | E189: Dec '25 Dec 31, 2025 | F189: 2.1816337 | G189: 41.8 | H189: 31.1 | I189: 44.4 | J189: 40.8 | K189: 48.1 | L189: 63 | M189: 61.3 | N189: 42.8 | O189: 48.4 | P189: 52.9 | Q189: 72 | R189: 52.5 | S189: 57.1 | T189: 45.3 | U189: 54.2 | V189: 40.5 | W189: 61.4 | X189: =SUM(Q189:T189)/SUM(P189:S189)-1 -> -0.032409382 | Y189: =SUM(R189:U189)/SUM(Q189:T189)-1 -> -0.078448656 | Z189: =SUM(S189:V189)/SUM(R189:U189)-1 -> -0.057388809 | AA189: =SUM(T189:W189)/SUM(S189:V189)-1 -> 0.021816337
A190: 260128 | B190: BMI | C190: United States | D190: Scientific & Technical Instruments | E190: Dec '25 Dec 31, 2025 | F190: 2.1540688 | G190: 22.83 | H190: 18.83 | I190: 22.06 | J190: 23.84 | K190: 22.44 | L190: 25.01 | M190: 29.47 | N190: 31.39 | O190: 32.05 | P190: 36.57 | Q190: 41.5 | R190: 40.61 | S190: 39.21 | T190: 49.45 | U190: 44.89 | V190: 46.11 | W190: 43.08 | X190: =SUM(Q190:T190)/SUM(P190:S190)-1 -> 0.081575781 | Y190: =SUM(R190:U190)/SUM(Q190:T190)-1 -> 0.019851262 | Z190: =SUM(S190:V190)/SUM(R190:U190)-1 -> 0.031580156 | AA190: =SUM(T190:W190)/SUM(S190:V190)-1 -> 0.021540688
A191: 260128 | B191: NOW | C191: United States | D191: Software - Application | E191: Dec '25 Dec 31, 2025 | F191: 1.980198 | G191: 35 | H191: 87 | I191: 22 | J191: 91 | K191: 155 | L191: 144 | M191: 117 | N191: 231 | O191: 308 | P191: 332 | Q191: 240 | R191: 418 | S191: 407 | T191: 451 | U191: 388 | V191: 572 | W191: 443 | X191: =SUM(Q191:T191)/SUM(P191:S191)-1 -> 0.085182534 | Y191: =SUM(R191:U191)/SUM(Q191:T191)-1 -> 0.09762533 | Z191: =SUM(S191:V191)/SUM(R191:U191)-1 -> 0.092548077 | AA191: =SUM(T191:W191)/SUM(S191:V191)-1 -> 0.01980198
A192: 260128 | B192: PB | C192: United States | D192: Banks - Regional | E192: Dec '25 Dec 31, 2025 | F192: 1.902649 | G192: 160.98 | H192: 155.22 | I192: 163.19 | J192: 173.15 | K192: 174.62 | L192: 158.73 | M192: 111.74 | N192: 142.61 | O192: 121.38 | P192: 141.27 | Q192: 142.88 | R192: 162.45 | S192: 166.07 | T192: 166.38 | U192: 172.14 | V192: 176.04 | W192: 179.02 | X192: =SUM(Q192:T192)/SUM(P192:S192)-1 -> 0.040984543 | Y192: =SUM(R192:U192)/SUM(Q192:T192)-1 -> 0.045877889 | Z192: =SUM(S192:V192)/SUM(R192:U192)-1 -> 0.020373591 | AA192: =SUM(T192:W192)/SUM(S192:V192)-1 -> 0.01902649
A193: 260128 | B193: ADP | C193: United States | D193: Software - Application | E193: Dec '25 Dec 31, 2025 | F193: 1.7081592 | G193: 919.6 | H193: 1201 | I193: 810.1 | J193: 1033 | K193: 1098 | L193: 1379 | M193: 1050 | N193: 1125 | O193: 1192 | P193: 1553 | Q193: 1106 | R193: 1280 | S193: 1308 | T193: 1641 | U193: 1214 | V193: 1340 | W193: 1402 | X193: =SUM(Q193:T193)/SUM(P193:S193)-1 -> 0.016771488 | Y193: =SUM(R193:U193)/SUM(Q193:T193)-1 -> 0.020243674 | Z193: =SUM(S193:V193)/SUM(R193:U193)-1 -> 0.011023333 | AA193: =SUM(T193:W193)/SUM(S193:V193)-1 -> 0.017081592
A194: 260128 | B194: CP | C194: United States | D194: Railroads | E194: Dec '25 Dec 31, 2025 | F194: 1.6733601 | G194: 969 | H194: 656 | I194: 988 | J194: 1039 | K194: 1170 | L194: 927 | M194: 1143 | N194: 1258 | O194: 1699 | P194: 1263 | Q194: 1383 | R194: 1328 | S194: 1607 | T194: 1444 | U194: 1469 | V194: 1456 | W194: 1707 | X194: =SUM(Q194:T194)/SUM(P194:S194)-1 -> 0.032431464 | Y194: =SUM(R194:U194)/SUM(Q194:T194)-1 -> 0.014925373 | Z194: =SUM(S194:V194)/SUM(R194:U194)-1 -> 0.021887825 | AA194: =SUM(T194:W194)/SUM(S194:V194)-1 -> 0.016733601
A195: 260128 | B195: WM | C195: United States | D195: Waste Management | E195: Dec '25 Dec 31, 2025 | F195: 1.6548985 | G195: 721 | H195: 785 | I195: 890 | J195: 943 | K195: 810 | L195: 825 | M195: 945 | N195: 1021 | O195: 1032 | P195: 1014 | Q195: 1067 | R195: 1127 | S195: 1101 | T195: 1028 | U195: 1187 | V195: 1216 | W195: 1176 | X195: =SUM(Q195:T195)/SUM(P195:S195)-1 -> 0.0032490137 | Y195: =SUM(R195:U195)/SUM(Q195:T195)-1 -> 0.027758501 | Z195: =SUM(S195:V195)/SUM(R195:U195)-1 -> 0.02003151 | AA195: =SUM(T195:W195)/SUM(S195:V195)-1 -> 0.016548985
...

Sheet 빨간줄
B2: (단위: mil $)
B4: SNDK | C4: 6 | D4: 7 | E4: 8 | F4: 9 | G4: 10 | H4: 11 | I4: 12 | J4: 13 | K4: 14 | L4: 15 | M4: 16 | N4: 17 | O4: 18 | P4: 19 | Q4: 20 | R4: 21 | S4: 22
C6: 4Q21 | D6: 1Q22 | E6: 2Q22 | F6: 3Q22 | G6: 4Q22 | H6: 1Q23 | I6: 2Q23 | J6: 3Q23 | K6: 4Q23 | L6: 1Q24 | M6: 2Q24 | N6: 3Q24 | O6: 4Q24 | P6: 1Q25 | Q6: 2Q25 | R6: 3Q25 | S6: 4Q25 | T6: 1Q26 | U6: 2Q26 | V6: 3Q26 | W6: 4Q26
B7: Revenue | C7: =VLOOKUP($B$4,Revenue!$B:$W,C4,FALSE) -> 1746 | D7: =VLOOKUP($B$4,Revenue!$B:$W,D4,FALSE) -> 1735 | E7: =VLOOKUP($B$4,Revenue!$B:$W,E4,FALSE) -> 1332 | F7: =VLOOKUP($B$4,Revenue!$B:$W,F4,FALSE) -> 1237 | G7: =VLOOKUP($B$4,Revenue!$B:$W,G4,FALSE) -> 1452 | H7: =VLOOKUP($B$4,Revenue!$B:$W,H4,FALSE) -> 0 | I7: =VLOOKUP($B$4,Revenue!$B:$W,I4,FALSE) -> 0 | J7: =VLOOKUP($B$4,Revenue!$B:$W,J4,FALSE) -> 1533 | ... S7: =VLOOKUP($B$4,Revenue!$B:$W,S4,FALSE) -> 3025
B8: OP | C8: =VLOOKUP($B$4,'Operating Income'!$B:$W,C4,FALSE) -> 0 | D8: =VLOOKUP($B$4,'Operating Income'!$B:$W,D4,FALSE) -> 0 | E8: =VLOOKUP($B$4,'Operating Income'!$B:$W,E4,FALSE) -> 0 | F8: =VLOOKUP($B$4,'Operating Income'!$B:$W,F4,FALSE) -> 0 | G8: =VLOOKUP($B$4,'Operating Income'!$B:$W,G4,FALSE) -> 0 | H8: =VLOOKUP($B$4,'Operating Income'!$B:$W,H4,FALSE) -> 0 | I8: =VLOOKUP($B$4,'Operating Income'!$B:$W,I4,FALSE) -> 0 | J8: =VLOOKUP($B$4,'Operating Income'!$B:$W,J4,FALSE) -> -546 | ... S8: =VLOOKUP($B$4,'Operating Income'!$B:$W,S4,FALSE) -> 1075
B9: Trailing 4Q OP avg. | C9: =AVERAGE(C8:C8) -> 0 | D9: =AVERAGE(C8:D8) -> 0 | E9: =AVERAGE(C8:E8) -> 0 | F9: =AVERAGE(C8:F8) -> 0 | G9: =AVERAGE(D8:G8) -> 0 | H9: =AVERAGE(E8:H8) -> 0 | I9: =AVERAGE(F8:I8) -> 0 | J9: =AVERAGE(G8:J8) -> -136.5 | K9: =AVERAGE(H8:K8) -> -186 | L9: =AVERAGE(I8:L8) -> -166.25 | M9: =AVERAGE(J8:M8) -> -120 | ... S9: =AVERAGE(P8:S8) -> 319
B10: Trailing 4Q OP sum. | C10: =SUM(C8:C8) -> 0 | D10: =SUM(C8:D8) -> 0 | E10: =SUM(C8:E8) -> 0 | F10: =SUM(C8:F8) -> 0 | G10: =SUM(D8:G8) -> 0 | H10: =SUM(E8:H8) -> 0 | I10: =SUM(F8:I8) -> 0 | J10: =SUM(G8:J8) -> -546 | K10: =SUM(H8:K8) -> -744 | L10: =SUM(I8:L8) -> -665 | M10: =SUM(J8:M8) -> -480 | ... S10: =SUM(P8:S8) -> 1276
B11: Trailing OP Delta | D11: =D9/C9-1 -> #DIV/0! | E11: =E9/D9-1 -> #DIV/0! | F11: =F9/E9-1 -> #DIV/0! | G11: =G9/F9-1 -> #DIV/0! | H11: =H9/G9-1 -> #DIV/0! | I11: =I9/H9-1 -> #DIV/0! | J11: =J9/I9-1 -> #DIV/0! | K11: =K9/J9-1 -> 0.36263736 | ... S11: =S9/R9-1 -> 2.3056995
B12: opm | C12: =IFERROR(C8/C7,"-") -> 0 | D12: =IFERROR(D8/D7,"-") -> 0 | E12: =IFERROR(E8/E7,"-") -> 0 | F12: =IFERROR(F8/F7,"-") -> 0 | G12: =IFERROR(G8/G7,"-") -> 0 | H12: =IFERROR(H8/H7,"-") -> - | I12: =IFERROR(I8/I7,"-") -> - | J12: =IFERROR(J8/J7,"-") -> -0.35616438 | ... S12: =IFERROR(S8/S7,"-") -> 0.3553719
B13: op yoy | C13: =C8/#REF!-1 -> #REF! | D13: =D8/#REF!-1 -> #REF! | E13: =E8/#REF!-1 -> #REF! | F13: =F8/#REF!-1 -> #REF! | G13: =G8/C8-1 -> #DIV/0! | H13: =H8/D8-1 -> #DIV/0! | I13: =I8/E8-1 -> #DIV/0! | J13: =J8/F8-1 -> #DIV/0! | K13: =K8/G8-1 -> #DIV/0! | L13: =L8/H8-1 -> #DIV/0! | M13: =M8/I8-1 -> #DIV/0! | N13: =N8/J8-1 -> -1.5732601 | ... S13: =S8/O8-1 -> 4.8108108
B14: rv yoy | G14: =G7/C7-1 -> -0.16838488 | H14: =H9/D9-1 -> #DIV/0! | I14: =I9/E9-1 -> #DIV/0! | J14: =J9/F9-1 -> #DIV/0! | K14: =K9/G9-1 -> #DIV/0! | L14: =L9/H9-1 -> #DIV/0! | M14: =M9/I9-1 -> #DIV/0! | N14: =N9/J9-1 -> -1.6941392 | O14: =O9/K9-1 -> -2.0241935 | ... S14: =S9/O9-1 -> 0.67454068
