Workbook

Sheet 해외 실적 기업 리스트
B2: 260129 실적 기업 정보
B4: Ticker | C4: Company | D4: Date | E4: Time | F4: Quarter Ending | G4: Market Cap (bil$)
B5: AAPL | C5: Apple Inc. | D5: 46051 | E5: After Hours | F5: 46381 | G5: 3755761
B6: V | C6: Visa Inc. | D6: 46051 | E6: After Hours | F6: 46381 | G6: 627788
B7: MA | C7: Mastercard Incorporated | D7: 46051 | E7: Pre Market | F7: 46381 | G7: 484460
B8: ROG | C8: Roche Holding AG | D8: 46051 | F8: 46381 | G8: 370914
B9: CAT | C9: Caterpillar Inc. | D9: 46051 | F9: 46381 | G9: 302731
B10: SAP | C10: SAP SE | D10: 46051 | E10: Pre Market | F10: 46381 | G10: 272488
B11: TMO | C11: Thermo Fisher Scientific Inc. | D11: 46051 | F11: 46381 | G11: 235186
B12: KLAC | C12: KLA Corporation | D12: 46051 | F12: 46381 | G12: 198768
B13: 6501 | C13: Hitachi, Ltd. | D13: 46051 | F13: 46381 | G13: 153613
B14: HON | C14: Honeywell International Inc. | D14: 46051 | E14: Pre Market | F14: 46381 | G14: 140602
B15: ABBN | C15: ABB Ltd | D15: 46051 | F15: 46381 | G15: 139029
B16: LMT | C16: Lockheed Martin Corporation | D16: 46051 | E16: Pre Market | F16: 46381 | G16: 136714
B17: SYK | C17: Stryker Corporation | D17: 46051 | E17: After Hours | F17: 46381 | G17: 135776
B18: BX | C18: Blackstone Inc. | D18: 46051 | E18: Pre Market | F18: 46381 | G18: 117785
B19: PH | C19: Parker-Hannifin Corporation | D19: 46051 | E19: Pre Market | F19: 46381 | G19: 117100
B20: SAN | C20: Sanofi | D20: 46051 | E20: Pre Market | F20: 46381 | G20: 113339
B21: CMCSA | C21: Comcast Corporation | D21: 46051 | E21: Pre Market | F21: 46381 | G21: 106766
B22: MO | C22: Altria Group, Inc. | D22: 46051 | F22: 46381 | G22: 103927
B23: 6861 | C23: Keyence Corporation | D23: 46051 | F23: 46381 | G23: 92593
B24: 4519 | C24: Chugai Pharmaceutical Co., Ltd. | D24: 46051 | F24: 46381 | G24: 92445
B25: MRSH | C25: Marsh & McLennan Companies, Inc. | D25: 46051 | F25: 46381 | G25: 89732
B26: SHW | C26: The Sherwin-Williams Company | D26: 46051 | F26: 46381 | G26: 85899
B27: TT | C27: Trane Technologies plc | D27: 46051 | E27: Pre Market | F27: 46381 | G27: 85640
B28: INGA | C28: ING Groep N.V. | D28: 46051 | F28: 46381 | G28: 82691
B29: A005380 | C29: Hyundai Motor Company | D29: 46051 | F29: 46381 | G29: 81607
B30: WDC | C30: Western Digital Corporation | D30: 46051 | E30: After Hours | F30: 46381 | G30: 80822
B31: RCL | C31: Royal Caribbean Cruises Ltd. | D31: 46051 | E31: Pre Market | F31: 46381 | G31: 78026
B32: DBK | C32: Deutsche Bank Aktiengesellschaft | D32: 46051 | F32: 46381 | G32: 74123
B33: NDA FI | C33: Nordea Bank Abp | D33: 46051 | F33: 46381 | G33: 67136
B34: LHX | C34: L3Harris Technologies, Inc. | D34: 46051 | E34: Pre Market | F34: 46381 | G34: 66353
B35: AJG | C35: Arthur J. Gallagher & Co. | D35: 46051 | E35: After Hours | F35: 46381 | G35: 65026
B36: NSC | C36: Norfolk Southern Corporation | D36: 46051 | E36: Pre Market | F36: 46381 | G36: 64491
B37: VLO | C37: Valero Energy Corporation | D37: 46051 | E37: Pre Market | F37: 46381 | G37: 57064
B38: NDAQ | C38: Nasdaq, Inc. | D38: 46051 | E38: Pre Market | F38: 46381 | G38: 55986
B39: 4502 | C39: Takeda Pharmaceutical Company Limited | D39: 46051 | E39: Pre Market | F39: 46381 | G39: 51863
B40: 6701 | C40: NEC Corporation | D40: 46051 | F40: 46381 | G40: 49922
B41: 6702 | C41: Fujitsu Limited | D41: 46051 | F41: 46381 | G41: 49365
B42: AMP | C42: Ameriprise Financial, Inc. | D42: 46051 | F42: 46381 | G42: 46137
B43: ITC | C43: ITC Limited | D43: 46051 | F43: 46381 | G43: 44222
B44: SEB A | C44: Skandinaviska Enskilda Banken AB (publ) | D44: 46051 | F44: 46381 | G44: 43115
B45: SWED A | C45: Swedbank AB (publ) | D45: 46051 | F45: 46381 | G45: 42398
B46: RMD | C46: ResMed Inc. | D46: 46051 | E46: After Hours | F46: 46381 | G46: 37520
B47: NOKIA | C47: Nokia Oyj | D47: 46051 | F47: 46381 | G47: 37047
B48: GIVN | C48: Givaudan SA | D48: 46051 | F48: 46381 | G48: 36590
B49: HIG | C49: The Hartford Insurance Group, Inc. | D49: 46051 | E49: After Hours | F49: 46381 | G49: 36110
B50: HM B | C50: H & M Hennes & Mauritz AB (publ) | D50: 46051 | F50: 46351 | G50: 30760
B51: ADANIPOWER | C51: Adani Power Limited | D51: 46051 | F51: 46381 | G51: 30313
B52: LPLA | C52: LPL Financial Holdings Inc. | D52: 46051 | E52: After Hours | F52: 46381 | G52: 30303
B53: 4661 | C53: Oriental Land Co., Ltd. | D53: 46051 | F53: 46381 | G53: 29263
B54: DOV | C54: Dover Corporation | D54: 46051 | E54: Pre Market | F54: 46381 | G54: 28337
B55: TSCO | C55: Tractor Supply Company | D55: 46051 | E55: Pre Market | F55: 46381 | G55: 26954
B56: 7751 | C56: Canon Inc. | D56: 46051 | F56: 46381 | G56: 26307
B57: PHM | C57: PulteGroup, Inc. | D57: 46051 | E57: Pre Market | F57: 46381 | G57: 25384
B58: STMPA | C58: STMicroelectronics N.V. | D58: 46051 | E58: Pre Market | F58: 46381 | G58: 25062
B59: IP | C59: International Paper Company | D59: 46051 | E59: Pre Market | F59: 46381 | G59: 22890
B60: 4307 | C60: Nomura Research Institute, Ltd. | D60: 46051 | F60: 46381 | G60: 21750
B61: 9766 | C61: Konami Group Corporation | D61: 46051 | F61: 46381 | G61: 20158
B62: RCI.B | C62: Rogers Communications Inc. | D62: 46051 | F62: 46381 | G62: 18892
B63: SNDK | C63: Sandisk Corporation | D63: 46051 | E63: After Hours | F63: 46381 | G63: 18723
B64: WY | C64: Weyerhaeuser Company | D64: 46051 | E64: After Hours | F64: 46381 | G64: 18124
B65: DOW | C65: Dow Inc. | D65: 46051 | E65: Pre Market | F65: 46381 | G65: 16885
B66: DECK | C66: Deckers Outdoor Corporation | D66: 46051 | E66: After Hours | F66: 46381 | G66: 15287
B67: HOLX | C67: Hologic, Inc. | D67: 46051 | E67: After Hours | F67: 46381 | G67: 15173
B68: TELIA | C68: Telia Company AB (publ) | D68: 46051 | F68: 46381 | G68: 14882
B69: A051910 | C69: LG Chem, Ltd. | D69: 46051 | F69: 46381 | G69: 14717
B70: A005490 | C70: POSCO Holdings Inc. | D70: 46051 | F70: 46381 | G70: 14691
B71: GJF | C71: Gjensidige Forsikring ASA | D71: 46051 | F71: 46381 | G71: 14499
B72: GARAN | C72: Turkiye Garanti Bankasi A.S. | D72: 46051 | F72: 46381 | G72: 13673
B73: ERF | C73: Eurofins Scientific SE | D73: 46051 | F73: 46381 | G73: 13111
B74: CANBK | C74: Canara Bank | D74: 46051 | F74: 46381 | G74: 12863
B75: DWS | C75: DWS Group GmbH & Co. KGaA | D75: 46051 | F75: 46381 | G75: 12578
B76: CRS | C76: Carpenter Technology Corporation | D76: 46051 | E76: Pre Market | F76: 46381 | G76: 12339
B77: DIXON | C77: Dixon Technologies (India) Limited | D77: 46051 | F77: 46381 | G77: 11309
B78: RECLTD | C78: REC Limited | D78: 46051 | F78: 46381 | G78: 11281
B79: 8421 | C79: Shinkin Central Bank | D79: 46051 | F79: 46381 | G79: 11183
B80: 6504 | C80: Fuji Electric Co., Ltd. | D80: 46051 | F80: 46381 | G80: 10234
B81: 9501 | C81: Tokyo Electric Power Company Holdings, Incorporated | D81: 46051 | F81: 46381 | G81: 9110
B82: INDT | C82: Indutrade AB (publ) | D82: 46051 | F82: 46381 | G82: 9065
B83: APPF | C83: AppFolio, Inc. | D83: 46051 | E83: After Hours | F83: 46381 | G83: 8958
B84: 1944 | C84: Kinden Corporation | D84: 46051 | F84: 46381 | G84: 8847
B85: TREL B | C85: Trelleborg AB (publ) | D85: 46051 | F85: 46381 | G85: 8669
B86: 6586 | C86: Makita Corporation | D86: 46051 | F86: 46381 | G86: 8552
B87: OSK | C87: Oshkosh Corporation | D87: 46051 | E87: Pre Market | F87: 46381 | G87: 8410
B88: PAYTM | C88: One97 Communications Limited | D88: 46051 | F88: 46381 | G88: 8402
B89: PRESTIGE | C89: Prestige Estates Projects Limited | D89: 46051 | F89: 46381 | G89: 8273
B90: CFR | C90: Cullen/Frost Bankers, Inc. | D90: 46051 | E90: Pre Market | F90: 46381 | G90: 8144
B91: 3443 | C91: Global Unichip Corp. | D91: 46051 | F91: 46381 | G91: 8123
B92: COROMANDEL | C92: Coromandel International Limited | D92: 46051 | F92: 46381 | G92: 7275
B93: TAL | C93: TAL Education Group | D93: 46051 | E93: Pre Market | F93: 46351 | G93: 6985
B94: PFSI | C94: PennyMac Financial Services, Inc. | D94: 46051 | E94: After Hours | F94: 46381 | G94: 6977
B95: 4204 | C95: Sekisui Chemical Co., Ltd. | D95: 46051 | F95: 46381 | G95: 6963
B96: EMN | C96: Eastman Chemical Company | D96: 46051 | E96: After Hours | F96: 46381 | G96: 6948
B97: EXP | C97: Eagle Materials Inc. | D97: 46051 | F97: 46381 | G97: 6932
B98: AXFO | C98: Axfood AB (publ) | D98: 46051 | F98: 46381 | G98: 6777
B99: VLY | C99: Valley National Bancorp | D99: 46051 | E99: Pre Market | F99: 46381 | G99: 6636
B100: 6305 | C100: Hitachi Construction Machinery Co., Ltd. | D100: 46051 | F100: 46381 | G100: 6372
B101: 500830 | C101: Colgate-Palmolive (India) Limited | D101: 46051 | F101: 46381 | G101: 6320
B102: 5333 | C102: NGK Insulators, Ltd. | D102: 46051 | F102: 46381 | G102: 6277
...

Sheet Revenue
B1: 1 | C1: 2 | D1: 3 | E1: 4 | F1: 5 | G1: 6 | H1: 7 | I1: 8 | J1: 9 | K1: 10 | L1: 11 | M1: 12 | N1: 13 | O1: 14 | P1: 15 | Q1: 16 | R1: 17 | S1: 18 | T1: 19 | U1: 20 | V1: 21 | W1: 22
B2: Ticker | C2: Country | D2: Industry | E2: Latest_Date | F2: Growth_Rate | G2: 4Q21 | H2: 1Q22 | I2: 2Q22 | J2: 3Q22 | K2: 4Q22 | L2: 1Q23 | M2: 2Q23 | N2: 3Q23 | O2: 4Q23 | P2: 1Q24 | Q2: 2Q24 | R2: 3Q24 | S2: 4Q24 | T2: 1Q25 | U2: 2Q25 | V2: 3Q25 | W2: 4Q25 | X2: 1Q25 | Y2: 2Q25 | Z2: 3Q25 | AA2: 4Q25
B3: FISI | C3: United States | D3: Banks - Regional | E3: Dec '25 Dec 31, 2025 | F3: 99.862943 | G3: 53.73 | H3: 48.56 | I3: 52.39 | J3: 51.41 | K3: 47.97 | L3: 48.53 | M3: 50.57 | N3: 51.2 | O3: 49.98 | P3: 56.44 | Q3: 63.17 | R3: 47.02 | S3: -55.86 | T3: 54.31 | U3: 57.18 | V3: 61.11 | W3: 60.72 | X3: =SUM(Q3:T3)/SUM(P3:S3)-1 -> -0.019229033 | Y3: =SUM(R3:U3)/SUM(Q3:T3)-1 -> -0.05513623 | Z3: =SUM(S3:V3)/SUM(R3:U3)-1 -> 0.13726254 | AA3: =SUM(T3:W3)/SUM(S3:V3)-1 -> 0.99862943
B4: IVR | C4: United States | D4: REIT - Mortgage | E4: Dec '25 Dec 31, 2025 | F4: 65.753804 | G4: -57.46 | H4: -221.12 | I4: -102.4 | J4: -95.57 | K4: 41.5 | L4: 26.53 | M4: 9.38 | N4: -63.78 | O4: 32.06 | P4: 33.82 | Q4: -8.32 | R4: 45.33 | S4: 8.52 | T4: 24.3 | U4: -18.46 | V4: 57.94 | W4: 56.06 | X4: =SUM(Q4:T4)/SUM(P4:S4)-1 -> -0.1199748 | Y4: =SUM(R4:U4)/SUM(Q4:T4)-1 -> -0.1452098 | Z4: =SUM(S4:V4)/SUM(R4:U4)-1 -> 0.21125817 | AA4: =SUM(T4:W4)/SUM(S4:V4)-1 -> 0.65753804
B5: WDC | C5: United States | D5: Computer Hardware | E5: Jan '26 Jan 2, 2026 | F5: 39.095503 | G5: 4833 | H5: 4381 | I5: 4528 | J5: 3736 | K5: 3107 | L5: 2803 | M5: 2672 | N5: 2750 | O5: 0 | P5: 1752 | Q5: 0 | R5: 2212 | S5: 0 | T5: 2294 | U5: 2605 | V5: 2818 | W5: 3017 | X5: =SUM(Q5:T5)/SUM(P5:S5)-1 -> 0.13673058 | Y5: =SUM(R5:U5)/SUM(Q5:T5)-1 -> 0.57811806 | Z5: =SUM(S5:V5)/SUM(R5:U5)-1 -> 0.085220082 | AA5: =SUM(T5:W5)/SUM(S5:V5)-1 -> 0.39095503
B6: PFSI | C6: United States | D6: Mortgage Finance | E6: Dec '25 Dec 31, 2025 | F6: 24.722392 | G6: 848.95 | H6: 444.05 | I6: 398.6 | J6: 380.35 | K6: 405.49 | L6: 539.17 | M6: 499.51 | N6: 602.23 | O6: 364.77 | P6: 333.84 | Q6: 507.25 | R6: 1040 | S6: -79.81 | T6: 862.08 | U6: 690.76 | V6: 1026 | W6: 538.01 | X6: =SUM(Q6:T6)/SUM(P6:S6)-1 -> 0.29325813 | Y6: =SUM(R6:U6)/SUM(Q6:T6)-1 -> 0.078775885 | Z6: =SUM(S6:V6)/SUM(R6:U6)-1 -> -0.0055709641 | AA6: =SUM(T6:W6)/SUM(S6:V6)-1 -> 0.24722392
B7: SNDK | C7: United States | D7: Computer Hardware | E7: Jan '26 Jan 2, 2026 | F7: 14.768638 | G7: 1746 | H7: 1735 | I7: 1332 | J7: 1237 | K7: 1452 | N7: 1533 | O7: 1665 | P7: 1705 | Q7: 1760 | R7: 1883 | S7: 1876 | T7: 1695 | U7: 1901 | V7: 2308 | W7: 3025 | X7: =SUM(Q7:T7)/SUM(P7:S7)-1 -> -0.0013842746 | Y7: =SUM(R7:U7)/SUM(Q7:T7)-1 -> 0.019545329 | Z7: =SUM(S7:V7)/SUM(R7:U7)-1 -> 0.057783821 | AA7: =SUM(T7:W7)/SUM(S7:V7)-1 -> 0.14768638
B8: CNX | C8: United States | D8: Oil & Gas E&P | E8: Dec '25 Dec 31, 2025 | F8: 14.671467 | G8: 908.93 | H8: 812.5 | I8: 1072 | J8: 1179 | K8: 860.84 | L8: 513.7 | M8: 295.89 | N8: 302.46 | O8: 350.62 | P8: 376.78 | Q8: 307.12 | R8: 334.72 | S8: 327.24 | T8: 610.55 | U8: 541.91 | V8: 450.85 | W8: 610.48 | X8: =SUM(Q8:T8)/SUM(P8:S8)-1 -> 0.17369563 | Y8: =SUM(R8:U8)/SUM(Q8:T8)-1 -> 0.14863607 | Z8: =SUM(S8:V8)/SUM(R8:U8)-1 -> 0.064003924 | AA8: =SUM(T8:W8)/SUM(S8:V8)-1 -> 0.14671467
B9: PMT | C9: United States | D9: REIT - Mortgage | E9: Dec '25 Dec 31, 2025 | F9: 13.97301 | G9: 221.21 | H9: -221.88 | I9: -112.28 | J9: 84.09 | K9: 104.41 | L9: 227.81 | M9: 178.45 | N9: 2.5 | O9: 317.11 | P9: 102.41 | Q9: 121.75 | R9: 265.78 | S9: 14.66 | T9: 189.06 | U9: 145.33 | V9: 215.61 | W9: 93.56 | X9: =SUM(Q9:T9)/SUM(P9:S9)-1 -> 0.17172017 | Y9: =SUM(R9:U9)/SUM(Q9:T9)-1 -> 0.039881607 | Z9: =SUM(S9:V9)/SUM(R9:U9)-1 -> -0.081599792 | AA9: =SUM(T9:W9)/SUM(S9:V9)-1 -> 0.1397301
B10: BX | C10: United States | D10: Asset Management | E10: Dec '25 Dec 31, 2025 | F10: 11.109374 | G10: 5655 | H10: 4987 | I10: 404.08 | J10: 778.23 | K10: 1847 | L10: 1292 | M10: 2738 | N10: 2367 | O10: 1287 | P10: 3535 | Q10: 2668 | R10: 3648 | S10: 2811 | T10: 3245 | U10: 3801 | V10: 2934 | W10: 4232 | X10: =SUM(Q10:T10)/SUM(P10:S10)-1 -> -0.022903175 | Y10: =SUM(R10:U10)/SUM(Q10:T10)-1 -> 0.091577756 | Z10: =SUM(S10:V10)/SUM(R10:U10)-1 -> -0.052869308 | AA10: =SUM(T10:W10)/SUM(S10:V10)-1 -> 0.11109374
B11: 6135 | C11: Japan | D11: N/A | E11: Sep '25 Sep 30, 2025 | F11: 3.2198364 | G11: 38401 | H11: 47532 | I11: 63719 | J11: 46481 | K11: 56558 | L11: 62459 | M11: 62487 | N11: 53850 | O11: 54665 | P11: 54477 | Q11: 62368 | R11: 51868 | S11: 56369 | T11: 60557 | U11: 65422 | V11: 55397 | W11: 64024
B12: MXL | C12: United States | D12: Semiconductors | E12: Dec '25 Dec 31, 2025 | F12: 10.456575 | G12: 247.89 | H12: 263.93 | I12: 280.01 | J12: 285.73 | K12: 290.59 | L12: 248.44 | M12: 183.94 | N12: 135.53 | O12: 125.35 | P12: 95.27 | Q12: 91.99 | R12: 81.1 | S12: 92.17 | T12: 95.93 | U12: 108.81 | V12: 126.46 | W12: 136.44 | X12: =SUM(Q12:T12)/SUM(P12:S12)-1 -> 0.0018306382 | Y12: =SUM(R12:U12)/SUM(Q12:T12)-1 -> 0.046568288 | Z12: =SUM(S12:V12)/SUM(R12:U12)-1 -> 0.11999683 | AA12: =SUM(T12:W12)/SUM(S12:V12)-1 -> 0.10456575
B13: 6995 | C13: Japan | D13: N/A | E13: Sep '25 Sep 30, 2025 | F13: 1.6376556 | G13: 107972 | H13: 126906 | I13: 129273 | J13: 124844 | K13: 142083 | L13: 141654 | M13: 144543 | N13: 148652 | O13: 158816 | P13: 167461 | Q13: 148629 | R13: 151966 | S13: 152006 | T13: 155520 | U13: 158168 | V13: 152690 | W13: 162133
B14: LPLA | C14: United States | D14: Capital Markets | E14: Dec '25 Dec 31, 2025 | F14: 9.3846864 | G14: 2067 | H14: 2038 | I14: 2010 | J14: 2130 | K14: 2296 | L14: 2379 | M14: 2424 | N14: 2474 | O14: 2589 | P14: 2773 | Q14: 2867 | R14: 3041 | S14: 3404 | T14: 3584 | U14: 3729 | V14: 4446 | W14: 4827 | X14: =SUM(Q14:T14)/SUM(P14:S14)-1 -> 0.067107985 | Y14: =SUM(R14:U14)/SUM(Q14:T14)-1 -> 0.066842432 | Z14: =SUM(S14:V14)/SUM(R14:U14)-1 -> 0.1021224 | AA14: =SUM(T14:W14)/SUM(S14:V14)-1 -> 0.093846864
B15: 2782 | C15: Japan | D15: N/A | E15: Sep '25 Sep 30, 2025 | F15: -24.572468 | G15: 50333 | H15: 52506 | I15: 51951 | J15: 56241 | K15: 51661 | L15: 53848 | M15: 53280 | N15: 166469 | O15: 166469 | P15: 56733 | Q15: 58115 | R15: 57784 | S15: 178047 | T15: 178047 | U15: 60214 | V15: 60498 | W15: 60884
B16: AJG | C16: United States | D16: Insurance Brokers | E16: Dec '25 Dec 31, 2025 | F16: 9.057791 | G16: 1904 | H16: 2385 | I16: 1982 | J16: 1976 | K16: 1927 | L16: 2607 | M16: 2326 | N16: 2352 | O16: 2274 | P16: 3125 | Q16: 2637 | R16: 2631 | S16: 2534 | T16: 3441 | U16: 2945 | V16: 3158 | W16: 3628 | X16: =SUM(Q16:T16)/SUM(P16:S16)-1 -> 0.028919191 | Y16: =SUM(R16:U16)/SUM(Q16:T16)-1 -> 0.027394823 | Z16: =SUM(S16:V16)/SUM(R16:U16)-1 -> 0.045623756 | AA16: =SUM(T16:W16)/SUM(S16:V16)-1 -> 0.09057791
B17: IP | C17: United States | D17: Packaging & Containers | E17: Dec '25 Dec 31, 2025 | F17: 8.5373885 | G17: 5086 | H17: 5237 | I17: 5389 | J17: 5402 | K17: 5133 | L17: 5020 | M17: 4682 | N17: 4613 | O17: 4601 | P17: 4619 | Q17: 0 | R17: 3979 | S17: 4580 | T17: 5901 | U17: 0 | V17: 6222 | W17: 6006 | X17: =SUM(Q17:T17)/SUM(P17:S17)-1 -> 0.097283351 | Y17: =SUM(R17:U17)/SUM(Q17:T17)-1 -> 0 | Z17: =SUM(S17:V17)/SUM(R17:U17)-1 -> 0.15511757 | AA17: =SUM(T17:W17)/SUM(S17:V17)-1 -> 0.085373885
B18: VLY | C18: United States | D18: Banks - Regional | E18: Dec '25 Dec 31, 2025 | F18: 8.2156332 | G18: 339.71 | H18: 350.49 | I18: 429.5 | J18: 505.06 | K18: 508.16 | L18: 468.93 | M18: 471.47 | N18: 457.77 | O18: 424.84 | P18: 404.2 | Q18: 365.04 | R18: 382.96 | S18: 365.9 | T18: 406.42 | U18: 448.08 | V18: 483.79 | W18: 505.91 | X18: =SUM(Q18:T18)/SUM(P18:S18)-1 -> 0.0014623543 | Y18: =SUM(R18:U18)/SUM(Q18:T18)-1 -> 0.05462008 | Z18: =SUM(S18:V18)/SUM(R18:U18)-1 -> 0.062886688 | AA18: =SUM(T18:W18)/SUM(S18:V18)-1 -> 0.082156332
B19: APTUS | C19: India | D19: N/A | E19: Sep '25 Sep 30, 2025 | F19: 5.5457814 | G19: 1405 | H19: 1677 | I19: 1500 | J19: 1850 | K19: 2011 | L19: 2099 | M19: 2172 | N19: 2276 | O19: 3336 | P19: 2562 | Q19: 2729 | R19: 2811 | S19: 2981 | T19: 3089 | U19: 3412 | V19: 3591 | W19: 3706
B20: EPR | C20: United States | D20: REIT - Specialty | E20: Sep '25 Sep 30, 2025 | F20: 0.81803671 | G20: 139.19 | H20: 151.66 | I20: 156.77 | J20: 161.84 | K20: 161.85 | L20: 174.9 | M20: 169.41 | N20: 172.08 | O20: 189.72 | P20: 167.04 | Q20: 163.61 | R20: 171.9 | S20: 179.4 | T20: 173.57 | U20: 172.39 | V20: 176.32 | W20: 185.14
B21: GMDCLTD | C21: India | D21: N/A | E21: Sep '25 Sep 30, 2025 | F21: -2.2739917 | G21: 4519 | H21: 7246 | I21: 10573 | J21: 11554 | K21: 5389 | L21: 8554 | M21: 9482 | N21: 7656 | O21: 3827 | P21: 5643 | Q21: 8019 | R21: 8181 | S21: 5930 | T21: 6534 | U21: 8970 | V21: 7326 | W21: 5276
B22: SBCF | C22: United States | D22: Banks - Regional | E22: Dec '25 Dec 31, 2025 | F22: 8.0549816 | G22: 94.94 | H22: 85.34 | I22: 97.79 | J22: 99.71 | K22: 123.23 | L22: 119.88 | M22: 149.3 | N22: 134.41 | O22: 124.17 | P22: 124.21 | Q22: 121.69 | R22: 124.07 | S22: 129.17 | T22: 134.45 | U22: 144.01 | V22: 148.92 | W22: 174 | X22: =SUM(Q22:T22)/SUM(P22:S22)-1 -> 0.020515286 | Y22: =SUM(R22:U22)/SUM(Q22:T22)-1 -> 0.043817975 | Z22: =SUM(S22:V22)/SUM(R22:U22)-1 -> 0.046736882 | AA22: =SUM(T22:W22)/SUM(S22:V22)-1 -> 0.080549816
B23: FFWM | C23: United States | D23: Banks - Regional | E23: Dec '25 Dec 31, 2025 | F23: 6.7978197 | G23: 71.91 | H23: 90.71 | I23: 95.03 | J23: 99.88 | K23: 80.77 | L23: 70.04 | M23: 60.18 | N23: 65.79 | O23: 56.14 | P23: 50.49 | Q23: 58.29 | R23: -56.74 | S23: 44.03 | T23: 67.98 | U23: 49.05 | V23: -1.45 | W23: 54.88 | X23: =SUM(Q23:T23)/SUM(P23:S23)-1 -> 0.18205475 | Y23: =SUM(R23:U23)/SUM(Q23:T23)-1 -> -0.081366678 | Z23: =SUM(S23:V23)/SUM(R23:U23)-1 -> 0.53000383 | AA23: =SUM(T23:W23)/SUM(S23:V23)-1 -> 0.067978197
B24: ALGM | C24: United States | D24: Semiconductors | E24: Dec '25 Dec 26, 2025 | F24: 6.5120055 | G24: 186.63 | H24: 200.29 | I24: 217.75 | J24: 237.67 | K24: 248.79 | L24: 269.45 | M24: 278.29 | N24: 275.51 | O24: 254.98 | P24: 240.58 | Q24: 166.92 | R24: 187.39 | S24: 177.87 | T24: 192.82 | U24: 203.41 | V24: 214.29 | W24: 229.21 | X24: =SUM(Q24:T24)/SUM(P24:S24)-1 -> -0.061804441 | Y24: =SUM(R24:U24)/SUM(Q24:T24)-1 -> 0.050331034 | Z24: =SUM(S24:V24)/SUM(R24:U24)-1 -> 0.03532548 | AA24: =SUM(T24:W24)/SUM(S24:V24)-1 -> 0.065120055
B25: TAL | C25: United States | D25: Education & Training Services | E25: Nov '25 Nov 30, 2025 | F25: 6.171034 | G25: 1021 | H25: 541.15 | I25: 224.05 | J25: 294.06 | K25: 232.68 | L25: 268.99 | M25: 275.44 | N25: 411.93 | O25: 373.51 | P25: 429.56 | Q25: 414.19 | R25: 619.36 | S25: 606.45 | T25: 610.24 | U25: 575 | V25: 861.35 | W25: 770.17 | X25: =SUM(Q25:T25)/SUM(P25:S25)-1 -> 0.087303581 | Y25: =SUM(R25:U25)/SUM(Q25:T25)-1 -> 0.071463488 | Z25: =SUM(S25:V25)/SUM(R25:U25)-1 -> 0.10036706 | AA25: =SUM(T25:W25)/SUM(S25:V25)-1 -> 0.06171034
B26: AX | C26: United States | D26: Banks - Regional | E26: Dec '25 Dec 31, 2025 | F26: 5.3584793 | G26: 172.36 | H26: 173.81 | I26: 186.51 | J26: 198.93 | K26: 225.24 | L26: 225.73 | M26: 229.46 | N26: 238.66 | O26: 246.84 | P26: 288.77 | Q26: 284.92 | R26: 306.66 | S26: 295.65 | T26: 294.34 | U26: 306.45 | V26: 306.14 | W26: 360.09 | X26: =SUM(Q26:T26)/SUM(P26:S26)-1 -> 0.0047363946 | Y26: =SUM(R26:U26)/SUM(Q26:T26)-1 -> 0.018221519 | Z26: =SUM(S26:V26)/SUM(R26:U26)-1 -> -0.00043221677 | AA26: =SUM(T26:W26)/SUM(S26:V26)-1 -> 0.053584793
B27: APPF | C27: United States | D27: Software - Application | E27: Dec '25 Dec 31, 2025 | F27: 4.9134383 | G27: 95.6 | H27: 105.3 | I27: 117.45 | J27: 125.08 | K27: 124.06 | L27: 136.1 | M27: 147.08 | N27: 165.44 | O27: 171.83 | P27: 187.43 | Q27: 197.38 | R27: 205.73 | S27: 203.66 | T27: 217.7 | U27: 235.58 | V27: 249.35 | W27: 248.19 | X27: =SUM(Q27:T27)/SUM(P27:S27)-1 -> 0.038113825 | Y27: =SUM(R27:U27)/SUM(Q27:T27)-1 -> 0.046332796 | Z27: =SUM(S27:V27)/SUM(R27:U27)-1 -> 0.050563947 | AA27: =SUM(T27:W27)/SUM(S27:V27)-1 -> 0.049134383
B28: AAPL | C28: United States | D28: Consumer Electronics | E28: Dec '25 Dec 27, 2025 | F28: 4.6751137 | G28: 123945 | H28: 97278 | I28: 82959 | J28: 90146 | K28: 117154 | L28: 94836 | M28: 81797 | N28: 89498 | O28: 119575 | P28: 90753 | Q28: 85777 | R28: 94930 | S28: 124300 | T28: 95359 | U28: 94036 | V28: 102466 | W28: 143756 | X28: =SUM(Q28:T28)/SUM(P28:S28)-1 -> 0.011638367 | Y28: =SUM(R28:U28)/SUM(Q28:T28)-1 -> 0.020628625 | Z28: =SUM(S28:V28)/SUM(R28:U28)-1 -> 0.018442337 | AA28: =SUM(T28:W28)/SUM(S28:V28)-1 -> 0.046751137
B29: VIRT | C29: United States | D29: Capital Markets | E29: Dec '25 Dec 31, 2025 | F29: 4.5555102 | G29: 618.89 | H29: 609.81 | I29: 529.5 | J29: 472.57 | K29: 395.94 | L29: 496.02 | M29: 365.64 | N29: 469.41 | O29: 352.44 | P29: 490.19 | Q29: 520.18 | R29: 547.11 | S29: 660.31 | T29: 675.97 | U29: 734.14 | V29: 623.68 | W29: 783.04 | X29: =SUM(Q29:T29)/SUM(P29:S29)-1 -> 0.083768075 | Y29: =SUM(R29:U29)/SUM(Q29:T29)-1 -> 0.089017586 | Z29: =SUM(S29:V29)/SUM(R29:U29)-1 -> 0.029252769 | AA29: =SUM(T29:W29)/SUM(S29:V29)-1 -> 0.045555102
B30: CAT | C30: United States | D30: Farm & Heavy Construction Machinery | E30: Dec '25 Dec 31, 2025 | F30: 4.5120688 | G30: 13798 | H30: 13589 | I30: 14247 | J30: 14994 | K30: 16597 | L30: 15862 | M30: 17318 | N30: 16810 | O30: 17070 | P30: 15799 | Q30: 16689 | R30: 16106 | S30: 16215 | T30: 14249 | U30: 16569 | V30: 17638 | W30: 19133 | X30: =SUM(Q30:T30)/SUM(P30:S30)-1 -> -0.023916431 | Y30: =SUM(R30:U30)/SUM(Q30:T30)-1 -> -0.0018969633 | Z30: =SUM(S30:V30)/SUM(R30:U30)-1 -> 0.024263926 | AA30: =SUM(T30:W30)/SUM(S30:V30)-1 -> 0.045120688
B31: MA | C31: United States | D31: Credit Services | E31: Dec '25 Dec 31, 2025 | F31: 4.1844062 | G31: 5216 | H31: 5167 | I31: 5497 | J31: 5756 | K31: 5817 | L31: 5748 | M31: 6269 | N31: 6533 | O31: 6548 | P31: 6348 | Q31: 6961 | R31: 7369 | S31: 7489 | T31: 7250 | U31: 8133 | V31: 8602 | W31: 8806 | X31: =SUM(Q31:T31)/SUM(P31:S31)-1 -> 0.03202329 | Y31: =SUM(R31:U31)/SUM(Q31:T31)-1 -> 0.040317864 | Z31: =SUM(S31:V31)/SUM(R31:U31)-1 -> 0.040772461 | AA31: =SUM(T31:W31)/SUM(S31:V31)-1 -> 0.041844062
B32: CSW | C32: United States | D32: Specialty Industrial Machinery | E32: Dec '25 Dec 31, 2025 | F32: 4.077529 | G32: 136.29 | H32: 173.3 | I32: 199.93 | J32: 191.19 | K32: 171.09 | L32: 195.69 | M32: 203.36 | N32: 203.65 | O32: 174.97 | P32: 210.86 | Q32: 226.18 | R32: 227.93 | S32: 193.65 | T32: 230.55 | U32: 263.65 | V32: 276.95 | W32: 232.99 | X32: =SUM(Q32:T32)/SUM(P32:S32)-1 -> 0.022932147 | Y32: =SUM(R32:U32)/SUM(Q32:T32)-1 -> 0.042661475 | Z32: =SUM(S32:V32)/SUM(R32:U32)-1 -> 0.05352814 | AA32: =SUM(T32:W32)/SUM(S32:V32)-1 -> 0.04077529
B33: SXI | C33: United States | D33: Specialty Industrial Machinery | E33: Dec '25 Dec 31, 2025 | F33: 3.7643208 | G33: 185.71 | H33: 189.28 | I33: 184.74 | J33: 180.6 | K33: 187.79 | L33: 184.33 | M33: 188.33 | N33: 184.77 | O33: 178.4 | P33: 177.27 | Q33: 180.19 | R33: 170.46 | S33: 189.81 | T33: 207.78 | U33: 222.05 | V33: 217.43 | W33: 221.32 | X33: =SUM(Q33:T33)/SUM(P33:S33)-1 -> 0.042509021 | Y33: =SUM(R33:U33)/SUM(Q33:T33)-1 -> 0.055944617 | Z33: =SUM(S33:V33)/SUM(R33:U33)-1 -> 0.059448171 | AA33: =SUM(T33:W33)/SUM(S33:V33)-1 -> 0.037643208
... B35: SRCE | C35: United States | D35: Banks - Regional | E35: Dec '25 Dec 31, 2025 | F35: 3.6874754 | G35: 85.01 | H35: 80.53 | I35: 83.79 | J35: 87.77 | K35: 89.39 | L35: 89.84 | M35: 91.24 | N35: 92.83 | O35: 89.5 | P35: 86.59 | Q35: 97.59 | R35: 96.21 | S35: 95.14 | T35: 100.78 | U35: 100.56 | V35: 109.76 | W35: 110.12 | X35: =SUM(Q35:T35)/SUM(P35:S35)-1 -> 0.037786595 | Y35: =SUM(R35:U35)/SUM(Q35:T35)-1 -> 0.007620856 | Z35: =SUM(S35:V35)/SUM(R35:U35)-1 -> 0.03450559 | AA35: =SUM(T35:W35)/SUM(S35:V35)-1 -> 0.036874754
B36: INOXWIND | C36: India | D36: N/A | E36: Sep '25 Sep 30, 2025 | F36: 10.334882 | G36: 1658 | H36: 1520 | I36: 1374 | J36: 2106 | K36: 1072 | L36: 2262 | M36: 0 | N36: 3487 | O36: 3706 | P36: 5035 | Q36: 5308 | R36: 6388 | S36: 7322 | T36: 9113 | U36: 12748 | V36: 8263 | W36: 11192
B37: MO | C37: United States | D37: Tobacco | E37: Dec '25 Dec 31, 2025 | F37: 3.6695428 | G37: 5086 | H37: 4819 | I37: 5374 | J37: 5412 | K37: 5083 | L37: 4763 | M37: 5438 | N37: 5277 | O37: 5024 | P37: 4717 | Q37: 5277 | R37: 5344 | S37: 5106 | T37: 4519 | U37: 5290 | V37: 5251 | W37: 5846 | X37: =SUM(Q37:T37)/SUM(P37:S37)-1 -> -0.0096849932 | Y37: =SUM(R37:U37)/SUM(Q37:T37)-1 -> 0.00064210214 | Z37: =SUM(S37:V37)/SUM(R37:U37)-1 -> -0.0045905523 | AA37: =SUM(T37:W37)/SUM(S37:V37)-1 -> 0.036695428
B38: HMN | C38: United States | D38: Insurance - Property & Casualty | E38: Sep '25 Sep 30, 2025 | F38: 1.6007761 | G38: 329.6 | H38: 331.4 | I38: 346.7 | J38: 345.9 | K38: 342.6 | L38: 346.4 | M38: 353.9 | N38: 356.4 | O38: 378.7 | P38: 402.9 | Q38: 386 | R38: 388.1 | S38: 412.1 | T38: 409 | U38: 416.4 | V38: 411.7 | W38: 438.5
B39: V | C39: United States | D39: Credit Services | E39: Dec '25 Dec 31, 2025 | F39: 3.4775 | G39: 7059 | H39: 7189 | I39: 7275 | J39: 7787 | K39: 7936 | L39: 7985 | M39: 8123 | N39: 8609 | O39: 8634 | P39: 8775 | Q39: 8900 | R39: 9617 | S39: 9510 | T39: 9594 | U39: 10172 | V39: 10724 | W39: 10901 | X39: =SUM(Q39:T39)/SUM(P39:S39)-1 -> 0.022254225 | Y39: =SUM(R39:U39)/SUM(Q39:T39)-1 -> 0.033810903 | Z39: =SUM(S39:V39)/SUM(R39:U39)-1 -> 0.028462705 | AA39: =SUM(T39:W39)/SUM(S39:V39)-1 -> 0.034775
B40: BC | C40: United States | D40: Recreational Vehicles | E40: Dec '25 Dec 31, 2025 | F40: 3.4529321 | G40: 1431 | H40: 1696 | I40: 1836 | J40: 1698 | K40: 1583 | L40: 1744 | M40: 1702 | N40: 1594 | O40: 1362 | P40: 1365 | Q40: 1444 | R40: 1273 | S40: 1155 | T40: 1222 | U40: 1447 | V40: 1360 | W40: 1334 | X40: =SUM(Q40:T40)/SUM(P40:S40)-1 -> -0.027305709 | Y40: =SUM(R40:U40)/SUM(Q40:T40)-1 -> 0.00058892815 | Z40: =SUM(S40:V40)/SUM(R40:U40)-1 -> 0.017068864 | AA40: =SUM(T40:W40)/SUM(S40:V40)-1 -> 0.034529321
B41: FHI | C41: United States | D41: Asset Management | E41: Dec '25 Dec 31, 2025 | F41: 3.3371401 | G41: 321.65 | H41: 324.76 | I41: 366.01 | J41: 381.14 | K41: 373.9 | L41: 382.19 | M41: 433.23 | N41: 402.66 | O41: 391.5 | P41: 396.37 | Q41: 402.58 | R41: 408.46 | S41: 424.68 | T41: 423.54 | U41: 424.84 | V41: 469.45 | W41: 482.83 | X41: =SUM(Q41:T41)/SUM(P41:S41)-1 -> 0.016647366 | Y41: =SUM(R41:U41)/SUM(Q41:T41)-1 -> 0.013415619 | Z41: =SUM(S41:V41)/SUM(R41:U41)-1 -> 0.036270755 | AA41: =SUM(T41:W41)/SUM(S41:V41)-1 -> 0.033371401
B42: LAZ | C42: United States | D42: Capital Markets | E42: Dec '25 Dec 31, 2025 | F42: 3.159908 | G42: 1001 | H42: 692.99 | I42: 635.84 | J42: 724.09 | K42: 720.25 | L42: 542.34 | M42: 643.91 | N42: 524.9 | O42: 809.91 | P42: 763.42 | Q42: 683.46 | R42: 790.73 | S42: 811.39 | T42: 653.45 | U42: 805.61 | V42: 746.41 | W42: 906.72 | X42: =SUM(Q42:T42)/SUM(P42:S42)-1 -> -0.036067563 | Y42: =SUM(R42:U42)/SUM(Q42:T42)-1 -> 0.041561331 | Z42: =SUM(S42:V42)/SUM(R42:U42)-1 -> -0.014478077 | AA42: =SUM(T42:W42)/SUM(S42:V42)-1 -> 0.03159908
B43: SYK | C43: United States | D43: Medical Devices | E43: Dec '25 Dec 31, 2025 | F43: 3.0146425 | G43: 4701 | H43: 4275 | I43: 4493 | J43: 4479 | K43: 5202 | L43: 4778 | M43: 4996 | N43: 4909 | O43: 5815 | P43: 5243 | Q43: 5422 | R43: 5494 | S43: 6436 | T43: 5866 | U43: 6022 | V43: 6057 | W43: 7171 | X43: =SUM(Q43:T43)/SUM(P43:S43)-1 -> 0.027572472 | Y43: =SUM(R43:U43)/SUM(Q43:T43)-1 -> 0.025842019 | Z43: =SUM(S43:V43)/SUM(R43:U43)-1 -> 0.023637585 | AA43: =SUM(T43:W43)/SUM(S43:V43)-1 -> 0.030146425
B44: RCL | C44: United States | D44: Travel Services | E44: Dec '25 Dec 31, 2025 | F44: 2.8559959 | G44: 982.25 | H44: 1059 | I44: 2184 | J44: 2993 | K44: 2603 | L44: 2886 | M44: 3523 | N44: 4160 | O44: 3331 | P44: 3728 | Q44: 4110 | R44: 4886 | S44: 3761 | T44: 3999 | U44: 4538 | V44: 5139 | W44: 4259 | X44: =SUM(Q44:T44)/SUM(P44:S44)-1 -> 0.016439187 | Y44: =SUM(R44:U44)/SUM(Q44:T44)-1 -> 0.025543089 | Z44: =SUM(S44:V44)/SUM(R44:U44)-1 -> 0.014722998 | AA44: =SUM(T44:W44)/SUM(S44:V44)-1 -> 0.028559959
B45: CVCO | C45: United States | D45: Residential Construction | E45: Dec '25 Dec 27, 2025 | F45: 2.7498029 | G45: 431.71 | H45: 505.48 | I45: 588.34 | J45: 577.39 | K45: 500.6 | L45: 476.38 | M45: 475.88 | N45: 452.03 | O45: 446.77 | P45: 420.12 | Q45: 477.6 | R45: 507.46 | S45: 522.04 | T45: 508.36 | U45: 556.86 | V45: 556.53 | W45: 580.99 | X45: =SUM(Q45:T45)/SUM(P45:S45)-1 -> 0.045786158 | Y45: =SUM(R45:U45)/SUM(Q45:T45)-1 -> 0.03932601 | Z45: =SUM(S45:V45)/SUM(R45:U45)-1 -> 0.023425565 | AA45: =SUM(T45:W45)/SUM(S45:V45)-1 -> 0.027498029
B46: IEX | C46: United States | D46: Specialty Industrial Machinery | E46: Sep '25 Sep 30, 2025 | F46: 2.4096025 | G46: 712 | H46: 714.8 | I46: 751.1 | J46: 796.1 | K46: 824 | L46: 810.7 | M46: 845.4 | N46: 846.2 | O46: 793.4 | P46: 788.9 | Q46: 800.5 | R46: 807.2 | S46: 798.2 | T46: 862.9 | U46: 814.3 | V46: 865.4 | W46: 878.7
B47: RMD | C47: United States | D47: Medical Instruments & Supplies | E47: Dec '25 Dec 31, 2025 | F47: 2.681628 | G47: 894.87 | H47: 864.5 | I47: 914.74 | J47: 950.29 | K47: 1034 | L47: 1117 | M47: 1122 | N47: 1102 | O47: 1163 | P47: 1197 | Q47: 1223 | R47: 1225 | S47: 1282 | T47: 1292 | U47: 1348 | V47: 1336 | W47: 1423 | X47: =SUM(Q47:T47)/SUM(P47:S47)-1 -> 0.01928151 | Y47: =SUM(R47:U47)/SUM(Q47:T47)-1 -> 0.024890482 | Z47: =SUM(S47:V47)/SUM(R47:U47)-1 -> 0.021565961 | AA47: =SUM(T47:W47)/SUM(S47:V47)-1 -> 0.02681628
B48: TFSL | C48: United States | D48: Banks - Regional | E48: Dec '25 Dec 31, 2025 | F48: 2.6334765 | G48: 68 | H48: 69.33 | I48: 72.98 | J48: 79.89 | K48: 81.31 | L48: 75.6 | M48: 74.62 | N48: 74.96 | O48: 76.41 | P48: 78.1 | Q48: 76.02 | R48: 74.14 | S48: 76.33 | T48: 77.62 | U48: 80.54 | V48: 84.48 | W48: 84.73 | X48: =SUM(Q48:T48)/SUM(P48:S48)-1 -> -0.0015758889 | Y48: =SUM(R48:U48)/SUM(Q48:T48)-1 -> 0.014863043 | Z48: =SUM(S48:V48)/SUM(R48:U48)-1 -> 0.0335029 | AA48: =SUM(T48:W48)/SUM(S48:V48)-1 -> 0.026334765
B49: LGBBROSLTD | C49: India | D49: N/A | E49: Sep '25 Sep 30, 2025 | F49: 4.7334835 | G49: 5767 | H49: 5739 | I49: 5589 | J49: 5209 | K49: 5780 | L49: 5810 | M49: 5230 | N49: 5386 | O49: 6001 | P49: 6004 | Q49: 6070 | R49: 5713 | S49: 6609 | T49: 6769 | U49: 6692 | V49: 6570 | W49: 7870
B50: 8014 | C50: Japan | D50: N/A | E50: Sep '25 Sep 30, 2025 | F50: -1.3379106 | G50: 69355 | H50: 75809 | I50: 78261 | J50: 81906 | K50: 86566 | L50: 86907 | M50: 74010 | N50: 75780 | O50: 77126 | P50: 80451 | Q50: 74342 | R50: 76974 | S50: 77481 | T50: 75802 | U50: 81289 | V50: 71577 | W50: 73385
B51: TEXRAIL | C51: India | D51: N/A | E51: Sep '25 Sep 30, 2025 | F51: -1.7812944 | G51: 3737 | H51: 4705 | I51: 4467 | J51: 2987 | K51: 4844 | L51: 6249 | M51: 8353 | N51: 6568 | O51: 8050 | P51: 8964 | Q51: 11446 | R51: 8917 | S51: 13459 | T51: 13261 | U51: 13464 | V51: 9106 | W51: 12581
B52: SXC | C52: United States | D52: Coking Coal | E52: Sep '25 Sep 30, 2025 | F52: -0.16791247 | G52: 366.5 | H52: 365.3 | I52: 439.8 | J52: 501.9 | K52: 516.8 | L52: 514 | M52: 487.8 | N52: 534.4 | O52: 520.4 | P52: 520.6 | Q52: 488.4 | R52: 470.9 | S52: 490.1 | T52: 486 | U52: 436 | V52: 434.1 | W52: 487
B53: SFL | C53: United States | D53: Marine Shipping | E53: Sep '25 Sep 30, 2025 | F53: -9.1503038 | G53: 134.1 | H53: 150.91 | I53: 151.28 | J53: 151.67 | K53: 165.35 | L53: 196.26 | M53: 171.15 | N53: 162.5 | O53: 203.22 | P53: 207.47 | Q53: 226.77 | R53: 188.59 | S53: 253.25 | T53: 225.46 | U53: 185.3 | V53: 188.53 | W53: 175.24
B54: OSIS | C54: United States | D54: Electronic Components | E54: Dec '25 Dec 31, 2025 | F54: 2.5225513 | G54: 276.68 | H54: 290.48 | I54: 336.82 | J54: 268.07 | K54: 295.6 | L54: 302.89 | M54: 411.87 | N54: 279.21 | O54: 373.24 | P54: 405.41 | Q54: 480.91 | R54: 344.01 | S54: 419.82 | T54: 444.35 | U54: 504.99 | V54: 384.62 | W54: 464.06 | X54: =SUM(Q54:T54)/SUM(P54:S54)-1 -> 0.023597855 | Y54: =SUM(R54:U54)/SUM(Q54:T54)-1 -> 0.014256197 | Z54: =SUM(S54:V54)/SUM(R54:U54)-1 -> 0.023704594 | AA54: =SUM(T54:W54)/SUM(S54:V54)-1 -> 0.025225513
B55: MHRIL | C55: India | D55: N/A | E55: Sep '25 Sep 30, 2025 | F55: 1.6470505 | G55: 5464 | H55: 5534 | I55: 5426 | J55: 6049 | K55: 5984 | L55: 6022 | M55: 7116 | N55: 6143 | O55: 6553 | P55: 6348 | Q55: 8002 | R55: 6529 | S55: 6707 | T55: 6784 | U55: 7788 | V55: 7014 | W55: 7173
B56: DECK | C56: United States | D56: Footwear & Accessories | E56: Dec '25 Dec 31, 2025 | F56: 2.4978358 | G56: 1188 | H56: 736.01 | I56: 614.46 | J56: 875.61 | K56: 1346 | L56: 791.57 | M56: 675.79 | N56: 1092 | O56: 1560 | P56: 959.76 | Q56: 825.35 | R56: 1311 | S56: 1827 | T56: 1022 | U56: 964.54 | V56: 1431 | W56: 1958 | X56: =SUM(Q56:T56)/SUM(P56:S56)-1 -> 0.012642415 | Y56: =SUM(R56:U56)/SUM(Q56:T56)-1 -> 0.027919805 | Z56: =SUM(S56:V56)/SUM(R56:U56)-1 -> 0.023416736 | AA56: =SUM(T56:W56)/SUM(S56:V56)-1 -> 0.024978358
B57: LMT | C57: United States | D57: Aerospace & Defense | E57: Dec '25 Dec 31, 2025 | F57: 2.3163233 | G57: 17729 | H57: 14964 | I57: 15446 | J57: 16583 | K57: 18991 | L57: 15126 | M57: 16693 | N57: 16878 | O57: 18874 | P57: 17195 | Q57: 18122 | R57: 17104 | S57: 18622 | T57: 17963 | U57: 18155 | V57: 18609 | W57: 20321 | X57: =SUM(Q57:T57)/SUM(P57:S57)-1 -> 0.010810354 | Y57: =SUM(R57:U57)/SUM(Q57:T57)-1 -> 0.00045953962 | Z57: =SUM(S57:V57)/SUM(R57:U57)-1 -> 0.020948165 | AA57: =SUM(T57:W57)/SUM(S57:V57)-1 -> 0.023163233
B58: CFR | C58: United States | D58: Banks - Regional | E58: Dec '25 Dec 31, 2025 | F58: 2.3099767 | G58: 349.76 | H58: 350.46 | I58: 386.14 | J58: 455.37 | K58: 501.14 | L58: 495.98 | M58: 478.89 | N58: 480.24 | O58: 485.92 | P58: 487.78 | Q58: 492.12 | R58: 498.65 | S58: 520.18 | T58: 527.16 | U58: 533.75 | V58: 560.49 | W58: 569.65 | X58: =SUM(Q58:T58)/SUM(P58:S58)-1 -> 0.019702511 | Y58: =SUM(R58:U58)/SUM(Q58:T58)-1 -> 0.020425787 | Z58: =SUM(S58:V58)/SUM(R58:U58)-1 -> 0.029734486 | AA58: =SUM(T58:W58)/SUM(S58:V58)-1 -> 0.023099767
B59: PRAJIND | C59: India | D59: N/A | E59: Sep '25 Sep 30, 2025 | F59: 0.80148938 | G59: 5324 | H59: 5856 | I59: 8390 | J59: 7299 | K59: 8766 | L59: 9100 | M59: 10116 | N59: 7367 | O59: 8824 | P59: 8286 | Q59: 10186 | R59: 6991 | S59: 8162 | T59: 8530 | U59: 8597 | V59: 6402 | W59: 8416
B60: PH | C60: United States | D60: Specialty Industrial Machinery | E60: Dec '25 Dec 31, 2025 | F60: 2.1517723 | G60: 3825 | H60: 4086 | I60: 4188 | J60: 4233 | K60: 4675 | L60: 5062 | M60: 5096 | N60: 4847 | O60: 4821 | P60: 5074 | Q60: 5187 | R60: 4904 | S60: 4743 | T60: 4960 | U60: 5243 | V60: 5084 | W60: 5174 | X60: =SUM(Q60:T60)/SUM(P60:S60)-1 -> -0.0057263412 | Y60: =SUM(R60:U60)/SUM(Q60:T60)-1 -> 0.0028291401 | Z60: =SUM(S60:V60)/SUM(R60:U60)-1 -> 0.0090680101 | AA60: =SUM(T60:W60)/SUM(S60:V60)-1 -> 0.021517723
B61: AMP | C61: United States | D61: Asset Management | E61: Dec '25 Dec 31, 2025 | F61: 2.1498407 | G61: 3762 | H61: 3627 | I61: 3489 | J61: 3499 | K61: 3719 | L61: 3845 | M61: 4007 | N61: 4076 | O61: 4168 | P61: 4325 | Q61: 4392 | R61: 4560 | S61: 4649 | T61: 4481 | U61: 4490 | V61: 4893 | W61: 5047 | X61: =SUM(Q61:T61)/SUM(P61:S61)-1 -> 0.0087024434 | Y61: =SUM(R61:U61)/SUM(Q61:T61)-1 -> 0.0054197545 | Z61: =SUM(S61:V61)/SUM(R61:U61)-1 -> 0.018316832 | AA61: =SUM(T61:W61)/SUM(S61:V61)-1 -> 0.021498407
B62: 4549 | C62: Japan | D62: N/A | E62: Sep '25 Sep 30, 2025 | F62: 0.055802218 | G62: 10827 | H62: 10490 | I62: 11165 | J62: 11097 | K62: 11768 | L62: 10995 | M62: 9411 | N62: 9864 | O62: 10400 | P62: 10229 | Q62: 9559 | R62: 9519 | S62: 10210 | T62: 10911 | U62: 9899 | V62: 10197 | W62: 10233
B63: AROW | C63: United States | D63: Banks - Regional | E63: Sep '25 Sep 30, 2025 | F63: 4.5503098 | G63: 36.23 | H63: 34.23 | I63: 35.22 | J63: 35.88 | K63: 37.01 | L63: 36.34 | M63: 33.22 | N63: 31.73 | O63: 33.05 | P63: 32.57 | Q63: 33.7 | R63: 34.23 | S63: 35.64 | T63: 31.06 | U63: 34.18 | V63: 39.55 | W63: 42.03
B64: RRBI | C64: United States | D64: Banks - Regional | E64: Sep '25 Sep 30, 2025 | F64: 3.190567 | G64: 23.6 | H64: 24.3 | I64: 22.98 | J64: 25.76 | K64: 27.36 | L64: 27.54 | M64: 27.25 | N64: 27.22 | O64: 26.12 | P64: 26.23 | Q64: 25.85 | R64: 26.59 | S64: 27.58 | T64: 28.24 | U64: 29.43 | V64: 30.09 | W64: 31.26
B65: 9997 | C65: Japan | D65: N/A | E65: Sep '25 Sep 30, 2025 | F65: 0.66899969 | G65: 46882 | H65: 62819 | I65: 51501 | J65: 53439 | K65: 45340 | L65: 61675 | M65: 51922 | N65: 51842 | O65: 44263 | P65: 60173 | Q65: 52020 | R65: 51368 | S65: 45759 | T65: 61520 | U65: 52209 | V65: 50826 | W65: 47166
B66: DOV | C66: United States | D66: Specialty Industrial Machinery | E66: Dec '25 Dec 31, 2025 | F66: 2.1327612 | G66: 1989 | H66: 2052 | I66: 2159 | J66: 2158 | K66: 2139 | L66: 2079 | M66: 0 | N66: 1958 | O66: 1905 | P66: 1884 | Q66: 1949 | R66: 1984 | S66: 1930 | T66: 1866 | U66: 2050 | V66: 2078 | W66: 2099 | X66: =SUM(Q66:T66)/SUM(P66:S66)-1 -> -0.0023234801 | Y66: =SUM(R66:U66)/SUM(Q66:T66)-1 -> 0.013067667 | Z66: =SUM(S66:V66)/SUM(R66:U66)-1 -> 0.012005109 | AA66: =SUM(T66:W66)/SUM(S66:V66)-1 -> 0.021327612
B67: 8871 | C67: Japan | D67: N/A | E67: Sep '25 Sep 30, 2025 | F67: -5.1904776 | G67: 3412 | H67: 20943 | I67: 4153 | J67: 15029 | K67: 4969 | L67: 3449 | M67: 4006 | N67: 2533 | O67: 3754 | P67: 6496 | Q67: 12062 | R67: 6741 | S67: 6967 | T67: 10544 | U67: 5042 | V67: 10758 | W67: 5238
B68: SIGI | C68: United States | D68: Insurance - Property & Casualty | E68: Dec '25 Dec 31, 2025 | F68: 2.0849273 | G68: 869.7 | H68: 846.06 | I68: 864.82 | J68: 895.02 | K68: 952.16 | L68: 999.82 | M68: 1041 | N68: 1081 | O68: 1111 | P68: 1165 | Q68: 1196 | R68: 1244 | S68: 1256 | T68: 1285 | U68: 1327 | V68: 1360 | W68: 1365 | X68: =SUM(Q68:T68)/SUM(P68:S68)-1 -> 0.024686279 | Y68: =SUM(R68:U68)/SUM(Q68:T68)-1 -> 0.02629994 | Z68: =SUM(S68:V68)/SUM(R68:U68)-1 -> 0.022691706 | AA68: =SUM(T68:W68)/SUM(S68:V68)-1 -> 0.020849273
B69: SKYW | C69: United States | D69: Airlines | E69: Dec '25 Dec 31, 2025 | F69: 2.001076 | G69: 777.16 | H69: 735.15 | I69: 799.09 | J69: 789.44 | K69: 681.25 | L69: 691.83 | M69: 725.64 | N69: 766.17 | O69: 751.79 | P69: 803.61 | Q69: 867.12 | R69: 912.79 | S69: 944.4 | T69: 948.46 | U69: 1035 | V69: 1050 | W69: 1024 | X69: =SUM(Q69:T69)/SUM(P69:S69)-1 -> 0.041058187 | Y69: =SUM(R69:U69)/SUM(Q69:T69)-1 -> 0.045709369 | Z69: =SUM(S69:V69)/SUM(R69:U69)-1 -> 0.035725724 | AA69: =SUM(T69:W69)/SUM(S69:V69)-1 -> 0.02001076
B70: GODREJAGRO | C70: India | D70: N/A | E70: Sep '25 Sep 30, 2025 | F70: 1.2557338 | G70: 21573 | H70: 20884 | I70: 20612 | J70: 24991 | K70: 24422 | L70: 23228 | M70: 21020 | N70: 24993 | O70: 25667 | P70: 23419 | Q70: 21391 | R70: 23434 | S70: 24427 | T70: 24446 | U70: 21452 | V70: 26033 | W70: 25637
B71: ORC | C71: United States | D71: REIT - Mortgage | E71: Sep '25 Sep 30, 2025 | F71: 230.54411 | G71: 29.71 | H71: -40.2 | I71: -144.35 | J71: -55.59 | K71: -80.18 | L71: 39.11 | M71: 8.53 | N71: 15.07 | O71: -75.49 | P71: 31.19 | Q71: 23.51 | R71: -0.6 | S71: 21.59 | T71: 9.9 | U71: 21.35 | V71: -28.58 | W71: 77.52
B72: 1950 | C72: Japan | D72: N/A | E72: Sep '25 Sep 30, 2025 | F72: 2.6015083 | G72: 35902 | H72: 41580 | I72: 68306 | J72: 25506 | K72: 35383 | L72: 40833 | M72: 70378 | N72: 28577 | O72: 42462 | P72: 46472 | Q72: 76520 | R72: 33011 | S72: 42614 | T72: 49388 | U72: 91909 | V72: 30234 | W72: 48185
B73: MRSH | C73: United States | D73: Insurance Brokers | E73: Dec '25 Dec 31, 2025 | F73: 1.9959929 | G73: 5137 | H73: 5549 | I73: 5379 | J73: 4770 | K73: 5022 | L73: 5924 | M73: 5876 | N73: 5382 | O73: 5554 | P73: 6473 | Q73: 6221 | R73: 5697 | S73: 6067 | T73: 7061 | U73: 6974 | V73: 6351 | W73: 6595 | X73: =SUM(Q73:T73)/SUM(P73:S73)-1 -> 0.024041214 | Y73: =SUM(R73:U73)/SUM(Q73:T73)-1 -> 0.030064681 | Z73: =SUM(S73:V73)/SUM(R73:U73)-1 -> 0.02534982 | AA73: =SUM(T73:W73)/SUM(S73:V73)-1 -> 0.019959929
B74: 5482 | C74: Japan | D74: N/A | E74: Sep '25 Sep 30, 2025 | F74: 0.55944981 | G74: 61439 | H74: 67560 | I74: 69552 | J74: 66857 | K74: 72952 | L74: 69876 | M74: 75455 | N74: 73813 | O74: 75500 | P74: 77654 | Q74: 69548 | R74: 71933 | S74: 73030 | T74: 76909 | U74: 77415 | V74: 75086 | W74: 74722
B75: MEDPLUS | C75: India | D75: N/A | E75: Sep '25 Sep 30, 2025 | F75: 1.6656435 | G75: 9247 | H75: 9335 | I75: 9659 | J75: 9937 | K75: 11206 | L75: 11903 | M75: 12530 | N75: 12843 | O75: 14086 | P75: 14415 | Q75: 14905 | R75: 14888 | S75: 15762 | T75: 15614 | U75: 15096 | V75: 15426 | W75: 16793
B76: TMO | C76: United States | D76: Diagnostics & Research | E76: Dec '25 Dec 31, 2025 | F76: 1.8748857 | G76: 10702 | H76: 11818 | I76: 10970 | J76: 10677 | K76: 11450 | L76: 10710 | M76: 10687 | N76: 10574 | O76: 10886 | P76: 10345 | Q76: 10541 | R76: 10598 | S76: 11395 | T76: 10364 | U76: 10855 | V76: 11122 | W76: 12215 | X76: =SUM(Q76:T76)/SUM(P76:S76)-1 -> 0.00044310735 | Y76: =SUM(R76:U76)/SUM(Q76:T76)-1 -> 0.0073196886 | Z76: =SUM(S76:V76)/SUM(R76:U76)-1 -> 0.012126261 | AA76: =SUM(T76:W76)/SUM(S76:V76)-1 -> 0.018748857
B77: KTKBANK | C77: India | D77: N/A | E77: Sep '25 Sep 30, 2025 | F77: -0.48653222 | G77: 5647 | H77: 6806 | I77: 8176 | J77: 4575 | K77: 10766 | L77: 8744 | M77: 10020 | N77: 9870 | O77: 9522 | P77: 10093 | Q77: 10688 | R77: 11421 | S77: 10722 | T77: 10080 | U77: 11712 | V77: 10032 | W77: 10515
B78: 8388 | C78: Japan | D78: N/A | E78: Sep '25 Sep 30, 2025 | F78: 6.8245223 | G78: 13716 | H78: 16114 | I78: 16398 | J78: 18816 | K78: 18049 | L78: 26480 | M78: 15872 | N78: 15521 | O78: 15706 | P78: 17162 | Q78: 15543 | R78: 17950 | S78: 16573 | T78: 18265 | U78: 15297 | V78: 21196 | W78: 21441
B79: MAN | C79: United States | D79: Staffing & Employment Services | E79: Dec '25 Dec 31, 2025 | F79: 1.7740747 | G79: 5382 | H79: 5143 | I79: 5074 | J79: 4801 | K79: 4809 | L79: 4752 | M79: 4856 | N79: 4676 | O79: 4631 | P79: 4403 | Q79: 4521 | R79: 4530 | S79: 4400 | T79: 4090 | U79: 4519 | V79: 4634 | W79: 4713 | X79: =SUM(Q79:T79)/SUM(P79:S79)-1 -> -0.017531085 | Y79: =SUM(R79:U79)/SUM(Q79:T79)-1 -> -0.00011401859 | Z79: =SUM(S79:V79)/SUM(R79:U79)-1 -> 0.0059296425 | AA79: =SUM(T79:W79)/SUM(S79:V79)-1 -> 0.017740747
B80: KLAC | C80: United States | D80: Semiconductor Equipment & Materials | E80: Dec '25 Dec 31, 2025 | F80: 1.756487 | G80: 2353 | H80: 2289 | I80: 2487 | J80: 2724 | K80: 2984 | L80: 2433 | M80: 2355 | N80: 2397 | O80: 2487 | P80: 2360 | Q80: 2569 | R80: 2842 | S80: 3077 | T80: 3063 | U80: 3175 | V80: 3210 | W80: 3297 | X80: =SUM(Q80:T80)/SUM(P80:S80)-1 -> 0.064804572 | Y80: =SUM(R80:U80)/SUM(Q80:T80)-1 -> 0.05246299 | Z80: =SUM(S80:V80)/SUM(R80:U80)-1 -> 0.030270626 | AA80: =SUM(T80:W80)/SUM(S80:V80)-1 -> 0.01756487
B81: HIG | C81: United States | D81: Insurance - Diversified | E81: Dec '25 Dec 31, 2025 | F81: 1.6155031 | G81: 5809 | H81: 5382 | I81: 5366 | J81: 5578 | K81: 6030 | L81: 5916 | M81: 6053 | N81: 6171 | O81: 6413 | P81: 6423 | Q81: 6491 | R81: 6757 | S81: 6889 | T81: 6809 | U81: 6987 | V81: 7232 | W81: 7340 | X81: =SUM(Q81:T81)/SUM(P81:S81)-1 -> 0.014533133 | Y81: =SUM(R81:U81)/SUM(Q81:T81)-1 -> 0.018407185 | Z81: =SUM(S81:V81)/SUM(R81:U81)-1 -> 0.017309234 | AA81: =SUM(T81:W81)/SUM(S81:V81)-1 -> 0.016155031
B82: MOFG | C82: United States | D82: Banks - Regional | E82: Sep '25 Sep 30, 2025 | F82: 224.75479 | G82: 50.6 | H82: 49.43 | I82: 48.98 | J82: 50.05 | K82: 57.68 | L82: 52.68 | M82: 35.1 | N82: 44.11 | O82: 42.89 | P82: 34.65 | Q82: 39.79 | R82: 56.63 | S82: -94.4 | T82: 58.48 | U82: 55.89 | V82: 48.34 | W82: 59.13
B83: 3191 | C83: Japan | D83: N/A | E83: Sep '25 Sep 20, 2025 | F83: -2.4497006 | G83: 38576 | H83: 41529 | I83: 37961 | J83: 39125 | K83: 36584 | L83: 39786 | M83: 37979 | N83: 39355 | O83: 36657 | P83: 39138 | Q83: 38921 | R83: 39596 | S83: 37329 | T83: 35220 | U83: 34252 | V83: 35298 | W83: 33848
B84: GMRP&UI | C84: India | D84: N/A | E84: Sep '25 Sep 30, 2025 | F84: 6.5582597 | G84: 10510 | H84: 9641 | I84: 12111 | J84: 10687 | K84: 15807 | L84: 14474 | M84: 14189 | N84: 11242 | O84: 6275 | P84: 11028 | Q84: 16341 | R84: 16119 | S84: 13841 | T84: 16115 | U84: 17365 | V84: 17681 | W84: 18104
B85: HZO | C85: United States | D85: Specialty Retail | E85: Dec '25 Dec 31, 2025 | F85: 1.5900991 | G85: 472.69 | H85: 610.11 | I85: 688.54 | J85: 536.76 | K85: 507.93 | L85: 570.34 | M85: 721.84 | N85: 594.6 | O85: 527.27 | P85: 582.89 | Q85: 757.72 | R85: 563.12 | S85: 468.46 | T85: 631.52 | U85: 657.16 | V85: 552.15 | W85: 505.18 | X85: =SUM(Q85:T85)/SUM(P85:S85)-1 -> 0.020500044 | Y85: =SUM(R85:U85)/SUM(Q85:T85)-1 -> -0.041539644 | Z85: =SUM(S85:V85)/SUM(R85:U85)-1 -> -0.0047279184 | AA85: =SUM(T85:W85)/SUM(S85:V85)-1 -> 0.015900991
B86: CRTO | C86: United States | D86: Advertising Agencies | E86: Sep '25 Sep 30, 2025 | F86: 0.55343443 | G86: 508.58 | H86: 653.27 | I86: 510.57 | J86: 495.09 | K86: 446.92 | L86: 564.43 | M86: 445.02 | N86: 468.93 | O86: 469.19 | P86: 566.3 | Q86: 450.06 | R86: 471.31 | S86: 458.89 | T86: 553.04 | U86: 451.43 | V86: 482.67 | W86: 469.66
B87: CVLG | C87: United States | D87: Trucking | E87: Dec '25 Dec 31, 2025 | F87: 1.5735806 | G87: 294.23 | H87: 291.59 | I87: 317.38 | J87: 311.84 | K87: 296.06 | L87: 266.85 | M87: 274.02 | N87: 288.72 | O87: 273.99 | P87: 278.76 | Q87: 287.5 | R87: 287.89 | S87: 277.33 | T87: 269.36 | U87: 302.85 | V87: 296.89 | W87: 295.37 | X87: =SUM(Q87:T87)/SUM(P87:S87)-1 -> -0.0083077032 | Y87: =SUM(R87:U87)/SUM(Q87:T87)-1 -> 0.013679952 | Z87: =SUM(S87:V87)/SUM(R87:U87)-1 -> 0.0079125748 | AA87: =SUM(T87:W87)/SUM(S87:V87)-1 -> 0.015735806
B88: 6946 | C88: Japan | D88: N/A | E88: Sep '25 Sep 30, 2025 | F88: 12.561693 | G88: 5274 | H88: 4532 | I88: 5050 | J88: 3263 | K88: 4599 | L88: 4762 | M88: 5130 | N88: 3605 | O88: 5064 | P88: 4584 | Q88: 4802 | R88: 4087 | S88: 5019 | T88: 4564 | U88: 6452 | V88: 5037 | W88: 7666
B89: KEX | C89: United States | D89: Marine Shipping | E89: Dec '25 Dec 31, 2025 | F89: 1.4921861 | G89: 591.27 | H89: 610.78 | I89: 697.96 | J89: 745.84 | K89: 730.17 | L89: 750.44 | M89: 777.25 | N89: 764.77 | O89: 799.18 | P89: 808.02 | Q89: 824.39 | R89: 831.15 | S89: 802.32 | T89: 785.66 | U89: 855.46 | V89: 871.16 | W89: 851.78 | X89: =SUM(Q89:T89)/SUM(P89:S89)-1 -> -0.0068465467 | Y89: =SUM(R89:U89)/SUM(Q89:T89)-1 -> 0.0095790993 | Z89: =SUM(S89:V89)/SUM(R89:U89)-1 -> 0.012218324 | AA89: =SUM(T89:W89)/SUM(S89:V89)-1 -> 0.014921861
B90: TT | C90: United States | D90: Building Products & Equipment | E90: Dec '25 Dec 31, 2025 | F90: 1.2872886 | G90: 3569 | H90: 3356 | I90: 4190 | J90: 4372 | K90: 4074 | L90: 3666 | M90: 4705 | N90: 4883 | O90: 4424 | P90: 4216 | Q90: 5307 | R90: 5441 | S90: 4874 | T90: 4689 | U90: 5746 | V90: 5743 | W90: 5145 | X90: =SUM(Q90:T90)/SUM(P90:S90)-1 -> 0.023843129 | Y90: =SUM(R90:U90)/SUM(Q90:T90)-1 -> 0.021613904 | Z90: =SUM(S90:V90)/SUM(R90:U90)-1 -> 0.014554217 | AA90: =SUM(T90:W90)/SUM(S90:V90)-1 -> 0.012872886
B91: SHW | C91: United States | D91: Specialty Chemicals | E91: Dec '25 Dec 31, 2025 | F91: 1.284585 | G91: 4762 | H91: 4999 | I91: 5872 | J91: 6047 | K91: 5231 | L91: 5442 | M91: 6241 | N91: 6117 | O91: 5252 | P91: 5367 | Q91: 6272 | R91: 6163 | S91: 5297 | T91: 5306 | U91: 6315 | V91: 6358 | W91: 5596 | X91: =SUM(Q91:T91)/SUM(P91:S91)-1 -> -0.002640807 | Y91: =SUM(R91:U91)/SUM(Q91:T91)-1 -> 0.0018664815 | Z91: =SUM(S91:V91)/SUM(R91:U91)-1 -> 0.0084485074 | AA91: =SUM(T91:W91)/SUM(S91:V91)-1 -> 0.01284585
B92: FMBH | C92: United States | D92: Banks - Regional | E92: Dec '25 Dec 31, 2025 | F92: 1.2533572 | G92: 57.65 | H92: 61.66 | I92: 64.48 | J92: 64.91 | K92: 63.07 | L92: 66.49 | M92: 61.4 | N92: 67.59 | O92: 78.68 | P92: 80.31 | Q92: 78.1 | R92: 79.3 | S92: 81.67 | T92: 82.62 | U92: 84.89 | V92: 85.92 | W92: 85.87 | X92: =SUM(Q92:T92)/SUM(P92:S92)-1 -> 0.0072327635 | Y92: =SUM(R92:U92)/SUM(Q92:T92)-1 -> 0.021107277 | Z92: =SUM(S92:V92)/SUM(R92:U92)-1 -> 0.020153434 | AA92: =SUM(T92:W92)/SUM(S92:V92)-1 -> 0.012533572
B93: JBSS | C93: United States | D93: Packaged Foods | E93: Dec '25 Dec 25, 2025 | F93: 1.2135536 | G93: 253.21 | H93: 218.58 | I93: 257.75 | J93: 252.6 | K93: 274.33 | L93: 238.54 | M93: 234.22 | N93: 234.11 | O93: 291.22 | P93: 271.88 | Q93: 269.57 | R93: 276.2 | S93: 301.07 | T93: 260.91 | U93: 269.08 | V93: 298.68 | W93: 314.78 | X93: =SUM(Q93:T93)/SUM(P93:S93)-1 -> -0.0098058495 | Y93: =SUM(R93:U93)/SUM(Q93:T93)-1 -> -0.00044233807 | Z93: =SUM(S93:V93)/SUM(R93:U93)-1 -> 0.020302368 | AA93: =SUM(T93:W93)/SUM(S93:V93)-1 -> 0.012135536
B94: HTH | C94: United States | D94: Financial Conglomerates | E94: Dec '25 Dec 31, 2025 | F94: 1.2013562 | G94: 407.71 | H94: 316.3 | I94: 345.99 | J94: 331.24 | K94: 289.59 | L94: 281.87 | M94: 294.08 | N94: 312.54 | O94: 288.94 | P94: 288.11 | Q94: 286.02 | R94: 306.76 | S94: 306.93 | T94: 309.12 | U94: 310.65 | V94: 332.71 | W94: 322.06 | X94: =SUM(Q94:T94)/SUM(P94:S94)-1 -> 0.017687865 | Y94: =SUM(R94:U94)/SUM(Q94:T94)-1 -> 0.020375073 | Z94: =SUM(S94:V94)/SUM(R94:U94)-1 -> 0.02103838 | AA94: =SUM(T94:W94)/SUM(S94:V94)-1 -> 0.012013562
B95: SNDR | C95: United States | D95: Trucking | E95: Dec '25 Dec 31, 2025 | F95: 1.0865693 | G95: 1575 | H95: 1621 | I95: 1747 | J95: 1675 | K95: 1562 | L95: 1429 | M95: 1347 | N95: 1352 | O95: 1372 | P95: 1319 | Q95: 1317 | R95: 1316 | S95: 1339 | T95: 1402 | U95: 1421 | V95: 1452 | W95: 1400 | X95: =SUM(Q95:T95)/SUM(P95:S95)-1 -> 0.015687016 | Y95: =SUM(R95:U95)/SUM(Q95:T95)-1 -> 0.019352438 | Z95: =SUM(S95:V95)/SUM(R95:U95)-1 -> 0.024826579 | AA95: =SUM(T95:W95)/SUM(S95:V95)-1 -> 0.010865693
B96: VLO | C96: United States | D96: Oil & Gas Refining & Marketing | E96: Dec '25 Dec 31, 2025 | F96: 0.97895378 | G96: 34410 | H96: 37119 | I96: 50387 | J96: 43241 | K96: 40442 | L96: 35017 | M96: 33060 | N96: 36936 | O96: 33988 | P96: 30372 | Q96: 33034 | R96: 31337 | S96: 29231 | T96: 28754 | U96: 28227 | V96: 30341 | W96: 30372 | X96: =SUM(Q96:T96)/SUM(P96:S96)-1 -> -0.013051124 | Y96: =SUM(R96:U96)/SUM(Q96:T96)-1 -> -0.039286999 | Z96: =SUM(S96:V96)/SUM(R96:U96)-1 -> -0.0084730623 | AA96: =SUM(T96:W96)/SUM(S96:V96)-1 -> 0.0097895378
B97: OSK | C97: United States | D97: Farm & Heavy Construction Machinery | E97: Dec '25 Dec 31, 2025 | F97: 0.88075881 | G97: 1792 | H97: 1946 | I97: 2066 | J97: 2067 | K97: 2204 | L97: 2268 | M97: 2413 | N97: 2510 | O97: 2467 | P97: 2544 | Q97: 2847 | R97: 2741 | S97: 2598 | T97: 2313 | U97: 2732 | V97: 2689 | W97: 2689 | X97: =SUM(Q97:T97)/SUM(P97:S97)-1 -> -0.021528425 | Y97: =SUM(R97:U97)/SUM(Q97:T97)-1 -> -0.010953424 | Z97: =SUM(S97:V97)/SUM(R97:U97)-1 -> -0.0050077042 | AA97: =SUM(T97:W97)/SUM(S97:V97)-1 -> 0.0088075881
B98: SAP | C98: United States | D98: Software - Application | E98: Dec '25 Dec 31, 2025 | F98: 0.838494 | G98: 7981 | H98: 6773 | I98: 7205 | J98: 7478 | K98: 8064 | L98: 7442 | M98: 7552 | N98: 7744 | O98: 8468 | P98: 8041 | Q98: 8288 | R98: 8470 | S98: 9378 | T98: 9013 | U98: 9027 | V98: 9076 | W98: 9684 | X98: =SUM(Q98:T98)/SUM(P98:S98)-1 -> 0.028440179 | Y98: =SUM(R98:U98)/SUM(Q98:T98)-1 -> 0.02102478 | Z98: =SUM(S98:V98)/SUM(R98:U98)-1 -> 0.016885867 | AA98: =SUM(T98:W98)/SUM(S98:V98)-1 -> 0.00838494
B99: TSCO | C99: United States | D99: Specialty Retail | E99: Dec '25 Dec 27, 2025 | F99: 0.80519481 | G99: 3319 | H99: 3024 | I99: 3903 | J99: 3271 | K99: 4006 | L99: 3299 | M99: 4185 | N99: 3412 | O99: 3660 | P99: 3395 | Q99: 4247 | R99: 3468 | S99: 3774 | T99: 3467 | U99: 4440 | V99: 3719 | W99: 3898 | X99: =SUM(Q99:T99)/SUM(P99:S99)-1 -> 0.0048374093 | Y99: =SUM(R99:U99)/SUM(Q99:T99)-1 -> 0.01290452 | Z99: =SUM(S99:V99)/SUM(R99:U99)-1 -> 0.01656875 | AA99: =SUM(T99:W99)/SUM(S99:V99)-1 -> 0.0080519481
B100: ABCB | C100: United States | D100: Banks - Regional | E100: Dec '25 Dec 31, 2025 | F100: 0.65557817 | G100: 240.8 | H100: 243.57 | I100: 249.44 | J100: 259.32 | K100: 239.64 | L100: 217.97 | M100: 231.37 | N100: 246.47 | O100: 241.3 | P100: 246.16 | Q100: 281.86 | R100: 277.66 | S100: 276.77 | T100: 263.97 | U100: 297.95 | V100: 291.61 | W100: 284.18 | X100: =SUM(Q100:T100)/SUM(P100:S100)-1 -> 0.016453416 | Y100: =SUM(R100:U100)/SUM(Q100:T100)-1 -> 0.014623816 | Z100: =SUM(S100:V100)/SUM(R100:U100)-1 -> 0.012496081 | AA100: =SUM(T100:W100)/SUM(S100:V100)-1 -> 0.0065557817
... B113: NSC | C113: United States | D113: Railroads | E113: Dec '25 Dec 31, 2025 | F113: -0.40883074 | G113: 2852 | H113: 2915 | I113: 3250 | J113: 3343 | K113: 3237 | L113: 3132 | M113: 2980 | N113: 2971 | O113: 3073 | P113: 3004 | Q113: 3044 | R113: 3051 | S113: 3024 | T113: 2993 | U113: 3110 | V113: 3103 | W113: 2974 | X113: =SUM(Q113:T113)/SUM(P113:S113)-1 -> -0.00090736616 | Y113: =SUM(R113:U113)/SUM(Q113:T113)-1 -> 0.0054491413 | Z113: =SUM(S113:V113)/SUM(R113:U113)-1 -> 0.0042699951 | AA113: =SUM(T113:W113)/SUM(S113:V113)-1 -> -0.0040883074
...

Sheet Operating Income
B1: 1 | C1: 2 | D1: 3 | E1: 4 | F1: 5 | G1: 6 | H1: 7 | I1: 8 | J1: 9 | K1: 10 | L1: 11 | M1: 12 | N1: 13 | O1: 14 | P1: 15 | Q1: 16 | R1: 17 | S1: 18 | T1: 19 | U1: 20 | V1: 21 | W1: 22
B2: Ticker | C2: Country | D2: Industry | E2: Latest_Date | F2: Growth_Rate | G2: 4Q21 | H2: 1Q22 | I2: 2Q22 | J2: 3Q22 | K2: 4Q22 | L2: 1Q23 | M2: 2Q23 | N2: 3Q23 | O2: 4Q23 | P2: 1Q24 | Q2: 2Q24 | R2: 3Q24 | S2: 4Q24 | T2: 1Q25 | U2: 2Q25 | V2: 3Q25 | W2: 4Q25 | X2: 1Q25 | Y2: 2Q25 | Z2: 3Q25 | AA2: 4Q25
B3: SNDK | C3: United States | D3: Computer Hardware | E3: Jan '26 Jan 2, 2026 | F3: 230.56995 | N3: -546 | O3: -198 | P3: 79 | Q3: 185 | R3: 313 | S3: 185 | T3: -42 | U3: 51 | V3: 192 | W3: 1075 | X3: =SUM(Q3:T3)/SUM(P3:S3)-1 -> -0.15879265 | Y3: =SUM(R3:U3)/SUM(Q3:T3)-1 -> -0.20904836 | Z3: =SUM(S3:V3)/SUM(R3:U3)-1 -> -0.23865878 | AA3: =SUM(T3:W3)/SUM(S3:V3)-1 -> 2.3056995
B4: TAL | C4: United States | D4: Education & Training Services | E4: Nov '25 Nov 30, 2025 | F4: 143.57143 | G4: -62.18 | H4: 33.26 | I4: -28.32 | J4: 14.89 | K4: -32.88 | L4: -44.42 | M4: -57.77 | N4: 31.79 | O4: -32.19 | P4: -11.06 | Q4: -17.33 | R4: 47.62 | S4: -17.43 | T4: -16.02 | U4: 14.35 | V4: 96.1 | W4: 93.12 | X4: =SUM(Q4:T4)/SUM(P4:S4)-1 -> -2.7555556 | Y4: =SUM(R4:U4)/SUM(Q4:T4)-1 -> -10.025316 | Z4: =SUM(S4:V4)/SUM(R4:U4)-1 -> 1.6998597 | AA4: =SUM(T4:W4)/SUM(S4:V4)-1 -> 1.4357143
B5: CNX | C5: United States | D5: Oil & Gas E&P | E5: Dec '25 Dec 31, 2025 | F5: 106.10558 | G5: 939.41 | H5: -1236 | I5: 90.52 | J5: -207.27 | K5: 1293 | L5: 955.26 | M5: 567.73 | N5: 50.32 | O5: 664.58 | P5: 65.45 | Q5: 20.67 | R5: 104.8 | S5: -189.17 | T5: -236.88 | U5: 616.3 | V5: 241.65 | W5: 269.1 | X5: =SUM(Q5:T5)/SUM(P5:S5)-1 -> -172.76 | Y5: =SUM(R5:U5)/SUM(Q5:T5)-1 -> -1.9816022 | Z5: =SUM(S5:V5)/SUM(R5:U5)-1 -> 0.46381969 | AA5: =SUM(T5:W5)/SUM(S5:V5)-1 -> 1.0610558
B6: IVR | C6: United States | D6: REIT - Mortgage | E6: Dec '25 Dec 31, 2025 | F6: 89.218984 | G6: -64.65 | H6: -228.42 | I6: -109.54 | J6: -101.43 | K6: 36.46 | L6: 21.46 | M6: 4.25 | N6: -68.56 | O6: 27.31 | P6: 29.16 | Q6: -13.2 | R6: 40.64 | S6: 3.74 | T6: 19.64 | U6: -23.33 | V6: 53.47 | W6: 51.49 | X6: =SUM(Q6:T6)/SUM(P6:S6)-1 -> -0.15777262 | Y6: =SUM(R6:U6)/SUM(Q6:T6)-1 -> -0.19933097 | Z6: =SUM(S6:V6)/SUM(R6:U6)-1 -> 0.31531089 | AA6: =SUM(T6:W6)/SUM(S6:V6)-1 -> 0.89218984
B7: WDC | C7: United States | D7: Computer Hardware | E7: Jan '26 Jan 2, 2026 | F7: 47.159647 | G7: 729 | H7: 524 | I7: 611 | J7: 182 | K7: -245 | L7: -432 | M7: -574 | N7: -539 | O7: 0 | P7: 100 | Q7: 0 | R7: 340 | S7: 0 | T7: 559 | U7: 688 | V7: 795 | W7: 963 | X7: =SUM(Q7:T7)/SUM(P7:S7)-1 -> 1.0431818 | Y7: =SUM(R7:U7)/SUM(Q7:T7)-1 -> 0.76529477 | Z7: =SUM(S7:V7)/SUM(R7:U7)-1 -> 0.28670447 | AA7: =SUM(T7:W7)/SUM(S7:V7)-1 -> 0.47159647
B8: VLO | C8: United States | D8: Oil & Gas Refining & Marketing | E8: Dec '25 Dec 31, 2025 | F8: 35.295841 | G8: 1601 | H8: 1400 | I8: 6237 | J8: 3796 | K8: 4383 | L8: 4067 | M8: 2785 | N8: 3529 | O8: 1575 | P8: 1703 | Q8: 1245 | R8: 527 | S8: 370 | T8: 250 | U8: 1117 | V8: 1677 | W8: 1575 | X8: =SUM(Q8:T8)/SUM(P8:S8)-1 -> -0.37789337 | Y8: =SUM(R8:U8)/SUM(Q8:T8)-1 -> -0.053511706 | Z8: =SUM(S8:V8)/SUM(R8:U8)-1 -> 0.50795053 | AA8: =SUM(T8:W8)/SUM(S8:V8)-1 -> 0.35295841
B9: VLY | C9: United States | D9: Banks - Regional | E9: Dec '25 Dec 31, 2025 | F9: 21.700506 | G9: 157.31 | H9: 156.04 | I9: 132.97 | J9: 246.52 | K9: 245.14 | L9: 203.72 | M9: 190.82 | N9: 194.83 | O9: 88.97 | P9: 129.45 | Q9: 93.33 | R9: 126.67 | S9: 89.06 | T9: 139.12 | U9: 173.09 | V9: 209.96 | W9: 221.7 | X9: =SUM(Q9:T9)/SUM(P9:S9)-1 -> 0.022051949 | Y9: =SUM(R9:U9)/SUM(Q9:T9)-1 -> 0.17796421 | Z9: =SUM(S9:V9)/SUM(R9:U9)-1 -> 0.15776414 | AA9: =SUM(T9:W9)/SUM(S9:V9)-1 -> 0.21700506
B10: KEX | C10: United States | D10: Marine Shipping | E10: Dec '25 Dec 31, 2025 | F10: 17.982016 | G10: 33.21 | H10: 28.25 | I10: 47.29 | J10: 62.03 | K10: 59.54 | L10: 60.42 | M10: 88.03 | N10: 93.2 | O10: 93.24 | P10: 103.8 | Q10: 122.68 | R10: 127.91 | S10: 52.65 | T10: 110.22 | U10: 134.46 | V10: 130.82 | W10: 129.64 | X10: =SUM(Q10:T10)/SUM(P10:S10)-1 -> 0.015772406 | Y10: =SUM(R10:U10)/SUM(Q10:T10)-1 -> 0.028491269 | Z10: =SUM(S10:V10)/SUM(R10:U10)-1 -> 0.0068431944 | AA10: =SUM(T10:W10)/SUM(S10:V10)-1 -> 0.17982016
B11: 6135 | C11: Japan | D11: N/A | E11: Sep '25 Sep 30, 2025 | F11: 8.9775029 | G11: 1919 | H11: 2356 | I11: 6106 | J11: 1643 | K11: 3761 | L11: 6207 | M11: 5883 | N11: 4267 | O11: 3510 | P11: 4380 | Q11: 4216 | R11: 2960 | S11: 4616 | T11: 5656 | U11: 5285 | V11: 3201 | W11: 6300
B12: LMT | C12: United States | D12: Aerospace & Defense | E12: Dec '25 Dec 31, 2025 | F12: 17.90892 | G12: 2498 | H12: 2099 | I12: 654 | J12: 2247 | K12: 2499 | L12: 2161 | M12: 2241 | N12: 2151 | O12: 2490 | P12: 2030 | Q12: 2240 | R12: 2151 | S12: 703 | T12: 2279 | U12: 705 | V12: 2176 | W12: 1753 | X12: =SUM(Q12:T12)/SUM(P12:S12)-1 -> 0.034952274 | Y12: =SUM(R12:U12)/SUM(Q12:T12)-1 -> -0.20819205 | Z12: =SUM(S12:V12)/SUM(R12:U12)-1 -> 0.0042822885 | AA12: =SUM(T12:W12)/SUM(S12:V12)-1 -> 0.1790892
B13: 6995 | C13: Japan | D13: N/A | E13: Sep '25 Sep 30, 2025 | F13: 2.3013305 | G13: 581 | H13: 4345 | I13: -2039 | J13: -772 | K13: 4692 | L13: 3422 | M13: 9315 | N13: 8783 | O13: 11464 | P13: 12967 | Q13: -4392 | R13: 7124 | S13: 11418 | T13: 9078 | U13: 7821 | V13: 7836 | W13: 12250
B14: APPF | C14: United States | D14: Software - Application | E14: Dec '25 Dec 31, 2025 | F14: 14.977444 | G14: -7.34 | H14: -14.67 | I14: -10.53 | J14: -7.82 | K14: -17.72 | L14: -26.53 | M14: -2.58 | N14: -0.07 | O14: 43.14 | P14: 34.09 | Q14: 36.03 | R14: 42.57 | S14: 23.66 | T14: 33.78 | U14: 40.51 | V14: 35.05 | W14: 43.58 | X14: =SUM(Q14:T14)/SUM(P14:S14)-1 -> -0.0022735607 | Y14: =SUM(R14:U14)/SUM(Q14:T14)-1 -> 0.032931491 | Z14: =SUM(S14:V14)/SUM(R14:U14)-1 -> -0.053515514 | AA14: =SUM(T14:W14)/SUM(S14:V14)-1 -> 0.14977444
B15: 2782 | C15: Japan | D15: N/A | E15: Sep '25 Sep 30, 2025 | F15: -25.546717 | G15: 4299 | H15: 4374 | I15: 3679 | J15: 4822 | K15: 2571 | L15: 3146 | M15: 3035 | N15: 11258 | O15: 11258 | P15: 3863 | Q15: 3968 | R15: 3680 | S15: 13166 | T15: 13166 | U15: 4595 | V15: 4146 | W15: 4206
B16: BFH | C16: United States | D16: Credit Services | E16: Dec '25 Dec 31, 2025 | F16: 13.703704 | G16: 0 | H16: 302 | I16: 16 | J16: 189 | K16: -208 | L16: 638 | M16: 86 | N16: 225 | O16: 18 | P16: 188 | Q16: 180 | R16: 40 | S16: -27 | T16: 197 | U16: 174 | V16: 196 | W16: 47 | X16: =SUM(Q16:T16)/SUM(P16:S16)-1 -> 0.023622047 | Y16: =SUM(R16:U16)/SUM(Q16:T16)-1 -> -0.015384615 | Z16: =SUM(S16:V16)/SUM(R16:U16)-1 -> 0.40625 | AA16: =SUM(T16:W16)/SUM(S16:V16)-1 -> 0.13703704
B17: VIRT | C17: United States | D17: Capital Markets | E17: Dec '25 Dec 31, 2025 | F17: 13.336436 | G17: 250.76 | H17: 242.52 | I17: 172.22 | J17: 101.62 | K17: 51.49 | L17: 137.21 | M17: 34.49 | N17: 139.02 | O17: 21.87 | P17: 139.62 | Q17: 155.48 | R17: 150.47 | S17: 220.86 | T17: 226.93 | U17: 284.22 | V17: 192 | W17: 344.09 | X17: =SUM(Q17:T17)/SUM(P17:S17)-1 -> 0.13101151 | Y17: =SUM(R17:U17)/SUM(Q17:T17)-1 -> 0.1708016 | Z17: =SUM(S17:V17)/SUM(R17:U17)-1 -> 0.047060557 | AA17: =SUM(T17:W17)/SUM(S17:V17)-1 -> 0.13336436
B18: BX | C18: United States | D18: Asset Management | E18: Dec '25 Dec 31, 2025 | F18: 13.013368 | G18: 3213 | H18: 2857 | I18: -270.39 | J18: -102.63 | K18: 876.81 | L18: 206.65 | M18: 1371 | N18: 1103 | O18: 454.33 | P18: 1853 | Q18: 1144 | R18: 1863 | S18: 1427 | T18: 1469 | U18: 2004 | V18: 1309 | W18: 2235 | X18: =SUM(Q18:T18)/SUM(P18:S18)-1 -> -0.061078416 | Y18: =SUM(R18:U18)/SUM(Q18:T18)-1 -> 0.14568863 | Z18: =SUM(S18:V18)/SUM(R18:U18)-1 -> -0.081916309 | AA18: =SUM(T18:W18)/SUM(S18:V18)-1 -> 0.13013368
B19: APTUS | C19: India | D19: N/A | E19: Sep '25 Sep 30, 2025 | F19: 5.5475296 | G19: 1094 | H19: 1312 | I19: 1437 | J19: 1523 | K19: 1566 | L19: 1684 | M19: 1706 | N19: 1834 | O19: 1896 | P19: 2051 | Q19: 2147 | R19: 2216 | S19: 2367 | T19: 2455 | U19: 2706 | V19: 2855 | W19: 2943
B20: EPR | C20: United States | D20: REIT - Specialty | E20: Sep '25 Sep 30, 2025 | F20: 2.0532877 | G20: 77.85 | H20: 59.94 | I20: 81.77 | J20: 86.31 | K20: 83.65 | L20: 98.61 | M20: 90.55 | N20: 89.99 | O20: 106.11 | P20: 83.74 | Q20: 78.6 | R20: 89.15 | S20: 94.43 | T20: 89.88 | U20: 89.49 | V20: 94.39 | W20: 101.99
B21: GMDCLTD | C21: India | D21: N/A | E21: Sep '25 Sep 30, 2025 | F21: -11.517512 | G21: 65.12 | H21: 1801 | I21: 4289 | J21: 4192 | K21: 1523 | L21: 3151 | M21: 3719 | N21: 2273 | O21: 345.33 | P21: 1013 | Q21: 2227 | R21: 1901 | S21: 1204 | T21: 658.6 | U21: 2981 | V21: 1472 | W21: 476.6
B22: SIGI | C22: United States | D22: Insurance - Property & Casualty | E22: Dec '25 Dec 31, 2025 | F22: 8.5367718 | G22: 131.09 | H22: 77.06 | I22: 57.16 | J22: 59.82 | K22: 115.01 | L22: 121.93 | M22: 81.42 | N22: 119.7 | O22: 164.77 | P22: 109.75 | Q22: -72.9 | R22: 123.74 | S22: 159.05 | T22: 148.46 | U22: 122.16 | V22: 158.96 | W22: 209.3 | X22: =SUM(Q22:T22)/SUM(P22:S22)-1 -> 0.12110499 | Y22: =SUM(R22:U22)/SUM(Q22:T22)-1 -> 0.54432817 | Z22: =SUM(S22:V22)/SUM(R22:U22)-1 -> 0.063641785 | AA22: =SUM(T22:W22)/SUM(S22:V22)-1 -> 0.085367718
B23: SXI | C23: United States | D23: Specialty Industrial Machinery | E23: Dec '25 Dec 31, 2025 | F23: 8.2875038 | G23: 25.24 | H23: 26.08 | I23: 26.06 | J23: 27.16 | K23: 28.49 | L23: 28.67 | M23: 28.05 | N23: 29.05 | O23: 28.39 | P23: 26.53 | Q23: 28.33 | R23: 27.03 | S23: 25.78 | T23: 30.38 | U23: 38.7 | V23: 36.06 | W23: 36.63 | X23: =SUM(Q23:T23)/SUM(P23:S23)-1 -> 0.035757407 | Y23: =SUM(R23:U23)/SUM(Q23:T23)-1 -> 0.092987805 | Z23: =SUM(S23:V23)/SUM(R23:U23)-1 -> 0.07408319 | AA23: =SUM(T23:W23)/SUM(S23:V23)-1 -> 0.082875038
B24: HIG | C24: United States | D24: Insurance - Diversified | E24: Dec '25 Dec 31, 2025 | F24: 7.1058315 | G24: 954 | H24: 590 | I24: 593 | J24: 483 | K24: 802 | L24: 709 | M24: 729 | N24: 867 | O24: 1014 | P24: 966 | Q24: 967 | R24: 1008 | S24: 1134 | T24: 832 | U24: 1296 | V24: 1368 | W24: 1463 | X24: =SUM(Q24:T24)/SUM(P24:S24)-1 -> -0.032883436 | Y24: =SUM(R24:U24)/SUM(Q24:T24)-1 -> 0.08348135 | Z24: =SUM(S24:V24)/SUM(R24:U24)-1 -> 0.084309133 | AA24: =SUM(T24:W24)/SUM(S24:V24)-1 -> 0.071058315
B25: SRCE | C25: United States | D25: Banks - Regional | E25: Dec '25 Dec 31, 2025 | F25: 7.0728768 | G25: 36.27 | H25: 35.19 | I25: 38.13 | J25: 42.44 | K25: 41.02 | L25: 40.42 | M25: 42.07 | N25: 42.67 | O25: 36.52 | P25: 37.89 | Q25: 47.72 | R25: 45.38 | S25: 40.06 | T25: 47.7 | U25: 48.13 | V25: 54.98 | W25: 53.56 | X25: =SUM(Q25:T25)/SUM(P25:S25)-1 -> 0.057351652 | Y25: =SUM(R25:U25)/SUM(Q25:T25)-1 -> 0.0022669468 | Z25: =SUM(S25:V25)/SUM(R25:U25)-1 -> 0.052959673 | AA25: =SUM(T25:W25)/SUM(S25:V25)-1 -> 0.070728768
B26: JBSS | C26: United States | D26: Packaged Foods | E26: Dec '25 Dec 25, 2025 | F26: 6.9604297 | G26: 17.32 | H26: 16.4 | I26: 23.52 | J26: 21.66 | K26: 23.81 | L26: 21.1 | M26: 20.94 | N26: 23.87 | O26: 24.77 | P26: 17.68 | Q26: 14.8 | R26: 16.24 | S26: 18.66 | T26: 27.2 | U26: 19.32 | V26: 26.05 | W26: 25.01 | X26: =SUM(Q26:T26)/SUM(P26:S26)-1 -> 0.14128822 | Y26: =SUM(R26:U26)/SUM(Q26:T26)-1 -> 0.058777633 | Z26: =SUM(S26:V26)/SUM(R26:U26)-1 -> 0.12048637 | AA26: =SUM(T26:W26)/SUM(S26:V26)-1 -> 0.069604297
B27: RCL | C27: United States | D27: Travel Services | E27: Dec '25 Dec 31, 2025 | F27: 6.7462039 | G27: -987.85 | H27: -859.21 | I27: -217.74 | J27: 303 | K27: 18.98 | L27: 272 | M27: 776 | N27: 1265 | O27: 591 | P27: 750 | Q27: 1108 | R27: 1636 | S27: 625 | T27: 949 | U27: 1333 | V27: 1703 | W27: 936 | X27: =SUM(Q27:T27)/SUM(P27:S27)-1 -> 0.048312697 | Y27: =SUM(R27:U27)/SUM(Q27:T27)-1 -> 0.052107457 | Z27: =SUM(S27:V27)/SUM(R27:U27)-1 -> 0.014747964 | AA27: =SUM(T27:W27)/SUM(S27:V27)-1 -> 0.067462039
B28: BC | C28: United States | D28: Recreational Vehicles | E28: Dec '25 Dec 31, 2025 | F28: 6.2075984 | G28: 137 | H28: 239.3 | I28: 278.7 | J28: 261.9 | K28: 195.2 | L28: 245.6 | M28: 208.3 | N28: 212.4 | O28: 125.4 | P28: 127.7 | Q28: 166.2 | R28: 110.6 | S28: 33.8 | T28: 58.1 | U28: 111.3 | V28: 91.6 | W28: 52.1 | X28: =SUM(Q28:T28)/SUM(P28:S28)-1 -> -0.15879535 | Y28: =SUM(R28:U28)/SUM(Q28:T28)-1 -> -0.14890155 | Z28: =SUM(S28:V28)/SUM(R28:U28)-1 -> -0.06054812 | AA28: =SUM(T28:W28)/SUM(S28:V28)-1 -> 0.062075984
B29: AAPL | C29: United States | D29: Consumer Electronics | E29: Dec '25 Dec 27, 2025 | F29: 6.0278091 | G29: 41488 | H29: 29979 | I29: 23076 | J29: 24894 | K29: 36016 | L29: 28318 | M29: 22998 | N29: 26969 | O29: 40373 | P29: 27900 | Q29: 25352 | R29: 29591 | S29: 42832 | T29: 29589 | U29: 28202 | V29: 32427 | W29: 50852 | X29: =SUM(Q29:T29)/SUM(P29:S29)-1 -> 0.013439427 | Y29: =SUM(R29:U29)/SUM(Q29:T29)-1 -> 0.02237681 | Z29: =SUM(S29:V29)/SUM(R29:U29)-1 -> 0.021779532 | AA29: =SUM(T29:W29)/SUM(S29:V29)-1 -> 0.060278091
B30: MA | C30: United States | D30: Credit Services | E30: Dec '25 Dec 31, 2025 | F30: 4.6722417 | G30: 2837 | H30: 2984 | I30: 3184 | J30: 3320 | K30: 3136 | L30: 3347 | M30: 3676 | N30: 3844 | O30: 3680 | P30: 3730 | Q30: 4134 | R30: 4370 | S30: 4218 | T30: 4300 | U30: 4873 | V30: 5144 | W30: 5084 | X30: =SUM(Q30:T30)/SUM(P30:S30)-1 -> 0.034646244 | Y30: =SUM(R30:U30)/SUM(Q30:T30)-1 -> 0.043414405 | Z30: =SUM(S30:V30)/SUM(R30:U30)-1 -> 0.043578627 | AA30: =SUM(T30:W30)/SUM(S30:V30)-1 -> 0.046722417
B31: RMD | C31: United States | D31: Medical Instruments & Supplies | E31: Dec '25 Dec 31, 2025 | F31: 4.5596137 | G31: 248.71 | H31: 234.27 | I31: 257.26 | J31: 275.74 | K31: 288.61 | L31: 300.67 | M31: 286.24 | N31: 289 | O31: 339.32 | P31: 374.58 | Q31: 381.22 | R31: 387.31 | S31: 417.24 | T31: 426.27 | U31: 456.57 | V31: 462.35 | W31: 497.6 | X31: =SUM(Q31:T31)/SUM(P31:S31)-1 -> 0.033127183 | Y31: =SUM(R31:U31)/SUM(Q31:T31)-1 -> 0.046742016 | Z31: =SUM(S31:V31)/SUM(R31:U31)-1 -> 0.044471047 | AA31: =SUM(T31:W31)/SUM(S31:V31)-1 -> 0.045596137
B32: NDAQ | C32: United States | D32: Financial Data & Stock Exchanges | E32: Dec '25 Dec 31, 2025 | F32: 4.2839143 | G32: 403 | H32: 428 | I32: 432 | J32: 421 | K32: 414 | L32: 441 | M32: 450 | N32: 461 | O32: 483 | P32: 455 | Q32: 501 | R32: 489 | S32: 560 | T32: 591 | U32: 611 | V32: 619 | W32: 662 | X32: =SUM(Q32:T32)/SUM(P32:S32)-1 -> 0.067830424 | Y32: =SUM(R32:U32)/SUM(Q32:T32)-1 -> 0.051377861 | Z32: =SUM(S32:V32)/SUM(R32:U32)-1 -> 0.05775211 | AA32: =SUM(T32:W32)/SUM(S32:V32)-1 -> 0.042839143
B33: HTH | C33: United States | D33: Financial Conglomerates | E33: Dec '25 Dec 31, 2025 | F33: 4.2293366 | G33: 85.51 | H33: 29.95 | I33: 47.45 | J33: 42.5 | K33: 36.22 | L33: 31.4 | M33: 27.11 | N33: 52.52 | O33: 38.09 | P33: 38.09 | Q33: 29.56 | R33: 42.44 | S33: 44.17 | T33: 57.65 | U33: 49.47 | V33: 60.8 | W33: 53.14 | X33: =SUM(Q33:T33)/SUM(P33:S33)-1 -> 0.12679891 | Y33: =SUM(R33:U33)/SUM(Q33:T33)-1 -> 0.11454378 | Z33: =SUM(S33:V33)/SUM(R33:U33)-1 -> 0.094771073 | AA33: =SUM(T33:W33)/SUM(S33:V33)-1 -> 0.042293366
... B35: FMBH | C35: United States | D35: Banks - Regional | E35: Dec '25 Dec 31, 2025 | F35: 4.1184843 | G35: 22 | H35: 21.27 | I35: 22.96 | J35: 23.36 | K35: 23.7 | L35: 24.91 | M35: 21.35 | N35: 20.49 | O35: 21.65 | P35: 26.94 | Q35: 26.71 | R35: 25.37 | S35: 25.37 | T35: 28.15 | U35: 30.13 | V35: 28.77 | W35: 30 | X35: =SUM(Q35:T35)/SUM(P35:S35)-1 -> 0.011591149 | Y35: =SUM(R35:U35)/SUM(Q35:T35)-1 -> 0.032386364 | Z35: =SUM(S35:V35)/SUM(R35:U35)-1 -> 0.031186938 | AA35: =SUM(T35:W35)/SUM(S35:V35)-1 -> 0.041184843
B36: INOXWIND | C36: India | D36: N/A | E36: Sep '25 Sep 30, 2025 | F36: 7.8421822 | G36: -215.2 | H36: -558.9 | I36: -2940 | J36: -530 | K36: -494.9 | L36: -2105 | M36: 0 | N36: 25.6 | O36: 220.8 | P36: 647.2 | Q36: 629.26 | R36: 944.8 | S36: 1286 | T36: 1605 | U36: 1918 | V36: 1350 | W36: 1769
B37: SAP | C37: United States | D37: Software - Application | E37: Dec '25 Dec 31, 2025 | F37: 4.0963133 | G37: 1558 | H37: 1557 | I37: 1285 | J37: 1651 | K37: 1889 | L37: 1154 | M37: 1453 | N37: 1763 | O37: 2136 | P37: 1534 | Q37: 1940 | R37: 2252 | S37: 2419 | T37: 2455 | U37: 2569 | V37: 2566 | W37: 2829 | X37: =SUM(Q37:T37)/SUM(P37:S37)-1 -> 0.11307551 | Y37: =SUM(R37:U37)/SUM(Q37:T37)-1 -> 0.069380101 | Z37: =SUM(S37:V37)/SUM(R37:U37)-1 -> 0.032387829 | AA37: =SUM(T37:W37)/SUM(S37:V37)-1 -> 0.040963133
B38: HMN | C38: United States | D38: Insurance - Property & Casualty | E38: Sep '25 Sep 30, 2025 | F38: 13.82928 | G38: 22.4 | H38: 53.1 | I38: 28.9 | J38: -1.7 | K38: 28.7 | L38: -15.2 | M38: 14.8 | N38: -8.7 | O38: 21.1 | P38: 55.8 | Q38: 41.7 | R38: 13.3 | S38: 51.4 | T38: 56.8 | U38: 56.4 | V38: 45.1 | W38: 80.4
B39: DECK | C39: United States | D39: Footwear & Accessories | E39: Dec '25 Dec 31, 2025 | F39: 3.8066758 | G39: 296.74 | H39: 81.28 | I39: 57.33 | J39: 126 | K39: 362.66 | L39: 108.74 | M39: 70.74 | N39: 224.62 | O39: 487.9 | P39: 153.44 | Q39: 132.81 | R39: 305.09 | S39: 567.27 | T39: 178.22 | U39: 165.29 | V39: 326.52 | W39: 614.37 | X39: =SUM(Q39:T39)/SUM(P39:S39)-1 -> 0.021387697 | Y39: =SUM(R39:U39)/SUM(Q39:T39)-1 -> 0.027446573 | Z39: =SUM(S39:V39)/SUM(R39:U39)-1 -> 0.01762524 | AA39: =SUM(T39:W39)/SUM(S39:V39)-1 -> 0.038066758
B40: V | C40: United States | D40: Credit Services | E40: Dec '25 Dec 31, 2025 | F40: 3.4131603 | G40: 4924 | H40: 4862 | I40: 4865 | J40: 5090 | K40: 5431 | L40: 5336 | M40: 5481 | N40: 5679 | O40: 5963 | P40: 5841 | Q40: 5833 | R40: 6359 | S40: 6530 | T40: 6435 | U40: 6792 | V40: 7051 | W40: 7445 | X40: =SUM(Q40:T40)/SUM(P40:S40)-1 -> 0.024182714 | Y40: =SUM(R40:U40)/SUM(Q40:T40)-1 -> 0.038120603 | Z40: =SUM(S40:V40)/SUM(R40:U40)-1 -> 0.026497166 | AA40: =SUM(T40:W40)/SUM(S40:V40)-1 -> 0.034131603
B41: LPLA | C41: United States | D41: Capital Markets | E41: Dec '25 Dec 31, 2025 | F41: 3.285609 | G41: 150.86 | H41: 186.68 | I41: 221.22 | J41: 314.23 | K41: 425.72 | L41: 447.6 | M41: 392.92 | N41: 323.67 | O41: 341.95 | P41: 383.79 | Q41: 366.9 | R41: 363.65 | S41: 340.51 | T41: 453.95 | U41: 440.41 | V41: 501.49 | W41: 397.56 | X41: =SUM(Q41:T41)/SUM(P41:S41)-1 -> 0.048224903 | Y41: =SUM(R41:U41)/SUM(Q41:T41)-1 -> 0.048202963 | Z41: =SUM(S41:V41)/SUM(R41:U41)-1 -> 0.086229763 | AA41: =SUM(T41:W41)/SUM(S41:V41)-1 -> 0.03285609
B42: TMO | C42: United States | D42: Diagnostics & Research | E42: Dec '25 Dec 31, 2025 | F42: 3.2097868 | G42: 2758 | H42: 2830 | I42: 1982 | J42: 1727 | K42: 2036 | L42: 1724 | M42: 1785 | N42: 1976 | O42: 1991 | P42: 1725 | Q42: 1833 | R42: 1912 | S42: 2335 | T42: 1840 | U42: 1937 | V42: 2144 | W42: 2600 | X42: =SUM(Q42:T42)/SUM(P42:S42)-1 -> 0.014734145 | Y42: =SUM(R42:U42)/SUM(Q42:T42)-1 -> 0.013131313 | Z42: =SUM(S42:V42)/SUM(R42:U42)-1 -> 0.02891326 | AA42: =SUM(T42:W42)/SUM(S42:V42)-1 -> 0.032097868
B43: SHW | C43: United States | D43: Specialty Chemicals | E43: Dec '25 Dec 31, 2025 | F43: 3.192758 | G43: 371.7 | H43: 565.9 | I43: 846.3 | J43: 972.3 | K43: 612.1 | L43: 717.9 | M43: 1114 | N43: 1116 | O43: 680.3 | P43: 730.7 | Q43: 1236 | R43: 1136 | S43: 671.9 | T43: 757.7 | U43: 1103 | V43: 1157 | W43: 789.7 | X43: =SUM(Q43:T43)/SUM(P43:S43)-1 -> 0.0071530758 | Y43: =SUM(R43:U43)/SUM(Q43:T43)-1 -> -0.034985269 | Z43: =SUM(S43:V43)/SUM(R43:U43)-1 -> 0.0057242545 | AA43: =SUM(T43:W43)/SUM(S43:V43)-1 -> 0.03192758
B44: SYK | C44: United States | D44: Medical Devices | E44: Dec '25 Dec 31, 2025 | F44: 2.990277 | G44: 1100 | H44: 687 | I44: 873 | J44: 781 | K44: 1167 | L44: 784 | M44: 1040 | N44: 959 | O44: 1331 | P44: 973 | Q44: 1149 | R44: 1186 | S44: 1648 | T44: 1132 | U44: 1322 | V44: 1349 | W44: 1811 | X44: =SUM(Q44:T44)/SUM(P44:S44)-1 -> 0.032082324 | Y44: =SUM(R44:U44)/SUM(Q44:T44)-1 -> 0.033822092 | Z44: =SUM(S44:V44)/SUM(R44:U44)-1 -> 0.030824508 | AA44: =SUM(T44:W44)/SUM(S44:V44)-1 -> 0.02990277
B45: ABCB | C45: United States | D45: Banks - Regional | E45: Dec '25 Dec 31, 2025 | F45: 2.9053963 | G45: 107.48 | H45: 109.4 | I45: 118.09 | J45: 121.08 | K45: 104.53 | L45: 78.55 | M45: 82.97 | N45: 105.03 | O45: 90.39 | P45: 97.45 | Q45: 126.5 | R45: 125.89 | S45: 126.02 | T45: 112.94 | U45: 142.69 | V45: 137.04 | W45: 141.09 | X45: =SUM(Q45:T45)/SUM(P45:S45)-1 -> 0.032551591 | Y45: =SUM(R45:U45)/SUM(Q45:T45)-1 -> 0.032950036 | Z45: =SUM(S45:V45)/SUM(R45:U45)-1 -> 0.021968712 | AA45: =SUM(T45:W45)/SUM(S45:V45)-1 -> 0.029053963
B46: IEX | C46: United States | D46: Specialty Industrial Machinery | E46: Sep '25 Sep 30, 2025 | F46: 1.3942239 | G46: 173.1 | H46: 168.7 | I46: 188.3 | J46: 190.4 | K46: 222 | L46: 188.3 | M46: 193.7 | N46: 206.3 | O46: 186.7 | P46: 164.7 | Q46: 165.8 | R46: 186.3 | S46: 178.4 | T46: 174.5 | U46: 160 | V46: 190 | W46: 188.2
B47: PH | C47: United States | D47: Specialty Industrial Machinery | E47: Dec '25 Dec 31, 2025 | F47: 2.7143782 | G47: 672.49 | H47: 738.85 | I47: 818.35 | J47: 630.86 | K47: 675.08 | L47: 913.55 | M47: 1271 | N47: 913.93 | O47: 952.17 | P47: 1016 | Q47: 1130 | R47: 984 | S47: 977.38 | T47: 1075 | U47: 1172 | V47: 1072 | W47: 1094 | X47: =SUM(Q47:T47)/SUM(P47:S47)-1 -> 0.014364388 | Y47: =SUM(R47:U47)/SUM(Q47:T47)-1 -> 0.010080694 | Z47: =SUM(S47:V47)/SUM(R47:U47)-1 -> 0.020910659 | AA47: =SUM(T47:W47)/SUM(S47:V47)-1 -> 0.027143782
B48: KLAC | C48: United States | D48: Semiconductor Equipment & Materials | E48: Dec '25 Dec 31, 2025 | F48: 2.2940164 | G48: 965.96 | H48: 894.91 | I48: 971.95 | J48: 1111 | K48: 1199 | L48: 860.59 | M48: 821.31 | N48: 899.21 | O48: 952.32 | P48: 806.84 | Q48: 977.32 | R48: 1120 | S48: 1242 | T48: 1300 | U48: 1352 | V48: 1337 | W48: 1362 | X48: =SUM(Q48:T48)/SUM(P48:S48)-1 -> 0.11894379 | Y48: =SUM(R48:U48)/SUM(Q48:T48)-1 -> 0.080761836 | Z48: =SUM(S48:V48)/SUM(R48:U48)-1 -> 0.043278819 | AA48: =SUM(T48:W48)/SUM(S48:V48)-1 -> 0.022940164
B49: LGBBROSLTD | C49: India | D49: N/A | E49: Sep '25 Sep 30, 2025 | F49: 6.3225289 | G49: 856.78 | H49: 945.07 | I49: 849.78 | J49: 654.08 | K49: 822.54 | L49: 871.04 | M49: 662.15 | N49: 692.32 | O49: 852.02 | P49: 869.25 | Q49: 754.96 | R49: 680.76 | S49: 881.51 | T49: 896.88 | U49: 780.2 | V49: 707.35 | W49: 1088
B50: 8014 | C50: Japan | D50: N/A | E50: Sep '25 Sep 30, 2025 | F50: -3.3030726 | G50: 2253 | H50: 2563 | I50: 1951 | J50: 3214 | K50: 3552 | L50: 4162 | M50: 1730 | N50: 3939 | O50: 3858 | P50: 4132 | Q50: 3112 | R50: 4398 | S50: 3793 | T50: 3134 | U50: 4042 | V50: 3351 | W50: 3320
B51: TEXRAIL | C51: India | D51: N/A | E51: Sep '25 Sep 30, 2025 | F51: -2.0552239 | G51: 297.76 | H51: 277.05 | I51: 185.54 | J51: -179.06 | K51: 346.08 | L51: 471.2 | M51: 430.51 | N51: 94.32 | O51: 674.53 | P51: 735.54 | Q51: 741.97 | R51: 619.61 | S51: 1213 | T51: 1198 | U51: 880.96 | V51: 600.56 | W51: 1133
B52: SXC | C52: United States | D52: Coking Coal | E52: Sep '25 Sep 30, 2025 | F52: -21.813725 | G52: 41.4 | H52: 27.6 | I52: 48.6 | J52: 34.5 | K52: 47.6 | L52: 22.5 | M52: 31.7 | N52: 37.5 | O52: 29.7 | P52: 26 | Q52: 34.5 | R52: 34.7 | S52: 47.2 | T52: 35.2 | U52: 30.2 | V52: 9.8 | W52: 20.5
B53: SFL | C53: United States | D53: Marine Shipping | E53: Sep '25 Sep 30, 2025 | F53: -19.075241 | G53: 54.69 | H53: 63.5 | I53: 59.33 | J53: 63.08 | K53: 65.46 | L53: 74.38 | M53: 47.27 | N53: 45.43 | O53: 63.19 | P53: 73.01 | Q53: 85.49 | R53: 62.23 | S53: 94.14 | T53: 59.49 | U53: 44.76 | V53: 41.24 | W53: 48.43
B54: CFR | C54: United States | D54: Banks - Regional | E54: Dec '25 Dec 31, 2025 | F54: 1.8436403 | G54: 111.17 | H54: 111.73 | I54: 139.79 | J54: 197.47 | K54: 219.84 | L54: 210.84 | M54: 193.85 | N54: 186.98 | O54: 120.7 | P54: 161.56 | Q54: 175.15 | R54: 175.24 | S54: 184.01 | T54: 179.1 | U54: 186.62 | V54: 208.01 | W54: 197.98 | X54: =SUM(Q54:T54)/SUM(P54:S54)-1 -> 0.025202598 | Y54: =SUM(R54:U54)/SUM(Q54:T54)-1 -> 0.016075683 | Z54: =SUM(S54:V54)/SUM(R54:U54)-1 -> 0.04520187 | AA54: =SUM(T54:W54)/SUM(S54:V54)-1 -> 0.018436403
B55: MHRIL | C55: India | D55: N/A | E55: Sep '25 Sep 30, 2025 | F55: 9.0042566 | G55: 517.78 | H55: 130.64 | I55: 682.83 | J55: 308.04 | K55: 464.02 | L55: 184.23 | M55: 1080 | N55: 26.74 | O55: 522.19 | P55: 195.82 | Q55: 1113 | R55: 167.02 | S55: 309.27 | T55: 526.95 | U55: 1252 | V55: 268.11 | W55: 521.44
B56: OSIS | C56: United States | D56: Electronic Components | E56: Dec '25 Dec 31, 2025 | F56: 1.5640361 | G56: 29.92 | H56: 29.9 | I56: 42.29 | J56: 19.52 | K56: 27.75 | L56: 35.23 | M56: 60.35 | N56: 23.03 | O56: 53.35 | P56: 52.37 | Q56: 66.71 | R56: 31.51 | S56: 58.17 | T56: 58.47 | U56: 71.34 | V56: 35.8 | W56: 61.67 | X56: =SUM(Q56:T56)/SUM(P56:S56)-1 -> 0.029220157 | Y56: =SUM(R56:U56)/SUM(Q56:T56)-1 -> 0.021548916 | Z56: =SUM(S56:V56)/SUM(R56:U56)-1 -> 0.01954531 | AA56: =SUM(T56:W56)/SUM(S56:V56)-1 -> 0.015640361
B57: TT | C57: United States | D57: Building Products & Equipment | E57: Dec '25 Dec 31, 2025 | F57: 1.2348555 | G57: 434.9 | H57: 382.9 | I57: 702.1 | J57: 701.3 | K57: 575.1 | L57: 453.9 | M57: 828.7 | N57: 859.5 | O57: 682.6 | P57: 631.1 | Q57: 1023 | R57: 1021 | S57: 789 | T57: 752.8 | U57: 1160 | V57: 1161 | W57: 836.7 | X57: =SUM(Q57:T57)/SUM(P57:S57)-1 -> 0.03513178 | Y57: =SUM(R57:U57)/SUM(Q57:T57)-1 -> 0.038206258 | Z57: =SUM(S57:V57)/SUM(R57:U57)-1 -> 0.037606103 | AA57: =SUM(T57:W57)/SUM(S57:V57)-1 -> 0.012348555
B58: AOS | C58: United States | D58: Specialty Industrial Machinery | E58: Dec '25 Dec 31, 2025 | F58: 1.068999 | G58: 165.9 | H58: 158.6 | I58: 164.3 | J58: 150.6 | K58: 150.6 | L58: 186.9 | M58: 204.2 | N58: 181.3 | O58: 168.5 | P58: 192.5 | Q58: 207.5 | R58: 160.7 | S58: 156.1 | T58: 182.8 | U58: 205.8 | V58: 175.6 | W58: 163.8 | X58: =SUM(Q58:T58)/SUM(P58:S58)-1 -> -0.013532366 | Y58: =SUM(R58:U58)/SUM(Q58:T58)-1 -> -0.0024041861 | Z58: =SUM(S58:V58)/SUM(R58:U58)-1 -> 0.021122767 | AA58: =SUM(T58:W58)/SUM(S58:V58)-1 -> 0.01068999
B59: PRAJIND | C59: India | D59: N/A | E59: Sep '25 Sep 30, 2025 | F59: -25.420956 | G59: 371.8 | H59: 419.6 | I59: 676.56 | J59: 494 | K59: 574.9 | L59: 788.2 | M59: 1019 | N59: 625.34 | O59: 687.84 | P59: 856.12 | Q59: 1108 | R59: 666.31 | S59: 735.79 | T59: 352.86 | U59: 555.62 | V59: 104.13 | W59: 291.33
B60: AMP | C60: United States | D60: Asset Management | E60: Dec '25 Dec 31, 2025 | F60: 0.98743268 | G60: 1073 | H60: 1293 | I60: 1499 | J60: 1248 | K60: 1192 | L60: 1329 | M60: 1429 | N60: 1659 | O60: 1196 | P60: 1590 | Q60: 1593 | R60: 1557 | S60: 1718 | T60: 1511 | U60: 1630 | V60: 1825 | W60: 1784 | X60: =SUM(Q60:T60)/SUM(P60:S60)-1 -> -0.012232889 | Y60: =SUM(R60:U60)/SUM(Q60:T60)-1 -> 0.0058002822 | Z60: =SUM(S60:V60)/SUM(R60:U60)-1 -> 0.041770574 | AA60: =SUM(T60:W60)/SUM(S60:V60)-1 -> 0.0098743268
B61: HOLX | C61: United States | D61: Medical Instruments & Supplies | E61: Dec '25 Dec 27, 2025 | F61: 0.67854114 | G61: 637.4 | H61: 593.9 | I61: 238.5 | J61: 178.4 | K61: 263.5 | L61: 261.5 | M61: 227.3 | N61: 181.4 | O61: 226.7 | P61: 243.3 | Q61: 263.9 | R61: 229 | S61: 233.7 | T61: 222.9 | U61: 260.9 | V61: 343.6 | W61: 240.9 | X61: =SUM(Q61:T61)/SUM(P61:S61)-1 -> -0.021033096 | Y61: =SUM(R61:U61)/SUM(Q61:T61)-1 -> -0.0031595577 | Z61: =SUM(S61:V61)/SUM(R61:U61)-1 -> 0.12107765 | AA61: =SUM(T61:W61)/SUM(S61:V61)-1 -> 0.0067854114
B62: 4549 | C62: Japan | D62: N/A | E62: Sep '25 Sep 30, 2025 | F62: -1.7096674 | G62: 2239 | H62: 1812 | I62: 1745 | J62: 2801 | K62: 2857 | L62: 1342 | M62: 457 | N62: 1053 | O62: 1096 | P62: 1269 | Q62: -39 | R62: 584 | S62: 983 | T62: 1069 | U62: 364 | V62: 801 | W62: 928
B63: AROW | C63: United States | D63: Banks - Regional | E63: Sep '25 Sep 30, 2025 | F63: 13.044599 | G63: 16.81 | H63: 13.37 | I63: 16.27 | J63: 15.53 | K63: 15.57 | L63: 15.54 | M63: 10.92 | N63: 7.65 | O63: 9.57 | P63: 9.38 | Q63: 9.68 | R63: 10.92 | S63: 11.54 | T63: 5.22 | U63: 8.13 | V63: 13.9 | W63: 16.6
B64: RRBI | C64: United States | D64: Banks - Regional | E64: Sep '25 Sep 30, 2025 | F64: 5.3213689 | G64: 9.92 | H64: 10.28 | I64: 8.92 | J64: 11.29 | K64: 12.31 | L64: 12.46 | M64: 11.76 | N64: 11.09 | O64: 9.89 | P64: 10.21 | Q64: 10.12 | R64: 9.9 | S64: 10.82 | T64: 11.54 | U64: 12.84 | V64: 12.72 | W64: 13.37
B65: 9997 | C65: Japan | D65: N/A | E65: Sep '25 Sep 30, 2025 | F65: 5.5871743 | G65: 2430 | H65: 5458 | I65: 3603 | J65: 1754 | K65: 1925 | L65: 4181 | M65: 3337 | N65: 1158 | O65: 1928 | P65: 2623 | Q65: 4057 | R65: 983 | S65: 2577 | T65: 3765 | U65: 4541 | V65: 1592 | W65: 3274
B66: DOV | C66: United States | D66: Specialty Industrial Machinery | E66: Dec '25 Dec 31, 2025 | F66: 0.66077877 | G66: 287.59 | H66: 307.51 | I66: 361.16 | J66: 377.73 | K66: 370.54 | L66: 327.43 | M66: 0 | N66: 341.28 | O66: 322.37 | P66: 273.53 | Q66: 333.27 | R66: 348.12 | S66: 336.06 | T66: 305.22 | U66: 368.72 | V66: 388.35 | W66: 345.3 | X66: =SUM(Q66:T66)/SUM(P66:S66)-1 -> 0.024547243 | Y66: =SUM(R66:U66)/SUM(Q66:T66)-1 -> 0.026801848 | Z66: =SUM(S66:V66)/SUM(R66:U66)-1 -> 0.02962183 | AA66: =SUM(T66:W66)/SUM(S66:V66)-1 -> 0.0066077877
B67: 8871 | C67: Japan | D67: N/A | E67: Sep '25 Sep 30, 2025 | F67: -4.8803428 | G67: 530 | H67: 8296 | I67: 859 | J67: 8766 | K67: 1205 | L67: 261 | M67: 323 | N67: -211 | O67: 594 | P67: 1040 | Q67: 4313 | R67: 1770 | S67: 1878 | T67: 3200 | U67: 671 | V67: 3820 | W67: 1411
B68: PFSI | C68: United States | D68: Mortgage Finance | E68: Dec '25 Dec 31, 2025 | F68: 0.64189313 | G68: 234.84 | H68: 234.52 | I68: 177.53 | J68: 185.47 | K68: 71.8 | L68: 38.15 | M68: 72.92 | N68: 126.8 | O68: 108.59 | P68: 43.88 | Q68: 133.85 | R68: 93.93 | S68: 130.9 | T68: 104.2 | U68: 75.35 | V68: 236.37 | W68: 134.41 | X68: =SUM(Q68:T68)/SUM(P68:S68)-1 -> 0.14984102 | Y68: =SUM(R68:U68)/SUM(Q68:T68)-1 -> -0.12638265 | Z68: =SUM(S68:V68)/SUM(R68:U68)-1 -> 0.35224294 | AA68: =SUM(T68:W68)/SUM(S68:V68)-1 -> 0.0064189313
B69: TFSL | C69: United States | D69: Banks - Regional | E69: Dec '25 Dec 31, 2025 | F69: 0.095885635 | G69: 20.33 | H69: 19.36 | I69: 21.22 | J69: 31.15 | K69: 28.12 | L69: 20.02 | M69: 21.75 | N69: 23.48 | O69: 26.13 | P69: 25.9 | Q69: 25.23 | R69: 23.05 | S69: 28.39 | T69: 26.53 | U69: 27.36 | V69: 32.44 | W69: 28.5 | X69: =SUM(Q69:T69)/SUM(P69:S69)-1 -> 0.0061421468 | Y69: =SUM(R69:U69)/SUM(Q69:T69)-1 -> 0.020639535 | Z69: =SUM(S69:V69)/SUM(R69:U69)-1 -> 0.089148391 | AA69: =SUM(T69:W69)/SUM(S69:V69)-1 -> 0.00095885635
B70: GODREJAGRO | C70: India | D70: N/A | E70: Sep '25 Sep 30, 2025 | F70: -1.3245033 | G70: 1537 | H70: 1021 | I70: 1102 | J70: 1167 | K70: 1042 | L70: 893.6 | M70: 288.3 | N70: 1401 | O70: 1486 | P70: 1061 | Q70: 1014 | R70: 1715 | S70: 1650 | T70: 1633 | U70: 1092 | V70: 2118 | W70: 1564
B71: ORC | C71: United States | D71: REIT - Mortgage | E71: Sep '25 Sep 30, 2025 | F71: 854.29017 | G71: 26.04 | H71: -44.56 | I71: -148.73 | J71: -60.14 | K71: -84.51 | L71: 34.93 | M71: 3.53 | N71: 10.25 | O71: -80.13 | P71: 27.13 | Q71: 19.78 | R71: -4.98 | S71: 17.32 | T71: 5.55 | U71: 17.12 | V71: -33.58 | W71: 72.08
B72: 1950 | C72: Japan | D72: N/A | E72: Sep '25 Sep 30, 2025 | F72: 13.826331 | G72: 175 | H72: 2334 | I72: 6659 | J72: -1798 | K72: 578 | L72: 1284 | M72: 9596 | N72: -1274 | O72: 1596 | P72: 2842 | Q72: 10285 | R72: -773 | S72: 1113 | T72: 3369 | U72: 14226 | V72: -858 | W72: 3581
B73: SBCF | C73: United States | D73: Banks - Regional | E73: Dec '25 Dec 31, 2025 | F73: -0.080360013 | G73: 44.67 | H73: 26.42 | I73: 41.64 | J73: 38.35 | K73: 31.72 | L73: 14.52 | M73: 41.44 | N73: 40.49 | O73: 37.8 | P73: 33.84 | Q73: 39.15 | R73: 39.25 | S73: 43.6 | T73: 40.85 | U73: 55.28 | V73: 46.93 | W73: 43.45 | X73: =SUM(Q73:T73)/SUM(P73:S73)-1 -> 0.044982033 | Y73: =SUM(R73:U73)/SUM(Q73:T73)-1 -> 0.099048204 | Z73: =SUM(S73:V73)/SUM(R73:U73)-1 -> 0.042909822 | AA73: =SUM(T73:W73)/SUM(S73:V73)-1 -> -0.00080360013
B74: 5482 | C74: Japan | D74: N/A | E74: Sep '25 Sep 30, 2025 | F74: 15.51746 | G74: 257 | H74: -97 | I74: 629 | J74: -1186 | K74: 1479 | L74: 314 | M74: 3436 | N74: 3068 | O74: 1655 | P74: 4382 | Q74: 3373 | R74: 1487 | S74: 1811 | T74: 4411 | U74: 4999 | V74: 4529 | W74: 4255
B75: MEDPLUS | C75: India | D75: N/A | E75: Sep '25 Sep 30, 2025 | F75: 6.740005 | G75: 344.54 | H75: 309.48 | I75: 278.63 | J75: 145.46 | K75: 177.96 | L75: 259.34 | M75: 378.09 | N75: 189.29 | O75: 296.18 | P75: 346.69 | Q75: 590.53 | R75: 337.33 | S75: 613.04 | T75: 700.55 | U75: 851.46 | V75: 651.12 | W75: 802.85
B76: NSC | C76: United States | D76: Railroads | E76: Dec '25 Dec 31, 2025 | F76: -0.39571695 | G76: 1155 | H76: 1116 | I76: 1304 | J76: 1302 | K76: 1249 | L76: 1127 | M76: 605 | N76: 949 | O76: 870 | P76: 930 | Q76: 1108 | R76: 1522 | S76: 1019 | T76: 983 | U76: 1159 | V76: 1135 | W76: 1002 | X76: =SUM(Q76:T76)/SUM(P76:S76)-1 -> 0.01157458 | Y76: =SUM(R76:U76)/SUM(Q76:T76)-1 -> 0.011010363 | Z76: =SUM(S76:V76)/SUM(R76:U76)-1 -> -0.082639334 | AA76: =SUM(T76:W76)/SUM(S76:V76)-1 -> -0.0039571695
B77: KTKBANK | C77: India | D77: N/A | E77: Sep '25 Sep 30, 2025 | F77: -0.61515582 | G77: 1462 | H77: 2177 | I77: 2841 | J77: 497.5 | K77: 5915 | L77: 3670 | M77: 4323 | N77: 4496 | O77: 4023 | P77: 3959 | Q77: 3153 | R77: 5184 | S77: 4292 | T77: 3493 | U77: 3442 | V77: 3566 | W77: 4201
B78: 8388 | C78: Japan | D78: N/A | E78: Sep '25 Sep 30, 2025 | F78: 11.452482 | G78: 2497 | H78: 4797 | I78: 4168 | J78: 5793 | K78: 1660 | L78: 3219 | M78: 3970 | N78: 3951 | O78: 3760 | P78: 4775 | Q78: 3487 | R78: 5147 | S78: 4344 | T78: 3155 | U78: 4139 | V78: 5808 | W78: 6342
B79: TBBK | C79: United States | D79: Banks - Regional | E79: Dec '25 Dec 31, 2025 | F79: -0.45657601 | G79: 35.56 | H79: 38.11 | I79: 41.13 | J79: 42.43 | K79: 0 | L79: 64.87 | M79: 66.23 | N79: 66.45 | O79: 59.22 | P79: 74.92 | Q79: 71.82 | R79: 69.03 | S79: 76.39 | T79: 75.24 | U79: 79.65 | V79: 73.16 | W79: 75 | X79: =SUM(Q79:T79)/SUM(P79:S79)-1 -> 0.0010952903 | Y79: =SUM(R79:U79)/SUM(Q79:T79)-1 -> 0.026771061 | Z79: =SUM(S79:V79)/SUM(R79:U79)-1 -> 0.013752456 | AA79: =SUM(T79:W79)/SUM(S79:V79)-1 -> -0.0045657601
B80: SKYW | C80: United States | D80: Airlines | E80: Dec '25 Dec 31, 2025 | F80: -0.91729878 | G80: 32.95 | H80: 52.05 | I80: 88.6 | J80: 75.58 | K80: 16.32 | L80: -4.7 | M80: 31.86 | N80: 49.29 | O80: 29.94 | P80: 99.51 | Q80: 119.64 | R80: 131.44 | S80: 139.92 | T80: 139.38 | U80: 170.13 | V80: 174.14 | W80: 134.2 | X80: =SUM(Q80:T80)/SUM(P80:S80)-1 -> 0.081282747 | Y80: =SUM(R80:U80)/SUM(Q80:T80)-1 -> 0.095195897 | Z80: =SUM(S80:V80)/SUM(R80:U80)-1 -> 0.073510424 | AA80: =SUM(T80:W80)/SUM(S80:V80)-1 -> -0.0091729878
B81: MO | C81: United States | D81: Tobacco | E81: Dec '25 Dec 31, 2025 | F81: -1.0446802 | G81: 2872 | H81: 2882 | I81: 3197 | J81: 3197 | K81: 3025 | L81: 2898 | M81: 3216 | N81: 3130 | O81: 2953 | P81: 2781 | Q81: 3133 | R81: 3257 | S81: 3055 | T81: 2788 | U81: 3302 | V81: 3299 | W81: 2925 | X81: =SUM(Q81:T81)/SUM(P81:S81)-1 -> 0.0005725503 | Y81: =SUM(R81:U81)/SUM(Q81:T81)-1 -> 0.01381509 | Z81: =SUM(S81:V81)/SUM(R81:U81)-1 -> 0.0033865506 | AA81: =SUM(T81:W81)/SUM(S81:V81)-1 -> -0.010446802
B82: MOFG | C82: United States | D82: Banks - Regional | E82: Sep '25 Sep 30, 2025 | F82: -197.23053 | G82: 20.82 | H82: 18.98 | I82: 17.34 | J82: 16.71 | K82: 23.06 | L82: 19.49 | M82: 1.78 | N82: 9.19 | O82: 11.34 | P82: 2.52 | Q82: 4.23 | R82: 20.87 | S82: -130.2 | T82: 21.11 | U82: 19.6 | V82: 12.58 | W82: 21.49
B83: 3191 | C83: Japan | D83: N/A | E83: Sep '25 Sep 20, 2025 | F83: 9.7059428 | G83: 1556 | H83: 2305 | I83: 1749 | J83: 2413 | K83: 1587 | L83: 2233 | M83: 1830 | N83: 2359 | O83: 1506 | P83: 2703 | Q83: 2581 | R83: 3035 | S83: 1764 | T83: 2542 | U83: 3035 | V83: 2385 | W83: 2708
B84: GMRP&UI | C84: India | D84: N/A | E84: Sep '25 Sep 30, 2025 | F84: -6.505295 | G84: 1367 | H84: 1301 | I84: 852.8 | J84: 1078 | K84: 156.2 | L84: 1020 | M84: 1113 | N84: 1298 | O84: 984.3 | P84: 2084 | Q84: 3779 | R84: 3326 | S84: 2766 | T84: 1892 | U84: 3484 | V84: 3756 | W84: 1992
B85: OSK | C85: United States | D85: Farm & Heavy Construction Machinery | E85: Dec '25 Dec 31, 2025 | F85: -1.298027 | G85: 55.6 | H85: 31.9 | I85: 76.3 | J85: 119.3 | K85: 152.6 | L85: 131.5 | M85: 235.5 | N85: 257.2 | O85: 216.1 | P85: 260.6 | Q85: 313.5 | R85: 267.2 | S85: 224.5 | T85: 177.1 | U85: 299.1 | V85: 262.3 | W85: 212 | X85: =SUM(Q85:T85)/SUM(P85:S85)-1 -> -0.078344905 | Y85: =SUM(R85:U85)/SUM(Q85:T85)-1 -> -0.014659473 | Z85: =SUM(S85:V85)/SUM(R85:U85)-1 -> -0.0050625065 | AA85: =SUM(T85:W85)/SUM(S85:V85)-1 -> -0.01298027
B86: CRTO | C86: United States | D86: Advertising Agencies | E86: Sep '25 Sep 30, 2025 | F86: 21.342609 | G86: 32.51 | H86: 40.74 | I86: 27.66 | J86: -56.51 | K86: 4.48 | L86: 48.64 | M86: -23.41 | N86: 0.96 | O86: 11.43 | P86: 111.32 | Q86: 13.59 | R86: 36.94 | S86: 9.6 | T86: 108.7 | U86: 48.17 | V86: 30.46 | W86: 51.63
B87: TSCO | C87: United States | D87: Specialty Retail | E87: Dec '25 Dec 27, 2025 | F87: -1.3857434 | G87: 293.05 | H87: 244.29 | I87: 525.04 | J87: 306.41 | K87: 359.21 | L87: 244.44 | M87: 559.33 | N87: 329.61 | O87: 334.24 | P87: 263.13 | Q87: 561.46 | R87: 324.6 | S87: 318.35 | T87: 249.14 | U87: 577.81 | V87: 342.71 | W87: 297.73 | X87: =SUM(Q87:T87)/SUM(P87:S87)-1 -> -0.0095329599 | Y87: =SUM(R87:U87)/SUM(Q87:T87)-1 -> 0.011248323 | Z87: =SUM(S87:V87)/SUM(R87:U87)-1 -> 0.012320566 | AA87: =SUM(T87:W87)/SUM(S87:V87)-1 -> -0.013857434
B88: 6946 | C88: Japan | D88: N/A | E88: Sep '25 Sep 30, 2025 | F88: 18.657938 | G88: 626 | H88: 373 | I88: 527 | J88: 34 | K88: 545 | L88: 566 | M88: 807 | N88: 276 | O88: 635 | P88: 599 | Q88: 669 | R88: 325 | S88: 825 | T88: 516 | U88: 1131 | V88: 583 | W88: 1395
B89: MAN | C89: United States | D89: Staffing & Employment Services | E89: Dec '25 Dec 31, 2025 | F89: -1.759134 | G89: 180.3 | H89: 142.4 | I89: 183.7 | J89: 167.4 | K89: 164.6 | L89: 117.9 | M89: 107.6 | N89: 107.9 | O89: 105.6 | P89: 65.9 | Q89: 101.1 | R89: 108.4 | S89: 85.8 | T89: 44 | U89: 77.8 | V89: 88 | W89: 80.6 | X89: =SUM(Q89:T89)/SUM(P89:S89)-1 -> -0.060631229 | Y89: =SUM(R89:U89)/SUM(Q89:T89)-1 -> -0.068670793 | Z89: =SUM(S89:V89)/SUM(R89:U89)-1 -> -0.064556962 | AA89: =SUM(T89:W89)/SUM(S89:V89)-1 -> -0.01759134
B90: SBSI | C90: United States | D90: Banks - Regional | E90: Dec '25 Dec 31, 2025 | F90: -1.9926462 | G90: 33.5 | H90: 28.14 | I90: 28.7 | J90: 30.83 | K90: 31.96 | L90: 30.58 | M90: 29.46 | N90: 21.57 | O90: 19.52 | P90: 26.13 | Q90: 29.89 | R90: 24.91 | S90: 26.45 | T90: 26.23 | U90: 26.53 | V90: 5.1 | W90: 24.77 | X90: =SUM(Q90:T90)/SUM(P90:S90)-1 -> 0.00093127212 | Y90: =SUM(R90:U90)/SUM(Q90:T90)-1 -> -0.03126163 | Z90: =SUM(S90:V90)/SUM(R90:U90)-1 -> -0.19026124 | AA90: =SUM(T90:W90)/SUM(S90:V90)-1 -> -0.019926462
B91: LAZ | C91: United States | D91: Capital Markets | E91: Dec '25 Dec 31, 2025 | F91: -2.1017171 | G91: 279.47 | H91: 157.82 | I91: 122.13 | J91: 155.49 | K91: 112.81 | L91: -46.04 | M91: 27.33 | N91: 5.07 | O91: 88.14 | P91: 99.89 | Q91: 61.8 | R91: 167.1 | S91: 93.37 | T91: 60.06 | U91: 102.72 | V91: 79.29 | W91: 86.32 | X91: =SUM(Q91:T91)/SUM(P91:S91)-1 -> -0.094348114 | Y91: =SUM(R91:U91)/SUM(Q91:T91)-1 -> 0.10702796 | Z91: =SUM(S91:V91)/SUM(R91:U91)-1 -> -0.20746604 | AA91: =SUM(T91:W91)/SUM(S91:V91)-1 -> -0.021017171
B92: GPI | C92: United States | D92: Auto & Truck Dealerships | E92: Dec '25 Dec 31, 2025 | F92: -2.1607783 | G92: 0 | H92: 285.1 | I92: 285.3 | J92: 279.8 | K92: 243.5 | L92: 242.7 | M92: 272.5 | N92: 266.4 | O92: 223.2 | P92: 242.7 | Q92: 241.1 | R92: 231.5 | S92: 236.8 | T92: 245.5 | U92: 261.1 | V92: 233.1 | W92: 215.7 | X92: =SUM(Q92:T92)/SUM(P92:S92)-1 -> 0.0029408676 | Y92: =SUM(R92:U92)/SUM(Q92:T92)-1 -> 0.020944602 | Z92: =SUM(S92:V92)/SUM(R92:U92)-1 -> 0.001641194 | AA92: =SUM(T92:W92)/SUM(S92:V92)-1 -> -0.021607783
B93: MTX | C93: United States | D93: Specialty Chemicals | E93: Dec '25 Dec 31, 2025 | F93: -2.6119403 | G93: 54.7 | H93: 67.8 | I93: 73.5 | J93: 67.2 | K93: 44 | L93: 63.1 | M93: 70.6 | N93: 77 | O93: 69.2 | P93: 77.3 | Q93: 84.8 | R93: 79.2 | S93: 74.2 | T93: 63.2 | U93: 79 | V93: 78.4 | W93: 66.5 | X93: =SUM(Q93:T93)/SUM(P93:S93)-1 -> -0.044690967 | Y93: =SUM(R93:U93)/SUM(Q93:T93)-1 -> -0.01924353 | Z93: =SUM(S93:V93)/SUM(R93:U93)-1 -> -0.0027063599 | AA93: =SUM(T93:W93)/SUM(S93:V93)-1 -> -0.026119403
B94: MRSH | C94: United States | D94: Insurance Brokers | E94: Dec '25 Dec 31, 2025 | F94: -3.2937685 | G94: 1215 | H94: 1507 | I94: 1423 | J94: 848 | K94: 1193 | L94: 1750 | M94: 1527 | N94: 1063 | O94: 1527 | P94: 1995 | Q94: 1708 | R94: 1176 | S94: 1492 | T94: 2149 | U94: 1877 | V94: 1222 | W94: 1270 | X94: =SUM(Q94:T94)/SUM(P94:S94)-1 -> 0.02417203 | Y94: =SUM(R94:U94)/SUM(Q94:T94)-1 -> 0.025900383 | Z94: =SUM(S94:V94)/SUM(R94:U94)-1 -> 0.0068718255 | AA94: =SUM(T94:W94)/SUM(S94:V94)-1 -> -0.032937685
B95: EXP | C95: United States | D95: Building Materials | E95: Dec '25 Dec 31, 2025 | F95: -3.4344884 | G95: 125.74 | H95: 85.36 | I95: 139.05 | J95: 180.61 | K95: 146.27 | L95: 119.71 | M95: 164.32 | N95: 192.44 | O95: 166.43 | P95: 102.34 | Q95: 171.22 | R95: 185.97 | S95: 157 | T95: 85.02 | U95: 164.82 | V95: 178.4 | W95: 136.9 | X95: =SUM(Q95:T95)/SUM(P95:S95)-1 -> -0.028092712 | Y95: =SUM(R95:U95)/SUM(Q95:T95)-1 -> -0.01068073 | Z95: =SUM(S95:V95)/SUM(R95:U95)-1 -> -0.01276969 | AA95: =SUM(T95:W95)/SUM(S95:V95)-1 -> -0.034344884
B96: DXC | C96: United States | D96: Information Technology Services | E96: Dec '25 Dec 31, 2025 | F96: -3.5377358 | G96: 233 | H96: 921 | I96: 116 | J96: 147 | K96: 148 | L96: -1202 | M96: 105 | N96: 155 | O96: 158 | P96: -252 | Q96: 130 | R96: 187 | S96: 197 | T96: 371 | U96: 119 | V96: 161 | W96: 167 | X96: =SUM(Q96:T96)/SUM(P96:S96)-1 -> 2.3778626 | Y96: =SUM(R96:U96)/SUM(Q96:T96)-1 -> -0.012429379 | Z96: =SUM(S96:V96)/SUM(R96:U96)-1 -> -0.029748284 | AA96: =SUM(T96:W96)/SUM(S96:V96)-1 -> -0.035377358
B97: CAT | C97: United States | D97: Farm & Heavy Construction Machinery | E97: Dec '25 Dec 31, 2025 | F97: -3.6497587 | G97: 2526 | H97: 1943 | I97: 2019 | J97: 2501 | K97: 3293 | L97: 3297 | M97: 3634 | N97: 3437 | O97: 3300 | P97: 3501 | Q97: 3745 | R97: 3206 | S97: 3111 | T97: 2629 | U97: 2939 | V97: 3130 | W97: 2680 | X97: =SUM(Q97:T97)/SUM(P97:S97)-1 -> -0.064292561 | Y97: =SUM(R97:U97)/SUM(Q97:T97)-1 -> -0.063509574 | Z97: =SUM(S97:V97)/SUM(R97:U97)-1 -> -0.0063946151 | AA97: =SUM(T97:W97)/SUM(S97:V97)-1 -> -0.036497587
B98: CVCO | C98: United States | D98: Residential Construction | E98: Dec '25 Dec 27, 2025 | F98: -3.936238 | G98: 54.68 | H98: 69.75 | I98: 78.43 | J98: 90.47 | K98: 72.85 | L98: 56.35 | M98: 55.93 | N98: 45.19 | O98: 38.9 | P98: 38.96 | Q98: 38.55 | R98: 49 | S98: 63.82 | T98: 49 | U98: 60.36 | V98: 62.07 | W98: 54.56 | X98: =SUM(Q98:T98)/SUM(P98:S98)-1 -> 0.052750486 | Y98: =SUM(R98:U98)/SUM(Q98:T98)-1 -> 0.10884863 | Z98: =SUM(S98:V98)/SUM(R98:U98)-1 -> 0.058826177 | AA98: =SUM(T98:W98)/SUM(S98:V98)-1 -> -0.03936238
B99: AJG | C99: United States | D99: Insurance Brokers | E99: Dec '25 Dec 31, 2025 | F99: -4.0807265 | G99: 248.6 | H99: 678.6 | I99: 410.7 | J99: 400.8 | K99: 506.1 | L99: 803.2 | M99: 415.8 | N99: 417.1 | O99: 331.1 | P99: 871.3 | Q99: 514.5 | R99: 492.6 | S99: 449.1 | T99: 957.6 | U99: 527.2 | V99: 543.6 | W99: 348 | X99: =SUM(Q99:T99)/SUM(P99:S99)-1 -> 0.03707841 | Y99: =SUM(R99:U99)/SUM(Q99:T99)-1 -> 0.0052614135 | Z99: =SUM(S99:V99)/SUM(R99:U99)-1 -> 0.021017927 | AA99: =SUM(T99:W99)/SUM(S99:V99)-1 -> -0.040807265
B100: LHX | C100: United States | D100: Aerospace & Defense | E100: Jan '26 Jan 2, 2026 | F100: -4.3201133 | G100: 173 | H100: 633 | I100: 621 | J100: 563 | K100: 766 | L100: 533 | M100: 558 | N100: 646 | O100: 670 | P100: 625 | Q100: 640 | R100: 641 | S100: 732 | T100: 667 | U100: 696 | V100: 729 | W100: 610 | X100: =SUM(Q100:T100)/SUM(P100:S100)-1 -> 0.015921152 | Y100: =SUM(R100:U100)/SUM(Q100:T100)-1 -> 0.020895522 | Z100: =SUM(S100:V100)/SUM(R100:U100)-1 -> 0.032163743 | AA100: =SUM(T100:W100)/SUM(S100:V100)-1 -> -0.043201133
... B113: IP | C113: United States | D113: Packaging & Containers | E113: Dec '25 Dec 31, 2025 | F113: -18.711019 | G113: 418 | H113: 385 | I113: 585 | J113: 513 | K113: 463 | L113: 283 | M113: 314 | N113: 319 | O113: 283 | P113: 154 | Q113: 0 | R113: 119 | S113: 338 | T113: 159 | U113: 0 | V113: 465 | W113: 158 | X113: =SUM(Q113:T113)/SUM(P113:S113)-1 -> 0.0081833061 | Y113: =SUM(R113:U113)/SUM(Q113:T113)-1 -> 0 | Z113: =SUM(S113:V113)/SUM(R113:U113)-1 -> 0.56168831 | AA113: =SUM(T113:W113)/SUM(S113:V113)-1 -> -0.18711019
...

Sheet 빨간줄
B2: (단위: mil $)
Y3: SNDK
B4: 6702 | C4: 6 | D4: 7 | E4: 8 | F4: 9 | G4: 10 | H4: 11 | I4: 12 | J4: 13 | K4: 14 | L4: 15 | M4: 16 | N4: 17 | O4: 18 | P4: 19 | Q4: 20 | R4: 21 | S4: 22 | Y4: TAL
Y5: CNX
C6: 4Q21 | D6: 1Q22 | E6: 2Q22 | F6: 3Q22 | G6: 4Q22 | H6: 1Q23 | I6: 2Q23 | J6: 3Q23 | K6: 4Q23 | L6: 1Q24 | M6: 2Q24 | N6: 3Q24 | O6: 4Q24 | P6: 1Q25 | Q6: 2Q25 | R6: 3Q25 | S6: 4Q25 | T6: 1Q26 | U6: 2Q26 | V6: 3Q26 | W6: 4Q26 | Y6: IVR
B7: Revenue | C7: =VLOOKUP($B$4,Revenue!$B:$W,C4,FALSE) -> 880526 | D7: =VLOOKUP($B$4,Revenue!$B:$W,D4,FALSE) -> 1043302 | E7: =VLOOKUP($B$4,Revenue!$B:$W,E4,FALSE) -> 818862 | F7: =VLOOKUP($B$4,Revenue!$B:$W,F4,FALSE) -> 886449 | G7: =VLOOKUP($B$4,Revenue!$B:$W,G4,FALSE) -> 931424 | H7: =VLOOKUP($B$4,Revenue!$B:$W,H4,FALSE) -> 1077032 | I7: =VLOOKUP($B$4,Revenue!$B:$W,I4,FALSE) -> 799640 | J7: =VLOOKUP($B$4,Revenue!$B:$W,J4,FALSE) -> 912257 | ... S7: =VLOOKUP($B$4,Revenue!$B:$W,S4,FALSE) -> 884642 | Y7: WDC
B8: OP | C8: =VLOOKUP($B$4,'Operating Income'!$B:$W,C4,FALSE) -> 65185 | D8: =VLOOKUP($B$4,'Operating Income'!$B:$W,D4,FALSE) -> 113339 | E8: =VLOOKUP($B$4,'Operating Income'!$B:$W,E4,FALSE) -> 25602 | F8: =VLOOKUP($B$4,'Operating Income'!$B:$W,F4,FALSE) -> 75367 | G8: =VLOOKUP($B$4,'Operating Income'!$B:$W,G4,FALSE) -> 72316 | H8: =VLOOKUP($B$4,'Operating Income'!$B:$W,H4,FALSE) -> 105062 | I8: =VLOOKUP($B$4,'Operating Income'!$B:$W,I4,FALSE) -> -1665 | J8: =VLOOKUP($B$4,'Operating Income'!$B:$W,J4,FALSE) -> 46445 | ... S8: =VLOOKUP($B$4,'Operating Income'!$B:$W,S4,FALSE) -> 105656 | Y8: VLO
B9: Trailing 4Q OP avg. | C9: =AVERAGE(C8:C8) -> 65185 | D9: =AVERAGE(C8:D8) -> 89262 | E9: =AVERAGE(C8:E8) -> 68042 | F9: =AVERAGE(C8:F8) -> 69873.25 | G9: =AVERAGE(D8:G8) -> 71656 | H9: =AVERAGE(E8:H8) -> 69586.75 | I9: =AVERAGE(F8:I8) -> 62770 | J9: =AVERAGE(G8:J8) -> 55539.5 | K9: =AVERAGE(H8:K8) -> 38287.75 | L9: =AVERAGE(I8:L8) -> 63843.75 | M9: =AVERAGE(J8:M8) -> 69606.75 | ... S9: =AVERAGE(P8:S8) -> 52750.25 | Y9: VLY
B10: Trailing 4Q OP sum. | C10: =SUM(C8:C8) -> 65185 | D10: =SUM(C8:D8) -> 178524 | E10: =SUM(C8:E8) -> 204126 | F10: =SUM(C8:F8) -> 279493 | G10: =SUM(D8:G8) -> 286624 | H10: =SUM(E8:H8) -> 278347 | I10: =SUM(F8:I8) -> 251080 | J10: =SUM(G8:J8) -> 222158 | K10: =SUM(H8:K8) -> 153151 | L10: =SUM(I8:L8) -> 255375 | M10: =SUM(J8:M8) -> 278427 | ... S10: =SUM(P8:S8) -> 211001 | Y10: KEX
B11: Trailing OP Delta | D11: =D9/C9-1 -> 0.36936412 | E11: =E9/D9-1 -> -0.23772714 | F11: =F9/E9-1 -> 0.026913524 | G11: =G9/F9-1 -> 0.025514056 | H11: =IFERROR(H9/G9-1,0) -> -0.028877554 | I11: =IFERROR(I9/H9-1,0) -> -0.097960459 | J11: =IFERROR(J9/I9-1,0) -> -0.11519038 | K11: =K9/J9-1 -> -0.31062127 | L11: =L9/K9-1 -> 0.66747197 | M11: =M9/L9-1 -> 0.090267254 | N11: =N9/M9-1 -> -0.041077194 | O11: =O9/N9-1 -> 0.245571 | P11: =P9/O9-1 -> -0.62331344 | Q11: =Q9/P9-1 -> 0.096584151 | R11: =R9/Q9-1 -> 0.26826481 | S11: =S9/R9-1 -> 0.21112508 | Y11: LMT
B12: opm | C12: =IFERROR(C8/C7,"-") -> 0.074029614 | D12: =IFERROR(D8/D7,"-") -> 0.10863489 | E12: =IFERROR(E8/E7,"-") -> 0.031265341 | F12: =IFERROR(F8/F7,"-") -> 0.085021248 | G12: =IFERROR(G8/G7,"-") -> 0.077640258 | H12: =IFERROR(H8/H7,"-") -> 0.097547705 | I12: =IFERROR(I8/I7,"-") -> -0.002082187 | J12: =IFERROR(J8/J7,"-") -> 0.050912188 | ... S12: =IFERROR(S8/S7,"-") -> 0.11943362 | Y12: APPF
B13: op yoy | C13: =C8/#REF!-1 -> #REF! | D13: =D8/#REF!-1 -> #REF! | E13: =E8/#REF!-1 -> #REF! | F13: =F8/#REF!-1 -> #REF! | G13: =G8/C8-1 -> 0.10939633 | H13: =IFERROR(H8/D8-1,0) -> -0.073028702 | I13: =IFERROR(I8/E8-1,0) -> -1.065034 | J13: =IFERROR(J8/F8-1,0) -> -0.38374886 | K13: =IFERROR(K8/G8-1,0) -> -0.95424249 | L13: =IFERROR(L8/H8-1,0) -> 0.97298738 | M13: =IFERROR(M8/I8-1,0) -> -13.845045 | N13: =N8/J8-1 -> -0.24624825 | O13: =O8/K8-1 -> 19.814143 | P13: =P8/L8-1 -> -1 | Q13: =Q8/M8-1 -> 0.56571749 | R13: =R8/N8-1 -> 1.0526451 | S13: =S8/O8-1 -> 0.53404768 | Y13: BFH
B14: rv yoy | G14: =G7/C7-1 -> 0.057804085 | H14: =H7/D7-1 -> 0.032330044 | I14: =I7/E7-1 -> -0.023474041 | J14: =J7/F7-1 -> 0.029113914 | K14: =K7/G7-1 -> -0.00064310132 | L14: =L7/H7-1 -> 0.033708376 | M14: =M7/I7-1 -> 0.038004602 | N14: =N7/J7-1 -> -0.049997972 | ... S14: =S7/O7-1 -> -0.043377929 | Y14: VIRT
Y15: BX
