Workbook

Sheet Revenue
B2: Ticker | C2: Country | D2: Industry | E2: Latest_Date | F2: Growth_Rate | G2: 4Q21 | H2: 1Q22 | I2: 2Q22 | J2: 3Q22 | K2: 4Q22 | L2: 1Q23 | M2: 2Q23 | N2: 3Q23 | O2: 4Q23 | P2: 1Q24 | Q2: 2Q24 | R2: 3Q24 | S2: 4Q24 | T2: 1Q25 | U2: 2Q25 | V2: 3Q25 | W2: 4Q25
B3: MC | C3: United States | D3: Capital Markets | E3: Sep '25 Sep 30, 2025 | F3: 6.0045505 | G3: 490.82 | H3: 425.02 | I3: 302.09 | J3: 242.52 | K3: 233.51 | L3: 207.18 | M3: 187.82 | N3: 179.87 | O3: 272.18 | P3: 214.88 | Q3: 217.49 | R3: 264.59 | S3: 273.76 | T3: 438.72 | U3: 306.59 | V3: 365.38 | W3: 356.89
B4: FFIC | C4: United States | D4: Banks - Regional | E4: Dec '25 Dec 31, 2025 | F4: 57.008956 | G4: 61.63 | H4: 63.43 | I4: 70.49 | J4: 68.06 | K4: 46.56 | L4: 44.61 | M4: 46.98 | N4: 47.14 | O4: 52.49 | P4: 44.89 | Q4: 46.18 | R4: 50.33 | S4: -26.05 | T4: 53.75 | U4: 59.29 | V4: 57.04 | W4: 56.06
B5: CLBK | C5: United States | D5: Banks - Regional | E5: Sep '25 Sep 30, 2025 | F5: 7.8820891 | G5: 65.75 | H5: 75.33 | I5: 68.31 | J5: 72.64 | K5: 75.8 | L5: 74.95 | M5: 68.76 | N5: 49.53 | O5: 54.75 | P5: 55.43 | Q5: 44.37 | R5: 51.07 | S5: 50.15 | T5: 19.84 | U5: 55.86 | V5: 61.41 | W5: 64.91
B6: CCNE | C6: United States | D6: Banks - Regional | E6: Dec '25 Dec 31, 2025 | F6: 19.927171 | G6: 50.17 | H6: 50.63 | I6: 51.54 | J6: 56.78 | K6: 56.89 | L6: 54.39 | M6: 53.15 | N6: 54.04 | O6: 55.59 | P6: 52.86 | Q6: 51.99 | R6: 56.08 | S6: 56.44 | T6: 55.38 | U6: 56.87 | V6: 59.24 | W6: 101.86
B7: NRIX | C7: United States | D7: Biotechnology | E7: Aug '25 Aug 31, 2025 | F7: -5.3179452 | G7: 10.25 | H7: 7.4 | I7: 9.62 | J7: 11.43 | K7: 10.79 | L7: 6.78 | M7: 12.69 | N7: 30.68 | O7: 18.47 | P7: 15.16 | Q7: 16.59 | R7: 12.09 | S7: 12.59 | T7: 13.28 | U7: 18.45 | V7: 44.06 | W7: 7.89
B8: ECL | C8: United States | D8: Specialty Chemicals | E8: Sep '25 Sep 30, 2025 | F8: 1.055711 | G8: 3321 | H8: 3365 | I8: 3267 | J8: 3581 | K8: 3669 | L8: 3671 | M8: 3572 | N8: 3852 | O8: 3958 | P8: 3938 | Q8: 3752 | R8: 3986 | S8: 3999 | T8: 4005 | U8: 3695 | V8: 4025 | W8: 4165
B9: CHALET | C9: India | D9: N/A | E9: Sep '25 Sep 30, 2025 | F9: 15.87766 | G9: 1334 | H9: 1642 | I9: 1540 | J9: 2530 | K9: 2188 | L9: 3218 | M9: 3386 | N9: 3108 | O9: 3091 | P9: 3799 | Q9: 4185 | R9: 3610 | S9: 3771 | T9: 4578 | U9: 5265 | V9: 8946 | W9: 7353
B10: BUSE | C10: United States | D10: Banks - Regional | E10: Dec '25 Dec 31, 2025 | F10: 14.067739 | G10: 110.33 | H10: 106.08 | I10: 105.29 | J10: 114.87 | K10: 119.37 | L10: 116.75 | M10: 106.06 | N10: 108.44 | O10: 108.19 | P10: 101.55 | Q10: 119.19 | R10: 118.08 | S10: 115.53 | T10: 72.64 | U10: 199.07 | V10: 197.36 | W10: 197.77
B11: RNST | C11: United States | D11: Banks - Regional | E11: Dec '25 Dec 31, 2025 | F11: 13.293955 | G11: 149.53 | H11: 135.59 | I11: 148.73 | J11: 161.7 | K11: 160.66 | L11: 166.61 | M11: 145.44 | N11: 160.97 | O11: 143.79 | P11: 162.23 | Q11: 160.49 | R11: 219.36 | S11: 164.5 | T11: 165.92 | U11: 185.87 | V11: 259.1 | W11: 267.58
B12: ECLERX | C12: India | D12: N/A | E12: Sep '25 Sep 30, 2025 | F12: 4.9197101 | G12: 5233 | H12: 5592 | I12: 5917 | J12: 6178 | K12: 6503 | L12: 6867 | M12: 6931 | N12: 6845 | O12: 7218 | P12: 7528 | Q12: 7665 | R12: 7819 | S12: 8318 | T12: 8538 | U12: 8983 | V12: 9346 | W12: 10049
B13: UMBF | C13: United States | D13: Banks - Regional | E13: Dec '25 Dec 31, 2025 | F13: 12.659895 | G13: 320.85 | H13: 340.53 | I13: 387.73 | J13: 340.21 | K13: 361.66 | L13: 348.65 | M13: 350.69 | N13: 350.63 | O13: 370.78 | P13: 388.68 | Q13: 375.98 | R13: 388.12 | S13: 415.19 | T13: 477.84 | U13: 665.71 | V13: 658.34 | W13: 695.87
B14: WSBC | C14: United States | D14: Banks - Regional | E14: Dec '25 Dec 31, 2025 | F14: 12.38036 | G14: 154.6 | H14: 141.53 | I14: 140.02 | J14: 157.29 | K14: 154.52 | L14: 148.41 | M14: 150.38 | N14: 142.23 | O14: 143.03 | P14: 140.58 | Q14: 137.41 | R14: 145.96 | S14: 163.04 | T14: 123.4 | U14: 257.51 | V14: 259.5 | W14: 262.51
... B81: PGC | C81: United States | D81: Banks - Regional | E81: Sep '25 Sep 30, 2025 | F81: 4.4060258 | G81: 51.39 | H81: 52.43 | I81: 51.96 | J81: 59.95 | K81: 61.31 | L81: 62.9 | M81: 60.52 | N81: 55.8 | O81: 50.01 | P81: 49.2 | Q81: 52.45 | R81: 52.69 | S81: 55.4 | T81: 59.86 | U81: 59.89 | V81: 63.16 | W81: 65.9

Sheet Operating Income
B1: 1 | C1: 2 | D1: 3 | E1: 4 | F1: 5 | G1: 6 | H1: 7 | I1: 8 | J1: 9 | K1: 10 | L1: 11 | M1: 12 | N1: 13 | O1: 14 | P1: 15 | Q1: 16 | R1: 17 | S1: 18 | T1: 19 | U1: 20 | V1: 21 | W1: 22
B2: Ticker | C2: Country | D2: Industry | E2: Latest_Date | F2: Growth_Rate | G2: 4Q21 | H2: 1Q22 | I2: 2Q22 | J2: 3Q22 | K2: 4Q22 | L2: 1Q23 | M2: 2Q23 | N2: 3Q23 | O2: 4Q23 | P2: 1Q24 | Q2: 2Q24 | R2: 3Q24 | S2: 4Q24 | T2: 1Q25 | U2: 2Q25 | V2: 3Q25 | W2: 4Q25
B3: MC | C3: United States | D3: Capital Markets | E3: Sep '25 Sep 30, 2025 | F3: 13.388659 | G3: 152.15 | H3: 153.11 | I3: 89.43 | J3: 62.2 | K3: 35.05 | L3: 29.43 | M3: -1.39 | N3: -9.59 | O3: -20.03 | P3: -8.2 | Q3: 5.8 | R3: 20.07 | S3: 15.56 | T3: 131.51 | U3: 36.91 | V3: 60.63 | W3: 48.31
B4: JBLU | C4: United States | D4: Airlines | E4: Dec '25 Dec 31, 2025 | F4: 54.460094 | G4: -111 | H4: -367 | I4: -69 | J4: 152 | K4: 99 | L4: -130 | M4: 259 | N4: -123 | O4: -38 | P4: -157 | Q4: 58 | R4: -11 | S4: 17 | T4: -174 | U4: 30 | V4: -86 | W4: -99
B5: CLBK | C5: United States | D5: Banks - Regional | E5: Sep '25 Sep 30, 2025 | F5: 137.6652 | G5: 28.69 | H5: 31.95 | I5: 27.56 | J5: 30.92 | K5: 27.96 | L5: 30.44 | M5: 24.86 | N5: 1.92 | O5: 11.84 | P5: 7.43 | Q5: -1.28 | R5: 4.82 | S5: 7.32 | T5: -26.76 | U5: 12.02 | V5: 16.5 | W5: 19.82
B6: CCNE | C6: United States | D6: Banks - Regional | E6: Dec '25 Dec 31, 2025 | F6: 39.055649 | G6: 17.7 | H6: 18.74 | I6: 18.93 | J6: 20.68 | K6: 19.87 | L6: 20.4 | M6: 17.16 | N6: 17.13 | O6: 17.14 | P6: 15.43 | Q6: 16 | R6: 17.29 | S6: 18.63 | T6: 14.34 | U6: 17.25 | V6: 9.08 | W6: 41.79
B7: NRIX | C7: United States | D7: Biotechnology | E7: Aug '25 Aug 31, 2025 | F7: 15.960078 | G7: -29 | H7: -37.95 | I7: -42.74 | J7: -45.72 | K7: -46.72 | L7: -48.69 | M7: -42.95 | N7: -26.77 | O7: -40.01 | P7: -45.33 | Q7: -45.22 | R7: -48.54 | S7: -54.61 | T7: -64.66 | U7: -62.86 | V7: -48.32 | W7: -91.39
B8: ECL | C8: United States | D8: Specialty Chemicals | E8: Sep '25 Sep 30, 2025 | F8: 2.6440751 | G8: 545 | H8: 489.9 | I8: 351.2 | J8: 450.6 | K8: 527 | L8: 519.2 | M8: 393 | N8: 528.2 | O8: 623.1 | P8: 641.8 | Q8: 560.7 | R8: 682.4 | S8: 726 | T8: 701 | U8: 602.6 | V8: 750.2 | W8: 799.5
B9: CHALET | C9: India | D9: N/A | E9: Sep '25 Sep 30, 2025 | F9: 17.555063 | G9: 93.77 | H9: 119.64 | I9: 87.15 | J9: 721.67 | K9: 263.96 | L9: 1174 | M9: 1279 | N9: 788.13 | O9: 855.64 | P9: 1369 | Q9: 1533 | R9: 1013 | S9: 1071 | T9: 1570 | U9: 1998 | V9: 3034 | W9: 2418
B10: QRVO | C10: United States | D10: Semiconductors | E10: Dec '25 Dec 27, 2025 | F10: 29.387435 | G10: 296.01 | H10: 344.3 | I10: 101.86 | J10: 261.56 | K10: 36.11 | L10: -71.66 | M10: -25.4 | N10: 207.85 | O10: 134.72 | P10: 88.79 | Q10: 21.41 | R10: 132.05 | S10: 53.59 | T10: 194.62 | U10: 35.85 | V10: 187.4 | W10: 192.14
B11: BUSE | C11: United States | D11: Banks - Regional | E11: Dec '25 Dec 31, 2025 | F11: 27.392491 | G11: 39.16 | H11: 35.71 | I11: 36.2 | J11: 44.14 | K11: 45.69 | L11: 46.35 | M11: 36.85 | N11: 37.49 | O11: 33.22 | P11: 34.96 | Q11: 38.42 | R11: 42.56 | S11: 37.36 | T11: -32.67 | U11: 64.51 | V11: 77.3 | W11: 77.49
B12: ECLERX | C12: India | D12: N/A | E12: Sep '25 Sep 30, 2025 | F12: 6.3533991 | G12: 1399 | H12: 1509 | I12: 1565 | J12: 1400 | K12: 1539 | L12: 1606 | M12: 1776 | N12: 1389 | O12: 1745 | P12: 1737 | Q12: 1706 | R12: 1347 | S12: 1829 | T12: 1717 | U12: 1811 | V12: 1836 | W12: 2286
B13: RNST | C13: United States | D13: Banks - Regional | E13: Dec '25 Dec 31, 2025 | F13: 26.205054 | G13: 48.42 | H13: 41.48 | I13: 50.54 | J13: 60.13 | K13: 59.16 | L13: 57.4 | M13: 35.28 | N13: 52.6 | O13: 31.91 | P13: 49.32 | Q13: 48.51 | R13: 97.38 | S13: 49.75 | T13: 51.97 | U13: 2.67 | V13: 75.27 | W13: 96.83
B14: WSBC | C14: United States | D14: Banks - Regional | E14: Dec '25 Dec 31, 2025 | F14: 23.253145 | G14: 66.29 | H14: 53.98 | I14: 53 | J14: 65.35 | K14: 64.07 | L14: 52.28 | M14: 53.94 | N14: 44.3 | O14: 43.53 | P14: 43.39 | Q14: 35.02 | R14: 44.77 | S14: 61.94 | T14: -9.67 | U14: 70.97 | V14: 103.31 | W14: 114.62
... B81: PGC | C81: United States | D81: Banks - Regional | E81: Sep '25 Sep 30, 2025 | F81: 6.3982103 | G81: 19.21 | H81: 20.72 | I81: 17.79 | J81: 27.29 | K81: 27.75 | L81: 29.51 | M81: 24.95 | N81: 18.11 | O81: 12.6 | P81: 11.62 | Q81: 12.41 | R81: 9.56 | S81: 10.75 | T81: 12.24 | U81: 10.45 | V81: 11.26 | W81: 13.61
B83: *최근에 실적 안나온 기업은 제외, 비미국 포함, 비미국은 산업 크롤링 불가

Sheet 빨간줄
B2: (단위: mil $)
B4: STX | C4: 6 | D4: 7 | E4: 8 | F4: 9 | G4: 10 | H4: 11 | I4: 12 | J4: 13 | K4: 14 | L4: 15 | M4: 16 | N4: 17 | O4: 18 | P4: 19 | Q4: 20 | R4: 21 | S4: 22
C6: 4Q21 | D6: 1Q22 | E6: 2Q22 | F6: 3Q22 | G6: 4Q22 | H6: 1Q23 | I6: 2Q23 | J6: 3Q23 | K6: 4Q23 | L6: 1Q24 | M6: 2Q24 | N6: 3Q24 | O6: 4Q24 | P6: 1Q25 | Q6: 2Q25 | R6: 3Q25 | S6: 4Q25
B7: Revenue | C7: =VLOOKUP($B$4,Revenue!$B$1:$W$81,C4,FALSE) -> 3116 | D7: =VLOOKUP($B$4,Revenue!$B$1:$W$81,D4,FALSE) -> 2802 | E7: =VLOOKUP($B$4,Revenue!$B$1:$W$81,E4,FALSE) -> 2628 | F7: =VLOOKUP($B$4,Revenue!$B$1:$W$81,F4,FALSE) -> 2035 | G7: =VLOOKUP($B$4,Revenue!$B$1:$W$81,G4,FALSE) -> 1887 | H7: =VLOOKUP($B$4,Revenue!$B$1:$W$81,H4,FALSE) -> 1860 | I7: =VLOOKUP($B$4,Revenue!$B$1:$W$81,I4,FALSE) -> 1602 | J7: =VLOOKUP($B$4,Revenue!$B$1:$W$81,J4,FALSE) -> 1454 | ... S7: =VLOOKUP($B$4,Revenue!$B$1:$W$81,S4,FALSE) -> 2825
B8: OP | C8: =VLOOKUP($B$4,'Operating Income'!$B$1:$W$81,C4,FALSE) -> 581 | D8: =VLOOKUP($B$4,'Operating Income'!$B$1:$W$81,D4,FALSE) -> 429 | E8: =VLOOKUP($B$4,'Operating Income'!$B$1:$W$81,E4,FALSE) -> 361 | F8: =VLOOKUP($B$4,'Operating Income'!$B$1:$W$81,F4,FALSE) -> 116 | G8: =VLOOKUP($B$4,'Operating Income'!$B$1:$W$81,G4,FALSE) -> -40 | H8: =VLOOKUP($B$4,'Operating Income'!$B$1:$W$81,H4,FALSE) -> 5 | I8: =VLOOKUP($B$4,'Operating Income'!$B$1:$W$81,I4,FALSE) -> 110 | J8: =VLOOKUP($B$4,'Operating Income'!$B$1:$W$81,J4,FALSE) -> -114 | ... S8: =VLOOKUP($B$4,'Operating Income'!$B$1:$W$81,S4,FALSE) -> 846
B9: Trailing 4Q OP avg. | C9: =AVERAGE(C8:C8) -> 581 | D9: =AVERAGE(C8:D8) -> 505 | E9: =AVERAGE(C8:E8) -> 457 | F9: =AVERAGE(C8:F8) -> 371.75 | G9: =AVERAGE(D8:G8) -> 216.5 | H9: =AVERAGE(E8:H8) -> 110.5 | I9: =AVERAGE(F8:I8) -> 47.75 | J9: =AVERAGE(G8:J8) -> -9.75 | K9: =AVERAGE(H8:K8) -> 23.5 | L9: =AVERAGE(I8:L8) -> 58.5 | M9: =AVERAGE(J8:M8) -> 101.75 | ... S9: =AVERAGE(P8:S8) -> 647
B10: Trailing 4Q OP sum. | C10: =SUM(C8:C8) -> 581 | D10: =SUM(C8:D8) -> 1010 | E10: =SUM(C8:E8) -> 1371 | F10: =SUM(C8:F8) -> 1487 | G10: =SUM(D8:G8) -> 866 | H10: =SUM(E8:H8) -> 442 | I10: =SUM(F8:I8) -> 191 | J10: =SUM(G8:J8) -> -39 | K10: =SUM(H8:K8) -> 94 | L10: =SUM(I8:L8) -> 234 | M10: =SUM(J8:M8) -> 407 | ... S10: =SUM(P8:S8) -> 2588
B11: Trailing OP Delta | D11: =D9/C9-1 -> -0.13080895 | E11: =E9/D9-1 -> -0.095049505 | F11: =F9/E9-1 -> -0.18654267 | G11: =G9/F9-1 -> -0.41761937 | H11: =H9/G9-1 -> -0.48960739 | I11: =I9/H9-1 -> -0.5678733 | J11: =J9/I9-1 -> -1.2041885 | K11: =K9/J9-1 -> -3.4102564 | ... S11: =S9/R9-1 -> 0.16001793
B12: opm | C12: =IFERROR(C8/C7,"-") -> 0.186457 | D12: =IFERROR(D8/D7,"-") -> 0.15310493 | E12: =IFERROR(E8/E7,"-") -> 0.13736682 | F12: =IFERROR(F8/F7,"-") -> 0.057002457 | G12: =IFERROR(G8/G7,"-") -> -0.021197668 | H12: =IFERROR(H8/H7,"-") -> 0.002688172 | I12: =IFERROR(I8/I7,"-") -> 0.06866417 | J12: =IFERROR(J8/J7,"-") -> -0.078404402 | ... S12: =IFERROR(S8/S7,"-") -> 0.29946903
B13: op yoy | C13: =C8/#REF!-1 -> #REF! | D13: =D8/#REF!-1 -> #REF! | E13: =E8/#REF!-1 -> #REF! | F13: =F8/#REF!-1 -> #REF! | G13: =G8/C8-1 -> -1.0688468 | H13: =H8/D8-1 -> -0.98834499 | I13: =I8/E8-1 -> -0.69529086 | J13: =J8/F8-1 -> -1.9827586 | K13: =K8/G8-1 -> -3.325 | L13: =L8/H8-1 -> 28 | M13: =M8/I8-1 -> 1.5727273 | N13: =N8/J8-1 -> -4.5438596 | ... S13: =S8/O8-1 -> 0.73006135
B14: 매출 YoY | G14: =G7/C7-1 -> -0.39441592 | H14: =H9/D9-1 -> -0.78118812 | I14: =I9/E9-1 -> -0.89551422 | J14: =J9/F9-1 -> -1.0262273 | K14: =K9/G9-1 -> -0.89145497 | L14: =L9/H9-1 -> -0.47058824 | M14: =M9/I9-1 -> 1.1308901 | N14: =N9/J9-1 -> -24.717949 | O14: =O9/K9-1 -> 13.053191 | ... S14: =S9/O9-1 -> 0.95912188
