Workbook

Sheet 영업이익
A1: 1 | B1: 2 | C1: 3 | D1: 4 | E1: 5 | F1: 6 | G1: 7 | H1: 8 | I1: 9 | J1: 10 | K1: 11 | L1: 12 | M1: 13 | N1: 14 | O1: 15 | P1: 16 | Q1: 17 | R1: 18 | S1: 19 | T1: 20 | U1: 21
A2: Ticker | B2: Latest_Date | C2: Growth_Rate | D2: Recent_Avg | E2: 4Q21 | F2: 1Q22 | G2: 2Q22 | H2: 3Q22 | I2: 4Q22 | J2: 1Q23 | K2: 2Q23 | L2: 3Q23 | M2: 4Q23 | N2: 1Q24 | O2: 2Q24 | P2: 3Q24 | Q2: 4Q24 | R2: 1Q25 | S2: 2Q25 | T2: 3Q25 | U2: 4Q25 | V2: Highlight_Quarters
A3: ASB | B3: ('Q4 2025', "Dec '25 Dec 31, 2025") | C3: 143.57062 | D3: 144.48 | E3: 92.05 | F3: 92.91 | G3: 110.19 | H3: 122.44 | I3: 134.09 | J3: 130.7 | K3: 110.69 | L3: 102.67 | M3: -138.01 | N3: 101.19 | O3: 102.88 | P3: 108.14 | Q3: -177.75 | R3: 121.1 | S3: 139.63 | T3: 154.29 | U3: 162.9 | V3: {'4Q22', '3Q25', '2Q25', '1Q25', '4Q25'} | W3: O
A4: CASS | B4: ('Q4 2025', "Dec '25 Dec 31, 2025") | C4: 31.991373 | D4: 13.77 | E4: 8.9 | F4: 10.5 | G4: 10.92 | H4: 11.67 | I4: 13.3 | J4: 12.22 | K4: 12.56 | L4: 13.8 | M4: 15.04 | N4: 14.08 | O4: 10.88 | P4: 15.48 | Q4: 2.53 | R4: 12.99 | S4: 10.44 | T4: 15.77 | U4: 15.88 | V4: {'4Q25', '4Q22'}
A5: EQT | B5: ('Q3 2025', "Sep '25 Sep 30, 2025") | C5: 29.635546 | D5: 663.465 | E5: -2569 | F5: 2748 | G5: -1859 | H5: 1408 | I5: 944.82 | J5: 2449 | K5: 1638 | L5: -29.89 | M5: 23.74 | N5: 875.08 | O5: 192.08 | P5: -279.5 | Q5: 15.37 | R5: 392.66 | S5: 499.14 | T5: 1140 | U5: 622.06 | V5: {'3Q25', '4Q25', '4Q23', '3Q23'}
A6: CUBI | B6: ('Q4 2025', "Dec '25 Dec 31, 2025") | C6: 27.067272 | D6: 72.1075 | E6: 115.25 | F6: 96.09 | G6: 77.55 | H6: 81.81 | I6: 35.85 | J6: 68.28 | K6: 68.34 | L6: 110.23 | M6: 83.89 | N6: 65.38 | O6: 77.12 | P6: 46.02 | Q6: 35.86 | R6: 11.89 | S6: 78.9 | T6: 100.34 | U6: 97.3 | V6: {'3Q25', '4Q25', '4Q22', '3Q24'} | W6: O
A7: AUB | B7: ('Q4 2025', "Dec '25 Dec 31, 2025") | C7: 26.416085 | D7: 84.25 | E7: 55.8 | F7: 52.96 | G7: 74.73 | H7: 69.96 | I7: 82.3 | J7: 42.95 | K7: 64.55 | L7: 65.54 | M7: 66.87 | N7: 59.87 | O7: 36.59 | P7: 92.03 | Q7: 71.3 | R7: 61.51 | S7: 17.49 | T7: 116.28 | U7: 141.72 | V7: {'3Q25', '4Q25', '4Q23', '1Q24'}
A8: SLM | B8: ('Q4 2025', "Dec '25 Dec 31, 2025") | C8: 22.730701 | D8: 248.14 | E8: 398.93 | F8: 166.17 | G8: 456.37 | H8: 104.72 | I8: -93.93 | J8: 155.86 | K8: 356.55 | L8: 40.61 | M8: 226.24 | N8: 387.49 | O8: 338.55 | P8: -59.56 | Q8: 132.17 | R8: 403.12 | S8: 87.63 | T8: 185.81 | U8: 316 | V8: {'4Q22', '2Q23', '1Q25', '2Q24', '3Q23'}
A9: EBC | B9: ('Q4 2025', "Dec '25 Dec 31, 2025") | C9: 20.501636 | D9: 24.8625 | E9: 32.15 | F9: 66.16 | G9: 0 | H9: 69.46 | I9: 48.96 | J9: -267.46 | K9: 60.36 | L9: 47.29 | M9: 33.82 | N9: 48.94 | O9: 38 | P9: -3.35 | Q9: 72.18 | R9: -183.94 | S9: 100.32 | T9: 93.97 | U9: 89.1 | V9: {'4Q22', '4Q23', '4Q25', '4Q24', '3Q23'}
A10: MBLY | B10: ('Q4 2025', "Dec '25 Dec 27, 2025") | C10: 15.364447 | D10: -110 | E10: -44 | F10: -46 | G10: 10 | H10: -25 | I10: 24 | J10: -81 | K10: -33 | L10: 8 | M10: 73 | N10: -238 | O10: -94 | P10: -112 | Q10: -81.4 | R10: -117 | S10: -74 | T10: -109 | U10: -140 | V10: {'3Q24', '1Q23', '2Q23', '1Q24', '4Q25', '4Q24', '2Q24'}
A11: SSB | B11: ('Q4 2025', "Dec '25 Dec 31, 2025") | C11: 14.040454 | D11: 260.055 | E11: 135.12 | F11: 127.41 | G11: 152.12 | H11: 171.08 | I11: 182.76 | J11: 179.02 | K11: 157.94 | L11: 157.3 | M11: 136.58 | N11: 153.52 | O11: 172.85 | P11: 186.54 | Q11: 187.34 | R11: 121.25 | S11: 282.2 | T11: 321.36 | U11: 315.41 | V11: {'3Q25', '4Q25', '2Q25'}
A12: COLB | B12: ('Q4 2025', "Dec '25 Dec 31, 2025") | C12: 14.037203 | D12: 182.0775 | E12: 117.14 | F12: 121.5 | G12: 105.14 | H12: 111.51 | I12: 112.43 | J12: -18.92 | K12: 179.08 | L12: 183.97 | M12: 127.07 | N12: 169.07 | O12: 161.09 | P12: 196 | Q12: 192.35 | R12: 123.85 | S12: 203.46 | T12: 119 | U12: 282 | V12: {'4Q25', '2Q23', '1Q24', '3Q23'}
A13: INDB | B13: ('Q4 2025', "Dec '25 Dec 31, 2025") | C13: 13.842814 | D13: 65.545 | E13: -1.12 | F13: 70.2 | G13: 82.2 | H13: 95.07 | I13: 100.29 | J13: 81.33 | K13: 82.75 | L13: 80.14 | M13: 70.92 | N13: 62.5 | O13: 66.39 | P13: 55.31 | Q13: 62.93 | R13: 57.17 | S13: 65.81 | T13: 44.39 | U13: 94.81 | V13: {'4Q25', '4Q22'}
A14: HFWA | B14: ('Q4 2025', "Dec '25 Dec 31, 2025") | C14: 13.499856 | D14: 19.6525 | E14: 24.32 | F14: 23.34 | G14: 22.56 | H14: 25.65 | I14: 27.89 | J14: 24.67 | K14: 19.87 | L14: 21.8 | M14: 6.58 | N14: 6.87 | O14: 16 | P14: 13.07 | Q14: 16.33 | R14: 16.16 | S14: 14.46 | T14: 22.31 | U14: 25.68 | V14: {'3Q25', '4Q25', '4Q24', '1Q25'}
A15: HTBK | B15: ('Q4 2025', "Dec '25 Dec 31, 2025") | C15: 11.938573 | D15: 16.9475 | E15: 19.31 | F15: 18 | G15: 20.97 | H15: 25.92 | I15: 29.49 | J15: 26.59 | K15: 23.12 | L15: 22.25 | M15: 18.46 | N15: 14.42 | O15: 13.07 | P15: 14.45 | Q15: 14.74 | R15: 16.33 | S15: 8.93 | T15: 20.56 | U15: 21.97 | V15: {'3Q25', '4Q25', '4Q22'}
A16: ACNB | B16: ('Q4 2025', "Dec '25 Dec 31, 2025") | C16: 11.924837 | D16: 11.615 | E16: 5.53 | F16: 8.23 | G16: 10.87 | H16: 13.05 | I16: 12.8 | J16: 11.42 | K16: 12.06 | L16: 11.63 | M16: 4.75 | N16: 8.53 | O16: 14.25 | P16: 9.41 | Q16: 8.23 | R16: -0.55 | S16: 14.91 | T16: 18.92 | U16: 13.18 | V16: {'3Q25', '4Q25', '4Q22'}
A17: ORI | B17: ('Q4 2025', "Dec '25 Dec 31, 2025") | C17: 11.796151 | D17: 313.7 | E17: 806 | F17: 399.5 | G17: -37.9 | H17: -103.3 | I17: 665.8 | J17: 266.1 | K17: 217.5 | L17: 80.5 | M17: 264.7 | N17: 415.2 | O17: 135.7 | P17: 448.2 | Q17: 148.2 | R17: 325.7 | S17: 278 | T17: 370.5 | U17: 280.6 | V17: {'3Q24', '2Q25', '2Q23', '1Q24', '4Q25', '3Q23'}
A18: NG | B18: ('Q4 2025', "Nov '25 Nov 30, 2025") | C18: 11.07221 | D18: -6.345 | E18: -5.01 | F18: -5.18 | G18: -5.37 | H18: -4.87 | I18: -4.69 | J18: -5.61 | K18: -5.54 | L18: -5.24 | M18: -5.4 | N18: -6.26 | O18: -7.6 | P18: -5.12 | Q18: -5.95 | R18: -4.8 | S18: -5.82 | T18: -6.28 | U18: -8.48 | V18: set()
... A59: MOFG | B59: ('Q3 2025', "Sep '25 Sep 30, 2025") | C59: -197.23053 | D59: 18.695 | E59: 20.82 | F59: 18.98 | G59: 17.34 | H59: 16.71 | I59: 23.06 | J59: 19.49 | K59: 1.78 | L59: 9.19 | M59: 11.34 | N59: 2.52 | O59: 4.23 | P59: 20.87 | Q59: -130.2 | R59: 21.11 | S59: 19.6 | T59: 12.58 | U59: 21.49 | V59: {'3Q25'}

Sheet 빨간줄
B4: aub | C4: 5 | D4: 6 | E4: 7 | F4: 8 | G4: 9 | H4: 10 | I4: 11 | J4: 12 | K4: 13 | L4: 14 | M4: 15 | N4: 16 | O4: 17 | P4: 18 | Q4: 19 | R4: 20 | S4: 21 | Y4: 금융주
Y5: Income Before Provision for Income Taxes
C7: 4Q21 | D7: 1Q22 | E7: 2Q22 | F7: 3Q22 | G7: 4Q22 | H7: 1Q23 | I7: 2Q23 | J7: 3Q23 | K7: 4Q23 | L7: 1Q24 | M7: 2Q24 | N7: 3Q24 | O7: 4Q24 | P7: 1Q25 | Q7: 2Q25 | R7: 3Q25 | S7: 4Q25 | T7: 1Q26 | U7: 2Q26 | V7: 3Q26 | W7: 4Q26
B8: Revenue
B9: OP | C9: =VLOOKUP($B$4,영업이익!$A$1:$U$58,C4,FALSE) -> 55.8 | D9: =VLOOKUP($B$4,영업이익!$A$1:$U$58,D4,FALSE) -> 52.96 | E9: =VLOOKUP($B$4,영업이익!$A$1:$U$58,E4,FALSE) -> 74.73 | F9: =VLOOKUP($B$4,영업이익!$A$1:$U$58,F4,FALSE) -> 69.96 | G9: =VLOOKUP($B$4,영업이익!$A$1:$U$58,G4,FALSE) -> 82.3 | H9: =VLOOKUP($B$4,영업이익!$A$1:$U$58,H4,FALSE) -> 42.95 | I9: =VLOOKUP($B$4,영업이익!$A$1:$U$58,I4,FALSE) -> 64.55 | J9: =VLOOKUP($B$4,영업이익!$A$1:$U$58,J4,FALSE) -> 65.54 | ... S9: =VLOOKUP($B$4,영업이익!$A$1:$U$58,S4,FALSE) -> 141.72
B10: Trailing 4Q OP avg. | C10: =AVERAGE(C9:C9) -> 55.8 | D10: =AVERAGE(C9:D9) -> 54.38 | E10: =AVERAGE(C9:E9) -> 61.163333 | F10: =AVERAGE(C9:F9) -> 63.3625 | G10: =AVERAGE(D9:G9) -> 69.9875 | H10: =AVERAGE(E9:H9) -> 67.485 | I10: =AVERAGE(F9:I9) -> 64.94 | J10: =AVERAGE(G9:J9) -> 63.835 | K10: =AVERAGE(H9:K9) -> 59.9775 | L10: =AVERAGE(I9:L9) -> 64.2075 | M10: =AVERAGE(J9:M9) -> 57.2175 | ... S10: =AVERAGE(P9:S9) -> 84.25
B11: Trailing 4Q OP sum. | C11: =SUM(C9:C9) -> 55.8 | D11: =SUM(C9:D9) -> 108.76 | E11: =SUM(C9:E9) -> 183.49 | F11: =SUM(C9:F9) -> 253.45 | G11: =SUM(D9:G9) -> 279.95 | H11: =SUM(E9:H9) -> 269.94 | I11: =SUM(F9:I9) -> 259.76 | J11: =SUM(G9:J9) -> 255.34 | K11: =SUM(H9:K9) -> 239.91 | L11: =SUM(I9:L9) -> 256.83 | M11: =SUM(J9:M9) -> 228.87 | ... S11: =SUM(P9:S9) -> 337
B12: Trailing OP Delta | D12: =D10/C10-1 -> -0.025448029 | E12: =E10/D10-1 -> 0.12473949 | F12: =F10/E10-1 -> 0.035955638 | G12: =G10/F10-1 -> 0.10455711 | H12: =H10/G10-1 -> -0.035756385 | I12: =I10/H10-1 -> -0.037712084 | J12: =J10/I10-1 -> -0.017015707 | K12: =K10/J10-1 -> -0.060429232 | ... S12: =S10/R10-1 -> 0.26416085
B13: opm | C13: =IFERROR(C9/C8,"-") -> - | D13: =IFERROR(D9/D8,"-") -> - | E13: =IFERROR(E9/E8,"-") -> - | F13: =IFERROR(F9/F8,"-") -> - | G13: =IFERROR(G9/G8,"-") -> - | H13: =IFERROR(H9/H8,"-") -> - | I13: =IFERROR(I9/I8,"-") -> - | J13: =IFERROR(J9/J8,"-") -> - | ... S13: =IFERROR(S9/S8,"-") -> -
B14: op yoy | C14: =C9/#REF!-1 -> #REF! | D14: =D9/#REF!-1 -> #REF! | E14: =E9/#REF!-1 -> #REF! | F14: =F9/#REF!-1 -> #REF! | G14: =G9/C9-1 -> 0.47491039 | H14: =H9/D9-1 -> -0.18901057 | I14: =I9/E9-1 -> -0.13622374 | J14: =J9/F9-1 -> -0.063178959 | K14: =K9/G9-1 -> -0.18748481 | L14: =L9/H9-1 -> 0.39394645 | M14: =M9/I9-1 -> -0.43315259 | N14: =N9/J9-1 -> 0.40418065 | ... S14: =S9/O9-1 -> 0.98765778
