Workbook

Sheet 실적 기업 정보
B2: 실적 기업 정보
B4: Ticker | C4: Company | D4: Date | E4: Time | F4: Quarter Ending | G4: Market Cap (mil$)
B5: GOOGL | C5: Alphabet Inc. | D5: 04-Feb-26 | E5: After Hours | F5: Dec-25 | G5: 4081510
B6: MSFT | C6: Microsoft Corporation | D6: 46050 | E6: After Hours | F6: 46381 | G6: 3417853.2
B7: AMZN | C7: Amazon.com, Inc. | D7: 05-Feb-26 | E7: After Hours | F7: Dec-25 | G7: 2558170
B8: META | C8: Meta Platforms, Inc. | D8: 46050 | E8: After Hours | F8: 46381 | G8: 1563357.2
B9: TSLA | C9: Tesla, Inc. | D9: 46050 | F9: 46381 | G9: 1455045.9
B10: WMT | C10: Walmart Inc. | D10: 19-Feb-26 | E10: Pre Market | F10: Jan-26 | G10: 1067130
B11: LLY | C11: Eli Lilly and Company | D11: 04-Feb-26 | E11: Pre Market | F11: Dec-25 | G11: 928644
B12: XOM | C12: Exxon Mobil Corporation | D12: 30-Jan-26 | E12: Pre Market | F12: 25-Dec | G12: 590910.6
B13: ASML | C13: ASML Holding N.V. | D13: 46050 | E13: Pre Market | F13: 46381 | G13: 522992.7
B14: ABBV | C14: AbbVie Inc. | D14: 04-Feb-26 | E14: Pre Market | F14: Dec-25 | G14: 394144
B15: AMD | C15: Advanced Micro Devices, Inc. | D15: 03-Feb-26 | E15: After Hours | F15: Dec-25 | G15: 385406
B16: A000660 | C16: SK hynix Inc. | D16: 46050 | F16: 46381 | G16: 354526.93
B17: CVX | C17: Chevron Corporation | D17: 30-Jan-26 | E17: Pre Market | F17: 25-Dec | G17: 350262
B18: PLTR | C18: Palantir Technologies Inc. | D18: 02-Feb-26 | E18: After Hours | F18: Dec-25 | G18: 349387.93
B19: BABA | C19: Alibaba Group Holding Limited | D19: 19-Feb-26 | F19: Dec-25 | G19: 348128
B20: KO | C20: The Coca-Cola Company | D20: 10-Feb-26 | F20: Dec-25 | G20: 339956
B21: CSCO | C21: Cisco Systems, Inc. | D21: 11-Feb-26 | E21: After Hours | F21: Jan-26 | G21: 335132
B22: AZN | C22: AstraZeneca PLC | D22: 10-Feb-26 | E22: Pre Market | F22: Dec-25 | G22: 297912
B23: 7203 | C23: Toyota Motor Corporation | D23: 06-Feb-26 | F23: Dec-25 | G23: 296741
B24: HSBA | C24: HSBC Holdings plc | D24: 18-Feb-26 | F24: Dec-25 | G24: 290025
B25: NOVN | C25: Novartis AG | D25: 04-Feb-26 | E25: Pre Market | F25: Dec-25 | G25: 284517
B26: PM | C26: Philip Morris International Inc. | D26: 06-Feb-26 | F26: Dec-25 | G26: 279323
B27: LRCX | C27: Lam Research Corporation | D27: 46050 | E27: After Hours | F27: 46381 | G27: 273739.18
B28: MRK | C28: Merck & Co., Inc. | D28: 03-Feb-26 | F28: Dec-25 | G28: 273693
B29: IBM | C29: International Business Machines Corporation | D29: 46050 | E29: After Hours | F29: 46381 | G29: 273353.96
B30: NOVO B | C30: Novo Nordisk A/S | D30: 04-Feb-26 | E30: Pre Market | F30: Dec-25 | G30: 261350
B31: AMAT | C31: Applied Materials, Inc. | D31: 12-Feb-26 | E31: After Hours | F31: Jan-26 | G31: 255983
B32: RMS | C32: Hermès International Société en commandite par actions | D32: 12-Feb-26 | F32: Dec-25 | G32: 254688
B33: OR | C33: L'Oréal S.A. | D33: 12-Feb-26 | F33: Dec-25 | G33: 248655
B34: AXP | C34: American Express Company | D34: 30-Jan-26 | E34: Pre Market | F34: 25-Dec | G34: 241588.62
B35: MCD | C35: McDonald's Corporation | D35: 11-Feb-26 | E35: Pre Market | F35: Dec-25 | G35: 232988
B36: SIE | C36: Siemens Aktiengesellschaft | D36: 12-Feb-26 | F36: Dec-25 | G36: 229885
B37: TMUS | C37: T-Mobile US, Inc. | D37: 11-Feb-26 | E37: Pre Market | F37: Dec-25 | G37: 220782
B38: SHEL | C38: Shell plc | D38: 05-Feb-26 | F38: Dec-25 | G38: 218501
B39: LIN | C39: Linde plc | D39: 05-Feb-26 | E39: Pre Market | F39: Dec-25 | G39: 213382
B40: PEP | C40: PepsiCo, Inc. | D40: 03-Feb-26 | F40: Dec-25 | G40: 212497
B41: 8306 | C41: Mitsubishi UFJ Financial Group, Inc. | D41: 04-Feb-26 | F41: Dec-25 | G41: 206552
B42: DIS | C42: The Walt Disney Company | D42: 02-Feb-26 | F42: Dec-25 | G42: 201380.58
B43: GILD | C43: Gilead Sciences, Inc. | D43: 10-Feb-26 | E43: After Hours | F43: Dec-25 | G43: 189204
B44: VZ | C44: Verizon Communications Inc. | D44: 30-Jan-26 | E44: Pre Market | F44: 25-Dec | G44: 187740.84
B45: CBA | C45: Commonwealth Bank of Australia | D45: 10-Feb-26 | F45: Dec-25 | G45: 184874
B46: APH | C46: Amphenol Corporation | D46: 46050 | E46: Pre Market | F46: 46381 | G46: 184820.14
B47: AMGN | C47: Amgen Inc. | D47: 03-Feb-26 | E47: After Hours | F47: Dec-25 | G47: 184096
B48: BHP | C48: BHP Group Limited | D48: 16-Feb-26 | F48: Dec-25 | G48: 183629
B49: AIR | C49: Airbus SE | D49: 19-Feb-26 | F49: Dec-25 | G49: 180309
B50: GEV | C50: GE Vernova Inc. | D50: 46050 | E50: Pre Market | F50: 46381 | G50: 178469.17
B51: ANET | C51: Arista Networks, Inc. | D51: 12-Feb-26 | E51: After Hours | F51: Dec-25 | G51: 173139
B52: RIO | C52: Rio Tinto Group | D52: 19-Feb-26 | F52: Dec-25 | G52: 167674
B53: T | C53: AT&T Inc. | D53: 46050 | E53: Pre Market | F53: 46381 | G53: 167240.11
B54: UBER | C54: Uber Technologies, Inc. | D54: 04-Feb-26 | E54: Pre Market | F54: Dec-25 | G54: 166330
B55: DHR | C55: Danaher Corporation | D55: 46050 | E55: Pre Market | F55: 46381 | G55: 165999.21
B56: ADI | C56: Analog Devices, Inc. | D56: 18-Feb-26 | E56: Pre Market | F56: Jan-26 | G56: 164717
B57: DE | C57: Deere & Company | D57: 19-Feb-26 | F57: Feb-26 | G57: 163436
B58: QCOM | C58: QUALCOMM Incorporated | D58: 04-Feb-26 | E58: After Hours | F58: Dec-25 | G58: 161905
B59: ULVR | C59: Unilever PLC | D59: 12-Feb-26 | F59: Dec-25 | G59: 158619
B60: TTE | C60: TotalEnergies SE | D60: 11-Feb-26 | E60: Pre Market | F60: Dec-25 | G60: 158504
B61: ENR | C61: Siemens Energy AG | D61: 11-Feb-26 | F61: Dec-25 | G61: 153697
B62: PFE | C62: Pfizer Inc. | D62: 03-Feb-26 | F62: Dec-25 | G62: 150330
B63: SAF | C63: Safran SA | D63: 13-Feb-26 | F63: Dec-25 | G63: 149707
B64: UBSG | C64: UBS Group AG | D64: 04-Feb-26 | F64: Dec-25 | G64: 149193
B65: ABI | C65: Anheuser-Busch InBev SA/NV | D65: 12-Feb-26 | F65: Dec-25 | G65: 148335
B66: SHOP | C66: Shopify Inc. | D66: 11-Feb-26 | E66: Pre Market | F66: Dec-25 | G66: 145872
B67: 9984 | C67: SoftBank Group Corp. | D67: 12-Feb-26 | F67: Dec-25 | G67: 145052
B68: BBVA | C68: Banco Bilbao Vizcaya Argentaria, S.A. | D68: 05-Feb-26 | F68: Dec-25 | G68: 145037
B69: EL | C69: EssilorLuxottica Société anonyme | D69: 11-Feb-26 | F69: Dec-25 | G69: 139685
B70: BSX | C70: Boston Scientific Corporation | D70: 04-Feb-26 | E70: Pre Market | F70: Dec-25 | G70: 138707
B71: NOW | C71: ServiceNow, Inc. | D71: 46050 | E71: After Hours | F71: 46381 | G71: 138089.32
B72: APP | C72: AppLovin Corporation | D72: 11-Feb-26 | F72: Dec-25 | G72: 137453
B73: NEM | C73: Newmont Corporation | D73: 19-Feb-26 | E73: After Hours | F73: Dec-25 | G73: 136937
B74: ETN | C74: Eaton Corporation plc | D74: 03-Feb-26 | F74: Dec-25 | G74: 136492
B75: BATS | C75: British American Tobacco p.l.c. | D75: 12-Feb-26 | F75: Dec-25 | G75: 136225
B76: UCG | C76: UniCredit S.p.A. | D76: 09-Feb-26 | F76: Dec-25 | G76: 136156
B77: 8316 | C77: Sumitomo Mitsui Financial Group, Inc. | D77: 30-Jan-26 | F77: 25-Dec | G77: 136109.76
B78: WELL | C78: Welltower Inc. | D78: 10-Feb-26 | E78: After Hours | F78: Dec-25 | G78: 134465
B79: 6758 | C79: Sony Group Corporation | D79: 05-Feb-26 | E79: Pre Market | F79: Dec-25 | G79: 133941
B80: BKNG | C80: Booking Holdings Inc. | D80: 18-Feb-26 | E80: After Hours | F80: Dec-25 | G80: 133467
B81: SPGI | C81: S&P Global Inc. | D81: 10-Feb-26 | E81: Pre Market | F81: Dec-25 | G81: 133014
B82: COP | C82: ConocoPhillips | D82: 05-Feb-26 | E82: Pre Market | F82: Dec-25 | G82: 128799
B83: MDT | C83: Medtronic plc | D83: 17-Feb-26 | E83: Pre Market | F83: Jan-26 | G83: 127548
B84: ISP | C84: Intesa Sanpaolo S.p.A. | D84: 02-Feb-26 | F84: Dec-25 | G84: 123582.78
B85: 8035 | C85: Tokyo Electron Limited | D85: 06-Feb-26 | F85: Dec-25 | G85: 123043
B86: CB | C86: Chubb Limited | D86: 03-Feb-26 | F86: Dec-25 | G86: 121828
B87: VRTX | C87: Vertex Pharmaceuticals Incorporated | D87: 12-Feb-26 | E87: After Hours | F87: Dec-25 | G87: 121257
B88: PGR | C88: The Progressive Corporation | D88: 46050 | F88: 46351 | G88: 120815.42
B89: BNP | C89: BNP Paribas SA | D89: 05-Feb-26 | F89: Dec-25 | G89: 119716
B90: PANW | C90: Palo Alto Networks, Inc. | D90: 17-Feb-26 | E90: After Hours | F90: Jan-26 | G90: 116364
B91: AI | C91: L'Air Liquide S.A. | D91: 20-Feb-26 | F91: Dec-25 | G91: 116220
B92: BMY | C92: Bristol-Myers Squibb Company | D92: 05-Feb-26 | E92: Pre Market | F92: Dec-25 | G92: 112068
B93: ARM | C93: Arm Holdings plc | D93: 04-Feb-26 | E93: After Hours | F93: Dec-25 | G93: 111787
B94: SBUX | C94: Starbucks Corporation | D94: 46050 | E94: Pre Market | F94: 46381 | G94: 111003.7
B95: ENB | C95: Enbridge Inc. | D95: 13-Feb-26 | F95: Dec-25 | G95: 109894
B96: 6857 | C96: Advantest Corporation | D96: 46050 | F96: 46381 | G96: 109823.18
B97: 8411 | C97: Mizuho Financial Group, Inc. | D97: 02-Feb-26 | F97: Dec-25 | G97: 108869.48
B98: SBIN | C98: State Bank of India | D98: 07-Feb-26 | F98: Dec-25 | G98: 108265
B99: SO | C99: The Southern Company | D99: 19-Feb-26 | F99: Dec-25 | G99: 104550
B100: CEG | C100: Constellation Energy Corporation | D100: 17-Feb-26 | F100: Dec-25 | G100: 104514
B101: ADP | C101: Automatic Data Processing, Inc. | D101: 46050 | E101: Pre Market | F101: 46381 | G101: 104295.2
B102: CME | C102: CME Group Inc. | D102: 04-Feb-26 | E102: Pre Market | F102: Dec-25 | G102: 104235
...

Sheet Revenue
B1: 1 | C1: 2 | D1: 3 | E1: 4 | F1: 5 | G1: 6 | H1: 7 | I1: 8 | J1: 9 | K1: 10 | L1: 11 | M1: 12 | N1: 13 | O1: 14 | P1: 15 | Q1: 16 | R1: 17 | S1: 18 | T1: 19 | U1: 20 | V1: 21 | W1: 22
B2: Ticker | C2: Country | D2: Industry | E2: Latest_Date | F2: Growth_Rate | G2: 4Q21 | H2: 1Q22 | I2: 2Q22 | J2: 3Q22 | K2: 4Q22 | L2: 1Q23 | M2: 2Q23 | N2: 3Q23 | O2: 4Q23 | P2: 1Q24 | Q2: 2Q24 | R2: 3Q24 | S2: 4Q24 | T2: 1Q25 | U2: 2Q25 | V2: 3Q25 | W2: 4Q25 | X2: 1Q25 | Y2: 2Q25 | Z2: 3Q25 | AA2: 4Q25
A3: 260220 | B3: ASB | C3: United States | D3: Banks - Regional | E3: Dec'25 | F3: 30.6 | G3: 270.3 | H3: 266.21 | I3: 291.61 | J3: 318.23 | K3: 330.65 | L3: 318.11 | M3: 301.36 | N3: 298.88 | O3: 101.38 | P3: 298.84 | Q3: 298.74 | R3: 308.74 | S3: 46.53 | T3: 331.72 | U3: 348.98 | V3: 370.49 | W3: 382.37 | X3: 0.034507005 | Y3: 0.050967303 | Z3: 0.059605973 | AA3: 0.30594323
A4: 260220 | B4: HBM | C4: United States | D4: Copper | E4: Dec'25 | F4: 7.2 | G4: 425.17 | H4: 378.62 | I4: 415.45 | J4: 346.17 | K4: 321.2 | L4: 295.22 | M4: 312.17 | N4: 480.46 | O4: 602.16 | P4: 525 | Q4: 425.5 | R4: 485.8 | S4: 584.9 | T4: 594.9 | U4: 536.4 | V4: 346.8 | W4: 732.9 | X4: 0.034583416 | Y4: 0.053034288 | Z4: -0.063124432 | AA4: 0.071740184
A5: 260220 | B5: RCL | C5: United States | D5: Travel Services | E5: Dec'25 | F5: 2.9 | G5: 982.25 | H5: 1059 | I5: 2184 | J5: 2993 | K5: 2603 | L5: 2886 | M5: 3523 | N5: 4160 | O5: 3331 | P5: 3728 | Q5: 4110 | R5: 4886 | S5: 3760 | T5: 3999 | U5: 4538 | V5: 5139 | W5: 4259 | X5: 0.016440184 | Y5: 0.025544614 | Z5: 0.014723855 | AA5: 0.028618949
A6: 260220 | B6: BCPC | C6: United States | D6: Specialty Chemicals | E6: Dec'25 | F6: 2.3 | G6: 213.13 | H6: 228.87 | I6: 236.69 | J6: 244.27 | K6: 232.53 | L6: 232.54 | M6: 231.25 | N6: 229.95 | O6: 228.7 | P6: 239.66 | Q6: 234.08 | R6: 239.94 | S6: 240 | T6: 250.52 | U6: 255.47 | V6: 267.56 | W6: 263.62 | X6: 0.011387467 | Y6: 0.022176374 | Z6: 0.028014159 | AA6: 0.023304228
A7: 260220 | B7: OIS | C7: United States | D7: Oil & Gas Equipment & Services | E7: Dec'25 | F7: 2.1 | G7: 161.32 | H7: 164.04 | I7: 181.83 | J7: 189.39 | K7: 202.43 | L7: 196.2 | M7: 183.53 | N7: 194.29 | O7: 208.27 | P7: 167.26 | Q7: 186.38 | R7: 174.35 | S7: 164.6 | T7: 159.94 | U7: 165.41 | V7: 165.18 | W7: 178.46 | X7: -0.010569024 | Y7: -0.030601077 | Z7: -0.013804004 | AA7: 0.021156106
A8: 260220 | B8: BN | C8: United States | D8: Asset Management | E8: Dec'25 | F8: 0.9 | G8: 22420 | H8: 22725 | I8: 23820 | J8: 24351 | K8: 24486 | L8: 23726 | M8: 24069 | N8: 25250 | O8: 24947 | P8: 23593 | Q8: 23875 | R8: 20807 | S8: 20460 | T8: 18463 | U8: 18550 | V8: 19460 | W8: 21184 | X8: -0.057812588 | Y8: -0.063692363 | Z8: -0.01720746 | AA8: 0.009410786
A9: 260220 | B9: AAL | C9: United States | D9: Airlines | E9: Dec'25 | F9: 0.6 | G9: 9427 | H9: 8899 | I9: 13422 | J9: 13462 | K9: 13188 | L9: 12189 | M9: 14055 | N9: 13482 | O9: 13062 | P9: 12570 | Q9: 14334 | R9: 13647 | S9: 13660 | T9: 12551 | U9: 14392 | V9: 13691 | W9: 13999 | X9: -0.00035048237 | Y9: 0.0010702687 | Z9: 0.00081105991 | AA9: 0.0062437838
A10: 260220 | B10: LAMR | C10: United States | D10: REIT - Specialty | E10: Dec'25 | F10: 0.6 | G10: 496.82 | H10: 452.13 | I10: 518.21 | J10: 528.94 | K10: 537.17 | L10: 471.51 | M10: 541.59 | N10: 543.31 | O10: 558.28 | P10: 497.59 | Q10: 565.26 | R10: 566.78 | S10: 582.57 | T10: 505.81 | U10: 579.14 | V10: 585.54 | W10: 595.93 | X10: 0.0037157581 | Y10: 0.0062510696 | Z10: 0.0083963658 | AA10: 0.0059297134
A11: 260220 | B11: RSG | C11: United States | D11: Waste Management | E11: Dec'25 | F11: 0.5 | G11: 2953 | H11: 2970 | I11: 3414 | J11: 3598 | K11: 3530 | L11: 3581 | M11: 3726 | N11: 3826 | O11: 3832 | P11: 3862 | Q11: 4048 | R11: 4076 | S11: 4046 | T11: 4009 | U11: 4235 | V11: 4212 | W11: 4135 | X11: 0.0091691617 | Y11: 0.011558193 | Z11: 0.0083099108 | AA11: 0.0053932857
A12: 260220 | B12: EA | C12: United States | D12: Electronic Gaming & Multimedia | E12: Sep'26 | F12: 0.2 | G12: 1789 | H12: 1825 | I12: 1767 | J12: 1904 | K12: 1881 | L12: 1874 | M12: 1924 | N12: 1914 | O12: 1945 | P12: 1779 | Q12: 1660 | R12: 2025 | S12: 1883 | T12: 1895 | U12: 1671 | V12: 1839 | W12: 1901 | X12: 0.015788757 | Y12: 0.0014739381 | Z12: -0.024886272 | AA12: 0.0024698134
A13: 260220 | B13: CCOI | C13: United States | D13: Telecom Services | E13: Dec'25 | F13: -1.2 | G13: 142.91 | H13: 145.48 | I13: 145.05 | J13: 145.9 | K13: 147.88 | L13: 149.39 | M13: 228.81 | N13: 260.83 | O13: 251.7 | P13: 245.67 | Q13: 241.24 | R13: 237.4 | S13: 231.39 | T13: 226.85 | U13: 226.25 | V13: 222.75 | W13: 220.72 | X13: -0.019692372 | Y13: -0.015999915 | Z13: -0.015891267 | AA13: -0.011760945
A14: 260220 | B14: WU | C14: United States | D14: Credit Services | E14: Dec'25 | F14: -1.2 | G14: 1285 | H14: 1156 | I14: 1138 | J14: 1090 | K14: 1092 | L14: 1037 | M14: 1170 | N14: 1098 | O14: 1052 | P14: 1049 | Q14: 1066 | R14: 1036 | S14: 1058 | T14: 983.6 | U14: 1026 | V14: 1033 | W14: 1008 | X14: -0.015538133 | Y14: -0.0096534415 | Z14: -0.00073106541 | AA14: -0.012193338
... A17: 260220 | B17: AD | C17: United States | D17: Telecom Services | E17: Dec'25 | F17: -47.7 | G17: 1069 | H17: 1010 | I17: 1027 | J17: 1083 | K17: 1049 | L17: 986 | M17: 957 | N17: 963 | O17: 1000 | P17: 950 | Q17: 0 | R17: 25.74 | S17: 971 | T17: 891 | U17: 0 | V17: 47.12 | W17: 60.33 | X17: -0.030307077 | Y17: 0 | Z17: 0.011325712 | AA17: -0.47701035
A18: 260220 | B18: 8987 | C18: Japan | D18: Japan Excellent, Inc. | E18: H2 2025 | F18: -4.5024388 | G18: 10666 | I18: 11065 | K18: 10672 | M18: 13763 | O18: 10799 | Q18: 11460 | S18: 12752 | U18: 11235 | W18: 11672 | X18: -0.093762723 | Y18: 0.087739791 | Z18: -0.0092929126 | AA18: -0.045024388
A19: 260220 | B19: 2350 | C19: Hong Kong | D19: Saudi Kayan Petrochemical Company | E19: H1 2026 | F19: 15.090926 | G19: 261.8 | I19: 369.71 | K19: 406.14 | M19: 346.41 | O19: 360.06 | Q19: 268.01 | S19: 220.28 | U19: 409.9 | W19: 315.38 | X19: -0.11097428 | Y19: -0.22255481 | Z19: 0.29058551 | AA19: 0.15090926
A20: 260219 | B20: INSM | C20: United States | D20: Biotechnology | E20: Dec'25 | F20: 35.7 | G20: 56.12 | H20: 53.11 | I20: 65.22 | J20: 67.73 | K20: 59.3 | L20: 65.21 | M20: 77.23 | N20: 79.07 | O20: 83.69 | P20: 75.5 | Q20: 90.34 | R20: 93.43 | S20: 104.44 | T20: 92.82 | U20: 107.42 | V20: 142.34 | W20: 263.84 | X20: 0.047620357 | Y20: 0.044825867 | Z20: 0.12285549 | AA20: 0.3565836
A21: 260219 | B21: SII | C21: United States | D21: Asset Management | E21: Dec'25 | F21: 31.8 | G21: 47.29 | H21: 42.46 | I21: 30.55 | J21: 36.01 | K21: 36.16 | L21: 39.92 | M21: 36.28 | N21: 34.47 | O21: 40.69 | P21: 41.54 | Q21: 47.99 | R21: 46.51 | S21: 42.62 | T21: 43.36 | U21: 65.17 | V21: 65.11 | W21: 111.43 | X21: 0.010186947 | Y21: 0.095190603 | Z21: 0.094100981 | AA21: 0.31818182
A22: 260219 | B22: AG | C22: United States | D22: Silver | E22: Dec'25 | F22: 30.2 | G22: 204.88 | H22: 156.84 | I22: 159.44 | J22: 159.75 | K22: 148.19 | L22: 156.95 | M22: 146.69 | N22: 133.21 | O22: 136.95 | P22: 106.01 | Q22: 136.17 | R22: 146.09 | S22: 172.34 | T22: 243.94 | U22: 264.23 | V22: 285.06 | W22: 463.92 | X22: 0.24603557 | Y22: 0.18332522 | Z22: 0.16812243 | AA22: 0.30197707
A23: 260219 | B23: MDGL | C23: United States | D23: Biotechnology | E23: Dec'25 | F23: 29.4 | G23: 0 | H23: 0 | I23: 0 | J23: 0 | K23: 0 | L23: 0 | M23: 0 | N23: 0 | O23: 0 | P23: 0 | Q23: 14.64 | R23: 62.18 | S23: 103.32 | T23: 137.25 | U23: 212.8 | V23: 287.27 | W23: 321.08 | X23: 0.76190741 | Y23: 0.62434229 | Z23: 0.43660169 | AA23: 0.29401599
A24: 260219 | B24: CG | C24: United States | D24: Asset Management | E24: Dec'25 | F24: 25.7 | G24: 1917 | H24: 1511 | I24: 981.5 | J24: 1008 | K24: 616.5 | L24: 735.6 | M24: 329.3 | N24: 582.7 | O24: 773.4 | P24: 533 | Q24: 887.2 | R24: 2443 | S24: 876.8 | T24: 831.8 | U24: 1374 | V24: 125.6 | W24: 1700 | X24: 0.063037975 | Y24: 0.096610304 | Z24: -0.41939337 | AA24: 0.25659248
A25: 260219 | B25: CHH | C25: United States | D25: Lodging | E25: Dec'25 | F25: 21.5 | G25: 140.18 | H25: 131.09 | I25: 178.59 | J25: 194.16 | K25: 172.66 | L25: 162.18 | M25: 213.12 | N25: 207.92 | O25: 176.79 | P25: 202.96 | Q25: 258.89 | R25: 256.14 | S25: 188.97 | T25: 209.44 | U25: 259.09 | V25: 277.91 | W25: 390.15 | X25: 0.0071447473 | Y25: 0.00021895253 | Z25: 0.023827766 | AA25: 0.21507147
A26: 260219 | B26: LMND | C26: United States | D26: Insurance - Property & Casualty | E26: Dec'25 | F26: 12 | G26: 41 | H26: 44.3 | I26: 50 | J26: 74 | K26: 88.4 | L26: 95.2 | M26: 104.6 | N26: 115.2 | O26: 114.8 | P26: 119.1 | Q26: 122 | R26: 136.6 | S26: 148.8 | T26: 151.2 | U26: 164.1 | V26: 194.3 | W26: 228.1 | X26: 0.060968661 | Y26: 0.075366989 | Z26: 0.096054603 | AA26: 0.1204435
A27: 260219 | B27: FIX | C27: United States | D27: Engineering & Construction | E27: Dec'25 | F27: 9.3 | G27: 856.08 | H27: 885.22 | I27: 1018 | J27: 1120 | K27: 1117 | L27: 1175 | M27: 1296 | N27: 1378 | O27: 1358 | P27: 1537 | Q27: 1810 | R27: 1812 | S27: 1868 | T27: 1831 | U27: 2173 | V27: 2451 | W27: 2646 | X27: 0.041838622 | Y27: 0.04958339 | Z27: 0.083159813 | AA27: 0.09347591
A28: 260219 | B28: GH | C28: United States | D28: Diagnostics & Research | E28: Dec'25 | F28: 8.8 | G28: 108.11 | H28: 96.1 | I28: 109.14 | J28: 117.4 | K28: 126.89 | L28: 128.71 | M28: 137.15 | N28: 143.03 | O28: 155.05 | P28: 168.49 | Q28: 177.24 | R28: 191.48 | S28: 201.81 | T28: 203.47 | U28: 232.09 | V28: 265.2 | W28: 281.27 | X28: 0.047332954 | Y28: 0.070865633 | Z28: 0.088942511 | AA28: 0.088037493
A29: 260219 | B29: LAUR | C29: United States | D29: Education & Training Services | E29: Dec'25 | F29: 7.5 | G29: 296.73 | H29: 209.56 | I29: 385.38 | J29: 301 | K29: 346.33 | L29: 251.26 | M29: 462.07 | N29: 361.53 | O29: 409.43 | P29: 275.37 | Q29: 499.25 | R29: 368.63 | S29: 423.39 | T29: 236.16 | U29: 524.16 | V29: 400.22 | W29: 541.4 | X29: -0.025028086 | Y29: 0.01630844 | Z29: 0.020349923 | AA29: 0.074504555
A30: 260219 | B30: PRU | C30: United States | D30: Insurance - Life | E30: Dec'25 | F30: 6.7 | G30: 16424 | H30: 11855 | I30: 11392 | J30: 20201 | K30: 11135 | L30: 17045 | M30: 13498 | N30: 8352 | O30: 15084 | P30: 23509 | Q30: 14883 | R30: 19490 | S30: 12314 | T30: 13470 | U30: 13726 | V30: 17879 | W30: 16158 | X30: -0.14301385 | Y30: -0.019233007 | Z30: -0.027305085 | AA30: 0.066981477
A31: 260219 | B31: TALK | C31: United States | D31: Health Information Services | E31: Dec'25 | F31: 6.7 | G31: 29.17 | H31: 30.15 | I31: 29.84 | J31: 29.33 | K31: 30.24 | L31: 33.34 | M31: 35.65 | N31: 38.65 | O31: 42.42 | P31: 45.42 | Q31: 46.06 | R31: 47.4 | S31: 48.72 | T31: 52.18 | U31: 54.31 | V31: 59.38 | W31: 63 | X31: 0.036034115 | Y31: 0.042447006 | Z31: 0.059128375 | AA31: 0.066545505
A32: 260219 | B32: IRTC | C32: United States | D32: Medical Devices | E32: Dec'25 | F32: 6.3 | G32: 81.8 | H32: 92.38 | I32: 102.05 | J32: 103.88 | K32: 112.62 | L32: 111.44 | M32: 124.13 | N32: 124.6 | O32: 132.51 | P32: 131.93 | Q32: 148.05 | R32: 147.54 | S32: 164.33 | T32: 158.68 | U32: 186.69 | V32: 192.88 | W32: 208.89 | X32: 0.045197263 | Y32: 0.062463628 | Z32: 0.068985454 | AA32: 0.063423382
A33: 260219 | B33: HG | C33: United States | D33: Insurance - Reinsurance | E33: Dec'25 | F33: 6 | H33: 246.31 | I33: 493.69 | J33: 225.04 | K33: 261.85 | L33: 324.43 | M33: 360.58 | N33: 394.83 | O33: 497.39 | P33: 660.77 | Q33: 589.72 | R33: 518.82 | S33: 563.84 | T33: 771.31 | U33: 745.28 | V33: 665.03 | W33: 729.89 | X33: 0.047378008 | Y33: 0.063657829 | Z33: 0.056250842 | AA33: 0.060481668
A34: 260219 | B34: NEM | C34: United States | D34: Gold | E34: Dec'25 | F34: 5.4 | G34: 3390 | H34: 3023 | I34: 3058 | J34: 2634 | K34: 3200 | L34: 2679 | M34: 2683 | N34: 2493 | O34: 3957 | P34: 4023 | Q34: 4402 | R34: 4605 | S34: 5652 | T34: 5010 | U34: 5317 | V34: 5524 | W34: 6818 | X34: 0.052831603 | Y34: 0.046519904 | Z34: 0.044646327 | AA34: 0.054224992
A35: 260219 | B35: APPN | C35: United States | D35: Software - Infrastructure | E35: Dec'25 | F35: 5.2 | G35: 104.99 | H35: 114.27 | I35: 110.06 | J35: 117.88 | K35: 125.79 | L35: 135.24 | M35: 127.72 | N35: 137.09 | O35: 145.32 | P35: 149.84 | Q35: 146.45 | R35: 154.05 | S35: 166.69 | T35: 166.43 | U35: 170.64 | V35: 187 | W35: 202.87 | X35: 0.026886861 | Y35: 0.038177457 | Z35: 0.050090452 | AA35: 0.052377092
A36: 260219 | B36: PWR | C36: United States | D36: Engineering & Construction | E36: Dec'25 | F36: 4.7 | G36: 3924 | H36: 3966 | I36: 4232 | J36: 4460 | K36: 4417 | L36: 4429 | M36: 5049 | N36: 5621 | O36: 5784 | P36: 5032 | Q36: 5594 | R36: 6493 | S36: 6553 | T36: 6233 | U36: 6773 | V36: 7631 | W36: 7842 | X36: 0.050735046 | Y36: 0.047400796 | Z36: 0.043681867 | AA36: 0.047407135
A37: 260219 | B37: WK | C37: United States | D37: Software - Application | E37: Dec'25 | F37: 4.6 | G37: 120.78 | H37: 129.67 | I37: 131.55 | J37: 132.85 | K37: 143.8 | L37: 150.19 | M37: 155.02 | N37: 158.18 | O37: 166.65 | P37: 175.67 | Q37: 177.5 | R37: 185.62 | S37: 199.89 | T37: 206.28 | U37: 215.19 | V37: 224.17 | W37: 238.94 | X37: 0.041438783 | Y37: 0.048993228 | Z37: 0.047770701 | AA37: 0.04618405
A38: 260219 | B38: PRDO | C38: United States | D38: Education & Training Services | E38: Dec'25 | F38: 4.3 | G38: 159.86 | H38: 182.96 | I38: 167.68 | J38: 168.42 | K38: 176.15 | L38: 195.6 | M38: 186.56 | N38: 179.92 | O38: 147.92 | P38: 168.26 | Q38: 166.74 | R38: 169.83 | S38: 176.43 | T38: 213 | U38: 209.58 | V38: 211.87 | W38: 211.64 | X38: 0.06567243 | Y38: 0.059008264 | Z38: 0.054679777 | AA38: 0.043421961
A39: 260219 | B39: WEAV | C39: United States | D39: Health Information Services | E39: Dec'25 | F39: 4 | G39: 31.84 | H39: 33.27 | I39: 34.93 | J39: 36.23 | K39: 37.69 | L39: 39.57 | M39: 41.67 | N39: 43.54 | O39: 45.69 | P39: 47.17 | Q39: 50.59 | R39: 52.39 | S39: 54.17 | T39: 55.81 | U39: 58.47 | V39: 61.34 | W39: 63.4 | X39: 0.042286609 | Y39: 0.037002254 | Z39: 0.040527078 | AA39: 0.040167109
A40: 260219 | B40: LZ | C40: United States | D40: Specialty Business Services | E40: Dec'25 | F40: 3.9 | G40: 142.14 | H40: 155.43 | I40: 162.65 | J40: 155.28 | K40: 146.63 | L40: 165.94 | M40: 168.85 | N40: 167.27 | O40: 158.66 | P40: 174.21 | Q40: 177.36 | R40: 168.6 | S40: 161.71 | T40: 183.11 | U40: 192.51 | V40: 190.16 | W40: 190.27 | X40: 0.01305215 | Y40: 0.021931729 | Z40: 0.030541272 | AA40: 0.039258272
A41: 260219 | B41: SVV | C41: United States | D41: Specialty Retail | E41: Dec'25 | F41: 3.9 | G41: 344.83 | H41: 327.47 | I41: 364.67 | J41: 378.29 | K41: 366.8 | L41: 345.68 | M41: 379.1 | N41: 392.7 | O41: 382.77 | P41: 354.17 | Q41: 386.66 | R41: 394.8 | S41: 401.99 | T41: 370.15 | U41: 417.21 | V41: 426.94 | W41: 464.67 | X41: 0.010392685 | Y41: 0.019664006 | Z41: 0.020288483 | AA41: 0.038780169
A42: 260219 | B42: AIR | C42: United States | D42: Aerospace & Defense | E42: Jun'26 | F42: 3.8 | G42: 436.6 | H42: 452.2 | I42: 476.1 | J42: 446.3 | K42: 469.8 | L42: 521.1 | M42: 553.3 | N42: 549.7 | O42: 545.4 | P42: 567.3 | Q42: 656.5 | R42: 661.7 | S42: 686.1 | T42: 678.2 | U42: 754.5 | V42: 739.6 | W42: 795.3 | X42: 0.043124903 | Y42: 0.036533085 | Z42: 0.028016544 | AA42: 0.038203191
A43: 260219 | B43: GRAL | C43: United States | D43: Diagnostics & Research | E43: Dec'25 | F43: 3.8 | G43: 0 | H43: 0 | I43: 0 | J43: 0.33 | K43: 0.33 | L43: 19.64 | M43: 22.41 | N43: 20.72 | O43: 30.33 | P43: 26.72 | Q43: 31.97 | R43: 28.65 | S43: 38.25 | T43: 31.84 | U43: 35.54 | V43: 36.19 | W43: 43.6 | X43: 0.040767577 | Y43: 0.027312371 | Z43: 0.056151326 | AA43: 0.037723875
A44: 260219 | B44: FNF | C44: United States | D44: Insurance - Specialty | E44: Dec'25 | F44: 3.1 | G44: 4796 | H44: 3171 | I44: 2644 | J44: 3214 | K44: 2578 | L44: 2478 | M44: 3088 | N44: 2785 | O44: 3438 | P44: 3299 | Q44: 3189 | R44: 3603 | S44: 3622 | T44: 2751 | U44: 3656 | V44: 4029 | W44: 4051 | X44: -0.03996208 | Y44: 0.035472845 | Z44: 0.03125 | AA44: 0.030516432
A45: 260219 | B45: RIO | C45: United States | D45: Other Industrial Metals & Mining | E45: H2 2025 | F45: 3.1 | G45: 30412 | I45: 29775 | K45: 25779 | M45: 26667 | O45: 27374 | Q45: 26802 | S45: 26856 | U45: 26873 | W45: 30765 | X45: -0.02712715 | Y45: 0.010101105 | Z45: 0.0019127383 | AA45: 0.031425791
A46: 260219 | B46: EPAM | C46: United States | D46: Information Technology Services | E46: Dec'25 | F46: 3 | G46: 1107 | H46: 1172 | I46: 1195 | J46: 1227 | K46: 1231 | L46: 1211 | M46: 1170 | N46: 1152 | O46: 1157 | P46: 1165 | Q46: 1147 | R46: 1168 | S46: 1248 | T46: 1302 | U46: 1353 | V46: 1394 | W46: 1408 | X46: 0.028976311 | Y46: 0.042343268 | Z46: 0.044567147 | AA46: 0.030205777
A47: 260219 | B47: NABL | C47: United States | D47: Information Technology Services | E47: Dec'25 | F47: 2.8 | G47: 89.5 | H47: 90.86 | I47: 91.63 | J47: 93.53 | K47: 95.76 | L47: 99.82 | M47: 106.08 | N47: 107.57 | O47: 108.42 | P47: 113.75 | Q47: 119.45 | R47: 116.44 | S47: 116.51 | T47: 118.2 | U47: 131.25 | V47: 131.71 | W47: 130.27 | X47: 0.0095462834 | Y47: 0.025074373 | Z47: 0.031654229 | AA47: 0.027648844
A48: 260219 | B48: CNP | C48: United States | D48: Utilities - Regulated Electric | E48: Dec'25 | F48: 2.7 | G48: 0 | H48: 2763 | I48: 1944 | J48: 1903 | K48: 2711 | L48: 2779 | M48: 1875 | N48: 1860 | O48: 2182 | P48: 2620 | Q48: 1905 | R48: 1856 | S48: 2262 | T48: 2920 | U48: 1944 | V48: 1988 | W48: 2505 | X48: 0.03471017 | Y48: 0.0043609527 | Z48: 0.014696059 | AA48: 0.026662278
A49: 260219 | B49: LYV | C49: United States | D49: Entertainment | E49: Dec'25 | F49: 2.6 | G49: 2703 | H49: 1803 | I49: 4434 | J49: 6154 | K49: 4291 | L49: 3127 | M49: 5626 | N49: 8155 | O49: 5819 | P49: 3800 | Q49: 6023 | R49: 7651 | S49: 5682 | T49: 3382 | U49: 7007 | V49: 8499 | W49: 6314 | X49: -0.018051477 | Y49: 0.043275574 | Z49: 0.035747407 | AA49: 0.025722426
A50: 260219 | B50: NMM | C50: United States | D50: Marine Shipping | E50: Dec'25 | F50: 2.5 | G50: 268.15 | H50: 236.62 | I50: 280.66 | J50: 322.39 | K50: 370.86 | L50: 309.52 | M50: 346.94 | N50: 323.18 | O50: 327.25 | P50: 318.56 | Q50: 342.16 | R50: 340.84 | S50: 332.52 | T50: 304.11 | U50: 327.56 | V50: 346.92 | W50: 365.55 | X50: -0.010831434 | Y50: -0.011063707 | Z50: 0.0046588967 | AA50: 0.025192394
A51: 260219 | B51: VICR | C51: United States | D51: Electronic Components | E51: Dec'25 | F51: 2.5 | G51: 90.28 | H51: 88.28 | I51: 102.19 | J51: 103.12 | K51: 105.49 | L51: 97.82 | M51: 106.75 | N51: 107.84 | O51: 92.65 | P51: 83.87 | Q51: 85.85 | R51: 93.17 | S51: 96.17 | T51: 93.97 | U51: 141.05 | V51: 110.42 | W51: 107.26 | X51: 0.028129004 | Y51: 0.14952866 | Z51: 0.040649449 | AA51: 0.025112656
A52: 260219 | B52: DE | C52: United States | D52: Farm & Heavy Construction Machinery | E52: Mar'26 | F52: 2.4 | G52: 9569 | H52: 13370 | I52: 14102 | J52: 15522 | K52: 12652 | L52: 17387 | M52: 15801 | N52: 15383 | O52: 12185 | P52: 15235 | Q52: 13152 | R52: 10960 | S52: 8508 | T52: 12763 | U52: 12018 | V52: 12338 | W52: 9611 | X52: -0.051656044 | Y52: -0.02498733 | Z52: 0.031141947 | AA52: 0.024174283
A53: 260219 | B53: MTUS | C53: United States | D53: Steel | E53: Dec'25 | F53: 2.4 | G53: 338.3 | H53: 352 | I53: 415.7 | J53: 316.8 | K53: 245.4 | L53: 323.5 | M53: 356.6 | N53: 354.2 | O53: 328.1 | P53: 321.6 | Q53: 294.7 | R53: 227.2 | S53: 240.5 | T53: 280.5 | U53: 304.6 | V53: 305.9 | W53: 267.3 | X53: -0.037915129 | Y53: 0.0094927606 | Z53: 0.07475304 | AA53: 0.023685373
A54: 260219 | B54: CWST | C54: United States | D54: Waste Management | E54: Dec'25 | F54: 2.3 | G54: 241.84 | H54: 234.03 | I54: 283.67 | J54: 295.27 | K54: 272.13 | L54: 262.6 | M54: 289.65 | N54: 352.74 | O54: 359.57 | P54: 341.01 | Q54: 377.16 | R54: 411.63 | S54: 427.49 | T54: 417.1 | U54: 465.33 | V54: 485.35 | W54: 469.06 | X54: 0.048860521 | Y54: 0.05398009 | Z54: 0.042821876 | AA54: 0.023155291
A55: 260219 | B55: NICE | C55: United States | D55: Software - Application | E55: Dec'25 | F55: 2.3 | G55: 519.69 | H55: 527.43 | I55: 530.58 | J55: 554.72 | K55: 568.56 | L55: 571.86 | M55: 581.11 | N55: 601.34 | O55: 623.19 | P55: 659.31 | Q55: 664.4 | R55: 689.96 | S55: 721.6 | T55: 700.19 | U55: 726.71 | V55: 732 | W55: 786.5 | X55: 0.014945508 | Y55: 0.022444753 | Z55: 0.014810848 | AA55: 0.022530811
A56: 260219 | B56: SO | C56: United States | D56: Utilities - Regulated Electric | E56: Dec'25 | F56: 2.2 | G56: 5767 | H56: 6648 | I56: 7206 | J56: 8378 | K56: 7047 | L56: 6480 | M56: 5748 | N56: 6980 | O56: 6045 | P56: 6646 | Q56: 6463 | R56: 7274 | S56: 6341 | T56: 7775 | U56: 6973 | V56: 7823 | W56: 6981 | X56: 0.04224667 | Y56: 0.018310415 | Z56: 0.019356204 | AA56: 0.022136137
A57: 260219 | B57: GATX | C57: United States | D57: Rental & Leasing Services | E57: Dec'25 | F57: 2.1 | G57: 321 | H57: 316.6 | I57: 312.7 | J57: 321 | K57: 322.7 | L57: 338.9 | M57: 343.2 | N57: 360.1 | O57: 368.7 | P57: 379.9 | Q57: 386.7 | R57: 405.4 | S57: 413.5 | T57: 421.6 | U57: 430.5 | V57: 439.3 | W57: 449 | X57: 0.026300851 | Y57: 0.026917404 | Z57: 0.020287253 | AA57: 0.020822336
... A109: 260219 | B109: BURE | C109: Sweden | D109: Bure Equity AB (publ) | E109: Dec'25 | F109: -13.3 | G109: 1301 | H109: -6603 | I109: -2555 | J109: -2434 | K109: 2419 | L109: 2434 | M109: 750 | N109: -1363 | O109: 2990 | P109: 3002 | Q109: 1780 | R109: 2287 | S109: -1260 | T109: -2619 | U109: -1225 | V109: -205 | W109: -552 | X109: -0.96763643 | Y109: -15.984043 | Z109: 0.88462904 | AA109: -0.13335845
A110: 260219 | B110: 5101 | C110: Japan | D110: The Yokohama Rubber Company, Limited | E110: Dec'25 | F110: 3.9 | G110: 210354 | H110: 185590 | I110: 205892 | J110: 224281 | K110: 244713 | L110: 204314 | M110: 238850 | N110: 249341 | O110: 292828 | P110: 252419 | Q110: 272864 | R110: 257623 | S110: 311840 | T110: 275118 | U110: 304083 | V110: 297988 | W110: 357770 | X110: 0.02073449 | Y110: 0.02793784 | Z110: 0.035140824 | AA110: 0.038628158
A111: 260219 | B111: 3040 | C111: Japan | D111: Qassim Cement Company | E111: Dec'25 | F111: 2.6 | G111: 4672 | H111: 4837 | I111: 4037 | J111: 5613 | K111: 5270 | L111: 4670 | M111: 4130 | N111: 4877 | O111: 5381 | P111: 4575 | Q111: 3967 | R111: 4702 | S111: 5362 | T111: 4585 | U111: 4125 | V111: 5194 | W111: 5858 | X111: 0.00053746103 | Y111: 0.0084873227 | Z111: 0.026206456 | AA111: 0.025744835
A112: 260219 | B112: NK | C112: France | D112: Imerys S.A. | E112: Dec'25 | F112: -0.9 | G112: 0 | H112: 1211 | I112: 0 | J112: 1116 | K112: 1024 | L112: 997 | M112: 985.4 | N112: 918 | O112: 894.4 | P112: 926 | Q112: 992.6 | R112: 855 | S112: 831.3 | T112: 871 | U112: 885.6 | V112: 827 | W112: 800.7 | X112: -0.015257011 | Y112: -0.030141694 | Z112: -0.0081326788 | AA112: -0.0089607309
A113: 260218 | B113: IMG | C113: United States | D113: Packaged Foods | E113: Dec'25 | F113: 2681.1 | G113: 0.48 | H113: 1.02 | I113: 0.72 | J113: 0.77 | K113: 0.6 | L113: 1.14 | M113: 0.78 | N113: 0.27 | O113: 0.55 | P113: 0.97 | Q113: 0.32 | R113: 0.37 | S113: 0.29 | T113: 0.02 | U113: 0 | V113: 0.06 | W113: 10.21 | X113: -0.48717949 | Y113: -0.32 | Z113: -0.45588235 | AA113: 26.810811
A114: 260218 | B114: ADAM | C114: United States | D114: REIT - Mortgage | E114: Dec'25 | F114: 49.3 | G114: 68.7 | H114: -18.78 | I114: 4.79 | J114: -60.43 | K114: 5.29 | L114: 71.26 | M114: 33.25 | N114: -4.35 | O114: 110.05 | P114: 28.85 | Q114: 32.27 | R114: 81.49 | S114: 0.69 | T114: 78.17 | U114: 45.12 | V114: 93.08 | W114: 107.72 | X114: 0.34417306 | Y114: 0.06671166 | Z114: 0.056407261 | AA114: 0.49308947
A115: 260218 | B115: JXN | C115: United States | D115: Insurance - Life | E115: Dec'25 | F115: 34.9 | G115: 1725 | H115: 2221 | I115: 6694 | J115: 2962 | K115: -2014 | L115: -764 | M115: 380 | N115: 2585 | O115: 882 | P115: -322 | Q115: 1270 | R115: 2157 | S115: 245 | T115: 3750 | U115: -433 | V115: 1435 | W115: 1988 | X115: 1.2155224 | Y115: -0.22945298 | Z115: -0.12624585 | AA115: 0.34880929
A116: 260218 | B116: VRSK | C116: United States | D116: Consulting Services | E116: Dec'25 | F116: 34 | G116: 0 | H116: 643.6 | I116: 612.8 | J116: 610.1 | K116: 0 | L116: 651.6 | M116: 675 | N116: 677.6 | O116: 677.2 | P116: 704 | Q116: 716.8 | R116: 725.3 | S116: 0 | T116: 753 | U116: 772.6 | V116: 768.3 | W116: 778.8 | X116: 0.022832114 | Y116: 0.025420254 | Z116: 0.01910347 | AA116: 0.33950913
A117: 260218 | B117: IAG | C117: United States | D117: Gold | E117: Dec'25 | F117: 27.7 | G117: 0 | H117: 265 | I117: 232.1 | J117: 254.5 | K117: 207.2 | L117: 226.2 | M117: 238.8 | N117: 224.5 | O117: 297.6 | P117: 338.9 | Q117: 385.3 | R117: 438.9 | S117: 469.9 | T117: 477.1 | U117: 580.9 | V117: 706.7 | W117: 1088 | X117: 0.084629516 | Y117: 0.1104336 | Z117: 0.13616026 | AA117: 0.27660431
A118: 260218 | B118: CDE | C118: United States | D118: Gold | E118: Dec'25 | F118: 21.7 | G118: 207.88 | H118: 188.4 | I118: 204.12 | J118: 182.99 | K118: 210.12 | L118: 187.3 | M118: 177.24 | N118: 194.58 | O118: 262.09 | P118: 213.06 | Q118: 222.03 | R118: 313.48 | S118: 305.44 | T118: 360.06 | U118: 480.65 | V118: 554.57 | W118: 674.85 | X118: 0.13946737 | Y118: 0.21533543 | Z118: 0.165172 | AA118: 0.21720801
A119: 260218 | B119: RGLD | C119: United States | D119: Gold | E119: Dec'25 | F119: 20.6 | G119: 166.16 | H119: 160.13 | I119: 145.02 | J119: 130.31 | K119: 160.72 | L119: 168.4 | M119: 142.77 | N119: 136.95 | O119: 150.31 | P119: 147.45 | Q119: 172.52 | R119: 192.32 | S119: 200.49 | T119: 191.68 | U119: 207.44 | V119: 249.65 | W119: 375.32 | X119: 0.062052807 | Y119: 0.046128849 | Z119: 0.072392762 | AA119: 0.20586157
A120: 260218 | B120: MFA | C120: United States | D120: REIT - Mortgage | E120: Dec'25 | F120: 16.9 | G120: 78.27 | H120: -49.68 | I120: -61.45 | J120: -17.79 | K120: 32.68 | L120: 110.54 | M120: 10.85 | N120: -15.63 | O120: 128.28 | P120: 67.57 | Q120: 79.89 | R120: 90.45 | S120: 41.7 | T120: 80.2 | U120: 72.14 | V120: 84.97 | W120: 88.99 | X120: 0.045170058 | Y120: -0.026519299 | Z120: -0.01926254 | AA120: 0.16949213
A121: 260218 | B121: HL | C121: United States | D121: Other Precious Metals & Mining | E121: Dec'25 | F121: 16.2 | G121: 185.08 | H121: 186.5 | I121: 191.24 | J121: 146.34 | K121: 194.83 | L121: 199.5 | M121: 178.13 | N121: 181.91 | O121: 160.69 | P121: 189.53 | Q121: 245.66 | R121: 245.09 | S121: 249.66 | T121: 261.34 | U121: 304.03 | V121: 409.54 | W121: 448.11 | X121: 0.077220036 | Y121: 0.058268031 | Z121: 0.15512395 | AA121: 0.16205689
A122: 260218 | B122: SUN | C122: United States | D122: Oil & Gas Refining & Marketing | E122: Dec'25 | F122: 15.2 | G122: 4954 | H122: 5402 | I122: 7815 | J122: 6594 | K122: 5918 | L122: 5362 | M122: 5745 | N122: 6320 | O122: 5641 | P122: 5499 | Q122: 6174 | R122: 5751 | S122: 5269 | T122: 5179 | U122: 5390 | V122: 6032 | W122: 8600 | X122: -0.014101265 | Y122: -0.035042238 | Z122: 0.013015888 | AA122: 0.1523091
A123: 260218 | B123: SUN | C123: United States | D123: Oil & Gas Refining & Marketing | E123: Dec'25 | F123: 15.2 | G123: 4954 | H123: 5402 | I123: 7815 | J123: 6594 | K123: 5918 | L123: 5362 | M123: 5745 | N123: 6320 | O123: 5641 | P123: 5499 | Q123: 6174 | R123: 5751 | S123: 5269 | T123: 5179 | U123: 5390 | V123: 6032 | W123: 8600 | X123: -0.014101265 | Y123: -0.035042238 | Z123: 0.013015888 | AA123: 0.1523091
A124: 260218 | B124: DRD | C124: United States | D124: Gold | E124: H1 2026 | F124: 14.7 | G124: 2499 | I124: 2620 | K124: 2654 | M124: 2842 | O124: 2974 | Q124: 3266 | S124: 3802 | U124: 4076 | W124: 5053 | X124: 0.058250676 | Y124: 0.097818678 | Z124: 0.095777709 | AA124: 0.14725882
A125: 260218 | B125: OXY | C125: United States | D125: Oil & Gas E&P | E125: Dec'25 | F125: 14.5 | G125: 7913 | H125: 8349 | I125: 10676 | J125: 9390 | K125: 8219 | L125: 7225 | M125: 6702 | N125: 7158 | O125: 7172 | P125: 5975 | Q125: 6817 | R125: 7173 | S125: 2230 | T125: 6803 | U125: 6414 | V125: 6624 | W125: 5423 | X125: 0.037305699 | Y125: -0.017504235 | Z125: -0.024270557 | AA125: 0.14466948
A126: 260218 | B126: CWAN | C126: United States | D126: Software - Application | E126: Dec'25 | F126: 14.2 | G126: 69.76 | H126: 70.78 | I126: 73.41 | J126: 76.55 | K126: 82.69 | L126: 84.61 | M126: 89.88 | N126: 94.66 | O126: 99.02 | P126: 102.72 | Q126: 106.79 | R126: 115.83 | S126: 126.47 | T126: 126.86 | U126: 181.94 | V126: 205.11 | W126: 217.46 | X126: 0.053429539 | Y126: 0.15789474 | Z126: 0.16200327 | AA126: 0.14208751
A127: 260218 | B127: SSRM | C127: United States | D127: Gold | E127: Dec'25 | F127: 13.9 | G127: 407.92 | H127: 355.45 | I127: 319.58 | J127: 166.63 | K127: 306.38 | L127: 314.61 | M127: 301.03 | N127: 385.39 | O127: 425.9 | P127: 230.23 | Q127: 184.84 | R127: 257.36 | S127: 323.19 | T127: 316.62 | U127: 405.46 | V127: 385.84 | W127: 521.73 | X127: 0.086770053 | Y127: 0.2038983 | Z127: 0.098631231 | AA127: 0.13873147
A128: 260218 | B128: OR | C128: United States | D128: Gold | E128: Dec'25 | F128: 13.8 | G128: 40.04 | H128: 40.6 | I128: 40.02 | J128: 39.08 | K128: 45.75 | L128: 44.04 | M128: 45.69 | N128: 45.88 | O128: 45.3 | P128: 45.05 | Q128: 47.39 | R128: 41.98 | S128: 56.74 | T128: 54.92 | U128: 60.36 | V128: 71.63 | W128: 90.47 | X128: 0.051632141 | Y128: 0.064517734 | Z128: 0.1385514 | AA128: 0.13843628
A129: 260218 | B129: TFPM | C129: United States | D129: Other Precious Metals & Mining | E129: Dec'25 | F129: 13 | G129: 36.99 | H129: 37.76 | I129: 36.49 | J129: 33.75 | K129: 43.89 | L129: 50.27 | M129: 52.59 | N129: 49.43 | O129: 51.74 | P129: 57.53 | Q129: 63.58 | R129: 73.67 | S129: 74.21 | T129: 82.25 | U129: 94.09 | V129: 93.46 | W129: 118.92 | X129: 0.091899327 | Y129: 0.10387797 | Z129: 0.061038801 | AA129: 0.12996715
A130: 260218 | B130: AGI | C130: United States | D130: Gold | E130: Dec'25 | F130: 12.4 | G130: 203.1 | H130: 184.5 | I130: 191.2 | J130: 213.6 | K130: 231.9 | L130: 251.5 | M130: 261 | N130: 256.2 | O130: 254.6 | P130: 277.6 | Q130: 332.6 | R130: 360.9 | S130: 375.8 | T130: 333 | U130: 438.2 | V130: 462.3 | W130: 575.3 | X130: 0.041131487 | Y130: 0.075304856 | Z130: 0.067245839 | AA130: 0.12396694
A131: 260218 | B131: AGI | C131: United States | D131: Gold | E131: Dec'25 | F131: 12.4 | G131: 203.1 | H131: 184.5 | I131: 191.2 | J131: 213.6 | K131: 231.9 | L131: 251.5 | M131: 261 | N131: 256.2 | O131: 254.6 | P131: 277.6 | Q131: 332.6 | R131: 360.9 | S131: 375.8 | T131: 333 | U131: 438.2 | V131: 462.3 | W131: 575.3 | X131: 0.041131487 | Y131: 0.075304856 | Z131: 0.067245839 | AA131: 0.12396694
A132: 260218 | B132: HALO | C132: United States | D132: Biotechnology | E132: Dec'25 | F132: 12.4 | G132: 102 | H132: 117.28 | I132: 152.37 | J132: 208.98 | K132: 181.5 | L132: 162.14 | M132: 221.04 | N132: 216.03 | O132: 230.04 | P132: 195.88 | Q132: 231.35 | R132: 290.08 | S132: 298.01 | T132: 264.86 | U132: 325.72 | V132: 354.26 | W132: 451.77 | X132: 0.067939172 | Y132: 0.087033109 | Z132: 0.054451203 | AA132: 0.12371565
A133: 260218 | B133: SPNT | C133: United States | D133: Insurance - Reinsurance | E133: Dec'25 | F133: 11.7 | G133: 398 | H133: 361.4 | I133: 473.1 | J133: 597.5 | K133: 673.6 | L133: 673.6 | M133: 759.4 | N133: 702.9 | O133: 656.3 | P133: 701.4 | Q133: 636.8 | R133: 679.5 | S133: 638.7 | T133: 727.3 | U133: 748.2 | V133: 744.9 | W133: 973.7 | X133: 0.0097500376 | Y133: 0.041531521 | Z133: 0.023409815 | AA133: 0.11716974
A134: 260218 | B134: CVNA | C134: United States | D134: Auto & Truck Dealerships | E134: Dec'25 | F134: 11.3 | G134: 3753 | H134: 3497 | I134: 3884 | J134: 3386 | K134: 2837 | L134: 2606 | M134: 2968 | N134: 2773 | O134: 2424 | P134: 3061 | Q134: 3410 | R134: 3655 | S134: 3547 | T134: 4232 | U134: 4840 | V134: 5647 | W134: 5603 | X134: 0.085643238 | Y134: 0.09633522 | Z134: 0.12240383 | AA134: 0.11255885
A135: 260218 | B135: PAAS | C135: United States | D135: Gold | E135: Dec'25 | F135: 11.2 | G135: 422.17 | H135: 439.9 | I135: 340.5 | J135: 338.9 | K135: 375.4 | L135: 390.3 | M135: 639.9 | N135: 616.3 | O135: 669.6 | P135: 601.4 | Q135: 686.3 | R135: 716.1 | S135: 815.2 | T135: 773.2 | U135: 811.9 | V135: 854.6 | W135: 1179 | X135: 0.060943597 | Y135: 0.041995453 | Z135: 0.044442305 | AA135: 0.11176995
A136: 260218 | B136: SGI | C136: United States | D136: Furnishings, Fixtures & Appliances | E136: Dec'25 | F136: 9.7 | G136: 1360 | H136: 1240 | I136: 1211 | J136: 1283 | K136: 1187 | L136: 1208 | M136: 1270 | N136: 1277 | O136: 1171 | P136: 1189 | Q136: 1234 | R136: 1300 | S136: 1208 | T136: 1605 | U136: 1881 | V136: 2123 | W136: 1868 | X136: 0.084364226 | Y136: 0.12100243 | Z136: 0.13730397 | AA136: 0.096816782
A137: 260218 | B137: FIG | C137: United States | D137: Software - Application | E137: Dec'25 | F137: 9 | P137: 156.23 | Q137: 177.2 | R137: 198.64 | S137: 216.95 | T137: 228.2 | U137: 249.64 | V137: 274.17 | W137: 303.78 | X137: 0.096085552 | Y137: 0.088234936 | Z137: 0.08453936 | AA137: 0.089611542
A138: 260218 | B138: DASH | C138: United States | D138: Internet Retail | E138: Dec'25 | F138: 8.6 | G138: 1300 | H138: 1456 | I138: 1608 | J138: 1701 | K138: 1818 | L138: 2035 | M138: 2133 | N138: 2164 | O138: 2303 | P138: 2513 | Q138: 2630 | R138: 2706 | S138: 2873 | T138: 3032 | U138: 3284 | V138: 3446 | W138: 3955 | X138: 0.048405148 | Y138: 0.058179877 | Z138: 0.062211013 | AA138: 0.08563514
A139: 260218 | B139: GLBE | C139: United States | D139: Internet Retail | E139: Dec'25 | F139: 8.3 | G139: 82.72 | H139: 76.32 | I139: 87.31 | J139: 105.56 | K139: 139.87 | L139: 117.63 | M139: 133.31 | N139: 133.61 | O139: 185.4 | P139: 145.87 | Q139: 168.01 | R139: 175.97 | S139: 262.91 | T139: 189.88 | U139: 214.88 | V139: 220.78 | W139: 336.66 | X139: 0.058464849 | Y139: 0.058825006 | Z139: 0.053115073 | AA139: 0.083009736
A140: 260218 | B140: GKOS | C140: United States | D140: Medical Devices | E140: Dec'25 | F140: 8 | G140: 73.24 | H140: 67.68 | I140: 72.69 | J140: 71.27 | K140: 71.23 | L140: 73.9 | M140: 80.4 | N140: 78.05 | O140: 82.37 | P140: 85.62 | Q140: 95.69 | R140: 96.67 | S140: 105.5 | T140: 106.66 | U140: 124.12 | V140: 133.54 | W140: 143.12 | X140: 0.054865964 | Y140: 0.070280827 | Z140: 0.085159949 | AA140: 0.08007322
A141: 260218 | B141: EXE | C141: United States | D141: Oil & Gas E&P | E141: Dec'25 | F141: 8 | G141: 2606 | H141: 2781 | I141: 4013 | J141: 4193 | K141: 3136 | L141: 2105 | M141: 1260 | N141: 1406 | O141: 1276 | P141: 901 | Q141: 514 | R141: 600 | S141: 2244 | T141: 3210 | U141: 2809 | V141: 2516 | W141: 3104 | X141: 0.54214604 | Y141: 0.34942144 | Z141: 0.21617962 | AA141: 0.079784767
A142: 260218 | B142: PODD | C142: United States | D142: Medical Devices | E142: Dec'25 | F142: 7.4 | G142: 307.7 | H142: 295.4 | I142: 299.4 | J142: 340.8 | K142: 369.7 | L142: 358.1 | M142: 396.5 | N142: 432.7 | O142: 509.8 | P142: 441.7 | Q142: 488.5 | R142: 543.9 | S142: 597.5 | T142: 569 | U142: 649.1 | V142: 706.3 | W142: 783.8 | X142: 0.061450087 | Y142: 0.073036518 | Z142: 0.068828142 | AA142: 0.073872874
A143: 260218 | B143: ET | C143: United States | D143: Oil & Gas Midstream | E143: Dec'25 | F143: 7.2 | G143: 18657 | H143: 20491 | I143: 25945 | J143: 22939 | K143: 20501 | L143: 18995 | M143: 18320 | N143: 20739 | O143: 20532 | P143: 21629 | Q143: 20729 | R143: 20772 | S143: 19541 | T143: 21020 | U143: 19242 | V143: 19954 | W143: 25320 | X143: -0.0073665493 | Y143: -0.018120446 | Z143: -0.010152032 | AA143: 0.07245759
A144: 260218 | B144: AIP | C144: United States | D144: Semiconductors | E144: Dec'25 | F144: 7.1 | G144: 11.43 | H144: 11.76 | I144: 14.82 | J144: 12.6 | K144: 11.2 | L144: 13.15 | M144: 14.73 | N144: 13.27 | O144: 12.5 | P144: 12.95 | Q144: 14.58 | R144: 14.71 | S144: 15.49 | T144: 16.53 | U144: 16.5 | V144: 17.41 | W144: 20.14 | X144: 0.062012818 | Y144: 0.031316262 | Z144: 0.042701249 | AA144: 0.070529349
A145: 260218 | B145: EIX | C145: United States | D145: Utilities - Regulated Electric | E145: Dec'25 | F145: 6.8 | G145: 3331 | H145: 3968 | I145: 4008 | J145: 5228 | K145: 4016 | L145: 3966 | M145: 3964 | N145: 4702 | O145: 3706 | P145: 4078 | Q145: 4336 | R145: 5201 | S145: 3984 | T145: 3811 | U145: 4543 | V145: 5750 | W145: 5213 | X145: -0.015171317 | Y145: 0.011943226 | Z145: 0.031301671 | AA145: 0.067945599
A146: 260218 | B146: ENLT | C146: United States | D146: Utilities - Renewable | E146: Dec'25 | F146: 6.7 | G146: 31.87 | H146: 35.02 | I146: 38.06 | J146: 53.45 | K146: 68.31 | L146: 70.99 | M146: 52.56 | N146: 58.32 | O146: 73.83 | P146: 90.4 | Q146: 84.7 | R146: 109.5 | S146: 93.35 | T146: 109.76 | U146: 116.12 | V146: 138.54 | W146: 124.19 | X146: 0.051223707 | Y146: 0.079081825 | Z146: 0.067734938 | AA146: 0.067370077
A147: 260218 | B147: EQT | C147: United States | D147: Oil & Gas E&P | E147: Dec'25 | F147: 6.7 | G147: 2792 | H147: 2467 | I147: 3333 | J147: 3655 | K147: 2541 | L147: 1817 | M147: 834.88 | N147: 985.42 | O147: 1337 | P147: 1258 | Q147: 850.26 | R147: 1177 | S147: 1756 | T147: 2372 | U147: 1798 | V147: 1783 | W147: 2274 | X147: 0.2209765 | Y147: 0.15397237 | Z147: 0.085316064 | AA147: 0.067194189
A148: 260218 | B148: DTE | C148: United States | D148: Utilities - Regulated Electric | E148: Dec'25 | F148: 6.7 | G148: 0 | H148: 4577 | I148: 4924 | J148: 5251 | K148: 4476 | L148: 3779 | M148: 2684 | N148: 2888 | O148: 3394 | P148: 3240 | Q148: 2875 | R148: 2906 | S148: 3436 | T148: 4440 | U148: 3419 | V148: 3527 | W148: 4428 | X148: 0.09633138 | Y148: 0.039833053 | Z148: 0.043729315 | AA148: 0.06692754
A149: 260218 | B149: ADI | C149: United States | D149: Semiconductors | E149: Mar'26 | F149: 6.7 | G149: 2684 | H149: 2972 | I149: 3110 | J149: 3248 | K149: 3250 | L149: 3263 | M149: 3076 | N149: 2716 | O149: 2513 | P149: 2159 | Q149: 2312 | R149: 2443 | S149: 2423 | T149: 2640 | U149: 2880 | V149: 3076 | W149: 3160 | X149: 0.051515476 | Y149: 0.057852923 | Z149: 0.060947429 | AA149: 0.066884472
... A152: 260218 | B152: TCMD | C152: United States | D152: Medical Devices | E152: Dec'25 | F152: 5.8 | G152: 61.73 | H152: 47.98 | I152: 59.65 | J152: 65.26 | K152: 73.9 | L152: 58.85 | M152: 68.34 | N152: 69.59 | O152: 77.65 | P152: 61.09 | Q152: 73.22 | R152: 73.09 | S152: 85.59 | T152: 61.27 | U152: 78.91 | V152: 85.76 | W152: 103.59 | X152: 0.00061435544 | Y152: 0.019408534 | Z152: 0.042394432 | AA152: 0.057779347
A153: 260218 | B153: WAY | C153: United States | D153: Health Information Services | E153: Dec'25 | F153: 5.7 | H153: 172.4 | I153: 173.38 | J153: 177.97 | K153: 182.1 | L153: 191.08 | M153: 195.97 | N153: 197.26 | O153: 206.7 | P153: 224.79 | Q153: 234.54 | R153: 240.11 | S153: 244.1 | T153: 256.44 | U153: 270.65 | V153: 268.65 | W153: 303.54 | X153: 0.033543888 | Y153: 0.037028682 | Z153: 0.028221102 | AA153: 0.05716264
A154: 260218 | B154: SON | C154: United States | D154: Packaging & Containers | E154: Dec'25 | F154: 5.7 | G154: 1439 | H154: 1771 | I154: 1913 | J154: 1890 | K154: 1676 | L154: 1730 | M154: 1705 | N154: 1710 | O154: 0 | P154: 1309 | Q154: 1279 | R154: 1355 | S154: 1363 | T154: 1709 | U154: 1910 | V154: 2131 | W154: 1768 | X154: 0.075386355 | Y154: 0.11058535 | Z154: 0.12245542 | AA154: 0.056938001
A155: 260218 | B155: RNW | C155: United States | D155: Utilities - Renewable | E155: Sep'26 | F155: 5.4 | G155: 11896 | H155: 14946 | I155: 22174 | J155: 19560 | K155: 13170 | L155: 23319 | M155: 21250 | N155: 25956 | O155: 15993 | P155: 18120 | Q155: 22995 | R155: 26735 | S155: 18472 | T155: 29045 | U155: 38998 | V155: 36266 | W155: 25140 | X155: 0.12656102 | Y155: 0.16456035 | Z155: 0.08415894 | AA155: 0.054308077
...

Sheet Operating Income
B1: 1 | C1: 2 | D1: 3 | E1: 4 | F1: 5 | G1: 6 | H1: 7 | I1: 8 | J1: 9 | K1: 10 | L1: 11 | M1: 12 | N1: 13 | O1: 14 | P1: 15 | Q1: 16 | R1: 17 | S1: 18 | T1: 19 | U1: 20 | V1: 21 | W1: 22
B2: Ticker | C2: Country | D2: Industry | E2: Latest_Date | F2: Growth_Rate | G2: 4Q21 | H2: 1Q22 | I2: 2Q22 | J2: 3Q22 | K2: 4Q22 | L2: 1Q23 | M2: 2Q23 | N2: 3Q23 | O2: 4Q23 | P2: 1Q24 | Q2: 2Q24 | R2: 3Q24 | S2: 4Q24 | T2: 1Q25 | U2: 2Q25 | V2: 3Q25 | W2: 4Q25 | X2: 1Q25 | Y2: 2Q25 | Z2: 3Q25 | AA2: 4Q25
A3: 260220 | B3: TDS | C3: United States | D3: Telecom Services | E3: Dec'25 | F3: 355.8 | G3: 32 | H3: 96 | I3: 73 | J3: -7 | K3: -11 | L3: 40 | M3: 38 | N3: 54 | O3: 26 | P3: 73 | Q3: 0 | R3: -24.6 | S3: -13 | T3: 37 | U3: 0 | V3: -18.05 | W3: 8.17 | X3: -1.0169492 | Y3: 0 | Z3: -10.916667 | AA3: 3.5579832
A4: 260220 | B4: ASB | C4: United States | D4: Banks - Regional | E4: Dec'25 | F4: 143.6 | G4: 92.05 | H4: 92.91 | I4: 110.19 | J4: 122.44 | K4: 134.09 | L4: 130.7 | M4: 110.69 | N4: 102.67 | O4: -138.01 | P4: 101.19 | Q4: 102.88 | R4: 108.14 | S4: -177.75 | T4: 121.1 | U4: 139.63 | V4: 154.29 | W4: 162.9 | X4: 0.14807378 | Y4: 0.23806439 | Z4: 0.24147133 | AA4: 1.4357062
A5: 260220 | B5: AD | C5: United States | D5: Telecom Services | E5: Dec'25 | F5: 52.8 | G5: 12 | H5: 72 | I5: 49 | J5: -14 | K5: -17 | L5: 36 | M5: 37 | N5: 58 | O5: 23 | P5: 56 | Q5: 0 | R5: -25.94 | S5: -6 | T5: 42 | U5: 0 | V5: -6.25 | W5: 9.72 | X5: -0.58187864 | Y5: 0 | Z5: 1.9572565 | AA5: 0.52840336
A6: 260220 | B6: LAMR | C6: United States | D6: REIT - Specialty | E6: Dec'25 | F6: 29 | G6: 151.99 | H6: 120.64 | I6: 165.49 | J6: 182.49 | K6: 97.98 | L6: 116.29 | M6: 175.56 | N6: 187.95 | O6: 193.85 | P6: 121.85 | Q6: 183.41 | R6: 186.72 | S6: 39.09 | T6: 121.83 | U6: 193.33 | V6: 186.93 | W6: 196.24 | X6: -3.7659819e-05 | Y6: 0.018679974 | Z6: 0.00038819158 | AA6: 0.29038398
A7: 260220 | B7: HBM | C7: United States | D7: Copper | E7: Dec'25 | F7: 13.7 | G7: 26.48 | H7: 128.14 | I7: 137.93 | J7: 17.83 | K7: 21.06 | L7: 52.48 | M7: 5.13 | N7: 114.94 | O7: 130.06 | P7: 121.8 | Q7: 44.4 | R7: 105.2 | S7: 149.7 | T7: 186.4 | U7: 150.7 | V7: 11.5 | W7: 218.1 | X7: 0.15340774 | Y7: 0.21885938 | Z7: -0.15827703 | AA7: 0.13726671
A8: 260220 | B8: AI | C8: United States | D8: Software - Infrastructure | E8: Jun'26 | F8: 9.8 | G8: -55.68 | H8: -47.41 | I8: -56.52 | J8: -73.21 | K8: -71.97 | L8: -72.04 | M8: -73.28 | N8: -74.09 | O8: -79.4 | P8: -82.55 | Q8: -82.31 | R8: -72.59 | S8: -75.29 | T8: -87.59 | U8: -88.97 | V8: -124.82 | W8: -112.11 | X8: 0.016115623 | Y8: 0.020957895 | Z8: 0.16098508 | AA8: 0.097751347
A9: 260220 | B9: RCL | C9: United States | D9: Travel Services | E9: Dec'25 | F9: 6.6 | G9: -987.85 | H9: -859.21 | I9: -217.74 | J9: 303 | K9: 18.98 | L9: 272 | M9: 776 | N9: 1265 | O9: 591 | P9: 750 | Q9: 1108 | R9: 1636 | S9: 633 | T9: 949 | U9: 1333 | V9: 1703 | W9: 936 | X9: 0.048219045 | Y9: 0.052011096 | Z9: 0.014722039 | AA9: 0.065612819
A10: 260220 | B10: BCPC | C10: United States | D10: Specialty Chemicals | E10: Dec'25 | F10: 2.6 | G10: 33.82 | H10: 38.34 | I10: 40.45 | J10: 33.63 | K10: 35.6 | L10: 34.97 | M10: 48.98 | N10: 45.23 | O10: 28.25 | P10: 42.12 | Q10: 45.8 | R10: 48.51 | S10: 48.04 | T10: 51.5 | U10: 51.44 | V10: 54.58 | W10: 53.34 | X10: 0.050848376 | Y10: 0.029094661 | Z10: 0.03042759 | AA10: 0.025783226
A11: 260220 | B11: BN | C11: United States | D11: Asset Management | E11: Dec'25 | F11: 0.7 | G11: 4020 | H11: 3997 | I11: 3953 | J11: 4553 | K11: 4246 | L11: 3892 | M11: 4140 | N11: 4146 | O11: 4336 | P11: 4530 | Q11: 4704 | R11: 5443 | S11: 6046 | T11: 4995 | U11: 4615 | V11: 4810 | W11: 6186 | X11: 0.022438836 | Y11: -0.0042004908 | Z11: -0.030001422 | AA11: 0.0068406137
A12: 260220 | B12: RSG | C12: United States | D12: Waste Management | E12: Dec'25 | F12: 0.1 | G12: 510.7 | H12: 571.4 | I12: 649.6 | J12: 674.6 | K12: 593 | L12: 657.2 | M12: 733.3 | N12: 738.8 | O12: 719.7 | P12: 739 | Q12: 818 | R12: 863 | S12: 804 | T12: 806 | U12: 870 | V12: 839 | W12: 806 | X12: 0.020781638 | Y12: 0.015800668 | Z12: -0.0071791804 | AA12: 0.00060259114
A13: 260220 | B13: WU | C13: United States | D13: Credit Services | E13: Dec'25 | F13: -0.1 | G13: 316 | H13: 256.2 | I13: 264.2 | J13: 231.2 | K13: 172.8 | L13: 211.8 | M13: 250.9 | N13: 215 | O13: 169.3 | P13: 206.1 | Q13: 200.1 | R13: 164.9 | S13: 197 | T13: 177.4 | U13: 192.7 | V13: 201.9 | W13: 196.2 | X13: -0.037364926 | Y13: -0.010008115 | Z13: 0.050546448 | AA13: -0.0010403121
A14: 260220 | B14: CCOI | C14: United States | D14: Telecom Services | E14: Dec'25 | F14: -17.3 | G14: 28.8 | H14: 28.41 | I14: 29.48 | J14: 30.77 | K14: 27.55 | L14: 24.71 | M14: -33.87 | N14: -50.21 | O14: -51.48 | P14: -50.35 | Q14: -38.11 | R14: -57.83 | S14: -33.23 | T14: -40.29 | U14: -31.46 | V14: -20.58 | W14: -11.48 | X14: -0.056038324 | Y14: -0.039242299 | Z14: -0.2287943 | AA14: -0.17322396
... A17: 260220 | B17: OIS | C17: United States | D17: Oil & Gas Equipment & Services | E17: Dec'25 | F17: -41.8 | G17: -9.06 | H17: -4.34 | I17: -1.09 | J17: -1.04 | K17: 0.42 | L17: 5.88 | M17: 3.27 | N17: 7.84 | O17: 4.61 | P17: 1.33 | Q17: 5.51 | R17: 7.17 | S17: -7.88 | T17: 6.87 | U17: 8.94 | V17: 8.31 | W17: -14.67 | X17: 0.90375204 | Y17: 0.29391602 | Z17: 0.075496689 | AA17: -0.41810345
A18: 260220 | B18: 8987 | C18: Japan | D18: Japan Excellent, Inc. | E18: H2 2025 | F18: -8.0237474 | G18: 4486 | I18: 4711 | K18: 4105 | M18: 7121 | O18: 4608 | Q18: 4836 | S18: 6098 | U18: 5019 | W18: 5206 | X18: -0.19481627 | Y18: 0.15777213 | Z18: 0.016736784 | AA18: -0.080237474
A19: 260220 | B19: 2350 | C19: Hong Kong | D19: Saudi Kayan Petrochemical Company | E19: H1 2026 | F19: -44.034091 | G19: 23.15 | I19: 41.52 | K19: 40.77 | M19: 16.02 | O19: 2.59 | Q19: -16.58 | S19: -17.61 | U19: 10.57 | W19: -14.51 | X19: -1.7517464 | Y19: 1.4438885 | Z19: -0.79409184 | AA19: -0.44034091
A20: 260219 | B20: ALIT | C20: United States | D20: Software - Application | E20: Dec'25 | F20: 325 | G20: 40 | H20: -2 | I20: -9 | J20: -27 | K20: 18 | L20: -40 | M20: -11 | N20: -30 | O20: -23 | P20: -40 | Q20: -34 | R20: -30 | S20: -1 | T20: -8 | U20: 9 | V20: 20 | W20: 64 | X20: -0.3047619 | Y20: -0.5890411 | Z20: -1.6666667 | AA20: 3.25
A21: 260219 | B21: TALK | C21: United States | D21: Health Information Services | E21: Dec'25 | F21: 189 | G21: -28.58 | H21: -21.21 | I21: -21.07 | J21: -19.55 | K21: -15.2 | L21: -9.04 | M21: -6.41 | N21: -5.18 | O21: -2.58 | P21: -1.68 | Q21: -3.49 | R21: 0.1 | S21: 1.77 | T21: -1.09 | U21: -1.79 | V21: 2.2 | W21: 3.83 | X21: -0.17878788 | Y21: -0.62730627 | Z21: -2.0792079 | AA21: 1.8899083
A22: 260219 | B22: AG | C22: United States | D22: Silver | E22: Dec'25 | F22: 105.6 | G22: 27.08 | H22: -4.71 | I22: -4.69 | J22: -13.74 | K22: -28.47 | L22: -115.47 | M22: -11.89 | N22: -9.25 | O22: -193.17 | P22: -22.8 | Q22: -5.59 | R22: 7.59 | S22: 35.95 | T22: 37.87 | U22: 24.93 | V22: 76.87 | W22: 221.36 | X22: 4.0046205 | Y22: 0.40253231 | Z22: 0.6514952 | AA22: 1.0557454
A23: 260219 | B23: LNT | C23: United States | D23: Utilities - Regulated Electric | E23: Dec'25 | F23: 95.6 | G23: 123 | H23: 248 | I23: 212 | J23: 309 | K23: 132 | L23: 222 | M23: 217 | N23: 482 | O23: -342 | P23: 222 | Q23: 190 | R23: 313 | S23: -305 | T23: 257 | U23: 223 | V23: 349 | W23: 196 | X23: 0.083333333 | Y23: 0.072527473 | Z23: 0.073770492 | AA23: 0.95610687
A24: 260219 | B24: PRU | C24: United States | D24: Insurance - Life | E24: Dec'25 | F24: 66.3 | G24: 2448 | H24: -657 | I24: -1061 | J24: -126 | K24: -1435 | L24: 1847 | M24: 621 | N24: -1058 | O24: 2069 | P24: 1390 | Q24: 1415 | R24: 553 | S24: -357 | T24: 920 | U24: 740 | V24: 1773 | W24: 1682 | X24: -0.15661446 | Y24: -0.26669301 | Z24: 0.65732759 | AA24: 0.66287386
A25: 260219 | B25: CG | C25: United States | D25: Asset Management | E25: Dec'25 | F25: 38.3 | G25: 890 | H25: 740.2 | I25: 323.4 | J25: 404.2 | K25: 143.2 | L25: 156.1 | M25: -85.6 | N25: 161.6 | O25: -839.7 | P25: 127.9 | Q25: 223.6 | R25: 786.2 | S25: 231.7 | T25: 164.9 | U25: 393.7 | V25: -37.4 | W25: 519.9 | X25: 0.027019132 | Y25: 0.1209471 | Z25: -0.52242309 | AA25: 0.38278656
A26: 260219 | B26: OPEN | C26: United States | D26: Real Estate Services | E26: Dec'25 | F26: 36.5 | G26: -102 | H26: 118 | I26: 32 | J26: -809 | K26: -192 | L26: -122 | M26: -57 | N26: -77 | O26: -106 | P26: -84 | Q26: -72 | R26: -66 | S26: -81 | T26: -53 | U26: -4 | V26: -65 | W26: -155 | X26: -0.10231023 | Y26: -0.25 | Z26: -0.0049019608 | AA26: 0.36453202
A27: 260219 | B27: SII | C27: United States | D27: Asset Management | E27: Dec'25 | F27: 36.3 | G27: 13.75 | H27: 11.04 | I27: 6.25 | J27: 9.05 | K27: 17.07 | L27: 13.21 | M27: 11.49 | N27: 11.27 | O27: 10.88 | P27: 16.32 | Q27: 19.06 | R27: 20.36 | S27: 14.4 | T27: 16.64 | U27: 22.41 | V27: 16.86 | W27: 39.95 | X27: 0.004562304 | Y27: 0.047544706 | Z27: -0.047419049 | AA27: 0.3633907
A28: 260219 | B28: AIR | C28: United States | D28: Aerospace & Defense | E28: Jun'26 | F28: 34.4 | G28: 28.1 | H28: 31.4 | I28: 34.1 | J28: 31.8 | K28: 33.1 | L28: 35.7 | M28: 37.1 | N28: 37.4 | O28: 39.1 | P28: 45.4 | Q28: 53.8 | R28: 42.6 | S28: -3.6 | T28: 64.7 | U28: 84 | V28: 61.9 | W28: 67.7 | X28: 0.13965268 | Y28: 0.19174603 | Z28: 0.10282365 | AA28: 0.34444444
A29: 260219 | B29: RNG | C29: United States | D29: Software - Application | E29: Dec'25 | F29: 29.6 | G29: -103.26 | H29: -103.54 | I29: -106.34 | J29: -74 | K29: -348.96 | L29: -49.66 | M29: -41.46 | N29: -49.73 | O29: -38.48 | P29: -6.32 | Q29: -4.16 | R29: 8.14 | S29: 12.11 | T29: 17.43 | U29: 39.78 | V29: 33.27 | W29: 42.44 | X29: 2.430911 | Y29: 1.3108592 | Z29: 0.32442551 | AA29: 0.29564285
A30: 260219 | B30: CNA | C30: United States | D30: Insurance - Property & Casualty | E30: Dec'25 | F30: 25.9 | G30: 358 | H30: 383 | I30: 255 | J30: -23 | K30: 311 | L30: 399 | M30: 392 | N30: 360 | O30: 494 | P30: 462 | Q30: 436 | R30: 393 | S30: 53 | T30: 381 | U30: 411 | V30: 549 | W30: 414 | X30: -0.060267857 | Y30: -0.019794141 | Z30: 0.12600969 | AA30: 0.258967
A31: 260219 | B31: FIX | C31: United States | D31: Engineering & Construction | E31: Dec'25 | F31: 18 | G31: 48.81 | H31: 35.37 | I31: 56.27 | J31: 81.03 | K31: 79.6 | L31: 63.07 | M31: 91.49 | N31: 134.56 | O31: 118.96 | P31: 134.64 | Q31: 184.06 | R31: 201.54 | S31: 226.1 | T31: 208.54 | U31: 299.43 | V31: 378.29 | W31: 426.35 | X31: 0.099016534 | Y31: 0.14065395 | Z31: 0.18891418 | AA31: 0.18002265
A32: 260219 | B32: NEM | C32: United States | D32: Gold | E32: Dec'25 | F32: 17.8 | G32: -645 | H32: 834 | I32: 562 | J32: 306 | K32: -97 | L32: 513 | M32: 407 | N32: 275 | O32: -487 | P32: 958 | Q32: 1344 | R32: 1298 | S32: 2310 | T32: 2016 | U32: 2417 | V32: 2588 | W32: 3974 | X32: 0.17901861 | Y32: 0.15398967 | Z32: 0.16042781 | AA32: 0.1783303
A33: 260219 | B33: HG | C33: United States | D33: Insurance - Reinsurance | E33: Dec'25 | F33: 16.5 | H33: -73.68 | I33: 249.93 | J33: -148.19 | K33: -21.21 | L33: 62.15 | M33: 52.77 | N33: 58.89 | O33: 109.03 | P33: 285.76 | Q33: 210.69 | R33: 75.39 | S33: 75.57 | T33: 192.6 | U33: 279.7 | V33: 182.61 | W33: 196.17 | X33: -0.14389645 | Y33: 0.1245106 | Z33: 0.17203093 | AA33: 0.16509692
A34: 260219 | B34: LAUR | C34: United States | D34: Education & Training Services | E34: Dec'25 | F34: 14.7 | G34: 32.2 | H34: 10.03 | I34: 126.94 | J34: 56.32 | K34: 78.02 | L34: 15.63 | M34: 156.11 | N34: 58.71 | O34: 111.45 | P34: 11.13 | Q34: 166.6 | R34: 72.04 | S34: 124.22 | T34: -13.19 | U34: 193.34 | V34: 71.47 | W34: 179.5 | X34: -0.065028477 | Y34: 0.076472102 | Z34: -0.0015143062 | AA34: 0.14708387
A35: 260219 | B35: SEM | C35: United States | D35: Medical Care Facilities | E35: Dec'25 | F35: 14.6 | G35: 67.68 | H35: 103.99 | I35: 105.84 | J35: 83.03 | K35: 86.63 | L35: 151.46 | M35: 159.2 | N35: 129.96 | O35: 0 | P35: 118.47 | Q35: 73.86 | R35: 54.9 | S35: 21.09 | T35: 112.75 | U35: 86.53 | V35: 72.96 | W35: 63.94 | X35: -0.021317829 | Y35: 0.048248286 | Z35: 0.065608312 | AA35: 0.14608121
A36: 260219 | B36: RIO | C36: United States | D36: Other Industrial Metals & Mining | E36: H2 2025 | F36: 11.665641 | G36: 12268 | I36: 11498 | K36: 6597 | M36: 7862 | O36: 7005 | Q36: 7718 | S36: 6272 | U36: 6732 | W36: 7789 | X36: -0.0096858815 | Y36: -0.049786049 | Z36: -0.070478914 | AA36: 0.11665641
A37: 260219 | B37: PRAX | C37: United States | D37: Biotechnology | E37: Dec'25 | F37: 11.3 | G37: -58.66 | H37: -68.85 | I37: -59.39 | J37: -44.29 | K37: -40.45 | L37: -38.09 | M37: -34.96 | N37: -25.52 | O37: -27.81 | P37: -41.89 | Q37: -37.49 | R37: -56.84 | S37: -63.96 | T37: -74.73 | U37: -76.07 | V37: -78.36 | W37: -97.04 | X37: 0.16405235 | Y37: 0.16556519 | Z37: 0.079234168 | AA37: 0.1128548
A38: 260219 | B38: FIVN | C38: United States | D38: Software - Infrastructure | E38: Dec'25 | F38: 9.4 | G38: 1.98 | H38: -27.28 | I38: -20.86 | J38: -20.93 | K38: -3.09 | L38: -28.4 | M38: -24.44 | N38: -25.74 | O38: -11.82 | P38: -20.7 | Q38: -19.37 | R38: -15.42 | S38: 16.48 | T38: -5.43 | U38: 8.31 | V38: 16.14 | W38: 19.8 | X38: -0.39143809 | Y38: -1.1659646 | Z38: 8.0101523 | AA38: 0.093521127
A39: 260219 | B39: CARG | C39: United States | D39: Auto & Truck Dealerships | E39: Dec'25 | F39: 7.4 | G39: 44.57 | H39: 26.66 | I39: 23.54 | J39: 28.66 | K39: 29.79 | L39: 14.06 | M39: 17.74 | N39: 23.1 | O39: -22.27 | P39: 26.28 | Q39: 34.07 | R39: 44.21 | S39: 53.28 | T39: 45.76 | U39: 57.4 | V39: 58.48 | W39: 69.13 | X39: 0.12341612 | Y39: 0.13157004 | Z39: 0.071118864 | AA39: 0.073748371
A40: 260219 | B40: VICR | C40: United States | D40: Electronic Components | E40: Dec'25 | F40: 7.4 | G40: 8.9 | H40: 4.78 | I40: 11.3 | J40: 9.5 | K40: 8.12 | L40: 10.44 | M40: 17.86 | N40: 15.7 | O40: 7.35 | P40: 1.09 | Q40: 2.51 | R40: 5.39 | S40: 9.65 | T40: 0.18 | U40: 50.83 | V40: 21.26 | W40: 15.69 | X40: -0.048819742 | Y40: 2.7253243 | Z40: 0.24027252 | AA40: 0.073730469
A41: 260219 | B41: TRGP | C41: United States | D41: Oil & Gas Midstream | E41: Dec'25 | F41: 7 | G41: 373 | H41: 295.8 | I41: 451.9 | J41: 430 | K41: 551.4 | L41: 836.7 | M41: 649.1 | N41: 505.1 | O41: 635.3 | P41: 639.4 | Q41: 627.2 | R41: 728.2 | S41: 700.5 | T41: 543.3 | U41: 1034 | V41: 836.9 | W41: 917.4 | X41: -0.035654658 | Y41: 0.1565097 | Z41: 0.036161011 | AA41: 0.069637525
A42: 260219 | B42: CVE | C42: United States | D42: Oil & Gas Integrated | E42: Dec'25 | F42: 6.5 | G42: 1691 | H42: 1880 | I42: 3552 | J42: 2073 | K42: 1401 | L42: 749 | M42: 1019 | N42: 2622 | O42: 951 | P42: 1588 | Q42: 1423 | R42: 998 | S42: 994 | T42: 1211 | U42: 724 | V42: 1452 | W42: 1277 | X42: -0.075354787 | Y42: -0.15110246 | Z42: 0.11560988 | AA42: 0.064597124
A43: 260219 | B43: NMM | C43: United States | D43: Marine Shipping | E43: Dec'25 | F43: 6.3 | G43: 104.69 | H43: 80.01 | I43: 117.42 | J43: 114.21 | K43: 135.73 | L43: 93.33 | M43: 128.68 | N43: 108.16 | O43: 105.62 | P43: 94.36 | Q43: 117.53 | R43: 122.54 | S43: 104.65 | T43: 74.89 | U43: 91.85 | V43: 85 | W43: 126.96 | X43: -0.044342717 | Y43: -0.061199685 | Z43: -0.095296119 | AA43: 0.062599961
A44: 260219 | B44: SO | C44: United States | D44: Utilities - Regulated Electric | E44: Dec'25 | F44: 5.7 | G44: -194 | H44: 1525 | I44: 1819 | J44: 2357 | K44: 553 | L44: 1367 | M44: 1438 | N44: 2260 | O44: 1355 | P44: 1855 | Q44: 2092 | R44: 2520 | S44: 601 | T44: 2163 | U44: 1958 | V44: 2860 | W44: 1033 | X44: 0.043576684 | Y44: -0.018167028 | Z44: 0.046948357 | AA44: 0.056977051
A45: 260219 | B45: NABL | C45: United States | D45: Information Technology Services | E45: Dec'25 | F45: 5.1 | G45: 8.7 | H45: 11.67 | I45: 10.92 | J45: 12.68 | K45: 15.22 | L45: 15.69 | M45: 15.97 | N45: 17.91 | O45: 20.36 | P45: 19.71 | Q45: 27.16 | R45: 19.7 | S45: 10.85 | T45: 2.39 | U45: 16.09 | V45: 17.13 | W45: 13.24 | X45: -0.2237148 | Y45: -0.18419301 | Z45: -0.052416888 | AA45: 0.051442101
A46: 260219 | B46: SVV | C46: United States | D46: Specialty Retail | E46: Dec'25 | F46: 4.9 | G46: 43.11 | H46: 32.96 | I46: 61.43 | J46: 65.68 | K46: 46.16 | L46: 15.77 | M46: 68.86 | N46: 20.35 | O46: 36.88 | P46: 16.27 | Q46: 32.22 | R46: 48.64 | S46: 37.47 | T46: 10.4 | U46: 34.91 | V46: 36.25 | W46: 43.34 | X46: -0.043610698 | Y46: 0.02089645 | Z46: -0.094277888 | AA46: 0.049315299
A47: 260219 | B47: FTI | C47: United States | D47: Oil & Gas Equipment & Services | E47: Dec'25 | F47: 4.4 | G47: 16.3 | H47: 11.5 | I47: 84.2 | J47: 81.8 | K47: 108.4 | L47: 47.7 | M47: 164.4 | N47: 162.3 | O47: 214.4 | P47: 164.1 | Q47: 307.8 | R47: 286.8 | S47: 198.1 | T47: 258.5 | U47: 403 | V47: 405 | W47: 253.7 | X47: 0.098662207 | Y47: 0.090563166 | Z47: 0.10310537 | AA47: 0.043966472
A48: 260219 | B48: NICE | C48: United States | D48: Software - Application | E48: Dec'25 | F48: 3.9 | G48: 68.19 | H48: 72.36 | I48: 84.69 | J48: 90.3 | K48: 87.87 | L48: 93.51 | M48: 105.43 | N48: 114.08 | O48: 117.94 | P48: 121.44 | Q48: 128.82 | R48: 142.2 | S48: 151.7 | T48: 148.17 | U48: 160.59 | V48: 169.45 | W48: 176.22 | X48: 0.049121582 | Y48: 0.05564995 | Z48: 0.045216208 | AA48: 0.038926196
... A109: 260219 | B109: BURE | C109: Sweden | D109: Bure Equity AB (publ) | E109: Dec'25 | F109: -13.3 | G109: 1280 | H109: -6618 | I109: -2587 | J109: -2445 | K109: 2405 | L109: 2419 | M109: 728 | N109: -1377 | O109: 2964 | P109: 2980 | Q109: 1755 | R109: 2265 | S109: -1295 | T109: -2637 | U109: -1251 | V109: -220 | W109: -578 | X109: -0.98457493 | Y109: -34.159091 | Z109: 0.85161069 | AA109: -0.13270405
A110: 260219 | B110: 5101 | C110: Japan | D110: The Yokohama Rubber Company, Limited | E110: Dec'25 | F110: 13.6 | G110: 4341 | H110: 13531 | I110: 13411 | J110: 18382 | K110: 23885 | L110: 13206 | M110: 14976 | N110: 24184 | O110: 46977 | P110: 26752 | Q110: 29501 | R110: 29521 | S110: 42972 | T110: 20759 | U110: 34099 | V110: 36799 | W110: 61244 | X110: -0.046549019 | Y110: 0.037457333 | Z110: 0.057149139 | AA110: 0.13572113
A111: 260219 | B111: 3040 | C111: Japan | D111: Qassim Cement Company | E111: Dec'25 | F111: -0.7 | G111: 702 | H111: 610 | I111: 86 | J111: 499 | K111: 843 | L111: 651 | M111: 275 | N111: 762 | O111: 921 | P111: 489 | Q111: 160 | R111: 393 | S111: 1002 | T111: 592 | U111: 202 | V111: 1070 | W111: 983 | X111: 0.050391389 | Y111: 0.01956218 | Z111: 0.30927364 | AA111: -0.0066294487
A112: 260219 | B112: NK | C112: France | D112: Imerys S.A. | E112: Dec'25 | F112: -12.8 | G112: 0 | H112: 121 | I112: 0 | J112: 118 | K112: 60.4 | L112: 105 | M112: 64.5 | N112: 82 | O112: -35.7 | P112: 123 | Q112: 40.3 | R112: 78 | S112: 42.1 | T112: 56 | U112: 73.3 | V112: 72 | W112: 10.9 | X112: -0.23641496 | Y112: 0.15249538 | Z112: -0.024057739 | AA112: -0.12818406
A113: 260218 | B113: FVRR | C113: United States | D113: Internet Content & Information | E113: Dec'25 | F113: 806.3 | G113: -15.94 | H113: -17.25 | I113: -17.65 | J113: -13 | K113: 0.99 | L113: -7.15 | M113: -4.01 | N113: -2.35 | O113: -1.61 | P113: -4.15 | Q113: -2.31 | R113: -2.2 | S113: -6.79 | T113: -0.6 | U113: 0.74 | V113: 9.18 | W113: 13.61 | X113: -0.22977346 | Y113: -0.25630252 | Z113: -1.2858757 | AA113: 8.0632411
A114: 260218 | B114: GLBE | C114: United States | D114: Internet Retail | E114: Dec'25 | F114: 427.8 | G114: -22.19 | H114: -51.68 | I114: -49.3 | J114: -53.23 | K114: -14.45 | L114: -42.01 | M114: -36.4 | N114: -35.6 | O114: -10.89 | P114: -29.26 | Q114: -22.82 | R114: -21.03 | S114: 5.18 | T114: -19.19 | U114: 10.51 | V114: 17.08 | W114: 63.27 | X114: -0.14824084 | Y114: -0.57604563 | Z114: -1.5536078 | AA114: 4.2776141
A115: 260218 | B115: ADAM | C115: United States | D115: REIT - Mortgage | E115: Dec'25 | F115: 188.7 | G115: 34.64 | H115: -90.61 | I115: -91.83 | J115: -135.85 | K115: -43.38 | L115: 23.28 | M115: -14.18 | N115: -49.91 | O115: 64.64 | P115: -28.83 | Q115: -19.8 | R115: 34.29 | S115: -40.19 | T115: 41.66 | U115: 8.21 | V115: 41.63 | W115: 56.65 | X115: -1.2926829 | Y115: 1.7550125 | Z115: 0.166932 | AA115: 1.8873514
A116: 260218 | B116: CWAN | C116: United States | D116: Software - Application | E116: Dec'25 | F116: 157.3 | G116: 1.15 | H116: 1.28 | I116: 1.13 | J116: -1.16 | K116: 7.51 | L116: -6.32 | M116: -7.13 | N116: -5.89 | O116: 4.64 | P116: 1.13 | Q116: 3.84 | R116: 7.34 | S116: 1.22 | T116: 7.08 | U116: -8.78 | V116: 6.55 | W116: 10.77 | X116: 0.43976349 | Y116: -0.64784394 | Z116: -0.11516035 | AA116: 1.5733114
A117: 260218 | B117: RELY | C117: United States | D117: Software - Infrastructure | E117: Dec'25 | F117: 126.3 | G117: -16.54 | H117: -23.17 | I117: -39.38 | J117: -33.23 | K117: -21.79 | L117: -26.87 | M117: -18.02 | N117: -34 | O117: -31.19 | P117: -19.16 | Q117: -15.76 | R117: 0.37 | S117: -4.53 | T117: 12.23 | U117: 14.64 | V117: 11.78 | W117: 38.58 | X117: -0.80322416 | Y117: -3.953186 | Z117: 0.50242184 | AA117: 1.2634818
A118: 260218 | B118: GSM | C118: United States | D118: Other Industrial Metals & Mining | E118: Dec'25 | F118: 108.2 | G118: 80.61 | H118: 211.13 | I118: 265.3 | J118: 154.42 | K118: 86.69 | L118: 44.21 | M118: 63.73 | N118: 76.45 | O118: 37.84 | P118: 2.56 | Q118: 44.55 | R118: 40.6 | S118: -6.49 | T118: -55.95 | U118: 8.74 | V118: -1.99 | W118: -66.77 | X118: -0.72038907 | Y118: -1.5768384 | Z118: 3.251145 | AA118: 1.0824205
A119: 260218 | B119: GNK | C119: United States | D119: Marine Shipping | E119: Dec'25 | F119: 107.4 | G119: 87.36 | H119: 42.09 | I119: 49.2 | J119: 45.18 | K119: 30.77 | L119: 4.44 | M119: 13.03 | N119: -2.25 | O119: 20.65 | P119: 23.07 | Q119: 18.74 | R119: 20.53 | S119: 14.83 | T119: -9.77 | U119: -3.61 | V119: 2.47 | W119: 19.04 | X119: -0.42555397 | Y119: -0.50417325 | Z119: -0.82165605 | AA119: 1.0739796
A120: 260218 | B120: JBGS | C120: United States | D120: REIT - Office | E120: Dec'25 | F120: 86 | G120: -4.78 | H120: 3.11 | I120: 3.03 | J120: -1.28 | K120: 18.69 | L120: 8.83 | M120: 15.85 | N120: 14.34 | O120: 10.53 | P120: 2.93 | Q120: -2.52 | R120: 6.19 | S120: 0.26 | T120: -4.73 | U120: 2.2 | V120: -1.08 | W120: -2.62 | X120: -1.1166181 | Y120: -5.9 | Z120: -1.8545918 | AA120: 0.85970149
A121: 260218 | B121: SPNT | C121: United States | D121: Insurance - Reinsurance | E121: Dec'25 | F121: 82.9 | G121: -162.5 | H121: -213.7 | I121: -119.2 | J121: -129 | K121: 57.7 | L121: 179.2 | M121: 167.1 | N121: 102.5 | O121: 53.8 | P121: 138.3 | Q121: 41.8 | R121: 145.2 | S121: 20 | T121: 91.2 | U121: 112.7 | V121: 123.3 | W121: 308 | X121: -0.13640313 | Y121: 0.23775989 | Z121: -0.059333514 | AA121: 0.82949309
A122: 260218 | B122: BLCO | C122: United States | D122: Medical Instruments & Supplies | E122: Dec'25 | F122: 67.2 | G122: 97 | H122: 56 | I122: 55 | J122: 53 | K122: 56 | L122: 7 | M122: 60 | N122: 68 | O122: 69 | P122: 15 | Q122: 40 | R122: 65 | S122: 86 | T122: -61 | U122: 11 | V122: 80 | W122: 164 | X122: -0.36893204 | Y122: -0.22307692 | Z122: 0.14851485 | AA122: 0.67241379
A123: 260218 | B123: EXE | C123: United States | D123: Oil & Gas E&P | E123: Dec'25 | F123: 58.6 | G123: 1513 | H123: -1050 | I123: 1320 | J123: 1007 | K123: 2272 | L123: 1485 | M123: 48 | N123: 79 | O123: 589 | P123: 35 | Q123: -258 | R123: -140 | S123: -119 | T123: -241 | U123: 1290 | V123: 731 | W123: 854 | X123: 0.57261411 | Y123: -2.0422164 | Z123: 1.1025316 | AA123: 0.58579169
... A126: 260218 | B126: MFA | C126: United States | D126: REIT - Mortgage | E126: Dec'25 | F126: 40.7 | G126: 44.12 | H126: -82.91 | I126: -100.37 | J126: -55.02 | K126: 6.71 | L126: 73.34 | M126: -26.28 | N126: -56.34 | O126: 89.73 | P126: 24.26 | Q126: 42.29 | R126: 49.7 | S126: 3.44 | T126: 40.3 | U126: 33.42 | V126: 48 | W126: 54.32 | X126: 0.13401287 | Y126: -0.065350328 | Z126: -0.013400599 | AA126: 0.40651965
A127: 260218 | B127: DRD | C127: United States | D127: Gold | E127: H1 2026 | F127: 39.3844 | G127: 585.4 | I127: 585.4 | K127: 587.9 | M127: 778.4 | O127: 659.6 | Q127: 896.6 | S127: 1213 | U127: 1646 | W127: 2339 | X127: 0.082197497 | Y127: 0.35560982 | Z127: 0.35523322 | AA127: 0.393844
A128: 260218 | B128: FLR | C128: United States | D128: Engineering & Construction | E128: Dec'25 | F128: 34.3 | G128: 83 | H128: 57 | I128: 85 | J128: -43 | K128: 59 | L128: -93 | M128: 152 | N128: 199 | O128: 2 | P128: 45 | Q128: 131 | R128: 54 | S128: 153 | T128: 106 | U128: 18 | V128: -478 | W128: 84 | X128: 0.15926893 | Y128: -0.2545045 | Z128: -1.6072508 | AA128: 0.34328358
A129: 260218 | B129: TX | C129: United States | D129: Steel | E129: Dec'25 | F129: 33.5 | G129: 1370 | H129: 1059 | I129: 1071 | J129: 526.24 | K129: 141.04 | L129: 357.39 | M129: 731.74 | N129: 527.32 | O129: 413.22 | P129: 674.86 | Q129: 370.52 | R129: 175.5 | S129: -18.03 | T129: 131.83 | U129: 199.23 | V129: 215.4 | W129: 159 | X129: -0.4514528 | Y129: -0.2596011 | Z129: 0.081673592 | AA129: 0.33501126
A130: 260218 | B130: VRSK | C130: United States | D130: Consulting Services | E130: Dec'25 | F130: 33.1 | G130: 0 | H130: 247.1 | I130: 263.2 | J130: 253.6 | K130: 0 | L130: 295.1 | M130: 284 | N130: 281.1 | O130: 275 | P130: 307.5 | Q130: 318.7 | R130: 311.7 | S130: 0 | T130: 330.9 | U130: 354.4 | V130: 349.8 | W130: 342.5 | X130: 0.024949355 | Y130: 0.03713721 | Z130: 0.038214644 | AA130: 0.3308859
A131: 260218 | B131: DINO | C131: United States | D131: Oil & Gas Refining & Marketing | E131: Dec'25 | F131: 31.2 | G131: -28.52 | H131: 256.93 | I131: 1678 | J131: 1337 | K131: 834.62 | L131: 507.14 | M131: 706.9 | N131: 1077 | O131: -49.15 | P131: 412 | Q131: 196 | R131: -121 | S131: -213.57 | T131: 82 | U131: 274 | V131: 564 | W131: 7 | X131: -1.2068902 | Y131: -1.3788227 | Z131: 31.964536 | AA131: 0.31223193
A132: 260218 | B132: HL | C132: United States | D132: Other Precious Metals & Mining | E132: Dec'25 | F132: 27.4 | G132: 46.95 | H132: 23.22 | I132: 15.78 | J132: -17.23 | K132: 4.12 | L132: 18.97 | M132: 19.38 | N132: 11.68 | O132: -12.63 | P132: 21.55 | Q132: 30.47 | R132: 23.87 | S132: 112.5 | T132: 57.26 | U132: 99.58 | V132: 153.98 | W132: 228.28 | X132: 0.18955359 | Y132: 0.30838911 | Z132: 0.44374339 | AA132: 0.27350468
A133: 260218 | B133: TCMD | C133: United States | D133: Medical Devices | E133: Dec'25 | F133: 27.2 | G133: 4.37 | H133: -14.9 | I133: -4.09 | J133: 1.78 | K133: 8.8 | L133: -3.15 | M133: 2.66 | N133: 4.29 | O133: 11.8 | P133: -2.96 | Q133: 5.85 | R133: 6.78 | S133: 12.52 | T133: -4.54 | U133: 4.08 | V133: 10.96 | W133: 18.78 | X133: -0.071203245 | Y133: -0.08588064 | Z133: 0.22186837 | AA133: 0.27193745
A134: 260218 | B134: MCY | C134: United States | D134: Insurance - Property & Casualty | E134: Dec'25 | F134: 26.7 | G134: 39.13 | H134: -248.85 | I134: -267.07 | J134: -124.63 | K134: -12.93 | L134: -57.15 | M134: -55.66 | N134: -9.31 | O134: 245.72 | P134: 96.99 | Q134: 88.3 | R134: 294.78 | S134: 110.83 | T134: -135.11 | U134: 211.24 | V134: 357.5 | W134: 255.94 | X134: -0.39279066 | Y134: 0.34264214 | Z134: 0.13019471 | AA134: 0.26652096
A135: 260218 | B135: DASH | C135: United States | D135: Internet Retail | E135: Dec'25 | F135: 26.5 | G135: -146 | H135: -159 | I135: -224 | J135: -296 | K135: -281 | L135: -168 | M135: -210 | N135: -108 | O135: -89 | P135: -61 | Q135: -116 | R135: 107 | S135: 32 | T135: 172 | U135: 185 | V135: 276 | W135: 208 | X135: -6.1315789 | Y135: 1.5435897 | Z135: 0.34072581 | AA135: 0.26466165
A136: 260218 | B136: MATV | C136: United States | D136: Specialty Chemicals | E136: Dec'25 | F136: 26.4 | G136: 17.7 | H136: 23.5 | I136: 0 | J136: 3.1 | K136: 4.2 | L136: -1.7 | M136: 10.4 | N136: -2.9 | O136: 3.9 | P136: 1 | Q136: 22.6 | R136: 18.6 | S136: 2.2 | T136: -12.8 | U136: 23.5 | V136: 23.5 | W136: 11.8 | X136: -0.31081081 | Y136: 0.029411765 | Z136: 0.15555556 | AA136: 0.26373626
A137: 260218 | B137: FIG | C137: United States | D137: Software - Application | E137: Dec'25 | F137: 24.2 | P137: 12.52 | Q137: -894.29 | R137: -47.34 | S137: 56.18 | T137: 39.75 | U137: 2.08 | V137: -1137 | W137: -195.5 | X137: -0.031193796 | Y137: -1.0599149 | Z137: -21.505033 | AA137: 0.24223525
A138: 260218 | B138: EQT | C138: United States | D138: Oil & Gas E&P | E138: Dec'25 | F138: 24 | G138: 2748 | H138: -1859 | I138: 1408 | J138: 944.82 | K138: 2449 | L138: 1638 | M138: -29.89 | N138: 23.74 | O138: 875.08 | P138: 192.08 | Q138: -279.5 | R138: 15.37 | S138: 392.66 | T138: 499.14 | U138: 1140 | V138: 622.06 | W138: 1029 | X138: 0.95773681 | Y138: 2.2615387 | Z138: 0.29635546 | AA138: 0.23977904
A139: 260218 | B139: EIX | C139: United States | D139: Utilities - Regulated Electric | E139: Dec'25 | F139: 23.7 | G139: 687 | H139: 771 | I139: 653 | J139: 932 | K139: 839 | L139: 794 | M139: 803 | N139: 1054 | O139: 957 | P139: 918 | Q139: 959 | R139: 1098 | S139: 753 | T139: 894 | U139: 832 | V139: 1872 | W139: 1785 | X139: -0.0064377682 | Y139: -0.034287257 | Z139: 0.21638244 | AA139: 0.23718685
A140: 260218 | B140: BHC | C140: United States | D140: Drug Manufacturers - Specialty & Generic | E140: Dec'25 | F140: 21.9 | G140: 494 | H140: 332 | I140: 286 | J140: 378 | K140: 428 | L140: 227 | M140: 381 | N140: 494 | O140: 507 | P140: 299 | Q140: 426 | R140: 544 | S140: 330 | T140: 297 | U140: 457 | V140: 717 | W140: 725 | X140: -0.0012507817 | Y140: 0.019411396 | Z140: 0.10626536 | AA140: 0.2193226
A141: 260218 | B141: SGI | C141: United States | D141: Furnishings, Fixtures & Appliances | E141: Dec'25 | F141: 18.3 | G141: 240.7 | H141: 181.7 | I141: 146.7 | J141: 198.4 | K141: 151.5 | L141: 138.7 | M141: 154.6 | N141: 178.6 | O141: 115.5 | P141: 126.6 | Q141: 170.2 | R141: 209.7 | S141: 119.2 | T141: 105.7 | U141: 191.5 | V141: 325.9 | W141: 255.1 | X141: -0.033402589 | Y141: 0.035218254 | Z141: 0.18559336 | AA141: 0.18307962
A142: 260218 | B142: ADI | C142: United States | D142: Semiconductors | E142: Mar'26 | F142: 16.4 | G142: 695.88 | H142: 964.84 | I142: 1032 | J142: 1129 | K142: 1131 | L142: 1152 | M142: 953.03 | N142: 743.57 | O142: 602.1 | P142: 392.1 | Q142: 503.6 | R142: 565.58 | S142: 555.2 | T142: 679.69 | U142: 822.38 | V142: 938.26 | W142: 1045 | X142: 0.14261981 | Y142: 0.13835517 | Z142: 0.14208971 | AA142: 0.1635103
A143: 260218 | B143: RGLD | C143: United States | D143: Gold | E143: Dec'25 | F143: 15.9 | G143: 83.96 | H143: 80.58 | I143: 67.91 | J143: 61.77 | K143: 73.45 | L143: 86.06 | M143: 71.9 | N143: 65.56 | O143: 79.69 | P143: 75.53 | Q143: 102.08 | R143: 118.85 | S143: 133.44 | T143: 123.11 | U143: 141.84 | V143: 175.14 | W143: 224.58 | X143: 0.1106769 | Y143: 0.083270503 | Z143: 0.10882762 | AA143: 0.15891061
A144: 260218 | B144: PUMP | C144: United States | D144: Oil & Gas Equipment & Services | E144: Dec'25 | F144: 15.3 | G144: 0.94 | H144: 23.32 | I144: 31.52 | J144: 45.09 | K144: 71.69 | L144: 77.36 | M144: 67.67 | N144: 58.59 | O144: 5.54 | P144: 30.99 | Q144: 1.04 | R144: 9.88 | S144: 3.26 | T144: 20.67 | U144: 1.77 | V144: -11.12 | W144: 5.49 | X144: -0.22847022 | Y144: 0.020946915 | Z144: -0.59021922 | AA144: 0.15294925
A145: 260218 | B145: ENLT | C145: United States | D145: Utilities - Renewable | E145: Dec'25 | F145: 15.2 | G145: 11.86 | H145: 15.07 | I145: 13.15 | J145: 36.73 | K145: 14.62 | L145: 39.05 | M145: 33.49 | N145: 42.68 | O145: -0.61 | P145: 42.89 | Q145: 34.88 | R145: 65.79 | S145: 22.26 | T145: 53.93 | U145: 56.99 | V145: 71.44 | W145: 53.4 | X145: 0.066578217 | Y145: 0.12501414 | Z145: 0.028396241 | AA145: 0.15218454
A146: 260218 | B146: HLF | C146: United States | D146: Packaged Foods | E146: Dec'25 | F146: 14.9 | G146: 84.3 | H146: 154.7 | I146: 159 | J146: 150.3 | K146: 93.3 | L146: 97.8 | M146: 133.5 | N146: 111.3 | O146: 68 | P146: 94.5 | Q146: 132.7 | R146: 129.8 | S146: 28.9 | T146: 126.1 | U146: 133.3 | V146: 127.2 | W146: 90.8 | X146: 0.081886499 | Y146: 0.0014371257 | Z146: -0.006218608 | AA146: 0.14897714
A147: 260218 | B147: BHP | C147: United States | D147: Other Industrial Metals & Mining | E147: H1 2026 | F147: 13.846071 | G147: 14911 | I147: 18029 | K147: 10010 | M147: 10971 | O147: 10325 | Q147: 11938 | S147: 8786 | U147: 9833 | W147: 11364 | X147: 0.045407588 | Y147: -0.06912815 | Z147: -0.10157306 | AA147: 0.13846071
A148: 260218 | B148: CAR | C148: United States | D148: Rental & Leasing Services | E148: Dec'25 | F148: 13.7 | G148: 680 | H148: 827 | I148: 1249 | J148: 1506 | K148: 718 | L148: 605 | M148: 848 | N148: 1052 | O148: 470 | P148: 185 | Q148: 389 | R148: 674 | S148: 54 | T148: -341 | U148: 433 | V148: 737 | W148: 175 | X148: -0.40399386 | Y148: 0.056701031 | Z148: 0.076829268 | AA148: 0.13703284
A149: 260218 | B149: PANW | C149: United States | D149: Software - Infrastructure | E149: Jun'26 | F149: 13.4 | G149: -73.9 | H149: -47.6 | I149: 15.4 | J149: 15.2 | K149: 39.9 | L149: 78.7 | M149: 253.5 | N149: 215.2 | O149: 230.4 | P149: 176.7 | Q149: 266 | R149: 249 | S149: 251 | T149: 224.4 | U149: 343.1 | V149: 297 | W149: 400 | X149: 0.050599342 | Y149: 0.077847334 | Z149: 0.044964871 | AA149: 0.13357239
A150: 260218 | B150: SABR | C150: United States | D150: Software - Infrastructure | E150: Dec'25 | F150: 13.4 | G150: -132.03 | H150: -76.06 | I150: -57.65 | J150: -41.17 | K150: -58.86 | L150: -0.21 | M150: -20.95 | N150: 55.72 | O150: 39.38 | P150: 89.2 | Q150: 48.72 | R150: 69.47 | S150: 33.42 | T150: 91.4 | U150: 89.13 | V150: 97.54 | W150: 75.28 | X150: 0.0091358332 | Y150: 0.16628945 | Z150: 0.099040294 | AA150: 0.13438634
A151: 260218 | B151: JLL | C151: United States | D151: Real Estate Services | E151: Dec'25 | F151: 13.3 | G151: 479.9 | H151: 195.2 | I151: 261 | J151: 223.6 | K151: 293.1 | L151: 53.5 | M151: 161 | N151: 150.7 | O151: 312 | P151: 115.9 | Q151: 163.9 | R151: 219.5 | S151: 391.9 | T151: 139.7 | U151: 218.7 | V151: 285.4 | W151: 529.5 | X151: 0.026705566 | Y151: 0.05989071 | Z151: 0.067952155 | AA151: 0.132857
A152: 260218 | B152: CF | C152: United States | D152: Agricultural Inputs | E152: Dec'25 | F152: 13.2 | G152: 1117 | H152: 1638 | I152: 1917 | J152: 828 | K152: 1188 | L152: 823 | M152: 729 | N152: 303 | O152: 408 | P152: 310 | Q152: 595 | R152: 316 | S152: 415 | T152: 477 | U152: 643 | V152: 563 | W152: 691 | X152: 0.10207824 | Y152: 0.026622296 | Z152: 0.13344138 | AA152: 0.13155386
A153: 260218 | B153: FLS | C153: United States | D153: Specialty Industrial Machinery | E153: Dec'25 | F153: 13.1 | G153: 79.53 | H153: 5.81 | I153: 58.45 | J153: 28.94 | K153: 129.02 | L153: 76.44 | M153: 111.83 | N153: 102.02 | O153: 110.85 | P153: 116.12 | Q153: 138.42 | R153: 123.3 | S153: 125.95 | T153: 134.77 | U153: 137.29 | V153: 159.69 | W153: 198.91 | X153: 0.037019393 | Y153: -0.0021629278 | Z153: 0.069804915 | AA153: 0.13082302
A154: 260218 | B154: PODD | C154: United States | D154: Medical Devices | E154: Dec'25 | F154: 11.9 | G154: 49.7 | H154: 37.9 | I154: 0.6 | J154: 39.7 | K154: 17.3 | L154: 27.7 | M154: 31.1 | N154: 52.9 | O154: 105.6 | P154: 56.9 | Q154: 68 | R154: 88.1 | S154: 95.8 | T154: 88.8 | U154: 121.1 | V154: 117.7 | W154: 146.3 | X154: 0.10330311 | Y154: 0.15585559 | Z154: 0.075165058 | AA154: 0.11927256
A155: 260218 | B155: AGI | C155: United States | D155: Gold | E155: Dec'25 | F155: 11.3 | G155: 49.8 | H155: 32.5 | I155: 25.7 | J155: 29.9 | K155: 61.6 | L155: 75 | M155: 88.6 | N155: 83.2 | O155: 59.9 | P155: 79.4 | Q155: 136.8 | R155: 95.4 | S155: 195.1 | T155: 92.3 | U155: 214 | V155: 373 | W155: 293.6 | X155: 0.025458851 | Y155: 0.14857583 | Z155: 0.46514745 | AA155: 0.11264867
A156: 260218 | B156: AGI | C156: United States | D156: Gold | E156: Dec'25 | F156: 11.3 | G156: 49.8 | H156: 32.5 | I156: 25.7 | J156: 29.9 | K156: 61.6 | L156: 75 | M156: 88.6 | N156: 83.2 | O156: 59.9 | P156: 79.4 | Q156: 136.8 | R156: 95.4 | S156: 195.1 | T156: 92.3 | U156: 214 | V156: 373 | W156: 293.6 | X156: 0.025458851 | Y156: 0.14857583 | Z156: 0.46514745 | AA156: 0.11264867
A157: 260218 | B157: LH | C157: United States | D157: Diagnostics & Research | E157: Dec'25 | F157: 11.1 | G157: 739.4 | H157: 609.9 | I157: 460.3 | J157: 384 | K157: 298 | L157: 339.5 | M157: 284.9 | N157: 270 | O157: 218.4 | P157: 328.8 | Q157: 306.4 | R157: 272.1 | S157: 230.7 | T157: 332.4 | U157: 398.6 | V157: 403.2 | W157: 382 | X157: 0.0031634446 | Y157: 0.08076384 | Z157: 0.10625709 | AA157: 0.11085061
A158: 260218 | B158: HALO | C158: United States | D158: Biotechnology | E158: Dec'25 | F158: 10.7 | G158: 56.53 | H158: 75.67 | I158: 34.06 | J158: 83.29 | K158: 96.41 | L158: 53.8 | M158: 94.46 | N158: 90.78 | O158: 101.04 | P158: 95.54 | Q158: 117.24 | R158: 163.2 | S158: 175.5 | T158: 141.54 | U158: 202.44 | V158: 217.92 | W158: 254.4 | X158: 0.08341191 | Y158: 0.14259892 | Z158: 0.080154684 | AA158: 0.10699756
A159: 260218 | B159: SON | C159: United States | D159: Packaging & Containers | E159: Dec'25 | F159: 10.6 | G159: 104.94 | H159: 226.89 | I159: 219.79 | J159: 203.85 | K159: 139.36 | L159: 185.85 | M159: 185.8 | N159: 185.3 | O159: 0 | P159: 105.79 | Q159: 129.99 | R159: 154.26 | S159: 59.06 | T159: 168.77 | U159: 192.14 | V159: 253.71 | W159: 130.66 | X159: 0.14023603 | Y159: 0.12136776 | Z159: 0.17318844 | AA159: 0.10628191
... A183: 260218 | B183: NDSN | C183: United States | D183: Specialty Industrial Machinery | E183: Mar'26 | F183: 3.3 | G183: 156.14 | H183: 184.72 | I183: 184.87 | J183: 222.53 | K183: 145.59 | L183: 173.84 | M183: 172.34 | N183: 181 | O183: 160.46 | P183: 169.65 | Q183: 168.63 | R183: 188.1 | S183: 141.96 | T183: 169.77 | U183: 201.5 | V183: 219.23 | W183: 166.41 | X183: 0.00017954933 | Y183: 0.049172725 | Z183: 0.044387093 | AA183: 0.033380662
A184: 260218 | B184: KNF | C184: United States | D184: Building Materials | E184: Dec'25 | F184: 3.3 | H184: -44.61 | I184: 60.21 | J184: 142.72 | K184: 34.88 | L184: -44.56 | M184: 93.47 | N184: 211.46 | O184: 49.71 | P184: -52.91 | Q184: 117.16 | R184: 209.18 | S184: 55.7 | T184: -77.35 | U184: 89.68 | V184: 218.11 | W184: 65.2 | X184: -0.074256373 | Y184: -0.090190029 | Z184: 0.032213845 | AA184: 0.033200531
A185: 260218 | B185: CLH | C185: United States | D185: Waste Management | E185: Dec'25 | F185: 3.3 | G185: 82.2 | H185: 87.09 | I185: 211.17 | J185: 209.09 | K185: 127.4 | L185: 120.96 | M185: 189.82 | N185: 154.37 | O185: 147.29 | P185: 125.48 | Q185: 215.49 | R185: 192.3 | S185: 136.97 | T185: 111.62 | U185: 210.3 | V185: 193.01 | W185: 158.45 | X185: -0.02067916 | Y185: -0.0079070051 | Z185: 0.0010903116 | AA185: 0.032949839
A186: 260218 | B186: WING | C186: United States | D186: Restaurants | E186: Dec'25 | F186: 3.2 | G186: 14.29 | H186: 17.05 | I186: 22.7 | J186: 24.32 | K186: 29.48 | L186: 28.52 | M186: 27.54 | N186: 31.97 | O186: 29.81 | P186: 42.74 | Q186: 41.22 | R186: 40.55 | S186: 41.79 | T186: 46.11 | U186: 46.77 | V186: 51.02 | W186: 47.77 | X186: 0.020264582 | Y186: 0.032710556 | Z186: 0.059753453 | AA186: 0.032204211
A187: 260218 | B187: AWR | C187: United States | D187: Utilities - Regulated Water | E187: Dec'25 | F187: 3.2 | G187: 33.6 | H187: 25.85 | I187: 35.78 | J187: 41.88 | K187: 30.64 | L187: 51.19 | M187: 58.97 | N187: 51.61 | O187: 36.58 | P187: 39.29 | Q187: 52.08 | R187: 55.36 | S187: 37.76 | T187: 45.86 | U187: 51.3 | V187: 62.06 | W187: 44.06 | X187: 0.035611686 | Y187: -0.0040824872 | Z187: 0.035211268 | AA187: 0.031982942
...

Sheet 빨간줄
B2: (단위: mil $)
B4: AAPL | C4: 6 | D4: 7 | E4: 8 | F4: 9 | G4: 10 | H4: 11 | I4: 12 | J4: 13 | K4: 14 | L4: 15 | M4: 16 | N4: 17 | O4: 18 | P4: 19 | Q4: 20 | R4: 21 | S4: 22
C6: 4Q21 | D6: 1Q22 | E6: 2Q22 | F6: 3Q22 | G6: 4Q22 | H6: 1Q23 | I6: 2Q23 | J6: 3Q23 | K6: 4Q23 | L6: 1Q24 | M6: 2Q24 | N6: 3Q24 | O6: 4Q24 | P6: 1Q25 | Q6: 2Q25 | R6: 3Q25 | S6: 4Q25 | T6: 1Q26 | U6: 2Q26 | V6: 3Q26 | W6: 4Q26
B7: Revenue | C7: =VLOOKUP($B$4,Revenue!$B:$W,C4,FALSE) -> 123945 | D7: =VLOOKUP($B$4,Revenue!$B:$W,D4,FALSE) -> 97278 | E7: =VLOOKUP($B$4,Revenue!$B:$W,E4,FALSE) -> 82959 | F7: =VLOOKUP($B$4,Revenue!$B:$W,F4,FALSE) -> 90146 | G7: =VLOOKUP($B$4,Revenue!$B:$W,G4,FALSE) -> 117154 | H7: =VLOOKUP($B$4,Revenue!$B:$W,H4,FALSE) -> 94836 | I7: =VLOOKUP($B$4,Revenue!$B:$W,I4,FALSE) -> 81797 | J7: =VLOOKUP($B$4,Revenue!$B:$W,J4,FALSE) -> 89498 | ... S7: =VLOOKUP($B$4,Revenue!$B:$W,S4,FALSE) -> 143756
B8: OP | C8: =VLOOKUP($B$4,'Operating Income'!$B:$W,C4,FALSE) -> 41488 | D8: =VLOOKUP($B$4,'Operating Income'!$B:$W,D4,FALSE) -> 29979 | E8: =VLOOKUP($B$4,'Operating Income'!$B:$W,E4,FALSE) -> 23076 | F8: =VLOOKUP($B$4,'Operating Income'!$B:$W,F4,FALSE) -> 24894 | G8: =VLOOKUP($B$4,'Operating Income'!$B:$W,G4,FALSE) -> 36016 | H8: =VLOOKUP($B$4,'Operating Income'!$B:$W,H4,FALSE) -> 28318 | I8: =VLOOKUP($B$4,'Operating Income'!$B:$W,I4,FALSE) -> 22998 | J8: =VLOOKUP($B$4,'Operating Income'!$B:$W,J4,FALSE) -> 26969 | ... S8: =VLOOKUP($B$4,'Operating Income'!$B:$W,S4,FALSE) -> 50852
B9: Trailing 4Q OP avg. | C9: =AVERAGE(C8:C8) -> 41488 | D9: =AVERAGE(C8:D8) -> 35733.5 | E9: =AVERAGE(C8:E8) -> 31514.333 | F9: =AVERAGE(C8:F8) -> 29859.25 | G9: =AVERAGE(D8:G8) -> 28491.25 | H9: =AVERAGE(E8:H8) -> 28076 | I9: =AVERAGE(F8:I8) -> 28056.5 | J9: =AVERAGE(G8:J8) -> 28575.25 | K9: =AVERAGE(H8:K8) -> 29664.5 | L9: =AVERAGE(I8:L8) -> 29560 | M9: =AVERAGE(J8:M8) -> 30148.5 | ... S9: =AVERAGE(P8:S8) -> 35267.5
B10: Trailing 4Q OP sum. | C10: =SUM(C8:C8) -> 41488 | D10: =SUM(C8:D8) -> 71467 | E10: =SUM(C8:E8) -> 94543 | F10: =SUM(C8:F8) -> 119437 | G10: =SUM(D8:G8) -> 113965 | H10: =SUM(E8:H8) -> 112304 | I10: =SUM(F8:I8) -> 112226 | J10: =SUM(G8:J8) -> 114301 | K10: =SUM(H8:K8) -> 118658 | L10: =SUM(I8:L8) -> 118240 | M10: =SUM(J8:M8) -> 120594 | ... S10: =SUM(P8:S8) -> 141070
B11: Trailing OP Delta | D11: =D9/C9-1 -> -0.13870276 | E11: =E9/D9-1 -> -0.11807314 | F11: =F9/E9-1 -> -0.052518431 | G11: =G9/F9-1 -> -0.045814948 | H11: =H9/G9-1 -> -0.01457465 | I11: =I9/H9-1 -> -0.00069454338 | J11: =J9/I9-1 -> 0.018489477 | K11: =K9/J9-1 -> 0.038118652 | ... S11: =S9/R9-1 -> 0.060278091
B12: opm | C12: =IFERROR(C8/C7,"-") -> 0.33472911 | D12: =IFERROR(D8/D7,"-") -> 0.30817862 | E12: =IFERROR(E8/E7,"-") -> 0.2781615 | F12: =IFERROR(F8/F7,"-") -> 0.27615202 | G12: =IFERROR(G8/G7,"-") -> 0.30742442 | H12: =IFERROR(H8/H7,"-") -> 0.29859969 | I12: =IFERROR(I8/I7,"-") -> 0.28115946 | J12: =IFERROR(J8/J7,"-") -> 0.30133634 | ... S12: =IFERROR(S8/S7,"-") -> 0.35373828
B13: op yoy | C13: =C8/#REF!-1 -> #REF! | D13: =D8/#REF!-1 -> #REF! | E13: =E8/#REF!-1 -> #REF! | F13: =F8/#REF!-1 -> #REF! | G13: =G8/C8-1 -> -0.13189356 | H13: =H8/D8-1 -> -0.05540545 | I13: =I8/E8-1 -> -0.0033801352 | J13: =J8/F8-1 -> 0.083353418 | K13: =K8/G8-1 -> 0.12097401 | L13: =L8/H8-1 -> -0.014760929 | M13: =M8/I8-1 -> 0.10235673 | N13: =N8/J8-1 -> 0.097222737 | ... S13: =S8/O8-1 -> 0.18724318
B14: rv yoy | G14: =G7/C7-1 -> -0.054790431 | H14: =H7/D7-1 -> -0.025103312 | I14: =I7/E7-1 -> -0.014006919 | J14: =J7/F7-1 -> -0.0071883389 | K14: =K7/G7-1 -> 0.020665107 | L14: =L7/H7-1 -> -0.043053271 | M14: =M7/I7-1 -> 0.048657041 | N14: =N7/J7-1 -> 0.060694094 | ... S14: =S7/O7-1 -> 0.15652454
